Workbook
Name GF500_DB: "C:\Users\AniyaBegheri\FG500\[GF500_Database_Merged.csv.xlsx]Table1'"

Sheet FG500_DataCollection_FY26 (2)
A1: Profile (FG500) | D1: Details (FG500) | N1: RE100 | Q1: SBTi | AC1: NZ Tracker Definition | AI1: Carbon Neutral | AO1: Net Zero | AV1: Use of carbon credits | AX1: Other reduction targets | BD1: Other | BG1: Binary | CL1: actions include all | CP1: number of companies with any commitments | CT1: DO NOT REOVE
CW2: 2024 Data | CX2: 2024 Data | CY2: 2024 Data | CZ2: 2024 Data | DA2: 2024 Data | DB2: 2024 Data | DC2: 2024 Data | DD2: 2024 Data | DE2: 2024 Data | DF2: 2024 Data | DG2: 2024 Data | DH2: 2024 Data | DI2: 2024 Data | DJ2: 2024 Data | DK2: 2024 Data | DL2: 2024 Data | DM2: 2024 Data | DN2: 2024 Data | DO2: 2024 Data | DP2: 2024 Data | DQ2: 2024 Data | DR2: 2024 Data | DS2: 2024 Data | DT2: Last year checks | DZ2: this year
A3: 2025 Rank | B3: 2024 rank | C3: Company name | D3: Sector (Fortune) | E3: Sector (final classification) | F3: Country | G3: Region | H3: Revenue ($M) usable | I3: Profits ($M) usable | J3: Profits (% change) | K3: Assets ($M) | L3: Employees | M3: Years on list (2025) | N3: RE100 (Y/N) | O3: Joining year | P3: Target year | Q3: In SBTI database? | R3: Near Term SBT (Y = yes, N=no) | S3: Target status (T = target set, C = committed, N=No, R=Removed) | T3: Target classification (near term) - temp | U3: Target year (near term) (earlier of the two dates if there were two) | V3: Long term - Target Status | W3: Long term - Target Classification | X3: Long term - Target Year | Y3: Net zero committed (SBTi) (Y = yes, N = no) | Z3: SBTi NZ Target Status | AA3: Net zero Target year (SBTi) | AB3: notes | AC3: NZ Tracker_End target (in their words) | AD3: NZ Tracker Target Grouping | AE3: Scope 1 | AF3: Scope 2 | AG3: Scope 3 | AH3: Carbon neutral scope(s) - Scope 1,2,3 (NZ Tracker) | AI3: Carbon neutral commitment (C = company, V = value chain, G= Government, S=Subsidiary, U = unspecified, N=no) | AJ3: CN (Y/N) | AK3: Carbon neutral claim (in their words) | AL3: Target year | AM3: Source | AN3: Notes (including climate positive) | AO3: Net zero commitment (V = value chain, C = company, U = unclear, S=Subsidiary) | AP3: NZ (Y/N) | AQ3: Primary net zero scope (in their words) | AR3: Primary net zero claim (in their words) | AS3: Net zero target year | AT3: Source | AU3: Notes | AV3: Carbon credits (Y = yes, N = no, R = removals only, U = unclear).1 | AW3: Removals | AX3: Separate Removal Target | AY3: Other reduction target (Y = yes) (either companies w/ no SBT or w/ SBT "C") | AZ3: Target details (Text) | BA3: Target Year | BB3: Source | BC3: Notes | BD3: Who did it? | BE3: When? | BF3: Oher Sources | BG3: RE100 <=2024 | BH3: RE100 2025-2030 | BI3: RE100>2030 | BJ3: All RE | BK3: SBTi ST <= 2025 | BL3: SBTi ST 2026-2030 | BM3: SBTi ST > 2030 | BN3: All SBTi ST | BO3: SBTi NZ <= 2024 | BP3: SBTi NZ 2026-2030 | BQ3: SBTi NZ > 2030 | BR3: Other NZ <= 2025 | BS3: Other NZ 2025-2030 | BT3: Other NZ > 2030 | BU3: CN <=2025 | BV3: CN 2026-2030 | BW3: CN 2031-2060 | BX3: CN <= 2024 | BY3: CN 2025-2030 | BZ3: CN > 2030 | CA3: All CN | CB3: ALL CN | CC3: Total NZ <=2025 | CD3: Total NZ 2026-2030 | CE3: Total NZ > 2030 | CF3: All NZ | CG3: CN/NZ-OLD | CH3: CN?NZ-NEW | CI3: Other Emission Reduction <=2024 | CJ3: Other Emission Reduction 2025-2030 | CK3: Other Emission Reduction > 2030 | CL3: actions already achieved | CM3: actions due by 2030 | CN3: actions due after 2030 | CO3: ALL Actions | CP3: One of the actions | CQ3: Carbon Credits (Y) | CR3: Carbon Credits (No) | CS3: Carbon Credits (Not Specified) | CT3: SBTi ST 2026-2030 | CU3: NZ both | CV3: NZ latest target year | CW3: CN already achieved | CX3: CN 2024-2030 | CY3: CN 2031-2050 | CZ3: Any CN | DA3: NZ already achieved | DB3: NZ 2024-2030 | DC3: NZ 2031-2050 | DD3: Any NZ | DE3: SBT already achieved | DF3: SBT 2024-2030 | DG3: SBT 2031-2050 | DH3: Any SBT | DI3: RE100 already achieved | DJ3: RE100 2024-2030 | DK3: RE100 2031-2050 | DL3: Any RE100 | DM3: CN/NZ - IF THE COMPANY HAS A Ccn or nz target | DN3: CN/NZ 2030 | DO3: CN/NZ 2050 | DP3: will use cabon credits | DQ3: will NOT use carbon credits | DR3: any target | DS3: any target already achived | DT3: sbti | DU3: nz-sbti | DV3: nz | DW3: cn | DX3: cn-cc | DY3: nz-cc | DZ3: sbti | EA3: nz-sbti | EB3: nz | EC3: cn | ED3: cn-cc | EE3: nz-cc | EF3: nz years
A4: 1 | B4: 1 | C4: Walmart | D4: General Merchandisers | E4: Retail | F4: U.S. | G4: North America | H4: $680,985 | I4: $19,436 | J4: 0.253 | K4: $260,823 | L4: 2100000 | M4: 31 | N4: Y | O4: 2015 | P4: 2035 | Q4: Y | R4: Y | S4: Targets set | T4: 1.5°C | U4: 2030 | Y4: N | Z4: Commitment removed | AC4: Zero emissions | AD4: Net Zero | AE4: Yes | AF4: Yes | AG4: No | AH4: 1,2 | AJ4: N | AO4: C | AP4: Y | AQ4: 1,2 | AR4: "Goal: Achieve zero emissions across global operations by 2040 (Scopes 1 & 2)" (Website, as of 14/08/2025: https://corporate.walmart.com/purpose/esgreport/environmental/climate-change) | AS4: 2040 | AV4: No | AW4: No | AX4: No | AY4: N | BG4: =IF(AND($N4="Y",$P4<=2025),1,0) -> 0 | BH4: =IF(AND($N4="Y",AND($P4>2025,$P4<=2030)),1,0) -> 0 | BI4: =IF(AND($N4="Y",$P4>2030),1,0) -> 1 | BJ4: =MAX(BG4:BI4) -> 1 | BK4: =IF(AND($R4="Y",$U4<=2025),1,0) -> 0 | BL4: =IF(AND($R4="Y",AND($U4>2025,$U4<=2030)),1,0) -> 1 | BM4: =IF(AND($R4="Y",$U4>2030),1,0) -> 0 | BN4: =MAX(BK4:BM4) -> 1 | BO4: =IF(AND($Y4="Y",$AA4<=2025),1,0) -> 0 | BP4: =IF(AND($Y4="Y",AND($AA4>2025,$AA4<=2030)),1,0) -> 0 | BQ4: =IF(AND($Y4="Y",$AA4>2030),1,0) -> 0 | BR4: =IF(AND($AP4="Y",$AS4<=2025),1,0) -> 0 | BS4: =IF(AND($AP4="Y",AND($AS4>2025,$AS4<=2030)),1,0) -> 0 | BT4: =IF(AND($AP4="Y",$AS4>2030),1,0) -> 1 | BU4: =IF(AND(AL4<=2025,CF4=0,AJ4="Y"),1,0) -> 0 | BV4: =IF(AND(AL4>=2026,AL4<=2030,AJ4="Y",CF4=0),1,0) -> 0 | BW4: =IF(AND(AL4>=2031,CF4=0,AJ4="Y"),1,0) -> 0 | BX4: =IF(AND($AJ4="Y",$AL4<=2024),1,0) -> 0 | BY4: =IF(AND($AJ4="Y",AND($AL4>2024,$AL4<=2030)),1,0) -> 0 | BZ4: =IF(AND($AJ4="Y",$AL4>2030),1,0) -> 0 | CA4: =MAX(BX4:BZ4) -> 0 | CB4: =IF(AND(CF4=0,AJ4="Y"),1,0) -> 0 | CC4: =MAX($BO4,$BR4) -> 0 | CD4: =MAX($BP4,$BS4) -> 0 | CE4: =MAX($BQ4,$BT4) -> 1 | CF4: =MAX(CC4:CE4) -> 1 | CG4: =MAX($CF4,$CA4) -> 1 | CH4: =MAX(CF4,CB4) -> 1 | CI4: =IF(AND($AY4="Y",$BA4<=2024),1,0) -> 0 | CJ4: =IF(AND($AY4="Y",AND($BA4>2024,$BA4<=2030)),1,0) -> 0 | CK4: =IF(AND($AY4="Y",$BA4>2030),1,0) -> 0 | CL4: =SUM(CC4,BU4,BK4,BG4) -> 0 | CM4: =SUM(CD4,BV4,BL4,BH4) -> 1 | CN4: =SUM(CE4,BW4,BM4,BI4) -> 2 | CO4: =CF4+CB4+BN4+BJ4 -> 3 | CP4: =MAX(CH4,BN4,BJ4) -> 1 | CQ4: =IF($AV4="Yes",1,0) -> 0 | CR4: =IF($AV4="No",1,0) -> 1 | CS4: =IF($AV4="Not Specified",1,0) -> 0 | CT4: =IF(OR(AND(U4>=2026,U4<=2030),AND(X4>=2026,X4<=2030)),1,"") -> 1 | CU4: =AA4&" "&AS4 -> 2040 | CV4: =MAX(AA4,AS4) -> 2040 | CW4: 0 | CX4: 0 | CY4: 0 | CZ4: 0 | DA4: 0 | DB4: 0 | DC4: 1 | DD4: 1 | DE4: 0 | DF4: 1 | DG4: 0 | DH4: 1 | DI4: 0 | DJ4: 0 | DK4: 1 | DL4: 1 | DM4: 1 | DN4: 0 | DO4: 1 | DP4: 0 | DQ4: 1 | DR4: 1 | DS4: 0 | DT4: Y | DU4: No | DV4: C | DW4: N | DX4: 0 | DY4: N | DZ4: =Q4 -> Y | EA4: =Z4 -> Commitment removed | EB4: =AP4 -> Y | EC4: =AJ4 -> N | ED4: =AV4 -> No | EF4: =MAX(AS4,AA4) -> 2040
A5: 2 | B5: 2 | C5: Amazon | D5: Internet Services and Retailing | E5: Retail | F5: U.S. | G5: North America | H5: $637,959 | I5: $59,248 | J5: 0.947 | K5: $624,894 | L5: 1556000 | M5: 17 | N5: N | Q5: Y | R5: N | S5: Commitment removed | AC5: Net zero | AD5: Net Zero | AE5: Not Specified | AF5: Not Specified | AG5: Partial | AJ5: N | AO5: C | AP5: Y | AR5: In 2019, we co-founded and committed to The Climate Pledge‚Äîour goal to reach net-zero carbon emissions by 2040, 10 years ahead of the Paris Agreement. (sustainability report 2024 p. 6) | AS5: 2040 | AV5: Yes | AW5: Yes (nature-based removals e.g. Forestation, soil carbon enhancement) | AX5: No | AY5: N | BG5: =IF(AND($N5="Y",$P5<=2025),1,0) -> 0 | BH5: =IF(AND($N5="Y",AND($P5>2025,$P5<=2030)),1,0) -> 0 | BI5: =IF(AND($N5="Y",$P5>2030),1,0) -> 0 | BJ5: =MAX(BG5:BI5) -> 0 | BK5: =IF(AND($R5="Y",$U5<=2025),1,0) -> 0 | BL5: =IF(AND($R5="Y",AND($U5>2025,$U5<=2030)),1,0) -> 0 | BM5: =IF(AND($R5="Y",$U5>2030),1,0) -> 0 | BN5: =MAX(BK5:BM5) -> 0 | BO5: =IF(AND($Y5="Y",$AA5<=2025),1,0) -> 0 | BP5: =IF(AND($Y5="Y",AND($AA5>2025,$AA5<=2030)),1,0) -> 0 | BQ5: =IF(AND($Y5="Y",$AA5>2030),1,0) -> 0 | BR5: =IF(AND($AP5="Y",$AS5<=2025),1,0) -> 0 | BS5: =IF(AND($AP5="Y",AND($AS5>2025,$AS5<=2030)),1,0) -> 0 | BT5: =IF(AND($AP5="Y",$AS5>2030),1,0) -> 1 | BU5: =IF(AND(AL5<=2025,CF5=0,AJ5="Y"),1,0) -> 0 | BV5: =IF(AND(AL5>=2026,AL5<=2030,AJ5="Y",CF5=0),1,0) -> 0 | BW5: =IF(AND(AL5>=2031,CF5=0,AJ5="Y"),1,0) -> 0 | BX5: =IF(AND($AJ5="Y",$AL5<=2024),1,0) -> 0 | BY5: =IF(AND($AJ5="Y",AND($AL5>2024,$AL5<=2030)),1,0) -> 0 | BZ5: =IF(AND($AJ5="Y",$AL5>2030),1,0) -> 0 | CA5: =MAX(BX5:BZ5) -> 0 | CB5: =IF(AND(CF5=0,AJ5="Y"),1,0) -> 0 | CC5: =MAX($BO5,$BR5) -> 0 | CD5: =MAX($BP5,$BS5) -> 0 | CE5: =MAX($BQ5,$BT5) -> 1 | CF5: =MAX(CC5:CE5) -> 1 | CG5: =MAX($CF5,$CA5) -> 1 | CH5: =MAX(CF5,CB5) -> 1 | CI5: =IF(AND($AY5="Y",$BA5<=2024),1,0) -> 0 | CJ5: =IF(AND($AY5="Y",AND($BA5>2024,$BA5<=2030)),1,0) -> 0 | CK5: =IF(AND($AY5="Y",$BA5>2030),1,0) -> 0 | CL5: =SUM(CC5,BU5,BK5,BG5) -> 0 | CM5: =SUM(CD5,BV5,BL5,BH5) -> 0 | CN5: =SUM(CE5,BW5,BM5,BI5) -> 1 | CO5: =CF5+CB5+BN5+BJ5 -> 1 | CP5: =MAX(CH5,BN5,BJ5) -> 1 | CQ5: =IF($AV5="Yes",1,0) -> 1 | CR5: =IF($AV5="No",1,0) -> 0 | CS5: =IF($AV5="Not Specified",1,0) -> 0 | CT5: =IF(OR(AND(U5>=2026,U5<=2030),AND(X5>=2026,X5<=2030)),1,"") | CU5: =AA5&" "&AS5 -> 2040 | CV5: =MAX(AA5,AS5) -> 2040 | CW5: 0 | CX5: 0 | CY5: 0 | CZ5: 0 | DA5: 0 | DB5: 0 | DC5: 1 | DD5: 1 | DE5: 0 | DF5: 0 | DG5: 0 | DH5: 0 | DI5: 0 | DJ5: 0 | DK5: 0 | DL5: 0 | DM5: 1 | DN5: 0 | DO5: 1 | DP5: 1 | DQ5: 0 | DR5: 1 | DS5: 0 | DT5: N | DU5: No | DV5: C | DW5: N | DX5: 0 | DY5: Y | DZ5: =Q5 -> Y | EA5: =Z5 | EB5: =AP5 -> Y | EC5: =AJ5 -> N | ED5: =AV5 -> Yes | EF5: =MAX(AS5,AA5) -> 2040
A6: 3 | B6: 3 | C6: State Grid | D6: Utilities | E6: Energy and utilities | F6: China | G6: Asia | H6: $548,414.4 | I6: $10,044.9 | J6: 0.091 | K6: $797,694 | L6: 1354310 | M6: 25 | N6: N | Q6: N | R6: N | AI6: G | AJ6: N | AL6: 2060 | AM6: http://www.sgcc.com.cn/u/cms/sgcc_main/other/202012/20201217092925545833884.pdf | AP6: N | AV6: Not Specified | AY6: N | BG6: =IF(AND($N6="Y",$P6<=2025),1,0) -> 0 | BH6: =IF(AND($N6="Y",AND($P6>2025,$P6<=2030)),1,0) -> 0 | BI6: =IF(AND($N6="Y",$P6>2030),1,0) -> 0 | BJ6: =MAX(BG6:BI6) -> 0 | BK6: =IF(AND($R6="Y",$U6<=2025),1,0) -> 0 | BL6: =IF(AND($R6="Y",AND($U6>2025,$U6<=2030)),1,0) -> 0 | BM6: =IF(AND($R6="Y",$U6>2030),1,0) -> 0 | BN6: =MAX(BK6:BM6) -> 0 | BO6: =IF(AND($Y6="Y",$AA6<=2025),1,0) -> 0 | BP6: =IF(AND($Y6="Y",AND($AA6>2025,$AA6<=2030)),1,0) -> 0 | BQ6: =IF(AND($Y6="Y",$AA6>2030),1,0) -> 0 | BR6: =IF(AND($AP6="Y",$AS6<=2025),1,0) -> 0 | BS6: =IF(AND($AP6="Y",AND($AS6>2025,$AS6<=2030)),1,0) -> 0 | BT6: =IF(AND($AP6="Y",$AS6>2030),1,0) -> 0 | BU6: =IF(AND(AL6<=2025,CF6=0,AJ6="Y"),1,0) -> 0 | BV6: =IF(AND(AL6>=2026,AL6<=2030,AJ6="Y",CF6=0),1,0) -> 0 | BW6: =IF(AND(AL6>=2031,CF6=0,AJ6="Y"),1,0) -> 0 | BX6: =IF(AND($AJ6="Y",$AL6<=2024),1,0) -> 0 | BY6: =IF(AND($AJ6="Y",AND($AL6>2024,$AL6<=2030)),1,0) -> 0 | BZ6: =IF(AND($AJ6="Y",$AL6>2030),1,0) -> 0 | CA6: =MAX(BX6:BZ6) -> 0 | CB6: =IF(AND(CF6=0,AJ6="Y"),1,0) -> 0 | CC6: =MAX($BO6,$BR6) -> 0 | CD6: =MAX($BP6,$BS6) -> 0 | CE6: =MAX($BQ6,$BT6) -> 0 | CF6: =MAX(CC6:CE6) -> 0 | CG6: =MAX($CF6,$CA6) -> 0 | CH6: =MAX(CF6,CB6) -> 0 | CI6: =IF(AND($AY6="Y",$BA6<=2024),1,0) -> 0 | CJ6: =IF(AND($AY6="Y",AND($BA6>2024,$BA6<=2030)),1,0) -> 0 | CK6: =IF(AND($AY6="Y",$BA6>2030),1,0) -> 0 | CL6: =SUM(CC6,BU6,BK6,BG6) -> 0 | CM6: =SUM(CD6,BV6,BL6,BH6) -> 0 | CN6: =SUM(CE6,BW6,BM6,BI6) -> 0 | CO6: =CF6+CB6+BN6+BJ6 -> 0 | CP6: =MAX(CH6,BN6,BJ6) -> 0 | CQ6: =IF($AV6="Yes",1,0) -> 0 | CR6: =IF($AV6="No",1,0) -> 0 | CS6: =IF($AV6="Not Specified",1,0) -> 1 | CT6: =IF(OR(AND(U6>=2026,U6<=2030),AND(X6>=2026,X6<=2030)),1,"") | CU6: =AA6&" "&AS6 | CV6: =MAX(AA6,AS6) -> 0 | CW6: 0 | CX6: 0 | CY6: 0 | CZ6: 0 | DA6: 0 | DB6: 0 | DC6: 0 | DD6: 0 | DE6: 0 | DF6: 0 | DG6: 0 | DH6: 0 | DI6: 0 | DJ6: 0 | DK6: 0 | DL6: 0 | DM6: 0 | DN6: 0 | DO6: 0 | DP6: 0 | DQ6: 0 | DR6: 0 | DS6: 0 | DT6: N | DU6: 0 | DV6: N | DW6: N | DX6: 0 | DY6: 0 | DZ6: =Q6 -> N | EA6: =Z6 | EB6: =AP6 -> N | EC6: =AJ6 -> N | ED6: =AV6 -> Not Specified | EF6: =MAX(AS6,AA6) -> 0
A7: 4 | B7: 4 | C7: Saudi Aramco | D7: Mining, Crude-Oil Production | E7: Metals and mining | F7: Saudi Arabia | G7: Other | H7: $480,193.5 | I7: $104,982.3 | J7: -0.13 | K7: $645,097.2 | L7: 75118 | M7: 7 | N7: N | Q7: N | R7: N | AC7: Net zero | AD7: Net Zero | AE7: Yes | AF7: Yes | AG7: No | AH7: 1,2 | AJ7: N | AO7: C | AP7: Y | AQ7: 1,2 | AR7: 'We have an ambition to reach net-zero Scope 1 and Scope 2 GHG emissions by 2050 across all our wholly-owned operated assets. (see p22 of the 2024 Aramco Sustainability Report). | AS7: 2050 | AV7: Yes | AW7: Yes (nature-based and CCS-based removals) | AX7: No | AY7: N | BG7: =IF(AND($N7="Y",$P7<=2025),1,0) -> 0 | BH7: =IF(AND($N7="Y",AND($P7>2025,$P7<=2030)),1,0) -> 0 | BI7: =IF(AND($N7="Y",$P7>2030),1,0) -> 0 | BJ7: =MAX(BG7:BI7) -> 0 | BK7: =IF(AND($R7="Y",$U7<=2025),1,0) -> 0 | BL7: =IF(AND($R7="Y",AND($U7>2025,$U7<=2030)),1,0) -> 0 | BM7: =IF(AND($R7="Y",$U7>2030),1,0) -> 0 | BN7: =MAX(BK7:BM7) -> 0 | BO7: =IF(AND($Y7="Y",$AA7<=2025),1,0) -> 0 | BP7: =IF(AND($Y7="Y",AND($AA7>2025,$AA7<=2030)),1,0) -> 0 | BQ7: =IF(AND($Y7="Y",$AA7>2030),1,0) -> 0 | BR7: =IF(AND($AP7="Y",$AS7<=2025),1,0) -> 0 | BS7: =IF(AND($AP7="Y",AND($AS7>2025,$AS7<=2030)),1,0) -> 0 | BT7: =IF(AND($AP7="Y",$AS7>2030),1,0) -> 1 | BU7: =IF(AND(AL7<=2025,CF7=0,AJ7="Y"),1,0) -> 0 | BV7: =IF(AND(AL7>=2026,AL7<=2030,AJ7="Y",CF7=0),1,0) -> 0 | BW7: =IF(AND(AL7>=2031,CF7=0,AJ7="Y"),1,0) -> 0 | BX7: =IF(AND($AJ7="Y",$AL7<=2024),1,0) -> 0 | BY7: =IF(AND($AJ7="Y",AND($AL7>2024,$AL7<=2030)),1,0) -> 0 | BZ7: =IF(AND($AJ7="Y",$AL7>2030),1,0) -> 0 | CA7: =MAX(BX7:BZ7) -> 0 | CB7: =IF(AND(CF7=0,AJ7="Y"),1,0) -> 0 | CC7: =MAX($BO7,$BR7) -> 0 | CD7: =MAX($BP7,$BS7) -> 0 | CE7: =MAX($BQ7,$BT7) -> 1 | CF7: =MAX(CC7:CE7) -> 1 | CG7: =MAX($CF7,$CA7) -> 1 | CH7: =MAX(CF7,CB7) -> 1 | CI7: =IF(AND($AY7="Y",$BA7<=2024),1,0) -> 0 | CJ7: =IF(AND($AY7="Y",AND($BA7>2024,$BA7<=2030)),1,0) -> 0 | CK7: =IF(AND($AY7="Y",$BA7>2030),1,0) -> 0 | CL7: =SUM(CC7,BU7,BK7,BG7) -> 0 | CM7: =SUM(CD7,BV7,BL7,BH7) -> 0 | CN7: =SUM(CE7,BW7,BM7,BI7) -> 1 | CO7: =CF7+CB7+BN7+BJ7 -> 1 | CP7: =MAX(CH7,BN7,BJ7) -> 1 | CQ7: =IF($AV7="Yes",1,0) -> 1 | CR7: =IF($AV7="No",1,0) -> 0 | CS7: =IF($AV7="Not Specified",1,0) -> 0 | CT7: =IF(OR(AND(U7>=2026,U7<=2030),AND(X7>=2026,X7<=2030)),1,"") | CU7: =AA7&" "&AS7 -> 2050 | CV7: =MAX(AA7,AS7) -> 2050 | CW7: 0 | CX7: 0 | CY7: 0 | CZ7: 0 | DA7: 0 | DB7: 0 | DC7: 1 | DD7: 1 | DE7: 0 | DF7: 0 | DG7: 0 | DH7: 0 | DI7: 0 | DJ7: 0 | DK7: 0 | DL7: 0 | DM7: 1 | DN7: 0 | DO7: 1 | DP7: 1 | DQ7: 0 | DR7: 1 | DS7: 0 | DT7: N | DU7: 0 | DV7: C | DW7: N | DX7: 0 | DY7: Y | DZ7: =Q7 -> N | EA7: =Z7 | EB7: =AP7 -> Y | EC7: =AJ7 -> N | ED7: =AV7 -> Yes | EF7: =MAX(AS7,AA7) -> 2050
A8: 5 | B8: 6 | C8: China National Petroleum | D8: Petroleum Refining | E8: Oil and gas | F8: China | G8: Asia | H8: $412,645.3 | I8: $22,424 | J8: 0.053 | K8: $607,615.1 | L8: 985155 | M8: 25 | N8: N | Q8: N | R8: N | AC8: Net zero | AD8: Net Zero | AE8: Yes | AF8: Yes | AG8: Not Specified | AH8: 1,2 | AI8: G | AJ8: N | AL8: 2060 | AO8: C | AP8: Y | AQ8: 1,2 | AR8: The 2024 report frequently mentions ‚Äúcarbon neutrality,‚Äù ‚Äúzero-carbon,‚Äù and the global ‚Äúnet-zero‚Äù context (including NZE-2050), it does not specify a corporate-wide net-zero year target for PetroChina itself ‚Äî it frames the ambition as ongoing pursuit of the national carbon-peak and carbon-neutrality goals. | AS8: 2050 | AV8: Not Specified | AW8: No | AX8: No | AY8: N | BG8: =IF(AND($N8="Y",$P8<=2025),1,0) -> 0 | BH8: =IF(AND($N8="Y",AND($P8>2025,$P8<=2030)),1,0) -> 0 | BI8: =IF(AND($N8="Y",$P8>2030),1,0) -> 0 | BJ8: =MAX(BG8:BI8) -> 0 | BK8: =IF(AND($R8="Y",$U8<=2025),1,0) -> 0 | BL8: =IF(AND($R8="Y",AND($U8>2025,$U8<=2030)),1,0) -> 0 | BM8: =IF(AND($R8="Y",$U8>2030),1,0) -> 0 | BN8: =MAX(BK8:BM8) -> 0 | BO8: =IF(AND($Y8="Y",$AA8<=2025),1,0) -> 0 | BP8: =IF(AND($Y8="Y",AND($AA8>2025,$AA8<=2030)),1,0) -> 0 | BQ8: =IF(AND($Y8="Y",$AA8>2030),1,0) -> 0 | BR8: =IF(AND($AP8="Y",$AS8<=2025),1,0) -> 0 | BS8: =IF(AND($AP8="Y",AND($AS8>2025,$AS8<=2030)),1,0) -> 0 | BT8: =IF(AND($AP8="Y",$AS8>2030),1,0) -> 1 | BU8: =IF(AND(AL8<=2025,CF8=0,AJ8="Y"),1,0) -> 0 | BV8: =IF(AND(AL8>=2026,AL8<=2030,AJ8="Y",CF8=0),1,0) -> 0 | BW8: =IF(AND(AL8>=2031,CF8=0,AJ8="Y"),1,0) -> 0 | BX8: =IF(AND($AJ8="Y",$AL8<=2024),1,0) -> 0 | BY8: =IF(AND($AJ8="Y",AND($AL8>2024,$AL8<=2030)),1,0) -> 0 | BZ8: =IF(AND($AJ8="Y",$AL8>2030),1,0) -> 0 | CA8: =MAX(BX8:BZ8) -> 0 | CB8: =IF(AND(CF8=0,AJ8="Y"),1,0) -> 0 | CC8: =MAX($BO8,$BR8) -> 0 | CD8: =MAX($BP8,$BS8) -> 0 | CE8: =MAX($BQ8,$BT8) -> 1 | CF8: =MAX(CC8:CE8) -> 1 | CG8: =MAX($CF8,$CA8) -> 1 | CH8: =MAX(CF8,CB8) -> 1 | CI8: =IF(AND($AY8="Y",$BA8<=2024),1,0) -> 0 | CJ8: =IF(AND($AY8="Y",AND($BA8>2024,$BA8<=2030)),1,0) -> 0 | CK8: =IF(AND($AY8="Y",$BA8>2030),1,0) -> 0 | CL8: =SUM(CC8,BU8,BK8,BG8) -> 0 | CM8: =SUM(CD8,BV8,BL8,BH8) -> 0 | CN8: =SUM(CE8,BW8,BM8,BI8) -> 1 | CO8: =CF8+CB8+BN8+BJ8 -> 1 | CP8: =MAX(CH8,BN8,BJ8) -> 1 | CQ8: =IF($AV8="Yes",1,0) -> 0 | CR8: =IF($AV8="No",1,0) -> 0 | CS8: =IF($AV8="Not Specified",1,0) -> 1 | CT8: =IF(OR(AND(U8>=2026,U8<=2030),AND(X8>=2026,X8<=2030)),1,"") | CU8: =AA8&" "&AS8 -> 2050 | CV8: =MAX(AA8,AS8) -> 2050 | CW8: 0 | CX8: 0 | CY8: 0 | CZ8: 0 | DA8: 0 | DB8: 0 | DC8: 0 | DD8: 0 | DE8: 0 | DF8: 0 | DG8: 0 | DH8: 0 | DI8: 0 | DJ8: 0 | DK8: 0 | DL8: 0 | DM8: 0 | DN8: 0 | DO8: 0 | DP8: 0 | DQ8: 0 | DR8: 0 | DS8: 0 | DT8: N | DU8: 0 | DV8: I | DW8: G | DX8: Y, g | DY8: 0 | DZ8: =Q8 -> N | EA8: =Z8 | EB8: =AP8 -> Y | EC8: =AJ8 -> N | ED8: =AV8 -> Not Specified | EF8: =MAX(AS8,AA8) -> 2050
A9: 6 | B9: 5 | C9: Sinopec Group | D9: Petroleum Refining | E9: Oil and gas | F9: China | G9: Asia | H9: $407,490.1 | I9: $8,036.4 | J9: -0.145 | K9: $375,395.1 | L9: 495096 | M9: 27 | N9: N | Q9: N | R9: N | AC9: Carbon neutral(ity) | AD9: Carbon Neutral | AE9: Yes | AF9: Yes | AG9: Not Specified | AH9: 1,2 | AI9: C | AJ9: Y | AK9: Strive to achieve carbon neutrality around 2050. | AL9: 2050 | AP9: N | AV9: Yes | AW9: Yes (nature-based removals e.g. Forestation, soil carbon enhancement) | AX9: No | AY9: N | BG9: =IF(AND($N9="Y",$P9<=2025),1,0) -> 0 | BH9: =IF(AND($N9="Y",AND($P9>2025,$P9<=2030)),1,0) -> 0 | BI9: =IF(AND($N9="Y",$P9>2030),1,0) -> 0 | BJ9: =MAX(BG9:BI9) -> 0 | BK9: =IF(AND($R9="Y",$U9<=2025),1,0) -> 0 | BL9: =IF(AND($R9="Y",AND($U9>2025,$U9<=2030)),1,0) -> 0 | BM9: =IF(AND($R9="Y",$U9>2030),1,0) -> 0 | BN9: =MAX(BK9:BM9) -> 0 | BO9: =IF(AND($Y9="Y",$AA9<=2025),1,0) -> 0 | BP9: =IF(AND($Y9="Y",AND($AA9>2025,$AA9<=2030)),1,0) -> 0 | BQ9: =IF(AND($Y9="Y",$AA9>2030),1,0) -> 0 | BR9: =IF(AND($AP9="Y",$AS9<=2025),1,0) -> 0 | BS9: =IF(AND($AP9="Y",AND($AS9>2025,$AS9<=2030)),1,0) -> 0 | BT9: =IF(AND($AP9="Y",$AS9>2030),1,0) -> 0 | BU9: =IF(AND(AL9<=2025,CF9=0,AJ9="Y"),1,0) -> 0 | BV9: =IF(AND(AL9>=2026,AL9<=2030,AJ9="Y",CF9=0),1,0) -> 0 | BW9: =IF(AND(AL9>=2031,CF9=0,AJ9="Y"),1,0) -> 1 | BX9: =IF(AND($AJ9="Y",$AL9<=2024),1,0) -> 0 | BY9: =IF(AND($AJ9="Y",AND($AL9>2024,$AL9<=2030)),1,0) -> 0 | BZ9: =IF(AND($AJ9="Y",$AL9>2030),1,0) -> 1 | CA9: =MAX(BX9:BZ9) -> 1 | CB9: =IF(AND(CF9=0,AJ9="Y"),1,0) -> 1 | CC9: =MAX($BO9,$BR9) -> 0 | CD9: =MAX($BP9,$BS9) -> 0 | CE9: =MAX($BQ9,$BT9) -> 0 | CF9: =MAX(CC9:CE9) -> 0 | CG9: =MAX($CF9,$CA9) -> 1 | CH9: =MAX(CF9,CB9) -> 1 | CI9: =IF(AND($AY9="Y",$BA9<=2024),1,0) -> 0 | CJ9: =IF(AND($AY9="Y",AND($BA9>2024,$BA9<=2030)),1,0) -> 0 | CK9: =IF(AND($AY9="Y",$BA9>2030),1,0) -> 0 | CL9: =SUM(CC9,BU9,BK9,BG9) -> 0 | CM9: =SUM(CD9,BV9,BL9,BH9) -> 0 | CN9: =SUM(CE9,BW9,BM9,BI9) -> 1 | CO9: =CF9+CB9+BN9+BJ9 -> 1 | CP9: =MAX(CH9,BN9,BJ9) -> 1 | CQ9: =IF($AV9="Yes",1,0) -> 1 | CR9: =IF($AV9="No",1,0) -> 0 | CS9: =IF($AV9="Not Specified",1,0) -> 0 | CT9: =IF(OR(AND(U9>=2026,U9<=2030),AND(X9>=2026,X9<=2030)),1,"") | CU9: =AA9&" "&AS9 | CV9: =MAX(AA9,AS9) -> 0 | CW9: 0 | CX9: 0 | CY9: 0 | CZ9: 0 | DA9: 0 | DB9: 0 | DC9: 0 | DD9: 0 | DE9: 0 | DF9: 0 | DG9: 0 | DH9: 0 | DI9: 0 | DJ9: 0 | DK9: 0 | DL9: 0 | DM9: 0 | DN9: 0 | DO9: 0 | DP9: 0 | DQ9: 0 | DR9: 0 | DS9: 0 | DT9: N | DU9: 0 | DV9: N | DW9: G | DX9: U | DY9: 0 | DZ9: =Q9 -> N | EA9: =Z9 | EB9: =AP9 -> N | EC9: =AJ9 -> Y | ED9: =AV9 -> Yes | EF9: =MAX(AS9,AA9) -> 0
A10: 7 | B10: 8 | C10: UnitedHealth Group | D10: Health Care: Insurance and Managed Care | E10: Health care and pharmaceuticals | F10: U.S. | G10: North America | H10: $400,278 | I10: $14,405 | J10: -0.356 | K10: $298,278 | L10: 400000 | M10: 29 | N10: N | Q10: Y | R10: Y | S10: Targets set | T10: 1.5°C | U10: 2030 | Y10: N | Z10: Committed | AC10: Net zero | AD10: Net Zero | AE10: Yes | AF10: Yes | AG10: No | AH10: 1,2 | AJ10: N | AO10: C | AP10: Y | AQ10: 1,2 | AR10: Achieving operational net-zero by 2035 We will continue to pursue our ambition to achieve net-zero emissions in scopes 1 and 2 by 2035 across our global operations | AS10: 2035 | AV10: Not Specified | AW10: Not Specified | AX10: No | AY10: N | BG10: =IF(AND($N10="Y",$P10<=2025),1,0) -> 0 | BH10: =IF(AND($N10="Y",AND($P10>2025,$P10<=2030)),1,0) -> 0 | BI10: =IF(AND($N10="Y",$P10>2030),1,0) -> 0 | BJ10: =MAX(BG10:BI10) -> 0 | BK10: =IF(AND($R10="Y",$U10<=2025),1,0) -> 0 | BL10: =IF(AND($R10="Y",AND($U10>2025,$U10<=2030)),1,0) -> 1 | BM10: =IF(AND($R10="Y",$U10>2030),1,0) -> 0 | BN10: =MAX(BK10:BM10) -> 1 | BO10: =IF(AND($Y10="Y",$AA10<=2025),1,0) -> 0 | BP10: =IF(AND($Y10="Y",AND($AA10>2025,$AA10<=2030)),1,0) -> 0 | BQ10: =IF(AND($Y10="Y",$AA10>2030),1,0) -> 0 | BR10: =IF(AND($AP10="Y",$AS10<=2025),1,0) -> 0 | BS10: =IF(AND($AP10="Y",AND($AS10>2025,$AS10<=2030)),1,0) -> 0 | BT10: =IF(AND($AP10="Y",$AS10>2030),1,0) -> 1 | BU10: =IF(AND(AL10<=2025,CF10=0,AJ10="Y"),1,0) -> 0 | BV10: =IF(AND(AL10>=2026,AL10<=2030,AJ10="Y",CF10=0),1,0) -> 0 | BW10: =IF(AND(AL10>=2031,CF10=0,AJ10="Y"),1,0) -> 0 | BX10: =IF(AND($AJ10="Y",$AL10<=2024),1,0) -> 0 | BY10: =IF(AND($AJ10="Y",AND($AL10>2024,$AL10<=2030)),1,0) -> 0 | BZ10: =IF(AND($AJ10="Y",$AL10>2030),1,0) -> 0 | CA10: =MAX(BX10:BZ10) -> 0 | CB10: =IF(AND(CF10=0,AJ10="Y"),1,0) -> 0 | CC10: =MAX($BO10,$BR10) -> 0 | CD10: =MAX($BP10,$BS10) -> 0 | CE10: =MAX($BQ10,$BT10) -> 1 | CF10: =MAX(CC10:CE10) -> 1 | CG10: =MAX($CF10,$CA10) -> 1 | CH10: =MAX(CF10,CB10) -> 1 | CI10: =IF(AND($AY10="Y",$BA10<=2024),1,0) -> 0 | CJ10: =IF(AND($AY10="Y",AND($BA10>2024,$BA10<=2030)),1,0) -> 0 | CK10: =IF(AND($AY10="Y",$BA10>2030),1,0) -> 0 | CL10: =SUM(CC10,BU10,BK10,BG10) -> 0 | CM10: =SUM(CD10,BV10,BL10,BH10) -> 1 | CN10: =SUM(CE10,BW10,BM10,BI10) -> 1 | CO10: =CF10+CB10+BN10+BJ10 -> 2 | CP10: =MAX(CH10,BN10,BJ10) -> 1 | CQ10: =IF($AV10="Yes",1,0) -> 0 | CR10: =IF($AV10="No",1,0) -> 0 | CS10: =IF($AV10="Not Specified",1,0) -> 1 | CT10: =IF(OR(AND(U10>=2026,U10<=2030),AND(X10>=2026,X10<=2030)),1,"") -> 1 | CU10: =AA10&" "&AS10 -> 2035 | CV10: =MAX(AA10,AS10) -> 2035 | CW10: 0 | CX10: 0 | CY10: 0 | CZ10: 0 | DA10: 0 | DB10: 0 | DC10: 1 | DD10: 1 | DE10: 0 | DF10: 1 | DG10: 0 | DH10: 1 | DI10: 0 | DJ10: 0 | DK10: 0 | DL10: 0 | DM10: 1 | DN10: 0 | DO10: 1 | DP10: 1 | DQ10: 0 | DR10: 1 | DS10: 0 | DT10: N | DU10: Yes | DV10: C | DW10: N | DX10: 0 | DY10: Y | DZ10: =Q10 -> Y | EA10: =Z10 -> Committed | EB10: =AP10 -> Y | EC10: =AJ10 -> N | ED10: =AV10 -> Not Specified | EF10: =MAX(AS10,AA10) -> 2035
A11: 8 | B11: 7 | C11: Apple | D11: Computers | E11: Technology | F11: U.S. | G11: North America | H11: $391,035 | I11: $93,736 | J11: -0.034 | K11: $364,980 | L11: 164000 | M11: 23 | N11: Y | O11: 2016 | P11: 2021 | Q11: Y | R11: Y | S11: Targets set | T11: 1.5°C | U11: 2030 | AC11: Carbon neutral(ity) | AD11: Carbon Neutral | AE11: Yes | AF11: Yes | AG11: Yes | AH11: 1,2,3 | AI11: C,V | AJ11: Y | AK11: We‚Äôre committed to our ambitious, sciencebased Apple 2030 goal to reduce our collective scope 1, 2, and 3 emissions ‚ upstream and downstream ‚ by 75 percent before balancing the remaining emissions with high-quality carbon removals. To achieve this goal, we're reducing emissions across our value chain and directing our efforts toward decarbonizing the largest sources of emissions. (pg 10) | AL11: 2030 | AP11: N | AV11: Yes | AW11: Yes (nature-based removals e.g. Forestation, soil carbon enhancement) | AX11: Yes | AY11: N | BG11: =IF(AND($N11="Y",$P11<=2025),1,0) -> 1 | BH11: =IF(AND($N11="Y",AND($P11>2025,$P11<=2030)),1,0) -> 0 | BI11: =IF(AND($N11="Y",$P11>2030),1,0) -> 0 | BJ11: =MAX(BG11:BI11) -> 1 | BK11: =IF(AND($R11="Y",$U11<=2025),1,0) -> 0 | BL11: =IF(AND($R11="Y",AND($U11>2025,$U11<=2030)),1,0) -> 1 | BM11: =IF(AND($R11="Y",$U11>2030),1,0) -> 0 | BN11: =MAX(BK11:BM11) -> 1 | BO11: =IF(AND($Y11="Y",$AA11<=2025),1,0) -> 0 | BP11: =IF(AND($Y11="Y",AND($AA11>2025,$AA11<=2030)),1,0) -> 0 | BQ11: =IF(AND($Y11="Y",$AA11>2030),1,0) -> 0 | BR11: =IF(AND($AP11="Y",$AS11<=2025),1,0) -> 0 | BS11: =IF(AND($AP11="Y",AND($AS11>2025,$AS11<=2030)),1,0) -> 0 | BT11: =IF(AND($AP11="Y",$AS11>2030),1,0) -> 0 | BU11: =IF(AND(AL11<=2025,CF11=0,AJ11="Y"),1,0) -> 0 | BV11: =IF(AND(AL11>=2026,AL11<=2030,AJ11="Y",CF11=0),1,0) -> 1 | BW11: =IF(AND(AL11>=2031,CF11=0,AJ11="Y"),1,0) -> 0 | BX11: =IF(AND($AJ11="Y",$AL11<=2024),1,0) -> 0 | BY11: =IF(AND($AJ11="Y",AND($AL11>2024,$AL11<=2030)),1,0) -> 1 | BZ11: =IF(AND($AJ11="Y",$AL11>2030),1,0) -> 0 | CA11: =MAX(BX11:BZ11) -> 1 | CB11: =IF(AND(CF11=0,AJ11="Y"),1,0) -> 1 | CC11: =MAX($BO11,$BR11) -> 0 | CD11: =MAX($BP11,$BS11) -> 0 | CE11: =MAX($BQ11,$BT11) -> 0 | CF11: =MAX(CC11:CE11) -> 0 | CG11: =MAX($CF11,$CA11) -> 1 | CH11: =MAX(CF11,CB11) -> 1 | CI11: =IF(AND($AY11="Y",$BA11<=2024),1,0) -> 0 | CJ11: =IF(AND($AY11="Y",AND($BA11>2024,$BA11<=2030)),1,0) -> 0 | CK11: =IF(AND($AY11="Y",$BA11>2030),1,0) -> 0 | CL11: =SUM(CC11,BU11,BK11,BG11) -> 1 | CM11: =SUM(CD11,BV11,BL11,BH11) -> 2 | CN11: =SUM(CE11,BW11,BM11,BI11) -> 0 | CO11: =CF11+CB11+BN11+BJ11 -> 3 | CP11: =MAX(CH11,BN11,BJ11) -> 1 | CQ11: =IF($AV11="Yes",1,0) -> 1 | CR11: =IF($AV11="No",1,0) -> 0 | CS11: =IF($AV11="Not Specified",1,0) -> 0 | CT11: =IF(OR(AND(U11>=2026,U11<=2030),AND(X11>=2026,X11<=2030)),1,"") -> 1 | CU11: =AA11&" "&AS11 | CV11: =MAX(AA11,AS11) -> 0 | CW11: 1 | CX11: 0 | CY11: 0 | CZ11: 1 | DA11: 0 | DB11: 0 | DC11: 0 | DD11: 0 | DE11: 0 | DF11: 1 | DG11: 0 | DH11: 1 | DI11: 1 | DJ11: 0 | DK11: 0 | DL11: 1 | DM11: 1 | DN11: 1 | DO11: 1 | DP11: 1 | DQ11: 0 | DR11: 1 | DS11: 1 | DT11: Y | DU11: No | DV11: N | DW11: C, V | DX11: R | DY11: 0 | DZ11: =Q11 -> Y | EA11: =Z11 | EB11: =AP11 -> N | EC11: =AJ11 -> Y | ED11: =AV11 -> Yes | EF11: =MAX(AS11,AA11) -> 0
A12: 9 | B12: 10 | C12: CVS Health | D12: Health Care: Pharmacy and Other Services | E12: Health care and pharmaceuticals | F12: U.S. | G12: North America | H12: $372,809 | I12: $4,614 | J12: -0.447 | K12: $253,215 | L12: 259500 | M12: 30 | N12: N | Q12: Y | R12: Y | S12: Targets set | T12: 1.5°C | U12: 2030 | V12: Targets set | W12: 1.5°C | X12: 2050 | Y12: Y | Z12: Targets set | AA12: 2050 | AC12: Net zero | AD12: Net Zero | AE12: Yes | AF12: Yes | AG12: Yes | AH12: 1,2,3 | AJ12: N | AO12: C,V | AP12: Y | AQ12: 1,2,3 | AR12: *CVS health is one of the first companies in the world to have our net zero targets validated by the Science-Based Targets initiative's (SBTi) net zero methodology. This set us on the path to achieving net zero emissions from our direct operations by 2048 and across their value chain by 2050. They also committed to achieving carbon neutrality by 2030. *Reduce absolute scope: 1, 2 and 3 (value chain) emissions by 90% by 2050. | AS12: 2050 | AV12: Yes | AW12: Not Specified | AX12: No | AY12: N | BG12: =IF(AND($N12="Y",$P12<=2025),1,0) -> 0 | BH12: =IF(AND($N12="Y",AND($P12>2025,$P12<=2030)),1,0) -> 0 | BI12: =IF(AND($N12="Y",$P12>2030),1,0) -> 0 | BJ12: =MAX(BG12:BI12) -> 0 | BK12: =IF(AND($R12="Y",$U12<=2025),1,0) -> 0 | BL12: =IF(AND($R12="Y",AND($U12>2025,$U12<=2030)),1,0) -> 1 | BM12: =IF(AND($R12="Y",$U12>2030),1,0) -> 0 | BN12: =MAX(BK12:BM12) -> 1 | BO12: =IF(AND($Y12="Y",$AA12<=2025),1,0) -> 0 | BP12: =IF(AND($Y12="Y",AND($AA12>2025,$AA12<=2030)),1,0) -> 0 | BQ12: =IF(AND($Y12="Y",$AA12>2030),1,0) -> 1 | BR12: =IF(AND($AP12="Y",$AS12<=2025),1,0) -> 0 | BS12: =IF(AND($AP12="Y",AND($AS12>2025,$AS12<=2030)),1,0) -> 0 | BT12: =IF(AND($AP12="Y",$AS12>2030),1,0) -> 1 | BU12: =IF(AND(AL12<=2025,CF12=0,AJ12="Y"),1,0) -> 0 | BV12: =IF(AND(AL12>=2026,AL12<=2030,AJ12="Y",CF12=0),1,0) -> 0 | BW12: =IF(AND(AL12>=2031,CF12=0,AJ12="Y"),1,0) -> 0 | BX12: =IF(AND($AJ12="Y",$AL12<=2024),1,0) -> 0 | BY12: =IF(AND($AJ12="Y",AND($AL12>2024,$AL12<=2030)),1,0) -> 0 | BZ12: =IF(AND($AJ12="Y",$AL12>2030),1,0) -> 0 | CA12: =MAX(BX12:BZ12) -> 0 | CB12: =IF(AND(CF12=0,AJ12="Y"),1,0) -> 0 | CC12: =MAX($BO12,$BR12) -> 0 | CD12: =MAX($BP12,$BS12) -> 0 | CE12: =MAX($BQ12,$BT12) -> 1 | CF12: =MAX(CC12:CE12) -> 1 | CG12: =MAX($CF12,$CA12) -> 1 | CH12: =MAX(CF12,CB12) -> 1 | CI12: =IF(AND($AY12="Y",$BA12<=2024),1,0) -> 0 | CJ12: =IF(AND($AY12="Y",AND($BA12>2024,$BA12<=2030)),1,0) -> 0 | CK12: =IF(AND($AY12="Y",$BA12>2030),1,0) -> 0 | CL12: =SUM(CC12,BU12,BK12,BG12) -> 0 | CM12: =SUM(CD12,BV12,BL12,BH12) -> 1 | CN12: =SUM(CE12,BW12,BM12,BI12) -> 1 | CO12: =CF12+CB12+BN12+BJ12 -> 2 | CP12: =MAX(CH12,BN12,BJ12) -> 1 | CQ12: =IF($AV12="Yes",1,0) -> 1 | CR12: =IF($AV12="No",1,0) -> 0 | CS12: =IF($AV12="Not Specified",1,0) -> 0 | CT12: =IF(OR(AND(U12>=2026,U12<=2030),AND(X12>=2026,X12<=2030)),1,"") -> 1 | CU12: =AA12&" "&AS12 -> 2050 2050 | CV12: =MAX(AA12,AS12) -> 2050 | CW12: 0 | CX12: 1 | CY12: 0 | CZ12: 1 | DA12: 0 | DB12: 0 | DC12: 1 | DD12: 1 | DE12: 0 | DF12: 1 | DG12: 0 | DH12: 1 | DI12: 0 | DJ12: 0 | DK12: 0 | DL12: 0 | DM12: 1 | DN12: 1 | DO12: 1 | DP12: 0 | DQ12: 0 | DR12: 1 | DS12: 0 | DT12: Y | DU12: Yes | DV12: C, V | DW12: C | DX12: U | DY12: U | DZ12: =Q12 -> Y | EA12: =Z12 -> Targets set | EB12: =AP12 -> Y | EC12: =AJ12 -> N | ED12: =AV12 -> Yes | EF12: =MAX(AS12,AA12) -> 2050
A13: 10 | B13: 9 | C13: Berkshire Hathaway | D13: Insurance: Property and Casualty | E13: Financial services | F13: U.S. | G13: North America | H13: $371,433 | I13: $88,995 | J13: -0.075 | K13: $1,153,881 | L13: 392400 | M13: 29 | N13: N | Q13: N | R13: N | AC13: No target | AD13: No Target | AE13: Not Specified | AF13: Not Specified | AG13: Not Specified | AJ13: N | AP13: N | AV13: Not Specified | AW13: Not Specified | AX13: No | AY13: N | BG13: =IF(AND($N13="Y",$P13<=2025),1,0) -> 0 | BH13: =IF(AND($N13="Y",AND($P13>2025,$P13<=2030)),1,0) -> 0 | BI13: =IF(AND($N13="Y",$P13>2030),1,0) -> 0 | BJ13: =MAX(BG13:BI13) -> 0 | BK13: =IF(AND($R13="Y",$U13<=2025),1,0) -> 0 | BL13: =IF(AND($R13="Y",AND($U13>2025,$U13<=2030)),1,0) -> 0 | BM13: =IF(AND($R13="Y",$U13>2030),1,0) -> 0 | BN13: =MAX(BK13:BM13) -> 0 | BO13: =IF(AND($Y13="Y",$AA13<=2025),1,0) -> 0 | BP13: =IF(AND($Y13="Y",AND($AA13>2025,$AA13<=2030)),1,0) -> 0 | BQ13: =IF(AND($Y13="Y",$AA13>2030),1,0) -> 0 | BR13: =IF(AND($AP13="Y",$AS13<=2025),1,0) -> 0 | BS13: =IF(AND($AP13="Y",AND($AS13>2025,$AS13<=2030)),1,0) -> 0 | BT13: =IF(AND($AP13="Y",$AS13>2030),1,0) -> 0 | BU13: =IF(AND(AL13<=2025,CF13=0,AJ13="Y"),1,0) -> 0 | BV13: =IF(AND(AL13>=2026,AL13<=2030,AJ13="Y",CF13=0),1,0) -> 0 | BW13: =IF(AND(AL13>=2031,CF13=0,AJ13="Y"),1,0) -> 0 | BX13: =IF(AND($AJ13="Y",$AL13<=2024),1,0) -> 0 | BY13: =IF(AND($AJ13="Y",AND($AL13>2024,$AL13<=2030)),1,0) -> 0 | BZ13: =IF(AND($AJ13="Y",$AL13>2030),1,0) -> 0 | CA13: =MAX(BX13:BZ13) -> 0 | CB13: =IF(AND(CF13=0,AJ13="Y"),1,0) -> 0 | CC13: =MAX($BO13,$BR13) -> 0 | CD13: =MAX($BP13,$BS13) -> 0 | CE13: =MAX($BQ13,$BT13) -> 0 | CF13: =MAX(CC13:CE13) -> 0 | CG13: =MAX($CF13,$CA13) -> 0 | CH13: =MAX(CF13,CB13) -> 0 | CI13: =IF(AND($AY13="Y",$BA13<=2024),1,0) -> 0 | CJ13: =IF(AND($AY13="Y",AND($BA13>2024,$BA13<=2030)),1,0) -> 0 | CK13: =IF(AND($AY13="Y",$BA13>2030),1,0) -> 0 | CL13: =SUM(CC13,BU13,BK13,BG13) -> 0 | CM13: =SUM(CD13,BV13,BL13,BH13) -> 0 | CN13: =SUM(CE13,BW13,BM13,BI13) -> 0 | CO13: =CF13+CB13+BN13+BJ13 -> 0 | CP13: =MAX(CH13,BN13,BJ13) -> 0 | CQ13: =IF($AV13="Yes",1,0) -> 0 | CR13: =IF($AV13="No",1,0) -> 0 | CS13: =IF($AV13="Not Specified",1,0) -> 1 | CT13: =IF(OR(AND(U13>=2026,U13<=2030),AND(X13>=2026,X13<=2030)),1,"") | CU13: =AA13&" "&AS13 | CV13: =MAX(AA13,AS13) -> 0 | CW13: 0 | CX13: 0 | CY13: 0 | CZ13: 0 | DA13: 0 | DB13: 0 | DC13: 0 | DD13: 0 | DE13: 0 | DF13: 0 | DG13: 0 | DH13: 0 | DI13: 0 | DJ13: 0 | DK13: 0 | DL13: 0 | DM13: 0 | DN13: 0 | DO13: 0 | DP13: 0 | DQ13: 0 | DR13: 0 | DS13: 0 | DT13: N | DU13: 0 | DV13: N | DW13: N | DX13: 0 | DY13: 0 | DZ13: =Q13 -> N | EA13: =Z13 | EB13: =AP13 -> N | EC13: =AJ13 -> N | ED13: =AV13 -> Not Specified | EF13: =MAX(AS13,AA13) -> 0
A14: 11 | B14: 16 | C14: McKesson | D14: Wholesalers: Health Care | E14: Health care and pharmaceuticals | F14: U.S. | G14: North America | H14: $359,051 | I14: $3,295 | J14: 0.098 | K14: $75,140 | L14: 44000 | M14: 31 | N14: N | Q14: Y | R14: Y | S14: Targets set | T14: 1.5°C | U14: 2032 | AC14: Other | AD14: Other Emission Reduction | AE14: Yes | AF14: Yes | AG14: Partial | AH14: 1,2 | AJ14: N | AP14: N | AV14: Not Specified | AW14: Not Specified | AX14: No | AY14: Y | AZ14: Mckesson has established the strategy to reduce GHG emissions from 2021, but has not clearly described about their end target (net zero). | BA14: 2032 | BG14: =IF(AND($N14="Y",$P14<=2025),1,0) -> 0 | BH14: =IF(AND($N14="Y",AND($P14>2025,$P14<=2030)),1,0) -> 0 | BI14: =IF(AND($N14="Y",$P14>2030),1,0) -> 0 | BJ14: =MAX(BG14:BI14) -> 0 | BK14: =IF(AND($R14="Y",$U14<=2025),1,0) -> 0 | BL14: =IF(AND($R14="Y",AND($U14>2025,$U14<=2030)),1,0) -> 0 | BM14: =IF(AND($R14="Y",$U14>2030),1,0) -> 1 | BN14: =MAX(BK14:BM14) -> 1 | BO14: =IF(AND($Y14="Y",$AA14<=2025),1,0) -> 0 | BP14: =IF(AND($Y14="Y",AND($AA14>2025,$AA14<=2030)),1,0) -> 0 | BQ14: =IF(AND($Y14="Y",$AA14>2030),1,0) -> 0 | BR14: =IF(AND($AP14="Y",$AS14<=2025),1,0) -> 0 | BS14: =IF(AND($AP14="Y",AND($AS14>2025,$AS14<=2030)),1,0) -> 0 | BT14: =IF(AND($AP14="Y",$AS14>2030),1,0) -> 0 | BU14: =IF(AND(AL14<=2025,CF14=0,AJ14="Y"),1,0) -> 0 | BV14: =IF(AND(AL14>=2026,AL14<=2030,AJ14="Y",CF14=0),1,0) -> 0 | BW14: =IF(AND(AL14>=2031,CF14=0,AJ14="Y"),1,0) -> 0 | BX14: =IF(AND($AJ14="Y",$AL14<=2024),1,0) -> 0 | BY14: =IF(AND($AJ14="Y",AND($AL14>2024,$AL14<=2030)),1,0) -> 0 | BZ14: =IF(AND($AJ14="Y",$AL14>2030),1,0) -> 0 | CA14: =MAX(BX14:BZ14) -> 0 | CB14: =IF(AND(CF14=0,AJ14="Y"),1,0) -> 0 | CC14: =MAX($BO14,$BR14) -> 0 | CD14: =MAX($BP14,$BS14) -> 0 | CE14: =MAX($BQ14,$BT14) -> 0 | CF14: =MAX(CC14:CE14) -> 0 | CG14: =MAX($CF14,$CA14) -> 0 | CH14: =MAX(CF14,CB14) -> 0 | CI14: =IF(AND($AY14="Y",$BA14<=2024),1,0) -> 0 | CJ14: =IF(AND($AY14="Y",AND($BA14>2024,$BA14<=2030)),1,0) -> 0 | CK14: =IF(AND($AY14="Y",$BA14>2030),1,0) -> 1 | CL14: =SUM(CC14,BU14,BK14,BG14) -> 0 | CM14: =SUM(CD14,BV14,BL14,BH14) -> 0 | CN14: =SUM(CE14,BW14,BM14,BI14) -> 1 | CO14: =CF14+CB14+BN14+BJ14 -> 1 | CP14: =MAX(CH14,BN14,BJ14) -> 1 | CQ14: =IF($AV14="Yes",1,0) -> 0 | CR14: =IF($AV14="No",1,0) -> 0 | CS14: =IF($AV14="Not Specified",1,0) -> 1 | CT14: =IF(OR(AND(U14>=2026,U14<=2030),AND(X14>=2026,X14<=2030)),1,"") | CU14: =AA14&" "&AS14 | CV14: =MAX(AA14,AS14) -> 0 | CW14: 0 | CX14: 0 | CY14: 0 | CZ14: 0 | DA14: 0 | DB14: 0 | DC14: 0 | DD14: 0 | DE14: 0 | DF14: 0 | DG14: 1 | DH14: 1 | DI14: 0 | DJ14: 0 | DK14: 0 | DL14: 0 | DM14: 0 | DN14: 0 | DO14: 0 | DP14: 0 | DQ14: 0 | DR14: 1 | DS14: 0 | DT14: Y | DU14: No | DV14: N | DW14: N | DX14: 0 | DY14: 0 | DZ14: =Q14 -> Y | EA14: =Z14 | EB14: =AP14 -> N | EC14: =AJ14 -> N | ED14: =AV14 -> Not Specified | EF14: =MAX(AS14,AA14) -> 0
A15: 12 | B15: 11 | C15: Volkswagen | D15: Motor Vehicles | E15: Automotive | F15: Germany | G15: Europe | H15: $351,093.3 | I15: $12,275.3 | J15: -0.316 | K15: $655,316.8 | L15: 646501 | M15: 31 | N15: N | Q15: Y | R15: Y | S15: Targets set | T15: 1.5Â°C/2Â°C | U15: 2030 | AC15: Carbon neutral(ity) | AD15: Carbon Neutral | AE15: Yes | AF15: Yes | AG15: Partial | AH15: 1,2 | AI15: C | AJ15: Y | AK15: achieve net carbon neutrality by 2050 (pg 236) | AL15: 2050 | AP15: N | AV15: Yes | AW15: Yes (nature-based removals e.g. Forestation, soil carbon enhancement) | AX15: No | AY15: N | BG15: =IF(AND($N15="Y",$P15<=2025),1,0) -> 0 | BH15: =IF(AND($N15="Y",AND($P15>2025,$P15<=2030)),1,0) -> 0 | BI15: =IF(AND($N15="Y",$P15>2030),1,0) -> 0 | BJ15: =MAX(BG15:BI15) -> 0 | BK15: =IF(AND($R15="Y",$U15<=2025),1,0) -> 0 | BL15: =IF(AND($R15="Y",AND($U15>2025,$U15<=2030)),1,0) -> 1 | BM15: =IF(AND($R15="Y",$U15>2030),1,0) -> 0 | BN15: =MAX(BK15:BM15) -> 1 | BO15: =IF(AND($Y15="Y",$AA15<=2025),1,0) -> 0 | BP15: =IF(AND($Y15="Y",AND($AA15>2025,$AA15<=2030)),1,0) -> 0 | BQ15: =IF(AND($Y15="Y",$AA15>2030),1,0) -> 0 | BR15: =IF(AND($AP15="Y",$AS15<=2025),1,0) -> 0 | BS15: =IF(AND($AP15="Y",AND($AS15>2025,$AS15<=2030)),1,0) -> 0 | BT15: =IF(AND($AP15="Y",$AS15>2030),1,0) -> 0 | BU15: =IF(AND(AL15<=2025,CF15=0,AJ15="Y"),1,0) -> 0 | BV15: =IF(AND(AL15>=2026,AL15<=2030,AJ15="Y",CF15=0),1,0) -> 0 | BW15: =IF(AND(AL15>=2031,CF15=0,AJ15="Y"),1,0) -> 1 | BX15: =IF(AND($AJ15="Y",$AL15<=2024),1,0) -> 0 | BY15: =IF(AND($AJ15="Y",AND($AL15>2024,$AL15<=2030)),1,0) -> 0 | BZ15: =IF(AND($AJ15="Y",$AL15>2030),1,0) -> 1 | CA15: =MAX(BX15:BZ15) -> 1 | CB15: =IF(AND(CF15=0,AJ15="Y"),1,0) -> 1 | CC15: =MAX($BO15,$BR15) -> 0 | CD15: =MAX($BP15,$BS15) -> 0 | CE15: =MAX($BQ15,$BT15) -> 0 | CF15: =MAX(CC15:CE15) -> 0 | CG15: =MAX($CF15,$CA15) -> 1 | CH15: =MAX(CF15,CB15) -> 1 | CI15: =IF(AND($AY15="Y",$BA15<=2024),1,0) -> 0 | CJ15: =IF(AND($AY15="Y",AND($BA15>2024,$BA15<=2030)),1,0) -> 0 | CK15: =IF(AND($AY15="Y",$BA15>2030),1,0) -> 0 | CL15: =SUM(CC15,BU15,BK15,BG15) -> 0 | CM15: =SUM(CD15,BV15,BL15,BH15) -> 1 | CN15: =SUM(CE15,BW15,BM15,BI15) -> 1 | CO15: =CF15+CB15+BN15+BJ15 -> 2 | CP15: =MAX(CH15,BN15,BJ15) -> 1 | CQ15: =IF($AV15="Yes",1,0) -> 1 | CR15: =IF($AV15="No",1,0) -> 0 | CS15: =IF($AV15="Not Specified",1,0) -> 0 | CT15: =IF(OR(AND(U15>=2026,U15<=2030),AND(X15>=2026,X15<=2030)),1,"") -> 1 | CU15: =AA15&" "&AS15 | CV15: =MAX(AA15,AS15) -> 0 | CW15: 0 | CX15: 0 | CY15: 1 | CZ15: 1 | DA15: 0 | DB15: 0 | DC15: 0 | DD15: 0 | DE15: 0 | DF15: 1 | DG15: 0 | DH15: 1 | DI15: 0 | DJ15: 0 | DK15: 0 | DL15: 0 | DM15: 1 | DN15: 0 | DO15: 1 | DP15: 1 | DQ15: 0 | DR15: 1 | DS15: 0 | DT15: Y | DU15: No | DV15: N | DW15: V | DX15: Y | DY15: 0 | DZ15: =Q15 -> Y | EA15: =Z15 | EB15: =AP15 -> N | EC15: =AJ15 -> Y | ED15: =AV15 -> Yes | EF15: =MAX(AS15,AA15) -> 0
A16: 13 | B16: 17 | C16: Alphabet | D16: Internet Services and Retailing | E16: Retail | F16: U.S. | G16: North America | H16: $350,018 | I16: $100,118 | J16: 0.357 | K16: $450,256 | L16: 183323 | M16: 17 | N16: N | Q16: Y | R16: Y | S16: Targets set | T16: 1.5°C | U16: 2030 | AC16: Net zero | AD16: Net Zero | AE16: Yes | AF16: Yes | AG16: Yes | AH16: 1,2,3 | AJ16: N | AO16: C,V | AP16: Y | AQ16: 1,2,3 | AR16: We aim to run on 24/7 carbon-free energy on every grid where we operate by 2030. Reduce 50% of our combined Scope 1, 2 (market-based), and 3 absolute emissions (versus our 2019 baseline) before 2030 | AS16: 2030 | AV16: No | AW16: Yes (nature-based and CCS-based removals) | AX16: Yes | AY16: N | BG16: =IF(AND($N16="Y",$P16<=2025),1,0) -> 0 | BH16: =IF(AND($N16="Y",AND($P16>2025,$P16<=2030)),1,0) -> 0 | BI16: =IF(AND($N16="Y",$P16>2030),1,0) -> 0 | BJ16: =MAX(BG16:BI16) -> 0 | BK16: =IF(AND($R16="Y",$U16<=2025),1,0) -> 0 | BL16: =IF(AND($R16="Y",AND($U16>2025,$U16<=2030)),1,0) -> 1 | BM16: =IF(AND($R16="Y",$U16>2030),1,0) -> 0 | BN16: =MAX(BK16:BM16) -> 1 | BO16: =IF(AND($Y16="Y",$AA16<=2025),1,0) -> 0 | BP16: =IF(AND($Y16="Y",AND($AA16>2025,$AA16<=2030)),1,0) -> 0 | BQ16: =IF(AND($Y16="Y",$AA16>2030),1,0) -> 0 | BR16: =IF(AND($AP16="Y",$AS16<=2025),1,0) -> 0 | BS16: =IF(AND($AP16="Y",AND($AS16>2025,$AS16<=2030)),1,0) -> 1 | BT16: =IF(AND($AP16="Y",$AS16>2030),1,0) -> 0 | BU16: =IF(AND(AL16<=2025,CF16=0,AJ16="Y"),1,0) -> 0 | BV16: =IF(AND(AL16>=2026,AL16<=2030,AJ16="Y",CF16=0),1,0) -> 0 | BW16: =IF(AND(AL16>=2031,CF16=0,AJ16="Y"),1,0) -> 0 | BX16: =IF(AND($AJ16="Y",$AL16<=2024),1,0) -> 0 | BY16: =IF(AND($AJ16="Y",AND($AL16>2024,$AL16<=2030)),1,0) -> 0 | BZ16: =IF(AND($AJ16="Y",$AL16>2030),1,0) -> 0 | CA16: =MAX(BX16:BZ16) -> 0 | CB16: =IF(AND(CF16=0,AJ16="Y"),1,0) -> 0 | CC16: =MAX($BO16,$BR16) -> 0 | CD16: =MAX($BP16,$BS16) -> 1 | CE16: =MAX($BQ16,$BT16) -> 0 | CF16: =MAX(CC16:CE16) -> 1 | CG16: =MAX($CF16,$CA16) -> 1 | CH16: =MAX(CF16,CB16) -> 1 | CI16: =IF(AND($AY16="Y",$BA16<=2024),1,0) -> 0 | CJ16: =IF(AND($AY16="Y",AND($BA16>2024,$BA16<=2030)),1,0) -> 0 | CK16: =IF(AND($AY16="Y",$BA16>2030),1,0) -> 0 | CL16: =SUM(CC16,BU16,BK16,BG16) -> 0 | CM16: =SUM(CD16,BV16,BL16,BH16) -> 2 | CN16: =SUM(CE16,BW16,BM16,BI16) -> 0 | CO16: =CF16+CB16+BN16+BJ16 -> 2 | CP16: =MAX(CH16,BN16,BJ16) -> 1 | CQ16: =IF($AV16="Yes",1,0) -> 0 | CR16: =IF($AV16="No",1,0) -> 1 | CS16: =IF($AV16="Not Specified",1,0) -> 0 | CT16: =IF(OR(AND(U16>=2026,U16<=2030),AND(X16>=2026,X16<=2030)),1,"") -> 1 | CU16: =AA16&" "&AS16 -> 2030 | CV16: =MAX(AA16,AS16) -> 2030 | CW16: 0 | CX16: 0 | CY16: 0 | CZ16: 0 | DA16: 0 | DB16: 1 | DC16: 0 | DD16: 1 | DE16: 0 | DF16: 1 | DG16: 0 | DH16: 1 | DI16: 0 | DJ16: 0 | DK16: 0 | DL16: 0 | DM16: 1 | DN16: 0 | DO16: 1 | DP16: 1 | DQ16: 0 | DR16: 1 | DS16: 0 | DT16: N | DU16: No | DV16: V | DW16: N | DX16: 0 | DY16: Y | DZ16: =Q16 -> Y | EA16: =Z16 | EB16: =AP16 -> Y | EC16: =AJ16 -> N | ED16: =AV16 -> No | EF16: =MAX(AS16,AA16) -> 2030
A17: 14 | B17: 12 | C17: Exxon Mobil | D17: Petroleum Refining | E17: Oil and gas | F17: U.S. | G17: North America | H17: $349,585 | I17: $33,680 | J17: -0.065 | K17: $453,475 | L17: 60900 | M17: 31 | N17: N | Q17: N | R17: N | AC17: Net zero | AD17: Net Zero | AE17: Yes | AF17: Yes | AG17: No | AH17: 1,2 | AJ17: N | AO17: C | AP17: Y | AQ17: 1,2 | AR17: "In January 2022, we announced a 2050 net-zero GHG ambition for our operated assets, which requires new advancements in technology and practical government policies." (covers Scopes 1 and 2) p7 | AS17: 2050 | AV17: Yes | AW17: Yes (CCS-based removals e.g. BECCS, DACCS) | AX17: No | AY17: N | BG17: =IF(AND($N17="Y",$P17<=2025),1,0) -> 0 | BH17: =IF(AND($N17="Y",AND($P17>2025,$P17<=2030)),1,0) -> 0 | BI17: =IF(AND($N17="Y",$P17>2030),1,0) -> 0 | BJ17: =MAX(BG17:BI17) -> 0 | BK17: =IF(AND($R17="Y",$U17<=2025),1,0) -> 0 | BL17: =IF(AND($R17="Y",AND($U17>2025,$U17<=2030)),1,0) -> 0 | BM17: =IF(AND($R17="Y",$U17>2030),1,0) -> 0 | BN17: =MAX(BK17:BM17) -> 0 | BO17: =IF(AND($Y17="Y",$AA17<=2025),1,0) -> 0 | BP17: =IF(AND($Y17="Y",AND($AA17>2025,$AA17<=2030)),1,0) -> 0 | BQ17: =IF(AND($Y17="Y",$AA17>2030),1,0) -> 0 | BR17: =IF(AND($AP17="Y",$AS17<=2025),1,0) -> 0 | BS17: =IF(AND($AP17="Y",AND($AS17>2025,$AS17<=2030)),1,0) -> 0 | BT17: =IF(AND($AP17="Y",$AS17>2030),1,0) -> 1 | BU17: =IF(AND(AL17<=2025,CF17=0,AJ17="Y"),1,0) -> 0 | BV17: =IF(AND(AL17>=2026,AL17<=2030,AJ17="Y",CF17=0),1,0) -> 0 | BW17: =IF(AND(AL17>=2031,CF17=0,AJ17="Y"),1,0) -> 0 | BX17: =IF(AND($AJ17="Y",$AL17<=2024),1,0) -> 0 | BY17: =IF(AND($AJ17="Y",AND($AL17>2024,$AL17<=2030)),1,0) -> 0 | BZ17: =IF(AND($AJ17="Y",$AL17>2030),1,0) -> 0 | CA17: =MAX(BX17:BZ17) -> 0 | CB17: =IF(AND(CF17=0,AJ17="Y"),1,0) -> 0 | CC17: =MAX($BO17,$BR17) -> 0 | CD17: =MAX($BP17,$BS17) -> 0 | CE17: =MAX($BQ17,$BT17) -> 1 | CF17: =MAX(CC17:CE17) -> 1 | CG17: =MAX($CF17,$CA17) -> 1 | CH17: =MAX(CF17,CB17) -> 1 | CI17: =IF(AND($AY17="Y",$BA17<=2024),1,0) -> 0 | CJ17: =IF(AND($AY17="Y",AND($BA17>2024,$BA17<=2030)),1,0) -> 0 | CK17: =IF(AND($AY17="Y",$BA17>2030),1,0) -> 0 | CL17: =SUM(CC17,BU17,BK17,BG17) -> 0 | CM17: =SUM(CD17,BV17,BL17,BH17) -> 0 | CN17: =SUM(CE17,BW17,BM17,BI17) -> 1 | CO17: =CF17+CB17+BN17+BJ17 -> 1 | CP17: =MAX(CH17,BN17,BJ17) -> 1 | CQ17: =IF($AV17="Yes",1,0) -> 1 | CR17: =IF($AV17="No",1,0) -> 0 | CS17: =IF($AV17="Not Specified",1,0) -> 0 | CT17: =IF(OR(AND(U17>=2026,U17<=2030),AND(X17>=2026,X17<=2030)),1,"") | CU17: =AA17&" "&AS17 -> 2050 | CV17: =MAX(AA17,AS17) -> 2050 | CW17: 0 | CX17: 0 | CY17: 0 | CZ17: 0 | DA17: 0 | DB17: 0 | DC17: 1 | DD17: 1 | DE17: 0 | DF17: 0 | DG17: 0 | DH17: 0 | DI17: 0 | DJ17: 0 | DK17: 0 | DL17: 0 | DM17: 1 | DN17: 0 | DO17: 1 | DP17: 1 | DQ17: 0 | DR17: 1 | DS17: 0 | DT17: N | DU17: 0 | DV17: C | DW17: N | DX17: 0 | DY17: Y | DZ17: =Q17 -> N | EA17: =Z17 | EB17: =AP17 -> Y | EC17: =AJ17 -> N | ED17: =AV17 -> Yes | EF17: =MAX(AS17,AA17) -> 2050
A18: 15 | B18: 15 | C18: Toyota Motor | D18: Motor Vehicles | E18: Automotive | F18: Japan | G18: Asia | H18: $315,110.2 | I18: $31,257.9 | J18: -0.086 | K18: $624,466.9 | L18: 383853 | M18: 31 | N18: N | Q18: Y | R18: Y | S18: Targets set | T18: 1.5°C / Well-below 2°C | U18: 2035 | AC18: Carbon neutral(ity) | AD18: Carbon Neutral | AE18: Yes | AF18: Yes | AG18: Yes | AH18: 1,2,3 | AI18: C,V | AJ18: Y | AK18: 2050: Achieve CN for GHG emissions throughout the life cycle, for average GHG emissions for new vehicles, for GHG emissions from corporate activities (pg 21 & 54) ** Applies to GHG emissions from the business activities of Toyota Motor Corporation and consolidated subsidiaries due to energy consumption and GHG emissions from business partners and customers in relation to vehicles under Toyota Motor Corporation and consolidated subsidiary brands. (Per vehicle, Scope1, 2, and 3) (Target for 2050 includes Toyota Motor Corporation and some consolidated subsidiaries.) | AL18: 2050 | AP18: N | AV18: Not Specified | AW18: Yes (CCS-based removals e.g. BECCS, DACCS) | AX18: No | AY18: N | BG18: =IF(AND($N18="Y",$P18<=2025),1,0) -> 0 | BH18: =IF(AND($N18="Y",AND($P18>2025,$P18<=2030)),1,0) -> 0 | BI18: =IF(AND($N18="Y",$P18>2030),1,0) -> 0 | BJ18: =MAX(BG18:BI18) -> 0 | BK18: =IF(AND($R18="Y",$U18<=2025),1,0) -> 0 | BL18: =IF(AND($R18="Y",AND($U18>2025,$U18<=2030)),1,0) -> 0 | BM18: =IF(AND($R18="Y",$U18>2030),1,0) -> 1 | BN18: =MAX(BK18:BM18) -> 1 | BO18: =IF(AND($Y18="Y",$AA18<=2025),1,0) -> 0 | BP18: =IF(AND($Y18="Y",AND($AA18>2025,$AA18<=2030)),1,0) -> 0 | BQ18: =IF(AND($Y18="Y",$AA18>2030),1,0) -> 0 | BR18: =IF(AND($AP18="Y",$AS18<=2025),1,0) -> 0 | BS18: =IF(AND($AP18="Y",AND($AS18>2025,$AS18<=2030)),1,0) -> 0 | BT18: =IF(AND($AP18="Y",$AS18>2030),1,0) -> 0 | BU18: =IF(AND(AL18<=2025,CF18=0,AJ18="Y"),1,0) -> 0 | BV18: =IF(AND(AL18>=2026,AL18<=2030,AJ18="Y",CF18=0),1,0) -> 0 | BW18: =IF(AND(AL18>=2031,CF18=0,AJ18="Y"),1,0) -> 1 | BX18: =IF(AND($AJ18="Y",$AL18<=2024),1,0) -> 0 | BY18: =IF(AND($AJ18="Y",AND($AL18>2024,$AL18<=2030)),1,0) -> 0 | BZ18: =IF(AND($AJ18="Y",$AL18>2030),1,0) -> 1 | CA18: =MAX(BX18:BZ18) -> 1 | CB18: =IF(AND(CF18=0,AJ18="Y"),1,0) -> 1 | CC18: =MAX($BO18,$BR18) -> 0 | CD18: =MAX($BP18,$BS18) -> 0 | CE18: =MAX($BQ18,$BT18) -> 0 | CF18: =MAX(CC18:CE18) -> 0 | CG18: =MAX($CF18,$CA18) -> 1 | CH18: =MAX(CF18,CB18) -> 1 | CI18: =IF(AND($AY18="Y",$BA18<=2024),1,0) -> 0 | CJ18: =IF(AND($AY18="Y",AND($BA18>2024,$BA18<=2030)),1,0) -> 0 | CK18: =IF(AND($AY18="Y",$BA18>2030),1,0) -> 0 | CL18: =SUM(CC18,BU18,BK18,BG18) -> 0 | CM18: =SUM(CD18,BV18,BL18,BH18) -> 0 | CN18: =SUM(CE18,BW18,BM18,BI18) -> 2 | CO18: =CF18+CB18+BN18+BJ18 -> 2 | CP18: =MAX(CH18,BN18,BJ18) -> 1 | CQ18: =IF($AV18="Yes",1,0) -> 0 | CR18: =IF($AV18="No",1,0) -> 0 | CS18: =IF($AV18="Not Specified",1,0) -> 1 | CT18: =IF(OR(AND(U18>=2026,U18<=2030),AND(X18>=2026,X18<=2030)),1,"") | CU18: =AA18&" "&AS18 | CV18: =MAX(AA18,AS18) -> 0 | CW18: 0 | CX18: 0 | CY18: 1 | CZ18: 1 | DA18: 0 | DB18: 0 | DC18: 0 | DD18: 0 | DE18: 0 | DF18: 1 | DG18: 0 | DH18: 1 | DI18: 0 | DJ18: 0 | DK18: 0 | DL18: 0 | DM18: 1 | DN18: 0 | DO18: 1 | DP18: 1 | DQ18: 0 | DR18: 1 | DS18: 0 | DT18: Y | DU18: No | DV18: N | DW18: V | DX18: Y | DY18: 0 | DZ18: =Q18 -> Y | EA18: =Z18 | EB18: =AP18 -> N | EC18: =AJ18 -> Y | ED18: =AV18 -> Not Specified | EF18: =MAX(AS18,AA18) -> 0
A19: 16 | B19: 14 | C19: China State Construction Engineering | D19: Engineering & Construction | E19: Engineering and construction | F19: China | G19: Asia | H19: $304,121.3 | I19: $3,667.4 | J19: -0.161 | K19: $438,013.2 | L19: 361249 | M19: 14 | N19: N | Q19: N | R19: N | AC19: Carbon neutral(ity) | AD19: Carbon Neutral | AE19: Yes | AF19: Yes | AG19: Not Specified | AH19: 1,2 | AI19: C | AJ19: Y | AK19: CSCEC will possess global core competitiveness in green, low carbon development, with world class capabilities in low-carbon industries, products, construction, and operations. We will secure a leading position in both domestic and global operations. The Company will realize the green transformation of production methods and play a pivotal role in the construction industry‚Äôs path to carbon neutrality, contributing significantly to China‚Äôs goal of carbon neutrality | AL19: 2060 | AP19: N | AV19: Not Specified | AW19: Not Specified | AX19: No | AY19: N | BG19: =IF(AND($N19="Y",$P19<=2025),1,0) -> 0 | BH19: =IF(AND($N19="Y",AND($P19>2025,$P19<=2030)),1,0) -> 0 | BI19: =IF(AND($N19="Y",$P19>2030),1,0) -> 0 | BJ19: =MAX(BG19:BI19) -> 0 | BK19: =IF(AND($R19="Y",$U19<=2025),1,0) -> 0 | BL19: =IF(AND($R19="Y",AND($U19>2025,$U19<=2030)),1,0) -> 0 | BM19: =IF(AND($R19="Y",$U19>2030),1,0) -> 0 | BN19: =MAX(BK19:BM19) -> 0 | BO19: =IF(AND($Y19="Y",$AA19<=2025),1,0) -> 0 | BP19: =IF(AND($Y19="Y",AND($AA19>2025,$AA19<=2030)),1,0) -> 0 | BQ19: =IF(AND($Y19="Y",$AA19>2030),1,0) -> 0 | BR19: =IF(AND($AP19="Y",$AS19<=2025),1,0) -> 0 | BS19: =IF(AND($AP19="Y",AND($AS19>2025,$AS19<=2030)),1,0) -> 0 | BT19: =IF(AND($AP19="Y",$AS19>2030),1,0) -> 0 | BU19: =IF(AND(AL19<=2025,CF19=0,AJ19="Y"),1,0) -> 0 | BV19: =IF(AND(AL19>=2026,AL19<=2030,AJ19="Y",CF19=0),1,0) -> 0 | BW19: =IF(AND(AL19>=2031,CF19=0,AJ19="Y"),1,0) -> 1 | BX19: =IF(AND($AJ19="Y",$AL19<=2024),1,0) -> 0 | BY19: =IF(AND($AJ19="Y",AND($AL19>2024,$AL19<=2030)),1,0) -> 0 | BZ19: =IF(AND($AJ19="Y",$AL19>2030),1,0) -> 1 | CA19: =MAX(BX19:BZ19) -> 1 | CB19: =IF(AND(CF19=0,AJ19="Y"),1,0) -> 1 | CC19: =MAX($BO19,$BR19) -> 0 | CD19: =MAX($BP19,$BS19) -> 0 | CE19: =MAX($BQ19,$BT19) -> 0 | CF19: =MAX(CC19:CE19) -> 0 | CG19: =MAX($CF19,$CA19) -> 1 | CH19: =MAX(CF19,CB19) -> 1 | CI19: =IF(AND($AY19="Y",$BA19<=2024),1,0) -> 0 | CJ19: =IF(AND($AY19="Y",AND($BA19>2024,$BA19<=2030)),1,0) -> 0 | CK19: =IF(AND($AY19="Y",$BA19>2030),1,0) -> 0 | CL19: =SUM(CC19,BU19,BK19,BG19) -> 0 | CM19: =SUM(CD19,BV19,BL19,BH19) -> 0 | CN19: =SUM(CE19,BW19,BM19,BI19) -> 1 | CO19: =CF19+CB19+BN19+BJ19 -> 1 | CP19: =MAX(CH19,BN19,BJ19) -> 1 | CQ19: =IF($AV19="Yes",1,0) -> 0 | CR19: =IF($AV19="No",1,0) -> 0 | CS19: =IF($AV19="Not Specified",1,0) -> 1 | CT19: =IF(OR(AND(U19>=2026,U19<=2030),AND(X19>=2026,X19<=2030)),1,"") | CU19: =AA19&" "&AS19 | CV19: =MAX(AA19,AS19) -> 0 | CW19: 0 | CX19: 0 | CY19: 1 | CZ19: 1 | DA19: 0 | DB19: 0 | DC19: 0 | DD19: 0 | DE19: 0 | DF19: 0 | DG19: 0 | DH19: 0 | DI19: 0 | DJ19: 0 | DK19: 0 | DL19: 0 | DM19: 1 | DN19: 0 | DO19: 1 | DP19: 0 | DQ19: 0 | DR19: 1 | DS19: 0 | DT19: N | DU19: 0 | DV19: N | DW19: C | DX19: U | DY19: 0 | DZ19: =Q19 -> N | EA19: =Z19 | EB19: =AP19 -> N | EC19: =AJ19 -> Y | ED19: =AV19 -> Not Specified | EF19: =MAX(AS19,AA19) -> 0
A20: 17 | B20: 18 | C20: Cencora | D20: Wholesalers: Health Care | E20: Health care and pharmaceuticals | F20: U.S. | G20: North America | H20: $293,958.6 | I20: $1,509.1 | J20: -0.135 | K20: $67,101.7 | L20: 44000 | M20: 26 | N20: N | Q20: Y | R20: Y | S20: Targets set | T20: 1.5°C | U20: 2032 | AC20: Emissions reduction target | AD20: Other Emission Reduction | AE20: Yes | AF20: Yes | AG20: Yes | AH20: 1,2,3 | AJ20: N | AP20: N | AV20: Not Specified | AW20: Not Specified | AX20: No | AY20: Y | AZ20: "Cencora has a fully verified science-based target to reduce absolute Scope 1 and 2 greenhouse gas emissions 54.6% by FY2032 from a FY2019 base year. Cencora also commits that 82% of its suppliers by spend, covering purchased goods and services, will have science-based targets by FY2027" (Page 7, Cencora FY23 ESG Reporting Index). | BA20: 2032 | BG20: =IF(AND($N20="Y",$P20<=2025),1,0) -> 0 | BH20: =IF(AND($N20="Y",AND($P20>2025,$P20<=2030)),1,0) -> 0 | BI20: =IF(AND($N20="Y",$P20>2030),1,0) -> 0 | BJ20: =MAX(BG20:BI20) -> 0 | BK20: =IF(AND($R20="Y",$U20<=2025),1,0) -> 0 | BL20: =IF(AND($R20="Y",AND($U20>2025,$U20<=2030)),1,0) -> 0 | BM20: =IF(AND($R20="Y",$U20>2030),1,0) -> 1 | BN20: =MAX(BK20:BM20) -> 1 | BO20: =IF(AND($Y20="Y",$AA20<=2025),1,0) -> 0 | BP20: =IF(AND($Y20="Y",AND($AA20>2025,$AA20<=2030)),1,0) -> 0 | BQ20: =IF(AND($Y20="Y",$AA20>2030),1,0) -> 0 | BR20: =IF(AND($AP20="Y",$AS20<=2025),1,0) -> 0 | BS20: =IF(AND($AP20="Y",AND($AS20>2025,$AS20<=2030)),1,0) -> 0 | BT20: =IF(AND($AP20="Y",$AS20>2030),1,0) -> 0 | BU20: =IF(AND(AL20<=2025,CF20=0,AJ20="Y"),1,0) -> 0 | BV20: =IF(AND(AL20>=2026,AL20<=2030,AJ20="Y",CF20=0),1,0) -> 0 | BW20: =IF(AND(AL20>=2031,CF20=0,AJ20="Y"),1,0) -> 0 | BX20: =IF(AND($AJ20="Y",$AL20<=2024),1,0) -> 0 | BY20: =IF(AND($AJ20="Y",AND($AL20>2024,$AL20<=2030)),1,0) -> 0 | BZ20: =IF(AND($AJ20="Y",$AL20>2030),1,0) -> 0 | CA20: =MAX(BX20:BZ20) -> 0 | CB20: =IF(AND(CF20=0,AJ20="Y"),1,0) -> 0 | CC20: =MAX($BO20,$BR20) -> 0 | CD20: =MAX($BP20,$BS20) -> 0 | CE20: =MAX($BQ20,$BT20) -> 0 | CF20: =MAX(CC20:CE20) -> 0 | CG20: =MAX($CF20,$CA20) -> 0 | CH20: =MAX(CF20,CB20) -> 0 | CI20: =IF(AND($AY20="Y",$BA20<=2024),1,0) -> 0 | CJ20: =IF(AND($AY20="Y",AND($BA20>2024,$BA20<=2030)),1,0) -> 0 | CK20: =IF(AND($AY20="Y",$BA20>2030),1,0) -> 1 | CL20: =SUM(CC20,BU20,BK20,BG20) -> 0 | CM20: =SUM(CD20,BV20,BL20,BH20) -> 0 | CN20: =SUM(CE20,BW20,BM20,BI20) -> 1 | CO20: =CF20+CB20+BN20+BJ20 -> 1 | CP20: =MAX(CH20,BN20,BJ20) -> 1 | CQ20: =IF($AV20="Yes",1,0) -> 0 | CR20: =IF($AV20="No",1,0) -> 0 | CS20: =IF($AV20="Not Specified",1,0) -> 1 | CT20: =IF(OR(AND(U20>=2026,U20<=2030),AND(X20>=2026,X20<=2030)),1,"") | CU20: =AA20&" "&AS20 | CV20: =MAX(AA20,AS20) -> 0 | CW20: 0 | CX20: 0 | CY20: 0 | CZ20: 0 | DA20: 0 | DB20: 0 | DC20: 0 | DD20: 0 | DE20: 0 | DF20: 1 | DG20: 0 | DH20: 1 | DI20: 0 | DJ20: 0 | DK20: 0 | DL20: 0 | DM20: 0 | DN20: 0 | DO20: 0 | DP20: 0 | DQ20: 0 | DR20: 1 | DS20: 0 | DT20: Y | DU20: No | DV20: N | DW20: N | DX20: 0 | DY20: 0 | DZ20: =Q20 -> Y | EA20: =Z20 | EB20: =AP20 -> N | EC20: =AJ20 -> N | ED20: =AV20 -> Not Specified | EF20: =MAX(AS20,AA20) -> 0
A21: 18 | B21: 13 | C21: Shell | D21: Petroleum Refining | E21: Oil and gas | F21: Britain | G21: Europe | H21: $289,029 | I21: $16,094 | J21: -0.169 | K21: $387,609 | L21: 96000 | M21: 31 | N21: N | Q21: N | R21: N | AC21: Net zero | AD21: Net Zero | AE21: Yes | AF21: Yes | AG21: Yes | AH21: 1,2,3 | AJ21: N | AO21: C,V | AP21: Y | AQ21: 1,2,3 | AR21: "Net-zero emissions by 2025 (Scope 1, 2 and 3)" p93 2024 report Scope 3: "Reduce the net carbon intensity (NCI) of the energy products we sell by 100% by 2050 (2016 baseline)" (Annual Report 2024, p. 15; Energy Transition Strategy 2024, pp. 9 & 10) | AS21: 2050 | AV21: Yes | AW21: Yes (nature-based and CCS-based removals) | AX21: No | AY21: N | BG21: =IF(AND($N21="Y",$P21<=2025),1,0) -> 0 | BH21: =IF(AND($N21="Y",AND($P21>2025,$P21<=2030)),1,0) -> 0 | BI21: =IF(AND($N21="Y",$P21>2030),1,0) -> 0 | BJ21: =MAX(BG21:BI21) -> 0 | BK21: =IF(AND($R21="Y",$U21<=2025),1,0) -> 0 | BL21: =IF(AND($R21="Y",AND($U21>2025,$U21<=2030)),1,0) -> 0 | BM21: =IF(AND($R21="Y",$U21>2030),1,0) -> 0 | BN21: =MAX(BK21:BM21) -> 0 | BO21: =IF(AND($Y21="Y",$AA21<=2025),1,0) -> 0 | BP21: =IF(AND($Y21="Y",AND($AA21>2025,$AA21<=2030)),1,0) -> 0 | BQ21: =IF(AND($Y21="Y",$AA21>2030),1,0) -> 0 | BR21: =IF(AND($AP21="Y",$AS21<=2025),1,0) -> 0 | BS21: =IF(AND($AP21="Y",AND($AS21>2025,$AS21<=2030)),1,0) -> 0 | BT21: =IF(AND($AP21="Y",$AS21>2030),1,0) -> 1 | BU21: =IF(AND(AL21<=2025,CF21=0,AJ21="Y"),1,0) -> 0 | BV21: =IF(AND(AL21>=2026,AL21<=2030,AJ21="Y",CF21=0),1,0) -> 0 | BW21: =IF(AND(AL21>=2031,CF21=0,AJ21="Y"),1,0) -> 0 | BX21: =IF(AND($AJ21="Y",$AL21<=2024),1,0) -> 0 | BY21: =IF(AND($AJ21="Y",AND($AL21>2024,$AL21<=2030)),1,0) -> 0 | BZ21: =IF(AND($AJ21="Y",$AL21>2030),1,0) -> 0 | CA21: =MAX(BX21:BZ21) -> 0 | CB21: =IF(AND(CF21=0,AJ21="Y"),1,0) -> 0 | CC21: =MAX($BO21,$BR21) -> 0 | CD21: =MAX($BP21,$BS21) -> 0 | CE21: =MAX($BQ21,$BT21) -> 1 | CF21: =MAX(CC21:CE21) -> 1 | CG21: =MAX($CF21,$CA21) -> 1 | CH21: =MAX(CF21,CB21) -> 1 | CI21: =IF(AND($AY21="Y",$BA21<=2024),1,0) -> 0 | CJ21: =IF(AND($AY21="Y",AND($BA21>2024,$BA21<=2030)),1,0) -> 0 | CK21: =IF(AND($AY21="Y",$BA21>2030),1,0) -> 0 | CL21: =SUM(CC21,BU21,BK21,BG21) -> 0 | CM21: =SUM(CD21,BV21,BL21,BH21) -> 0 | CN21: =SUM(CE21,BW21,BM21,BI21) -> 1 | CO21: =CF21+CB21+BN21+BJ21 -> 1 | CP21: =MAX(CH21,BN21,BJ21) -> 1 | CQ21: =IF($AV21="Yes",1,0) -> 1 | CR21: =IF($AV21="No",1,0) -> 0 | CS21: =IF($AV21="Not Specified",1,0) -> 0 | CT21: =IF(OR(AND(U21>=2026,U21<=2030),AND(X21>=2026,X21<=2030)),1,"") | CU21: =AA21&" "&AS21 -> 2050 | CV21: =MAX(AA21,AS21) -> 2050 | CW21: 0 | CX21: 0 | CY21: 0 | CZ21: 0 | DA21: 0 | DB21: 0 | DC21: 1 | DD21: 1 | DE21: 0 | DF21: 0 | DG21: 0 | DH21: 0 | DI21: 0 | DJ21: 0 | DK21: 0 | DL21: 0 | DM21: 1 | DN21: 0 | DO21: 1 | DP21: 1 | DQ21: 0 | DR21: 1 | DS21: 0 | DT21: N | DU21: 0 | DV21: V | DW21: N | DX21: 0 | DY21: Y | DZ21: =Q21 -> N | EA21: =Z21 | EB21: =AP21 -> Y | EC21: =AJ21 -> N | ED21: =AV21 -> Yes | EF21: =MAX(AS21,AA21) -> 2050
A22: 19 | B22: 21 | C22: JPMorgan Chase | D22: Megabanks | E22: Financial services | F22: U.S. | G22: North America | H22: $278,906 | I22: $58,471 | J22: 0.18 | K22: $4,002,814 | L22: 317233 | M22: 31 | N22: N | Q22: N | R22: N | AC22: Net zero | AD22: Net Zero | AE22: Yes | AF22: Yes | AG22: Partial | AH22: 1,2 | AJ22: N | AO22: C | AP22: Y | AQ22: 1,2 | AR22: The goal of accelerating the low-carbon transition and encouraging near-term actions that set a path for global net-zero emissions by 2050. We are aligning key sectors of our financing portfolio with net-zero emissions by 2050. | AS22: 2050 | AV22: Yes | AW22: Yes (nature-based and CCS-based removals) | AX22: Yes | AY22: N | BG22: =IF(AND($N22="Y",$P22<=2025),1,0) -> 0 | BH22: =IF(AND($N22="Y",AND($P22>2025,$P22<=2030)),1,0) -> 0 | BI22: =IF(AND($N22="Y",$P22>2030),1,0) -> 0 | BJ22: =MAX(BG22:BI22) -> 0 | BK22: =IF(AND($R22="Y",$U22<=2025),1,0) -> 0 | BL22: =IF(AND($R22="Y",AND($U22>2025,$U22<=2030)),1,0) -> 0 | BM22: =IF(AND($R22="Y",$U22>2030),1,0) -> 0 | BN22: =MAX(BK22:BM22) -> 0 | BO22: =IF(AND($Y22="Y",$AA22<=2025),1,0) -> 0 | BP22: =IF(AND($Y22="Y",AND($AA22>2025,$AA22<=2030)),1,0) -> 0 | BQ22: =IF(AND($Y22="Y",$AA22>2030),1,0) -> 0 | BR22: =IF(AND($AP22="Y",$AS22<=2025),1,0) -> 0 | BS22: =IF(AND($AP22="Y",AND($AS22>2025,$AS22<=2030)),1,0) -> 0 | BT22: =IF(AND($AP22="Y",$AS22>2030),1,0) -> 1 | BU22: =IF(AND(AL22<=2025,CF22=0,AJ22="Y"),1,0) -> 0 | BV22: =IF(AND(AL22>=2026,AL22<=2030,AJ22="Y",CF22=0),1,0) -> 0 | BW22: =IF(AND(AL22>=2031,CF22=0,AJ22="Y"),1,0) -> 0 | BX22: =IF(AND($AJ22="Y",$AL22<=2024),1,0) -> 0 | BY22: =IF(AND($AJ22="Y",AND($AL22>2024,$AL22<=2030)),1,0) -> 0 | BZ22: =IF(AND($AJ22="Y",$AL22>2030),1,0) -> 0 | CA22: =MAX(BX22:BZ22) -> 0 | CB22: =IF(AND(CF22=0,AJ22="Y"),1,0) -> 0 | CC22: =MAX($BO22,$BR22) -> 0 | CD22: =MAX($BP22,$BS22) -> 0 | CE22: =MAX($BQ22,$BT22) -> 1 | CF22: =MAX(CC22:CE22) -> 1 | CG22: =MAX($CF22,$CA22) -> 1 | CH22: =MAX(CF22,CB22) -> 1 | CI22: =IF(AND($AY22="Y",$BA22<=2024),1,0) -> 0 | CJ22: =IF(AND($AY22="Y",AND($BA22>2024,$BA22<=2030)),1,0) -> 0 | CK22: =IF(AND($AY22="Y",$BA22>2030),1,0) -> 0 | CL22: =SUM(CC22,BU22,BK22,BG22) -> 0 | CM22: =SUM(CD22,BV22,BL22,BH22) -> 0 | CN22: =SUM(CE22,BW22,BM22,BI22) -> 1 | CO22: =CF22+CB22+BN22+BJ22 -> 1 | CP22: =MAX(CH22,BN22,BJ22) -> 1 | CQ22: =IF($AV22="Yes",1,0) -> 1 | CR22: =IF($AV22="No",1,0) -> 0 | CS22: =IF($AV22="Not Specified",1,0) -> 0 | CT22: =IF(OR(AND(U22>=2026,U22<=2030),AND(X22>=2026,X22<=2030)),1,"") | CU22: =AA22&" "&AS22 -> 2050 | CV22: =MAX(AA22,AS22) -> 2050 | CW22: 1 | CX22: 0 | CY22: 0 | CZ22: 1 | DA22: 0 | DB22: 0 | DC22: 1 | DD22: 1 | DE22: 0 | DF22: 0 | DG22: 0 | DH22: 0 | DI22: 0 | DJ22: 0 | DK22: 0 | DL22: 0 | DM22: 1 | DN22: 1 | DO22: 1 | DP22: 1 | DQ22: 0 | DR22: 1 | DS22: 1 | DT22: N | DU22: 0 | DV22: C | DW22: C | DX22: Y | DY22: Y | DZ22: =Q22 -> N | EA22: =Z22 | EB22: =AP22 -> Y | EC22: =AJ22 -> N | ED22: =AV22 -> Yes | EF22: =MAX(AS22,AA22) -> 2050
A23: 20 | B23: 20 | C23: Costco Wholesale | D23: General Merchandisers | E23: Retail | F23: U.S. | G23: North America | H23: $254,453 | I23: $7,367 | J23: 0.171 | K23: $69,831 | M23: 31 | N23: N | Q23: N | R23: N | AC23: Emissions reduction target | AD23: Other Emission Reduction | AE23: Yes | AF23: Yes | AG23: Partial | AH23: 1,2 | AJ23: N | AP23: N | AV23: Not Specified | AW23: Not Specified | AX23: No | AY23: Y | AZ23: We have committed to an ambitious Scope 1 and Scope 2 emission reduction target: 39% absolute reduction by 2030 compared to our 2020 base year. | BA23: 2030 | BG23: =IF(AND($N23="Y",$P23<=2025),1,0) -> 0 | BH23: =IF(AND($N23="Y",AND($P23>2025,$P23<=2030)),1,0) -> 0 | BI23: =IF(AND($N23="Y",$P23>2030),1,0) -> 0 | BJ23: =MAX(BG23:BI23) -> 0 | BK23: =IF(AND($R23="Y",$U23<=2025),1,0) -> 0 | BL23: =IF(AND($R23="Y",AND($U23>2025,$U23<=2030)),1,0) -> 0 | BM23: =IF(AND($R23="Y",$U23>2030),1,0) -> 0 | BN23: =MAX(BK23:BM23) -> 0 | BO23: =IF(AND($Y23="Y",$AA23<=2025),1,0) -> 0 | BP23: =IF(AND($Y23="Y",AND($AA23>2025,$AA23<=2030)),1,0) -> 0 | BQ23: =IF(AND($Y23="Y",$AA23>2030),1,0) -> 0 | BR23: =IF(AND($AP23="Y",$AS23<=2025),1,0) -> 0 | BS23: =IF(AND($AP23="Y",AND($AS23>2025,$AS23<=2030)),1,0) -> 0 | BT23: =IF(AND($AP23="Y",$AS23>2030),1,0) -> 0 | BU23: =IF(AND(AL23<=2025,CF23=0,AJ23="Y"),1,0) -> 0 | BV23: =IF(AND(AL23>=2026,AL23<=2030,AJ23="Y",CF23=0),1,0) -> 0 | BW23: =IF(AND(AL23>=2031,CF23=0,AJ23="Y"),1,0) -> 0 | BX23: =IF(AND($AJ23="Y",$AL23<=2024),1,0) -> 0 | BY23: =IF(AND($AJ23="Y",AND($AL23>2024,$AL23<=2030)),1,0) -> 0 | BZ23: =IF(AND($AJ23="Y",$AL23>2030),1,0) -> 0 | CA23: =MAX(BX23:BZ23) -> 0 | CB23: =IF(AND(CF23=0,AJ23="Y"),1,0) -> 0 | CC23: =MAX($BO23,$BR23) -> 0 | CD23: =MAX($BP23,$BS23) -> 0 | CE23: =MAX($BQ23,$BT23) -> 0 | CF23: =MAX(CC23:CE23) -> 0 | CG23: =MAX($CF23,$CA23) -> 0 | CH23: =MAX(CF23,CB23) -> 0 | CI23: =IF(AND($AY23="Y",$BA23<=2024),1,0) -> 0 | CJ23: =IF(AND($AY23="Y",AND($BA23>2024,$BA23<=2030)),1,0) -> 1 | CK23: =IF(AND($AY23="Y",$BA23>2030),1,0) -> 0 | CL23: =SUM(CC23,BU23,BK23,BG23) -> 0 | CM23: =SUM(CD23,BV23,BL23,BH23) -> 0 | CN23: =SUM(CE23,BW23,BM23,BI23) -> 0 | CO23: =CF23+CB23+BN23+BJ23 -> 0 | CP23: =MAX(CH23,BN23,BJ23) -> 0 | CQ23: =IF($AV23="Yes",1,0) -> 0 | CR23: =IF($AV23="No",1,0) -> 0 | CS23: =IF($AV23="Not Specified",1,0) -> 1 | CT23: =IF(OR(AND(U23>=2026,U23<=2030),AND(X23>=2026,X23<=2030)),1,"") | CU23: =AA23&" "&AS23 | CV23: =MAX(AA23,AS23) -> 0 | CW23: 0 | CX23: 0 | CY23: 0 | CZ23: 0 | DA23: 0 | DB23: 0 | DC23: 0 | DD23: 0 | DE23: 0 | DF23: 0 | DG23: 0 | DH23: 0 | DI23: 0 | DJ23: 0 | DK23: 0 | DL23: 0 | DM23: 0 | DN23: 0 | DO23: 0 | DP23: 0 | DQ23: 0 | DR23: 0 | DS23: 0 | DT23: N | DU23: 0 | DV23: N | DW23: N | DX23: 0 | DY23: 0 | DZ23: =Q23 -> N | EA23: =Z23 | EB23: =AP23 -> N | EC23: =AJ23 -> N | ED23: =AV23 -> Not Specified | EF23: =MAX(AS23,AA23) -> 0
A24: 21 | B24: 33 | C24: Cigna | D24: Health Care: Pharmacy and Other Services | E24: Health care and pharmaceuticals | F24: U.S. | G24: North America | H24: $247,121 | I24: $3,434 | J24: -0.335 | K24: $155,881 | L24: 72398 | M24: 30 | N24: Y | O24: 2022 | P24: 2030 | Q24: Y | R24: N | S24: Committed | U24: 2030 | AC24: Carbon neutral(ity) | AD24: Carbon Neutral | AE24: Yes | AF24: Yes | AG24: Yes | AH24: 1,2,3 | AI24: C,V | AJ24: Y | AK24: We are committed to maintaining carbon-neutral operations after we achieve our initial goal set for 2040. Our commitment includes Scope 1 (direct) GHG emissions from building operations and company-owned aircraft and vehicles, as well as Scope 2 (indirect) GHG emissions from purchased electricity. For the purposes of communicating progress towards our 2040 carbon neutrality goal, we calculate our total operational emissions by summing Scope 1 and Scope 2 (market-based) emissions. This market-based subtotal has been reduced by procuring EACs and market-based emission factors. As we get closer to 2040, we plan to evaluate the use of high-quality carbon offsets103 to achieve our goal. | AL24: 2040 | AP24: N | AV24: Not Specified | AW24: Not Specified | AX24: Yes | AY24: N | BG24: =IF(AND($N24="Y",$P24<=2025),1,0) -> 0 | BH24: =IF(AND($N24="Y",AND($P24>2025,$P24<=2030)),1,0) -> 1 | BI24: =IF(AND($N24="Y",$P24>2030),1,0) -> 0 | BJ24: =MAX(BG24:BI24) -> 1 | BK24: =IF(AND($R24="Y",$U24<=2025),1,0) -> 0 | BL24: =IF(AND($R24="Y",AND($U24>2025,$U24<=2030)),1,0) -> 0 | BM24: =IF(AND($R24="Y",$U24>2030),1,0) -> 0 | BN24: =MAX(BK24:BM24) -> 0 | BO24: =IF(AND($Y24="Y",$AA24<=2025),1,0) -> 0 | BP24: =IF(AND($Y24="Y",AND($AA24>2025,$AA24<=2030)),1,0) -> 0 | BQ24: =IF(AND($Y24="Y",$AA24>2030),1,0) -> 0 | BR24: =IF(AND($AP24="Y",$AS24<=2025),1,0) -> 0 | BS24: =IF(AND($AP24="Y",AND($AS24>2025,$AS24<=2030)),1,0) -> 0 | BT24: =IF(AND($AP24="Y",$AS24>2030),1,0) -> 0 | BU24: =IF(AND(AL24<=2025,CF24=0,AJ24="Y"),1,0) -> 0 | BV24: =IF(AND(AL24>=2026,AL24<=2030,AJ24="Y",CF24=0),1,0) -> 0 | BW24: =IF(AND(AL24>=2031,CF24=0,AJ24="Y"),1,0) -> 1 | BX24: =IF(AND($AJ24="Y",$AL24<=2024),1,0) -> 0 | BY24: =IF(AND($AJ24="Y",AND($AL24>2024,$AL24<=2030)),1,0) -> 0 | BZ24: =IF(AND($AJ24="Y",$AL24>2030),1,0) -> 1 | CA24: =MAX(BX24:BZ24) -> 1 | CB24: =IF(AND(CF24=0,AJ24="Y"),1,0) -> 1 | CC24: =MAX($BO24,$BR24) -> 0 | CD24: =MAX($BP24,$BS24) -> 0 | CE24: =MAX($BQ24,$BT24) -> 0 | CF24: =MAX(CC24:CE24) -> 0 | CG24: =MAX($CF24,$CA24) -> 1 | CH24: =MAX(CF24,CB24) -> 1 | CI24: =IF(AND($AY24="Y",$BA24<=2024),1,0) -> 0 | CJ24: =IF(AND($AY24="Y",AND($BA24>2024,$BA24<=2030)),1,0) -> 0 | CK24: =IF(AND($AY24="Y",$BA24>2030),1,0) -> 0 | CL24: =SUM(CC24,BU24,BK24,BG24) -> 0 | CM24: =SUM(CD24,BV24,BL24,BH24) -> 1 | CN24: =SUM(CE24,BW24,BM24,BI24) -> 1 | CO24: =CF24+CB24+BN24+BJ24 -> 2 | CP24: =MAX(CH24,BN24,BJ24) -> 1 | CQ24: =IF($AV24="Yes",1,0) -> 0 | CR24: =IF($AV24="No",1,0) -> 0 | CS24: =IF($AV24="Not Specified",1,0) -> 1 | CT24: =IF(OR(AND(U24>=2026,U24<=2030),AND(X24>=2026,X24<=2030)),1,"") -> 1 | CU24: =AA24&" "&AS24 | CV24: =MAX(AA24,AS24) -> 0 | CW24: 0 | CX24: 0 | CY24: 1 | CZ24: 1 | DA24: 0 | DB24: 0 | DC24: 0 | DD24: 0 | DE24: 0 | DF24: 1 | DG24: 0 | DH24: 1 | DI24: 0 | DJ24: 1 | DK24: 0 | DL24: 1 | DM24: 1 | DN24: 0 | DO24: 1 | DP24: 1 | DQ24: 0 | DR24: 1 | DS24: 0 | DT24: N | DU24: No | DV24: N | DW24: C | DX24: Y | DY24: 0 | DZ24: =Q24 -> Y | EA24: =Z24 | EB24: =AP24 -> N | EC24: =AJ24 -> Y | ED24: =AV24 -> Not Specified | EF24: =MAX(AS24,AA24) -> 0
A25: 22 | B25: 26 | C25: Microsoft | D25: Computer Software | E25: Technology | F25: U.S. | G25: North America | H25: $245,122 | I25: $88,136 | J25: 0.218 | K25: $512,163 | L25: 228000 | M25: 28 | N25: Y | O25: 2015 | P25: 2014 | Q25: Y | R25: Y | S25: Targets set | T25: 1.5°C | U25: 2030 | Y25: N | Z25: Commitment removed | AC25: Carbon negative | AD25: Carbon Neutral | AE25: Yes | AF25: Yes | AG25: Yes | AH25: 1,2,3 | AI25: C,V | AJ25: Y | AK25: We are committed to being carbon negative by 2030 and by 2050 to remove from the atmosphere an equivalent amount of all the carbon dioxide our company has emitted either directly or by our electricity consumption since we were founded in 1975. Our carbon negative commitment includes three primary areas: reducing carbon emissions, increasing use of carbon-free electricity, and carbon removal. Reducing Direct Emissions: We will reduce our Scope 1 and 2 emissions to near zero by increasing energy efficiency, decarbonization of our operations, and reaching 100% renewable energy by 2025. Reducing Value Chain Emissions: By 2030, Microsoft will remove more carbon than it emits. Replacing with 100/100/0 carbon-free energy: By 2030, we will reduce our Scope 3 emissions by more than half from a 2020 baseline. Removing the rest of our emissions: By 2030, 100% of our electricity consumption will be matched by zero carbon energy purchases 100% of the time. | AL25: 2030 | AP25: N | AV25: Yes | AW25: Yes (unspecified) | AX25: Yes | AY25: N | BG25: =IF(AND($N25="Y",$P25<=2025),1,0) -> 1 | BH25: =IF(AND($N25="Y",AND($P25>2025,$P25<=2030)),1,0) -> 0 | BI25: =IF(AND($N25="Y",$P25>2030),1,0) -> 0 | BJ25: =MAX(BG25:BI25) -> 1 | BK25: =IF(AND($R25="Y",$U25<=2025),1,0) -> 0 | BL25: =IF(AND($R25="Y",AND($U25>2025,$U25<=2030)),1,0) -> 1 | BM25: =IF(AND($R25="Y",$U25>2030),1,0) -> 0 | BN25: =MAX(BK25:BM25) -> 1 | BO25: =IF(AND($Y25="Y",$AA25<=2025),1,0) -> 0 | BP25: =IF(AND($Y25="Y",AND($AA25>2025,$AA25<=2030)),1,0) -> 0 | BQ25: =IF(AND($Y25="Y",$AA25>2030),1,0) -> 0 | BR25: =IF(AND($AP25="Y",$AS25<=2025),1,0) -> 0 | BS25: =IF(AND($AP25="Y",AND($AS25>2025,$AS25<=2030)),1,0) -> 0 | BT25: =IF(AND($AP25="Y",$AS25>2030),1,0) -> 0 | BU25: =IF(AND(AL25<=2025,CF25=0,AJ25="Y"),1,0) -> 0 | BV25: =IF(AND(AL25>=2026,AL25<=2030,AJ25="Y",CF25=0),1,0) -> 1 | BW25: =IF(AND(AL25>=2031,CF25=0,AJ25="Y"),1,0) -> 0 | BX25: =IF(AND($AJ25="Y",$AL25<=2024),1,0) -> 0 | BY25: =IF(AND($AJ25="Y",AND($AL25>2024,$AL25<=2030)),1,0) -> 1 | BZ25: =IF(AND($AJ25="Y",$AL25>2030),1,0) -> 0 | CA25: =MAX(BX25:BZ25) -> 1 | CB25: =IF(AND(CF25=0,AJ25="Y"),1,0) -> 1 | CC25: =MAX($BO25,$BR25) -> 0 | CD25: =MAX($BP25,$BS25) -> 0 | CE25: =MAX($BQ25,$BT25) -> 0 | CF25: =MAX(CC25:CE25) -> 0 | CG25: =MAX($CF25,$CA25) -> 1 | CH25: =MAX(CF25,CB25) -> 1 | CI25: =IF(AND($AY25="Y",$BA25<=2024),1,0) -> 0 | CJ25: =IF(AND($AY25="Y",AND($BA25>2024,$BA25<=2030)),1,0) -> 0 | CK25: =IF(AND($AY25="Y",$BA25>2030),1,0) -> 0 | CL25: =SUM(CC25,BU25,BK25,BG25) -> 1 | CM25: =SUM(CD25,BV25,BL25,BH25) -> 2 | CN25: =SUM(CE25,BW25,BM25,BI25) -> 0 | CO25: =CF25+CB25+BN25+BJ25 -> 3 | CP25: =MAX(CH25,BN25,BJ25) -> 1 | CQ25: =IF($AV25="Yes",1,0) -> 1 | CR25: =IF($AV25="No",1,0) -> 0 | CS25: =IF($AV25="Not Specified",1,0) -> 0 | CT25: =IF(OR(AND(U25>=2026,U25<=2030),AND(X25>=2026,X25<=2030)),1,"") -> 1 | CU25: =AA25&" "&AS25 | CV25: =MAX(AA25,AS25) -> 0 | CW25: 1 | CX25: 0 | CY25: 0 | CZ25: 1 | DA25: 0 | DB25: 0 | DC25: 0 | DD25: 0 | DE25: 0 | DF25: 1 | DG25: 0 | DH25: 1 | DI25: 1 | DJ25: 0 | DK25: 0 | DL25: 1 | DM25: 1 | DN25: 1 | DO25: 1 | DP25: 1 | DQ25: 0 | DR25: 1 | DS25: 1 | DT25: Y | DU25: No | DV25: N | DW25: C, V | DX25: Y | DY25: 0 | DZ25: =Q25 -> Y | EA25: =Z25 -> Commitment removed | EB25: =AP25 -> N | EC25: =AJ25 -> Y | ED25: =AV25 -> Yes | EF25: =MAX(AS25,AA25) -> 0
A26: 23 | B26: 19 | C26: Trafigura Group | D26: Trading | E26: Financial services | F26: Singapore | G26: Asia | H26: $243,201.8 | I26: $2,771.8 | J26: -0.625 | K26: $76,426.5 | L26: 13086 | M26: 11 | N26: N | Q26: N | R26: N | AC26: Carbon neutral(ity) | AD26: Carbon Neutral | AE26: Yes | AF26: Yes | AG26: Yes | AH26: 1,2,3 | AI26: C,V | AJ26: Y | AK26: "We have also set out an indicative pathway to achieve operational carbon neutrality by 2050." [url: https://web.archive.org/web/20250812213839/https://www.trafigura.com/sustainability/environment-and-climate/] | AL26: 2050 | AP26: N | AV26: Yes | AW26: Yes (nature-based removals e.g. Forestation, soil carbon enhancement) | AX26: No | AY26: N | BG26: =IF(AND($N26="Y",$P26<=2025),1,0) -> 0 | BH26: =IF(AND($N26="Y",AND($P26>2025,$P26<=2030)),1,0) -> 0 | BI26: =IF(AND($N26="Y",$P26>2030),1,0) -> 0 | BJ26: =MAX(BG26:BI26) -> 0 | BK26: =IF(AND($R26="Y",$U26<=2025),1,0) -> 0 | BL26: =IF(AND($R26="Y",AND($U26>2025,$U26<=2030)),1,0) -> 0 | BM26: =IF(AND($R26="Y",$U26>2030),1,0) -> 0 | BN26: =MAX(BK26:BM26) -> 0 | BO26: =IF(AND($Y26="Y",$AA26<=2025),1,0) -> 0 | BP26: =IF(AND($Y26="Y",AND($AA26>2025,$AA26<=2030)),1,0) -> 0 | BQ26: =IF(AND($Y26="Y",$AA26>2030),1,0) -> 0 | BR26: =IF(AND($AP26="Y",$AS26<=2025),1,0) -> 0 | BS26: =IF(AND($AP26="Y",AND($AS26>2025,$AS26<=2030)),1,0) -> 0 | BT26: =IF(AND($AP26="Y",$AS26>2030),1,0) -> 0 | BU26: =IF(AND(AL26<=2025,CF26=0,AJ26="Y"),1,0) -> 0 | BV26: =IF(AND(AL26>=2026,AL26<=2030,AJ26="Y",CF26=0),1,0) -> 0 | BW26: =IF(AND(AL26>=2031,CF26=0,AJ26="Y"),1,0) -> 1 | BX26: =IF(AND($AJ26="Y",$AL26<=2024),1,0) -> 0 | BY26: =IF(AND($AJ26="Y",AND($AL26>2024,$AL26<=2030)),1,0) -> 0 | BZ26: =IF(AND($AJ26="Y",$AL26>2030),1,0) -> 1 | CA26: =MAX(BX26:BZ26) -> 1 | CB26: =IF(AND(CF26=0,AJ26="Y"),1,0) -> 1 | CC26: =MAX($BO26,$BR26) -> 0 | CD26: =MAX($BP26,$BS26) -> 0 | CE26: =MAX($BQ26,$BT26) -> 0 | CF26: =MAX(CC26:CE26) -> 0 | CG26: =MAX($CF26,$CA26) -> 1 | CH26: =MAX(CF26,CB26) -> 1 | CI26: =IF(AND($AY26="Y",$BA26<=2024),1,0) -> 0 | CJ26: =IF(AND($AY26="Y",AND($BA26>2024,$BA26<=2030)),1,0) -> 0 | CK26: =IF(AND($AY26="Y",$BA26>2030),1,0) -> 0 | CL26: =SUM(CC26,BU26,BK26,BG26) -> 0 | CM26: =SUM(CD26,BV26,BL26,BH26) -> 0 | CN26: =SUM(CE26,BW26,BM26,BI26) -> 1 | CO26: =CF26+CB26+BN26+BJ26 -> 1 | CP26: =MAX(CH26,BN26,BJ26) -> 1 | CQ26: =IF($AV26="Yes",1,0) -> 1 | CR26: =IF($AV26="No",1,0) -> 0 | CS26: =IF($AV26="Not Specified",1,0) -> 0 | CT26: =IF(OR(AND(U26>=2026,U26<=2030),AND(X26>=2026,X26<=2030)),1,"") | CU26: =AA26&" "&AS26 | CV26: =MAX(AA26,AS26) -> 0 | CW26: 0 | CX26: 0 | CY26: 1 | CZ26: 1 | DA26: 0 | DB26: 0 | DC26: 0 | DD26: 0 | DE26: 0 | DF26: 0 | DG26: 0 | DH26: 0 | DI26: 0 | DJ26: 0 | DK26: 0 | DL26: 0 | DM26: 1 | DN26: 0 | DO26: 1 | DP26: 1 | DQ26: 0 | DR26: 1 | DS26: 0 | DT26: N | DU26: 0 | DV26: N | DW26: C | DX26: Y | DY26: 0 | DZ26: =Q26 -> N | EA26: =Z26 | EB26: =AP26 -> N | EC26: =AJ26 -> Y | ED26: =AV26 -> Yes | EF26: =MAX(AS26,AA26) -> 0
A27: 24 | B27: 24 | C27: Glencore | D27: Mining, Crude-Oil Production | E27: Metals and mining | F27: Switzerland | G27: Europe | H27: $230,944 | I27: $-1,634 | J27: -1.382 | K27: $130,460 | L27: 84146 | M27: 15 | N27: N | Q27: N | R27: N | AC27: Net zero | AD27: Net Zero | AE27: Yes | AF27: Yes | AG27: Yes | AH27: 1,2,3 | AJ27: N | AO27: C,V | AP27: Y | AQ27: 1,2,3 | AR27: "In our 2024-2026 Climate Action Transition Plan, we outlined our responsible thermal coal decline strategy and holistic scope 1, 2 and 3 industrial emissions reduction targets of 15% by the end of 2026, 25% by the end of 2030 and 50% by the end of 2035 (all against a restated 2019 baseline). We also further reiterated our ambition of achieving net zero industrial emissions by the end of 2050, subject to a supportive policy environment. " (p. 45 of Annual Report 2024) | AS27: 2050 | AV27: Not Specified | AW27: Yes (CCS-based removals e.g. BECCS, DACCS) | AX27: No | AY27: N | BG27: =IF(AND($N27="Y",$P27<=2025),1,0) -> 0 | BH27: =IF(AND($N27="Y",AND($P27>2025,$P27<=2030)),1,0) -> 0 | BI27: =IF(AND($N27="Y",$P27>2030),1,0) -> 0 | BJ27: =MAX(BG27:BI27) -> 0 | BK27: =IF(AND($R27="Y",$U27<=2025),1,0) -> 0 | BL27: =IF(AND($R27="Y",AND($U27>2025,$U27<=2030)),1,0) -> 0 | BM27: =IF(AND($R27="Y",$U27>2030),1,0) -> 0 | BN27: =MAX(BK27:BM27) -> 0 | BO27: =IF(AND($Y27="Y",$AA27<=2025),1,0) -> 0 | BP27: =IF(AND($Y27="Y",AND($AA27>2025,$AA27<=2030)),1,0) -> 0 | BQ27: =IF(AND($Y27="Y",$AA27>2030),1,0) -> 0 | BR27: =IF(AND($AP27="Y",$AS27<=2025),1,0) -> 0 | BS27: =IF(AND($AP27="Y",AND($AS27>2025,$AS27<=2030)),1,0) -> 0 | BT27: =IF(AND($AP27="Y",$AS27>2030),1,0) -> 1 | BU27: =IF(AND(AL27<=2025,CF27=0,AJ27="Y"),1,0) -> 0 | BV27: =IF(AND(AL27>=2026,AL27<=2030,AJ27="Y",CF27=0),1,0) -> 0 | BW27: =IF(AND(AL27>=2031,CF27=0,AJ27="Y"),1,0) -> 0 | BX27: =IF(AND($AJ27="Y",$AL27<=2024),1,0) -> 0 | BY27: =IF(AND($AJ27="Y",AND($AL27>2024,$AL27<=2030)),1,0) -> 0 | BZ27: =IF(AND($AJ27="Y",$AL27>2030),1,0) -> 0 | CA27: =MAX(BX27:BZ27) -> 0 | CB27: =IF(AND(CF27=0,AJ27="Y"),1,0) -> 0 | CC27: =MAX($BO27,$BR27) -> 0 | CD27: =MAX($BP27,$BS27) -> 0 | CE27: =MAX($BQ27,$BT27) -> 1 | CF27: =MAX(CC27:CE27) -> 1 | CG27: =MAX($CF27,$CA27) -> 1 | CH27: =MAX(CF27,CB27) -> 1 | CI27: =IF(AND($AY27="Y",$BA27<=2024),1,0) -> 0 | CJ27: =IF(AND($AY27="Y",AND($BA27>2024,$BA27<=2030)),1,0) -> 0 | CK27: =IF(AND($AY27="Y",$BA27>2030),1,0) -> 0 | CL27: =SUM(CC27,BU27,BK27,BG27) -> 0 | CM27: =SUM(CD27,BV27,BL27,BH27) -> 0 | CN27: =SUM(CE27,BW27,BM27,BI27) -> 1 | CO27: =CF27+CB27+BN27+BJ27 -> 1 | CP27: =MAX(CH27,BN27,BJ27) -> 1 | CQ27: =IF($AV27="Yes",1,0) -> 0 | CR27: =IF($AV27="No",1,0) -> 0 | CS27: =IF($AV27="Not Specified",1,0) -> 1 | CT27: =IF(OR(AND(U27>=2026,U27<=2030),AND(X27>=2026,X27<=2030)),1,"") | CU27: =AA27&" "&AS27 -> 2050 | CV27: =MAX(AA27,AS27) -> 2050 | CW27: 0 | CX27: 0 | CY27: 0 | CZ27: 0 | DA27: 0 | DB27: 0 | DC27: 1 | DD27: 1 | DE27: 0 | DF27: 0 | DG27: 0 | DH27: 0 | DI27: 0 | DJ27: 0 | DK27: 0 | DL27: 0 | DM27: 1 | DN27: 0 | DO27: 1 | DP27: 0 | DQ27: 0 | DR27: 1 | DS27: 0 | DT27: N | DU27: 0 | DV27: V | DW27: N | DX27: 0 | DY27: U | DZ27: =Q27 -> N | EA27: =Z27 | EB27: =AP27 -> Y | EC27: =AJ27 -> N | ED27: =AV27 -> Not Specified | EF27: =MAX(AS27,AA27) -> 2050
A28: 25 | B28: 27 | C28: Cardinal Health | D28: Wholesalers: Health Care | E28: Health care and pharmaceuticals | F28: U.S. | G28: North America | H28: $226,827 | I28: $852 | J28: 2.264 | K28: $45,121 | L28: 48411 | M28: 28 | N28: N | Q28: Y | R28: Y | S28: Targets set | T28: 1.5°C | U28: 2030 | AC28: Emissions reduction target | AD28: Other Emission Reduction | AE28: Yes | AF28: Yes | AG28: Partial | AH28: 1,2 | AJ28: N | AP28: N | AR28: The target covers carbon dioxide emissions, including scope 1 and 2 emissions, and partially covers scope 3 emissions. Net Zero Tracker | AV28: Not Specified | AW28: Not Specified | AX28: No | AY28: Y | AZ28: Target 1: Reduce absolute Scope 1 and 2 GHG emissions 50% by fiscal 2030 from a fiscal 2019 base year. The target boundary includes land-related emissions and removals from bioenergy feedstocks Target 2: 75% of its suppliers by spend, covering purchased goods and services and upstream transportation and distribution, will have science-based targets by fiscal 2028. | BA28: 2030 | BG28: =IF(AND($N28="Y",$P28<=2025),1,0) -> 0 | BH28: =IF(AND($N28="Y",AND($P28>2025,$P28<=2030)),1,0) -> 0 | BI28: =IF(AND($N28="Y",$P28>2030),1,0) -> 0 | BJ28: =MAX(BG28:BI28) -> 0 | BK28: =IF(AND($R28="Y",$U28<=2025),1,0) -> 0 | BL28: =IF(AND($R28="Y",AND($U28>2025,$U28<=2030)),1,0) -> 1 | BM28: =IF(AND($R28="Y",$U28>2030),1,0) -> 0 | BN28: =MAX(BK28:BM28) -> 1 | BO28: =IF(AND($Y28="Y",$AA28<=2025),1,0) -> 0 | BP28: =IF(AND($Y28="Y",AND($AA28>2025,$AA28<=2030)),1,0) -> 0 | BQ28: =IF(AND($Y28="Y",$AA28>2030),1,0) -> 0 | BR28: =IF(AND($AP28="Y",$AS28<=2025),1,0) -> 0 | BS28: =IF(AND($AP28="Y",AND($AS28>2025,$AS28<=2030)),1,0) -> 0 | BT28: =IF(AND($AP28="Y",$AS28>2030),1,0) -> 0 | BU28: =IF(AND(AL28<=2025,CF28=0,AJ28="Y"),1,0) -> 0 | BV28: =IF(AND(AL28>=2026,AL28<=2030,AJ28="Y",CF28=0),1,0) -> 0 | BW28: =IF(AND(AL28>=2031,CF28=0,AJ28="Y"),1,0) -> 0 | BX28: =IF(AND($AJ28="Y",$AL28<=2024),1,0) -> 0 | BY28: =IF(AND($AJ28="Y",AND($AL28>2024,$AL28<=2030)),1,0) -> 0 | BZ28: =IF(AND($AJ28="Y",$AL28>2030),1,0) -> 0 | CA28: =MAX(BX28:BZ28) -> 0 | CB28: =IF(AND(CF28=0,AJ28="Y"),1,0) -> 0 | CC28: =MAX($BO28,$BR28) -> 0 | CD28: =MAX($BP28,$BS28) -> 0 | CE28: =MAX($BQ28,$BT28) -> 0 | CF28: =MAX(CC28:CE28) -> 0 | CG28: =MAX($CF28,$CA28) -> 0 | CH28: =MAX(CF28,CB28) -> 0 | CI28: =IF(AND($AY28="Y",$BA28<=2024),1,0) -> 0 | CJ28: =IF(AND($AY28="Y",AND($BA28>2024,$BA28<=2030)),1,0) -> 1 | CK28: =IF(AND($AY28="Y",$BA28>2030),1,0) -> 0 | CL28: =SUM(CC28,BU28,BK28,BG28) -> 0 | CM28: =SUM(CD28,BV28,BL28,BH28) -> 1 | CN28: =SUM(CE28,BW28,BM28,BI28) -> 0 | CO28: =CF28+CB28+BN28+BJ28 -> 1 | CP28: =MAX(CH28,BN28,BJ28) -> 1 | CQ28: =IF($AV28="Yes",1,0) -> 0 | CR28: =IF($AV28="No",1,0) -> 0 | CS28: =IF($AV28="Not Specified",1,0) -> 1 | CT28: =IF(OR(AND(U28>=2026,U28<=2030),AND(X28>=2026,X28<=2030)),1,"") -> 1 | CU28: =AA28&" "&AS28 | CV28: =MAX(AA28,AS28) -> 0 | CW28: 0 | CX28: 0 | CY28: 0 | CZ28: 0 | DA28: 0 | DB28: 0 | DC28: 0 | DD28: 0 | DE28: 0 | DF28: 1 | DG28: 0 | DH28: 1 | DI28: 0 | DJ28: 0 | DK28: 0 | DL28: 0 | DM28: 0 | DN28: 0 | DO28: 0 | DP28: 0 | DQ28: 0 | DR28: 1 | DS28: 0 | DT28: Y | DU28: No | DV28: N | DW28: N | DX28: 0 | DY28: 0 | DZ28: =Q28 -> Y | EA28: =Z28 | EB28: =AP28 -> N | EC28: =AJ28 -> N | ED28: =AV28 -> Not Specified | EF28: =MAX(AS28,AA28) -> 0
A29: 26 | B29: 22 | C29: Industrial & Commercial Bank of China | D29: Banks: Commercial and Savings | E29: Financial services | F29: China | G29: Asia | H29: $221,461.3 | I29: $50,848.5 | J29: -0.011 | K29: $6,688,551.8 | L29: 415159 | M29: 27 | N29: N | Q29: N | R29: N | AC29: No target | AD29: No Target | AE29: yes | AF29: yes | AG29: Not Specified | AH29: 1,2 | AI29: G | AJ29: N | AK29: committed to national peak and neutrality targets | AL29: 2060 | AM29: https://v.icbc.com.cn/userfiles/resources/icbcltd/download/2025/esg2024en.pdf | AP29: N | AV29: Yes | AW29: Not Specified | AX29: No | AY29: N | BG29: =IF(AND($N29="Y",$P29<=2025),1,0) -> 0 | BH29: =IF(AND($N29="Y",AND($P29>2025,$P29<=2030)),1,0) -> 0 | BI29: =IF(AND($N29="Y",$P29>2030),1,0) -> 0 | BJ29: =MAX(BG29:BI29) -> 0 | BK29: =IF(AND($R29="Y",$U29<=2025),1,0) -> 0 | BL29: =IF(AND($R29="Y",AND($U29>2025,$U29<=2030)),1,0) -> 0 | BM29: =IF(AND($R29="Y",$U29>2030),1,0) -> 0 | BN29: =MAX(BK29:BM29) -> 0 | BO29: =IF(AND($Y29="Y",$AA29<=2025),1,0) -> 0 | BP29: =IF(AND($Y29="Y",AND($AA29>2025,$AA29<=2030)),1,0) -> 0 | BQ29: =IF(AND($Y29="Y",$AA29>2030),1,0) -> 0 | BR29: =IF(AND($AP29="Y",$AS29<=2025),1,0) -> 0 | BS29: =IF(AND($AP29="Y",AND($AS29>2025,$AS29<=2030)),1,0) -> 0 | BT29: =IF(AND($AP29="Y",$AS29>2030),1,0) -> 0 | BU29: =IF(AND(AL29<=2025,CF29=0,AJ29="Y"),1,0) -> 0 | BV29: =IF(AND(AL29>=2026,AL29<=2030,AJ29="Y",CF29=0),1,0) -> 0 | BW29: =IF(AND(AL29>=2031,CF29=0,AJ29="Y"),1,0) -> 0 | BX29: =IF(AND($AJ29="Y",$AL29<=2024),1,0) -> 0 | BY29: =IF(AND($AJ29="Y",AND($AL29>2024,$AL29<=2030)),1,0) -> 0 | BZ29: =IF(AND($AJ29="Y",$AL29>2030),1,0) -> 0 | CA29: =MAX(BX29:BZ29) -> 0 | CB29: =IF(AND(CF29=0,AJ29="Y"),1,0) -> 0 | CC29: =MAX($BO29,$BR29) -> 0 | CD29: =MAX($BP29,$BS29) -> 0 | CE29: =MAX($BQ29,$BT29) -> 0 | CF29: =MAX(CC29:CE29) -> 0 | CG29: =MAX($CF29,$CA29) -> 0 | CH29: =MAX(CF29,CB29) -> 0 | CI29: =IF(AND($AY29="Y",$BA29<=2024),1,0) -> 0 | CJ29: =IF(AND($AY29="Y",AND($BA29>2024,$BA29<=2030)),1,0) -> 0 | CK29: =IF(AND($AY29="Y",$BA29>2030),1,0) -> 0 | CL29: =SUM(CC29,BU29,BK29,BG29) -> 0 | CM29: =SUM(CD29,BV29,BL29,BH29) -> 0 | CN29: =SUM(CE29,BW29,BM29,BI29) -> 0 | CO29: =CF29+CB29+BN29+BJ29 -> 0 | CP29: =MAX(CH29,BN29,BJ29) -> 0 | CQ29: =IF($AV29="Yes",1,0) -> 1 | CR29: =IF($AV29="No",1,0) -> 0 | CS29: =IF($AV29="Not Specified",1,0) -> 0 | CT29: =IF(OR(AND(U29>=2026,U29<=2030),AND(X29>=2026,X29<=2030)),1,"") | CU29: =AA29&" "&AS29 | CV29: =MAX(AA29,AS29) -> 0 | CW29: 0 | CX29: 0 | CY29: 0 | CZ29: 0 | DA29: 0 | DB29: 0 | DC29: 0 | DD29: 0 | DE29: 0 | DF29: 0 | DG29: 0 | DH29: 0 | DI29: 0 | DJ29: 0 | DK29: 0 | DL29: 0 | DM29: 0 | DN29: 0 | DO29: 0 | DP29: 0 | DQ29: 0 | DR29: 0 | DS29: 0 | DT29: N | DU29: 0 | DV29: N | DW29: G | DX29: U | DY29: 0 | DZ29: =Q29 -> N | EA29: =Z29 | EB29: =AP29 -> N | EC29: =AJ29 -> N | ED29: =AV29 -> Yes | EF29: =MAX(AS29,AA29) -> 0
A30: 27 | B30: 31 | C30: Samsung Electronics | D30: Electronics | E30: Technology | F30: South Korea | G30: Asia | H30: $220,636.7 | I30: $24,655.4 | J30: 1.225 | K30: $348,381.7 | L30: 262647 | M30: 31 | N30: Y | O30: 2022 | P30: 2050 | Q30: N | R30: N | AC30: Net zero | AD30: Net Zero | AE30: Yes | AF30: Yes | AG30: No | AH30: 1,2 | AJ30: N | AO30: C | AP30: Y | AQ30: 1,2 | AR30: "At the heart of the new commitment is achieving net zero carbon emissions (Scope 1 & Scope 2) ... across all global operations, including the Device Solutions (DS) Division, by 2050." (Source: https://web.archive.org/web/20250821204128/https://news.samsung.com/global/samsung-electronics-announces-new-environmental-strategy (Sept 2022)) | AS30: 2050 | AV30: Yes | AW30: Yes (nature-based and CCS-based removals) | AX30: No | AY30: N | BG30: =IF(AND($N30="Y",$P30<=2025),1,0) -> 0 | BH30: =IF(AND($N30="Y",AND($P30>2025,$P30<=2030)),1,0) -> 0 | BI30: =IF(AND($N30="Y",$P30>2030),1,0) -> 1 | BJ30: =MAX(BG30:BI30) -> 1 | BK30: =IF(AND($R30="Y",$U30<=2025),1,0) -> 0 | BL30: =IF(AND($R30="Y",AND($U30>2025,$U30<=2030)),1,0) -> 0 | BM30: =IF(AND($R30="Y",$U30>2030),1,0) -> 0 | BN30: =MAX(BK30:BM30) -> 0 | BO30: =IF(AND($Y30="Y",$AA30<=2025),1,0) -> 0 | BP30: =IF(AND($Y30="Y",AND($AA30>2025,$AA30<=2030)),1,0) -> 0 | BQ30: =IF(AND($Y30="Y",$AA30>2030),1,0) -> 0 | BR30: =IF(AND($AP30="Y",$AS30<=2025),1,0) -> 0 | BS30: =IF(AND($AP30="Y",AND($AS30>2025,$AS30<=2030)),1,0) -> 0 | BT30: =IF(AND($AP30="Y",$AS30>2030),1,0) -> 1 | BU30: =IF(AND(AL30<=2025,CF30=0,AJ30="Y"),1,0) -> 0 | BV30: =IF(AND(AL30>=2026,AL30<=2030,AJ30="Y",CF30=0),1,0) -> 0 | BW30: =IF(AND(AL30>=2031,CF30=0,AJ30="Y"),1,0) -> 0 | BX30: =IF(AND($AJ30="Y",$AL30<=2024),1,0) -> 0 | BY30: =IF(AND($AJ30="Y",AND($AL30>2024,$AL30<=2030)),1,0) -> 0 | BZ30: =IF(AND($AJ30="Y",$AL30>2030),1,0) -> 0 | CA30: =MAX(BX30:BZ30) -> 0 | CB30: =IF(AND(CF30=0,AJ30="Y"),1,0) -> 0 | CC30: =MAX($BO30,$BR30) -> 0 | CD30: =MAX($BP30,$BS30) -> 0 | CE30: =MAX($BQ30,$BT30) -> 1 | CF30: =MAX(CC30:CE30) -> 1 | CG30: =MAX($CF30,$CA30) -> 1 | CH30: =MAX(CF30,CB30) -> 1 | CI30: =IF(AND($AY30="Y",$BA30<=2024),1,0) -> 0 | CJ30: =IF(AND($AY30="Y",AND($BA30>2024,$BA30<=2030)),1,0) -> 0 | CK30: =IF(AND($AY30="Y",$BA30>2030),1,0) -> 0 | CL30: =SUM(CC30,BU30,BK30,BG30) -> 0 | CM30: =SUM(CD30,BV30,BL30,BH30) -> 0 | CN30: =SUM(CE30,BW30,BM30,BI30) -> 2 | CO30: =CF30+CB30+BN30+BJ30 -> 2 | CP30: =MAX(CH30,BN30,BJ30) -> 1 | CQ30: =IF($AV30="Yes",1,0) -> 1 | CR30: =IF($AV30="No",1,0) -> 0 | CS30: =IF($AV30="Not Specified",1,0) -> 0 | CT30: =IF(OR(AND(U30>=2026,U30<=2030),AND(X30>=2026,X30<=2030)),1,"") | CU30: =AA30&" "&AS30 -> 2050 | CV30: =MAX(AA30,AS30) -> 2050 | CW30: 0 | CX30: 0 | CY30: 0 | CZ30: 0 | DA30: 0 | DB30: 0 | DC30: 1 | DD30: 1 | DE30: 0 | DF30: 0 | DG30: 0 | DH30: 0 | DI30: 0 | DJ30: 0 | DK30: 1 | DL30: 1 | DM30: 1 | DN30: 0 | DO30: 1 | DP30: 0 | DQ30: 0 | DR30: 1 | DS30: 0 | DT30: N | DU30: 0 | DV30: C | DW30: N | DX30: 0 | DY30: U | DZ30: =Q30 -> N | EA30: =Z30 | EB30: =AP30 -> Y | EC30: =AJ30 -> N | ED30: =AV30 -> Yes | EF30: =MAX(AS30,AA30) -> 2050
A31: 28 | B31: 32 | C31: Hon Hai Precision Industry | D31: Electronics, Electrical Equip. | E31: Technology | F31: Taiwan | G31: Asia | H31: $213,699.1 | I31: $4,757.3 | J31: 0.043 | K31: $133,999.1 | L31: 633167 | M31: 21 | N31: Y | O31: 2024 | P31: 2040 | Q31: Y | R31: Y | S31: Targets set | T31: 1.5Â°C | U31: 2030 | V31: Targets set | W31: 1.5Â°C | X31: 2050 | Y31: Y | Z31: Targets set | AA31: 2050 | AC31: Net zero | AD31: Net Zero | AE31: Yes | AF31: Yes | AG31: No | AH31: 1,2 | AJ31: N | AO31: C | AP31: Y | AQ31: 1,2 | AR31: 'We became a founding member of the Taiwan Alliance for Net Zero Emission and pledged to achieve net zero emissions in our offices in Taiwan by 2030 and in our production bases by 2050' (p4) | AS31: 2050 | AV31: Not Specified | AW31: Not Specified | AX31: No | AY31: N | BG31: =IF(AND($N31="Y",$P31<=2025),1,0) -> 0 | BH31: =IF(AND($N31="Y",AND($P31>2025,$P31<=2030)),1,0) -> 0 | BI31: =IF(AND($N31="Y",$P31>2030),1,0) -> 1 | BJ31: =MAX(BG31:BI31) -> 1 | BK31: =IF(AND($R31="Y",$U31<=2025),1,0) -> 0 | BL31: =IF(AND($R31="Y",AND($U31>2025,$U31<=2030)),1,0) -> 1 | BM31: =IF(AND($R31="Y",$U31>2030),1,0) -> 0 | BN31: =MAX(BK31:BM31) -> 1 | BO31: =IF(AND($Y31="Y",$AA31<=2025),1,0) -> 0 | BP31: =IF(AND($Y31="Y",AND($AA31>2025,$AA31<=2030)),1,0) -> 0 | BQ31: =IF(AND($Y31="Y",$AA31>2030),1,0) -> 1 | BR31: =IF(AND($AP31="Y",$AS31<=2025),1,0) -> 0 | BS31: =IF(AND($AP31="Y",AND($AS31>2025,$AS31<=2030)),1,0) -> 0 | BT31: =IF(AND($AP31="Y",$AS31>2030),1,0) -> 1 | BU31: =IF(AND(AL31<=2025,CF31=0,AJ31="Y"),1,0) -> 0 | BV31: =IF(AND(AL31>=2026,AL31<=2030,AJ31="Y",CF31=0),1,0) -> 0 | BW31: =IF(AND(AL31>=2031,CF31=0,AJ31="Y"),1,0) -> 0 | BX31: =IF(AND($AJ31="Y",$AL31<=2024),1,0) -> 0 | BY31: =IF(AND($AJ31="Y",AND($AL31>2024,$AL31<=2030)),1,0) -> 0 | BZ31: =IF(AND($AJ31="Y",$AL31>2030),1,0) -> 0 | CA31: =MAX(BX31:BZ31) -> 0 | CB31: =IF(AND(CF31=0,AJ31="Y"),1,0) -> 0 | CC31: =MAX($BO31,$BR31) -> 0 | CD31: =MAX($BP31,$BS31) -> 0 | CE31: =MAX($BQ31,$BT31) -> 1 | CF31: =MAX(CC31:CE31) -> 1 | CG31: =MAX($CF31,$CA31) -> 1 | CH31: =MAX(CF31,CB31) -> 1 | CI31: =IF(AND($AY31="Y",$BA31<=2024),1,0) -> 0 | CJ31: =IF(AND($AY31="Y",AND($BA31>2024,$BA31<=2030)),1,0) -> 0 | CK31: =IF(AND($AY31="Y",$BA31>2030),1,0) -> 0 | CL31: =SUM(CC31,BU31,BK31,BG31) -> 0 | CM31: =SUM(CD31,BV31,BL31,BH31) -> 1 | CN31: =SUM(CE31,BW31,BM31,BI31) -> 2 | CO31: =CF31+CB31+BN31+BJ31 -> 3 | CP31: =MAX(CH31,BN31,BJ31) -> 1 | CQ31: =IF($AV31="Yes",1,0) -> 0 | CR31: =IF($AV31="No",1,0) -> 0 | CS31: =IF($AV31="Not Specified",1,0) -> 1 | CT31: =IF(OR(AND(U31>=2026,U31<=2030),AND(X31>=2026,X31<=2030)),1,"") -> 1 | CU31: =AA31&" "&AS31 -> 2050 2050 | CV31: =MAX(AA31,AS31) -> 2050 | CW31: 0 | CX31: 0 | CY31: 0 | CZ31: 0 | DA31: 0 | DB31: 0 | DC31: 1 | DD31: 1 | DE31: 0 | DF31: 1 | DG31: 0 | DH31: 1 | DI31: 0 | DJ31: 0 | DK31: 0 | DL31: 0 | DM31: 1 | DN31: 0 | DO31: 1 | DP31: 1 | DQ31: 0 | DR31: 1 | DS31: 0 | DT31: Y | DU31: Yes | DV31: V | DW31: N | DX31: 0 | DY31: Y | DZ31: =Q31 -> Y | EA31: =Z31 -> Targets set | EB31: =AP31 -> Y | EC31: =AJ31 -> N | ED31: =AV31 -> Not Specified | EF31: =MAX(AS31,AA31) -> 2050
A32: 29 | B32: 29 | C32: Chevron | D32: Petroleum Refining | E32: Oil and gas | F32: U.S. | G32: North America | H32: $202,792 | I32: $17,661 | J32: -0.174 | K32: $256,938 | L32: 45298 | M32: 31 | N32: N | Q32: N | R32: N | AC32: Net zero | AD32: Net Zero | AE32: Yes | AF32: Yes | AG32: Partial | AH32: 1,2 | AJ32: N | AO32: C | AP32: Y | AQ32: 1,2 | AR32: "Chevron aspires to achieve net zero for upstream production Scope 1 and 2 GHG emissions on an equity basis by 2050" | AS32: 2050 | AV32: Yes | AW32: Yes (CCS-based removals e.g. BECCS, DACCS) | AX32: Yes | AY32: N | BG32: =IF(AND($N32="Y",$P32<=2025),1,0) -> 0 | BH32: =IF(AND($N32="Y",AND($P32>2025,$P32<=2030)),1,0) -> 0 | BI32: =IF(AND($N32="Y",$P32>2030),1,0) -> 0 | BJ32: =MAX(BG32:BI32) -> 0 | BK32: =IF(AND($R32="Y",$U32<=2025),1,0) -> 0 | BL32: =IF(AND($R32="Y",AND($U32>2025,$U32<=2030)),1,0) -> 0 | BM32: =IF(AND($R32="Y",$U32>2030),1,0) -> 0 | BN32: =MAX(BK32:BM32) -> 0 | BO32: =IF(AND($Y32="Y",$AA32<=2025),1,0) -> 0 | BP32: =IF(AND($Y32="Y",AND($AA32>2025,$AA32<=2030)),1,0) -> 0 | BQ32: =IF(AND($Y32="Y",$AA32>2030),1,0) -> 0 | BR32: =IF(AND($AP32="Y",$AS32<=2025),1,0) -> 0 | BS32: =IF(AND($AP32="Y",AND($AS32>2025,$AS32<=2030)),1,0) -> 0 | BT32: =IF(AND($AP32="Y",$AS32>2030),1,0) -> 1 | BU32: =IF(AND(AL32<=2025,CF32=0,AJ32="Y"),1,0) -> 0 | BV32: =IF(AND(AL32>=2026,AL32<=2030,AJ32="Y",CF32=0),1,0) -> 0 | BW32: =IF(AND(AL32>=2031,CF32=0,AJ32="Y"),1,0) -> 0 | BX32: =IF(AND($AJ32="Y",$AL32<=2024),1,0) -> 0 | BY32: =IF(AND($AJ32="Y",AND($AL32>2024,$AL32<=2030)),1,0) -> 0 | BZ32: =IF(AND($AJ32="Y",$AL32>2030),1,0) -> 0 | CA32: =MAX(BX32:BZ32) -> 0 | CB32: =IF(AND(CF32=0,AJ32="Y"),1,0) -> 0 | CC32: =MAX($BO32,$BR32) -> 0 | CD32: =MAX($BP32,$BS32) -> 0 | CE32: =MAX($BQ32,$BT32) -> 1 | CF32: =MAX(CC32:CE32) -> 1 | CG32: =MAX($CF32,$CA32) -> 1 | CH32: =MAX(CF32,CB32) -> 1 | CI32: =IF(AND($AY32="Y",$BA32<=2024),1,0) -> 0 | CJ32: =IF(AND($AY32="Y",AND($BA32>2024,$BA32<=2030)),1,0) -> 0 | CK32: =IF(AND($AY32="Y",$BA32>2030),1,0) -> 0 | CL32: =SUM(CC32,BU32,BK32,BG32) -> 0 | CM32: =SUM(CD32,BV32,BL32,BH32) -> 0 | CN32: =SUM(CE32,BW32,BM32,BI32) -> 1 | CO32: =CF32+CB32+BN32+BJ32 -> 1 | CP32: =MAX(CH32,BN32,BJ32) -> 1 | CQ32: =IF($AV32="Yes",1,0) -> 1 | CR32: =IF($AV32="No",1,0) -> 0 | CS32: =IF($AV32="Not Specified",1,0) -> 0 | CT32: =IF(OR(AND(U32>=2026,U32<=2030),AND(X32>=2026,X32<=2030)),1,"") | CU32: =AA32&" "&AS32 -> 2050 | CV32: =MAX(AA32,AS32) -> 2050 | CW32: 0 | CX32: 0 | CY32: 0 | CZ32: 0 | DA32: 0 | DB32: 0 | DC32: 1 | DD32: 1 | DE32: 0 | DF32: 0 | DG32: 0 | DH32: 0 | DI32: 0 | DJ32: 0 | DK32: 0 | DL32: 0 | DM32: 1 | DN32: 0 | DO32: 1 | DP32: 1 | DQ32: 0 | DR32: 1 | DS32: 0 | DT32: N | DU32: 0 | DV32: C | DW32: N | DX32: 0 | DY32: Y | DZ32: =Q32 -> N | EA32: =Z32 | EB32: =AP32 -> Y | EC32: =AJ32 -> N | ED32: =AV32 -> Yes | EF32: =MAX(AS32,AA32) -> 2050
A33: 30 | B33: 34 | C33: Agricultural Bank of China | D33: Banks: Commercial and Savings | E33: Financial services | F33: China | G33: Asia | H33: $197,466.4 | I33: $39,204.6 | J33: 0.03 | K33: $5,923,600.2 | L33: 454716 | M33: 26 | N33: N | Q33: N | R33: N | AC33: No target | AD33: No Target | AE33: yes | AF33: yes | AG33: No | AH33: 1,2 | AI33: G | AJ33: N | AK33: committed to national peak and neutrality targets | AL33: 2060 | AM33: https://finance.sina.com.cn/stock/relnews/cn/2025-04-08/doc-inesmepe5162164.shtml | AP33: N | AV33: No | AW33: No | AX33: No | AY33: Y | AZ33: emission reduction | BB33: https://ditchcarbon.com/organizations/agricultural-bank-of-china | BG33: =IF(AND($N33="Y",$P33<=2025),1,0) -> 0 | BH33: =IF(AND($N33="Y",AND($P33>2025,$P33<=2030)),1,0) -> 0 | BI33: =IF(AND($N33="Y",$P33>2030),1,0) -> 0 | BJ33: =MAX(BG33:BI33) -> 0 | BK33: =IF(AND($R33="Y",$U33<=2025),1,0) -> 0 | BL33: =IF(AND($R33="Y",AND($U33>2025,$U33<=2030)),1,0) -> 0 | BM33: =IF(AND($R33="Y",$U33>2030),1,0) -> 0 | BN33: =MAX(BK33:BM33) -> 0 | BO33: =IF(AND($Y33="Y",$AA33<=2025),1,0) -> 0 | BP33: =IF(AND($Y33="Y",AND($AA33>2025,$AA33<=2030)),1,0) -> 0 | BQ33: =IF(AND($Y33="Y",$AA33>2030),1,0) -> 0 | BR33: =IF(AND($AP33="Y",$AS33<=2025),1,0) -> 0 | BS33: =IF(AND($AP33="Y",AND($AS33>2025,$AS33<=2030)),1,0) -> 0 | BT33: =IF(AND($AP33="Y",$AS33>2030),1,0) -> 0 | BU33: =IF(AND(AL33<=2025,CF33=0,AJ33="Y"),1,0) -> 0 | BV33: =IF(AND(AL33>=2026,AL33<=2030,AJ33="Y",CF33=0),1,0) -> 0 | BW33: =IF(AND(AL33>=2031,CF33=0,AJ33="Y"),1,0) -> 0 | BX33: =IF(AND($AJ33="Y",$AL33<=2024),1,0) -> 0 | BY33: =IF(AND($AJ33="Y",AND($AL33>2024,$AL33<=2030)),1,0) -> 0 | BZ33: =IF(AND($AJ33="Y",$AL33>2030),1,0) -> 0 | CA33: =MAX(BX33:BZ33) -> 0 | CB33: =IF(AND(CF33=0,AJ33="Y"),1,0) -> 0 | CC33: =MAX($BO33,$BR33) -> 0 | CD33: =MAX($BP33,$BS33) -> 0 | CE33: =MAX($BQ33,$BT33) -> 0 | CF33: =MAX(CC33:CE33) -> 0 | CG33: =MAX($CF33,$CA33) -> 0 | CH33: =MAX(CF33,CB33) -> 0 | CI33: =IF(AND($AY33="Y",$BA33<=2024),1,0) -> 0 | CJ33: =IF(AND($AY33="Y",AND($BA33>2024,$BA33<=2030)),1,0) -> 0 | CK33: =IF(AND($AY33="Y",$BA33>2030),1,0) -> 1 | CL33: =SUM(CC33,BU33,BK33,BG33) -> 0 | CM33: =SUM(CD33,BV33,BL33,BH33) -> 0 | CN33: =SUM(CE33,BW33,BM33,BI33) -> 0 | CO33: =CF33+CB33+BN33+BJ33 -> 0 | CP33: =MAX(CH33,BN33,BJ33) -> 0 | CQ33: =IF($AV33="Yes",1,0) -> 0 | CR33: =IF($AV33="No",1,0) -> 1 | CS33: =IF($AV33="Not Specified",1,0) -> 0 | CT33: =IF(OR(AND(U33>=2026,U33<=2030),AND(X33>=2026,X33<=2030)),1,"") | CU33: =AA33&" "&AS33 | CV33: =MAX(AA33,AS33) -> 0 | CW33: 0 | CX33: 0 | CY33: 0 | CZ33: 0 | DA33: 0 | DB33: 0 | DC33: 0 | DD33: 0 | DE33: 0 | DF33: 0 | DG33: 0 | DH33: 0 | DI33: 0 | DJ33: 0 | DK33: 0 | DL33: 0 | DM33: 0 | DN33: 0 | DO33: 0 | DP33: 0 | DQ33: 0 | DR33: 0 | DS33: 0 | DT33: N | DU33: 0 | DV33: N | DW33: G | DX33: Y, g | DY33: 0 | DZ33: =Q33 -> N | EA33: =Z33 | EB33: =AP33 -> N | EC33: =AJ33 -> N | ED33: =AV33 -> No | EF33: =MAX(AS33,AA33) -> 0
A34: 31 | B34: 30 | C34: China Construction Bank | D34: Banks: Commercial and Savings | E34: Financial services | F34: China | G34: Asia | H34: $196,738.3 | I34: $46,639.3 | J34: -0.008 | K34: $5,558,224.6 | L34: 376847 | M34: 26 | N34: N | Q34: N | R34: N | AC34: Other | AD34: Other Emission Reduction | AE34: yes | AF34: yes | AH34: 1,2 | AI34: G | AJ34: N | AK34: committed to national peak and neutrality targets | AL34: 2060 | AM34: https://ccb.com/chn/2025-04/22/article_2025042218375214433.shtml | AP34: N | AV34: Not Specified | AW34: Not Specified | AX34: No | AY34: Y | AZ34: "The Group proactively implemented the strategic plan for green finance development, advanced the carbon peaking and carbon neutrality action plan" (Annual Report 2022, p.58). | BG34: =IF(AND($N34="Y",$P34<=2025),1,0) -> 0 | BH34: =IF(AND($N34="Y",AND($P34>2025,$P34<=2030)),1,0) -> 0 | BI34: =IF(AND($N34="Y",$P34>2030),1,0) -> 0 | BJ34: =MAX(BG34:BI34) -> 0 | BK34: =IF(AND($R34="Y",$U34<=2025),1,0) -> 0 | BL34: =IF(AND($R34="Y",AND($U34>2025,$U34<=2030)),1,0) -> 0 | BM34: =IF(AND($R34="Y",$U34>2030),1,0) -> 0 | BN34: =MAX(BK34:BM34) -> 0 | BO34: =IF(AND($Y34="Y",$AA34<=2025),1,0) -> 0 | BP34: =IF(AND($Y34="Y",AND($AA34>2025,$AA34<=2030)),1,0) -> 0 | BQ34: =IF(AND($Y34="Y",$AA34>2030),1,0) -> 0 | BR34: =IF(AND($AP34="Y",$AS34<=2025),1,0) -> 0 | BS34: =IF(AND($AP34="Y",AND($AS34>2025,$AS34<=2030)),1,0) -> 0 | BT34: =IF(AND($AP34="Y",$AS34>2030),1,0) -> 0 | BU34: =IF(AND(AL34<=2025,CF34=0,AJ34="Y"),1,0) -> 0 | BV34: =IF(AND(AL34>=2026,AL34<=2030,AJ34="Y",CF34=0),1,0) -> 0 | BW34: =IF(AND(AL34>=2031,CF34=0,AJ34="Y"),1,0) -> 0 | BX34: =IF(AND($AJ34="Y",$AL34<=2024),1,0) -> 0 | BY34: =IF(AND($AJ34="Y",AND($AL34>2024,$AL34<=2030)),1,0) -> 0 | BZ34: =IF(AND($AJ34="Y",$AL34>2030),1,0) -> 0 | CA34: =MAX(BX34:BZ34) -> 0 | CB34: =IF(AND(CF34=0,AJ34="Y"),1,0) -> 0 | CC34: =MAX($BO34,$BR34) -> 0 | CD34: =MAX($BP34,$BS34) -> 0 | CE34: =MAX($BQ34,$BT34) -> 0 | CF34: =MAX(CC34:CE34) -> 0 | CG34: =MAX($CF34,$CA34) -> 0 | CH34: =MAX(CF34,CB34) -> 0 | CI34: =IF(AND($AY34="Y",$BA34<=2024),1,0) -> 0 | CJ34: =IF(AND($AY34="Y",AND($BA34>2024,$BA34<=2030)),1,0) -> 0 | CK34: =IF(AND($AY34="Y",$BA34>2030),1,0) -> 1 | CL34: =SUM(CC34,BU34,BK34,BG34) -> 0 | CM34: =SUM(CD34,BV34,BL34,BH34) -> 0 | CN34: =SUM(CE34,BW34,BM34,BI34) -> 0 | CO34: =CF34+CB34+BN34+BJ34 -> 0 | CP34: =MAX(CH34,BN34,BJ34) -> 0 | CQ34: =IF($AV34="Yes",1,0) -> 0 | CR34: =IF($AV34="No",1,0) -> 0 | CS34: =IF($AV34="Not Specified",1,0) -> 1 | CT34: =IF(OR(AND(U34>=2026,U34<=2030),AND(X34>=2026,X34<=2030)),1,"") | CU34: =AA34&" "&AS34 | CV34: =MAX(AA34,AS34) -> 0 | CW34: 0 | CX34: 0 | CY34: 0 | CZ34: 0 | DA34: 0 | DB34: 0 | DC34: 0 | DD34: 0 | DE34: 0 | DF34: 0 | DG34: 0 | DH34: 0 | DI34: 0 | DJ34: 0 | DK34: 0 | DL34: 0 | DM34: 0 | DN34: 0 | DO34: 0 | DP34: 0 | DQ34: 0 | DR34: 0 | DS34: 0 | DT34: N | DU34: 0 | DV34: N | DW34: G | DX34: U | DY34: 0 | DZ34: =Q34 -> N | EA34: =Z34 | EB34: =AP34 -> N | EC34: =AJ34 -> N | ED34: =AV34 -> Not Specified | EF34: =MAX(AS34,AA34) -> 0
A35: 32 | B35: 23 | C35: TotalEnergies | D35: Petroleum Refining | E35: Oil and gas | F35: France | G35: Europe | H35: $195,610 | I35: $15,758 | J35: -0.263 | K35: $285,487 | L35: 102887 | M35: 31 | N35: N | Q35: N | R35: N | AC35: Net zero | AD35: Net Zero | AE35: Yes | AF35: Yes | AG35: Partial | AH35: 1,2 | AJ35: N | AO35: C | AP35: Y | AQ35: 1,2 | AR35: By 2050, TotalEnergies would produce about 10‚ÄØMt CO‚ÇÇe/year of Scope‚ÄØ1 residual emissions, with methane emissions aiming towards zero (below 0.1‚ÄØMt‚ÄØCO‚ÇÇe/year); Scope‚ÄØ3 emissions totaling about 100‚ÄØMt‚ÄØCO‚ÇÇe/year. To get to net‚Äëzero together with society, TotalEnergies would contribute to ‚Äòeliminate‚Äô the equivalent of 100‚ÄØMt/year of CO‚ÇÇ generated by our customers by developing carbon utilization (CCU) and carbon capture and storage (CCS) solutions of approximately 100‚ÄØMt CO‚ÇÇe/year. | AS35: 2050 | AV35: Yes | AW35: Yes (nature-based removals e.g. Forestation, soil carbon enhancement) | AX35: No | AY35: N | BG35: =IF(AND($N35="Y",$P35<=2025),1,0) -> 0 | BH35: =IF(AND($N35="Y",AND($P35>2025,$P35<=2030)),1,0) -> 0 | BI35: =IF(AND($N35="Y",$P35>2030),1,0) -> 0 | BJ35: =MAX(BG35:BI35) -> 0 | BK35: =IF(AND($R35="Y",$U35<=2025),1,0) -> 0 | BL35: =IF(AND($R35="Y",AND($U35>2025,$U35<=2030)),1,0) -> 0 | BM35: =IF(AND($R35="Y",$U35>2030),1,0) -> 0 | BN35: =MAX(BK35:BM35) -> 0 | BO35: =IF(AND($Y35="Y",$AA35<=2025),1,0) -> 0 | BP35: =IF(AND($Y35="Y",AND($AA35>2025,$AA35<=2030)),1,0) -> 0 | BQ35: =IF(AND($Y35="Y",$AA35>2030),1,0) -> 0 | BR35: =IF(AND($AP35="Y",$AS35<=2025),1,0) -> 0 | BS35: =IF(AND($AP35="Y",AND($AS35>2025,$AS35<=2030)),1,0) -> 0 | BT35: =IF(AND($AP35="Y",$AS35>2030),1,0) -> 1 | BU35: =IF(AND(AL35<=2025,CF35=0,AJ35="Y"),1,0) -> 0 | BV35: =IF(AND(AL35>=2026,AL35<=2030,AJ35="Y",CF35=0),1,0) -> 0 | BW35: =IF(AND(AL35>=2031,CF35=0,AJ35="Y"),1,0) -> 0 | BX35: =IF(AND($AJ35="Y",$AL35<=2024),1,0) -> 0 | BY35: =IF(AND($AJ35="Y",AND($AL35>2024,$AL35<=2030)),1,0) -> 0 | BZ35: =IF(AND($AJ35="Y",$AL35>2030),1,0) -> 0 | CA35: =MAX(BX35:BZ35) -> 0 | CB35: =IF(AND(CF35=0,AJ35="Y"),1,0) -> 0 | CC35: =MAX($BO35,$BR35) -> 0 | CD35: =MAX($BP35,$BS35) -> 0 | CE35: =MAX($BQ35,$BT35) -> 1 | CF35: =MAX(CC35:CE35) -> 1 | CG35: =MAX($CF35,$CA35) -> 1 | CH35: =MAX(CF35,CB35) -> 1 | CI35: =IF(AND($AY35="Y",$BA35<=2024),1,0) -> 0 | CJ35: =IF(AND($AY35="Y",AND($BA35>2024,$BA35<=2030)),1,0) -> 0 | CK35: =IF(AND($AY35="Y",$BA35>2030),1,0) -> 0 | CL35: =SUM(CC35,BU35,BK35,BG35) -> 0 | CM35: =SUM(CD35,BV35,BL35,BH35) -> 0 | CN35: =SUM(CE35,BW35,BM35,BI35) -> 1 | CO35: =CF35+CB35+BN35+BJ35 -> 1 | CP35: =MAX(CH35,BN35,BJ35) -> 1 | CQ35: =IF($AV35="Yes",1,0) -> 1 | CR35: =IF($AV35="No",1,0) -> 0 | CS35: =IF($AV35="Not Specified",1,0) -> 0 | CT35: =IF(OR(AND(U35>=2026,U35<=2030),AND(X35>=2026,X35<=2030)),1,"") | CU35: =AA35&" "&AS35 -> 2050 | CV35: =MAX(AA35,AS35) -> 2050 | CW35: 0 | CX35: 1 | CY35: 0 | CZ35: 1 | DA35: 0 | DB35: 0 | DC35: 0 | DD35: 0 | DE35: 0 | DF35: 0 | DG35: 0 | DH35: 0 | DI35: 0 | DJ35: 0 | DK35: 0 | DL35: 0 | DM35: 1 | DN35: 1 | DO35: 1 | DP35: 1 | DQ35: 0 | DR35: 1 | DS35: 0 | DT35: N | DU35: 0 | DV35: I | DW35: C, V | DX35: Y | DY35: 0 | DZ35: =Q35 -> N | EA35: =Z35 | EB35: =AP35 -> Y | EC35: =AJ35 -> N | ED35: =AV35 -> Yes | EF35: =MAX(AS35,AA35) -> 2050
A36: 33 | B36: 25 | C36: BP | D36: Petroleum Refining | E36: Oil and gas | F36: Britain | G36: Europe | H36: $194,629 | I36: $381 | J36: -0.975 | K36: $282,228 | L36: 100500 | M36: 31 | N36: N | Q36: N | R36: N | AC36: Net zero | AD36: Net Zero | AE36: Yes | AF36: Yes | AG36: No | AH36: 1,2 | AJ36: N | AO36: C | AP36: Y | AQ36: 1,2 | AR36: Our aim is to reach net zero by 2050 or sooner for Scope 1 and 2 emissions within bp‚Äôs operational control (on a CO2e basis), including by maintaining ‚Äònear-zero‚Äô methane intensity across our operated producing assets, enabled by supportive government policies (see page 17 of bp's 2024 Sustainability Report). Removal of Scope 3 ambition We have retired our aim related to the estimated Scope 3 (category 11) emissions from the carbon in our upstream oil and gas production. The estimated Scope 3 emissions from the carbon in our upstream oil and gas production were 322MtCO2 in 2024 ‚Äì an 11% reduction relative to our 2019 baseline and a slight increase from 315MtCO2 in 2023. This increase was mainly associated with an increase in underlying production due to the ramp-up of major projects and higher asset performance (see page 24). https://web.archive.org/web/20250829133514/http://www.bp.com/content/dam/bp/business-sites/en/global/corporate/pdfs/sustainability/group-reports/bp-sustainability-report-2024.pdf | AS36: 2050 | AV36: Yes | AW36: Yes (nature-based and CCS-based removals) | AX36: No | AY36: N | BG36: =IF(AND($N36="Y",$P36<=2025),1,0) -> 0 | BH36: =IF(AND($N36="Y",AND($P36>2025,$P36<=2030)),1,0) -> 0 | BI36: =IF(AND($N36="Y",$P36>2030),1,0) -> 0 | BJ36: =MAX(BG36:BI36) -> 0 | BK36: =IF(AND($R36="Y",$U36<=2025),1,0) -> 0 | BL36: =IF(AND($R36="Y",AND($U36>2025,$U36<=2030)),1,0) -> 0 | BM36: =IF(AND($R36="Y",$U36>2030),1,0) -> 0 | BN36: =MAX(BK36:BM36) -> 0 | BO36: =IF(AND($Y36="Y",$AA36<=2025),1,0) -> 0 | BP36: =IF(AND($Y36="Y",AND($AA36>2025,$AA36<=2030)),1,0) -> 0 | BQ36: =IF(AND($Y36="Y",$AA36>2030),1,0) -> 0 | BR36: =IF(AND($AP36="Y",$AS36<=2025),1,0) -> 0 | BS36: =IF(AND($AP36="Y",AND($AS36>2025,$AS36<=2030)),1,0) -> 0 | BT36: =IF(AND($AP36="Y",$AS36>2030),1,0) -> 1 | BU36: =IF(AND(AL36<=2025,CF36=0,AJ36="Y"),1,0) -> 0 | BV36: =IF(AND(AL36>=2026,AL36<=2030,AJ36="Y",CF36=0),1,0) -> 0 | BW36: =IF(AND(AL36>=2031,CF36=0,AJ36="Y"),1,0) -> 0 | BX36: =IF(AND($AJ36="Y",$AL36<=2024),1,0) -> 0 | BY36: =IF(AND($AJ36="Y",AND($AL36>2024,$AL36<=2030)),1,0) -> 0 | BZ36: =IF(AND($AJ36="Y",$AL36>2030),1,0) -> 0 | CA36: =MAX(BX36:BZ36) -> 0 | CB36: =IF(AND(CF36=0,AJ36="Y"),1,0) -> 0 | CC36: =MAX($BO36,$BR36) -> 0 | CD36: =MAX($BP36,$BS36) -> 0 | CE36: =MAX($BQ36,$BT36) -> 1 | CF36: =MAX(CC36:CE36) -> 1 | CG36: =MAX($CF36,$CA36) -> 1 | CH36: =MAX(CF36,CB36) -> 1 | CI36: =IF(AND($AY36="Y",$BA36<=2024),1,0) -> 0 | CJ36: =IF(AND($AY36="Y",AND($BA36>2024,$BA36<=2030)),1,0) -> 0 | CK36: =IF(AND($AY36="Y",$BA36>2030),1,0) -> 0 | CL36: =SUM(CC36,BU36,BK36,BG36) -> 0 | CM36: =SUM(CD36,BV36,BL36,BH36) -> 0 | CN36: =SUM(CE36,BW36,BM36,BI36) -> 1 | CO36: =CF36+CB36+BN36+BJ36 -> 1 | CP36: =MAX(CH36,BN36,BJ36) -> 1 | CQ36: =IF($AV36="Yes",1,0) -> 1 | CR36: =IF($AV36="No",1,0) -> 0 | CS36: =IF($AV36="Not Specified",1,0) -> 0 | CT36: =IF(OR(AND(U36>=2026,U36<=2030),AND(X36>=2026,X36<=2030)),1,"") | CU36: =AA36&" "&AS36 -> 2050 | CV36: =MAX(AA36,AS36) -> 2050 | CW36: 0 | CX36: 0 | CY36: 0 | CZ36: 0 | DA36: 0 | DB36: 0 | DC36: 1 | DD36: 1 | DE36: 0 | DF36: 0 | DG36: 0 | DH36: 0 | DI36: 0 | DJ36: 0 | DK36: 0 | DL36: 0 | DM36: 1 | DN36: 0 | DO36: 1 | DP36: 1 | DQ36: 0 | DR36: 1 | DS36: 0 | DT36: N | DU36: 0 | DV36: V | DW36: N | DX36: 0 | DY36: Y | DZ36: =Q36 -> N | EA36: =Z36 | EB36: =AP36 -> Y | EC36: =AJ36 -> N | ED36: =AV36 -> Yes | EF36: =MAX(AS36,AA36) -> 2050
A37: 34 | B37: 38 | C37: Bank of America | D37: Megabanks | E37: Financial services | F37: U.S. | G37: North America | H37: $192,434 | I37: $27,132 | J37: 0.023 | K37: $3,261,519 | L37: 213193 | M37: 31 | N37: N | Q37: N | R37: N | AC37: Net zero | AD37: Net Zero | AE37: Yes | AF37: Yes | AG37: Yes | AH37: 1,2,3 | AJ37: N | AO37: C,V | AP37: Y | AQ37: 1,2,3 | AR37: ' Net Zero emissions before 2050 for our financing activities, operations and supply chain. ' p7 | AS37: 2050 | AV37: Yes | AW37: Not Specified | AX37: No | AY37: N | BG37: =IF(AND($N37="Y",$P37<=2025),1,0) -> 0 | BH37: =IF(AND($N37="Y",AND($P37>2025,$P37<=2030)),1,0) -> 0 | BI37: =IF(AND($N37="Y",$P37>2030),1,0) -> 0 | BJ37: =MAX(BG37:BI37) -> 0 | BK37: =IF(AND($R37="Y",$U37<=2025),1,0) -> 0 | BL37: =IF(AND($R37="Y",AND($U37>2025,$U37<=2030)),1,0) -> 0 | BM37: =IF(AND($R37="Y",$U37>2030),1,0) -> 0 | BN37: =MAX(BK37:BM37) -> 0 | BO37: =IF(AND($Y37="Y",$AA37<=2025),1,0) -> 0 | BP37: =IF(AND($Y37="Y",AND($AA37>2025,$AA37<=2030)),1,0) -> 0 | BQ37: =IF(AND($Y37="Y",$AA37>2030),1,0) -> 0 | BR37: =IF(AND($AP37="Y",$AS37<=2025),1,0) -> 0 | BS37: =IF(AND($AP37="Y",AND($AS37>2025,$AS37<=2030)),1,0) -> 0 | BT37: =IF(AND($AP37="Y",$AS37>2030),1,0) -> 1 | BU37: =IF(AND(AL37<=2025,CF37=0,AJ37="Y"),1,0) -> 0 | BV37: =IF(AND(AL37>=2026,AL37<=2030,AJ37="Y",CF37=0),1,0) -> 0 | BW37: =IF(AND(AL37>=2031,CF37=0,AJ37="Y"),1,0) -> 0 | BX37: =IF(AND($AJ37="Y",$AL37<=2024),1,0) -> 0 | BY37: =IF(AND($AJ37="Y",AND($AL37>2024,$AL37<=2030)),1,0) -> 0 | BZ37: =IF(AND($AJ37="Y",$AL37>2030),1,0) -> 0 | CA37: =MAX(BX37:BZ37) -> 0 | CB37: =IF(AND(CF37=0,AJ37="Y"),1,0) -> 0 | CC37: =MAX($BO37,$BR37) -> 0 | CD37: =MAX($BP37,$BS37) -> 0 | CE37: =MAX($BQ37,$BT37) -> 1 | CF37: =MAX(CC37:CE37) -> 1 | CG37: =MAX($CF37,$CA37) -> 1 | CH37: =MAX(CF37,CB37) -> 1 | CI37: =IF(AND($AY37="Y",$BA37<=2024),1,0) -> 0 | CJ37: =IF(AND($AY37="Y",AND($BA37>2024,$BA37<=2030)),1,0) -> 0 | CK37: =IF(AND($AY37="Y",$BA37>2030),1,0) -> 0 | CL37: =SUM(CC37,BU37,BK37,BG37) -> 0 | CM37: =SUM(CD37,BV37,BL37,BH37) -> 0 | CN37: =SUM(CE37,BW37,BM37,BI37) -> 1 | CO37: =CF37+CB37+BN37+BJ37 -> 1 | CP37: =MAX(CH37,BN37,BJ37) -> 1 | CQ37: =IF($AV37="Yes",1,0) -> 1 | CR37: =IF($AV37="No",1,0) -> 0 | CS37: =IF($AV37="Not Specified",1,0) -> 0 | CT37: =IF(OR(AND(U37>=2026,U37<=2030),AND(X37>=2026,X37<=2030)),1,"") | CU37: =AA37&" "&AS37 -> 2050 | CV37: =MAX(AA37,AS37) -> 2050 | CW37: 1 | CX37: 0 | CY37: 0 | CZ37: 1 | DA37: 0 | DB37: 1 | DC37: 0 | DD37: 1 | DE37: 0 | DF37: 0 | DG37: 0 | DH37: 0 | DI37: 0 | DJ37: 0 | DK37: 0 | DL37: 0 | DM37: 1 | DN37: 1 | DO37: 1 | DP37: 1 | DQ37: 0 | DR37: 1 | DS37: 1 | DT37: N | DU37: 0 | DV37: V, F | DW37: C | DX37: Y | DY37: U | DZ37: =Q37 -> N | EA37: =Z37 | EB37: =AP37 -> Y | EC37: =AJ37 -> N | ED37: =AV37 -> Yes | EF37: =MAX(AS37,AA37) -> 2050
A38: 35 | B38: 39 | C38: General Motors | D38: Motor Vehicles | E38: Automotive | F38: U.S. | G38: North America | H38: $187,442 | I38: $6,008 | J38: -0.407 | K38: $279,761 | L38: 162000 | M38: 31 | N38: Y | O38: 2016 | P38: 2035 | Q38: Y | R38: Y | S38: Targets set | T38: 1.5°C / Well-below 2°C | U38: 2035 | Y38: N | Z38: Commitment removed | AC38: Carbon neutral(ity) | AD38: Carbon Neutral | AE38: Yes | AF38: Yes | AG38: Partial | AH38: 1,2 | AI38: C | AJ38: Y | AK38: GM has announced plans to become carbon neutral in our global products and operations by 2040 (source: https://web.archive.org/web/20250807000628/https://www.gm.com/content/dam/company/docs/us/en/gmcom/company/GM_2023_SR.pdf) | AL38: 2040 | AP38: N | AV38: Yes | AW38: No | AX38: No | AY38: N | BG38: =IF(AND($N38="Y",$P38<=2025),1,0) -> 0 | BH38: =IF(AND($N38="Y",AND($P38>2025,$P38<=2030)),1,0) -> 0 | BI38: =IF(AND($N38="Y",$P38>2030),1,0) -> 1 | BJ38: =MAX(BG38:BI38) -> 1 | BK38: =IF(AND($R38="Y",$U38<=2025),1,0) -> 0 | BL38: =IF(AND($R38="Y",AND($U38>2025,$U38<=2030)),1,0) -> 0 | BM38: =IF(AND($R38="Y",$U38>2030),1,0) -> 1 | BN38: =MAX(BK38:BM38) -> 1 | BO38: =IF(AND($Y38="Y",$AA38<=2025),1,0) -> 0 | BP38: =IF(AND($Y38="Y",AND($AA38>2025,$AA38<=2030)),1,0) -> 0 | BQ38: =IF(AND($Y38="Y",$AA38>2030),1,0) -> 0 | BR38: =IF(AND($AP38="Y",$AS38<=2025),1,0) -> 0 | BS38: =IF(AND($AP38="Y",AND($AS38>2025,$AS38<=2030)),1,0) -> 0 | BT38: =IF(AND($AP38="Y",$AS38>2030),1,0) -> 0 | BU38: =IF(AND(AL38<=2025,CF38=0,AJ38="Y"),1,0) -> 0 | BV38: =IF(AND(AL38>=2026,AL38<=2030,AJ38="Y",CF38=0),1,0) -> 0 | BW38: =IF(AND(AL38>=2031,CF38=0,AJ38="Y"),1,0) -> 1 | BX38: =IF(AND($AJ38="Y",$AL38<=2024),1,0) -> 0 | BY38: =IF(AND($AJ38="Y",AND($AL38>2024,$AL38<=2030)),1,0) -> 0 | BZ38: =IF(AND($AJ38="Y",$AL38>2030),1,0) -> 1 | CA38: =MAX(BX38:BZ38) -> 1 | CB38: =IF(AND(CF38=0,AJ38="Y"),1,0) -> 1 | CC38: =MAX($BO38,$BR38) -> 0 | CD38: =MAX($BP38,$BS38) -> 0 | CE38: =MAX($BQ38,$BT38) -> 0 | CF38: =MAX(CC38:CE38) -> 0 | CG38: =MAX($CF38,$CA38) -> 1 | CH38: =MAX(CF38,CB38) -> 1 | CI38: =IF(AND($AY38="Y",$BA38<=2024),1,0) -> 0 | CJ38: =IF(AND($AY38="Y",AND($BA38>2024,$BA38<=2030)),1,0) -> 0 | CK38: =IF(AND($AY38="Y",$BA38>2030),1,0) -> 0 | CL38: =SUM(CC38,BU38,BK38,BG38) -> 0 | CM38: =SUM(CD38,BV38,BL38,BH38) -> 0 | CN38: =SUM(CE38,BW38,BM38,BI38) -> 3 | CO38: =CF38+CB38+BN38+BJ38 -> 3 | CP38: =MAX(CH38,BN38,BJ38) -> 1 | CQ38: =IF($AV38="Yes",1,0) -> 1 | CR38: =IF($AV38="No",1,0) -> 0 | CS38: =IF($AV38="Not Specified",1,0) -> 0 | CT38: =IF(OR(AND(U38>=2026,U38<=2030),AND(X38>=2026,X38<=2030)),1,"") | CU38: =AA38&" "&AS38 | CV38: =MAX(AA38,AS38) -> 0 | CW38: 0 | CX38: 0 | CY38: 1 | CZ38: 1 | DA38: 0 | DB38: 0 | DC38: 0 | DD38: 0 | DE38: 0 | DF38: 0 | DG38: 1 | DH38: 1 | DI38: 0 | DJ38: 0 | DK38: 1 | DL38: 1 | DM38: 1 | DN38: 0 | DO38: 1 | DP38: 0 | DQ38: 0 | DR38: 1 | DS38: 0 | DT38: Y | DU38: Yes | DV38: N | DW38: C | DX38: U | DY38: 0 | DZ38: =Q38 -> Y | EA38: =Z38 -> Commitment removed | EB38: =AP38 -> N | EC38: =AJ38 -> Y | ED38: =AV38 -> Yes | EF38: =MAX(AS38,AA38) -> 0
A39: 36 | B39: 36 | C39: Ford Motor | D39: Motor Vehicles | E39: Automotive | F39: U.S. | G39: North America | H39: $184,992 | I39: $5,879 | J39: 0.352 | K39: $285,196 | L39: 171000 | M39: 31 | N39: N | Q39: Y | R39: Y | S39: Targets set | T39: 1.5°C / Well-below 2°C | U39: 2035 | Y39: N | Z39: Commitment removed | AC39: Carbon neutral(ity) | AD39: Carbon Neutral | AE39: Yes | AF39: Yes | AG39: Yes | AH39: 1,2,3 | AI39: C,V | AJ39: Y | AK39: Achieve carbon neutrality by 2050 https://web.archive.org/web/20251010223020/https://corporate.ford.com//corporate/articles/sustainability/ford-expands-climate-change-goals/ | AL39: 2050 | AP39: N | AV39: Yes | AW39: Yes (unspecified) | AX39: No | AY39: N | BG39: =IF(AND($N39="Y",$P39<=2025),1,0) -> 0 | BH39: =IF(AND($N39="Y",AND($P39>2025,$P39<=2030)),1,0) -> 0 | BI39: =IF(AND($N39="Y",$P39>2030),1,0) -> 0 | BJ39: =MAX(BG39:BI39) -> 0 | BK39: =IF(AND($R39="Y",$U39<=2025),1,0) -> 0 | BL39: =IF(AND($R39="Y",AND($U39>2025,$U39<=2030)),1,0) -> 0 | BM39: =IF(AND($R39="Y",$U39>2030),1,0) -> 1 | BN39: =MAX(BK39:BM39) -> 1 | BO39: =IF(AND($Y39="Y",$AA39<=2025),1,0) -> 0 | BP39: =IF(AND($Y39="Y",AND($AA39>2025,$AA39<=2030)),1,0) -> 0 | BQ39: =IF(AND($Y39="Y",$AA39>2030),1,0) -> 0 | BR39: =IF(AND($AP39="Y",$AS39<=2025),1,0) -> 0 | BS39: =IF(AND($AP39="Y",AND($AS39>2025,$AS39<=2030)),1,0) -> 0 | BT39: =IF(AND($AP39="Y",$AS39>2030),1,0) -> 0 | BU39: =IF(AND(AL39<=2025,CF39=0,AJ39="Y"),1,0) -> 0 | BV39: =IF(AND(AL39>=2026,AL39<=2030,AJ39="Y",CF39=0),1,0) -> 0 | BW39: =IF(AND(AL39>=2031,CF39=0,AJ39="Y"),1,0) -> 1 | BX39: =IF(AND($AJ39="Y",$AL39<=2024),1,0) -> 0 | BY39: =IF(AND($AJ39="Y",AND($AL39>2024,$AL39<=2030)),1,0) -> 0 | BZ39: =IF(AND($AJ39="Y",$AL39>2030),1,0) -> 1 | CA39: =MAX(BX39:BZ39) -> 1 | CB39: =IF(AND(CF39=0,AJ39="Y"),1,0) -> 1 | CC39: =MAX($BO39,$BR39) -> 0 | CD39: =MAX($BP39,$BS39) -> 0 | CE39: =MAX($BQ39,$BT39) -> 0 | CF39: =MAX(CC39:CE39) -> 0 | CG39: =MAX($CF39,$CA39) -> 1 | CH39: =MAX(CF39,CB39) -> 1 | CI39: =IF(AND($AY39="Y",$BA39<=2024),1,0) -> 0 | CJ39: =IF(AND($AY39="Y",AND($BA39>2024,$BA39<=2030)),1,0) -> 0 | CK39: =IF(AND($AY39="Y",$BA39>2030),1,0) -> 0 | CL39: =SUM(CC39,BU39,BK39,BG39) -> 0 | CM39: =SUM(CD39,BV39,BL39,BH39) -> 0 | CN39: =SUM(CE39,BW39,BM39,BI39) -> 2 | CO39: =CF39+CB39+BN39+BJ39 -> 2 | CP39: =MAX(CH39,BN39,BJ39) -> 1 | CQ39: =IF($AV39="Yes",1,0) -> 1 | CR39: =IF($AV39="No",1,0) -> 0 | CS39: =IF($AV39="Not Specified",1,0) -> 0 | CT39: =IF(OR(AND(U39>=2026,U39<=2030),AND(X39>=2026,X39<=2030)),1,"") | CU39: =AA39&" "&AS39 | CV39: =MAX(AA39,AS39) -> 0 | CW39: 0 | CX39: 0 | CY39: 1 | CZ39: 1 | DA39: 0 | DB39: 0 | DC39: 0 | DD39: 0 | DE39: 0 | DF39: 0 | DG39: 1 | DH39: 1 | DI39: 0 | DJ39: 0 | DK39: 0 | DL39: 0 | DM39: 1 | DN39: 0 | DO39: 1 | DP39: 1 | DQ39: 0 | DR39: 1 | DS39: 0 | DT39: Y | DU39: Yes | DV39: N | DW39: V | DX39: Y | DY39: 0 | DZ39: =Q39 -> Y | EA39: =Z39 -> Commitment removed | EB39: =AP39 -> N | EC39: =AJ39 -> Y | ED39: =AV39 -> Yes | EF39: =MAX(AS39,AA39) -> 0
A40: 37 | B40: 40 | C40: Elevance Health | D40: Health Care: Insurance and Managed Care | E40: Health care and pharmaceuticals | F40: U.S. | G40: North America | H40: $177,011 | I40: $5,980 | J40: -0.001 | K40: $116,889 | L40: 103679 | M40: 24 | N40: Y | O40: 2019 | P40: 2025 | Q40: Y | R40: Y | S40: Targets set | T40: 1.5°C | U40: 2030 | AC40: Net zero | AD40: Net Zero | AE40: Yes | AF40: Yes | AG40: Partial | AH40: 1,2 | AJ40: N | AO40: C | AP40: Y | AQ40: 1,2 | AR40: Develop and implement a long-term transition plan for the general account in line with net zero by 2050. | AS40: 2050 | AV40: Yes | AW40: Not Specified | AX40: No | AY40: N | BG40: =IF(AND($N40="Y",$P40<=2025),1,0) -> 1 | BH40: =IF(AND($N40="Y",AND($P40>2025,$P40<=2030)),1,0) -> 0 | BI40: =IF(AND($N40="Y",$P40>2030),1,0) -> 0 | BJ40: =MAX(BG40:BI40) -> 1 | BK40: =IF(AND($R40="Y",$U40<=2025),1,0) -> 0 | BL40: =IF(AND($R40="Y",AND($U40>2025,$U40<=2030)),1,0) -> 1 | BM40: =IF(AND($R40="Y",$U40>2030),1,0) -> 0 | BN40: =MAX(BK40:BM40) -> 1 | BO40: =IF(AND($Y40="Y",$AA40<=2025),1,0) -> 0 | BP40: =IF(AND($Y40="Y",AND($AA40>2025,$AA40<=2030)),1,0) -> 0 | BQ40: =IF(AND($Y40="Y",$AA40>2030),1,0) -> 0 | BR40: =IF(AND($AP40="Y",$AS40<=2025),1,0) -> 0 | BS40: =IF(AND($AP40="Y",AND($AS40>2025,$AS40<=2030)),1,0) -> 0 | BT40: =IF(AND($AP40="Y",$AS40>2030),1,0) -> 1 | BU40: =IF(AND(AL40<=2025,CF40=0,AJ40="Y"),1,0) -> 0 | BV40: =IF(AND(AL40>=2026,AL40<=2030,AJ40="Y",CF40=0),1,0) -> 0 | BW40: =IF(AND(AL40>=2031,CF40=0,AJ40="Y"),1,0) -> 0 | BX40: =IF(AND($AJ40="Y",$AL40<=2024),1,0) -> 0 | BY40: =IF(AND($AJ40="Y",AND($AL40>2024,$AL40<=2030)),1,0) -> 0 | BZ40: =IF(AND($AJ40="Y",$AL40>2030),1,0) -> 0 | CA40: =MAX(BX40:BZ40) -> 0 | CB40: =IF(AND(CF40=0,AJ40="Y"),1,0) -> 0 | CC40: =MAX($BO40,$BR40) -> 0 | CD40: =MAX($BP40,$BS40) -> 0 | CE40: =MAX($BQ40,$BT40) -> 1 | CF40: =MAX(CC40:CE40) -> 1 | CG40: =MAX($CF40,$CA40) -> 1 | CH40: =MAX(CF40,CB40) -> 1 | CI40: =IF(AND($AY40="Y",$BA40<=2024),1,0) -> 0 | CJ40: =IF(AND($AY40="Y",AND($BA40>2024,$BA40<=2030)),1,0) -> 0 | CK40: =IF(AND($AY40="Y",$BA40>2030),1,0) -> 0 | CL40: =SUM(CC40,BU40,BK40,BG40) -> 1 | CM40: =SUM(CD40,BV40,BL40,BH40) -> 1 | CN40: =SUM(CE40,BW40,BM40,BI40) -> 1 | CO40: =CF40+CB40+BN40+BJ40 -> 3 | CP40: =MAX(CH40,BN40,BJ40) -> 1 | CQ40: =IF($AV40="Yes",1,0) -> 1 | CR40: =IF($AV40="No",1,0) -> 0 | CS40: =IF($AV40="Not Specified",1,0) -> 0 | CT40: =IF(OR(AND(U40>=2026,U40<=2030),AND(X40>=2026,X40<=2030)),1,"") -> 1 | CU40: =AA40&" "&AS40 -> 2050 | CV40: =MAX(AA40,AS40) -> 2050 | CW40: 1 | CX40: 0 | CY40: 0 | CZ40: 1 | DA40: 0 | DB40: 0 | DC40: 1 | DD40: 1 | DE40: 0 | DF40: 0 | DG40: 0 | DH40: 0 | DI40: 0 | DJ40: 1 | DK40: 0 | DL40: 1 | DM40: 1 | DN40: 1 | DO40: 1 | DP40: 0 | DQ40: 0 | DR40: 1 | DS40: 1 | DT40: N | DU40: 0 | DV40: C | DW40: C | DX40: U | DY40: U | DZ40: =Q40 -> Y | EA40: =Z40 | EB40: =AP40 -> Y | EC40: =AJ40 -> N | ED40: =AV40 -> Yes | EF40: =MAX(AS40,AA40) -> 2050
A41: 38 | B41: 37 | C41: Bank of China | D41: Banks: Commercial and Savings | E41: Financial services | F41: China | G41: Asia | H41: $176,142.5 | I41: $33,055.7 | J41: 0.009 | K41: $4,803,378.3 | L41: 312757 | M41: 31 | N41: N | Q41: N | R41: N | AC41: Carbon neutral(ity) | AD41: Carbon Neutral | AE41: Yes | AF41: Yes | AG41: Partial | AH41: 1,2 | AI41: C | AJ41: Y | AK41: BOC actively aligned with the national strategy of carbon peaking and carbon neutrality, striving to become the preferred bank for green finance services. (pg 4 AR) decarbonization targets of BOC's business strategy are in full alignment with China's goals of reaching carbon emissions peak before 2030, and achieving carbon neutrality before 2060. (pg 5 Bank of China Limited Transition Bonds Management Statement: https://web.archive.org/web/20251025060944/https://pic.bankofchina.com/bocappd/report/202310/P020231011315246686358.pdf#:~:text=,before%202030%2C%20and%20achieving | AL41: 2060 | AP41: N | AV41: Yes | AW41: Yes (CCS-based removals e.g. BECCS, DACCS) | AX41: No | AY41: N | BG41: =IF(AND($N41="Y",$P41<=2025),1,0) -> 0 | BH41: =IF(AND($N41="Y",AND($P41>2025,$P41<=2030)),1,0) -> 0 | BI41: =IF(AND($N41="Y",$P41>2030),1,0) -> 0 | BJ41: =MAX(BG41:BI41) -> 0 | BK41: =IF(AND($R41="Y",$U41<=2025),1,0) -> 0 | BL41: =IF(AND($R41="Y",AND($U41>2025,$U41<=2030)),1,0) -> 0 | BM41: =IF(AND($R41="Y",$U41>2030),1,0) -> 0 | BN41: =MAX(BK41:BM41) -> 0 | BO41: =IF(AND($Y41="Y",$AA41<=2025),1,0) -> 0 | BP41: =IF(AND($Y41="Y",AND($AA41>2025,$AA41<=2030)),1,0) -> 0 | BQ41: =IF(AND($Y41="Y",$AA41>2030),1,0) -> 0 | BR41: =IF(AND($AP41="Y",$AS41<=2025),1,0) -> 0 | BS41: =IF(AND($AP41="Y",AND($AS41>2025,$AS41<=2030)),1,0) -> 0 | BT41: =IF(AND($AP41="Y",$AS41>2030),1,0) -> 0 | BU41: =IF(AND(AL41<=2025,CF41=0,AJ41="Y"),1,0) -> 0 | BV41: =IF(AND(AL41>=2026,AL41<=2030,AJ41="Y",CF41=0),1,0) -> 0 | BW41: =IF(AND(AL41>=2031,CF41=0,AJ41="Y"),1,0) -> 1 | BX41: =IF(AND($AJ41="Y",$AL41<=2024),1,0) -> 0 | BY41: =IF(AND($AJ41="Y",AND($AL41>2024,$AL41<=2030)),1,0) -> 0 | BZ41: =IF(AND($AJ41="Y",$AL41>2030),1,0) -> 1 | CA41: =MAX(BX41:BZ41) -> 1 | CB41: =IF(AND(CF41=0,AJ41="Y"),1,0) -> 1 | CC41: =MAX($BO41,$BR41) -> 0 | CD41: =MAX($BP41,$BS41) -> 0 | CE41: =MAX($BQ41,$BT41) -> 0 | CF41: =MAX(CC41:CE41) -> 0 | CG41: =MAX($CF41,$CA41) -> 1 | CH41: =MAX(CF41,CB41) -> 1 | CI41: =IF(AND($AY41="Y",$BA41<=2024),1,0) -> 0 | CJ41: =IF(AND($AY41="Y",AND($BA41>2024,$BA41<=2030)),1,0) -> 0 | CK41: =IF(AND($AY41="Y",$BA41>2030),1,0) -> 0 | CL41: =SUM(CC41,BU41,BK41,BG41) -> 0 | CM41: =SUM(CD41,BV41,BL41,BH41) -> 0 | CN41: =SUM(CE41,BW41,BM41,BI41) -> 1 | CO41: =CF41+CB41+BN41+BJ41 -> 1 | CP41: =MAX(CH41,BN41,BJ41) -> 1 | CQ41: =IF($AV41="Yes",1,0) -> 1 | CR41: =IF($AV41="No",1,0) -> 0 | CS41: =IF($AV41="Not Specified",1,0) -> 0 | CT41: =IF(OR(AND(U41>=2026,U41<=2030),AND(X41>=2026,X41<=2030)),1,"") | CU41: =AA41&" "&AS41 | CV41: =MAX(AA41,AS41) -> 0 | CW41: 0 | CX41: 1 | CY41: 0 | CZ41: 1 | DA41: 0 | DB41: 0 | DC41: 0 | DD41: 0 | DE41: 0 | DF41: 0 | DG41: 0 | DH41: 0 | DI41: 0 | DJ41: 0 | DK41: 0 | DL41: 0 | DM41: 1 | DN41: 1 | DO41: 1 | DP41: 0 | DQ41: 0 | DR41: 1 | DS41: 0 | DT41: N | DU41: 0 | DV41: N | DW41: C | DX41: U | DY41: 0 | DZ41: =Q41 -> N | EA41: =Z41 | EB41: =AP41 -> N | EC41: =AJ41 -> Y | ED41: =AV41 -> Yes | EF41: =MAX(AS41,AA41) -> 0
A42: 39 | B42: 45 | C42: Citigroup | D42: Megabanks | E42: Financial services | F42: U.S. | G42: North America | H42: $170,757 | I42: $12,682 | J42: 0.374 | K42: $2,352,945 | L42: 227855 | M42: 31 | N42: N | Q42: N | R42: N | AC42: Net zero | AD42: Net Zero | AE42: Yes | AF42: Yes | AG42: Yes | AH42: 1,2,3 | AJ42: N | AO42: C,V | AP42: Y | AQ42: 1,2,3 | AR42: In March 2021, Citi made a commitment to reach net zero greenhouse gas emissions by 2050, including our own operations by 2030. https://www.citigroup.com/global/our-impact/sustainability/net-zero | AS42: 2050 | AV42: Yes | AW42: Not Specified | AX42: No | AY42: N | BG42: =IF(AND($N42="Y",$P42<=2025),1,0) -> 0 | BH42: =IF(AND($N42="Y",AND($P42>2025,$P42<=2030)),1,0) -> 0 | BI42: =IF(AND($N42="Y",$P42>2030),1,0) -> 0 | BJ42: =MAX(BG42:BI42) -> 0 | BK42: =IF(AND($R42="Y",$U42<=2025),1,0) -> 0 | BL42: =IF(AND($R42="Y",AND($U42>2025,$U42<=2030)),1,0) -> 0 | BM42: =IF(AND($R42="Y",$U42>2030),1,0) -> 0 | BN42: =MAX(BK42:BM42) -> 0 | BO42: =IF(AND($Y42="Y",$AA42<=2025),1,0) -> 0 | BP42: =IF(AND($Y42="Y",AND($AA42>2025,$AA42<=2030)),1,0) -> 0 | BQ42: =IF(AND($Y42="Y",$AA42>2030),1,0) -> 0 | BR42: =IF(AND($AP42="Y",$AS42<=2025),1,0) -> 0 | BS42: =IF(AND($AP42="Y",AND($AS42>2025,$AS42<=2030)),1,0) -> 0 | BT42: =IF(AND($AP42="Y",$AS42>2030),1,0) -> 1 | BU42: =IF(AND(AL42<=2025,CF42=0,AJ42="Y"),1,0) -> 0 | BV42: =IF(AND(AL42>=2026,AL42<=2030,AJ42="Y",CF42=0),1,0) -> 0 | BW42: =IF(AND(AL42>=2031,CF42=0,AJ42="Y"),1,0) -> 0 | BX42: =IF(AND($AJ42="Y",$AL42<=2024),1,0) -> 0 | BY42: =IF(AND($AJ42="Y",AND($AL42>2024,$AL42<=2030)),1,0) -> 0 | BZ42: =IF(AND($AJ42="Y",$AL42>2030),1,0) -> 0 | CA42: =MAX(BX42:BZ42) -> 0 | CB42: =IF(AND(CF42=0,AJ42="Y"),1,0) -> 0 | CC42: =MAX($BO42,$BR42) -> 0 | CD42: =MAX($BP42,$BS42) -> 0 | CE42: =MAX($BQ42,$BT42) -> 1 | CF42: =MAX(CC42:CE42) -> 1 | CG42: =MAX($CF42,$CA42) -> 1 | CH42: =MAX(CF42,CB42) -> 1 | CI42: =IF(AND($AY42="Y",$BA42<=2024),1,0) -> 0 | CJ42: =IF(AND($AY42="Y",AND($BA42>2024,$BA42<=2030)),1,0) -> 0 | CK42: =IF(AND($AY42="Y",$BA42>2030),1,0) -> 0 | CL42: =SUM(CC42,BU42,BK42,BG42) -> 0 | CM42: =SUM(CD42,BV42,BL42,BH42) -> 0 | CN42: =SUM(CE42,BW42,BM42,BI42) -> 1 | CO42: =CF42+CB42+BN42+BJ42 -> 1 | CP42: =MAX(CH42,BN42,BJ42) -> 1 | CQ42: =IF($AV42="Yes",1,0) -> 1 | CR42: =IF($AV42="No",1,0) -> 0 | CS42: =IF($AV42="Not Specified",1,0) -> 0 | CT42: =IF(OR(AND(U42>=2026,U42<=2030),AND(X42>=2026,X42<=2030)),1,"") | CU42: =AA42&" "&AS42 -> 2050 | CV42: =MAX(AA42,AS42) -> 2050 | CW42: 0 | CX42: 0 | CY42: 0 | CZ42: 0 | DA42: 0 | DB42: 1 | DC42: 0 | DD42: 1 | DE42: 0 | DF42: 0 | DG42: 0 | DH42: 0 | DI42: 0 | DJ42: 0 | DK42: 0 | DL42: 0 | DM42: 1 | DN42: 1 | DO42: 1 | DP42: 1 | DQ42: 0 | DR42: 1 | DS42: 0 | DT42: N | DU42: 0 | DV42: C, F | DW42: N | DX42: 0 | DY42: Y | DZ42: =Q42 -> N | EA42: =Z42 | EB42: =AP42 -> Y | EC42: =AJ42 -> N | ED42: =AV42 -> Yes | EF42: =MAX(AS42,AA42) -> 2050
A43: 40 | B43: 28 | C43: Stellantis | D43: Motor Vehicles & Parts | E43: Automotive | F43: Netherlands | G43: Europe | H43: $169,652.9 | I43: $5,918.7 | J43: -0.706 | K43: $214,958.6 | L43: 248243 | M43: 20 | N43: N | Q43: N | R43: N | AC43: Net zero | AD43: Net Zero | AE43: Yes | AF43: Yes | AG43: Yes | AH43: 1,2,3 | AJ43: N | AO43: C,V | AP43: Y | AQ43: 1,2,3 | AR43: "Our strategic plan currently sets a target to reduce absolute greenhouse gas emissions (scopes1, 2 and 3) by 30% by 2030 vs. our 2021 baseline, and achieve carbon net zero by 2038 with single digit percentage compensation of the remaining emissions" | AS43: 2038 | AV43: Yes | AW43: No | AX43: No | AY43: N | BG43: =IF(AND($N43="Y",$P43<=2025),1,0) -> 0 | BH43: =IF(AND($N43="Y",AND($P43>2025,$P43<=2030)),1,0) -> 0 | BI43: =IF(AND($N43="Y",$P43>2030),1,0) -> 0 | BJ43: =MAX(BG43:BI43) -> 0 | BK43: =IF(AND($R43="Y",$U43<=2025),1,0) -> 0 | BL43: =IF(AND($R43="Y",AND($U43>2025,$U43<=2030)),1,0) -> 0 | BM43: =IF(AND($R43="Y",$U43>2030),1,0) -> 0 | BN43: =MAX(BK43:BM43) -> 0 | BO43: =IF(AND($Y43="Y",$AA43<=2025),1,0) -> 0 | BP43: =IF(AND($Y43="Y",AND($AA43>2025,$AA43<=2030)),1,0) -> 0 | BQ43: =IF(AND($Y43="Y",$AA43>2030),1,0) -> 0 | BR43: =IF(AND($AP43="Y",$AS43<=2025),1,0) -> 0 | BS43: =IF(AND($AP43="Y",AND($AS43>2025,$AS43<=2030)),1,0) -> 0 | BT43: =IF(AND($AP43="Y",$AS43>2030),1,0) -> 1 | BU43: =IF(AND(AL43<=2025,CF43=0,AJ43="Y"),1,0) -> 0 | BV43: =IF(AND(AL43>=2026,AL43<=2030,AJ43="Y",CF43=0),1,0) -> 0 | BW43: =IF(AND(AL43>=2031,CF43=0,AJ43="Y"),1,0) -> 0 | BX43: =IF(AND($AJ43="Y",$AL43<=2024),1,0) -> 0 | BY43: =IF(AND($AJ43="Y",AND($AL43>2024,$AL43<=2030)),1,0) -> 0 | BZ43: =IF(AND($AJ43="Y",$AL43>2030),1,0) -> 0 | CA43: =MAX(BX43:BZ43) -> 0 | CB43: =IF(AND(CF43=0,AJ43="Y"),1,0) -> 0 | CC43: =MAX($BO43,$BR43) -> 0 | CD43: =MAX($BP43,$BS43) -> 0 | CE43: =MAX($BQ43,$BT43) -> 1 | CF43: =MAX(CC43:CE43) -> 1 | CG43: =MAX($CF43,$CA43) -> 1 | CH43: =MAX(CF43,CB43) -> 1 | CI43: =IF(AND($AY43="Y",$BA43<=2024),1,0) -> 0 | CJ43: =IF(AND($AY43="Y",AND($BA43>2024,$BA43<=2030)),1,0) -> 0 | CK43: =IF(AND($AY43="Y",$BA43>2030),1,0) -> 0 | CL43: =SUM(CC43,BU43,BK43,BG43) -> 0 | CM43: =SUM(CD43,BV43,BL43,BH43) -> 0 | CN43: =SUM(CE43,BW43,BM43,BI43) -> 1 | CO43: =CF43+CB43+BN43+BJ43 -> 1 | CP43: =MAX(CH43,BN43,BJ43) -> 1 | CQ43: =IF($AV43="Yes",1,0) -> 1 | CR43: =IF($AV43="No",1,0) -> 0 | CS43: =IF($AV43="Not Specified",1,0) -> 0 | CT43: =IF(OR(AND(U43>=2026,U43<=2030),AND(X43>=2026,X43<=2030)),1,"") | CU43: =AA43&" "&AS43 -> 2038 | CV43: =MAX(AA43,AS43) -> 2038 | CW43: 0 | CX43: 0 | CY43: 0 | CZ43: 0 | DA43: 0 | DB43: 0 | DC43: 1 | DD43: 1 | DE43: 0 | DF43: 0 | DG43: 0 | DH43: 0 | DI43: 0 | DJ43: 0 | DK43: 0 | DL43: 0 | DM43: 1 | DN43: 0 | DO43: 1 | DP43: 1 | DQ43: 0 | DR43: 1 | DS43: 0 | DT43: N | DU43: 0 | DV43: V | DW43: N | DX43: 0 | DY43: Y | DZ43: =Q43 -> N | EA43: =Z43 | EB43: =AP43 -> Y | EC43: =AJ43 -> N | ED43: =AV43 -> Yes | EF43: =MAX(AS43,AA43) -> 2038
A44: 41 | B44: 66 | C44: Meta Platforms | D44: Internet Services and Retailing | E44: Retail | F44: U.S. | G44: North America | H44: $164,501 | I44: $62,360 | J44: 0.595 | K44: $276,054 | L44: 74067 | M44: 9 | N44: N | Q44: Y | R44: Y | S44: Targets set | T44: 1.5°C | U44: 2031 | Y44: N | Z44: Committed | AC44: Net zero | AD44: Net Zero | AE44: Yes | AF44: Yes | AG44: Yes | AH44: 1,2,3 | AJ44: N | AO44: C,V | AP44: Y | AQ44: 1,2,3 | AR44: Since 2020, we have maintained net zero emissions across our global operations. We have publicly committed to achieving net zero emissions across our value chain and becoming water positive in 2030. (pg 17) | AS44: 2030 | AV44: Yes | AW44: Yes (nature-based and CCS-based removals) | AX44: Yes | AY44: N | BG44: =IF(AND($N44="Y",$P44<=2025),1,0) -> 0 | BH44: =IF(AND($N44="Y",AND($P44>2025,$P44<=2030)),1,0) -> 0 | BI44: =IF(AND($N44="Y",$P44>2030),1,0) -> 0 | BJ44: =MAX(BG44:BI44) -> 0 | BK44: =IF(AND($R44="Y",$U44<=2025),1,0) -> 0 | BL44: =IF(AND($R44="Y",AND($U44>2025,$U44<=2030)),1,0) -> 0 | BM44: =IF(AND($R44="Y",$U44>2030),1,0) -> 1 | BN44: =MAX(BK44:BM44) -> 1 | BO44: =IF(AND($Y44="Y",$AA44<=2025),1,0) -> 0 | BP44: =IF(AND($Y44="Y",AND($AA44>2025,$AA44<=2030)),1,0) -> 0 | BQ44: =IF(AND($Y44="Y",$AA44>2030),1,0) -> 0 | BR44: =IF(AND($AP44="Y",$AS44<=2025),1,0) -> 0 | BS44: =IF(AND($AP44="Y",AND($AS44>2025,$AS44<=2030)),1,0) -> 1 | BT44: =IF(AND($AP44="Y",$AS44>2030),1,0) -> 0 | BU44: =IF(AND(AL44<=2025,CF44=0,AJ44="Y"),1,0) -> 0 | BV44: =IF(AND(AL44>=2026,AL44<=2030,AJ44="Y",CF44=0),1,0) -> 0 | BW44: =IF(AND(AL44>=2031,CF44=0,AJ44="Y"),1,0) -> 0 | BX44: =IF(AND($AJ44="Y",$AL44<=2024),1,0) -> 0 | BY44: =IF(AND($AJ44="Y",AND($AL44>2024,$AL44<=2030)),1,0) -> 0 | BZ44: =IF(AND($AJ44="Y",$AL44>2030),1,0) -> 0 | CA44: =MAX(BX44:BZ44) -> 0 | CB44: =IF(AND(CF44=0,AJ44="Y"),1,0) -> 0 | CC44: =MAX($BO44,$BR44) -> 0 | CD44: =MAX($BP44,$BS44) -> 1 | CE44: =MAX($BQ44,$BT44) -> 0 | CF44: =MAX(CC44:CE44) -> 1 | CG44: =MAX($CF44,$CA44) -> 1 | CH44: =MAX(CF44,CB44) -> 1 | CI44: =IF(AND($AY44="Y",$BA44<=2024),1,0) -> 0 | CJ44: =IF(AND($AY44="Y",AND($BA44>2024,$BA44<=2030)),1,0) -> 0 | CK44: =IF(AND($AY44="Y",$BA44>2030),1,0) -> 0 | CL44: =SUM(CC44,BU44,BK44,BG44) -> 0 | CM44: =SUM(CD44,BV44,BL44,BH44) -> 1 | CN44: =SUM(CE44,BW44,BM44,BI44) -> 1 | CO44: =CF44+CB44+BN44+BJ44 -> 2 | CP44: =MAX(CH44,BN44,BJ44) -> 1 | CQ44: =IF($AV44="Yes",1,0) -> 1 | CR44: =IF($AV44="No",1,0) -> 0 | CS44: =IF($AV44="Not Specified",1,0) -> 0 | CT44: =IF(OR(AND(U44>=2026,U44<=2030),AND(X44>=2026,X44<=2030)),1,"") | CU44: =AA44&" "&AS44 -> 2030 | CV44: =MAX(AA44,AS44) -> 2030 | CW44: 0 | CX44: 0 | CY44: 0 | CZ44: 0 | DA44: 1 | DB44: 0 | DC44: 0 | DD44: 1 | DE44: 0 | DF44: 0 | DG44: 1 | DH44: 1 | DI44: 1 | DJ44: 0 | DK44: 0 | DL44: 1 | DM44: 1 | DN44: 1 | DO44: 1 | DP44: 1 | DQ44: 0 | DR44: 1 | DS44: 1 | DT44: Y | DU44: Yes | DV44: C, V | DW44: N | DX44: 0 | DY44: Y | DZ44: =Q44 -> Y | EA44: =Z44 -> Committed | EB44: =AP44 -> Y | EC44: =AJ44 -> N | ED44: =AV44 -> Yes | EF44: =MAX(AS44,AA44) -> 2030
A45: 42 | B45: 46 | C45: Centene | D45: Health Care: Insurance and Managed Care | E45: Health care and pharmaceuticals | F45: U.S. | G45: North America | H45: $163,071 | I45: $3,305 | J45: 0.223 | K45: $82,445 | L45: 60500 | M45: 10 | N45: N | Q45: N | R45: N | AC45: No target | AD45: No Target | AE45: Not Specified | AF45: Not Specified | AG45: Not Specified | AJ45: N | AM45: https://www.centene.com/why-were-different/corporate-sustainability/healthy-environment/environmental-sustainability.html | AN45: no usefull information | AP45: N | AV45: Not Specified | AW45: Not Specified | AX45: No | AY45: N | BG45: =IF(AND($N45="Y",$P45<=2025),1,0) -> 0 | BH45: =IF(AND($N45="Y",AND($P45>2025,$P45<=2030)),1,0) -> 0 | BI45: =IF(AND($N45="Y",$P45>2030),1,0) -> 0 | BJ45: =MAX(BG45:BI45) -> 0 | BK45: =IF(AND($R45="Y",$U45<=2025),1,0) -> 0 | BL45: =IF(AND($R45="Y",AND($U45>2025,$U45<=2030)),1,0) -> 0 | BM45: =IF(AND($R45="Y",$U45>2030),1,0) -> 0 | BN45: =MAX(BK45:BM45) -> 0 | BO45: =IF(AND($Y45="Y",$AA45<=2025),1,0) -> 0 | BP45: =IF(AND($Y45="Y",AND($AA45>2025,$AA45<=2030)),1,0) -> 0 | BQ45: =IF(AND($Y45="Y",$AA45>2030),1,0) -> 0 | BR45: =IF(AND($AP45="Y",$AS45<=2025),1,0) -> 0 | BS45: =IF(AND($AP45="Y",AND($AS45>2025,$AS45<=2030)),1,0) -> 0 | BT45: =IF(AND($AP45="Y",$AS45>2030),1,0) -> 0 | BU45: =IF(AND(AL45<=2025,CF45=0,AJ45="Y"),1,0) -> 0 | BV45: =IF(AND(AL45>=2026,AL45<=2030,AJ45="Y",CF45=0),1,0) -> 0 | BW45: =IF(AND(AL45>=2031,CF45=0,AJ45="Y"),1,0) -> 0 | BX45: =IF(AND($AJ45="Y",$AL45<=2024),1,0) -> 0 | BY45: =IF(AND($AJ45="Y",AND($AL45>2024,$AL45<=2030)),1,0) -> 0 | BZ45: =IF(AND($AJ45="Y",$AL45>2030),1,0) -> 0 | CA45: =MAX(BX45:BZ45) -> 0 | CB45: =IF(AND(CF45=0,AJ45="Y"),1,0) -> 0 | CC45: =MAX($BO45,$BR45) -> 0 | CD45: =MAX($BP45,$BS45) -> 0 | CE45: =MAX($BQ45,$BT45) -> 0 | CF45: =MAX(CC45:CE45) -> 0 | CG45: =MAX($CF45,$CA45) -> 0 | CH45: =MAX(CF45,CB45) -> 0 | CI45: =IF(AND($AY45="Y",$BA45<=2024),1,0) -> 0 | CJ45: =IF(AND($AY45="Y",AND($BA45>2024,$BA45<=2030)),1,0) -> 0 | CK45: =IF(AND($AY45="Y",$BA45>2030),1,0) -> 0 | CL45: =SUM(CC45,BU45,BK45,BG45) -> 0 | CM45: =SUM(CD45,BV45,BL45,BH45) -> 0 | CN45: =SUM(CE45,BW45,BM45,BI45) -> 0 | CO45: =CF45+CB45+BN45+BJ45 -> 0 | CP45: =MAX(CH45,BN45,BJ45) -> 0 | CQ45: =IF($AV45="Yes",1,0) -> 0 | CR45: =IF($AV45="No",1,0) -> 0 | CS45: =IF($AV45="Not Specified",1,0) -> 1 | CT45: =IF(OR(AND(U45>=2026,U45<=2030),AND(X45>=2026,X45<=2030)),1,"") | CU45: =AA45&" "&AS45 | CV45: =MAX(AA45,AS45) -> 0 | CW45: 0 | CX45: 0 | CY45: 0 | CZ45: 0 | DA45: 0 | DB45: 0 | DC45: 0 | DD45: 0 | DE45: 0 | DF45: 0 | DG45: 0 | DH45: 0 | DI45: 0 | DJ45: 0 | DK45: 0 | DL45: 0 | DM45: 0 | DN45: 0 | DO45: 0 | DP45: 0 | DQ45: 0 | DR45: 0 | DS45: 0 | DT45: N | DU45: 0 | DV45: N | DW45: N | DX45: 0 | DY45: 0 | DZ45: =Q45 -> N | EA45: =Z45 | EB45: =AP45 -> N | EC45: =AJ45 -> N | ED45: =AV45 -> Not Specified | EF45: =MAX(AS45,AA45) -> 0
A46: 43 | B46: 35 | C46: China Railway Engineering Group | D46: Engineering & Construction | E46: Engineering and construction | F46: China | G46: Asia | H46: $161,336.5 | I46: $1,810.5 | J46: -0.159 | K46: $309,912.3 | L46: 313067 | M46: 11 | N46: N | Q46: N | R46: N | AJ46: N | AP46: N | AV46: Not Specified | AY46: N | BG46: =IF(AND($N46="Y",$P46<=2025),1,0) -> 0 | BH46: =IF(AND($N46="Y",AND($P46>2025,$P46<=2030)),1,0) -> 0 | BI46: =IF(AND($N46="Y",$P46>2030),1,0) -> 0 | BJ46: =MAX(BG46:BI46) -> 0 | BK46: =IF(AND($R46="Y",$U46<=2025),1,0) -> 0 | BL46: =IF(AND($R46="Y",AND($U46>2025,$U46<=2030)),1,0) -> 0 | BM46: =IF(AND($R46="Y",$U46>2030),1,0) -> 0 | BN46: =MAX(BK46:BM46) -> 0 | BO46: =IF(AND($Y46="Y",$AA46<=2025),1,0) -> 0 | BP46: =IF(AND($Y46="Y",AND($AA46>2025,$AA46<=2030)),1,0) -> 0 | BQ46: =IF(AND($Y46="Y",$AA46>2030),1,0) -> 0 | BR46: =IF(AND($AP46="Y",$AS46<=2025),1,0) -> 0 | BS46: =IF(AND($AP46="Y",AND($AS46>2025,$AS46<=2030)),1,0) -> 0 | BT46: =IF(AND($AP46="Y",$AS46>2030),1,0) -> 0 | BU46: =IF(AND(AL46<=2025,CF46=0,AJ46="Y"),1,0) -> 0 | BV46: =IF(AND(AL46>=2026,AL46<=2030,AJ46="Y",CF46=0),1,0) -> 0 | BW46: =IF(AND(AL46>=2031,CF46=0,AJ46="Y"),1,0) -> 0 | BX46: =IF(AND($AJ46="Y",$AL46<=2024),1,0) -> 0 | BY46: =IF(AND($AJ46="Y",AND($AL46>2024,$AL46<=2030)),1,0) -> 0 | BZ46: =IF(AND($AJ46="Y",$AL46>2030),1,0) -> 0 | CA46: =MAX(BX46:BZ46) -> 0 | CB46: =IF(AND(CF46=0,AJ46="Y"),1,0) -> 0 | CC46: =MAX($BO46,$BR46) -> 0 | CD46: =MAX($BP46,$BS46) -> 0 | CE46: =MAX($BQ46,$BT46) -> 0 | CF46: =MAX(CC46:CE46) -> 0 | CG46: =MAX($CF46,$CA46) -> 0 | CH46: =MAX(CF46,CB46) -> 0 | CI46: =IF(AND($AY46="Y",$BA46<=2024),1,0) -> 0 | CJ46: =IF(AND($AY46="Y",AND($BA46>2024,$BA46<=2030)),1,0) -> 0 | CK46: =IF(AND($AY46="Y",$BA46>2030),1,0) -> 0 | CL46: =SUM(CC46,BU46,BK46,BG46) -> 0 | CM46: =SUM(CD46,BV46,BL46,BH46) -> 0 | CN46: =SUM(CE46,BW46,BM46,BI46) -> 0 | CO46: =CF46+CB46+BN46+BJ46 -> 0 | CP46: =MAX(CH46,BN46,BJ46) -> 0 | CQ46: =IF($AV46="Yes",1,0) -> 0 | CR46: =IF($AV46="No",1,0) -> 0 | CS46: =IF($AV46="Not Specified",1,0) -> 1 | CT46: =IF(OR(AND(U46>=2026,U46<=2030),AND(X46>=2026,X46<=2030)),1,"") | CU46: =AA46&" "&AS46 | CV46: =MAX(AA46,AS46) -> 0 | CW46: 0 | CX46: 0 | CY46: 0 | CZ46: 0 | DA46: 0 | DB46: 0 | DC46: 0 | DD46: 0 | DE46: 0 | DF46: 0 | DG46: 0 | DH46: 0 | DI46: 0 | DJ46: 0 | DK46: 0 | DL46: 0 | DM46: 0 | DN46: 0 | DO46: 0 | DP46: 0 | DQ46: 0 | DR46: 0 | DS46: 0 | DT46: N | DU46: 0 | DV46: N | DW46: G | DX46: U | DY46: 0 | DZ46: =Q46 -> N | EA46: =Z46 | EB46: =AP46 -> N | EC46: =AJ46 -> N | ED46: =AV46 -> Not Specified | EF46: =MAX(AS46,AA46) -> 0
A47: 44 | B47: 47 | C47: JD.com | D47: Internet and Direct Marketing Retail | E47: Retail | F47: China | G47: Asia | H47: $161,055.4 | I47: $5,748.2 | J47: 0.684 | K47: $95,657.7 | L47: 570895 | M47: 10 | N47: N | Q47: N | R47: N | AC47: No target | AD47: No Target | AE47: Not Specified | AF47: Not Specified | AG47: Not Specified | AI47: G | AJ47: N | AL47: 2060 | AP47: N | AV47: Not Specified | AW47: Not Specified | AX47: No | AY47: N | BB47: 2024_jd.com_inc._environmental_social_and_governance_report.pdf | BG47: =IF(AND($N47="Y",$P47<=2025),1,0) -> 0 | BH47: =IF(AND($N47="Y",AND($P47>2025,$P47<=2030)),1,0) -> 0 | BI47: =IF(AND($N47="Y",$P47>2030),1,0) -> 0 | BJ47: =MAX(BG47:BI47) -> 0 | BK47: =IF(AND($R47="Y",$U47<=2025),1,0) -> 0 | BL47: =IF(AND($R47="Y",AND($U47>2025,$U47<=2030)),1,0) -> 0 | BM47: =IF(AND($R47="Y",$U47>2030),1,0) -> 0 | BN47: =MAX(BK47:BM47) -> 0 | BO47: =IF(AND($Y47="Y",$AA47<=2025),1,0) -> 0 | BP47: =IF(AND($Y47="Y",AND($AA47>2025,$AA47<=2030)),1,0) -> 0 | BQ47: =IF(AND($Y47="Y",$AA47>2030),1,0) -> 0 | BR47: =IF(AND($AP47="Y",$AS47<=2025),1,0) -> 0 | BS47: =IF(AND($AP47="Y",AND($AS47>2025,$AS47<=2030)),1,0) -> 0 | BT47: =IF(AND($AP47="Y",$AS47>2030),1,0) -> 0 | BU47: =IF(AND(AL47<=2025,CF47=0,AJ47="Y"),1,0) -> 0 | BV47: =IF(AND(AL47>=2026,AL47<=2030,AJ47="Y",CF47=0),1,0) -> 0 | BW47: =IF(AND(AL47>=2031,CF47=0,AJ47="Y"),1,0) -> 0 | BX47: =IF(AND($AJ47="Y",$AL47<=2024),1,0) -> 0 | BY47: =IF(AND($AJ47="Y",AND($AL47>2024,$AL47<=2030)),1,0) -> 0 | BZ47: =IF(AND($AJ47="Y",$AL47>2030),1,0) -> 0 | CA47: =MAX(BX47:BZ47) -> 0 | CB47: =IF(AND(CF47=0,AJ47="Y"),1,0) -> 0 | CC47: =MAX($BO47,$BR47) -> 0 | CD47: =MAX($BP47,$BS47) -> 0 | CE47: =MAX($BQ47,$BT47) -> 0 | CF47: =MAX(CC47:CE47) -> 0 | CG47: =MAX($CF47,$CA47) -> 0 | CH47: =MAX(CF47,CB47) -> 0 | CI47: =IF(AND($AY47="Y",$BA47<=2024),1,0) -> 0 | CJ47: =IF(AND($AY47="Y",AND($BA47>2024,$BA47<=2030)),1,0) -> 0 | CK47: =IF(AND($AY47="Y",$BA47>2030),1,0) -> 0 | CL47: =SUM(CC47,BU47,BK47,BG47) -> 0 | CM47: =SUM(CD47,BV47,BL47,BH47) -> 0 | CN47: =SUM(CE47,BW47,BM47,BI47) -> 0 | CO47: =CF47+CB47+BN47+BJ47 -> 0 | CP47: =MAX(CH47,BN47,BJ47) -> 0 | CQ47: =IF($AV47="Yes",1,0) -> 0 | CR47: =IF($AV47="No",1,0) -> 0 | CS47: =IF($AV47="Not Specified",1,0) -> 1 | CT47: =IF(OR(AND(U47>=2026,U47<=2030),AND(X47>=2026,X47<=2030)),1,"") | CU47: =AA47&" "&AS47 | CV47: =MAX(AA47,AS47) -> 0 | CW47: 0 | CX47: 0 | CY47: 0 | CZ47: 0 | DA47: 0 | DB47: 0 | DC47: 0 | DD47: 0 | DE47: 0 | DF47: 0 | DG47: 0 | DH47: 0 | DI47: 0 | DJ47: 0 | DK47: 0 | DL47: 0 | DM47: 0 | DN47: 0 | DO47: 0 | DP47: 0 | DQ47: 0 | DR47: 0 | DS47: 0 | DT47: N | DU47: 0 | DV47: N | DW47: N | DX47: 0 | DY47: 0 | DZ47: =Q47 -> N | EA47: =Z47 | EB47: =AP47 -> N | EC47: =AJ47 -> N | ED47: =AV47 -> Not Specified | EF47: =MAX(AS47,AA47) -> 0
A48: 45 | B48: 59 | C48: China Life Insurance | D48: Insurance: Life, Health (stock) | E48: Financial services | F48: China | G48: Asia | H48: $160,276.8 | I48: $1,329.2 | J48: 0 | K48: $1,024,671.4 | L48: 179415 | M48: 23 | N48: N | Q48: N | R48: N | AC48: No target | AD48: No Target | AE48: yes | AF48: yes | AH48: 1,2 | AI48: G | AJ48: N | AK48: committed to national peak and neutrality targets | AL48: 2060 | AM48: https://cn.chinadaily.com.cn/a/202505/09/WS681d94e5a3102053770324d2.html? | AP48: N | AV48: Not Specified | AW48: Not Specified | AX48: No | AY48: N | BG48: =IF(AND($N48="Y",$P48<=2025),1,0) -> 0 | BH48: =IF(AND($N48="Y",AND($P48>2025,$P48<=2030)),1,0) -> 0 | BI48: =IF(AND($N48="Y",$P48>2030),1,0) -> 0 | BJ48: =MAX(BG48:BI48) -> 0 | BK48: =IF(AND($R48="Y",$U48<=2025),1,0) -> 0 | BL48: =IF(AND($R48="Y",AND($U48>2025,$U48<=2030)),1,0) -> 0 | BM48: =IF(AND($R48="Y",$U48>2030),1,0) -> 0 | BN48: =MAX(BK48:BM48) -> 0 | BO48: =IF(AND($Y48="Y",$AA48<=2025),1,0) -> 0 | BP48: =IF(AND($Y48="Y",AND($AA48>2025,$AA48<=2030)),1,0) -> 0 | BQ48: =IF(AND($Y48="Y",$AA48>2030),1,0) -> 0 | BR48: =IF(AND($AP48="Y",$AS48<=2025),1,0) -> 0 | BS48: =IF(AND($AP48="Y",AND($AS48>2025,$AS48<=2030)),1,0) -> 0 | BT48: =IF(AND($AP48="Y",$AS48>2030),1,0) -> 0 | BU48: =IF(AND(AL48<=2025,CF48=0,AJ48="Y"),1,0) -> 0 | BV48: =IF(AND(AL48>=2026,AL48<=2030,AJ48="Y",CF48=0),1,0) -> 0 | BW48: =IF(AND(AL48>=2031,CF48=0,AJ48="Y"),1,0) -> 0 | BX48: =IF(AND($AJ48="Y",$AL48<=2024),1,0) -> 0 | BY48: =IF(AND($AJ48="Y",AND($AL48>2024,$AL48<=2030)),1,0) -> 0 | BZ48: =IF(AND($AJ48="Y",$AL48>2030),1,0) -> 0 | CA48: =MAX(BX48:BZ48) -> 0 | CB48: =IF(AND(CF48=0,AJ48="Y"),1,0) -> 0 | CC48: =MAX($BO48,$BR48) -> 0 | CD48: =MAX($BP48,$BS48) -> 0 | CE48: =MAX($BQ48,$BT48) -> 0 | CF48: =MAX(CC48:CE48) -> 0 | CG48: =MAX($CF48,$CA48) -> 0 | CH48: =MAX(CF48,CB48) -> 0 | CI48: =IF(AND($AY48="Y",$BA48<=2024),1,0) -> 0 | CJ48: =IF(AND($AY48="Y",AND($BA48>2024,$BA48<=2030)),1,0) -> 0 | CK48: =IF(AND($AY48="Y",$BA48>2030),1,0) -> 0 | CL48: =SUM(CC48,BU48,BK48,BG48) -> 0 | CM48: =SUM(CD48,BV48,BL48,BH48) -> 0 | CN48: =SUM(CE48,BW48,BM48,BI48) -> 0 | CO48: =CF48+CB48+BN48+BJ48 -> 0 | CP48: =MAX(CH48,BN48,BJ48) -> 0 | CQ48: =IF($AV48="Yes",1,0) -> 0 | CR48: =IF($AV48="No",1,0) -> 0 | CS48: =IF($AV48="Not Specified",1,0) -> 1 | CT48: =IF(OR(AND(U48>=2026,U48<=2030),AND(X48>=2026,X48<=2030)),1,"") | CU48: =AA48&" "&AS48 | CV48: =MAX(AA48,AS48) -> 0 | CW48: 0 | CX48: 0 | CY48: 0 | CZ48: 0 | DA48: 0 | DB48: 0 | DC48: 0 | DD48: 0 | DE48: 0 | DF48: 0 | DG48: 0 | DH48: 0 | DI48: 0 | DJ48: 0 | DK48: 0 | DL48: 0 | DM48: 0 | DN48: 0 | DO48: 0 | DP48: 0 | DQ48: 0 | DR48: 0 | DS48: 0 | DT48: N | DU48: 0 | DV48: N | DW48: N | DX48: 0 | DY48: 0 | DZ48: =Q48 -> N | EA48: =Z48 | EB48: =AP48 -> N | EC48: =AJ48 -> N | ED48: =AV48 -> Not Specified | EF48: =MAX(AS48,AA48) -> 0
A49: 46 | B49: 48 | C49: Home Depot | D49: Specialty Retailers | E49: Retail | F49: U.S. | G49: North America | H49: $159,514 | I49: $14,806 | J49: -0.022 | K49: $96,119 | L49: 470100 | M49: 31 | N49: Y | O49: 2021 | P49: 2030 | Q49: Y | R49: Y | S49: Targets set | T49: 1.5Â°C | U49: 2030 | AC49: Emissions reduction target | AD49: Other Emission Reduction | AE49: Yes | AF49: Yes | AG49: Yes | AH49: 1,2,3 | AJ49: N | AP49: N | AV49: Not Specified | AW49: Not Specified | AX49: No | AY49: Y | AZ49: - Reduce absolute Scopes 1 and 2 emissions 42% by 2030, from a 2020 base year (SBTi validated) - Reduce absolute Scope 3 Category 11 ‚ÄúUse of Sold Products‚Äù emissions 42% by 2030, from the 2020 base year (SBTi validated) | BA49: 2030 | BG49: =IF(AND($N49="Y",$P49<=2025),1,0) -> 0 | BH49: =IF(AND($N49="Y",AND($P49>2025,$P49<=2030)),1,0) -> 1 | BI49: =IF(AND($N49="Y",$P49>2030),1,0) -> 0 | BJ49: =MAX(BG49:BI49) -> 1 | BK49: =IF(AND($R49="Y",$U49<=2025),1,0) -> 0 | BL49: =IF(AND($R49="Y",AND($U49>2025,$U49<=2030)),1,0) -> 1 | BM49: =IF(AND($R49="Y",$U49>2030),1,0) -> 0 | BN49: =MAX(BK49:BM49) -> 1 | BO49: =IF(AND($Y49="Y",$AA49<=2025),1,0) -> 0 | BP49: =IF(AND($Y49="Y",AND($AA49>2025,$AA49<=2030)),1,0) -> 0 | BQ49: =IF(AND($Y49="Y",$AA49>2030),1,0) -> 0 | BR49: =IF(AND($AP49="Y",$AS49<=2025),1,0) -> 0 | BS49: =IF(AND($AP49="Y",AND($AS49>2025,$AS49<=2030)),1,0) -> 0 | BT49: =IF(AND($AP49="Y",$AS49>2030),1,0) -> 0 | BU49: =IF(AND(AL49<=2025,CF49=0,AJ49="Y"),1,0) -> 0 | BV49: =IF(AND(AL49>=2026,AL49<=2030,AJ49="Y",CF49=0),1,0) -> 0 | BW49: =IF(AND(AL49>=2031,CF49=0,AJ49="Y"),1,0) -> 0 | BX49: =IF(AND($AJ49="Y",$AL49<=2024),1,0) -> 0 | BY49: =IF(AND($AJ49="Y",AND($AL49>2024,$AL49<=2030)),1,0) -> 0 | BZ49: =IF(AND($AJ49="Y",$AL49>2030),1,0) -> 0 | CA49: =MAX(BX49:BZ49) -> 0 | CB49: =IF(AND(CF49=0,AJ49="Y"),1,0) -> 0 | CC49: =MAX($BO49,$BR49) -> 0 | CD49: =MAX($BP49,$BS49) -> 0 | CE49: =MAX($BQ49,$BT49) -> 0 | CF49: =MAX(CC49:CE49) -> 0 | CG49: =MAX($CF49,$CA49) -> 0 | CH49: =MAX(CF49,CB49) -> 0 | CI49: =IF(AND($AY49="Y",$BA49<=2024),1,0) -> 0 | CJ49: =IF(AND($AY49="Y",AND($BA49>2024,$BA49<=2030)),1,0) -> 1 | CK49: =IF(AND($AY49="Y",$BA49>2030),1,0) -> 0 | CL49: =SUM(CC49,BU49,BK49,BG49) -> 0 | CM49: =SUM(CD49,BV49,BL49,BH49) -> 2 | CN49: =SUM(CE49,BW49,BM49,BI49) -> 0 | CO49: =CF49+CB49+BN49+BJ49 -> 2 | CP49: =MAX(CH49,BN49,BJ49) -> 1 | CQ49: =IF($AV49="Yes",1,0) -> 0 | CR49: =IF($AV49="No",1,0) -> 0 | CS49: =IF($AV49="Not Specified",1,0) -> 1 | CT49: =IF(OR(AND(U49>=2026,U49<=2030),AND(X49>=2026,X49<=2030)),1,"") -> 1 | CU49: =AA49&" "&AS49 | CV49: =MAX(AA49,AS49) -> 0 | CW49: 0 | CX49: 0 | CY49: 0 | CZ49: 0 | DA49: 0 | DB49: 0 | DC49: 0 | DD49: 0 | DE49: 0 | DF49: 1 | DG49: 0 | DH49: 1 | DI49: 0 | DJ49: 1 | DK49: 0 | DL49: 1 | DM49: 0 | DN49: 0 | DO49: 0 | DP49: 0 | DQ49: 0 | DR49: 1 | DS49: 0 | DT49: Y | DU49: No | DV49: N | DW49: N | DX49: 0 | DY49: 0 | DZ49: =Q49 -> Y | EA49: =Z49 | EB49: =AP49 -> N | EC49: =AJ49 -> N | ED49: =AV49 -> Not Specified | EF49: =MAX(AS49,AA49) -> 0
A50: 47 | B50: 53 | C50: Ping An Insurance | D50: Insurance: Life, Health (stock) | E50: Financial services | F50: China | G50: Asia | H50: $158,627 | I50: $17,596.1 | J50: 0.454 | K50: $1,775,215 | L50: 273053 | M50: 16 | N50: N | Q50: N | R50: N | AC50: Carbon neutral(ity) | AD50: Carbon Neutral | AE50: Yes | AF50: Yes | AG50: Yes | AH50: 1,2,3 | AI50: C,V | AJ50: Y | AK50: 'In 2021, Ping An fully upgraded its action in green finance, announced its five-year business goals, and committed to achieving carbon neutrality in operation by 2030' (p32) | AL50: 2030 | AP50: N | AV50: Not Specified | AW50: Yes (nature-based removals e.g. Forestation, soil carbon enhancement) | AX50: No | AY50: N | BG50: =IF(AND($N50="Y",$P50<=2025),1,0) -> 0 | BH50: =IF(AND($N50="Y",AND($P50>2025,$P50<=2030)),1,0) -> 0 | BI50: =IF(AND($N50="Y",$P50>2030),1,0) -> 0 | BJ50: =MAX(BG50:BI50) -> 0 | BK50: =IF(AND($R50="Y",$U50<=2025),1,0) -> 0 | BL50: =IF(AND($R50="Y",AND($U50>2025,$U50<=2030)),1,0) -> 0 | BM50: =IF(AND($R50="Y",$U50>2030),1,0) -> 0 | BN50: =MAX(BK50:BM50) -> 0 | BO50: =IF(AND($Y50="Y",$AA50<=2025),1,0) -> 0 | BP50: =IF(AND($Y50="Y",AND($AA50>2025,$AA50<=2030)),1,0) -> 0 | BQ50: =IF(AND($Y50="Y",$AA50>2030),1,0) -> 0 | BR50: =IF(AND($AP50="Y",$AS50<=2025),1,0) -> 0 | BS50: =IF(AND($AP50="Y",AND($AS50>2025,$AS50<=2030)),1,0) -> 0 | BT50: =IF(AND($AP50="Y",$AS50>2030),1,0) -> 0 | BU50: =IF(AND(AL50<=2025,CF50=0,AJ50="Y"),1,0) -> 0 | BV50: =IF(AND(AL50>=2026,AL50<=2030,AJ50="Y",CF50=0),1,0) -> 1 | BW50: =IF(AND(AL50>=2031,CF50=0,AJ50="Y"),1,0) -> 0 | BX50: =IF(AND($AJ50="Y",$AL50<=2024),1,0) -> 0 | BY50: =IF(AND($AJ50="Y",AND($AL50>2024,$AL50<=2030)),1,0) -> 1 | BZ50: =IF(AND($AJ50="Y",$AL50>2030),1,0) -> 0 | CA50: =MAX(BX50:BZ50) -> 1 | CB50: =IF(AND(CF50=0,AJ50="Y"),1,0) -> 1 | CC50: =MAX($BO50,$BR50) -> 0 | CD50: =MAX($BP50,$BS50) -> 0 | CE50: =MAX($BQ50,$BT50) -> 0 | CF50: =MAX(CC50:CE50) -> 0 | CG50: =MAX($CF50,$CA50) -> 1 | CH50: =MAX(CF50,CB50) -> 1 | CI50: =IF(AND($AY50="Y",$BA50<=2024),1,0) -> 0 | CJ50: =IF(AND($AY50="Y",AND($BA50>2024,$BA50<=2030)),1,0) -> 0 | CK50: =IF(AND($AY50="Y",$BA50>2030),1,0) -> 0 | CL50: =SUM(CC50,BU50,BK50,BG50) -> 0 | CM50: =SUM(CD50,BV50,BL50,BH50) -> 1 | CN50: =SUM(CE50,BW50,BM50,BI50) -> 0 | CO50: =CF50+CB50+BN50+BJ50 -> 1 | CP50: =MAX(CH50,BN50,BJ50) -> 1 | CQ50: =IF($AV50="Yes",1,0) -> 0 | CR50: =IF($AV50="No",1,0) -> 0 | CS50: =IF($AV50="Not Specified",1,0) -> 1 | CT50: =IF(OR(AND(U50>=2026,U50<=2030),AND(X50>=2026,X50<=2030)),1,"") | CU50: =AA50&" "&AS50 | CV50: =MAX(AA50,AS50) -> 0 | CW50: 0 | CX50: 1 | CY50: 0 | CZ50: 1 | DA50: 0 | DB50: 0 | DC50: 0 | DD50: 0 | DE50: 0 | DF50: 0 | DG50: 0 | DH50: 0 | DI50: 0 | DJ50: 0 | DK50: 0 | DL50: 0 | DM50: 1 | DN50: 1 | DO50: 1 | DP50: 1 | DQ50: 0 | DR50: 1 | DS50: 0 | DT50: N | DU50: 0 | DV50: N | DW50: C | DX50: Y | DY50: 0 | DZ50: =Q50 -> N | EA50: =Z50 | EB50: =AP50 -> N | EC50: =AJ50 -> Y | ED50: =AV50 -> Not Specified | EF50: =MAX(AS50,AA50) -> 0
A51: 48 | B51: 42 | C51: Mercedes-Benz Group | D51: Motor Vehicles | E51: Automotive | F51: Germany | G51: Europe | H51: $157,450 | I51: $11,038.2 | J51: -0.284 | K51: $274,394.3 | L51: 169198 | M51: 31 | N51: N | Q51: Y | R51: Y | S51: Targets set | T51: 1.5Â°C/Well-below 2Â°C | U51: 2030 | AC51: Carbon neutral(ity) | AD51: Carbon Neutral | AE51: Yes | AF51: Yes | AG51: Partial | AH51: 1,2 | AI51: C | AJ51: Y | AK51: The overall ambition of Mercedes-Benz is to achieve net carbon neutrality across its fleet, entire value chain and the vehicles‚Äô entire life cycle by 2039. It also aims to supply all production plants worldwide with 100% renewable energy by 2039 and reduce the carbon emissions of cars and vans by 60 % compared to 2021 by 2039. In support of the Paris Climate Agreement, they have identified decarbonisation as a key focus and core element to their sustainability strategy with a focus on actual avoidance and reduction of CO‚ÇÇ emissions through electrified fleets. sources - https://web.archive.org/web/20250928161623/https://group.mercedes-benz.com/documents/investors/reports/annual-report/mercedes-benz/mercedes-benz-climate-transition-action-plan-2025.pdf and https://web.archive.org/web/20250726210848/https://group.mercedes-benz.com/documents/investors/reports/annual-report/mercedes-benz/mercedes-benz-annual-report-2024-incl-combined-management-report-mbg-ag.pdf#page=112 - In 2022, Mercedes-Benz already achieved its originally set target of reducing CO‚ÇÇ emissions in its own plants (Scope 1 and 2) by 50 % by 2030 compared to 2018 and defined a new goal - see interim target | AL51: 2030 | AP51: N | AV51: Not Specified | AW51: Yes (nature-based and CCS-based removals) | AX51: No | AY51: N | BG51: =IF(AND($N51="Y",$P51<=2025),1,0) -> 0 | BH51: =IF(AND($N51="Y",AND($P51>2025,$P51<=2030)),1,0) -> 0 | BI51: =IF(AND($N51="Y",$P51>2030),1,0) -> 0 | BJ51: =MAX(BG51:BI51) -> 0 | BK51: =IF(AND($R51="Y",$U51<=2025),1,0) -> 0 | BL51: =IF(AND($R51="Y",AND($U51>2025,$U51<=2030)),1,0) -> 1 | BM51: =IF(AND($R51="Y",$U51>2030),1,0) -> 0 | BN51: =MAX(BK51:BM51) -> 1 | BO51: =IF(AND($Y51="Y",$AA51<=2025),1,0) -> 0 | BP51: =IF(AND($Y51="Y",AND($AA51>2025,$AA51<=2030)),1,0) -> 0 | BQ51: =IF(AND($Y51="Y",$AA51>2030),1,0) -> 0 | BR51: =IF(AND($AP51="Y",$AS51<=2025),1,0) -> 0 | BS51: =IF(AND($AP51="Y",AND($AS51>2025,$AS51<=2030)),1,0) -> 0 | BT51: =IF(AND($AP51="Y",$AS51>2030),1,0) -> 0 | BU51: =IF(AND(AL51<=2025,CF51=0,AJ51="Y"),1,0) -> 0 | BV51: =IF(AND(AL51>=2026,AL51<=2030,AJ51="Y",CF51=0),1,0) -> 1 | BW51: =IF(AND(AL51>=2031,CF51=0,AJ51="Y"),1,0) -> 0 | BX51: =IF(AND($AJ51="Y",$AL51<=2024),1,0) -> 0 | BY51: =IF(AND($AJ51="Y",AND($AL51>2024,$AL51<=2030)),1,0) -> 1 | BZ51: =IF(AND($AJ51="Y",$AL51>2030),1,0) -> 0 | CA51: =MAX(BX51:BZ51) -> 1 | CB51: =IF(AND(CF51=0,AJ51="Y"),1,0) -> 1 | CC51: =MAX($BO51,$BR51) -> 0 | CD51: =MAX($BP51,$BS51) -> 0 | CE51: =MAX($BQ51,$BT51) -> 0 | CF51: =MAX(CC51:CE51) -> 0 | CG51: =MAX($CF51,$CA51) -> 1 | CH51: =MAX(CF51,CB51) -> 1 | CI51: =IF(AND($AY51="Y",$BA51<=2024),1,0) -> 0 | CJ51: =IF(AND($AY51="Y",AND($BA51>2024,$BA51<=2030)),1,0) -> 0 | CK51: =IF(AND($AY51="Y",$BA51>2030),1,0) -> 0 | CL51: =SUM(CC51,BU51,BK51,BG51) -> 0 | CM51: =SUM(CD51,BV51,BL51,BH51) -> 2 | CN51: =SUM(CE51,BW51,BM51,BI51) -> 0 | CO51: =CF51+CB51+BN51+BJ51 -> 2 | CP51: =MAX(CH51,BN51,BJ51) -> 1 | CQ51: =IF($AV51="Yes",1,0) -> 0 | CR51: =IF($AV51="No",1,0) -> 0 | CS51: =IF($AV51="Not Specified",1,0) -> 1 | CT51: =IF(OR(AND(U51>=2026,U51<=2030),AND(X51>=2026,X51<=2030)),1,"") -> 1 | CU51: =AA51&" "&AS51 | CV51: =MAX(AA51,AS51) -> 0 | CW51: 1 | CX51: 0 | CY51: 0 | CZ51: 1 | DA51: 0 | DB51: 0 | DC51: 0 | DD51: 0 | DE51: 0 | DF51: 1 | DG51: 0 | DH51: 1 | DI51: 0 | DJ51: 0 | DK51: 0 | DL51: 0 | DM51: 1 | DN51: 1 | DO51: 1 | DP51: 1 | DQ51: 0 | DR51: 1 | DS51: 1 | DT51: Y | DU51: Yes | DV51: N | DW51: C, V | DX51: Y | DY51: 0 | DZ51: =Q51 -> Y | EA51: =Z51 | EB51: =AP51 -> N | EC51: =AJ51 -> Y | ED51: =AV51 -> Not Specified | EF51: =MAX(AS51,AA51) -> 0
A52: 49 | B52: 41 | C52: BMW Group | D52: Motor Vehicles | E52: Automotive | F52: Germany | G52: Europe | H52: $153,974.3 | I52: $7,883.6 | J52: -0.354 | K52: $277,212.7 | L52: 159104 | M52: 31 | N52: Y | O52: 2015 | P52: 2050 | Q52: Y | R52: Y | S52: Targets set | T52: 1.5°C / Well-below 2°C | U52: 2030 | Y52: N | Z52: Commitment removed | AC52: Emissions reduction target | AD52: Other Emission Reduction | AE52: Yes | AF52: Yes | AG52: Yes | AH52: 1,2,3 | AJ52: N | AO52: C | AP52: Y | AS52: 2050 | AT52: https://www.bmwgroup.com/content/dam/grpw/websites/bmwgroup_com/ir/downloads/en/2025/hv/BMWGroup_Report2024.pdf | AV52: Yes | AW52: Not Specified | AX52: No | AY52: Y | AZ52: The BMW Group is committed to the Paris Agreement: by 2050 at the latest, we intend to reduce our COâ‚‚e emissions by 90 percent compared with 2019. | BA52: 2050 | BG52: =IF(AND($N52="Y",$P52<=2025),1,0) -> 0 | BH52: =IF(AND($N52="Y",AND($P52>2025,$P52<=2030)),1,0) -> 0 | BI52: =IF(AND($N52="Y",$P52>2030),1,0) -> 1 | BJ52: =MAX(BG52:BI52) -> 1 | BK52: =IF(AND($R52="Y",$U52<=2025),1,0) -> 0 | BL52: =IF(AND($R52="Y",AND($U52>2025,$U52<=2030)),1,0) -> 1 | BM52: =IF(AND($R52="Y",$U52>2030),1,0) -> 0 | BN52: =MAX(BK52:BM52) -> 1 | BO52: =IF(AND($Y52="Y",$AA52<=2025),1,0) -> 0 | BP52: =IF(AND($Y52="Y",AND($AA52>2025,$AA52<=2030)),1,0) -> 0 | BQ52: =IF(AND($Y52="Y",$AA52>2030),1,0) -> 0 | BR52: =IF(AND($AP52="Y",$AS52<=2025),1,0) -> 0 | BS52: =IF(AND($AP52="Y",AND($AS52>2025,$AS52<=2030)),1,0) -> 0 | BT52: =IF(AND($AP52="Y",$AS52>2030),1,0) -> 1 | BU52: =IF(AND(AL52<=2025,CF52=0,AJ52="Y"),1,0) -> 0 | BV52: =IF(AND(AL52>=2026,AL52<=2030,AJ52="Y",CF52=0),1,0) -> 0 | BW52: =IF(AND(AL52>=2031,CF52=0,AJ52="Y"),1,0) -> 0 | BX52: =IF(AND($AJ52="Y",$AL52<=2024),1,0) -> 0 | BY52: =IF(AND($AJ52="Y",AND($AL52>2024,$AL52<=2030)),1,0) -> 0 | BZ52: =IF(AND($AJ52="Y",$AL52>2030),1,0) -> 0 | CA52: =MAX(BX52:BZ52) -> 0 | CB52: =IF(AND(CF52=0,AJ52="Y"),1,0) -> 0 | CC52: =MAX($BO52,$BR52) -> 0 | CD52: =MAX($BP52,$BS52) -> 0 | CE52: =MAX($BQ52,$BT52) -> 1 | CF52: =MAX(CC52:CE52) -> 1 | CG52: =MAX($CF52,$CA52) -> 1 | CH52: =MAX(CF52,CB52) -> 1 | CI52: =IF(AND($AY52="Y",$BA52<=2024),1,0) -> 0 | CJ52: =IF(AND($AY52="Y",AND($BA52>2024,$BA52<=2030)),1,0) -> 0 | CK52: =IF(AND($AY52="Y",$BA52>2030),1,0) -> 1 | CL52: =SUM(CC52,BU52,BK52,BG52) -> 0 | CM52: =SUM(CD52,BV52,BL52,BH52) -> 1 | CN52: =SUM(CE52,BW52,BM52,BI52) -> 2 | CO52: =CF52+CB52+BN52+BJ52 -> 3 | CP52: =MAX(CH52,BN52,BJ52) -> 1 | CQ52: =IF($AV52="Yes",1,0) -> 1 | CR52: =IF($AV52="No",1,0) -> 0 | CS52: =IF($AV52="Not Specified",1,0) -> 0 | CT52: =IF(OR(AND(U52>=2026,U52<=2030),AND(X52>=2026,X52<=2030)),1,"") -> 1 | CU52: =AA52&" "&AS52 -> 2050 | CV52: =MAX(AA52,AS52) -> 2050 | CW52: 0 | CX52: 0 | CY52: 1 | CZ52: 1 | DA52: 0 | DB52: 0 | DC52: 1 | DD52: 1 | DE52: 0 | DF52: 1 | DG52: 0 | DH52: 1 | DI52: 0 | DJ52: 0 | DK52: 1 | DL52: 1 | DM52: 1 | DN52: 0 | DO52: 1 | DP52: 1 | DQ52: 0 | DR52: 1 | DS52: 0 | DT52: Y | DU52: Yes | DV52: V | DW52: F | DX52: Y | DY52: U | DZ52: =Q52 -> Y | EA52: =Z52 -> Commitment removed | EB52: =AP52 -> Y | EC52: =AJ52 -> N | ED52: =AV52 -> Yes | EF52: =MAX(AS52,AA52) -> 2050
A53: 50 | B53: 58 | C53: Fannie Mae | D53: Diversified Financials | E53: Financial services | F53: U.S. | G53: North America | H53: $152,670 | I53: $16,978 | J53: -0.025 | K53: $4,349,731 | L53: 8200 | M53: 28 | N53: N | Q53: N | R53: N | AC53: No target | AD53: No Target | AE53: No | AF53: No | AG53: No | AJ53: N | AM53: https://capitalmarkets.fanniemae.com/mortgage-backed-securities/multifamily-mbs/fannie-mae-publishes-multifamily-green-mbs-energy-metrics-report | AN53: no usefull information | AP53: N | AV53: Not Specified | AW53: No | AX53: No | AY53: N | BG53: =IF(AND($N53="Y",$P53<=2025),1,0) -> 0 | BH53: =IF(AND($N53="Y",AND($P53>2025,$P53<=2030)),1,0) -> 0 | BI53: =IF(AND($N53="Y",$P53>2030),1,0) -> 0 | BJ53: =MAX(BG53:BI53) -> 0 | BK53: =IF(AND($R53="Y",$U53<=2025),1,0) -> 0 | BL53: =IF(AND($R53="Y",AND($U53>2025,$U53<=2030)),1,0) -> 0 | BM53: =IF(AND($R53="Y",$U53>2030),1,0) -> 0 | BN53: =MAX(BK53:BM53) -> 0 | BO53: =IF(AND($Y53="Y",$AA53<=2025),1,0) -> 0 | BP53: =IF(AND($Y53="Y",AND($AA53>2025,$AA53<=2030)),1,0) -> 0 | BQ53: =IF(AND($Y53="Y",$AA53>2030),1,0) -> 0 | BR53: =IF(AND($AP53="Y",$AS53<=2025),1,0) -> 0 | BS53: =IF(AND($AP53="Y",AND($AS53>2025,$AS53<=2030)),1,0) -> 0 | BT53: =IF(AND($AP53="Y",$AS53>2030),1,0) -> 0 | BU53: =IF(AND(AL53<=2025,CF53=0,AJ53="Y"),1,0) -> 0 | BV53: =IF(AND(AL53>=2026,AL53<=2030,AJ53="Y",CF53=0),1,0) -> 0 | BW53: =IF(AND(AL53>=2031,CF53=0,AJ53="Y"),1,0) -> 0 | BX53: =IF(AND($AJ53="Y",$AL53<=2024),1,0) -> 0 | BY53: =IF(AND($AJ53="Y",AND($AL53>2024,$AL53<=2030)),1,0) -> 0 | BZ53: =IF(AND($AJ53="Y",$AL53>2030),1,0) -> 0 | CA53: =MAX(BX53:BZ53) -> 0 | CB53: =IF(AND(CF53=0,AJ53="Y"),1,0) -> 0 | CC53: =MAX($BO53,$BR53) -> 0 | CD53: =MAX($BP53,$BS53) -> 0 | CE53: =MAX($BQ53,$BT53) -> 0 | CF53: =MAX(CC53:CE53) -> 0 | CG53: =MAX($CF53,$CA53) -> 0 | CH53: =MAX(CF53,CB53) -> 0 | CI53: =IF(AND($AY53="Y",$BA53<=2024),1,0) -> 0 | CJ53: =IF(AND($AY53="Y",AND($BA53>2024,$BA53<=2030)),1,0) -> 0 | CK53: =IF(AND($AY53="Y",$BA53>2030),1,0) -> 0 | CL53: =SUM(CC53,BU53,BK53,BG53) -> 0 | CM53: =SUM(CD53,BV53,BL53,BH53) -> 0 | CN53: =SUM(CE53,BW53,BM53,BI53) -> 0 | CO53: =CF53+CB53+BN53+BJ53 -> 0 | CP53: =MAX(CH53,BN53,BJ53) -> 0 | CQ53: =IF($AV53="Yes",1,0) -> 0 | CR53: =IF($AV53="No",1,0) -> 0 | CS53: =IF($AV53="Not Specified",1,0) -> 1 | CT53: =IF(OR(AND(U53>=2026,U53<=2030),AND(X53>=2026,X53<=2030)),1,"") | CU53: =AA53&" "&AS53 | CV53: =MAX(AA53,AS53) -> 0 | CW53: 0 | CX53: 0 | CY53: 0 | CZ53: 0 | DA53: 0 | DB53: 0 | DC53: 0 | DD53: 0 | DE53: 0 | DF53: 0 | DG53: 0 | DH53: 0 | DI53: 0 | DJ53: 0 | DK53: 0 | DL53: 0 | DM53: 0 | DN53: 0 | DO53: 0 | DP53: 0 | DQ53: 0 | DR53: 0 | DS53: 0 | DT53: N | DU53: 0 | DV53: N | DW53: N | DX53: 0 | DY53: 0 | DZ53: =Q53 -> N | EA53: =Z53 | EB53: =AP53 -> N | EC53: =AJ53 -> N | ED53: =AV53 -> Not Specified | EF53: =MAX(AS53,AA53) -> 0
A54: 51 | B54: 43 | C54: China Railway Construction | D54: Engineering & Construction | E54: Engineering and construction | F54: China | G54: Asia | H54: $148,467.4 | I54: $1,265.2 | J54: -0.256 | K54: $260,668.3 | L54: 325108 | M54: 14 | N54: N | Q54: N | R54: N | AC54: Carbon neutral(ity) | AD54: Carbon Neutral | AE54: Yes | AF54: Yes | AG54: No | AH54: 1,2 | AI54: C | AJ54: Y | AK54: Actively respond: "actively respond to the national ‚Äúdual carbon‚Äù strategy" (pg 42 Sustainability Report) - "dual carbon goals" are China's national commitment to peak carbon dioxide emissions before 2030 and achieve carbon neutrality before 2060 It implements directives on ecological environmental protection and the dual goals of peaking carbon emissions and achieving carbon neutrality (pg 42 Sustainability Report) | AL54: 2060 | AP54: N | AV54: Not Specified | AW54: Yes (nature-based removals e.g. Forestation, soil carbon enhancement) | AX54: No | AY54: N | BG54: =IF(AND($N54="Y",$P54<=2025),1,0) -> 0 | BH54: =IF(AND($N54="Y",AND($P54>2025,$P54<=2030)),1,0) -> 0 | BI54: =IF(AND($N54="Y",$P54>2030),1,0) -> 0 | BJ54: =MAX(BG54:BI54) -> 0 | BK54: =IF(AND($R54="Y",$U54<=2025),1,0) -> 0 | BL54: =IF(AND($R54="Y",AND($U54>2025,$U54<=2030)),1,0) -> 0 | BM54: =IF(AND($R54="Y",$U54>2030),1,0) -> 0 | BN54: =MAX(BK54:BM54) -> 0 | BO54: =IF(AND($Y54="Y",$AA54<=2025),1,0) -> 0 | BP54: =IF(AND($Y54="Y",AND($AA54>2025,$AA54<=2030)),1,0) -> 0 | BQ54: =IF(AND($Y54="Y",$AA54>2030),1,0) -> 0 | BR54: =IF(AND($AP54="Y",$AS54<=2025),1,0) -> 0 | BS54: =IF(AND($AP54="Y",AND($AS54>2025,$AS54<=2030)),1,0) -> 0 | BT54: =IF(AND($AP54="Y",$AS54>2030),1,0) -> 0 | BU54: =IF(AND(AL54<=2025,CF54=0,AJ54="Y"),1,0) -> 0 | BV54: =IF(AND(AL54>=2026,AL54<=2030,AJ54="Y",CF54=0),1,0) -> 0 | BW54: =IF(AND(AL54>=2031,CF54=0,AJ54="Y"),1,0) -> 1 | BX54: =IF(AND($AJ54="Y",$AL54<=2024),1,0) -> 0 | BY54: =IF(AND($AJ54="Y",AND($AL54>2024,$AL54<=2030)),1,0) -> 0 | BZ54: =IF(AND($AJ54="Y",$AL54>2030),1,0) -> 1 | CA54: =MAX(BX54:BZ54) -> 1 | CB54: =IF(AND(CF54=0,AJ54="Y"),1,0) -> 1 | CC54: =MAX($BO54,$BR54) -> 0 | CD54: =MAX($BP54,$BS54) -> 0 | CE54: =MAX($BQ54,$BT54) -> 0 | CF54: =MAX(CC54:CE54) -> 0 | CG54: =MAX($CF54,$CA54) -> 1 | CH54: =MAX(CF54,CB54) -> 1 | CI54: =IF(AND($AY54="Y",$BA54<=2024),1,0) -> 0 | CJ54: =IF(AND($AY54="Y",AND($BA54>2024,$BA54<=2030)),1,0) -> 0 | CK54: =IF(AND($AY54="Y",$BA54>2030),1,0) -> 0 | CL54: =SUM(CC54,BU54,BK54,BG54) -> 0 | CM54: =SUM(CD54,BV54,BL54,BH54) -> 0 | CN54: =SUM(CE54,BW54,BM54,BI54) -> 1 | CO54: =CF54+CB54+BN54+BJ54 -> 1 | CP54: =MAX(CH54,BN54,BJ54) -> 1 | CQ54: =IF($AV54="Yes",1,0) -> 0 | CR54: =IF($AV54="No",1,0) -> 0 | CS54: =IF($AV54="Not Specified",1,0) -> 1 | CT54: =IF(OR(AND(U54>=2026,U54<=2030),AND(X54>=2026,X54<=2030)),1,"") | CU54: =AA54&" "&AS54 | CV54: =MAX(AA54,AS54) -> 0 | CW54: 0 | CX54: 0 | CY54: 0 | CZ54: 0 | DA54: 0 | DB54: 0 | DC54: 0 | DD54: 0 | DE54: 0 | DF54: 0 | DG54: 0 | DH54: 0 | DI54: 0 | DJ54: 0 | DK54: 0 | DL54: 0 | DM54: 0 | DN54: 0 | DO54: 0 | DP54: 0 | DQ54: 0 | DR54: 0 | DS54: 0 | DT54: N | DU54: 0 | DV54: N | DW54: N | DX54: 0 | DY54: 0 | DZ54: =Q54 -> N | EA54: =Z54 | EB54: =AP54 -> N | EC54: =AJ54 -> Y | ED54: =AV54 -> Not Specified | EF54: =MAX(AS54,AA54) -> 0
A55: 52 | B55: 60 | C55: Walgreens Boots Alliance | D55: Health Care: Pharmacy and Other Services | E55: Health care and pharmaceuticals | F55: U.S. | G55: North America | H55: $147,658 | I55: $-8,636 | J55: 0 | K55: $81,037 | L55: 252500 | M55: 31 | N55: N | Q55: N | R55: N | AC55: Emissions reduction target | AD55: Other Emission Reduction | AE55: Yes | AF55: Yes | AG55: No | AH55: 1,2 | AJ55: N | AP55: N | AV55: Not Specified | AW55: Not Specified | AX55: No | AY55: Y | AZ55: "Reduce absolute Scope 1 and Scope 2 global carbon emissions by 30%, as compared with 2019 baseline." | BA55: 2030 | BG55: =IF(AND($N55="Y",$P55<=2025),1,0) -> 0 | BH55: =IF(AND($N55="Y",AND($P55>2025,$P55<=2030)),1,0) -> 0 | BI55: =IF(AND($N55="Y",$P55>2030),1,0) -> 0 | BJ55: =MAX(BG55:BI55) -> 0 | BK55: =IF(AND($R55="Y",$U55<=2025),1,0) -> 0 | BL55: =IF(AND($R55="Y",AND($U55>2025,$U55<=2030)),1,0) -> 0 | BM55: =IF(AND($R55="Y",$U55>2030),1,0) -> 0 | BN55: =MAX(BK55:BM55) -> 0 | BO55: =IF(AND($Y55="Y",$AA55<=2025),1,0) -> 0 | BP55: =IF(AND($Y55="Y",AND($AA55>2025,$AA55<=2030)),1,0) -> 0 | BQ55: =IF(AND($Y55="Y",$AA55>2030),1,0) -> 0 | BR55: =IF(AND($AP55="Y",$AS55<=2025),1,0) -> 0 | BS55: =IF(AND($AP55="Y",AND($AS55>2025,$AS55<=2030)),1,0) -> 0 | BT55: =IF(AND($AP55="Y",$AS55>2030),1,0) -> 0 | BU55: =IF(AND(AL55<=2025,CF55=0,AJ55="Y"),1,0) -> 0 | BV55: =IF(AND(AL55>=2026,AL55<=2030,AJ55="Y",CF55=0),1,0) -> 0 | BW55: =IF(AND(AL55>=2031,CF55=0,AJ55="Y"),1,0) -> 0 | BX55: =IF(AND($AJ55="Y",$AL55<=2024),1,0) -> 0 | BY55: =IF(AND($AJ55="Y",AND($AL55>2024,$AL55<=2030)),1,0) -> 0 | BZ55: =IF(AND($AJ55="Y",$AL55>2030),1,0) -> 0 | CA55: =MAX(BX55:BZ55) -> 0 | CB55: =IF(AND(CF55=0,AJ55="Y"),1,0) -> 0 | CC55: =MAX($BO55,$BR55) -> 0 | CD55: =MAX($BP55,$BS55) -> 0 | CE55: =MAX($BQ55,$BT55) -> 0 | CF55: =MAX(CC55:CE55) -> 0 | CG55: =MAX($CF55,$CA55) -> 0 | CH55: =MAX(CF55,CB55) -> 0 | CI55: =IF(AND($AY55="Y",$BA55<=2024),1,0) -> 0 | CJ55: =IF(AND($AY55="Y",AND($BA55>2024,$BA55<=2030)),1,0) -> 1 | CK55: =IF(AND($AY55="Y",$BA55>2030),1,0) -> 0 | CL55: =SUM(CC55,BU55,BK55,BG55) -> 0 | CM55: =SUM(CD55,BV55,BL55,BH55) -> 0 | CN55: =SUM(CE55,BW55,BM55,BI55) -> 0 | CO55: =CF55+CB55+BN55+BJ55 -> 0 | CP55: =MAX(CH55,BN55,BJ55) -> 0 | CQ55: =IF($AV55="Yes",1,0) -> 0 | CR55: =IF($AV55="No",1,0) -> 0 | CS55: =IF($AV55="Not Specified",1,0) -> 1 | CT55: =IF(OR(AND(U55>=2026,U55<=2030),AND(X55>=2026,X55<=2030)),1,"") | CU55: =AA55&" "&AS55 | CV55: =MAX(AA55,AS55) -> 0 | CW55: 0 | CX55: 0 | CY55: 0 | CZ55: 0 | DA55: 0 | DB55: 0 | DC55: 1 | DD55: 1 | DE55: 0 | DF55: 0 | DG55: 0 | DH55: 0 | DI55: 0 | DJ55: 0 | DK55: 0 | DL55: 0 | DM55: 1 | DN55: 0 | DO55: 1 | DP55: 0 | DQ55: 0 | DR55: 1 | DS55: 0 | DT55: N | DU55: 0 | DV55: C, V | DW55: N | DX55: 0 | DY55: U | DZ55: =Q55 -> N | EA55: =Z55 | EB55: =AP55 -> N | EC55: =AJ55 -> N | ED55: =AV55 -> Not Specified | EF55: =MAX(AS55,AA55) -> 0
A56: 53 | B56: 51 | C56: Kroger | D56: Food and Drugstores | E56: Retail | F56: U.S. | G56: North America | H56: $147,123 | I56: $2,665 | J56: 0.232 | K56: $52,616 | L56: 409000 | M56: 31 | N56: N | Q56: Y | R56: N | S56: Commitment removed | AC56: Emissions reduction target | AD56: Other Emission Reduction | AE56: Yes | AF56: Yes | AG56: Partial | AH56: 1,2 | AJ56: N | AP56: N | AV56: Not Specified | AW56: Not Specified | AX56: No | AY56: Y | AZ56: "Kroger‚Äôs current goal is to reduce GHG emissions from our operations by 30% by 2030, from a 2018 baseline. The goal was developed using climate science, supporting a well-below 2¬∞C climate scenario according to the absolute contraction method." (page 39) | BA56: 2030 | BG56: =IF(AND($N56="Y",$P56<=2025),1,0) -> 0 | BH56: =IF(AND($N56="Y",AND($P56>2025,$P56<=2030)),1,0) -> 0 | BI56: =IF(AND($N56="Y",$P56>2030),1,0) -> 0 | BJ56: =MAX(BG56:BI56) -> 0 | BK56: =IF(AND($R56="Y",$U56<=2025),1,0) -> 0 | BL56: =IF(AND($R56="Y",AND($U56>2025,$U56<=2030)),1,0) -> 0 | BM56: =IF(AND($R56="Y",$U56>2030),1,0) -> 0 | BN56: =MAX(BK56:BM56) -> 0 | BO56: =IF(AND($Y56="Y",$AA56<=2025),1,0) -> 0 | BP56: =IF(AND($Y56="Y",AND($AA56>2025,$AA56<=2030)),1,0) -> 0 | BQ56: =IF(AND($Y56="Y",$AA56>2030),1,0) -> 0 | BR56: =IF(AND($AP56="Y",$AS56<=2025),1,0) -> 0 | BS56: =IF(AND($AP56="Y",AND($AS56>2025,$AS56<=2030)),1,0) -> 0 | BT56: =IF(AND($AP56="Y",$AS56>2030),1,0) -> 0 | BU56: =IF(AND(AL56<=2025,CF56=0,AJ56="Y"),1,0) -> 0 | BV56: =IF(AND(AL56>=2026,AL56<=2030,AJ56="Y",CF56=0),1,0) -> 0 | BW56: =IF(AND(AL56>=2031,CF56=0,AJ56="Y"),1,0) -> 0 | BX56: =IF(AND($AJ56="Y",$AL56<=2024),1,0) -> 0 | BY56: =IF(AND($AJ56="Y",AND($AL56>2024,$AL56<=2030)),1,0) -> 0 | BZ56: =IF(AND($AJ56="Y",$AL56>2030),1,0) -> 0 | CA56: =MAX(BX56:BZ56) -> 0 | CB56: =IF(AND(CF56=0,AJ56="Y"),1,0) -> 0 | CC56: =MAX($BO56,$BR56) -> 0 | CD56: =MAX($BP56,$BS56) -> 0 | CE56: =MAX($BQ56,$BT56) -> 0 | CF56: =MAX(CC56:CE56) -> 0 | CG56: =MAX($CF56,$CA56) -> 0 | CH56: =MAX(CF56,CB56) -> 0 | CI56: =IF(AND($AY56="Y",$BA56<=2024),1,0) -> 0 | CJ56: =IF(AND($AY56="Y",AND($BA56>2024,$BA56<=2030)),1,0) -> 1 | CK56: =IF(AND($AY56="Y",$BA56>2030),1,0) -> 0 | CL56: =SUM(CC56,BU56,BK56,BG56) -> 0 | CM56: =SUM(CD56,BV56,BL56,BH56) -> 0 | CN56: =SUM(CE56,BW56,BM56,BI56) -> 0 | CO56: =CF56+CB56+BN56+BJ56 -> 0 | CP56: =MAX(CH56,BN56,BJ56) -> 0 | CQ56: =IF($AV56="Yes",1,0) -> 0 | CR56: =IF($AV56="No",1,0) -> 0 | CS56: =IF($AV56="Not Specified",1,0) -> 1 | CT56: =IF(OR(AND(U56>=2026,U56<=2030),AND(X56>=2026,X56<=2030)),1,"") | CU56: =AA56&" "&AS56 | CV56: =MAX(AA56,AS56) -> 0 | CW56: 0 | CX56: 0 | CY56: 0 | CZ56: 0 | DA56: 0 | DB56: 0 | DC56: 0 | DD56: 0 | DE56: 0 | DF56: 0 | DG56: 0 | DH56: 0 | DI56: 0 | DJ56: 0 | DK56: 0 | DL56: 0 | DM56: 0 | DN56: 0 | DO56: 0 | DP56: 0 | DQ56: 0 | DR56: 0 | DS56: 0 | DT56: N | DU56: No | DV56: N | DW56: N | DX56: 0 | DY56: 0 | DZ56: =Q56 -> Y | EA56: =Z56 | EB56: =AP56 -> N | EC56: =AJ56 -> N | ED56: =AV56 -> Not Specified | EF56: =MAX(AS56,AA56) -> 0
A57: 54 | B57: 64 | C57: BNP Paribas | D57: Megabanks | E57: Financial services | F57: France | G57: Europe | H57: $146,390.2 | I57: $12,639.8 | J57: 0.065 | K57: $2,800,691.7 | L57: 175853 | M57: 31 | N57: N | Q57: Y | R57: N | S57: Committed | U57: 2030 | AC57: Carbon neutral(ity) | AD57: Carbon Neutral | AE57: Yes | AF57: Yes | AG57: Partial | AH57: 1,2 | AI57: C | AJ57: Y | AK57: "Sustainability is at the core of the 2025 GTS strategic plan and is reinforced by the commitment of BNP Paribas to align its activities with a carbon neutrality trajectory by 2050" (2022 climate change report, p13). | AL57: 2050 | AP57: N | AV57: Yes | AW57: Yes (nature-based removals e.g. Forestation, soil carbon enhancement) | AX57: No | AY57: N | BG57: =IF(AND($N57="Y",$P57<=2025),1,0) -> 0 | BH57: =IF(AND($N57="Y",AND($P57>2025,$P57<=2030)),1,0) -> 0 | BI57: =IF(AND($N57="Y",$P57>2030),1,0) -> 0 | BJ57: =MAX(BG57:BI57) -> 0 | BK57: =IF(AND($R57="Y",$U57<=2025),1,0) -> 0 | BL57: =IF(AND($R57="Y",AND($U57>2025,$U57<=2030)),1,0) -> 0 | BM57: =IF(AND($R57="Y",$U57>2030),1,0) -> 0 | BN57: =MAX(BK57:BM57) -> 0 | BO57: =IF(AND($Y57="Y",$AA57<=2025),1,0) -> 0 | BP57: =IF(AND($Y57="Y",AND($AA57>2025,$AA57<=2030)),1,0) -> 0 | BQ57: =IF(AND($Y57="Y",$AA57>2030),1,0) -> 0 | BR57: =IF(AND($AP57="Y",$AS57<=2025),1,0) -> 0 | BS57: =IF(AND($AP57="Y",AND($AS57>2025,$AS57<=2030)),1,0) -> 0 | BT57: =IF(AND($AP57="Y",$AS57>2030),1,0) -> 0 | BU57: =IF(AND(AL57<=2025,CF57=0,AJ57="Y"),1,0) -> 0 | BV57: =IF(AND(AL57>=2026,AL57<=2030,AJ57="Y",CF57=0),1,0) -> 0 | BW57: =IF(AND(AL57>=2031,CF57=0,AJ57="Y"),1,0) -> 1 | BX57: =IF(AND($AJ57="Y",$AL57<=2024),1,0) -> 0 | BY57: =IF(AND($AJ57="Y",AND($AL57>2024,$AL57<=2030)),1,0) -> 0 | BZ57: =IF(AND($AJ57="Y",$AL57>2030),1,0) -> 1 | CA57: =MAX(BX57:BZ57) -> 1 | CB57: =IF(AND(CF57=0,AJ57="Y"),1,0) -> 1 | CC57: =MAX($BO57,$BR57) -> 0 | CD57: =MAX($BP57,$BS57) -> 0 | CE57: =MAX($BQ57,$BT57) -> 0 | CF57: =MAX(CC57:CE57) -> 0 | CG57: =MAX($CF57,$CA57) -> 1 | CH57: =MAX(CF57,CB57) -> 1 | CI57: =IF(AND($AY57="Y",$BA57<=2024),1,0) -> 0 | CJ57: =IF(AND($AY57="Y",AND($BA57>2024,$BA57<=2030)),1,0) -> 0 | CK57: =IF(AND($AY57="Y",$BA57>2030),1,0) -> 0 | CL57: =SUM(CC57,BU57,BK57,BG57) -> 0 | CM57: =SUM(CD57,BV57,BL57,BH57) -> 0 | CN57: =SUM(CE57,BW57,BM57,BI57) -> 1 | CO57: =CF57+CB57+BN57+BJ57 -> 1 | CP57: =MAX(CH57,BN57,BJ57) -> 1 | CQ57: =IF($AV57="Yes",1,0) -> 1 | CR57: =IF($AV57="No",1,0) -> 0 | CS57: =IF($AV57="Not Specified",1,0) -> 0 | CT57: =IF(OR(AND(U57>=2026,U57<=2030),AND(X57>=2026,X57<=2030)),1,"") -> 1 | CU57: =AA57&" "&AS57 | CV57: =MAX(AA57,AS57) -> 0 | CW57: 0 | CX57: 0 | CY57: 1 | CZ57: 1 | DA57: 0 | DB57: 0 | DC57: 0 | DD57: 0 | DE57: 0 | DF57: 1 | DG57: 0 | DH57: 1 | DI57: 0 | DJ57: 0 | DK57: 0 | DL57: 0 | DM57: 1 | DN57: 0 | DO57: 1 | DP57: 1 | DQ57: 0 | DR57: 1 | DS57: 0 | DT57: N | DU57: No | DV57: I | DW57: F | DX57: 0 | DY57: 0 | DZ57: =Q57 -> Y | EA57: =Z57 | EB57: =AP57 -> N | EC57: =AJ57 -> Y | ED57: =AV57 -> Yes | EF57: =MAX(AS57,AA57) -> 0
A58: 55 | B58: 62 | C58: Banco Santander | D58: Megabanks | E58: Financial services | F58: Spain | G58: Europe | H58: $146,326.4 | I58: $13,597.9 | J58: 0.136 | K58: $1,902,134 | L58: 206417 | M58: 31 | N58: N | Q58: N | R58: N | AC58: Net zero | AD58: Net Zero | AE58: Yes | AF58: Yes | AG58: Yes | AH58: 1,2,3 | AJ58: N | AO58: C,V | AP58: Y | AQ58: 1,2,3 | AR58: In order to be aligned with the Paris Agreement and with the aim of limiting global temperature increase to 1.5¬∞C, we have committed to be net zero in carbon emissions by 2050 also as part of the Net Zero Banking Alliance (NZBA). This is done through: - Contribute to limiting temperature increases to 1.5¬∫C in line with the NZBA and NZAMi -Support our customers transition to a lowcarbon economy - Remain carbon neutral and consume 100% electricity from renewable sources by 2025 -Manage climate and environmental risk according to regulatory and supervisory expectations & setting sector portfolio alignment targets for 2030 in high-emissions portfolios. (https://www.santander.com/content/dam/santander-com/en/documentos/informe-anual-de-sostenibilidad/2024/sustainability_statement-2024-en.pdf ) | AS58: 2050 | AV58: Yes | AW58: Yes (nature-based and CCS-based removals) | AX58: No | AY58: N | BG58: =IF(AND($N58="Y",$P58<=2025),1,0) -> 0 | BH58: =IF(AND($N58="Y",AND($P58>2025,$P58<=2030)),1,0) -> 0 | BI58: =IF(AND($N58="Y",$P58>2030),1,0) -> 0 | BJ58: =MAX(BG58:BI58) -> 0 | BK58: =IF(AND($R58="Y",$U58<=2025),1,0) -> 0 | BL58: =IF(AND($R58="Y",AND($U58>2025,$U58<=2030)),1,0) -> 0 | BM58: =IF(AND($R58="Y",$U58>2030),1,0) -> 0 | BN58: =MAX(BK58:BM58) -> 0 | BO58: =IF(AND($Y58="Y",$AA58<=2025),1,0) -> 0 | BP58: =IF(AND($Y58="Y",AND($AA58>2025,$AA58<=2030)),1,0) -> 0 | BQ58: =IF(AND($Y58="Y",$AA58>2030),1,0) -> 0 | BR58: =IF(AND($AP58="Y",$AS58<=2025),1,0) -> 0 | BS58: =IF(AND($AP58="Y",AND($AS58>2025,$AS58<=2030)),1,0) -> 0 | BT58: =IF(AND($AP58="Y",$AS58>2030),1,0) -> 1 | BU58: =IF(AND(AL58<=2025,CF58=0,AJ58="Y"),1,0) -> 0 | BV58: =IF(AND(AL58>=2026,AL58<=2030,AJ58="Y",CF58=0),1,0) -> 0 | BW58: =IF(AND(AL58>=2031,CF58=0,AJ58="Y"),1,0) -> 0 | BX58: =IF(AND($AJ58="Y",$AL58<=2024),1,0) -> 0 | BY58: =IF(AND($AJ58="Y",AND($AL58>2024,$AL58<=2030)),1,0) -> 0 | BZ58: =IF(AND($AJ58="Y",$AL58>2030),1,0) -> 0 | CA58: =MAX(BX58:BZ58) -> 0 | CB58: =IF(AND(CF58=0,AJ58="Y"),1,0) -> 0 | CC58: =MAX($BO58,$BR58) -> 0 | CD58: =MAX($BP58,$BS58) -> 0 | CE58: =MAX($BQ58,$BT58) -> 1 | CF58: =MAX(CC58:CE58) -> 1 | CG58: =MAX($CF58,$CA58) -> 1 | CH58: =MAX(CF58,CB58) -> 1 | CI58: =IF(AND($AY58="Y",$BA58<=2024),1,0) -> 0 | CJ58: =IF(AND($AY58="Y",AND($BA58>2024,$BA58<=2030)),1,0) -> 0 | CK58: =IF(AND($AY58="Y",$BA58>2030),1,0) -> 0 | CL58: =SUM(CC58,BU58,BK58,BG58) -> 0 | CM58: =SUM(CD58,BV58,BL58,BH58) -> 0 | CN58: =SUM(CE58,BW58,BM58,BI58) -> 1 | CO58: =CF58+CB58+BN58+BJ58 -> 1 | CP58: =MAX(CH58,BN58,BJ58) -> 1 | CQ58: =IF($AV58="Yes",1,0) -> 1 | CR58: =IF($AV58="No",1,0) -> 0 | CS58: =IF($AV58="Not Specified",1,0) -> 0 | CT58: =IF(OR(AND(U58>=2026,U58<=2030),AND(X58>=2026,X58<=2030)),1,"") | CU58: =AA58&" "&AS58 -> 2050 | CV58: =MAX(AA58,AS58) -> 2050 | CW58: 1 | CX58: 0 | CY58: 0 | CZ58: 1 | DA58: 0 | DB58: 0 | DC58: 1 | DD58: 1 | DE58: 0 | DF58: 0 | DG58: 0 | DH58: 0 | DI58: 0 | DJ58: 0 | DK58: 0 | DL58: 0 | DM58: 1 | DN58: 1 | DO58: 1 | DP58: 1 | DQ58: 0 | DR58: 1 | DS58: 1 | DT58: N | DU58: 0 | DV58: C, F | DW58: N | DX58: Y | DY58: Y | DZ58: =Q58 -> N | EA58: =Z58 | EB58: =AP58 -> Y | EC58: =AJ58 -> N | ED58: =AV58 -> Yes | EF58: =MAX(AS58,AA58) -> 2050
A59: 56 | B59: 67 | C59: HSBC Holdings | D59: Megabanks | E59: Financial services | F59: Britain | G59: Europe | H59: $145,717 | I59: $23,979 | J59: 0.019 | K59: $3,017,048 | L59: 211304 | M59: 31 | N59: Y | O59: 2017 | P59: 2030 | Q59: N | R59: N | AC59: Net zero | AD59: Net Zero | AE59: Yes | AF59: Yes | AG59: Yes | AH59: 1,2,3 | AJ59: N | AO59: C,V | AP59: Y | AQ59: 1,2,3 | AR59: We have revisited our ambition to take into account latest best practice guidance on carbon offsets. We are now focused on achieving net zero across our operations, travel and supply chain by 2050. [2024 Annual Report, p42] ....we are now focused on actions to cut emissions across these areas as part of our overall ambition to become net zero by 2050. [2024 Annual Report, p58]. "we expect to update our net zero transition plan in the second half of 2025, taking into consideration latest scientific methodologies, climate-related policy measures and real-world progress." https://www.hsbc.com/who-we-are/our-climate-strategy/our-net-zero-transition-plan | AS59: 2050 | AV59: Yes | AW59: Yes (unspecified) | AX59: No | AY59: N | BG59: =IF(AND($N59="Y",$P59<=2025),1,0) -> 0 | BH59: =IF(AND($N59="Y",AND($P59>2025,$P59<=2030)),1,0) -> 1 | BI59: =IF(AND($N59="Y",$P59>2030),1,0) -> 0 | BJ59: =MAX(BG59:BI59) -> 1 | BK59: =IF(AND($R59="Y",$U59<=2025),1,0) -> 0 | BL59: =IF(AND($R59="Y",AND($U59>2025,$U59<=2030)),1,0) -> 0 | BM59: =IF(AND($R59="Y",$U59>2030),1,0) -> 0 | BN59: =MAX(BK59:BM59) -> 0 | BO59: =IF(AND($Y59="Y",$AA59<=2025),1,0) -> 0 | BP59: =IF(AND($Y59="Y",AND($AA59>2025,$AA59<=2030)),1,0) -> 0 | BQ59: =IF(AND($Y59="Y",$AA59>2030),1,0) -> 0 | BR59: =IF(AND($AP59="Y",$AS59<=2025),1,0) -> 0 | BS59: =IF(AND($AP59="Y",AND($AS59>2025,$AS59<=2030)),1,0) -> 0 | BT59: =IF(AND($AP59="Y",$AS59>2030),1,0) -> 1 | BU59: =IF(AND(AL59<=2025,CF59=0,AJ59="Y"),1,0) -> 0 | BV59: =IF(AND(AL59>=2026,AL59<=2030,AJ59="Y",CF59=0),1,0) -> 0 | BW59: =IF(AND(AL59>=2031,CF59=0,AJ59="Y"),1,0) -> 0 | BX59: =IF(AND($AJ59="Y",$AL59<=2024),1,0) -> 0 | BY59: =IF(AND($AJ59="Y",AND($AL59>2024,$AL59<=2030)),1,0) -> 0 | BZ59: =IF(AND($AJ59="Y",$AL59>2030),1,0) -> 0 | CA59: =MAX(BX59:BZ59) -> 0 | CB59: =IF(AND(CF59=0,AJ59="Y"),1,0) -> 0 | CC59: =MAX($BO59,$BR59) -> 0 | CD59: =MAX($BP59,$BS59) -> 0 | CE59: =MAX($BQ59,$BT59) -> 1 | CF59: =MAX(CC59:CE59) -> 1 | CG59: =MAX($CF59,$CA59) -> 1 | CH59: =MAX(CF59,CB59) -> 1 | CI59: =IF(AND($AY59="Y",$BA59<=2024),1,0) -> 0 | CJ59: =IF(AND($AY59="Y",AND($BA59>2024,$BA59<=2030)),1,0) -> 0 | CK59: =IF(AND($AY59="Y",$BA59>2030),1,0) -> 0 | CL59: =SUM(CC59,BU59,BK59,BG59) -> 0 | CM59: =SUM(CD59,BV59,BL59,BH59) -> 1 | CN59: =SUM(CE59,BW59,BM59,BI59) -> 1 | CO59: =CF59+CB59+BN59+BJ59 -> 2 | CP59: =MAX(CH59,BN59,BJ59) -> 1 | CQ59: =IF($AV59="Yes",1,0) -> 1 | CR59: =IF($AV59="No",1,0) -> 0 | CS59: =IF($AV59="Not Specified",1,0) -> 0 | CT59: =IF(OR(AND(U59>=2026,U59<=2030),AND(X59>=2026,X59<=2030)),1,"") | CU59: =AA59&" "&AS59 -> 2050 | CV59: =MAX(AA59,AS59) -> 2050 | CW59: 0 | CX59: 0 | CY59: 0 | CZ59: 0 | DA59: 0 | DB59: 1 | DC59: 0 | DD59: 1 | DE59: 0 | DF59: 0 | DG59: 0 | DH59: 0 | DI59: 0 | DJ59: 1 | DK59: 0 | DL59: 1 | DM59: 1 | DN59: 1 | DO59: 1 | DP59: 1 | DQ59: 0 | DR59: 1 | DS59: 0 | DT59: N | DU59: 0 | DV59: C, F | DW59: N | DX59: 0 | DY59: Y | DZ59: =Q59 -> N | EA59: =Z59 | EB59: =AP59 -> Y | EC59: =AJ59 -> N | ED59: =AV59 -> Yes | EF59: =MAX(AS59,AA59) -> 2050
A60: 57 | B60: 52 | C60: Phillips 66 | D60: Petroleum Refining | E60: Oil and gas | F60: U.S. | G60: North America | H60: $145,496 | I60: $2,117 | J60: -0.698 | K60: $72,582 | L60: 13200 | M60: 13 | N60: N | Q60: N | R60: N | AC60: Emissions intensity target | AD60: Other Emission Reduction | AE60: Yes | AF60: Yes | AG60: Yes | AH60: 1,2,3 | AJ60: N | AP60: N | AV60: Not Specified | AW60: Yes (CCS-based removals e.g. BECCS, DACCS) | AX60: No | AY60: Y | AZ60: MANUFACTURING EMISSIONS INTENSITY (Scope 1 and 2 Metric Tons of CO2e/MBOE): 50% reduction by 2050 with baseline year 2019 https://www.phillips66.com/sustainability/our-targets/ https://phillips66.widen.net/s/xrz9pvmmvh/eyassurance-review-report | BA60: 2050 | BG60: =IF(AND($N60="Y",$P60<=2025),1,0) -> 0 | BH60: =IF(AND($N60="Y",AND($P60>2025,$P60<=2030)),1,0) -> 0 | BI60: =IF(AND($N60="Y",$P60>2030),1,0) -> 0 | BJ60: =MAX(BG60:BI60) -> 0 | BK60: =IF(AND($R60="Y",$U60<=2025),1,0) -> 0 | BL60: =IF(AND($R60="Y",AND($U60>2025,$U60<=2030)),1,0) -> 0 | BM60: =IF(AND($R60="Y",$U60>2030),1,0) -> 0 | BN60: =MAX(BK60:BM60) -> 0 | BO60: =IF(AND($Y60="Y",$AA60<=2025),1,0) -> 0 | BP60: =IF(AND($Y60="Y",AND($AA60>2025,$AA60<=2030)),1,0) -> 0 | BQ60: =IF(AND($Y60="Y",$AA60>2030),1,0) -> 0 | BR60: =IF(AND($AP60="Y",$AS60<=2025),1,0) -> 0 | BS60: =IF(AND($AP60="Y",AND($AS60>2025,$AS60<=2030)),1,0) -> 0 | BT60: =IF(AND($AP60="Y",$AS60>2030),1,0) -> 0 | BU60: =IF(AND(AL60<=2025,CF60=0,AJ60="Y"),1,0) -> 0 | BV60: =IF(AND(AL60>=2026,AL60<=2030,AJ60="Y",CF60=0),1,0) -> 0 | BW60: =IF(AND(AL60>=2031,CF60=0,AJ60="Y"),1,0) -> 0 | BX60: =IF(AND($AJ60="Y",$AL60<=2024),1,0) -> 0 | BY60: =IF(AND($AJ60="Y",AND($AL60>2024,$AL60<=2030)),1,0) -> 0 | BZ60: =IF(AND($AJ60="Y",$AL60>2030),1,0) -> 0 | CA60: =MAX(BX60:BZ60) -> 0 | CB60: =IF(AND(CF60=0,AJ60="Y"),1,0) -> 0 | CC60: =MAX($BO60,$BR60) -> 0 | CD60: =MAX($BP60,$BS60) -> 0 | CE60: =MAX($BQ60,$BT60) -> 0 | CF60: =MAX(CC60:CE60) -> 0 | CG60: =MAX($CF60,$CA60) -> 0 | CH60: =MAX(CF60,CB60) -> 0 | CI60: =IF(AND($AY60="Y",$BA60<=2024),1,0) -> 0 | CJ60: =IF(AND($AY60="Y",AND($BA60>2024,$BA60<=2030)),1,0) -> 0 | CK60: =IF(AND($AY60="Y",$BA60>2030),1,0) -> 1 | CL60: =SUM(CC60,BU60,BK60,BG60) -> 0 | CM60: =SUM(CD60,BV60,BL60,BH60) -> 0 | CN60: =SUM(CE60,BW60,BM60,BI60) -> 0 | CO60: =CF60+CB60+BN60+BJ60 -> 0 | CP60: =MAX(CH60,BN60,BJ60) -> 0 | CQ60: =IF($AV60="Yes",1,0) -> 0 | CR60: =IF($AV60="No",1,0) -> 0 | CS60: =IF($AV60="Not Specified",1,0) -> 1 | CT60: =IF(OR(AND(U60>=2026,U60<=2030),AND(X60>=2026,X60<=2030)),1,"") | CU60: =AA60&" "&AS60 | CV60: =MAX(AA60,AS60) -> 0 | CW60: 0 | CX60: 0 | CY60: 0 | CZ60: 0 | DA60: 0 | DB60: 0 | DC60: 0 | DD60: 0 | DE60: 0 | DF60: 0 | DG60: 0 | DH60: 0 | DI60: 0 | DJ60: 0 | DK60: 0 | DL60: 0 | DM60: 0 | DN60: 0 | DO60: 0 | DP60: 0 | DQ60: 0 | DR60: 0 | DS60: 0 | DT60: N | DU60: 0 | DV60: N | DW60: N | DX60: 0 | DY60: 0 | DZ60: =Q60 -> N | EA60: =Z60 | EB60: =AP60 -> N | EC60: =AJ60 -> N | ED60: =AV60 -> Not Specified | EF60: =MAX(AS60,AA60) -> 0
A61: 58 | B61: 55 | C61: China Mobile Communications | D61: Telecommunications | E61: Telecommunications and media | F61: China | G61: Asia | H61: $145,239.9 | I61: $14,698.8 | J61: -0.036 | K61: $350,174.2 | L61: 456965 | M61: 25 | N61: N | Q61: N | R61: N | AC61: Emissions intensity target | AD61: Other Emission Reduction | AE61: Yes | AF61: Yes | AG61: No | AH61: 1,2 | AJ61: N | AP61: N | AV61: Not Specified | AW61: Not Specified | AX61: No | AY61: Y | AZ61: ‚ÄòBased on likely climate-related impact on our future operations, we pledge to reduce Scope 1 and Scope 2 GHG emission intensity by 20% by 2025 from the 2020 baseline.‚Äô p42 | BA61: 2025 | BG61: =IF(AND($N61="Y",$P61<=2025),1,0) -> 0 | BH61: =IF(AND($N61="Y",AND($P61>2025,$P61<=2030)),1,0) -> 0 | BI61: =IF(AND($N61="Y",$P61>2030),1,0) -> 0 | BJ61: =MAX(BG61:BI61) -> 0 | BK61: =IF(AND($R61="Y",$U61<=2025),1,0) -> 0 | BL61: =IF(AND($R61="Y",AND($U61>2025,$U61<=2030)),1,0) -> 0 | BM61: =IF(AND($R61="Y",$U61>2030),1,0) -> 0 | BN61: =MAX(BK61:BM61) -> 0 | BO61: =IF(AND($Y61="Y",$AA61<=2025),1,0) -> 0 | BP61: =IF(AND($Y61="Y",AND($AA61>2025,$AA61<=2030)),1,0) -> 0 | BQ61: =IF(AND($Y61="Y",$AA61>2030),1,0) -> 0 | BR61: =IF(AND($AP61="Y",$AS61<=2025),1,0) -> 0 | BS61: =IF(AND($AP61="Y",AND($AS61>2025,$AS61<=2030)),1,0) -> 0 | BT61: =IF(AND($AP61="Y",$AS61>2030),1,0) -> 0 | BU61: =IF(AND(AL61<=2025,CF61=0,AJ61="Y"),1,0) -> 0 | BV61: =IF(AND(AL61>=2026,AL61<=2030,AJ61="Y",CF61=0),1,0) -> 0 | BW61: =IF(AND(AL61>=2031,CF61=0,AJ61="Y"),1,0) -> 0 | BX61: =IF(AND($AJ61="Y",$AL61<=2024),1,0) -> 0 | BY61: =IF(AND($AJ61="Y",AND($AL61>2024,$AL61<=2030)),1,0) -> 0 | BZ61: =IF(AND($AJ61="Y",$AL61>2030),1,0) -> 0 | CA61: =MAX(BX61:BZ61) -> 0 | CB61: =IF(AND(CF61=0,AJ61="Y"),1,0) -> 0 | CC61: =MAX($BO61,$BR61) -> 0 | CD61: =MAX($BP61,$BS61) -> 0 | CE61: =MAX($BQ61,$BT61) -> 0 | CF61: =MAX(CC61:CE61) -> 0 | CG61: =MAX($CF61,$CA61) -> 0 | CH61: =MAX(CF61,CB61) -> 0 | CI61: =IF(AND($AY61="Y",$BA61<=2024),1,0) -> 0 | CJ61: =IF(AND($AY61="Y",AND($BA61>2024,$BA61<=2030)),1,0) -> 1 | CK61: =IF(AND($AY61="Y",$BA61>2030),1,0) -> 0 | CL61: =SUM(CC61,BU61,BK61,BG61) -> 0 | CM61: =SUM(CD61,BV61,BL61,BH61) -> 0 | CN61: =SUM(CE61,BW61,BM61,BI61) -> 0 | CO61: =CF61+CB61+BN61+BJ61 -> 0 | CP61: =MAX(CH61,BN61,BJ61) -> 0 | CQ61: =IF($AV61="Yes",1,0) -> 0 | CR61: =IF($AV61="No",1,0) -> 0 | CS61: =IF($AV61="Not Specified",1,0) -> 1 | CT61: =IF(OR(AND(U61>=2026,U61<=2030),AND(X61>=2026,X61<=2030)),1,"") | CU61: =AA61&" "&AS61 | CV61: =MAX(AA61,AS61) -> 0 | CW61: 0 | CX61: 0 | CY61: 0 | CZ61: 0 | DA61: 0 | DB61: 0 | DC61: 0 | DD61: 0 | DE61: 0 | DF61: 0 | DG61: 0 | DH61: 0 | DI61: 0 | DJ61: 0 | DK61: 0 | DL61: 0 | DM61: 0 | DN61: 0 | DO61: 0 | DP61: 0 | DQ61: 0 | DR61: 0 | DS61: 0 | DT61: N | DU61: 0 | DV61: N | DW61: G | DX61: U | DY61: 0 | DZ61: =Q61 -> N | EA61: =Z61 | EB61: =AP61 -> N | EC61: =AJ61 -> N | ED61: =AV61 -> Not Specified | EF61: =MAX(AS61,AA61) -> 0
A62: 59 | B62: 57 | C62: Honda Motor | D62: Motor Vehicles | E62: Automotive | F62: Japan | G62: Asia | H62: $142,273.6 | I62: $5,482.9 | J62: -0.284 | K62: $205,323 | L62: 194173 | M62: 31 | N62: N | Q62: N | R62: N | AC62: Carbon neutral(ity) | AD62: Carbon Neutral | AE62: Yes | AF62: Yes | AG62: Yes | AH62: 1,2,3 | AI62: C,V | AJ62: Y | AK62: Our company aim for ‚Äúcarbon neutrality by 2050‚Äù across the entire product lifecycle, and is focusing on the four materialities and is prioritizing ‚Äúaddressing climate change‚Äù and ‚Äúaddressing energy issues." | AL62: 2050 | AP62: N | AV62: Yes | AW62: Not Specified | AX62: No | AY62: N | BG62: =IF(AND($N62="Y",$P62<=2025),1,0) -> 0 | BH62: =IF(AND($N62="Y",AND($P62>2025,$P62<=2030)),1,0) -> 0 | BI62: =IF(AND($N62="Y",$P62>2030),1,0) -> 0 | BJ62: =MAX(BG62:BI62) -> 0 | BK62: =IF(AND($R62="Y",$U62<=2025),1,0) -> 0 | BL62: =IF(AND($R62="Y",AND($U62>2025,$U62<=2030)),1,0) -> 0 | BM62: =IF(AND($R62="Y",$U62>2030),1,0) -> 0 | BN62: =MAX(BK62:BM62) -> 0 | BO62: =IF(AND($Y62="Y",$AA62<=2025),1,0) -> 0 | BP62: =IF(AND($Y62="Y",AND($AA62>2025,$AA62<=2030)),1,0) -> 0 | BQ62: =IF(AND($Y62="Y",$AA62>2030),1,0) -> 0 | BR62: =IF(AND($AP62="Y",$AS62<=2025),1,0) -> 0 | BS62: =IF(AND($AP62="Y",AND($AS62>2025,$AS62<=2030)),1,0) -> 0 | BT62: =IF(AND($AP62="Y",$AS62>2030),1,0) -> 0 | BU62: =IF(AND(AL62<=2025,CF62=0,AJ62="Y"),1,0) -> 0 | BV62: =IF(AND(AL62>=2026,AL62<=2030,AJ62="Y",CF62=0),1,0) -> 0 | BW62: =IF(AND(AL62>=2031,CF62=0,AJ62="Y"),1,0) -> 1 | BX62: =IF(AND($AJ62="Y",$AL62<=2024),1,0) -> 0 | BY62: =IF(AND($AJ62="Y",AND($AL62>2024,$AL62<=2030)),1,0) -> 0 | BZ62: =IF(AND($AJ62="Y",$AL62>2030),1,0) -> 1 | CA62: =MAX(BX62:BZ62) -> 1 | CB62: =IF(AND(CF62=0,AJ62="Y"),1,0) -> 1 | CC62: =MAX($BO62,$BR62) -> 0 | CD62: =MAX($BP62,$BS62) -> 0 | CE62: =MAX($BQ62,$BT62) -> 0 | CF62: =MAX(CC62:CE62) -> 0 | CG62: =MAX($CF62,$CA62) -> 1 | CH62: =MAX(CF62,CB62) -> 1 | CI62: =IF(AND($AY62="Y",$BA62<=2024),1,0) -> 0 | CJ62: =IF(AND($AY62="Y",AND($BA62>2024,$BA62<=2030)),1,0) -> 0 | CK62: =IF(AND($AY62="Y",$BA62>2030),1,0) -> 0 | CL62: =SUM(CC62,BU62,BK62,BG62) -> 0 | CM62: =SUM(CD62,BV62,BL62,BH62) -> 0 | CN62: =SUM(CE62,BW62,BM62,BI62) -> 1 | CO62: =CF62+CB62+BN62+BJ62 -> 1 | CP62: =MAX(CH62,BN62,BJ62) -> 1 | CQ62: =IF($AV62="Yes",1,0) -> 1 | CR62: =IF($AV62="No",1,0) -> 0 | CS62: =IF($AV62="Not Specified",1,0) -> 0 | CT62: =IF(OR(AND(U62>=2026,U62<=2030),AND(X62>=2026,X62<=2030)),1,"") | CU62: =AA62&" "&AS62 | CV62: =MAX(AA62,AS62) -> 0 | CW62: 0 | CX62: 0 | CY62: 1 | CZ62: 1 | DA62: 0 | DB62: 0 | DC62: 0 | DD62: 0 | DE62: 0 | DF62: 0 | DG62: 0 | DH62: 0 | DI62: 0 | DJ62: 0 | DK62: 0 | DL62: 0 | DM62: 1 | DN62: 0 | DO62: 1 | DP62: 0 | DQ62: 0 | DR62: 1 | DS62: 0 | DT62: N | DU62: 0 | DV62: I | DW62: V | DX62: U | DY62: 0 | DZ62: =Q62 -> N | EA62: =Z62 | EB62: =AP62 -> N | EC62: =AJ62 -> Y | ED62: =AV62 -> Yes | EF62: =MAX(AS62,AA62) -> 0
A63: 60 | B63: 50 | C63: Marathon Petroleum | D63: Petroleum Refining | E63: Oil and gas | F63: U.S. | G63: North America | H63: $140,412 | I63: $3,445 | J63: -0.644 | K63: $78,858 | L63: 18300 | M63: 14 | N63: N | Q63: N | R63: N | AC63: Emissions intensity target | AD63: Other Emission Reduction | AE63: Yes | AF63: Yes | AG63: Partial | AH63: 1,2 | AJ63: N | AP63: N | AV63: Not Specified | AW63: Yes (nature-based and CCS-based removals) | AX63: No | AY63: Y | AZ63: 30% reduction of scope 1 and 2 GHG emissions intensity by 2030 from 2014 levels; 15% reduction of scope 3 - category 11 GHG emissions by 2030 from 2019 levels | BA63: 2035 | BG63: =IF(AND($N63="Y",$P63<=2025),1,0) -> 0 | BH63: =IF(AND($N63="Y",AND($P63>2025,$P63<=2030)),1,0) -> 0 | BI63: =IF(AND($N63="Y",$P63>2030),1,0) -> 0 | BJ63: =MAX(BG63:BI63) -> 0 | BK63: =IF(AND($R63="Y",$U63<=2025),1,0) -> 0 | BL63: =IF(AND($R63="Y",AND($U63>2025,$U63<=2030)),1,0) -> 0 | BM63: =IF(AND($R63="Y",$U63>2030),1,0) -> 0 | BN63: =MAX(BK63:BM63) -> 0 | BO63: =IF(AND($Y63="Y",$AA63<=2025),1,0) -> 0 | BP63: =IF(AND($Y63="Y",AND($AA63>2025,$AA63<=2030)),1,0) -> 0 | BQ63: =IF(AND($Y63="Y",$AA63>2030),1,0) -> 0 | BR63: =IF(AND($AP63="Y",$AS63<=2025),1,0) -> 0 | BS63: =IF(AND($AP63="Y",AND($AS63>2025,$AS63<=2030)),1,0) -> 0 | BT63: =IF(AND($AP63="Y",$AS63>2030),1,0) -> 0 | BU63: =IF(AND(AL63<=2025,CF63=0,AJ63="Y"),1,0) -> 0 | BV63: =IF(AND(AL63>=2026,AL63<=2030,AJ63="Y",CF63=0),1,0) -> 0 | BW63: =IF(AND(AL63>=2031,CF63=0,AJ63="Y"),1,0) -> 0 | BX63: =IF(AND($AJ63="Y",$AL63<=2024),1,0) -> 0 | BY63: =IF(AND($AJ63="Y",AND($AL63>2024,$AL63<=2030)),1,0) -> 0 | BZ63: =IF(AND($AJ63="Y",$AL63>2030),1,0) -> 0 | CA63: =MAX(BX63:BZ63) -> 0 | CB63: =IF(AND(CF63=0,AJ63="Y"),1,0) -> 0 | CC63: =MAX($BO63,$BR63) -> 0 | CD63: =MAX($BP63,$BS63) -> 0 | CE63: =MAX($BQ63,$BT63) -> 0 | CF63: =MAX(CC63:CE63) -> 0 | CG63: =MAX($CF63,$CA63) -> 0 | CH63: =MAX(CF63,CB63) -> 0 | CI63: =IF(AND($AY63="Y",$BA63<=2024),1,0) -> 0 | CJ63: =IF(AND($AY63="Y",AND($BA63>2024,$BA63<=2030)),1,0) -> 0 | CK63: =IF(AND($AY63="Y",$BA63>2030),1,0) -> 1 | CL63: =SUM(CC63,BU63,BK63,BG63) -> 0 | CM63: =SUM(CD63,BV63,BL63,BH63) -> 0 | CN63: =SUM(CE63,BW63,BM63,BI63) -> 0 | CO63: =CF63+CB63+BN63+BJ63 -> 0 | CP63: =MAX(CH63,BN63,BJ63) -> 0 | CQ63: =IF($AV63="Yes",1,0) -> 0 | CR63: =IF($AV63="No",1,0) -> 0 | CS63: =IF($AV63="Not Specified",1,0) -> 1 | CT63: =IF(OR(AND(U63>=2026,U63<=2030),AND(X63>=2026,X63<=2030)),1,"") | CU63: =AA63&" "&AS63 | CV63: =MAX(AA63,AS63) -> 0 | CW63: 0 | CX63: 0 | CY63: 0 | CZ63: 0 | DA63: 0 | DB63: 0 | DC63: 0 | DD63: 0 | DE63: 0 | DF63: 0 | DG63: 0 | DH63: 0 | DI63: 0 | DJ63: 0 | DK63: 0 | DL63: 0 | DM63: 0 | DN63: 0 | DO63: 0 | DP63: 0 | DQ63: 0 | DR63: 0 | DS63: 0 | DT63: N | DU63: 0 | DV63: N | DW63: N | DX63: 0 | DY63: 0 | DZ63: =Q63 -> N | EA63: =Z63 | EB63: =AP63 -> N | EC63: =AJ63 -> N | ED63: =AV63 -> Not Specified | EF63: =MAX(AS63,AA63) -> 0
A64: 61 | B64: 63 | C64: China Communications Construction | D64: Engineering & Construction | E64: Engineering and construction | F64: China | G64: Asia | H64: $139,229 | I64: $937 | J64: -0.44 | K64: $371,057.2 | L64: 204994 | M64: 18 | N64: N | Q64: N | R64: N | AC64: Other | AD64: Other Emission Reduction | AE64: No | AF64: No | AG64: No | AJ64: N | AP64: N | AV64: No | AW64: No | AX64: No | AY64: Y | AZ64: CCCC will significantly reduce carbon emission in key areas, make significant breakthroughs in green and low-carbon technologies, significantly increase the scale of green and low-carbon industries, and reach peak carbon emissions in infrastructure construction by 2030 and in equipment manufacturing by 2028. | BG64: =IF(AND($N64="Y",$P64<=2025),1,0) -> 0 | BH64: =IF(AND($N64="Y",AND($P64>2025,$P64<=2030)),1,0) -> 0 | BI64: =IF(AND($N64="Y",$P64>2030),1,0) -> 0 | BJ64: =MAX(BG64:BI64) -> 0 | BK64: =IF(AND($R64="Y",$U64<=2025),1,0) -> 0 | BL64: =IF(AND($R64="Y",AND($U64>2025,$U64<=2030)),1,0) -> 0 | BM64: =IF(AND($R64="Y",$U64>2030),1,0) -> 0 | BN64: =MAX(BK64:BM64) -> 0 | BO64: =IF(AND($Y64="Y",$AA64<=2025),1,0) -> 0 | BP64: =IF(AND($Y64="Y",AND($AA64>2025,$AA64<=2030)),1,0) -> 0 | BQ64: =IF(AND($Y64="Y",$AA64>2030),1,0) -> 0 | BR64: =IF(AND($AP64="Y",$AS64<=2025),1,0) -> 0 | BS64: =IF(AND($AP64="Y",AND($AS64>2025,$AS64<=2030)),1,0) -> 0 | BT64: =IF(AND($AP64="Y",$AS64>2030),1,0) -> 0 | BU64: =IF(AND(AL64<=2025,CF64=0,AJ64="Y"),1,0) -> 0 | BV64: =IF(AND(AL64>=2026,AL64<=2030,AJ64="Y",CF64=0),1,0) -> 0 | BW64: =IF(AND(AL64>=2031,CF64=0,AJ64="Y"),1,0) -> 0 | BX64: =IF(AND($AJ64="Y",$AL64<=2024),1,0) -> 0 | BY64: =IF(AND($AJ64="Y",AND($AL64>2024,$AL64<=2030)),1,0) -> 0 | BZ64: =IF(AND($AJ64="Y",$AL64>2030),1,0) -> 0 | CA64: =MAX(BX64:BZ64) -> 0 | CB64: =IF(AND(CF64=0,AJ64="Y"),1,0) -> 0 | CC64: =MAX($BO64,$BR64) -> 0 | CD64: =MAX($BP64,$BS64) -> 0 | CE64: =MAX($BQ64,$BT64) -> 0 | CF64: =MAX(CC64:CE64) -> 0 | CG64: =MAX($CF64,$CA64) -> 0 | CH64: =MAX(CF64,CB64) -> 0 | CI64: =IF(AND($AY64="Y",$BA64<=2024),1,0) -> 0 | CJ64: =IF(AND($AY64="Y",AND($BA64>2024,$BA64<=2030)),1,0) -> 0 | CK64: =IF(AND($AY64="Y",$BA64>2030),1,0) -> 1 | CL64: =SUM(CC64,BU64,BK64,BG64) -> 0 | CM64: =SUM(CD64,BV64,BL64,BH64) -> 0 | CN64: =SUM(CE64,BW64,BM64,BI64) -> 0 | CO64: =CF64+CB64+BN64+BJ64 -> 0 | CP64: =MAX(CH64,BN64,BJ64) -> 0 | CQ64: =IF($AV64="Yes",1,0) -> 0 | CR64: =IF($AV64="No",1,0) -> 1 | CS64: =IF($AV64="Not Specified",1,0) -> 0 | CT64: =IF(OR(AND(U64>=2026,U64<=2030),AND(X64>=2026,X64<=2030)),1,"") | CU64: =AA64&" "&AS64 | CV64: =MAX(AA64,AS64) -> 0 | CW64: 0 | CX64: 0 | CY64: 0 | CZ64: 0 | DA64: 0 | DB64: 0 | DC64: 0 | DD64: 0 | DE64: 0 | DF64: 0 | DG64: 0 | DH64: 0 | DI64: 0 | DJ64: 0 | DK64: 0 | DL64: 0 | DM64: 0 | DN64: 0 | DO64: 0 | DP64: 0 | DQ64: 0 | DR64: 0 | DS64: 0 | DT64: N | DU64: 0 | DV64: N | DW64: G | DX64: U | DY64: 0 | DZ64: =Q64 -> N | EA64: =Z64 | EB64: =AP64 -> N | EC64: =AJ64 -> N | ED64: =AV64 -> No | EF64: =MAX(AS64,AA64) -> 0
A65: 62 | B65: 71 | C65: CITIC Group | D65: Diversified Financials | E65: Financial services | F65: China | G65: Asia | H65: $138,940.6 | I65: $3,953.1 | J65: -0.042 | K65: $1,690,451.4 | L65: 214660 | M65: 17 | N65: N | Q65: N | R65: N | AC65: Carbon neutral(ity) | AD65: Carbon Neutral | AE65: Yes | AF65: Yes | AG65: Yes | AH65: 1,2,3 | AI65: C,V | AJ65: Y | AK65: "2060: Achieve the comprehensive integration of a green, low-carbon and recycling industrial system and a clean, low-carbon, safe and efficient energy system, with energy utilization efficiency aligning with world-leading enterprises." | AL65: 2060 | AP65: N | AV65: Not Specified | AW65: Yes (CCS-based removals e.g. BECCS, DACCS) | AX65: No | AY65: N | BG65: =IF(AND($N65="Y",$P65<=2025),1,0) -> 0 | BH65: =IF(AND($N65="Y",AND($P65>2025,$P65<=2030)),1,0) -> 0 | BI65: =IF(AND($N65="Y",$P65>2030),1,0) -> 0 | BJ65: =MAX(BG65:BI65) -> 0 | BK65: =IF(AND($R65="Y",$U65<=2025),1,0) -> 0 | BL65: =IF(AND($R65="Y",AND($U65>2025,$U65<=2030)),1,0) -> 0 | BM65: =IF(AND($R65="Y",$U65>2030),1,0) -> 0 | BN65: =MAX(BK65:BM65) -> 0 | BO65: =IF(AND($Y65="Y",$AA65<=2025),1,0) -> 0 | BP65: =IF(AND($Y65="Y",AND($AA65>2025,$AA65<=2030)),1,0) -> 0 | BQ65: =IF(AND($Y65="Y",$AA65>2030),1,0) -> 0 | BR65: =IF(AND($AP65="Y",$AS65<=2025),1,0) -> 0 | BS65: =IF(AND($AP65="Y",AND($AS65>2025,$AS65<=2030)),1,0) -> 0 | BT65: =IF(AND($AP65="Y",$AS65>2030),1,0) -> 0 | BU65: =IF(AND(AL65<=2025,CF65=0,AJ65="Y"),1,0) -> 0 | BV65: =IF(AND(AL65>=2026,AL65<=2030,AJ65="Y",CF65=0),1,0) -> 0 | BW65: =IF(AND(AL65>=2031,CF65=0,AJ65="Y"),1,0) -> 1 | BX65: =IF(AND($AJ65="Y",$AL65<=2024),1,0) -> 0 | BY65: =IF(AND($AJ65="Y",AND($AL65>2024,$AL65<=2030)),1,0) -> 0 | BZ65: =IF(AND($AJ65="Y",$AL65>2030),1,0) -> 1 | CA65: =MAX(BX65:BZ65) -> 1 | CB65: =IF(AND(CF65=0,AJ65="Y"),1,0) -> 1 | CC65: =MAX($BO65,$BR65) -> 0 | CD65: =MAX($BP65,$BS65) -> 0 | CE65: =MAX($BQ65,$BT65) -> 0 | CF65: =MAX(CC65:CE65) -> 0 | CG65: =MAX($CF65,$CA65) -> 1 | CH65: =MAX(CF65,CB65) -> 1 | CI65: =IF(AND($AY65="Y",$BA65<=2024),1,0) -> 0 | CJ65: =IF(AND($AY65="Y",AND($BA65>2024,$BA65<=2030)),1,0) -> 0 | CK65: =IF(AND($AY65="Y",$BA65>2030),1,0) -> 0 | CL65: =SUM(CC65,BU65,BK65,BG65) -> 0 | CM65: =SUM(CD65,BV65,BL65,BH65) -> 0 | CN65: =SUM(CE65,BW65,BM65,BI65) -> 1 | CO65: =CF65+CB65+BN65+BJ65 -> 1 | CP65: =MAX(CH65,BN65,BJ65) -> 1 | CQ65: =IF($AV65="Yes",1,0) -> 0 | CR65: =IF($AV65="No",1,0) -> 0 | CS65: =IF($AV65="Not Specified",1,0) -> 1 | CT65: =IF(OR(AND(U65>=2026,U65<=2030),AND(X65>=2026,X65<=2030)),1,"") | CU65: =AA65&" "&AS65 | CV65: =MAX(AA65,AS65) -> 0 | CW65: 0 | CX65: 0 | CY65: 0 | CZ65: 0 | DA65: 0 | DB65: 0 | DC65: 0 | DD65: 0 | DE65: 0 | DF65: 0 | DG65: 0 | DH65: 0 | DI65: 0 | DJ65: 0 | DK65: 0 | DL65: 0 | DM65: 0 | DN65: 0 | DO65: 0 | DP65: 0 | DQ65: 0 | DR65: 0 | DS65: 0 | DT65: N | DU65: 0 | DV65: N | DW65: G | DX65: Y, g | DY65: 0 | DZ65: =Q65 -> N | EA65: =Z65 | EB65: =AP65 -> N | EC65: =AJ65 -> Y | ED65: =AV65 -> Not Specified | EF65: =MAX(AS65,AA65) -> 0
A66: 63 | B66: 70 | C66: Alibaba Group Holding | D66: Internet Services and Retailing | E66: Retail | F66: China | G66: Asia | H66: $138,065 | I66: $18,029.4 | J66: 0.615 | K66: $248,629.1 | L66: 124320 | M66: 9 | N66: N | Q66: Y | R66: N | S66: Commitment removed | Y66: N | Z66: Commitment removed | AC66: Carbon neutral(ity) | AD66: Carbon Neutral | AE66: Yes | AF66: Yes | AG66: Yes | AH66: 1,2,3 | AI66: C,V | AJ66: Y | AK66: In 2021, we set the goals of: (1) achieving carbon neutrality in our own operations by 2030; (2) halving the net emissions intensity in the value chain by 2030 (cf. 2024 Alibaba Group ESG Report, p. 9) Baseline year - Jan 2020 - Dec 2020 (cf. 2024 Alibaba Group ESG Report, p. 27). | AL66: 2030 | AP66: N | AQ66: Achieve Net Zero emissions in company operations by 2040. | AR66: Engage top suppliers to set science-based carbon reduction targets by 2026. | AV66: Not Specified | AW66: Yes (nature-based and CCS-based removals) | AX66: No | AY66: N | BG66: =IF(AND($N66="Y",$P66<=2025),1,0) -> 0 | BH66: =IF(AND($N66="Y",AND($P66>2025,$P66<=2030)),1,0) -> 0 | BI66: =IF(AND($N66="Y",$P66>2030),1,0) -> 0 | BJ66: =MAX(BG66:BI66) -> 0 | BK66: =IF(AND($R66="Y",$U66<=2025),1,0) -> 0 | BL66: =IF(AND($R66="Y",AND($U66>2025,$U66<=2030)),1,0) -> 0 | BM66: =IF(AND($R66="Y",$U66>2030),1,0) -> 0 | BN66: =MAX(BK66:BM66) -> 0 | BO66: =IF(AND($Y66="Y",$AA66<=2025),1,0) -> 0 | BP66: =IF(AND($Y66="Y",AND($AA66>2025,$AA66<=2030)),1,0) -> 0 | BQ66: =IF(AND($Y66="Y",$AA66>2030),1,0) -> 0 | BR66: =IF(AND($AP66="Y",$AS66<=2025),1,0) -> 0 | BS66: =IF(AND($AP66="Y",AND($AS66>2025,$AS66<=2030)),1,0) -> 0 | BT66: =IF(AND($AP66="Y",$AS66>2030),1,0) -> 0 | BU66: =IF(AND(AL66<=2025,CF66=0,AJ66="Y"),1,0) -> 0 | BV66: =IF(AND(AL66>=2026,AL66<=2030,AJ66="Y",CF66=0),1,0) -> 1 | BW66: =IF(AND(AL66>=2031,CF66=0,AJ66="Y"),1,0) -> 0 | BX66: =IF(AND($AJ66="Y",$AL66<=2024),1,0) -> 0 | BY66: =IF(AND($AJ66="Y",AND($AL66>2024,$AL66<=2030)),1,0) -> 1 | BZ66: =IF(AND($AJ66="Y",$AL66>2030),1,0) -> 0 | CA66: =MAX(BX66:BZ66) -> 1 | CB66: =IF(AND(CF66=0,AJ66="Y"),1,0) -> 1 | CC66: =MAX($BO66,$BR66) -> 0 | CD66: =MAX($BP66,$BS66) -> 0 | CE66: =MAX($BQ66,$BT66) -> 0 | CF66: =MAX(CC66:CE66) -> 0 | CG66: =MAX($CF66,$CA66) -> 1 | CH66: =MAX(CF66,CB66) -> 1 | CI66: =IF(AND($AY66="Y",$BA66<=2024),1,0) -> 0 | CJ66: =IF(AND($AY66="Y",AND($BA66>2024,$BA66<=2030)),1,0) -> 0 | CK66: =IF(AND($AY66="Y",$BA66>2030),1,0) -> 0 | CL66: =SUM(CC66,BU66,BK66,BG66) -> 0 | CM66: =SUM(CD66,BV66,BL66,BH66) -> 1 | CN66: =SUM(CE66,BW66,BM66,BI66) -> 0 | CO66: =CF66+CB66+BN66+BJ66 -> 1 | CP66: =MAX(CH66,BN66,BJ66) -> 1 | CQ66: =IF($AV66="Yes",1,0) -> 0 | CR66: =IF($AV66="No",1,0) -> 0 | CS66: =IF($AV66="Not Specified",1,0) -> 1 | CT66: =IF(OR(AND(U66>=2026,U66<=2030),AND(X66>=2026,X66<=2030)),1,"") | CU66: =AA66&" "&AS66 | CV66: =MAX(AA66,AS66) -> 0 | CW66: 0 | CX66: 1 | CY66: 0 | CZ66: 1 | DA66: 0 | DB66: 0 | DC66: 0 | DD66: 0 | DE66: 0 | DF66: 1 | DG66: 0 | DH66: 1 | DI66: 0 | DJ66: 0 | DK66: 0 | DL66: 0 | DM66: 1 | DN66: 1 | DO66: 1 | DP66: 1 | DQ66: 0 | DR66: 1 | DS66: 0 | DT66: N | DU66: Yes | DV66: N | DW66: C | DX66: Y | DY66: 0 | DZ66: =Q66 -> Y | EA66: =Z66 -> Commitment removed | EB66: =AP66 -> N | EC66: =AJ66 -> Y | ED66: =AV66 -> Not Specified | EF66: =MAX(AS66,AA66) -> 0
A67: 64 | B67: 68 | C67: Verizon Communications | D67: Telecommunications | E67: Telecommunications and media | F67: U.S. | G67: North America | H67: $134,788 | I67: $17,506 | J67: 0.507 | K67: $384,711 | L67: 99600 | M67: 31 | N67: Y | O67: 2024 | P67: 2030 | Q67: N | R67: N | AC67: Net zero | AD67: Net Zero | AE67: Yes | AF67: Yes | AG67: Yes | AH67: 1,2,3 | AJ67: N | AO67: C,V | AP67: Y | AQ67: 1,2,3 | AR67: Verizon has committed to set an SBTi-approved target to reach net-zero GHG emissions across our value chain (scopes 1, 2 and 3) by 2050._x000d_ _x000d_ From website (https://web.archive.org/web/20250713122219/https://www.verizon.com/about/responsibility/sustainability) | AS67: 2050 | AV67: Not Specified | AW67: Yes (unspecified) | AX67: No | AY67: N | BG67: =IF(AND($N67="Y",$P67<=2025),1,0) -> 0 | BH67: =IF(AND($N67="Y",AND($P67>2025,$P67<=2030)),1,0) -> 1 | BI67: =IF(AND($N67="Y",$P67>2030),1,0) -> 0 | BJ67: =MAX(BG67:BI67) -> 1 | BK67: =IF(AND($R67="Y",$U67<=2025),1,0) -> 0 | BL67: =IF(AND($R67="Y",AND($U67>2025,$U67<=2030)),1,0) -> 0 | BM67: =IF(AND($R67="Y",$U67>2030),1,0) -> 0 | BN67: =MAX(BK67:BM67) -> 0 | BO67: =IF(AND($Y67="Y",$AA67<=2025),1,0) -> 0 | BP67: =IF(AND($Y67="Y",AND($AA67>2025,$AA67<=2030)),1,0) -> 0 | BQ67: =IF(AND($Y67="Y",$AA67>2030),1,0) -> 0 | BR67: =IF(AND($AP67="Y",$AS67<=2025),1,0) -> 0 | BS67: =IF(AND($AP67="Y",AND($AS67>2025,$AS67<=2030)),1,0) -> 0 | BT67: =IF(AND($AP67="Y",$AS67>2030),1,0) -> 1 | BU67: =IF(AND(AL67<=2025,CF67=0,AJ67="Y"),1,0) -> 0 | BV67: =IF(AND(AL67>=2026,AL67<=2030,AJ67="Y",CF67=0),1,0) -> 0 | BW67: =IF(AND(AL67>=2031,CF67=0,AJ67="Y"),1,0) -> 0 | BX67: =IF(AND($AJ67="Y",$AL67<=2024),1,0) -> 0 | BY67: =IF(AND($AJ67="Y",AND($AL67>2024,$AL67<=2030)),1,0) -> 0 | BZ67: =IF(AND($AJ67="Y",$AL67>2030),1,0) -> 0 | CA67: =MAX(BX67:BZ67) -> 0 | CB67: =IF(AND(CF67=0,AJ67="Y"),1,0) -> 0 | CC67: =MAX($BO67,$BR67) -> 0 | CD67: =MAX($BP67,$BS67) -> 0 | CE67: =MAX($BQ67,$BT67) -> 1 | CF67: =MAX(CC67:CE67) -> 1 | CG67: =MAX($CF67,$CA67) -> 1 | CH67: =MAX(CF67,CB67) -> 1 | CI67: =IF(AND($AY67="Y",$BA67<=2024),1,0) -> 0 | CJ67: =IF(AND($AY67="Y",AND($BA67>2024,$BA67<=2030)),1,0) -> 0 | CK67: =IF(AND($AY67="Y",$BA67>2030),1,0) -> 0 | CL67: =SUM(CC67,BU67,BK67,BG67) -> 0 | CM67: =SUM(CD67,BV67,BL67,BH67) -> 1 | CN67: =SUM(CE67,BW67,BM67,BI67) -> 1 | CO67: =CF67+CB67+BN67+BJ67 -> 2 | CP67: =MAX(CH67,BN67,BJ67) -> 1 | CQ67: =IF($AV67="Yes",1,0) -> 0 | CR67: =IF($AV67="No",1,0) -> 0 | CS67: =IF($AV67="Not Specified",1,0) -> 1 | CT67: =IF(OR(AND(U67>=2026,U67<=2030),AND(X67>=2026,X67<=2030)),1,"") | CU67: =AA67&" "&AS67 -> 2050 | CV67: =MAX(AA67,AS67) -> 2050 | CW67: 0 | CX67: 0 | CY67: 0 | CZ67: 0 | DA67: 0 | DB67: 0 | DC67: 1 | DD67: 1 | DE67: 0 | DF67: 0 | DG67: 1 | DH67: 1 | DI67: 0 | DJ67: 1 | DK67: 0 | DL67: 1 | DM67: 1 | DN67: 0 | DO67: 1 | DP67: 0 | DQ67: 0 | DR67: 1 | DS67: 0 | DT67: Y | DU67: No | DV67: C | DW67: N | DX67: 0 | DY67: U | DZ67: =Q67 -> N | EA67: =Z67 | EB67: =AP67 -> Y | EC67: =AJ67 -> N | ED67: =AV67 -> Not Specified | EF67: =MAX(AS67,AA67) -> 2050
