Workbook

Sheet target portfolio 
A1: company | B1: country | C1: sector | D1: 2021 cc yes/no | E1: 2022 cc yes/no | F1: 2023 cc yes/no | G1: 2024 cc yes/no | H1: 2025 cc yes/no | I1: 2021 cn | J1: 2022 cn | K1: 2023 cn | L1: 2024 cn | M1: 2025 cn | N1: 2021 re | O1: 2022 re | P1: 2023 re | Q1: 2024 re | R1: 2025 re | S1: 2021 sbti nt | T1: 2022 sbti nt | U1: 2023 sbti nt | V1: 2024 sbti nt | W1: 2025 sbti nt | X1: 2021 nz | Y1: 2022 nz | Z1: 2023 nz | AA1: 2024 nz | AB1: 2025 nz
A2: 3M | E2: =_xlfn.XLOOKUP(A2,'2022'!A:A,'2022'!AA:AA) | F2: =_xlfn.XLOOKUP(A2,'2023'!B:B,'2023'!AG:AG) -> U | G2: =_xlfn.XLOOKUP(A2,'2024'!B:B,'2024'!BL:BL) -> 1 | H2: =_xlfn.XLOOKUP(A2,'2025'!A:A,'2025'!G:G) -> #N/A | I2: =_xlfn.XLOOKUP(A2,'2021'!A:A,'2021'!U:U) -> 1 | J2: =_xlfn.XLOOKUP(A2,'2022'!A:A,'2022'!V:V) -> 1 | K2: =_xlfn.XLOOKUP(A2,'2023'!B:B,'2023'!AD:AD) -> 1 | L2: =_xlfn.XLOOKUP(A2,'2024'!B:B,'2024'!AV:AV) -> 1 | M2: =_xlfn.XLOOKUP(A2,'2025'!A:A,'2025'!G:G) -> #N/A | N2: =_xlfn.XLOOKUP(A2,'2021'!A:A,'2021'!E:E) -> Y | O2: =_xlfn.XLOOKUP(A2,'2022'!A:A,'2022'!E:E) -> Y | P2: =_xlfn.XLOOKUP(A2,'2023'!B:B,'2023'!G:G) -> Y | Q2: =_xlfn.XLOOKUP(A2,'2024'!B:B,'2024'!BH:BH) -> 1 | R2: =_xlfn.XLOOKUP(A2,'2025'!A:A,'2025'!B:B) -> #N/A | S2: =_xlfn.XLOOKUP(A2,'2021'!A:A,'2021'!X:X) | T2: =_xlfn.XLOOKUP(A2,'2022'!A:A,'2022'!X:X) | U2: =_xlfn.XLOOKUP(A2,'2023'!B:B,'2023'!AF:AF) | V2: =_xlfn.XLOOKUP(A2,'2024'!B:B,'2024'!BW:BW) | W2: =_xlfn.XLOOKUP(A2,'2025'!A:A,'2025'!C:C) -> #N/A | X2: =_xlfn.XLOOKUP(A2,'2021'!A:A,'2021'!V:V) | Y2: =_xlfn.XLOOKUP(A2,'2022'!A:A,'2022'!W:W) | Z2: =_xlfn.XLOOKUP(A2,'2023'!B:B,'2023'!AE:AE) | AA2: =_xlfn.XLOOKUP(A2,'2024'!B:B,'2024'!AZ:AZ) -> 0 | AB2: =_xlfn.XLOOKUP(A2,'2025'!A:A,'2025'!F:F) -> #N/A
A3: ABB | E3: =_xlfn.XLOOKUP(A3,'2022'!A:A,'2022'!AA:AA) -> Y | F3: =_xlfn.XLOOKUP(A3,'2023'!B:B,'2023'!AG:AG) -> #N/A | G3: =_xlfn.XLOOKUP(A3,'2024'!B:B,'2024'!BL:BL) -> 1 | H3: =_xlfn.XLOOKUP(A3,'2025'!A:A,'2025'!G:G) -> 0 | I3: =_xlfn.XLOOKUP(A3,'2021'!A:A,'2021'!U:U) -> 1 | J3: =_xlfn.XLOOKUP(A3,'2022'!A:A,'2022'!V:V) -> 1 | K3: =_xlfn.XLOOKUP(A3,'2023'!B:B,'2023'!AD:AD) -> #N/A | L3: =_xlfn.XLOOKUP(A3,'2024'!B:B,'2024'!AV:AV) | M3: =_xlfn.XLOOKUP(A3,'2025'!A:A,'2025'!G:G) -> 0 | N3: =_xlfn.XLOOKUP(A3,'2021'!A:A,'2021'!E:E) -> Y | O3: =_xlfn.XLOOKUP(A3,'2022'!A:A,'2022'!E:E) -> Y | P3: =_xlfn.XLOOKUP(A3,'2023'!B:B,'2023'!G:G) -> #N/A | Q3: =_xlfn.XLOOKUP(A3,'2024'!B:B,'2024'!BH:BH) -> 1 | R3: =_xlfn.XLOOKUP(A3,'2025'!A:A,'2025'!B:B) -> 1 | S3: =_xlfn.XLOOKUP(A3,'2021'!A:A,'2021'!X:X) -> 1 | T3: =_xlfn.XLOOKUP(A3,'2022'!A:A,'2022'!X:X) -> 1 | U3: =_xlfn.XLOOKUP(A3,'2023'!B:B,'2023'!AF:AF) -> #N/A | V3: =_xlfn.XLOOKUP(A3,'2024'!B:B,'2024'!BW:BW) -> 1 | W3: =_xlfn.XLOOKUP(A3,'2025'!A:A,'2025'!C:C) -> 1 | X3: =_xlfn.XLOOKUP(A3,'2021'!A:A,'2021'!V:V) | Y3: =_xlfn.XLOOKUP(A3,'2022'!A:A,'2022'!W:W) | Z3: =_xlfn.XLOOKUP(A3,'2023'!B:B,'2023'!AE:AE) -> #N/A | AA3: =_xlfn.XLOOKUP(A3,'2024'!B:B,'2024'!AZ:AZ) -> 1 | AB3: =_xlfn.XLOOKUP(A3,'2025'!A:A,'2025'!F:F) -> 1
A4: ACS | E4: =_xlfn.XLOOKUP(A4,'2022'!A:A,'2022'!AA:AA) | F4: =_xlfn.XLOOKUP(A4,'2023'!B:B,'2023'!AG:AG) -> Y | G4: =_xlfn.XLOOKUP(A4,'2024'!B:B,'2024'!BL:BL) -> 0 | H4: =_xlfn.XLOOKUP(A4,'2025'!A:A,'2025'!G:G) -> 1 | I4: =_xlfn.XLOOKUP(A4,'2021'!A:A,'2021'!U:U) | J4: =_xlfn.XLOOKUP(A4,'2022'!A:A,'2022'!V:V) -> 1 | K4: =_xlfn.XLOOKUP(A4,'2023'!B:B,'2023'!AD:AD) -> 1 | L4: =_xlfn.XLOOKUP(A4,'2024'!B:B,'2024'!AV:AV) -> 1 | M4: =_xlfn.XLOOKUP(A4,'2025'!A:A,'2025'!G:G) -> 1 | N4: =_xlfn.XLOOKUP(A4,'2021'!A:A,'2021'!E:E) -> 0 | O4: =_xlfn.XLOOKUP(A4,'2022'!A:A,'2022'!E:E) -> 0 | P4: =_xlfn.XLOOKUP(A4,'2023'!B:B,'2023'!G:G) -> 0 | Q4: =_xlfn.XLOOKUP(A4,'2024'!B:B,'2024'!BH:BH) -> 0 | R4: =_xlfn.XLOOKUP(A4,'2025'!A:A,'2025'!B:B) -> 0 | S4: =_xlfn.XLOOKUP(A4,'2021'!A:A,'2021'!X:X) | T4: =_xlfn.XLOOKUP(A4,'2022'!A:A,'2022'!X:X) | U4: =_xlfn.XLOOKUP(A4,'2023'!B:B,'2023'!AF:AF) | V4: =_xlfn.XLOOKUP(A4,'2024'!B:B,'2024'!BW:BW) | W4: =_xlfn.XLOOKUP(A4,'2025'!A:A,'2025'!C:C) -> 0 | X4: =_xlfn.XLOOKUP(A4,'2021'!A:A,'2021'!V:V) | Y4: =_xlfn.XLOOKUP(A4,'2022'!A:A,'2022'!W:W) | Z4: =_xlfn.XLOOKUP(A4,'2023'!B:B,'2023'!AE:AE) | AA4: =_xlfn.XLOOKUP(A4,'2024'!B:B,'2024'!AZ:AZ) -> 0 | AB4: =_xlfn.XLOOKUP(A4,'2025'!A:A,'2025'!F:F) -> 1
A5: AEON | E5: =_xlfn.XLOOKUP(A5,'2022'!A:A,'2022'!AA:AA) -> N | F5: =_xlfn.XLOOKUP(A5,'2023'!B:B,'2023'!AG:AG) -> 0 | G5: =_xlfn.XLOOKUP(A5,'2024'!B:B,'2024'!BL:BL) -> 1 | H5: =_xlfn.XLOOKUP(A5,'2025'!A:A,'2025'!G:G) -> 0 | I5: =_xlfn.XLOOKUP(A5,'2021'!A:A,'2021'!U:U) | J5: =_xlfn.XLOOKUP(A5,'2022'!A:A,'2022'!V:V) | K5: =_xlfn.XLOOKUP(A5,'2023'!B:B,'2023'!AD:AD) | L5: =_xlfn.XLOOKUP(A5,'2024'!B:B,'2024'!AV:AV) | M5: =_xlfn.XLOOKUP(A5,'2025'!A:A,'2025'!G:G) -> 0 | N5: =_xlfn.XLOOKUP(A5,'2021'!A:A,'2021'!E:E) -> Y | O5: =_xlfn.XLOOKUP(A5,'2022'!A:A,'2022'!E:E) -> Y | P5: =_xlfn.XLOOKUP(A5,'2023'!B:B,'2023'!G:G) -> Y | Q5: =_xlfn.XLOOKUP(A5,'2024'!B:B,'2024'!BH:BH) -> 1 | R5: =_xlfn.XLOOKUP(A5,'2025'!A:A,'2025'!B:B) -> 1 | S5: =_xlfn.XLOOKUP(A5,'2021'!A:A,'2021'!X:X) -> 1 | T5: =_xlfn.XLOOKUP(A5,'2022'!A:A,'2022'!X:X) -> 1 | U5: =_xlfn.XLOOKUP(A5,'2023'!B:B,'2023'!AF:AF) -> 1 | V5: =_xlfn.XLOOKUP(A5,'2024'!B:B,'2024'!BW:BW) -> 1 | W5: =_xlfn.XLOOKUP(A5,'2025'!A:A,'2025'!C:C) -> 1 | X5: =_xlfn.XLOOKUP(A5,'2021'!A:A,'2021'!V:V) -> 1 | Y5: =_xlfn.XLOOKUP(A5,'2022'!A:A,'2022'!W:W) -> 1 | Z5: =_xlfn.XLOOKUP(A5,'2023'!B:B,'2023'!AE:AE) -> 1 | AA5: =_xlfn.XLOOKUP(A5,'2024'!B:B,'2024'!AZ:AZ) -> 1 | AB5: =_xlfn.XLOOKUP(A5,'2025'!A:A,'2025'!F:F) -> 1
A6: AIA Group | E6: =_xlfn.XLOOKUP(A6,'2022'!A:A,'2022'!AA:AA) | F6: =_xlfn.XLOOKUP(A6,'2023'!B:B,'2023'!AG:AG) -> #N/A | G6: =_xlfn.XLOOKUP(A6,'2024'!B:B,'2024'!BL:BL) -> 0 | H6: =_xlfn.XLOOKUP(A6,'2025'!A:A,'2025'!G:G) -> 0 | I6: =_xlfn.XLOOKUP(A6,'2021'!A:A,'2021'!U:U) | J6: =_xlfn.XLOOKUP(A6,'2022'!A:A,'2022'!V:V) | K6: =_xlfn.XLOOKUP(A6,'2023'!B:B,'2023'!AD:AD) -> #N/A | L6: =_xlfn.XLOOKUP(A6,'2024'!B:B,'2024'!AV:AV) | M6: =_xlfn.XLOOKUP(A6,'2025'!A:A,'2025'!G:G) -> 0 | N6: =_xlfn.XLOOKUP(A6,'2021'!A:A,'2021'!E:E) -> 0 | O6: =_xlfn.XLOOKUP(A6,'2022'!A:A,'2022'!E:E) -> 0 | P6: =_xlfn.XLOOKUP(A6,'2023'!B:B,'2023'!G:G) -> #N/A | Q6: =_xlfn.XLOOKUP(A6,'2024'!B:B,'2024'!BH:BH) -> 0 | R6: =_xlfn.XLOOKUP(A6,'2025'!A:A,'2025'!B:B) -> 0 | S6: =_xlfn.XLOOKUP(A6,'2021'!A:A,'2021'!X:X) | T6: =_xlfn.XLOOKUP(A6,'2022'!A:A,'2022'!X:X) | U6: =_xlfn.XLOOKUP(A6,'2023'!B:B,'2023'!AF:AF) -> #N/A | V6: =_xlfn.XLOOKUP(A6,'2024'!B:B,'2024'!BW:BW) -> 1 | W6: =_xlfn.XLOOKUP(A6,'2025'!A:A,'2025'!C:C) -> 1 | X6: =_xlfn.XLOOKUP(A6,'2021'!A:A,'2021'!V:V) | Y6: =_xlfn.XLOOKUP(A6,'2022'!A:A,'2022'!W:W) -> 1 | Z6: =_xlfn.XLOOKUP(A6,'2023'!B:B,'2023'!AE:AE) -> #N/A | AA6: =_xlfn.XLOOKUP(A6,'2024'!B:B,'2024'!AZ:AZ) -> 1 | AB6: =_xlfn.XLOOKUP(A6,'2025'!A:A,'2025'!F:F) -> 1
A7: AIG | E7: =_xlfn.XLOOKUP(A7,'2022'!A:A,'2022'!AA:AA) -> #N/A | F7: =_xlfn.XLOOKUP(A7,'2023'!B:B,'2023'!AG:AG) -> #N/A | G7: =_xlfn.XLOOKUP(A7,'2024'!B:B,'2024'!BL:BL) -> 0 | H7: =_xlfn.XLOOKUP(A7,'2025'!A:A,'2025'!G:G) -> #N/A | I7: =_xlfn.XLOOKUP(A7,'2021'!A:A,'2021'!U:U) -> #N/A | J7: =_xlfn.XLOOKUP(A7,'2022'!A:A,'2022'!V:V) -> #N/A | K7: =_xlfn.XLOOKUP(A7,'2023'!B:B,'2023'!AD:AD) -> #N/A | L7: =_xlfn.XLOOKUP(A7,'2024'!B:B,'2024'!AV:AV) | M7: =_xlfn.XLOOKUP(A7,'2025'!A:A,'2025'!G:G) -> #N/A | N7: =_xlfn.XLOOKUP(A7,'2021'!A:A,'2021'!E:E) -> #N/A | O7: =_xlfn.XLOOKUP(A7,'2022'!A:A,'2022'!E:E) -> #N/A | P7: =_xlfn.XLOOKUP(A7,'2023'!B:B,'2023'!G:G) -> #N/A | Q7: =_xlfn.XLOOKUP(A7,'2024'!B:B,'2024'!BH:BH) -> 0 | R7: =_xlfn.XLOOKUP(A7,'2025'!A:A,'2025'!B:B) -> #N/A | S7: =_xlfn.XLOOKUP(A7,'2021'!A:A,'2021'!X:X) -> #N/A | T7: =_xlfn.XLOOKUP(A7,'2022'!A:A,'2022'!X:X) -> #N/A | U7: =_xlfn.XLOOKUP(A7,'2023'!B:B,'2023'!AF:AF) -> #N/A | V7: =_xlfn.XLOOKUP(A7,'2024'!B:B,'2024'!BW:BW) | W7: =_xlfn.XLOOKUP(A7,'2025'!A:A,'2025'!C:C) -> #N/A | X7: =_xlfn.XLOOKUP(A7,'2021'!A:A,'2021'!V:V) -> #N/A | Y7: =_xlfn.XLOOKUP(A7,'2022'!A:A,'2022'!W:W) -> #N/A | Z7: =_xlfn.XLOOKUP(A7,'2023'!B:B,'2023'!AE:AE) -> #N/A | AA7: =_xlfn.XLOOKUP(A7,'2024'!B:B,'2024'!AZ:AZ) -> 1 | AB7: =_xlfn.XLOOKUP(A7,'2025'!A:A,'2025'!F:F) -> #N/A
A8: ANZ Group Holdings | E8: =_xlfn.XLOOKUP(A8,'2022'!A:A,'2022'!AA:AA) -> #N/A | F8: =_xlfn.XLOOKUP(A8,'2023'!B:B,'2023'!AG:AG) -> #N/A | G8: =_xlfn.XLOOKUP(A8,'2024'!B:B,'2024'!BL:BL) -> 0 | H8: =_xlfn.XLOOKUP(A8,'2025'!A:A,'2025'!G:G) -> 1 | I8: =_xlfn.XLOOKUP(A8,'2021'!A:A,'2021'!U:U) -> #N/A | J8: =_xlfn.XLOOKUP(A8,'2022'!A:A,'2022'!V:V) -> #N/A | K8: =_xlfn.XLOOKUP(A8,'2023'!B:B,'2023'!AD:AD) -> #N/A | L8: =_xlfn.XLOOKUP(A8,'2024'!B:B,'2024'!AV:AV) | M8: =_xlfn.XLOOKUP(A8,'2025'!A:A,'2025'!G:G) -> 1 | N8: =_xlfn.XLOOKUP(A8,'2021'!A:A,'2021'!E:E) -> #N/A | O8: =_xlfn.XLOOKUP(A8,'2022'!A:A,'2022'!E:E) -> #N/A | P8: =_xlfn.XLOOKUP(A8,'2023'!B:B,'2023'!G:G) -> #N/A | Q8: =_xlfn.XLOOKUP(A8,'2024'!B:B,'2024'!BH:BH) -> 1 | R8: =_xlfn.XLOOKUP(A8,'2025'!A:A,'2025'!B:B) -> 1 | S8: =_xlfn.XLOOKUP(A8,'2021'!A:A,'2021'!X:X) -> #N/A | T8: =_xlfn.XLOOKUP(A8,'2022'!A:A,'2022'!X:X) -> #N/A | U8: =_xlfn.XLOOKUP(A8,'2023'!B:B,'2023'!AF:AF) -> #N/A | V8: =_xlfn.XLOOKUP(A8,'2024'!B:B,'2024'!BW:BW) | W8: =_xlfn.XLOOKUP(A8,'2025'!A:A,'2025'!C:C) -> 0 | X8: =_xlfn.XLOOKUP(A8,'2021'!A:A,'2021'!V:V) -> #N/A | Y8: =_xlfn.XLOOKUP(A8,'2022'!A:A,'2022'!W:W) -> #N/A | Z8: =_xlfn.XLOOKUP(A8,'2023'!B:B,'2023'!AE:AE) -> #N/A | AA8: =_xlfn.XLOOKUP(A8,'2024'!B:B,'2024'!AZ:AZ) -> 1 | AB8: =_xlfn.XLOOKUP(A8,'2025'!A:A,'2025'!F:F) -> 0
A9: AT&T | E9: =_xlfn.XLOOKUP(A9,'2022'!A:A,'2022'!AA:AA) | F9: =_xlfn.XLOOKUP(A9,'2023'!B:B,'2023'!AG:AG) -> Y | G9: =_xlfn.XLOOKUP(A9,'2024'!B:B,'2024'!BL:BL) -> 1 | H9: =_xlfn.XLOOKUP(A9,'2025'!A:A,'2025'!G:G) -> 1 | I9: =_xlfn.XLOOKUP(A9,'2021'!A:A,'2021'!U:U) -> 1 | J9: =_xlfn.XLOOKUP(A9,'2022'!A:A,'2022'!V:V) -> 1 | K9: =_xlfn.XLOOKUP(A9,'2023'!B:B,'2023'!AD:AD) -> 1 | L9: =_xlfn.XLOOKUP(A9,'2024'!B:B,'2024'!AV:AV) -> 1 | M9: =_xlfn.XLOOKUP(A9,'2025'!A:A,'2025'!G:G) -> 1 | N9: =_xlfn.XLOOKUP(A9,'2021'!A:A,'2021'!E:E) -> 0 | O9: =_xlfn.XLOOKUP(A9,'2022'!A:A,'2022'!E:E) -> 0 | P9: =_xlfn.XLOOKUP(A9,'2023'!B:B,'2023'!G:G) -> 0 | Q9: =_xlfn.XLOOKUP(A9,'2024'!B:B,'2024'!BH:BH) -> 0 | R9: =_xlfn.XLOOKUP(A9,'2025'!A:A,'2025'!B:B) -> 0 | S9: =_xlfn.XLOOKUP(A9,'2021'!A:A,'2021'!X:X) -> 1 | T9: =_xlfn.XLOOKUP(A9,'2022'!A:A,'2022'!X:X) -> 1 | U9: =_xlfn.XLOOKUP(A9,'2023'!B:B,'2023'!AF:AF) -> 1 | V9: =_xlfn.XLOOKUP(A9,'2024'!B:B,'2024'!BW:BW) -> 1 | W9: =_xlfn.XLOOKUP(A9,'2025'!A:A,'2025'!C:C) -> 1 | X9: =_xlfn.XLOOKUP(A9,'2021'!A:A,'2021'!V:V) | Y9: =_xlfn.XLOOKUP(A9,'2022'!A:A,'2022'!W:W) | Z9: =_xlfn.XLOOKUP(A9,'2023'!B:B,'2023'!AE:AE) | AA9: =_xlfn.XLOOKUP(A9,'2024'!B:B,'2024'!AZ:AZ) -> 0 | AB9: =_xlfn.XLOOKUP(A9,'2025'!A:A,'2025'!F:F) -> 1
A10: AXA | E10: =_xlfn.XLOOKUP(A10,'2022'!A:A,'2022'!AA:AA) -> Y | F10: =_xlfn.XLOOKUP(A10,'2023'!B:B,'2023'!AG:AG) -> Y | G10: =_xlfn.XLOOKUP(A10,'2024'!B:B,'2024'!BL:BL) -> 1 | H10: =_xlfn.XLOOKUP(A10,'2025'!A:A,'2025'!G:G) -> 1 | I10: =_xlfn.XLOOKUP(A10,'2021'!A:A,'2021'!U:U) -> 1 | J10: =_xlfn.XLOOKUP(A10,'2022'!A:A,'2022'!V:V) -> 1 | K10: =_xlfn.XLOOKUP(A10,'2023'!B:B,'2023'!AD:AD) | L10: =_xlfn.XLOOKUP(A10,'2024'!B:B,'2024'!AV:AV) | M10: =_xlfn.XLOOKUP(A10,'2025'!A:A,'2025'!G:G) -> 1 | N10: =_xlfn.XLOOKUP(A10,'2021'!A:A,'2021'!E:E) -> Y | O10: =_xlfn.XLOOKUP(A10,'2022'!A:A,'2022'!E:E) -> Y | P10: =_xlfn.XLOOKUP(A10,'2023'!B:B,'2023'!G:G) -> Y | Q10: =_xlfn.XLOOKUP(A10,'2024'!B:B,'2024'!BH:BH) -> 1 | R10: =_xlfn.XLOOKUP(A10,'2025'!A:A,'2025'!B:B) -> 1 | S10: =_xlfn.XLOOKUP(A10,'2021'!A:A,'2021'!X:X) | T10: =_xlfn.XLOOKUP(A10,'2022'!A:A,'2022'!X:X) | U10: =_xlfn.XLOOKUP(A10,'2023'!B:B,'2023'!AF:AF) | V10: =_xlfn.XLOOKUP(A10,'2024'!B:B,'2024'!BW:BW) | W10: =_xlfn.XLOOKUP(A10,'2025'!A:A,'2025'!C:C) -> 0 | X10: =_xlfn.XLOOKUP(A10,'2021'!A:A,'2021'!V:V) -> 1 | Y10: =_xlfn.XLOOKUP(A10,'2022'!A:A,'2022'!W:W) -> 1 | Z10: =_xlfn.XLOOKUP(A10,'2023'!B:B,'2023'!AE:AE) -> 1 | AA10: =_xlfn.XLOOKUP(A10,'2024'!B:B,'2024'!AZ:AZ) -> 1 | AB10: =_xlfn.XLOOKUP(A10,'2025'!A:A,'2025'!F:F) -> 1
A11: AbbVie | E11: =_xlfn.XLOOKUP(A11,'2022'!A:A,'2022'!AA:AA) | F11: =_xlfn.XLOOKUP(A11,'2023'!B:B,'2023'!AG:AG) -> 0 | G11: =_xlfn.XLOOKUP(A11,'2024'!B:B,'2024'!BL:BL) -> 1 | H11: =_xlfn.XLOOKUP(A11,'2025'!A:A,'2025'!G:G) -> 0 | I11: =_xlfn.XLOOKUP(A11,'2021'!A:A,'2021'!U:U) | J11: =_xlfn.XLOOKUP(A11,'2022'!A:A,'2022'!V:V) | K11: =_xlfn.XLOOKUP(A11,'2023'!B:B,'2023'!AD:AD) | L11: =_xlfn.XLOOKUP(A11,'2024'!B:B,'2024'!AV:AV) | M11: =_xlfn.XLOOKUP(A11,'2025'!A:A,'2025'!G:G) -> 0 | N11: =_xlfn.XLOOKUP(A11,'2021'!A:A,'2021'!E:E) -> 0 | O11: =_xlfn.XLOOKUP(A11,'2022'!A:A,'2022'!E:E) -> 0 | P11: =_xlfn.XLOOKUP(A11,'2023'!B:B,'2023'!G:G) -> 0 | Q11: =_xlfn.XLOOKUP(A11,'2024'!B:B,'2024'!BH:BH) -> 0 | R11: =_xlfn.XLOOKUP(A11,'2025'!A:A,'2025'!B:B) -> 0 | S11: =_xlfn.XLOOKUP(A11,'2021'!A:A,'2021'!X:X) | T11: =_xlfn.XLOOKUP(A11,'2022'!A:A,'2022'!X:X) | U11: =_xlfn.XLOOKUP(A11,'2023'!B:B,'2023'!AF:AF) -> 1 | V11: =_xlfn.XLOOKUP(A11,'2024'!B:B,'2024'!BW:BW) -> 1 | W11: =_xlfn.XLOOKUP(A11,'2025'!A:A,'2025'!C:C) -> 1 | X11: =_xlfn.XLOOKUP(A11,'2021'!A:A,'2021'!V:V) | Y11: =_xlfn.XLOOKUP(A11,'2022'!A:A,'2022'!W:W) | Z11: =_xlfn.XLOOKUP(A11,'2023'!B:B,'2023'!AE:AE) | AA11: =_xlfn.XLOOKUP(A11,'2024'!B:B,'2024'!AZ:AZ) -> 1 | AB11: =_xlfn.XLOOKUP(A11,'2025'!A:A,'2025'!F:F) -> 0
A12: Abbott Laboratories | E12: =_xlfn.XLOOKUP(A12,'2022'!A:A,'2022'!AA:AA) | F12: =_xlfn.XLOOKUP(A12,'2023'!B:B,'2023'!AG:AG) -> 0 | G12: =_xlfn.XLOOKUP(A12,'2024'!B:B,'2024'!BL:BL) -> 0 | H12: =_xlfn.XLOOKUP(A12,'2025'!A:A,'2025'!G:G) -> 0 | I12: =_xlfn.XLOOKUP(A12,'2021'!A:A,'2021'!U:U) | J12: =_xlfn.XLOOKUP(A12,'2022'!A:A,'2022'!V:V) | K12: =_xlfn.XLOOKUP(A12,'2023'!B:B,'2023'!AD:AD) | L12: =_xlfn.XLOOKUP(A12,'2024'!B:B,'2024'!AV:AV) | M12: =_xlfn.XLOOKUP(A12,'2025'!A:A,'2025'!G:G) -> 0 | N12: =_xlfn.XLOOKUP(A12,'2021'!A:A,'2021'!E:E) -> 0 | O12: =_xlfn.XLOOKUP(A12,'2022'!A:A,'2022'!E:E) -> 0 | P12: =_xlfn.XLOOKUP(A12,'2023'!B:B,'2023'!G:G) -> 0 | Q12: =_xlfn.XLOOKUP(A12,'2024'!B:B,'2024'!BH:BH) -> 0 | R12: =_xlfn.XLOOKUP(A12,'2025'!A:A,'2025'!B:B) -> 0 | S12: =_xlfn.XLOOKUP(A12,'2021'!A:A,'2021'!X:X) | T12: =_xlfn.XLOOKUP(A12,'2022'!A:A,'2022'!X:X) | U12: =_xlfn.XLOOKUP(A12,'2023'!B:B,'2023'!AF:AF) -> 1 | V12: =_xlfn.XLOOKUP(A12,'2024'!B:B,'2024'!BW:BW) -> 1 | W12: =_xlfn.XLOOKUP(A12,'2025'!A:A,'2025'!C:C) -> 0 | X12: =_xlfn.XLOOKUP(A12,'2021'!A:A,'2021'!V:V) | Y12: =_xlfn.XLOOKUP(A12,'2022'!A:A,'2022'!W:W) | Z12: =_xlfn.XLOOKUP(A12,'2023'!B:B,'2023'!AE:AE) | AA12: =_xlfn.XLOOKUP(A12,'2024'!B:B,'2024'!AZ:AZ) -> 0 | AB12: =_xlfn.XLOOKUP(A12,'2025'!A:A,'2025'!F:F) -> 1
A13: Accenture | E13: =_xlfn.XLOOKUP(A13,'2022'!A:A,'2022'!AA:AA) | F13: =_xlfn.XLOOKUP(A13,'2023'!B:B,'2023'!AG:AG) -> 0 | G13: =_xlfn.XLOOKUP(A13,'2024'!B:B,'2024'!BL:BL) -> 1 | H13: =_xlfn.XLOOKUP(A13,'2025'!A:A,'2025'!G:G) -> 0 | I13: =_xlfn.XLOOKUP(A13,'2021'!A:A,'2021'!U:U) | J13: =_xlfn.XLOOKUP(A13,'2022'!A:A,'2022'!V:V) | K13: =_xlfn.XLOOKUP(A13,'2023'!B:B,'2023'!AD:AD) | L13: =_xlfn.XLOOKUP(A13,'2024'!B:B,'2024'!AV:AV) | M13: =_xlfn.XLOOKUP(A13,'2025'!A:A,'2025'!G:G) -> 0 | N13: =_xlfn.XLOOKUP(A13,'2021'!A:A,'2021'!E:E) -> Y | O13: =_xlfn.XLOOKUP(A13,'2022'!A:A,'2022'!E:E) -> Y | P13: =_xlfn.XLOOKUP(A13,'2023'!B:B,'2023'!G:G) -> Y | Q13: =_xlfn.XLOOKUP(A13,'2024'!B:B,'2024'!BH:BH) -> 1 | R13: =_xlfn.XLOOKUP(A13,'2025'!A:A,'2025'!B:B) -> 1 | S13: =_xlfn.XLOOKUP(A13,'2021'!A:A,'2021'!X:X) -> 1 | T13: =_xlfn.XLOOKUP(A13,'2022'!A:A,'2022'!X:X) -> 1 | U13: =_xlfn.XLOOKUP(A13,'2023'!B:B,'2023'!AF:AF) -> 1 | V13: =_xlfn.XLOOKUP(A13,'2024'!B:B,'2024'!BW:BW) -> 1 | W13: =_xlfn.XLOOKUP(A13,'2025'!A:A,'2025'!C:C) -> 1 | X13: =_xlfn.XLOOKUP(A13,'2021'!A:A,'2021'!V:V) -> 1 | Y13: =_xlfn.XLOOKUP(A13,'2022'!A:A,'2022'!W:W) -> 1 | Z13: =_xlfn.XLOOKUP(A13,'2023'!B:B,'2023'!AE:AE) -> 1 | AA13: =_xlfn.XLOOKUP(A13,'2024'!B:B,'2024'!AZ:AZ) -> 1 | AB13: =_xlfn.XLOOKUP(A13,'2025'!A:A,'2025'!F:F) -> 1
... A652: Zurich Insurance Group | E652: =_xlfn.XLOOKUP(A652,'2022'!A:A,'2022'!AA:AA) -> Y | F652: =_xlfn.XLOOKUP(A652,'2023'!B:B,'2023'!AG:AG) -> Y | G652: =_xlfn.XLOOKUP(A652,'2024'!B:B,'2024'!BL:BL) -> 1 | H652: =_xlfn.XLOOKUP(A652,'2025'!A:A,'2025'!G:G) -> 1 | I652: =_xlfn.XLOOKUP(A652,'2021'!A:A,'2021'!U:U) -> 1 | J652: =_xlfn.XLOOKUP(A652,'2022'!A:A,'2022'!V:V) -> 1 | K652: =_xlfn.XLOOKUP(A652,'2023'!B:B,'2023'!AD:AD) | L652: =_xlfn.XLOOKUP(A652,'2024'!B:B,'2024'!AV:AV) | M652: =_xlfn.XLOOKUP(A652,'2025'!A:A,'2025'!G:G) -> 1 | N652: =_xlfn.XLOOKUP(A652,'2021'!A:A,'2021'!E:E) -> Y | O652: =_xlfn.XLOOKUP(A652,'2022'!A:A,'2022'!E:E) -> Y | P652: =_xlfn.XLOOKUP(A652,'2023'!B:B,'2023'!G:G) -> Y | Q652: =_xlfn.XLOOKUP(A652,'2024'!B:B,'2024'!BH:BH) -> 1 | R652: =_xlfn.XLOOKUP(A652,'2025'!A:A,'2025'!B:B) -> 1 | S652: =_xlfn.XLOOKUP(A652,'2021'!A:A,'2021'!X:X) | T652: =_xlfn.XLOOKUP(A652,'2022'!A:A,'2022'!X:X) | U652: =_xlfn.XLOOKUP(A652,'2023'!B:B,'2023'!AF:AF) | V652: =_xlfn.XLOOKUP(A652,'2024'!B:B,'2024'!BW:BW) | W652: =_xlfn.XLOOKUP(A652,'2025'!A:A,'2025'!C:C) -> 0 | X652: =_xlfn.XLOOKUP(A652,'2021'!A:A,'2021'!V:V) -> 1 | Y652: =_xlfn.XLOOKUP(A652,'2022'!A:A,'2022'!W:W) -> 1 | Z652: =_xlfn.XLOOKUP(A652,'2023'!B:B,'2023'!AE:AE) -> 1 | AA652: =_xlfn.XLOOKUP(A652,'2024'!B:B,'2024'!AZ:AZ) -> 1 | AB652: =_xlfn.XLOOKUP(A652,'2025'!A:A,'2025'!F:F) -> 1
E653: =_xlfn.XLOOKUP(A653,'2022'!A:A,'2022'!AA:AA) -> #N/A | F653: =_xlfn.XLOOKUP(A653,'2023'!B:B,'2023'!AG:AG) -> #N/A | G653: =_xlfn.XLOOKUP(A653,'2024'!B:B,'2024'!BL:BL) -> #N/A | H653: =_xlfn.XLOOKUP(A653,'2025'!A:A,'2025'!G:G) | I653: =_xlfn.XLOOKUP(A653,'2021'!A:A,'2021'!U:U) -> #N/A | J653: =_xlfn.XLOOKUP(A653,'2022'!A:A,'2022'!V:V) -> #N/A | K653: =_xlfn.XLOOKUP(A653,'2023'!B:B,'2023'!AD:AD) -> #N/A | L653: =_xlfn.XLOOKUP(A653,'2024'!B:B,'2024'!AV:AV) -> #N/A | M653: =_xlfn.XLOOKUP(A653,'2025'!A:A,'2025'!G:G) | N653: =_xlfn.XLOOKUP(A653,'2021'!A:A,'2021'!E:E) -> #N/A | O653: =_xlfn.XLOOKUP(A653,'2022'!A:A,'2022'!E:E) -> #N/A | P653: =_xlfn.XLOOKUP(A653,'2023'!B:B,'2023'!G:G) -> #N/A | Q653: =_xlfn.XLOOKUP(A653,'2024'!B:B,'2024'!BH:BH) -> #N/A | R653: =_xlfn.XLOOKUP(A653,'2025'!A:A,'2025'!B:B) | S653: =_xlfn.XLOOKUP(A653,'2021'!A:A,'2021'!X:X) -> #N/A | T653: =_xlfn.XLOOKUP(A653,'2022'!A:A,'2022'!X:X) -> #N/A | U653: =_xlfn.XLOOKUP(A653,'2023'!B:B,'2023'!AF:AF) -> #N/A | V653: =_xlfn.XLOOKUP(A653,'2024'!B:B,'2024'!BW:BW) -> #N/A | W653: =_xlfn.XLOOKUP(A653,'2025'!A:A,'2025'!C:C) | X653: =_xlfn.XLOOKUP(A653,'2021'!A:A,'2021'!V:V) -> #N/A | Y653: =_xlfn.XLOOKUP(A653,'2022'!A:A,'2022'!W:W) -> #N/A | Z653: =_xlfn.XLOOKUP(A653,'2023'!B:B,'2023'!AE:AE) -> #N/A | AA653: =_xlfn.XLOOKUP(A653,'2024'!B:B,'2024'!AZ:AZ) -> #N/A | AB653: =_xlfn.XLOOKUP(A653,'2025'!A:A,'2025'!F:F)
E654: =_xlfn.XLOOKUP(A654,'2022'!A:A,'2022'!AA:AA) -> #N/A | F654: =_xlfn.XLOOKUP(A654,'2023'!B:B,'2023'!AG:AG) -> #N/A | G654: =_xlfn.XLOOKUP(A654,'2024'!B:B,'2024'!BL:BL) -> #N/A | H654: =_xlfn.XLOOKUP(A654,'2025'!A:A,'2025'!G:G) | I654: =_xlfn.XLOOKUP(A654,'2021'!A:A,'2021'!U:U) -> #N/A | J654: =_xlfn.XLOOKUP(A654,'2022'!A:A,'2022'!V:V) -> #N/A | K654: =_xlfn.XLOOKUP(A654,'2023'!B:B,'2023'!AD:AD) -> #N/A | L654: =_xlfn.XLOOKUP(A654,'2024'!B:B,'2024'!AV:AV) -> #N/A | M654: =_xlfn.XLOOKUP(A654,'2025'!A:A,'2025'!G:G) | N654: =_xlfn.XLOOKUP(A654,'2021'!A:A,'2021'!E:E) -> #N/A | O654: =_xlfn.XLOOKUP(A654,'2022'!A:A,'2022'!E:E) -> #N/A | P654: =_xlfn.XLOOKUP(A654,'2023'!B:B,'2023'!G:G) -> #N/A | Q654: =_xlfn.XLOOKUP(A654,'2024'!B:B,'2024'!BH:BH) -> #N/A | R654: =_xlfn.XLOOKUP(A654,'2025'!A:A,'2025'!B:B) | S654: =_xlfn.XLOOKUP(A654,'2021'!A:A,'2021'!X:X) -> #N/A | T654: =_xlfn.XLOOKUP(A654,'2022'!A:A,'2022'!X:X) -> #N/A | U654: =_xlfn.XLOOKUP(A654,'2023'!B:B,'2023'!AF:AF) -> #N/A | V654: =_xlfn.XLOOKUP(A654,'2024'!B:B,'2024'!BW:BW) -> #N/A | W654: =_xlfn.XLOOKUP(A654,'2025'!A:A,'2025'!C:C) | X654: =_xlfn.XLOOKUP(A654,'2021'!A:A,'2021'!V:V) -> #N/A | Y654: =_xlfn.XLOOKUP(A654,'2022'!A:A,'2022'!W:W) -> #N/A | Z654: =_xlfn.XLOOKUP(A654,'2023'!B:B,'2023'!AE:AE) -> #N/A | AA654: =_xlfn.XLOOKUP(A654,'2024'!B:B,'2024'!AZ:AZ) -> #N/A | AB654: =_xlfn.XLOOKUP(A654,'2025'!A:A,'2025'!F:F)
E655: =_xlfn.XLOOKUP(A655,'2022'!A:A,'2022'!AA:AA) -> #N/A | F655: =_xlfn.XLOOKUP(A655,'2023'!B:B,'2023'!AG:AG) -> #N/A | G655: =_xlfn.XLOOKUP(A655,'2024'!B:B,'2024'!BL:BL) -> #N/A | H655: =_xlfn.XLOOKUP(A655,'2025'!A:A,'2025'!G:G) | I655: =_xlfn.XLOOKUP(A655,'2021'!A:A,'2021'!U:U) -> #N/A | J655: =_xlfn.XLOOKUP(A655,'2022'!A:A,'2022'!V:V) -> #N/A | K655: =_xlfn.XLOOKUP(A655,'2023'!B:B,'2023'!AD:AD) -> #N/A | L655: =_xlfn.XLOOKUP(A655,'2024'!B:B,'2024'!AV:AV) -> #N/A | M655: =_xlfn.XLOOKUP(A655,'2025'!A:A,'2025'!G:G) | N655: =_xlfn.XLOOKUP(A655,'2021'!A:A,'2021'!E:E) -> #N/A | O655: =_xlfn.XLOOKUP(A655,'2022'!A:A,'2022'!E:E) -> #N/A | P655: =_xlfn.XLOOKUP(A655,'2023'!B:B,'2023'!G:G) -> #N/A | Q655: =_xlfn.XLOOKUP(A655,'2024'!B:B,'2024'!BH:BH) -> #N/A | R655: =_xlfn.XLOOKUP(A655,'2025'!A:A,'2025'!B:B) | S655: =_xlfn.XLOOKUP(A655,'2021'!A:A,'2021'!X:X) -> #N/A | T655: =_xlfn.XLOOKUP(A655,'2022'!A:A,'2022'!X:X) -> #N/A | U655: =_xlfn.XLOOKUP(A655,'2023'!B:B,'2023'!AF:AF) -> #N/A | V655: =_xlfn.XLOOKUP(A655,'2024'!B:B,'2024'!BW:BW) -> #N/A | W655: =_xlfn.XLOOKUP(A655,'2025'!A:A,'2025'!C:C) | X655: =_xlfn.XLOOKUP(A655,'2021'!A:A,'2021'!V:V) -> #N/A | Y655: =_xlfn.XLOOKUP(A655,'2022'!A:A,'2022'!W:W) -> #N/A | Z655: =_xlfn.XLOOKUP(A655,'2023'!B:B,'2023'!AE:AE) -> #N/A | AA655: =_xlfn.XLOOKUP(A655,'2024'!B:B,'2024'!AZ:AZ) -> #N/A | AB655: =_xlfn.XLOOKUP(A655,'2025'!A:A,'2025'!F:F)
E656: =_xlfn.XLOOKUP(A656,'2022'!A:A,'2022'!AA:AA) -> #N/A | F656: =_xlfn.XLOOKUP(A656,'2023'!B:B,'2023'!AG:AG) -> #N/A | G656: =_xlfn.XLOOKUP(A656,'2024'!B:B,'2024'!BL:BL) -> #N/A | H656: =_xlfn.XLOOKUP(A656,'2025'!A:A,'2025'!G:G) | I656: =_xlfn.XLOOKUP(A656,'2021'!A:A,'2021'!U:U) -> #N/A | J656: =_xlfn.XLOOKUP(A656,'2022'!A:A,'2022'!V:V) -> #N/A | K656: =_xlfn.XLOOKUP(A656,'2023'!B:B,'2023'!AD:AD) -> #N/A | L656: =_xlfn.XLOOKUP(A656,'2024'!B:B,'2024'!AV:AV) -> #N/A | M656: =_xlfn.XLOOKUP(A656,'2025'!A:A,'2025'!G:G) | N656: =_xlfn.XLOOKUP(A656,'2021'!A:A,'2021'!E:E) -> #N/A | O656: =_xlfn.XLOOKUP(A656,'2022'!A:A,'2022'!E:E) -> #N/A | P656: =_xlfn.XLOOKUP(A656,'2023'!B:B,'2023'!G:G) -> #N/A | Q656: =_xlfn.XLOOKUP(A656,'2024'!B:B,'2024'!BH:BH) -> #N/A | R656: =_xlfn.XLOOKUP(A656,'2025'!A:A,'2025'!B:B) | S656: =_xlfn.XLOOKUP(A656,'2021'!A:A,'2021'!X:X) -> #N/A | T656: =_xlfn.XLOOKUP(A656,'2022'!A:A,'2022'!X:X) -> #N/A | U656: =_xlfn.XLOOKUP(A656,'2023'!B:B,'2023'!AF:AF) -> #N/A | V656: =_xlfn.XLOOKUP(A656,'2024'!B:B,'2024'!BW:BW) -> #N/A | W656: =_xlfn.XLOOKUP(A656,'2025'!A:A,'2025'!C:C) | X656: =_xlfn.XLOOKUP(A656,'2021'!A:A,'2021'!V:V) -> #N/A | Y656: =_xlfn.XLOOKUP(A656,'2022'!A:A,'2022'!W:W) -> #N/A | Z656: =_xlfn.XLOOKUP(A656,'2023'!B:B,'2023'!AE:AE) -> #N/A | AA656: =_xlfn.XLOOKUP(A656,'2024'!B:B,'2024'!AZ:AZ) -> #N/A | AB656: =_xlfn.XLOOKUP(A656,'2025'!A:A,'2025'!F:F)
E657: =_xlfn.XLOOKUP(A657,'2022'!A:A,'2022'!AA:AA) -> #N/A | F657: =_xlfn.XLOOKUP(A657,'2023'!B:B,'2023'!AG:AG) -> #N/A | G657: =_xlfn.XLOOKUP(A657,'2024'!B:B,'2024'!BL:BL) -> #N/A | H657: =_xlfn.XLOOKUP(A657,'2025'!A:A,'2025'!G:G) | I657: =_xlfn.XLOOKUP(A657,'2021'!A:A,'2021'!U:U) -> #N/A | J657: =_xlfn.XLOOKUP(A657,'2022'!A:A,'2022'!V:V) -> #N/A | K657: =_xlfn.XLOOKUP(A657,'2023'!B:B,'2023'!AD:AD) -> #N/A | L657: =_xlfn.XLOOKUP(A657,'2024'!B:B,'2024'!AV:AV) -> #N/A | M657: =_xlfn.XLOOKUP(A657,'2025'!A:A,'2025'!G:G) | N657: =_xlfn.XLOOKUP(A657,'2021'!A:A,'2021'!E:E) -> #N/A | O657: =_xlfn.XLOOKUP(A657,'2022'!A:A,'2022'!E:E) -> #N/A | P657: =_xlfn.XLOOKUP(A657,'2023'!B:B,'2023'!G:G) -> #N/A | Q657: =_xlfn.XLOOKUP(A657,'2024'!B:B,'2024'!BH:BH) -> #N/A | R657: =_xlfn.XLOOKUP(A657,'2025'!A:A,'2025'!B:B) | S657: =_xlfn.XLOOKUP(A657,'2021'!A:A,'2021'!X:X) -> #N/A | T657: =_xlfn.XLOOKUP(A657,'2022'!A:A,'2022'!X:X) -> #N/A | U657: =_xlfn.XLOOKUP(A657,'2023'!B:B,'2023'!AF:AF) -> #N/A | V657: =_xlfn.XLOOKUP(A657,'2024'!B:B,'2024'!BW:BW) -> #N/A | W657: =_xlfn.XLOOKUP(A657,'2025'!A:A,'2025'!C:C) | X657: =_xlfn.XLOOKUP(A657,'2021'!A:A,'2021'!V:V) -> #N/A | Y657: =_xlfn.XLOOKUP(A657,'2022'!A:A,'2022'!W:W) -> #N/A | Z657: =_xlfn.XLOOKUP(A657,'2023'!B:B,'2023'!AE:AE) -> #N/A | AA657: =_xlfn.XLOOKUP(A657,'2024'!B:B,'2024'!AZ:AZ) -> #N/A | AB657: =_xlfn.XLOOKUP(A657,'2025'!A:A,'2025'!F:F)
E658: =_xlfn.XLOOKUP(A658,'2022'!A:A,'2022'!AA:AA) -> #N/A | F658: =_xlfn.XLOOKUP(A658,'2023'!B:B,'2023'!AG:AG) -> #N/A | G658: =_xlfn.XLOOKUP(A658,'2024'!B:B,'2024'!BL:BL) -> #N/A | H658: =_xlfn.XLOOKUP(A658,'2025'!A:A,'2025'!G:G) | I658: =_xlfn.XLOOKUP(A658,'2021'!A:A,'2021'!U:U) -> #N/A | J658: =_xlfn.XLOOKUP(A658,'2022'!A:A,'2022'!V:V) -> #N/A | K658: =_xlfn.XLOOKUP(A658,'2023'!B:B,'2023'!AD:AD) -> #N/A | L658: =_xlfn.XLOOKUP(A658,'2024'!B:B,'2024'!AV:AV) -> #N/A | M658: =_xlfn.XLOOKUP(A658,'2025'!A:A,'2025'!G:G) | N658: =_xlfn.XLOOKUP(A658,'2021'!A:A,'2021'!E:E) -> #N/A | O658: =_xlfn.XLOOKUP(A658,'2022'!A:A,'2022'!E:E) -> #N/A | P658: =_xlfn.XLOOKUP(A658,'2023'!B:B,'2023'!G:G) -> #N/A | Q658: =_xlfn.XLOOKUP(A658,'2024'!B:B,'2024'!BH:BH) -> #N/A | R658: =_xlfn.XLOOKUP(A658,'2025'!A:A,'2025'!B:B) | S658: =_xlfn.XLOOKUP(A658,'2021'!A:A,'2021'!X:X) -> #N/A | T658: =_xlfn.XLOOKUP(A658,'2022'!A:A,'2022'!X:X) -> #N/A | U658: =_xlfn.XLOOKUP(A658,'2023'!B:B,'2023'!AF:AF) -> #N/A | V658: =_xlfn.XLOOKUP(A658,'2024'!B:B,'2024'!BW:BW) -> #N/A | W658: =_xlfn.XLOOKUP(A658,'2025'!A:A,'2025'!C:C) | X658: =_xlfn.XLOOKUP(A658,'2021'!A:A,'2021'!V:V) -> #N/A | Y658: =_xlfn.XLOOKUP(A658,'2022'!A:A,'2022'!W:W) -> #N/A | Z658: =_xlfn.XLOOKUP(A658,'2023'!B:B,'2023'!AE:AE) -> #N/A | AA658: =_xlfn.XLOOKUP(A658,'2024'!B:B,'2024'!AZ:AZ) -> #N/A | AB658: =_xlfn.XLOOKUP(A658,'2025'!A:A,'2025'!F:F)
E659: =_xlfn.XLOOKUP(A659,'2022'!A:A,'2022'!AA:AA) -> #N/A | F659: =_xlfn.XLOOKUP(A659,'2023'!B:B,'2023'!AG:AG) -> #N/A | G659: =_xlfn.XLOOKUP(A659,'2024'!B:B,'2024'!BL:BL) -> #N/A | H659: =_xlfn.XLOOKUP(A659,'2025'!A:A,'2025'!G:G) | I659: =_xlfn.XLOOKUP(A659,'2021'!A:A,'2021'!U:U) -> #N/A | J659: =_xlfn.XLOOKUP(A659,'2022'!A:A,'2022'!V:V) -> #N/A | K659: =_xlfn.XLOOKUP(A659,'2023'!B:B,'2023'!AD:AD) -> #N/A | L659: =_xlfn.XLOOKUP(A659,'2024'!B:B,'2024'!AV:AV) -> #N/A | M659: =_xlfn.XLOOKUP(A659,'2025'!A:A,'2025'!G:G) | N659: =_xlfn.XLOOKUP(A659,'2021'!A:A,'2021'!E:E) -> #N/A | O659: =_xlfn.XLOOKUP(A659,'2022'!A:A,'2022'!E:E) -> #N/A | P659: =_xlfn.XLOOKUP(A659,'2023'!B:B,'2023'!G:G) -> #N/A | Q659: =_xlfn.XLOOKUP(A659,'2024'!B:B,'2024'!BH:BH) -> #N/A | R659: =_xlfn.XLOOKUP(A659,'2025'!A:A,'2025'!B:B) | S659: =_xlfn.XLOOKUP(A659,'2021'!A:A,'2021'!X:X) -> #N/A | T659: =_xlfn.XLOOKUP(A659,'2022'!A:A,'2022'!X:X) -> #N/A | U659: =_xlfn.XLOOKUP(A659,'2023'!B:B,'2023'!AF:AF) -> #N/A | V659: =_xlfn.XLOOKUP(A659,'2024'!B:B,'2024'!BW:BW) -> #N/A | W659: =_xlfn.XLOOKUP(A659,'2025'!A:A,'2025'!C:C) | X659: =_xlfn.XLOOKUP(A659,'2021'!A:A,'2021'!V:V) -> #N/A | Y659: =_xlfn.XLOOKUP(A659,'2022'!A:A,'2022'!W:W) -> #N/A | Z659: =_xlfn.XLOOKUP(A659,'2023'!B:B,'2023'!AE:AE) -> #N/A | AA659: =_xlfn.XLOOKUP(A659,'2024'!B:B,'2024'!AZ:AZ) -> #N/A | AB659: =_xlfn.XLOOKUP(A659,'2025'!A:A,'2025'!F:F)
E660: =_xlfn.XLOOKUP(A660,'2022'!A:A,'2022'!AA:AA) -> #N/A | F660: =_xlfn.XLOOKUP(A660,'2023'!B:B,'2023'!AG:AG) -> #N/A | G660: =_xlfn.XLOOKUP(A660,'2024'!B:B,'2024'!BL:BL) -> #N/A | H660: =_xlfn.XLOOKUP(A660,'2025'!A:A,'2025'!G:G) | I660: =_xlfn.XLOOKUP(A660,'2021'!A:A,'2021'!U:U) -> #N/A | J660: =_xlfn.XLOOKUP(A660,'2022'!A:A,'2022'!V:V) -> #N/A | K660: =_xlfn.XLOOKUP(A660,'2023'!B:B,'2023'!AD:AD) -> #N/A | L660: =_xlfn.XLOOKUP(A660,'2024'!B:B,'2024'!AV:AV) -> #N/A | M660: =_xlfn.XLOOKUP(A660,'2025'!A:A,'2025'!G:G) | N660: =_xlfn.XLOOKUP(A660,'2021'!A:A,'2021'!E:E) -> #N/A | O660: =_xlfn.XLOOKUP(A660,'2022'!A:A,'2022'!E:E) -> #N/A | P660: =_xlfn.XLOOKUP(A660,'2023'!B:B,'2023'!G:G) -> #N/A | Q660: =_xlfn.XLOOKUP(A660,'2024'!B:B,'2024'!BH:BH) -> #N/A | R660: =_xlfn.XLOOKUP(A660,'2025'!A:A,'2025'!B:B) | S660: =_xlfn.XLOOKUP(A660,'2021'!A:A,'2021'!X:X) -> #N/A | T660: =_xlfn.XLOOKUP(A660,'2022'!A:A,'2022'!X:X) -> #N/A | U660: =_xlfn.XLOOKUP(A660,'2023'!B:B,'2023'!AF:AF) -> #N/A | V660: =_xlfn.XLOOKUP(A660,'2024'!B:B,'2024'!BW:BW) -> #N/A | W660: =_xlfn.XLOOKUP(A660,'2025'!A:A,'2025'!C:C) | X660: =_xlfn.XLOOKUP(A660,'2021'!A:A,'2021'!V:V) -> #N/A | Y660: =_xlfn.XLOOKUP(A660,'2022'!A:A,'2022'!W:W) -> #N/A | Z660: =_xlfn.XLOOKUP(A660,'2023'!B:B,'2023'!AE:AE) -> #N/A | AA660: =_xlfn.XLOOKUP(A660,'2024'!B:B,'2024'!AZ:AZ) -> #N/A | AB660: =_xlfn.XLOOKUP(A660,'2025'!A:A,'2025'!F:F)
E661: =_xlfn.XLOOKUP(A661,'2022'!A:A,'2022'!AA:AA) -> #N/A | F661: =_xlfn.XLOOKUP(A661,'2023'!B:B,'2023'!AG:AG) -> #N/A | G661: =_xlfn.XLOOKUP(A661,'2024'!B:B,'2024'!BL:BL) -> #N/A | H661: =_xlfn.XLOOKUP(A661,'2025'!A:A,'2025'!G:G) | I661: =_xlfn.XLOOKUP(A661,'2021'!A:A,'2021'!U:U) -> #N/A | J661: =_xlfn.XLOOKUP(A661,'2022'!A:A,'2022'!V:V) -> #N/A | K661: =_xlfn.XLOOKUP(A661,'2023'!B:B,'2023'!AD:AD) -> #N/A | L661: =_xlfn.XLOOKUP(A661,'2024'!B:B,'2024'!AV:AV) -> #N/A | M661: =_xlfn.XLOOKUP(A661,'2025'!A:A,'2025'!G:G) | N661: =_xlfn.XLOOKUP(A661,'2021'!A:A,'2021'!E:E) -> #N/A | O661: =_xlfn.XLOOKUP(A661,'2022'!A:A,'2022'!E:E) -> #N/A | P661: =_xlfn.XLOOKUP(A661,'2023'!B:B,'2023'!G:G) -> #N/A | Q661: =_xlfn.XLOOKUP(A661,'2024'!B:B,'2024'!BH:BH) -> #N/A | R661: =_xlfn.XLOOKUP(A661,'2025'!A:A,'2025'!B:B) | S661: =_xlfn.XLOOKUP(A661,'2021'!A:A,'2021'!X:X) -> #N/A | T661: =_xlfn.XLOOKUP(A661,'2022'!A:A,'2022'!X:X) -> #N/A | U661: =_xlfn.XLOOKUP(A661,'2023'!B:B,'2023'!AF:AF) -> #N/A | V661: =_xlfn.XLOOKUP(A661,'2024'!B:B,'2024'!BW:BW) -> #N/A | W661: =_xlfn.XLOOKUP(A661,'2025'!A:A,'2025'!C:C) | X661: =_xlfn.XLOOKUP(A661,'2021'!A:A,'2021'!V:V) -> #N/A | Y661: =_xlfn.XLOOKUP(A661,'2022'!A:A,'2022'!W:W) -> #N/A | Z661: =_xlfn.XLOOKUP(A661,'2023'!B:B,'2023'!AE:AE) -> #N/A | AA661: =_xlfn.XLOOKUP(A661,'2024'!B:B,'2024'!AZ:AZ) -> #N/A | AB661: =_xlfn.XLOOKUP(A661,'2025'!A:A,'2025'!F:F)
E662: =_xlfn.XLOOKUP(A662,'2022'!A:A,'2022'!AA:AA) -> #N/A | F662: =_xlfn.XLOOKUP(A662,'2023'!B:B,'2023'!AG:AG) -> #N/A | G662: =_xlfn.XLOOKUP(A662,'2024'!B:B,'2024'!BL:BL) -> #N/A | H662: =_xlfn.XLOOKUP(A662,'2025'!A:A,'2025'!G:G) | I662: =_xlfn.XLOOKUP(A662,'2021'!A:A,'2021'!U:U) -> #N/A | J662: =_xlfn.XLOOKUP(A662,'2022'!A:A,'2022'!V:V) -> #N/A | K662: =_xlfn.XLOOKUP(A662,'2023'!B:B,'2023'!AD:AD) -> #N/A | L662: =_xlfn.XLOOKUP(A662,'2024'!B:B,'2024'!AV:AV) -> #N/A | M662: =_xlfn.XLOOKUP(A662,'2025'!A:A,'2025'!G:G) | N662: =_xlfn.XLOOKUP(A662,'2021'!A:A,'2021'!E:E) -> #N/A | O662: =_xlfn.XLOOKUP(A662,'2022'!A:A,'2022'!E:E) -> #N/A | P662: =_xlfn.XLOOKUP(A662,'2023'!B:B,'2023'!G:G) -> #N/A | Q662: =_xlfn.XLOOKUP(A662,'2024'!B:B,'2024'!BH:BH) -> #N/A | R662: =_xlfn.XLOOKUP(A662,'2025'!A:A,'2025'!B:B) | S662: =_xlfn.XLOOKUP(A662,'2021'!A:A,'2021'!X:X) -> #N/A | T662: =_xlfn.XLOOKUP(A662,'2022'!A:A,'2022'!X:X) -> #N/A | U662: =_xlfn.XLOOKUP(A662,'2023'!B:B,'2023'!AF:AF) -> #N/A | V662: =_xlfn.XLOOKUP(A662,'2024'!B:B,'2024'!BW:BW) -> #N/A | W662: =_xlfn.XLOOKUP(A662,'2025'!A:A,'2025'!C:C) | X662: =_xlfn.XLOOKUP(A662,'2021'!A:A,'2021'!V:V) -> #N/A | Y662: =_xlfn.XLOOKUP(A662,'2022'!A:A,'2022'!W:W) -> #N/A | Z662: =_xlfn.XLOOKUP(A662,'2023'!B:B,'2023'!AE:AE) -> #N/A | AA662: =_xlfn.XLOOKUP(A662,'2024'!B:B,'2024'!AZ:AZ) -> #N/A | AB662: =_xlfn.XLOOKUP(A662,'2025'!A:A,'2025'!F:F)
E663: =_xlfn.XLOOKUP(A663,'2022'!A:A,'2022'!AA:AA) -> #N/A | F663: =_xlfn.XLOOKUP(A663,'2023'!B:B,'2023'!AG:AG) -> #N/A | G663: =_xlfn.XLOOKUP(A663,'2024'!B:B,'2024'!BL:BL) -> #N/A | H663: =_xlfn.XLOOKUP(A663,'2025'!A:A,'2025'!G:G) | I663: =_xlfn.XLOOKUP(A663,'2021'!A:A,'2021'!U:U) -> #N/A | J663: =_xlfn.XLOOKUP(A663,'2022'!A:A,'2022'!V:V) -> #N/A | K663: =_xlfn.XLOOKUP(A663,'2023'!B:B,'2023'!AD:AD) -> #N/A | L663: =_xlfn.XLOOKUP(A663,'2024'!B:B,'2024'!AV:AV) -> #N/A | M663: =_xlfn.XLOOKUP(A663,'2025'!A:A,'2025'!G:G) | N663: =_xlfn.XLOOKUP(A663,'2021'!A:A,'2021'!E:E) -> #N/A | O663: =_xlfn.XLOOKUP(A663,'2022'!A:A,'2022'!E:E) -> #N/A | P663: =_xlfn.XLOOKUP(A663,'2023'!B:B,'2023'!G:G) -> #N/A | Q663: =_xlfn.XLOOKUP(A663,'2024'!B:B,'2024'!BH:BH) -> #N/A | R663: =_xlfn.XLOOKUP(A663,'2025'!A:A,'2025'!B:B) | S663: =_xlfn.XLOOKUP(A663,'2021'!A:A,'2021'!X:X) -> #N/A | T663: =_xlfn.XLOOKUP(A663,'2022'!A:A,'2022'!X:X) -> #N/A | U663: =_xlfn.XLOOKUP(A663,'2023'!B:B,'2023'!AF:AF) -> #N/A | V663: =_xlfn.XLOOKUP(A663,'2024'!B:B,'2024'!BW:BW) -> #N/A | W663: =_xlfn.XLOOKUP(A663,'2025'!A:A,'2025'!C:C) | X663: =_xlfn.XLOOKUP(A663,'2021'!A:A,'2021'!V:V) -> #N/A | Y663: =_xlfn.XLOOKUP(A663,'2022'!A:A,'2022'!W:W) -> #N/A | Z663: =_xlfn.XLOOKUP(A663,'2023'!B:B,'2023'!AE:AE) -> #N/A | AA663: =_xlfn.XLOOKUP(A663,'2024'!B:B,'2024'!AZ:AZ) -> #N/A | AB663: =_xlfn.XLOOKUP(A663,'2025'!A:A,'2025'!F:F)
E664: =_xlfn.XLOOKUP(A664,'2022'!A:A,'2022'!AA:AA) -> #N/A | F664: =_xlfn.XLOOKUP(A664,'2023'!B:B,'2023'!AG:AG) -> #N/A | G664: =_xlfn.XLOOKUP(A664,'2024'!B:B,'2024'!BL:BL) -> #N/A | H664: =_xlfn.XLOOKUP(A664,'2025'!A:A,'2025'!G:G) | I664: =_xlfn.XLOOKUP(A664,'2021'!A:A,'2021'!U:U) -> #N/A | J664: =_xlfn.XLOOKUP(A664,'2022'!A:A,'2022'!V:V) -> #N/A | K664: =_xlfn.XLOOKUP(A664,'2023'!B:B,'2023'!AD:AD) -> #N/A | L664: =_xlfn.XLOOKUP(A664,'2024'!B:B,'2024'!AV:AV) -> #N/A | M664: =_xlfn.XLOOKUP(A664,'2025'!A:A,'2025'!G:G) | N664: =_xlfn.XLOOKUP(A664,'2021'!A:A,'2021'!E:E) -> #N/A | O664: =_xlfn.XLOOKUP(A664,'2022'!A:A,'2022'!E:E) -> #N/A | P664: =_xlfn.XLOOKUP(A664,'2023'!B:B,'2023'!G:G) -> #N/A | Q664: =_xlfn.XLOOKUP(A664,'2024'!B:B,'2024'!BH:BH) -> #N/A | R664: =_xlfn.XLOOKUP(A664,'2025'!A:A,'2025'!B:B) | S664: =_xlfn.XLOOKUP(A664,'2021'!A:A,'2021'!X:X) -> #N/A | T664: =_xlfn.XLOOKUP(A664,'2022'!A:A,'2022'!X:X) -> #N/A | U664: =_xlfn.XLOOKUP(A664,'2023'!B:B,'2023'!AF:AF) -> #N/A | V664: =_xlfn.XLOOKUP(A664,'2024'!B:B,'2024'!BW:BW) -> #N/A | W664: =_xlfn.XLOOKUP(A664,'2025'!A:A,'2025'!C:C) | X664: =_xlfn.XLOOKUP(A664,'2021'!A:A,'2021'!V:V) -> #N/A | Y664: =_xlfn.XLOOKUP(A664,'2022'!A:A,'2022'!W:W) -> #N/A | Z664: =_xlfn.XLOOKUP(A664,'2023'!B:B,'2023'!AE:AE) -> #N/A | AA664: =_xlfn.XLOOKUP(A664,'2024'!B:B,'2024'!AZ:AZ) -> #N/A | AB664: =_xlfn.XLOOKUP(A664,'2025'!A:A,'2025'!F:F)
... E685: =_xlfn.XLOOKUP(A685,'2022'!A:A,'2022'!AA:AA) -> #N/A | F685: =_xlfn.XLOOKUP(A685,'2023'!B:B,'2023'!AG:AG) -> #N/A | G685: =_xlfn.XLOOKUP(A685,'2024'!B:B,'2024'!BL:BL) -> #N/A | H685: =_xlfn.XLOOKUP(A685,'2025'!A:A,'2025'!G:G) | I685: =_xlfn.XLOOKUP(A685,'2021'!A:A,'2021'!U:U) -> #N/A | J685: =_xlfn.XLOOKUP(A685,'2022'!A:A,'2022'!V:V) -> #N/A | K685: =_xlfn.XLOOKUP(A685,'2023'!B:B,'2023'!AD:AD) -> #N/A | L685: =_xlfn.XLOOKUP(A685,'2024'!B:B,'2024'!AV:AV) -> #N/A | M685: =_xlfn.XLOOKUP(A685,'2025'!A:A,'2025'!G:G) | N685: =_xlfn.XLOOKUP(A685,'2021'!A:A,'2021'!E:E) -> #N/A | O685: =_xlfn.XLOOKUP(A685,'2022'!A:A,'2022'!E:E) -> #N/A | P685: =_xlfn.XLOOKUP(A685,'2023'!B:B,'2023'!G:G) -> #N/A | Q685: =_xlfn.XLOOKUP(A685,'2024'!B:B,'2024'!BH:BH) -> #N/A | R685: =_xlfn.XLOOKUP(A685,'2025'!A:A,'2025'!B:B) | S685: =_xlfn.XLOOKUP(A685,'2021'!A:A,'2021'!X:X) -> #N/A | T685: =_xlfn.XLOOKUP(A685,'2022'!A:A,'2022'!X:X) -> #N/A | U685: =_xlfn.XLOOKUP(A685,'2023'!B:B,'2023'!AF:AF) -> #N/A | V685: =_xlfn.XLOOKUP(A685,'2024'!B:B,'2024'!BW:BW) -> #N/A | W685: =_xlfn.XLOOKUP(A685,'2025'!A:A,'2025'!C:C) | X685: =_xlfn.XLOOKUP(A685,'2021'!A:A,'2021'!V:V) -> #N/A | Y685: =_xlfn.XLOOKUP(A685,'2022'!A:A,'2022'!W:W) -> #N/A | Z685: =_xlfn.XLOOKUP(A685,'2023'!B:B,'2023'!AE:AE) -> #N/A | AA685: =_xlfn.XLOOKUP(A685,'2024'!B:B,'2024'!AZ:AZ) -> #N/A | AB685: =_xlfn.XLOOKUP(A685,'2025'!A:A,'2025'!F:F)

Sheet CN_NZ
A1: company | B1: 2021-CN | C1: 2021-NZ | D1: 2022-CN | E1: 2022-NZ | F1: 2023-CN | G1: 2023-NZ | H1: 2024-CN | I1: 2024-NZ | J1: 2025-CN | K1: 2025-NZ
A2: {=_xlfn.UNIQUE(_xlfn.VSTACK('2025'!A3:A502,'2024'!A3:A502,'2023'!B3:B502,'2022'!A3:A502,'2021'!A3:A502))} -> Walmart | B2: =_xlfn.XLOOKUP(A2,'2021'!A:A,'2021'!U:U, "") | C2: =_xlfn.XLOOKUP(A2,'2021'!A:A,'2021'!V:V,"") -> 1 | D2: =_xlfn.XLOOKUP(A2,'2022'!A:A,'2022'!V:V,"") | E2: =_xlfn.XLOOKUP(A2,'2022'!A:A,'2022'!W:W,"") -> 1 | F2: =_xlfn.XLOOKUP(A2,'2023'!B:B,'2023'!AD:AD,"") | G2: =_xlfn.XLOOKUP(A2,'2023'!B:B,'2023'!AE:AE,"") -> 1 | H2: =_xlfn.XLOOKUP(A2,'2024'!B:B,'2024'!AV:AV,"") | I2: =_xlfn.XLOOKUP(A2,'2024'!B:B,'2024'!AZ:AZ,"") -> 1 | J2: =_xlfn.XLOOKUP(A2,'2025'!A:A,'2025'!E:E,"") -> 0 | K2: =_xlfn.XLOOKUP(A2,'2025'!A:A,'2025'!F:F,"") -> 1
A3: Amazon | B3: =_xlfn.XLOOKUP(A3,'2021'!A:A,'2021'!U:U, "") | C3: =_xlfn.XLOOKUP(A3,'2021'!A:A,'2021'!V:V,"") -> 1 | D3: =_xlfn.XLOOKUP(A3,'2022'!A:A,'2022'!V:V,"") | E3: =_xlfn.XLOOKUP(A3,'2022'!A:A,'2022'!W:W,"") -> 1 | F3: =_xlfn.XLOOKUP(A3,'2023'!B:B,'2023'!AD:AD,"") | G3: =_xlfn.XLOOKUP(A3,'2023'!B:B,'2023'!AE:AE,"") -> 1 | H3: =_xlfn.XLOOKUP(A3,'2024'!B:B,'2024'!AV:AV,"") | I3: =_xlfn.XLOOKUP(A3,'2024'!B:B,'2024'!AZ:AZ,"") -> 1 | J3: =_xlfn.XLOOKUP(A3,'2025'!A:A,'2025'!E:E,"") -> 0 | K3: =_xlfn.XLOOKUP(A3,'2025'!A:A,'2025'!F:F,"") -> 1
A4: State Grid | B4: =_xlfn.XLOOKUP(A4,'2021'!A:A,'2021'!U:U, "") | C4: =_xlfn.XLOOKUP(A4,'2021'!A:A,'2021'!V:V,"") | D4: =_xlfn.XLOOKUP(A4,'2022'!A:A,'2022'!V:V,"") | E4: =_xlfn.XLOOKUP(A4,'2022'!A:A,'2022'!W:W,"") | F4: =_xlfn.XLOOKUP(A4,'2023'!B:B,'2023'!AD:AD,"") | G4: =_xlfn.XLOOKUP(A4,'2023'!B:B,'2023'!AE:AE,"") | H4: =_xlfn.XLOOKUP(A4,'2024'!B:B,'2024'!AV:AV,"") | I4: =_xlfn.XLOOKUP(A4,'2024'!B:B,'2024'!AZ:AZ,"") -> 0 | J4: =_xlfn.XLOOKUP(A4,'2025'!A:A,'2025'!E:E,"") -> 0 | K4: =_xlfn.XLOOKUP(A4,'2025'!A:A,'2025'!F:F,"") -> 0
A5: Saudi Aramco | B5: =_xlfn.XLOOKUP(A5,'2021'!A:A,'2021'!U:U, "") | C5: =_xlfn.XLOOKUP(A5,'2021'!A:A,'2021'!V:V,"") | D5: =_xlfn.XLOOKUP(A5,'2022'!A:A,'2022'!V:V,"") | E5: =_xlfn.XLOOKUP(A5,'2022'!A:A,'2022'!W:W,"") -> 1 | F5: =_xlfn.XLOOKUP(A5,'2023'!B:B,'2023'!AD:AD,"") | G5: =_xlfn.XLOOKUP(A5,'2023'!B:B,'2023'!AE:AE,"") -> 1 | H5: =_xlfn.XLOOKUP(A5,'2024'!B:B,'2024'!AV:AV,"") | I5: =_xlfn.XLOOKUP(A5,'2024'!B:B,'2024'!AZ:AZ,"") -> 1 | J5: =_xlfn.XLOOKUP(A5,'2025'!A:A,'2025'!E:E,"") -> 0 | K5: =_xlfn.XLOOKUP(A5,'2025'!A:A,'2025'!F:F,"") -> 1
A6: China National Petroleum | B6: =_xlfn.XLOOKUP(A6,'2021'!A:A,'2021'!U:U, "") | C6: =_xlfn.XLOOKUP(A6,'2021'!A:A,'2021'!V:V,"") -> 1 | D6: =_xlfn.XLOOKUP(A6,'2022'!A:A,'2022'!V:V,"") | E6: =_xlfn.XLOOKUP(A6,'2022'!A:A,'2022'!W:W,"") -> 1 | F6: =_xlfn.XLOOKUP(A6,'2023'!B:B,'2023'!AD:AD,"") | G6: =_xlfn.XLOOKUP(A6,'2023'!B:B,'2023'!AE:AE,"") | H6: =_xlfn.XLOOKUP(A6,'2024'!B:B,'2024'!AV:AV,"") | I6: =_xlfn.XLOOKUP(A6,'2024'!B:B,'2024'!AZ:AZ,"") -> 0 | J6: =_xlfn.XLOOKUP(A6,'2025'!A:A,'2025'!E:E,"") -> 0 | K6: =_xlfn.XLOOKUP(A6,'2025'!A:A,'2025'!F:F,"") -> 1
A7: Sinopec Group | B7: =_xlfn.XLOOKUP(A7,'2021'!A:A,'2021'!U:U, "") -> 1 | C7: =_xlfn.XLOOKUP(A7,'2021'!A:A,'2021'!V:V,"") | D7: =_xlfn.XLOOKUP(A7,'2022'!A:A,'2022'!V:V,"") | E7: =_xlfn.XLOOKUP(A7,'2022'!A:A,'2022'!W:W,"") | F7: =_xlfn.XLOOKUP(A7,'2023'!B:B,'2023'!AD:AD,"") | G7: =_xlfn.XLOOKUP(A7,'2023'!B:B,'2023'!AE:AE,"") | H7: =_xlfn.XLOOKUP(A7,'2024'!B:B,'2024'!AV:AV,"") | I7: =_xlfn.XLOOKUP(A7,'2024'!B:B,'2024'!AZ:AZ,"") -> 0 | J7: =_xlfn.XLOOKUP(A7,'2025'!A:A,'2025'!E:E,"") -> 1 | K7: =_xlfn.XLOOKUP(A7,'2025'!A:A,'2025'!F:F,"") -> 0
A8: UnitedHealth Group | B8: =_xlfn.XLOOKUP(A8,'2021'!A:A,'2021'!U:U, "") | C8: =_xlfn.XLOOKUP(A8,'2021'!A:A,'2021'!V:V,"") | D8: =_xlfn.XLOOKUP(A8,'2022'!A:A,'2022'!V:V,"") | E8: =_xlfn.XLOOKUP(A8,'2022'!A:A,'2022'!W:W,"") -> 1 | F8: =_xlfn.XLOOKUP(A8,'2023'!B:B,'2023'!AD:AD,"") | G8: =_xlfn.XLOOKUP(A8,'2023'!B:B,'2023'!AE:AE,"") -> 1 | H8: =_xlfn.XLOOKUP(A8,'2024'!B:B,'2024'!AV:AV,"") | I8: =_xlfn.XLOOKUP(A8,'2024'!B:B,'2024'!AZ:AZ,"") -> 1 | J8: =_xlfn.XLOOKUP(A8,'2025'!A:A,'2025'!E:E,"") -> 0 | K8: =_xlfn.XLOOKUP(A8,'2025'!A:A,'2025'!F:F,"") -> 1
A9: Apple | B9: =_xlfn.XLOOKUP(A9,'2021'!A:A,'2021'!U:U, "") -> 1 | C9: =_xlfn.XLOOKUP(A9,'2021'!A:A,'2021'!V:V,"") -> 1 | D9: =_xlfn.XLOOKUP(A9,'2022'!A:A,'2022'!V:V,"") -> 1 | E9: =_xlfn.XLOOKUP(A9,'2022'!A:A,'2022'!W:W,"") | F9: =_xlfn.XLOOKUP(A9,'2023'!B:B,'2023'!AD:AD,"") -> 1 | G9: =_xlfn.XLOOKUP(A9,'2023'!B:B,'2023'!AE:AE,"") | H9: =_xlfn.XLOOKUP(A9,'2024'!B:B,'2024'!AV:AV,"") -> 1 | I9: =_xlfn.XLOOKUP(A9,'2024'!B:B,'2024'!AZ:AZ,"") -> 0 | J9: =_xlfn.XLOOKUP(A9,'2025'!A:A,'2025'!E:E,"") -> 1 | K9: =_xlfn.XLOOKUP(A9,'2025'!A:A,'2025'!F:F,"") -> 0
A10: CVS Health | B10: =_xlfn.XLOOKUP(A10,'2021'!A:A,'2021'!U:U, "") | C10: =_xlfn.XLOOKUP(A10,'2021'!A:A,'2021'!V:V,"") | D10: =_xlfn.XLOOKUP(A10,'2022'!A:A,'2022'!V:V,"") -> 1 | E10: =_xlfn.XLOOKUP(A10,'2022'!A:A,'2022'!W:W,"") -> 1 | F10: =_xlfn.XLOOKUP(A10,'2023'!B:B,'2023'!AD:AD,"") | G10: =_xlfn.XLOOKUP(A10,'2023'!B:B,'2023'!AE:AE,"") -> 1 | H10: =_xlfn.XLOOKUP(A10,'2024'!B:B,'2024'!AV:AV,"") | I10: =_xlfn.XLOOKUP(A10,'2024'!B:B,'2024'!AZ:AZ,"") -> 1 | J10: =_xlfn.XLOOKUP(A10,'2025'!A:A,'2025'!E:E,"") -> 0 | K10: =_xlfn.XLOOKUP(A10,'2025'!A:A,'2025'!F:F,"") -> 1
A11: Berkshire Hathaway | B11: =_xlfn.XLOOKUP(A11,'2021'!A:A,'2021'!U:U, "") | C11: =_xlfn.XLOOKUP(A11,'2021'!A:A,'2021'!V:V,"") | D11: =_xlfn.XLOOKUP(A11,'2022'!A:A,'2022'!V:V,"") | E11: =_xlfn.XLOOKUP(A11,'2022'!A:A,'2022'!W:W,"") | F11: =_xlfn.XLOOKUP(A11,'2023'!B:B,'2023'!AD:AD,"") | G11: =_xlfn.XLOOKUP(A11,'2023'!B:B,'2023'!AE:AE,"") | H11: =_xlfn.XLOOKUP(A11,'2024'!B:B,'2024'!AV:AV,"") | I11: =_xlfn.XLOOKUP(A11,'2024'!B:B,'2024'!AZ:AZ,"") -> 0 | J11: =_xlfn.XLOOKUP(A11,'2025'!A:A,'2025'!E:E,"") -> 0 | K11: =_xlfn.XLOOKUP(A11,'2025'!A:A,'2025'!F:F,"") -> 0
A12: McKesson | B12: =_xlfn.XLOOKUP(A12,'2021'!A:A,'2021'!U:U, "") | C12: =_xlfn.XLOOKUP(A12,'2021'!A:A,'2021'!V:V,"") | D12: =_xlfn.XLOOKUP(A12,'2022'!A:A,'2022'!V:V,"") -> 1 | E12: =_xlfn.XLOOKUP(A12,'2022'!A:A,'2022'!W:W,"") | F12: =_xlfn.XLOOKUP(A12,'2023'!B:B,'2023'!AD:AD,"") | G12: =_xlfn.XLOOKUP(A12,'2023'!B:B,'2023'!AE:AE,"") | H12: =_xlfn.XLOOKUP(A12,'2024'!B:B,'2024'!AV:AV,"") | I12: =_xlfn.XLOOKUP(A12,'2024'!B:B,'2024'!AZ:AZ,"") -> 0 | J12: =_xlfn.XLOOKUP(A12,'2025'!A:A,'2025'!E:E,"") -> 0 | K12: =_xlfn.XLOOKUP(A12,'2025'!A:A,'2025'!F:F,"") -> 0
A13: Volkswagen | B13: =_xlfn.XLOOKUP(A13,'2021'!A:A,'2021'!U:U, "") -> 1 | C13: =_xlfn.XLOOKUP(A13,'2021'!A:A,'2021'!V:V,"") | D13: =_xlfn.XLOOKUP(A13,'2022'!A:A,'2022'!V:V,"") -> 1 | E13: =_xlfn.XLOOKUP(A13,'2022'!A:A,'2022'!W:W,"") | F13: =_xlfn.XLOOKUP(A13,'2023'!B:B,'2023'!AD:AD,"") -> 1 | G13: =_xlfn.XLOOKUP(A13,'2023'!B:B,'2023'!AE:AE,"") | H13: =_xlfn.XLOOKUP(A13,'2024'!B:B,'2024'!AV:AV,"") -> 1 | I13: =_xlfn.XLOOKUP(A13,'2024'!B:B,'2024'!AZ:AZ,"") -> 0 | J13: =_xlfn.XLOOKUP(A13,'2025'!A:A,'2025'!E:E,"") -> 1 | K13: =_xlfn.XLOOKUP(A13,'2025'!A:A,'2025'!F:F,"") -> 0
A14: Alphabet | B14: =_xlfn.XLOOKUP(A14,'2021'!A:A,'2021'!U:U, "") -> 1 | C14: =_xlfn.XLOOKUP(A14,'2021'!A:A,'2021'!V:V,"") | D14: =_xlfn.XLOOKUP(A14,'2022'!A:A,'2022'!V:V,"") -> 1 | E14: =_xlfn.XLOOKUP(A14,'2022'!A:A,'2022'!W:W,"") -> 1 | F14: =_xlfn.XLOOKUP(A14,'2023'!B:B,'2023'!AD:AD,"") | G14: =_xlfn.XLOOKUP(A14,'2023'!B:B,'2023'!AE:AE,"") -> 1 | H14: =_xlfn.XLOOKUP(A14,'2024'!B:B,'2024'!AV:AV,"") | I14: =_xlfn.XLOOKUP(A14,'2024'!B:B,'2024'!AZ:AZ,"") -> 1 | J14: =_xlfn.XLOOKUP(A14,'2025'!A:A,'2025'!E:E,"") -> 0 | K14: =_xlfn.XLOOKUP(A14,'2025'!A:A,'2025'!F:F,"") -> 1
... A501: Heineken | B501: =_xlfn.XLOOKUP(A501,'2021'!A:A,'2021'!U:U, "") | C501: =_xlfn.XLOOKUP(A501,'2021'!A:A,'2021'!V:V,"") | D501: =_xlfn.XLOOKUP(A501,'2022'!A:A,'2022'!V:V,"") | E501: =_xlfn.XLOOKUP(A501,'2022'!A:A,'2022'!W:W,"") | F501: =_xlfn.XLOOKUP(A501,'2023'!B:B,'2023'!AD:AD,"") | G501: =_xlfn.XLOOKUP(A501,'2023'!B:B,'2023'!AE:AE,"") | H501: =_xlfn.XLOOKUP(A501,'2024'!B:B,'2024'!AV:AV,"") | I501: =_xlfn.XLOOKUP(A501,'2024'!B:B,'2024'!AZ:AZ,"") -> 1 | J501: =_xlfn.XLOOKUP(A501,'2025'!A:A,'2025'!E:E,"") -> 0 | K501: =_xlfn.XLOOKUP(A501,'2025'!A:A,'2025'!F:F,"") -> 1
A502: 489 | B502: =_xlfn.XLOOKUP(A502,'2021'!A:A,'2021'!U:U, "") | C502: =_xlfn.XLOOKUP(A502,'2021'!A:A,'2021'!V:V,"") | D502: =_xlfn.XLOOKUP(A502,'2022'!A:A,'2022'!V:V,"") | E502: =_xlfn.XLOOKUP(A502,'2022'!A:A,'2022'!W:W,"") | F502: =_xlfn.XLOOKUP(A502,'2023'!B:B,'2023'!AD:AD,"") | G502: =_xlfn.XLOOKUP(A502,'2023'!B:B,'2023'!AE:AE,"") | H502: =_xlfn.XLOOKUP(A502,'2024'!B:B,'2024'!AV:AV,"") | I502: =_xlfn.XLOOKUP(A502,'2024'!B:B,'2024'!AZ:AZ,"") | J502: =_xlfn.XLOOKUP(A502,'2025'!A:A,'2025'!E:E,"") | K502: =_xlfn.XLOOKUP(A502,'2025'!A:A,'2025'!F:F,"")
A503: 498 | B503: =_xlfn.XLOOKUP(A503,'2021'!A:A,'2021'!U:U, "") | C503: =_xlfn.XLOOKUP(A503,'2021'!A:A,'2021'!V:V,"") | D503: =_xlfn.XLOOKUP(A503,'2022'!A:A,'2022'!V:V,"") | E503: =_xlfn.XLOOKUP(A503,'2022'!A:A,'2022'!W:W,"") | F503: =_xlfn.XLOOKUP(A503,'2023'!B:B,'2023'!AD:AD,"") | G503: =_xlfn.XLOOKUP(A503,'2023'!B:B,'2023'!AE:AE,"") | H503: =_xlfn.XLOOKUP(A503,'2024'!B:B,'2024'!AV:AV,"") | I503: =_xlfn.XLOOKUP(A503,'2024'!B:B,'2024'!AZ:AZ,"") | J503: =_xlfn.XLOOKUP(A503,'2025'!A:A,'2025'!E:E,"") | K503: =_xlfn.XLOOKUP(A503,'2025'!A:A,'2025'!F:F,"")
A504: 376 | B504: =_xlfn.XLOOKUP(A504,'2021'!A:A,'2021'!U:U, "") | C504: =_xlfn.XLOOKUP(A504,'2021'!A:A,'2021'!V:V,"") | D504: =_xlfn.XLOOKUP(A504,'2022'!A:A,'2022'!V:V,"") | E504: =_xlfn.XLOOKUP(A504,'2022'!A:A,'2022'!W:W,"") | F504: =_xlfn.XLOOKUP(A504,'2023'!B:B,'2023'!AD:AD,"") | G504: =_xlfn.XLOOKUP(A504,'2023'!B:B,'2023'!AE:AE,"") | H504: =_xlfn.XLOOKUP(A504,'2024'!B:B,'2024'!AV:AV,"") | I504: =_xlfn.XLOOKUP(A504,'2024'!B:B,'2024'!AZ:AZ,"") | J504: =_xlfn.XLOOKUP(A504,'2025'!A:A,'2025'!E:E,"") | K504: =_xlfn.XLOOKUP(A504,'2025'!A:A,'2025'!F:F,"")
A505: 259 | B505: =_xlfn.XLOOKUP(A505,'2021'!A:A,'2021'!U:U, "") | C505: =_xlfn.XLOOKUP(A505,'2021'!A:A,'2021'!V:V,"") | D505: =_xlfn.XLOOKUP(A505,'2022'!A:A,'2022'!V:V,"") | E505: =_xlfn.XLOOKUP(A505,'2022'!A:A,'2022'!W:W,"") | F505: =_xlfn.XLOOKUP(A505,'2023'!B:B,'2023'!AD:AD,"") | G505: =_xlfn.XLOOKUP(A505,'2023'!B:B,'2023'!AE:AE,"") | H505: =_xlfn.XLOOKUP(A505,'2024'!B:B,'2024'!AV:AV,"") | I505: =_xlfn.XLOOKUP(A505,'2024'!B:B,'2024'!AZ:AZ,"") | J505: =_xlfn.XLOOKUP(A505,'2025'!A:A,'2025'!E:E,"") | K505: =_xlfn.XLOOKUP(A505,'2025'!A:A,'2025'!F:F,"")
A506: 211 | B506: =_xlfn.XLOOKUP(A506,'2021'!A:A,'2021'!U:U, "") | C506: =_xlfn.XLOOKUP(A506,'2021'!A:A,'2021'!V:V,"") | D506: =_xlfn.XLOOKUP(A506,'2022'!A:A,'2022'!V:V,"") | E506: =_xlfn.XLOOKUP(A506,'2022'!A:A,'2022'!W:W,"") | F506: =_xlfn.XLOOKUP(A506,'2023'!B:B,'2023'!AD:AD,"") | G506: =_xlfn.XLOOKUP(A506,'2023'!B:B,'2023'!AE:AE,"") | H506: =_xlfn.XLOOKUP(A506,'2024'!B:B,'2024'!AV:AV,"") | I506: =_xlfn.XLOOKUP(A506,'2024'!B:B,'2024'!AZ:AZ,"") | J506: =_xlfn.XLOOKUP(A506,'2025'!A:A,'2025'!E:E,"") | K506: =_xlfn.XLOOKUP(A506,'2025'!A:A,'2025'!F:F,"")
A507: 391 | B507: =_xlfn.XLOOKUP(A507,'2021'!A:A,'2021'!U:U, "") | C507: =_xlfn.XLOOKUP(A507,'2021'!A:A,'2021'!V:V,"") | D507: =_xlfn.XLOOKUP(A507,'2022'!A:A,'2022'!V:V,"") | E507: =_xlfn.XLOOKUP(A507,'2022'!A:A,'2022'!W:W,"") | F507: =_xlfn.XLOOKUP(A507,'2023'!B:B,'2023'!AD:AD,"") | G507: =_xlfn.XLOOKUP(A507,'2023'!B:B,'2023'!AE:AE,"") | H507: =_xlfn.XLOOKUP(A507,'2024'!B:B,'2024'!AV:AV,"") | I507: =_xlfn.XLOOKUP(A507,'2024'!B:B,'2024'!AZ:AZ,"") | J507: =_xlfn.XLOOKUP(A507,'2025'!A:A,'2025'!E:E,"") | K507: =_xlfn.XLOOKUP(A507,'2025'!A:A,'2025'!F:F,"")
A508: 203 | B508: =_xlfn.XLOOKUP(A508,'2021'!A:A,'2021'!U:U, "") | C508: =_xlfn.XLOOKUP(A508,'2021'!A:A,'2021'!V:V,"") | D508: =_xlfn.XLOOKUP(A508,'2022'!A:A,'2022'!V:V,"") | E508: =_xlfn.XLOOKUP(A508,'2022'!A:A,'2022'!W:W,"") | F508: =_xlfn.XLOOKUP(A508,'2023'!B:B,'2023'!AD:AD,"") | G508: =_xlfn.XLOOKUP(A508,'2023'!B:B,'2023'!AE:AE,"") | H508: =_xlfn.XLOOKUP(A508,'2024'!B:B,'2024'!AV:AV,"") | I508: =_xlfn.XLOOKUP(A508,'2024'!B:B,'2024'!AZ:AZ,"") | J508: =_xlfn.XLOOKUP(A508,'2025'!A:A,'2025'!E:E,"") | K508: =_xlfn.XLOOKUP(A508,'2025'!A:A,'2025'!F:F,"")
A509: 34 | B509: =_xlfn.XLOOKUP(A509,'2021'!A:A,'2021'!U:U, "") | C509: =_xlfn.XLOOKUP(A509,'2021'!A:A,'2021'!V:V,"") | D509: =_xlfn.XLOOKUP(A509,'2022'!A:A,'2022'!V:V,"") | E509: =_xlfn.XLOOKUP(A509,'2022'!A:A,'2022'!W:W,"") | F509: =_xlfn.XLOOKUP(A509,'2023'!B:B,'2023'!AD:AD,"") | G509: =_xlfn.XLOOKUP(A509,'2023'!B:B,'2023'!AE:AE,"") | H509: =_xlfn.XLOOKUP(A509,'2024'!B:B,'2024'!AV:AV,"") | I509: =_xlfn.XLOOKUP(A509,'2024'!B:B,'2024'!AZ:AZ,"") | J509: =_xlfn.XLOOKUP(A509,'2025'!A:A,'2025'!E:E,"") | K509: =_xlfn.XLOOKUP(A509,'2025'!A:A,'2025'!F:F,"")
A510: 446 | B510: =_xlfn.XLOOKUP(A510,'2021'!A:A,'2021'!U:U, "") | C510: =_xlfn.XLOOKUP(A510,'2021'!A:A,'2021'!V:V,"") | D510: =_xlfn.XLOOKUP(A510,'2022'!A:A,'2022'!V:V,"") | E510: =_xlfn.XLOOKUP(A510,'2022'!A:A,'2022'!W:W,"") | F510: =_xlfn.XLOOKUP(A510,'2023'!B:B,'2023'!AD:AD,"") | G510: =_xlfn.XLOOKUP(A510,'2023'!B:B,'2023'!AE:AE,"") | H510: =_xlfn.XLOOKUP(A510,'2024'!B:B,'2024'!AV:AV,"") | I510: =_xlfn.XLOOKUP(A510,'2024'!B:B,'2024'!AZ:AZ,"") | J510: =_xlfn.XLOOKUP(A510,'2025'!A:A,'2025'!E:E,"") | K510: =_xlfn.XLOOKUP(A510,'2025'!A:A,'2025'!F:F,"")
A511: 324 | B511: =_xlfn.XLOOKUP(A511,'2021'!A:A,'2021'!U:U, "") | C511: =_xlfn.XLOOKUP(A511,'2021'!A:A,'2021'!V:V,"") | D511: =_xlfn.XLOOKUP(A511,'2022'!A:A,'2022'!V:V,"") | E511: =_xlfn.XLOOKUP(A511,'2022'!A:A,'2022'!W:W,"") | F511: =_xlfn.XLOOKUP(A511,'2023'!B:B,'2023'!AD:AD,"") | G511: =_xlfn.XLOOKUP(A511,'2023'!B:B,'2023'!AE:AE,"") | H511: =_xlfn.XLOOKUP(A511,'2024'!B:B,'2024'!AV:AV,"") | I511: =_xlfn.XLOOKUP(A511,'2024'!B:B,'2024'!AZ:AZ,"") | J511: =_xlfn.XLOOKUP(A511,'2025'!A:A,'2025'!E:E,"") | K511: =_xlfn.XLOOKUP(A511,'2025'!A:A,'2025'!F:F,"")
A512: 496 | B512: =_xlfn.XLOOKUP(A512,'2021'!A:A,'2021'!U:U, "") | C512: =_xlfn.XLOOKUP(A512,'2021'!A:A,'2021'!V:V,"") | D512: =_xlfn.XLOOKUP(A512,'2022'!A:A,'2022'!V:V,"") | E512: =_xlfn.XLOOKUP(A512,'2022'!A:A,'2022'!W:W,"") | F512: =_xlfn.XLOOKUP(A512,'2023'!B:B,'2023'!AD:AD,"") | G512: =_xlfn.XLOOKUP(A512,'2023'!B:B,'2023'!AE:AE,"") | H512: =_xlfn.XLOOKUP(A512,'2024'!B:B,'2024'!AV:AV,"") | I512: =_xlfn.XLOOKUP(A512,'2024'!B:B,'2024'!AZ:AZ,"") | J512: =_xlfn.XLOOKUP(A512,'2025'!A:A,'2025'!E:E,"") | K512: =_xlfn.XLOOKUP(A512,'2025'!A:A,'2025'!F:F,"")
A513: 183 | B513: =_xlfn.XLOOKUP(A513,'2021'!A:A,'2021'!U:U, "") | C513: =_xlfn.XLOOKUP(A513,'2021'!A:A,'2021'!V:V,"") | D513: =_xlfn.XLOOKUP(A513,'2022'!A:A,'2022'!V:V,"") | E513: =_xlfn.XLOOKUP(A513,'2022'!A:A,'2022'!W:W,"") | F513: =_xlfn.XLOOKUP(A513,'2023'!B:B,'2023'!AD:AD,"") | G513: =_xlfn.XLOOKUP(A513,'2023'!B:B,'2023'!AE:AE,"") | H513: =_xlfn.XLOOKUP(A513,'2024'!B:B,'2024'!AV:AV,"") | I513: =_xlfn.XLOOKUP(A513,'2024'!B:B,'2024'!AZ:AZ,"") | J513: =_xlfn.XLOOKUP(A513,'2025'!A:A,'2025'!E:E,"") | K513: =_xlfn.XLOOKUP(A513,'2025'!A:A,'2025'!F:F,"")
... A1001: 224 | B1001: =_xlfn.XLOOKUP(A1001,'2021'!A:A,'2021'!U:U, "") | C1001: =_xlfn.XLOOKUP(A1001,'2021'!A:A,'2021'!V:V,"") | D1001: =_xlfn.XLOOKUP(A1001,'2022'!A:A,'2022'!V:V,"") | E1001: =_xlfn.XLOOKUP(A1001,'2022'!A:A,'2022'!W:W,"") | F1001: =_xlfn.XLOOKUP(A1001,'2023'!B:B,'2023'!AD:AD,"") | G1001: =_xlfn.XLOOKUP(A1001,'2023'!B:B,'2023'!AE:AE,"") | H1001: =_xlfn.XLOOKUP(A1001,'2024'!B:B,'2024'!AV:AV,"") | I1001: =_xlfn.XLOOKUP(A1001,'2024'!B:B,'2024'!AZ:AZ,"") | J1001: =_xlfn.XLOOKUP(A1001,'2025'!A:A,'2025'!E:E,"") | K1001: =_xlfn.XLOOKUP(A1001,'2025'!A:A,'2025'!F:F,"")
A1002: AmerisourceBergen | B1002: =_xlfn.XLOOKUP(A1002,'2021'!A:A,'2021'!U:U, "") | C1002: =_xlfn.XLOOKUP(A1002,'2021'!A:A,'2021'!V:V,"") | D1002: =_xlfn.XLOOKUP(A1002,'2022'!A:A,'2022'!V:V,"") | E1002: =_xlfn.XLOOKUP(A1002,'2022'!A:A,'2022'!W:W,"") | F1002: =_xlfn.XLOOKUP(A1002,'2023'!B:B,'2023'!AD:AD,"") | G1002: =_xlfn.XLOOKUP(A1002,'2023'!B:B,'2023'!AE:AE,"") | H1002: =_xlfn.XLOOKUP(A1002,'2024'!B:B,'2024'!AV:AV,"") | I1002: =_xlfn.XLOOKUP(A1002,'2024'!B:B,'2024'!AZ:AZ,"") | J1002: =_xlfn.XLOOKUP(A1002,'2025'!A:A,'2025'!E:E,"") | K1002: =_xlfn.XLOOKUP(A1002,'2025'!A:A,'2025'!F:F,"")
A1003: Sinochem Holdings | B1003: =_xlfn.XLOOKUP(A1003,'2021'!A:A,'2021'!U:U, "") | C1003: =_xlfn.XLOOKUP(A1003,'2021'!A:A,'2021'!V:V,"") | D1003: =_xlfn.XLOOKUP(A1003,'2022'!A:A,'2022'!V:V,"") | E1003: =_xlfn.XLOOKUP(A1003,'2022'!A:A,'2022'!W:W,"") | F1003: =_xlfn.XLOOKUP(A1003,'2023'!B:B,'2023'!AD:AD,"") | G1003: =_xlfn.XLOOKUP(A1003,'2023'!B:B,'2023'!AE:AE,"") | H1003: =_xlfn.XLOOKUP(A1003,'2024'!B:B,'2024'!AV:AV,"") | I1003: =_xlfn.XLOOKUP(A1003,'2024'!B:B,'2024'!AZ:AZ,"") -> 0 | J1003: =_xlfn.XLOOKUP(A1003,'2025'!A:A,'2025'!E:E,"") | K1003: =_xlfn.XLOOKUP(A1003,'2025'!A:A,'2025'!F:F,"")
A1004: Electricité de France | B1004: =_xlfn.XLOOKUP(A1004,'2021'!A:A,'2021'!U:U, "") -> 1 | C1004: =_xlfn.XLOOKUP(A1004,'2021'!A:A,'2021'!V:V,"") | D1004: =_xlfn.XLOOKUP(A1004,'2022'!A:A,'2022'!V:V,"") -> 1 | E1004: =_xlfn.XLOOKUP(A1004,'2022'!A:A,'2022'!W:W,"") | F1004: =_xlfn.XLOOKUP(A1004,'2023'!B:B,'2023'!AD:AD,"") | G1004: =_xlfn.XLOOKUP(A1004,'2023'!B:B,'2023'!AE:AE,"") -> 1 | H1004: =_xlfn.XLOOKUP(A1004,'2024'!B:B,'2024'!AV:AV,"") | I1004: =_xlfn.XLOOKUP(A1004,'2024'!B:B,'2024'!AZ:AZ,"") | J1004: =_xlfn.XLOOKUP(A1004,'2025'!A:A,'2025'!E:E,"") | K1004: =_xlfn.XLOOKUP(A1004,'2025'!A:A,'2025'!F:F,"")
A1005: SK Group | B1005: =_xlfn.XLOOKUP(A1005,'2021'!A:A,'2021'!U:U, "") | C1005: =_xlfn.XLOOKUP(A1005,'2021'!A:A,'2021'!V:V,"") | D1005: =_xlfn.XLOOKUP(A1005,'2022'!A:A,'2022'!V:V,"") | E1005: =_xlfn.XLOOKUP(A1005,'2022'!A:A,'2022'!W:W,"") -> 1 | F1005: =_xlfn.XLOOKUP(A1005,'2023'!B:B,'2023'!AD:AD,"") | G1005: =_xlfn.XLOOKUP(A1005,'2023'!B:B,'2023'!AE:AE,"") -> 1 | H1005: =_xlfn.XLOOKUP(A1005,'2024'!B:B,'2024'!AV:AV,"") | I1005: =_xlfn.XLOOKUP(A1005,'2024'!B:B,'2024'!AZ:AZ,"") | J1005: =_xlfn.XLOOKUP(A1005,'2025'!A:A,'2025'!E:E,"") | K1005: =_xlfn.XLOOKUP(A1005,'2025'!A:A,'2025'!F:F,"")
A1006: Deutsche Post DHL Group | B1006: =_xlfn.XLOOKUP(A1006,'2021'!A:A,'2021'!U:U, "") | C1006: =_xlfn.XLOOKUP(A1006,'2021'!A:A,'2021'!V:V,"") -> 1 | D1006: =_xlfn.XLOOKUP(A1006,'2022'!A:A,'2022'!V:V,"") | E1006: =_xlfn.XLOOKUP(A1006,'2022'!A:A,'2022'!W:W,"") -> 1 | F1006: =_xlfn.XLOOKUP(A1006,'2023'!B:B,'2023'!AD:AD,"") | G1006: =_xlfn.XLOOKUP(A1006,'2023'!B:B,'2023'!AE:AE,"") -> 1 | H1006: =_xlfn.XLOOKUP(A1006,'2024'!B:B,'2024'!AV:AV,"") | I1006: =_xlfn.XLOOKUP(A1006,'2024'!B:B,'2024'!AZ:AZ,"") | J1006: =_xlfn.XLOOKUP(A1006,'2025'!A:A,'2025'!E:E,"") | K1006: =_xlfn.XLOOKUP(A1006,'2025'!A:A,'2025'!F:F,"")
A1007: Nippon Telegraph and Telephone | B1007: =_xlfn.XLOOKUP(A1007,'2021'!A:A,'2021'!U:U, "") | C1007: =_xlfn.XLOOKUP(A1007,'2021'!A:A,'2021'!V:V,"") | D1007: =_xlfn.XLOOKUP(A1007,'2022'!A:A,'2022'!V:V,"") -> 1 | E1007: =_xlfn.XLOOKUP(A1007,'2022'!A:A,'2022'!W:W,"") | F1007: =_xlfn.XLOOKUP(A1007,'2023'!B:B,'2023'!AD:AD,"") -> 1 | G1007: =_xlfn.XLOOKUP(A1007,'2023'!B:B,'2023'!AE:AE,"") | H1007: =_xlfn.XLOOKUP(A1007,'2024'!B:B,'2024'!AV:AV,"") -> 1 | I1007: =_xlfn.XLOOKUP(A1007,'2024'!B:B,'2024'!AZ:AZ,"") -> 0 | J1007: =_xlfn.XLOOKUP(A1007,'2025'!A:A,'2025'!E:E,"") | K1007: =_xlfn.XLOOKUP(A1007,'2025'!A:A,'2025'!F:F,"")
A1008: Brookfield Asset Management | B1008: =_xlfn.XLOOKUP(A1008,'2021'!A:A,'2021'!U:U, "") | C1008: =_xlfn.XLOOKUP(A1008,'2021'!A:A,'2021'!V:V,"") -> 1 | D1008: =_xlfn.XLOOKUP(A1008,'2022'!A:A,'2022'!V:V,"") | E1008: =_xlfn.XLOOKUP(A1008,'2022'!A:A,'2022'!W:W,"") -> 1 | F1008: =_xlfn.XLOOKUP(A1008,'2023'!B:B,'2023'!AD:AD,"") | G1008: =_xlfn.XLOOKUP(A1008,'2023'!B:B,'2023'!AE:AE,"") -> 1 | H1008: =_xlfn.XLOOKUP(A1008,'2024'!B:B,'2024'!AV:AV,"") | I1008: =_xlfn.XLOOKUP(A1008,'2024'!B:B,'2024'!AZ:AZ,"") | J1008: =_xlfn.XLOOKUP(A1008,'2025'!A:A,'2025'!E:E,"") | K1008: =_xlfn.XLOOKUP(A1008,'2025'!A:A,'2025'!F:F,"")
A1009: Amer International Group | B1009: =_xlfn.XLOOKUP(A1009,'2021'!A:A,'2021'!U:U, "") | C1009: =_xlfn.XLOOKUP(A1009,'2021'!A:A,'2021'!V:V,"") | D1009: =_xlfn.XLOOKUP(A1009,'2022'!A:A,'2022'!V:V,"") | E1009: =_xlfn.XLOOKUP(A1009,'2022'!A:A,'2022'!W:W,"") | F1009: =_xlfn.XLOOKUP(A1009,'2023'!B:B,'2023'!AD:AD,"") | G1009: =_xlfn.XLOOKUP(A1009,'2023'!B:B,'2023'!AE:AE,"") | H1009: =_xlfn.XLOOKUP(A1009,'2024'!B:B,'2024'!AV:AV,"") | I1009: =_xlfn.XLOOKUP(A1009,'2024'!B:B,'2024'!AZ:AZ,"") | J1009: =_xlfn.XLOOKUP(A1009,'2025'!A:A,'2025'!E:E,"") | K1009: =_xlfn.XLOOKUP(A1009,'2025'!A:A,'2025'!F:F,"")
A1010: Crédit Agricole | B1010: =_xlfn.XLOOKUP(A1010,'2021'!A:A,'2021'!U:U, "") | C1010: =_xlfn.XLOOKUP(A1010,'2021'!A:A,'2021'!V:V,"") -> 1 | D1010: =_xlfn.XLOOKUP(A1010,'2022'!A:A,'2022'!V:V,"") | E1010: =_xlfn.XLOOKUP(A1010,'2022'!A:A,'2022'!W:W,"") | F1010: =_xlfn.XLOOKUP(A1010,'2023'!B:B,'2023'!AD:AD,"") -> 1 | G1010: =_xlfn.XLOOKUP(A1010,'2023'!B:B,'2023'!AE:AE,"") | H1010: =_xlfn.XLOOKUP(A1010,'2024'!B:B,'2024'!AV:AV,"") | I1010: =_xlfn.XLOOKUP(A1010,'2024'!B:B,'2024'!AZ:AZ,"") | J1010: =_xlfn.XLOOKUP(A1010,'2025'!A:A,'2025'!E:E,"") | K1010: =_xlfn.XLOOKUP(A1010,'2025'!A:A,'2025'!F:F,"")
A1011: Aviation Industry Corp. of China | B1011: =_xlfn.XLOOKUP(A1011,'2021'!A:A,'2021'!U:U, "") | C1011: =_xlfn.XLOOKUP(A1011,'2021'!A:A,'2021'!V:V,"") | D1011: =_xlfn.XLOOKUP(A1011,'2022'!A:A,'2022'!V:V,"") | E1011: =_xlfn.XLOOKUP(A1011,'2022'!A:A,'2022'!W:W,"") -> 1 | F1011: =_xlfn.XLOOKUP(A1011,'2023'!B:B,'2023'!AD:AD,"") | G1011: =_xlfn.XLOOKUP(A1011,'2023'!B:B,'2023'!AE:AE,"") | H1011: =_xlfn.XLOOKUP(A1011,'2024'!B:B,'2024'!AV:AV,"") | I1011: =_xlfn.XLOOKUP(A1011,'2024'!B:B,'2024'!AZ:AZ,"") -> 1 | J1011: =_xlfn.XLOOKUP(A1011,'2025'!A:A,'2025'!E:E,"") | K1011: =_xlfn.XLOOKUP(A1011,'2025'!A:A,'2025'!F:F,"")
A1012: General Electric | B1012: =_xlfn.XLOOKUP(A1012,'2021'!A:A,'2021'!U:U, "") -> 1 | C1012: =_xlfn.XLOOKUP(A1012,'2021'!A:A,'2021'!V:V,"") -> 1 | D1012: =_xlfn.XLOOKUP(A1012,'2022'!A:A,'2022'!V:V,"") -> 1 | E1012: =_xlfn.XLOOKUP(A1012,'2022'!A:A,'2022'!W:W,"") -> 1 | F1012: =_xlfn.XLOOKUP(A1012,'2023'!B:B,'2023'!AD:AD,"") | G1012: =_xlfn.XLOOKUP(A1012,'2023'!B:B,'2023'!AE:AE,"") -> 1 | H1012: =_xlfn.XLOOKUP(A1012,'2024'!B:B,'2024'!AV:AV,"") | I1012: =_xlfn.XLOOKUP(A1012,'2024'!B:B,'2024'!AZ:AZ,"") -> 1 | J1012: =_xlfn.XLOOKUP(A1012,'2025'!A:A,'2025'!E:E,"") | K1012: =_xlfn.XLOOKUP(A1012,'2025'!A:A,'2025'!F:F,"")
A1013: China Merchants Group | B1013: =_xlfn.XLOOKUP(A1013,'2021'!A:A,'2021'!U:U, "") | C1013: =_xlfn.XLOOKUP(A1013,'2021'!A:A,'2021'!V:V,"") | D1013: =_xlfn.XLOOKUP(A1013,'2022'!A:A,'2022'!V:V,"") | E1013: =_xlfn.XLOOKUP(A1013,'2022'!A:A,'2022'!W:W,"") | F1013: =_xlfn.XLOOKUP(A1013,'2023'!B:B,'2023'!AD:AD,"") | G1013: =_xlfn.XLOOKUP(A1013,'2023'!B:B,'2023'!AE:AE,"") | H1013: =_xlfn.XLOOKUP(A1013,'2024'!B:B,'2024'!AV:AV,"") | I1013: =_xlfn.XLOOKUP(A1013,'2024'!B:B,'2024'!AZ:AZ,"") | J1013: =_xlfn.XLOOKUP(A1013,'2025'!A:A,'2025'!E:E,"") | K1013: =_xlfn.XLOOKUP(A1013,'2025'!A:A,'2025'!F:F,"")
... A1154: Yango Longking Group | B1154: =_xlfn.XLOOKUP(A1154,'2021'!A:A,'2021'!U:U, "") | C1154: =_xlfn.XLOOKUP(A1154,'2021'!A:A,'2021'!V:V,"") | D1154: =_xlfn.XLOOKUP(A1154,'2022'!A:A,'2022'!V:V,"") | E1154: =_xlfn.XLOOKUP(A1154,'2022'!A:A,'2022'!W:W,"") | F1154: =_xlfn.XLOOKUP(A1154,'2023'!B:B,'2023'!AD:AD,"") | G1154: =_xlfn.XLOOKUP(A1154,'2023'!B:B,'2023'!AE:AE,"") | H1154: =_xlfn.XLOOKUP(A1154,'2024'!B:B,'2024'!AV:AV,"") | I1154: =_xlfn.XLOOKUP(A1154,'2024'!B:B,'2024'!AZ:AZ,"") | J1154: =_xlfn.XLOOKUP(A1154,'2025'!A:A,'2025'!E:E,"") | K1154: =_xlfn.XLOOKUP(A1154,'2025'!A:A,'2025'!F:F,"")

Sheet sbti nz
A1: company | B1: 2021 sbti nt | C1: 2021 nz | D1: 2022 sbti nt | E1: 2022 nz | F1: 2023 sbti nt | G1: 2023 nz | H1: 2024 sbti nt | I1: 2024 nz | J1: 2025 sbti nt | K1: 2025 nz
A2: {=_xlfn.UNIQUE(_xlfn.VSTACK(sbti!A3:A502,sbti!F3:F503,sbti!L3:L502,sbti!R3:R502,sbti!W3:W502))} -> Walmart | B2: =_xlfn.XLOOKUP(A2,'2021'!A:A,'2021'!X:X,"") -> 1 | C2: =_xlfn.XLOOKUP(A2,'2021'!A:A,'2021'!V:V,"") -> 1 | D2: =_xlfn.XLOOKUP(A2,'2022'!A:A,'2022'!X:X,"") -> 1 | E2: =_xlfn.XLOOKUP(A2,'2022'!A:A,'2022'!W:W,"") -> 1 | F2: =_xlfn.XLOOKUP(A2,'2023'!B:B,'2023'!AF:AF,"") -> 1 | G2: =_xlfn.XLOOKUP(A2,'2023'!B:B,'2023'!AE:AE,"") -> 1 | H2: =_xlfn.XLOOKUP(A2,'2024'!B:B,'2024'!BW:BW,"") -> 1 | I2: =_xlfn.XLOOKUP(A2,'2024'!B:B,'2024'!AZ:AZ,"") -> 1 | J2: =_xlfn.XLOOKUP(A2,'2025'!A:A,'2025'!C:C,"") -> 1 | K2: =_xlfn.XLOOKUP(A2,'2025'!A:A,'2025'!F:F,"") -> 1
A3: Amazon | B3: =_xlfn.XLOOKUP(A3,'2021'!A:A,'2021'!X:X,"") | C3: =_xlfn.XLOOKUP(A3,'2021'!A:A,'2021'!V:V,"") -> 1 | D3: =_xlfn.XLOOKUP(A3,'2022'!A:A,'2022'!X:X,"") | E3: =_xlfn.XLOOKUP(A3,'2022'!A:A,'2022'!W:W,"") -> 1 | F3: =_xlfn.XLOOKUP(A3,'2023'!B:B,'2023'!AF:AF,"") | G3: =_xlfn.XLOOKUP(A3,'2023'!B:B,'2023'!AE:AE,"") -> 1 | H3: =_xlfn.XLOOKUP(A3,'2024'!B:B,'2024'!BW:BW,"") | I3: =_xlfn.XLOOKUP(A3,'2024'!B:B,'2024'!AZ:AZ,"") -> 1 | J3: =_xlfn.XLOOKUP(A3,'2025'!A:A,'2025'!C:C,"") -> 0 | K3: =_xlfn.XLOOKUP(A3,'2025'!A:A,'2025'!F:F,"") -> 1
A4: State Grid | B4: =_xlfn.XLOOKUP(A4,'2021'!A:A,'2021'!X:X,"") | C4: =_xlfn.XLOOKUP(A4,'2021'!A:A,'2021'!V:V,"") | D4: =_xlfn.XLOOKUP(A4,'2022'!A:A,'2022'!X:X,"") | E4: =_xlfn.XLOOKUP(A4,'2022'!A:A,'2022'!W:W,"") | F4: =_xlfn.XLOOKUP(A4,'2023'!B:B,'2023'!AF:AF,"") | G4: =_xlfn.XLOOKUP(A4,'2023'!B:B,'2023'!AE:AE,"") | H4: =_xlfn.XLOOKUP(A4,'2024'!B:B,'2024'!BW:BW,"") | I4: =_xlfn.XLOOKUP(A4,'2024'!B:B,'2024'!AZ:AZ,"") -> 0 | J4: =_xlfn.XLOOKUP(A4,'2025'!A:A,'2025'!C:C,"") -> 0 | K4: =_xlfn.XLOOKUP(A4,'2025'!A:A,'2025'!F:F,"") -> 0
A5: Saudi Aramco | B5: =_xlfn.XLOOKUP(A5,'2021'!A:A,'2021'!X:X,"") | C5: =_xlfn.XLOOKUP(A5,'2021'!A:A,'2021'!V:V,"") | D5: =_xlfn.XLOOKUP(A5,'2022'!A:A,'2022'!X:X,"") | E5: =_xlfn.XLOOKUP(A5,'2022'!A:A,'2022'!W:W,"") -> 1 | F5: =_xlfn.XLOOKUP(A5,'2023'!B:B,'2023'!AF:AF,"") | G5: =_xlfn.XLOOKUP(A5,'2023'!B:B,'2023'!AE:AE,"") -> 1 | H5: =_xlfn.XLOOKUP(A5,'2024'!B:B,'2024'!BW:BW,"") | I5: =_xlfn.XLOOKUP(A5,'2024'!B:B,'2024'!AZ:AZ,"") -> 1 | J5: =_xlfn.XLOOKUP(A5,'2025'!A:A,'2025'!C:C,"") -> 0 | K5: =_xlfn.XLOOKUP(A5,'2025'!A:A,'2025'!F:F,"") -> 1
A6: China National Petroleum | B6: =_xlfn.XLOOKUP(A6,'2021'!A:A,'2021'!X:X,"") | C6: =_xlfn.XLOOKUP(A6,'2021'!A:A,'2021'!V:V,"") -> 1 | D6: =_xlfn.XLOOKUP(A6,'2022'!A:A,'2022'!X:X,"") | E6: =_xlfn.XLOOKUP(A6,'2022'!A:A,'2022'!W:W,"") -> 1 | F6: =_xlfn.XLOOKUP(A6,'2023'!B:B,'2023'!AF:AF,"") | G6: =_xlfn.XLOOKUP(A6,'2023'!B:B,'2023'!AE:AE,"") | H6: =_xlfn.XLOOKUP(A6,'2024'!B:B,'2024'!BW:BW,"") | I6: =_xlfn.XLOOKUP(A6,'2024'!B:B,'2024'!AZ:AZ,"") -> 0 | J6: =_xlfn.XLOOKUP(A6,'2025'!A:A,'2025'!C:C,"") -> 0 | K6: =_xlfn.XLOOKUP(A6,'2025'!A:A,'2025'!F:F,"") -> 1
A7: Sinopec Group | B7: =_xlfn.XLOOKUP(A7,'2021'!A:A,'2021'!X:X,"") | C7: =_xlfn.XLOOKUP(A7,'2021'!A:A,'2021'!V:V,"") | D7: =_xlfn.XLOOKUP(A7,'2022'!A:A,'2022'!X:X,"") | E7: =_xlfn.XLOOKUP(A7,'2022'!A:A,'2022'!W:W,"") | F7: =_xlfn.XLOOKUP(A7,'2023'!B:B,'2023'!AF:AF,"") | G7: =_xlfn.XLOOKUP(A7,'2023'!B:B,'2023'!AE:AE,"") | H7: =_xlfn.XLOOKUP(A7,'2024'!B:B,'2024'!BW:BW,"") | I7: =_xlfn.XLOOKUP(A7,'2024'!B:B,'2024'!AZ:AZ,"") -> 0 | J7: =_xlfn.XLOOKUP(A7,'2025'!A:A,'2025'!C:C,"") -> 0 | K7: =_xlfn.XLOOKUP(A7,'2025'!A:A,'2025'!F:F,"") -> 0
A8: UnitedHealth Group | B8: =_xlfn.XLOOKUP(A8,'2021'!A:A,'2021'!X:X,"") | C8: =_xlfn.XLOOKUP(A8,'2021'!A:A,'2021'!V:V,"") | D8: =_xlfn.XLOOKUP(A8,'2022'!A:A,'2022'!X:X,"") | E8: =_xlfn.XLOOKUP(A8,'2022'!A:A,'2022'!W:W,"") -> 1 | F8: =_xlfn.XLOOKUP(A8,'2023'!B:B,'2023'!AF:AF,"") | G8: =_xlfn.XLOOKUP(A8,'2023'!B:B,'2023'!AE:AE,"") -> 1 | H8: =_xlfn.XLOOKUP(A8,'2024'!B:B,'2024'!BW:BW,"") | I8: =_xlfn.XLOOKUP(A8,'2024'!B:B,'2024'!AZ:AZ,"") -> 1 | J8: =_xlfn.XLOOKUP(A8,'2025'!A:A,'2025'!C:C,"") -> 1 | K8: =_xlfn.XLOOKUP(A8,'2025'!A:A,'2025'!F:F,"") -> 1
A9: Apple | B9: =_xlfn.XLOOKUP(A9,'2021'!A:A,'2021'!X:X,"") -> 1 | C9: =_xlfn.XLOOKUP(A9,'2021'!A:A,'2021'!V:V,"") -> 1 | D9: =_xlfn.XLOOKUP(A9,'2022'!A:A,'2022'!X:X,"") -> 1 | E9: =_xlfn.XLOOKUP(A9,'2022'!A:A,'2022'!W:W,"") | F9: =_xlfn.XLOOKUP(A9,'2023'!B:B,'2023'!AF:AF,"") -> 1 | G9: =_xlfn.XLOOKUP(A9,'2023'!B:B,'2023'!AE:AE,"") | H9: =_xlfn.XLOOKUP(A9,'2024'!B:B,'2024'!BW:BW,"") -> 1 | I9: =_xlfn.XLOOKUP(A9,'2024'!B:B,'2024'!AZ:AZ,"") -> 0 | J9: =_xlfn.XLOOKUP(A9,'2025'!A:A,'2025'!C:C,"") -> 1 | K9: =_xlfn.XLOOKUP(A9,'2025'!A:A,'2025'!F:F,"") -> 0
A10: CVS Health | B10: =_xlfn.XLOOKUP(A10,'2021'!A:A,'2021'!X:X,"") -> 1 | C10: =_xlfn.XLOOKUP(A10,'2021'!A:A,'2021'!V:V,"") | D10: =_xlfn.XLOOKUP(A10,'2022'!A:A,'2022'!X:X,"") -> 1 | E10: =_xlfn.XLOOKUP(A10,'2022'!A:A,'2022'!W:W,"") -> 1 | F10: =_xlfn.XLOOKUP(A10,'2023'!B:B,'2023'!AF:AF,"") -> 1 | G10: =_xlfn.XLOOKUP(A10,'2023'!B:B,'2023'!AE:AE,"") -> 1 | H10: =_xlfn.XLOOKUP(A10,'2024'!B:B,'2024'!BW:BW,"") -> 1 | I10: =_xlfn.XLOOKUP(A10,'2024'!B:B,'2024'!AZ:AZ,"") -> 1 | J10: =_xlfn.XLOOKUP(A10,'2025'!A:A,'2025'!C:C,"") -> 1 | K10: =_xlfn.XLOOKUP(A10,'2025'!A:A,'2025'!F:F,"") -> 1
A11: Berkshire Hathaway | B11: =_xlfn.XLOOKUP(A11,'2021'!A:A,'2021'!X:X,"") | C11: =_xlfn.XLOOKUP(A11,'2021'!A:A,'2021'!V:V,"") | D11: =_xlfn.XLOOKUP(A11,'2022'!A:A,'2022'!X:X,"") | E11: =_xlfn.XLOOKUP(A11,'2022'!A:A,'2022'!W:W,"") | F11: =_xlfn.XLOOKUP(A11,'2023'!B:B,'2023'!AF:AF,"") | G11: =_xlfn.XLOOKUP(A11,'2023'!B:B,'2023'!AE:AE,"") | H11: =_xlfn.XLOOKUP(A11,'2024'!B:B,'2024'!BW:BW,"") | I11: =_xlfn.XLOOKUP(A11,'2024'!B:B,'2024'!AZ:AZ,"") -> 0 | J11: =_xlfn.XLOOKUP(A11,'2025'!A:A,'2025'!C:C,"") -> 0 | K11: =_xlfn.XLOOKUP(A11,'2025'!A:A,'2025'!F:F,"") -> 0
A12: McKesson | B12: =_xlfn.XLOOKUP(A12,'2021'!A:A,'2021'!X:X,"") | C12: =_xlfn.XLOOKUP(A12,'2021'!A:A,'2021'!V:V,"") | D12: =_xlfn.XLOOKUP(A12,'2022'!A:A,'2022'!X:X,"") | E12: =_xlfn.XLOOKUP(A12,'2022'!A:A,'2022'!W:W,"") | F12: =_xlfn.XLOOKUP(A12,'2023'!B:B,'2023'!AF:AF,"") -> 1 | G12: =_xlfn.XLOOKUP(A12,'2023'!B:B,'2023'!AE:AE,"") | H12: =_xlfn.XLOOKUP(A12,'2024'!B:B,'2024'!BW:BW,"") -> 1 | I12: =_xlfn.XLOOKUP(A12,'2024'!B:B,'2024'!AZ:AZ,"") -> 0 | J12: =_xlfn.XLOOKUP(A12,'2025'!A:A,'2025'!C:C,"") -> 1 | K12: =_xlfn.XLOOKUP(A12,'2025'!A:A,'2025'!F:F,"") -> 0
A13: Volkswagen | B13: =_xlfn.XLOOKUP(A13,'2021'!A:A,'2021'!X:X,"") -> 1 | C13: =_xlfn.XLOOKUP(A13,'2021'!A:A,'2021'!V:V,"") | D13: =_xlfn.XLOOKUP(A13,'2022'!A:A,'2022'!X:X,"") -> 1 | E13: =_xlfn.XLOOKUP(A13,'2022'!A:A,'2022'!W:W,"") | F13: =_xlfn.XLOOKUP(A13,'2023'!B:B,'2023'!AF:AF,"") -> 1 | G13: =_xlfn.XLOOKUP(A13,'2023'!B:B,'2023'!AE:AE,"") | H13: =_xlfn.XLOOKUP(A13,'2024'!B:B,'2024'!BW:BW,"") -> 1 | I13: =_xlfn.XLOOKUP(A13,'2024'!B:B,'2024'!AZ:AZ,"") -> 0 | J13: =_xlfn.XLOOKUP(A13,'2025'!A:A,'2025'!C:C,"") -> 1 | K13: =_xlfn.XLOOKUP(A13,'2025'!A:A,'2025'!F:F,"") -> 0
A14: Alphabet | B14: =_xlfn.XLOOKUP(A14,'2021'!A:A,'2021'!X:X,"") | C14: =_xlfn.XLOOKUP(A14,'2021'!A:A,'2021'!V:V,"") | D14: =_xlfn.XLOOKUP(A14,'2022'!A:A,'2022'!X:X,"") | E14: =_xlfn.XLOOKUP(A14,'2022'!A:A,'2022'!W:W,"") -> 1 | F14: =_xlfn.XLOOKUP(A14,'2023'!B:B,'2023'!AF:AF,"") | G14: =_xlfn.XLOOKUP(A14,'2023'!B:B,'2023'!AE:AE,"") -> 1 | H14: =_xlfn.XLOOKUP(A14,'2024'!B:B,'2024'!BW:BW,"") | I14: =_xlfn.XLOOKUP(A14,'2024'!B:B,'2024'!AZ:AZ,"") -> 1 | J14: =_xlfn.XLOOKUP(A14,'2025'!A:A,'2025'!C:C,"") -> 1 | K14: =_xlfn.XLOOKUP(A14,'2025'!A:A,'2025'!F:F,"") -> 1
... A534: Vibra Energia | B534: =_xlfn.XLOOKUP(A534,'2021'!A:A,'2021'!X:X,"") | C534: =_xlfn.XLOOKUP(A534,'2021'!A:A,'2021'!V:V,"") | D534: =_xlfn.XLOOKUP(A534,'2022'!A:A,'2022'!X:X,"") | E534: =_xlfn.XLOOKUP(A534,'2022'!A:A,'2022'!W:W,"") | F534: =_xlfn.XLOOKUP(A534,'2023'!B:B,'2023'!AF:AF,"") | G534: =_xlfn.XLOOKUP(A534,'2023'!B:B,'2023'!AE:AE,"") | H534: =_xlfn.XLOOKUP(A534,'2024'!B:B,'2024'!BW:BW,"") | I534: =_xlfn.XLOOKUP(A534,'2024'!B:B,'2024'!AZ:AZ,"") -> 0 | J534: =_xlfn.XLOOKUP(A534,'2025'!A:A,'2025'!C:C,"") | K534: =_xlfn.XLOOKUP(A534,'2025'!A:A,'2025'!F:F,"")
A535: 0 | B535: =_xlfn.XLOOKUP(A535,'2021'!A:A,'2021'!X:X,"") | C535: =_xlfn.XLOOKUP(A535,'2021'!A:A,'2021'!V:V,"") | D535: =_xlfn.XLOOKUP(A535,'2022'!A:A,'2022'!X:X,"") | E535: =_xlfn.XLOOKUP(A535,'2022'!A:A,'2022'!W:W,"") | F535: =_xlfn.XLOOKUP(A535,'2023'!B:B,'2023'!AF:AF,"") | G535: =_xlfn.XLOOKUP(A535,'2023'!B:B,'2023'!AE:AE,"") | H535: =_xlfn.XLOOKUP(A535,'2024'!B:B,'2024'!BW:BW,"") | I535: =_xlfn.XLOOKUP(A535,'2024'!B:B,'2024'!AZ:AZ,"") | J535: =_xlfn.XLOOKUP(A535,'2025'!A:A,'2025'!C:C,"") | K535: =_xlfn.XLOOKUP(A535,'2025'!A:A,'2025'!F:F,"")
A536: Crédit Agricole | B536: =_xlfn.XLOOKUP(A536,'2021'!A:A,'2021'!X:X,"") | C536: =_xlfn.XLOOKUP(A536,'2021'!A:A,'2021'!V:V,"") -> 1 | D536: =_xlfn.XLOOKUP(A536,'2022'!A:A,'2022'!X:X,"") | E536: =_xlfn.XLOOKUP(A536,'2022'!A:A,'2022'!W:W,"") | F536: =_xlfn.XLOOKUP(A536,'2023'!B:B,'2023'!AF:AF,"") | G536: =_xlfn.XLOOKUP(A536,'2023'!B:B,'2023'!AE:AE,"") | H536: =_xlfn.XLOOKUP(A536,'2024'!B:B,'2024'!BW:BW,"") | I536: =_xlfn.XLOOKUP(A536,'2024'!B:B,'2024'!AZ:AZ,"") | J536: =_xlfn.XLOOKUP(A536,'2025'!A:A,'2025'!C:C,"") | K536: =_xlfn.XLOOKUP(A536,'2025'!A:A,'2025'!F:F,"")
A537: China Merchants Group | B537: =_xlfn.XLOOKUP(A537,'2021'!A:A,'2021'!X:X,"") | C537: =_xlfn.XLOOKUP(A537,'2021'!A:A,'2021'!V:V,"") | D537: =_xlfn.XLOOKUP(A537,'2022'!A:A,'2022'!X:X,"") | E537: =_xlfn.XLOOKUP(A537,'2022'!A:A,'2022'!W:W,"") | F537: =_xlfn.XLOOKUP(A537,'2023'!B:B,'2023'!AF:AF,"") | G537: =_xlfn.XLOOKUP(A537,'2023'!B:B,'2023'!AE:AE,"") | H537: =_xlfn.XLOOKUP(A537,'2024'!B:B,'2024'!BW:BW,"") | I537: =_xlfn.XLOOKUP(A537,'2024'!B:B,'2024'!AZ:AZ,"") | J537: =_xlfn.XLOOKUP(A537,'2025'!A:A,'2025'!C:C,"") | K537: =_xlfn.XLOOKUP(A537,'2025'!A:A,'2025'!F:F,"")
A538: Itaú Unibanco Holding | B538: =_xlfn.XLOOKUP(A538,'2021'!A:A,'2021'!X:X,"") | C538: =_xlfn.XLOOKUP(A538,'2021'!A:A,'2021'!V:V,"") | D538: =_xlfn.XLOOKUP(A538,'2022'!A:A,'2022'!X:X,"") | E538: =_xlfn.XLOOKUP(A538,'2022'!A:A,'2022'!W:W,"") -> 1 | F538: =_xlfn.XLOOKUP(A538,'2023'!B:B,'2023'!AF:AF,"") | G538: =_xlfn.XLOOKUP(A538,'2023'!B:B,'2023'!AE:AE,"") -> 1 | H538: =_xlfn.XLOOKUP(A538,'2024'!B:B,'2024'!BW:BW,"") | I538: =_xlfn.XLOOKUP(A538,'2024'!B:B,'2024'!AZ:AZ,"") | J538: =_xlfn.XLOOKUP(A538,'2025'!A:A,'2025'!C:C,"") | K538: =_xlfn.XLOOKUP(A538,'2025'!A:A,'2025'!F:F,"")
A539: Société Générale | B539: =_xlfn.XLOOKUP(A539,'2021'!A:A,'2021'!X:X,"") | C539: =_xlfn.XLOOKUP(A539,'2021'!A:A,'2021'!V:V,"") | D539: =_xlfn.XLOOKUP(A539,'2022'!A:A,'2022'!X:X,"") | E539: =_xlfn.XLOOKUP(A539,'2022'!A:A,'2022'!W:W,"") | F539: =_xlfn.XLOOKUP(A539,'2023'!B:B,'2023'!AF:AF,"") | G539: =_xlfn.XLOOKUP(A539,'2023'!B:B,'2023'!AE:AE,"") | H539: =_xlfn.XLOOKUP(A539,'2024'!B:B,'2024'!BW:BW,"") | I539: =_xlfn.XLOOKUP(A539,'2024'!B:B,'2024'!AZ:AZ,"") | J539: =_xlfn.XLOOKUP(A539,'2025'!A:A,'2025'!C:C,"") | K539: =_xlfn.XLOOKUP(A539,'2025'!A:A,'2025'!F:F,"")
A540: American International Group | B540: =_xlfn.XLOOKUP(A540,'2021'!A:A,'2021'!X:X,"") | C540: =_xlfn.XLOOKUP(A540,'2021'!A:A,'2021'!V:V,"") -> 1 | D540: =_xlfn.XLOOKUP(A540,'2022'!A:A,'2022'!X:X,"") | E540: =_xlfn.XLOOKUP(A540,'2022'!A:A,'2022'!W:W,"") -> 1 | F540: =_xlfn.XLOOKUP(A540,'2023'!B:B,'2023'!AF:AF,"") | G540: =_xlfn.XLOOKUP(A540,'2023'!B:B,'2023'!AE:AE,"") -> 1 | H540: =_xlfn.XLOOKUP(A540,'2024'!B:B,'2024'!BW:BW,"") | I540: =_xlfn.XLOOKUP(A540,'2024'!B:B,'2024'!AZ:AZ,"") | J540: =_xlfn.XLOOKUP(A540,'2025'!A:A,'2025'!C:C,"") | K540: =_xlfn.XLOOKUP(A540,'2025'!A:A,'2025'!F:F,"")
A541: Koç Holding | B541: =_xlfn.XLOOKUP(A541,'2021'!A:A,'2021'!X:X,"") | C541: =_xlfn.XLOOKUP(A541,'2021'!A:A,'2021'!V:V,"") | D541: =_xlfn.XLOOKUP(A541,'2022'!A:A,'2022'!X:X,"") | E541: =_xlfn.XLOOKUP(A541,'2022'!A:A,'2022'!W:W,"") | F541: =_xlfn.XLOOKUP(A541,'2023'!B:B,'2023'!AF:AF,"") | G541: =_xlfn.XLOOKUP(A541,'2023'!B:B,'2023'!AE:AE,"") | H541: =_xlfn.XLOOKUP(A541,'2024'!B:B,'2024'!BW:BW,"") | I541: =_xlfn.XLOOKUP(A541,'2024'!B:B,'2024'!AZ:AZ,"") | J541: =_xlfn.XLOOKUP(A541,'2025'!A:A,'2025'!C:C,"") | K541: =_xlfn.XLOOKUP(A541,'2025'!A:A,'2025'!F:F,"")
A542: Energi Danmark Group | B542: =_xlfn.XLOOKUP(A542,'2021'!A:A,'2021'!X:X,"") | C542: =_xlfn.XLOOKUP(A542,'2021'!A:A,'2021'!V:V,"") | D542: =_xlfn.XLOOKUP(A542,'2022'!A:A,'2022'!X:X,"") | E542: =_xlfn.XLOOKUP(A542,'2022'!A:A,'2022'!W:W,"") | F542: =_xlfn.XLOOKUP(A542,'2023'!B:B,'2023'!AF:AF,"") | G542: =_xlfn.XLOOKUP(A542,'2023'!B:B,'2023'!AE:AE,"") | H542: =_xlfn.XLOOKUP(A542,'2024'!B:B,'2024'!BW:BW,"") | I542: =_xlfn.XLOOKUP(A542,'2024'!B:B,'2024'!AZ:AZ,"") | J542: =_xlfn.XLOOKUP(A542,'2025'!A:A,'2025'!C:C,"") | K542: =_xlfn.XLOOKUP(A542,'2025'!A:A,'2025'!F:F,"")
A543: Fresenius | B543: =_xlfn.XLOOKUP(A543,'2021'!A:A,'2021'!X:X,"") | C543: =_xlfn.XLOOKUP(A543,'2021'!A:A,'2021'!V:V,"") | D543: =_xlfn.XLOOKUP(A543,'2022'!A:A,'2022'!X:X,"") | E543: =_xlfn.XLOOKUP(A543,'2022'!A:A,'2022'!W:W,"") -> 1 | F543: =_xlfn.XLOOKUP(A543,'2023'!B:B,'2023'!AF:AF,"") | G543: =_xlfn.XLOOKUP(A543,'2023'!B:B,'2023'!AE:AE,"") | H543: =_xlfn.XLOOKUP(A543,'2024'!B:B,'2024'!BW:BW,"") | I543: =_xlfn.XLOOKUP(A543,'2024'!B:B,'2024'!AZ:AZ,"") | J543: =_xlfn.XLOOKUP(A543,'2025'!A:A,'2025'!C:C,"") | K543: =_xlfn.XLOOKUP(A543,'2025'!A:A,'2025'!F:F,"")
A544: Telefónica | B544: =_xlfn.XLOOKUP(A544,'2021'!A:A,'2021'!X:X,"") -> 1 | C544: =_xlfn.XLOOKUP(A544,'2021'!A:A,'2021'!V:V,"") -> 1 | D544: =_xlfn.XLOOKUP(A544,'2022'!A:A,'2022'!X:X,"") -> 1 | E544: =_xlfn.XLOOKUP(A544,'2022'!A:A,'2022'!W:W,"") -> 1 | F544: =_xlfn.XLOOKUP(A544,'2023'!B:B,'2023'!AF:AF,"") -> 1 | G544: =_xlfn.XLOOKUP(A544,'2023'!B:B,'2023'!AE:AE,"") -> 1 | H544: =_xlfn.XLOOKUP(A544,'2024'!B:B,'2024'!BW:BW,"") | I544: =_xlfn.XLOOKUP(A544,'2024'!B:B,'2024'!AZ:AZ,"") | J544: =_xlfn.XLOOKUP(A544,'2025'!A:A,'2025'!C:C,"") | K544: =_xlfn.XLOOKUP(A544,'2025'!A:A,'2025'!F:F,"")
A545: Kuehne + Nagel International | B545: =_xlfn.XLOOKUP(A545,'2021'!A:A,'2021'!X:X,"") | C545: =_xlfn.XLOOKUP(A545,'2021'!A:A,'2021'!V:V,"") | D545: =_xlfn.XLOOKUP(A545,'2022'!A:A,'2022'!X:X,"") -> 1 | E545: =_xlfn.XLOOKUP(A545,'2022'!A:A,'2022'!W:W,"") | F545: =_xlfn.XLOOKUP(A545,'2023'!B:B,'2023'!AF:AF,"") -> 1 | G545: =_xlfn.XLOOKUP(A545,'2023'!B:B,'2023'!AE:AE,"") -> 1 | H545: =_xlfn.XLOOKUP(A545,'2024'!B:B,'2024'!BW:BW,"") | I545: =_xlfn.XLOOKUP(A545,'2024'!B:B,'2024'!AZ:AZ,"") | J545: =_xlfn.XLOOKUP(A545,'2025'!A:A,'2025'!C:C,"") | K545: =_xlfn.XLOOKUP(A545,'2025'!A:A,'2025'!F:F,"")
A546: RWE | B546: =_xlfn.XLOOKUP(A546,'2021'!A:A,'2021'!X:X,"") | C546: =_xlfn.XLOOKUP(A546,'2021'!A:A,'2021'!V:V,"") | D546: =_xlfn.XLOOKUP(A546,'2022'!A:A,'2022'!X:X,"") -> 1 | E546: =_xlfn.XLOOKUP(A546,'2022'!A:A,'2022'!W:W,"") | F546: =_xlfn.XLOOKUP(A546,'2023'!B:B,'2023'!AF:AF,"") -> 1 | G546: =_xlfn.XLOOKUP(A546,'2023'!B:B,'2023'!AE:AE,"") | H546: =_xlfn.XLOOKUP(A546,'2024'!B:B,'2024'!BW:BW,"") | I546: =_xlfn.XLOOKUP(A546,'2024'!B:B,'2024'!AZ:AZ,"") | J546: =_xlfn.XLOOKUP(A546,'2025'!A:A,'2025'!C:C,"") | K546: =_xlfn.XLOOKUP(A546,'2025'!A:A,'2025'!F:F,"")
A547: China Taiping Insurance Group | B547: =_xlfn.XLOOKUP(A547,'2021'!A:A,'2021'!X:X,"") | C547: =_xlfn.XLOOKUP(A547,'2021'!A:A,'2021'!V:V,"") | D547: =_xlfn.XLOOKUP(A547,'2022'!A:A,'2022'!X:X,"") | E547: =_xlfn.XLOOKUP(A547,'2022'!A:A,'2022'!W:W,"") | F547: =_xlfn.XLOOKUP(A547,'2023'!B:B,'2023'!AF:AF,"") | G547: =_xlfn.XLOOKUP(A547,'2023'!B:B,'2023'!AE:AE,"") -> 1 | H547: =_xlfn.XLOOKUP(A547,'2024'!B:B,'2024'!BW:BW,"") | I547: =_xlfn.XLOOKUP(A547,'2024'!B:B,'2024'!AZ:AZ,"") | J547: =_xlfn.XLOOKUP(A547,'2025'!A:A,'2025'!C:C,"") | K547: =_xlfn.XLOOKUP(A547,'2025'!A:A,'2025'!F:F,"")
... A638: Yango Longking Group | B638: =_xlfn.XLOOKUP(A638,'2021'!A:A,'2021'!X:X,"") | C638: =_xlfn.XLOOKUP(A638,'2021'!A:A,'2021'!V:V,"") | D638: =_xlfn.XLOOKUP(A638,'2022'!A:A,'2022'!X:X,"") | E638: =_xlfn.XLOOKUP(A638,'2022'!A:A,'2022'!W:W,"") | F638: =_xlfn.XLOOKUP(A638,'2023'!B:B,'2023'!AF:AF,"") | G638: =_xlfn.XLOOKUP(A638,'2023'!B:B,'2023'!AE:AE,"") | H638: =_xlfn.XLOOKUP(A638,'2024'!B:B,'2024'!BW:BW,"") | I638: =_xlfn.XLOOKUP(A638,'2024'!B:B,'2024'!AZ:AZ,"") | J638: =_xlfn.XLOOKUP(A638,'2025'!A:A,'2025'!C:C,"") | K638: =_xlfn.XLOOKUP(A638,'2025'!A:A,'2025'!F:F,"")
A639: #N/A | B639: =_xlfn.XLOOKUP(A639,'2021'!A:A,'2021'!X:X,"") -> #N/A | C639: =_xlfn.XLOOKUP(A639,'2021'!A:A,'2021'!V:V,"") -> #N/A | D639: =_xlfn.XLOOKUP(A639,'2022'!A:A,'2022'!X:X,"") -> #N/A | E639: =_xlfn.XLOOKUP(A639,'2022'!A:A,'2022'!W:W,"") -> #N/A | F639: =_xlfn.XLOOKUP(A639,'2023'!B:B,'2023'!AF:AF,"") -> #N/A | G639: =_xlfn.XLOOKUP(A639,'2023'!B:B,'2023'!AE:AE,"") -> #N/A | H639: =_xlfn.XLOOKUP(A639,'2024'!B:B,'2024'!BW:BW,"") -> #N/A | I639: =_xlfn.XLOOKUP(A639,'2024'!B:B,'2024'!AZ:AZ,"") -> #N/A | J639: =_xlfn.XLOOKUP(A639,'2025'!A:A,'2025'!C:C,"") -> #N/A | K639: =_xlfn.XLOOKUP(A639,'2025'!A:A,'2025'!F:F,"") -> #N/A
A640: #N/A | B640: =_xlfn.XLOOKUP(A640,'2021'!A:A,'2021'!X:X,"") -> #N/A | C640: =_xlfn.XLOOKUP(A640,'2021'!A:A,'2021'!V:V,"") -> #N/A | D640: =_xlfn.XLOOKUP(A640,'2022'!A:A,'2022'!X:X,"") -> #N/A | E640: =_xlfn.XLOOKUP(A640,'2022'!A:A,'2022'!W:W,"") -> #N/A | F640: =_xlfn.XLOOKUP(A640,'2023'!B:B,'2023'!AF:AF,"") -> #N/A | G640: =_xlfn.XLOOKUP(A640,'2023'!B:B,'2023'!AE:AE,"") -> #N/A | H640: =_xlfn.XLOOKUP(A640,'2024'!B:B,'2024'!BW:BW,"") -> #N/A | I640: =_xlfn.XLOOKUP(A640,'2024'!B:B,'2024'!AZ:AZ,"") -> #N/A | J640: =_xlfn.XLOOKUP(A640,'2025'!A:A,'2025'!C:C,"") -> #N/A | K640: =_xlfn.XLOOKUP(A640,'2025'!A:A,'2025'!F:F,"") -> #N/A
A641: #N/A | B641: =_xlfn.XLOOKUP(A641,'2021'!A:A,'2021'!X:X,"") -> #N/A | C641: =_xlfn.XLOOKUP(A641,'2021'!A:A,'2021'!V:V,"") -> #N/A | D641: =_xlfn.XLOOKUP(A641,'2022'!A:A,'2022'!X:X,"") -> #N/A | E641: =_xlfn.XLOOKUP(A641,'2022'!A:A,'2022'!W:W,"") -> #N/A | F641: =_xlfn.XLOOKUP(A641,'2023'!B:B,'2023'!AF:AF,"") -> #N/A | G641: =_xlfn.XLOOKUP(A641,'2023'!B:B,'2023'!AE:AE,"") -> #N/A | H641: =_xlfn.XLOOKUP(A641,'2024'!B:B,'2024'!BW:BW,"") -> #N/A | I641: =_xlfn.XLOOKUP(A641,'2024'!B:B,'2024'!AZ:AZ,"") -> #N/A | J641: =_xlfn.XLOOKUP(A641,'2025'!A:A,'2025'!C:C,"") -> #N/A | K641: =_xlfn.XLOOKUP(A641,'2025'!A:A,'2025'!F:F,"") -> #N/A
A642: #N/A | B642: =_xlfn.XLOOKUP(A642,'2021'!A:A,'2021'!X:X,"") -> #N/A | C642: =_xlfn.XLOOKUP(A642,'2021'!A:A,'2021'!V:V,"") -> #N/A | D642: =_xlfn.XLOOKUP(A642,'2022'!A:A,'2022'!X:X,"") -> #N/A | E642: =_xlfn.XLOOKUP(A642,'2022'!A:A,'2022'!W:W,"") -> #N/A | F642: =_xlfn.XLOOKUP(A642,'2023'!B:B,'2023'!AF:AF,"") -> #N/A | G642: =_xlfn.XLOOKUP(A642,'2023'!B:B,'2023'!AE:AE,"") -> #N/A | H642: =_xlfn.XLOOKUP(A642,'2024'!B:B,'2024'!BW:BW,"") -> #N/A | I642: =_xlfn.XLOOKUP(A642,'2024'!B:B,'2024'!AZ:AZ,"") -> #N/A | J642: =_xlfn.XLOOKUP(A642,'2025'!A:A,'2025'!C:C,"") -> #N/A | K642: =_xlfn.XLOOKUP(A642,'2025'!A:A,'2025'!F:F,"") -> #N/A
A643: #N/A | B643: =_xlfn.XLOOKUP(A643,'2021'!A:A,'2021'!X:X,"") -> #N/A | C643: =_xlfn.XLOOKUP(A643,'2021'!A:A,'2021'!V:V,"") -> #N/A | D643: =_xlfn.XLOOKUP(A643,'2022'!A:A,'2022'!X:X,"") -> #N/A | E643: =_xlfn.XLOOKUP(A643,'2022'!A:A,'2022'!W:W,"") -> #N/A | F643: =_xlfn.XLOOKUP(A643,'2023'!B:B,'2023'!AF:AF,"") -> #N/A | G643: =_xlfn.XLOOKUP(A643,'2023'!B:B,'2023'!AE:AE,"") -> #N/A | H643: =_xlfn.XLOOKUP(A643,'2024'!B:B,'2024'!BW:BW,"") -> #N/A | I643: =_xlfn.XLOOKUP(A643,'2024'!B:B,'2024'!AZ:AZ,"") -> #N/A | J643: =_xlfn.XLOOKUP(A643,'2025'!A:A,'2025'!C:C,"") -> #N/A | K643: =_xlfn.XLOOKUP(A643,'2025'!A:A,'2025'!F:F,"") -> #N/A
A644: #N/A | B644: =_xlfn.XLOOKUP(A644,'2021'!A:A,'2021'!X:X,"") -> #N/A | C644: =_xlfn.XLOOKUP(A644,'2021'!A:A,'2021'!V:V,"") -> #N/A | D644: =_xlfn.XLOOKUP(A644,'2022'!A:A,'2022'!X:X,"") -> #N/A | E644: =_xlfn.XLOOKUP(A644,'2022'!A:A,'2022'!W:W,"") -> #N/A | F644: =_xlfn.XLOOKUP(A644,'2023'!B:B,'2023'!AF:AF,"") -> #N/A | G644: =_xlfn.XLOOKUP(A644,'2023'!B:B,'2023'!AE:AE,"") -> #N/A | H644: =_xlfn.XLOOKUP(A644,'2024'!B:B,'2024'!BW:BW,"") -> #N/A | I644: =_xlfn.XLOOKUP(A644,'2024'!B:B,'2024'!AZ:AZ,"") -> #N/A | J644: =_xlfn.XLOOKUP(A644,'2025'!A:A,'2025'!C:C,"") -> #N/A | K644: =_xlfn.XLOOKUP(A644,'2025'!A:A,'2025'!F:F,"") -> #N/A
A645: #N/A | B645: =_xlfn.XLOOKUP(A645,'2021'!A:A,'2021'!X:X,"") -> #N/A | C645: =_xlfn.XLOOKUP(A645,'2021'!A:A,'2021'!V:V,"") -> #N/A | D645: =_xlfn.XLOOKUP(A645,'2022'!A:A,'2022'!X:X,"") -> #N/A | E645: =_xlfn.XLOOKUP(A645,'2022'!A:A,'2022'!W:W,"") -> #N/A | F645: =_xlfn.XLOOKUP(A645,'2023'!B:B,'2023'!AF:AF,"") -> #N/A | G645: =_xlfn.XLOOKUP(A645,'2023'!B:B,'2023'!AE:AE,"") -> #N/A | H645: =_xlfn.XLOOKUP(A645,'2024'!B:B,'2024'!BW:BW,"") -> #N/A | I645: =_xlfn.XLOOKUP(A645,'2024'!B:B,'2024'!AZ:AZ,"") -> #N/A | J645: =_xlfn.XLOOKUP(A645,'2025'!A:A,'2025'!C:C,"") -> #N/A | K645: =_xlfn.XLOOKUP(A645,'2025'!A:A,'2025'!F:F,"") -> #N/A
A646: #N/A | B646: =_xlfn.XLOOKUP(A646,'2021'!A:A,'2021'!X:X,"") -> #N/A | C646: =_xlfn.XLOOKUP(A646,'2021'!A:A,'2021'!V:V,"") -> #N/A | D646: =_xlfn.XLOOKUP(A646,'2022'!A:A,'2022'!X:X,"") -> #N/A | E646: =_xlfn.XLOOKUP(A646,'2022'!A:A,'2022'!W:W,"") -> #N/A | F646: =_xlfn.XLOOKUP(A646,'2023'!B:B,'2023'!AF:AF,"") -> #N/A | G646: =_xlfn.XLOOKUP(A646,'2023'!B:B,'2023'!AE:AE,"") -> #N/A | H646: =_xlfn.XLOOKUP(A646,'2024'!B:B,'2024'!BW:BW,"") -> #N/A | I646: =_xlfn.XLOOKUP(A646,'2024'!B:B,'2024'!AZ:AZ,"") -> #N/A | J646: =_xlfn.XLOOKUP(A646,'2025'!A:A,'2025'!C:C,"") -> #N/A | K646: =_xlfn.XLOOKUP(A646,'2025'!A:A,'2025'!F:F,"") -> #N/A
A647: #N/A | B647: =_xlfn.XLOOKUP(A647,'2021'!A:A,'2021'!X:X,"") -> #N/A | C647: =_xlfn.XLOOKUP(A647,'2021'!A:A,'2021'!V:V,"") -> #N/A | D647: =_xlfn.XLOOKUP(A647,'2022'!A:A,'2022'!X:X,"") -> #N/A | E647: =_xlfn.XLOOKUP(A647,'2022'!A:A,'2022'!W:W,"") -> #N/A | F647: =_xlfn.XLOOKUP(A647,'2023'!B:B,'2023'!AF:AF,"") -> #N/A | G647: =_xlfn.XLOOKUP(A647,'2023'!B:B,'2023'!AE:AE,"") -> #N/A | H647: =_xlfn.XLOOKUP(A647,'2024'!B:B,'2024'!BW:BW,"") -> #N/A | I647: =_xlfn.XLOOKUP(A647,'2024'!B:B,'2024'!AZ:AZ,"") -> #N/A | J647: =_xlfn.XLOOKUP(A647,'2025'!A:A,'2025'!C:C,"") -> #N/A | K647: =_xlfn.XLOOKUP(A647,'2025'!A:A,'2025'!F:F,"") -> #N/A
A648: #N/A | B648: =_xlfn.XLOOKUP(A648,'2021'!A:A,'2021'!X:X,"") -> #N/A | C648: =_xlfn.XLOOKUP(A648,'2021'!A:A,'2021'!V:V,"") -> #N/A | D648: =_xlfn.XLOOKUP(A648,'2022'!A:A,'2022'!X:X,"") -> #N/A | E648: =_xlfn.XLOOKUP(A648,'2022'!A:A,'2022'!W:W,"") -> #N/A | F648: =_xlfn.XLOOKUP(A648,'2023'!B:B,'2023'!AF:AF,"") -> #N/A | G648: =_xlfn.XLOOKUP(A648,'2023'!B:B,'2023'!AE:AE,"") -> #N/A | H648: =_xlfn.XLOOKUP(A648,'2024'!B:B,'2024'!BW:BW,"") -> #N/A | I648: =_xlfn.XLOOKUP(A648,'2024'!B:B,'2024'!AZ:AZ,"") -> #N/A | J648: =_xlfn.XLOOKUP(A648,'2025'!A:A,'2025'!C:C,"") -> #N/A | K648: =_xlfn.XLOOKUP(A648,'2025'!A:A,'2025'!F:F,"") -> #N/A
A649: #N/A | B649: =_xlfn.XLOOKUP(A649,'2021'!A:A,'2021'!X:X,"") -> #N/A | C649: =_xlfn.XLOOKUP(A649,'2021'!A:A,'2021'!V:V,"") -> #N/A | D649: =_xlfn.XLOOKUP(A649,'2022'!A:A,'2022'!X:X,"") -> #N/A | E649: =_xlfn.XLOOKUP(A649,'2022'!A:A,'2022'!W:W,"") -> #N/A | F649: =_xlfn.XLOOKUP(A649,'2023'!B:B,'2023'!AF:AF,"") -> #N/A | G649: =_xlfn.XLOOKUP(A649,'2023'!B:B,'2023'!AE:AE,"") -> #N/A | H649: =_xlfn.XLOOKUP(A649,'2024'!B:B,'2024'!BW:BW,"") -> #N/A | I649: =_xlfn.XLOOKUP(A649,'2024'!B:B,'2024'!AZ:AZ,"") -> #N/A | J649: =_xlfn.XLOOKUP(A649,'2025'!A:A,'2025'!C:C,"") -> #N/A | K649: =_xlfn.XLOOKUP(A649,'2025'!A:A,'2025'!F:F,"") -> #N/A
A650: #N/A | B650: =_xlfn.XLOOKUP(A650,'2021'!A:A,'2021'!X:X,"") -> #N/A | C650: =_xlfn.XLOOKUP(A650,'2021'!A:A,'2021'!V:V,"") -> #N/A | D650: =_xlfn.XLOOKUP(A650,'2022'!A:A,'2022'!X:X,"") -> #N/A | E650: =_xlfn.XLOOKUP(A650,'2022'!A:A,'2022'!W:W,"") -> #N/A | F650: =_xlfn.XLOOKUP(A650,'2023'!B:B,'2023'!AF:AF,"") -> #N/A | G650: =_xlfn.XLOOKUP(A650,'2023'!B:B,'2023'!AE:AE,"") -> #N/A | H650: =_xlfn.XLOOKUP(A650,'2024'!B:B,'2024'!BW:BW,"") -> #N/A | I650: =_xlfn.XLOOKUP(A650,'2024'!B:B,'2024'!AZ:AZ,"") -> #N/A | J650: =_xlfn.XLOOKUP(A650,'2025'!A:A,'2025'!C:C,"") -> #N/A | K650: =_xlfn.XLOOKUP(A650,'2025'!A:A,'2025'!F:F,"") -> #N/A
... A664: #N/A | B664: =_xlfn.XLOOKUP(A664,'2021'!A:A,'2021'!X:X,"") -> #N/A | C664: =_xlfn.XLOOKUP(A664,'2021'!A:A,'2021'!V:V,"") -> #N/A | D664: =_xlfn.XLOOKUP(A664,'2022'!A:A,'2022'!X:X,"") -> #N/A | E664: =_xlfn.XLOOKUP(A664,'2022'!A:A,'2022'!W:W,"") -> #N/A | F664: =_xlfn.XLOOKUP(A664,'2023'!B:B,'2023'!AF:AF,"") -> #N/A | G664: =_xlfn.XLOOKUP(A664,'2023'!B:B,'2023'!AE:AE,"") -> #N/A | H664: =_xlfn.XLOOKUP(A664,'2024'!B:B,'2024'!BW:BW,"") -> #N/A | I664: =_xlfn.XLOOKUP(A664,'2024'!B:B,'2024'!AZ:AZ,"") -> #N/A | J664: =_xlfn.XLOOKUP(A664,'2025'!A:A,'2025'!C:C,"") -> #N/A | K664: =_xlfn.XLOOKUP(A664,'2025'!A:A,'2025'!F:F,"") -> #N/A

Sheet 2025
A2: Company name | B2: All RE | C2: All SBTi ST | D2: gov cn | E2: CN | F2: NZ | G2: Carbon Credits (Y) | H2: Carbon Credits (No) | I2: at least one of the actions
A3: Walmart | B3: 1 | C3: 1 | D3: 0 | E3: 0 | F3: 1 | G3: 0 | H3: 1 | I3: =IF(OR(F3=1,G3=1,C3=1),"1","") -> 1
A4: Amazon | B4: 0 | C4: 0 | D4: 0 | E4: 0 | F4: 1 | G4: 1 | H4: 0 | I4: =IF(OR(F4=1,G4=1,C4=1),"1","") -> 1
A5: State Grid | B5: 0 | C5: 0 | D5: 1 | E5: 0 | F5: 0 | G5: 0 | H5: 0 | I5: =IF(OR(F5=1,G5=1,C5=1),"1","")
A6: Saudi Aramco | B6: 0 | C6: 0 | D6: 0 | E6: 0 | F6: 1 | G6: 1 | H6: 0 | I6: =IF(OR(F6=1,G6=1,C6=1),"1","") -> 1
A7: China National Petroleum | B7: 0 | C7: 0 | D7: 1 | E7: 0 | F7: 1 | G7: 0 | H7: 0 | I7: =IF(OR(F7=1,G7=1,C7=1),"1","") -> 1
A8: Sinopec Group | B8: 0 | C8: 0 | D8: 0 | E8: 1 | F8: 0 | G8: 1 | H8: 0 | I8: =IF(OR(F8=1,G8=1,C8=1),"1","") -> 1
A9: UnitedHealth Group | B9: 0 | C9: 1 | D9: 0 | E9: 0 | F9: 1 | G9: 0 | H9: 0 | I9: =IF(OR(F9=1,G9=1,C9=1),"1","") -> 1
A10: Apple | B10: 1 | C10: 1 | D10: 0 | E10: 1 | F10: 0 | G10: 1 | H10: 0 | I10: =IF(OR(F10=1,G10=1,C10=1),"1","") -> 1
A11: CVS Health | B11: 0 | C11: 1 | D11: 0 | E11: 0 | F11: 1 | G11: 1 | H11: 0 | I11: =IF(OR(F11=1,G11=1,C11=1),"1","") -> 1
A12: Berkshire Hathaway | B12: 0 | C12: 0 | D12: 0 | E12: 0 | F12: 0 | G12: 0 | H12: 0 | I12: =IF(OR(F12=1,G12=1,C12=1),"1","")
A13: McKesson | B13: 0 | C13: 1 | D13: 0 | E13: 0 | F13: 0 | G13: 0 | H13: 0 | I13: =IF(OR(F13=1,G13=1,C13=1),"1","") -> 1
A14: Volkswagen | B14: 0 | C14: 1 | D14: 0 | E14: 1 | F14: 0 | G14: 1 | H14: 0 | I14: =IF(OR(F14=1,G14=1,C14=1),"1","") -> 1
... A502: Heineken | B502: 1 | C502: 1 | D502: 0 | E502: 0 | F502: 1 | G502: 1 | H502: 0 | I502: =IF(OR(F502=1,G502=1,C502=1),"1","") -> 1
B503: 78 | C503: 157 | D503: 56 | E503: 91 | F503: 253 | G503: 222 | H503: 17 | I503: =SUM(I3:I502) -> 0
B504: 0.16 | C504: 0.31 | D504: 0.11 | E504: 0.18 | F504: 0.51 | G504: 0.44 | H504: 0.03 | I504: =COUNTIF(I3:I502,1) -> 332
B505: 18 | C505: 29 | D505: 54 | E505: 49 | F505: 62 | G505: 52 | H505: 4 | I505: =IF(OR(F505=1,G505=1,C505=1),"1","")
B506: 34 | C506: 68 | D506: 1 | E506: 24 | F506: 95 | G506: 82 | H506: 6 | I506: =IF(OR(F506=1,G506=1,C506=1),"1","")
B507: 22 | C507: 59 | D507: 0 | E507: 18 | F507: 82 | G507: 73 | H507: 7 | I507: =IF(OR(F507=1,G507=1,C507=1),"1","")
B508: 4 | C508: 1 | D508: 1 | E508: 0 | F508: 14 | G508: 15 | H508: 0 | I508: =IF(OR(F508=1,G508=1,C508=1),"1","") -> 1
B509: 78 | C509: 157 | D509: 56 | E509: 91 | F509: 253 | G509: 222 | H509: 17 | I509: =IF(OR(F509=1,G509=1,C509=1),"1","")
B510: 0 | C510: 2 | D510: 0 | E510: 1 | F510: 3 | G510: 4 | H510: 0 | I510: =IF(OR(F510=1,G510=1,C510=1),"1","")
B511: 7 | C511: 14 | D511: 1 | E511: 24 | F511: 6 | G511: 14 | H511: 0 | I511: =IF(OR(F511=1,G511=1,C511=1),"1","")
B512: 0 | C512: 2 | D512: 2 | E512: 2 | F512: 4 | G512: 3 | H512: 0 | I512: =IF(OR(F512=1,G512=1,C512=1),"1","")
B513: 1 | C513: 8 | D513: 5 | E513: 9 | F513: 10 | G513: 12 | H513: 2 | I513: =IF(OR(F513=1,G513=1,C513=1),"1","")
B514: 0 | C514: 5 | D514: 3 | E514: 2 | F514: 7 | G514: 5 | H514: 1 | I514: =IF(OR(F514=1,G514=1,C514=1),"1","")
B515: 22 | C515: 9 | D515: 17 | E515: 18 | F515: 72 | G515: 71 | H515: 5 | I515: =IF(OR(F515=1,G515=1,C515=1),"1","")
B516: 5 | C516: 14 | D516: 0 | E516: 2 | F516: 12 | G516: 5 | H516: 2 | I516: =IF(OR(F516=1,G516=1,C516=1),"1","")
... B526: 1 | C526: 12 | D526: 3 | E526: 3 | F526: 11 | G526: 11 | H526: 2 | I526: =IF(OR(F526=1,G526=1,C526=1),"1","")
B527: 78 | C527: 157 | D527: 56 | E527: 91 | F527: 253 | G527: 222 | H527: 17
I528: =IF(OR(F528=1,G528=1,C528=1),"1","")
I529: =IF(OR(F529=1,G529=1,C529=1),"1","")
I530: =IF(OR(F530=1,G530=1,C530=1),"1","")
I531: =IF(OR(F531=1,G531=1,C531=1),"1","")
I532: =IF(OR(F532=1,G532=1,C532=1),"1","")
I533: =IF(OR(F533=1,G533=1,C533=1),"1","")
I534: =IF(OR(F534=1,G534=1,C534=1),"1","")
I535: =IF(OR(F535=1,G535=1,C535=1),"1","")

Sheet 2024
A2: Rank | B2: Company Name | C2: Sector (final classification) | D2: Country | E2: Region | F2: RE100 (Y/N) | G2: Joining year | H2: Target year | I2: SBT (Y = yes, N=no) | J2: Target status - NT | K2: Target classification NT - temp | L2: Target year NT (earlier of the two dates if there were two) - if committed, then year set to 2030 | M2: Net zero committed (SBTi) | N2: SBTi NZ approved year | O2: Commitment date (SBTi) | P2: Commitment year (SBTi) | Q2: Carbon neutral commitment (C = company, V = value chain, G= Government, S = subsidiary, U = unspecified, x = less than 50% of rev, N=no) | R2: Carbon neutral scope(s) (in their words) (+ indicates two targets/ a later target) | S2: Carbon neutral claim (in their words) | T2: Carbon neutral commitment - EARLY | U2: Earlier carbon neutral target year | V2: Earlier carbon neutral announcement year | W2: Carbon neutral commitment - LATE | X2: Later carbon neutral target year | Y2: Later carbon neutral announcement year | Z2: Carbon credits (Y = yes, N = no, R = removals only, U = unclear) | AA2: Souce Date | AB2: Source Target Mention (Y or N) | AC2: Net zero commitment (V = value chain, C = company, S = subsidiary, U = unclear, x = less than 50% rev) | AD2: Primary net zero scope (in their words) | AE2: Primary net zero claim (in their words) | AF2: Net Zero Target - EARLY | AG2: Earlier net zero target year | AH2: Earlier net zero announcement year | AI2: Net Zero Target - LATE | AJ2: Later net zero target year | AK2: Later net zero announcement year | AL2: Carbon credits (Y = yes, N = no, R = removals only, U = unclear).1 | AM2: Souce Date.1 | AN2: Source Target Mention (Y or N).1 | AO2: Reduction targets for Decarbonization (V = value chain, C = company) | AP2: Using Carbon Credits without target (Y=yes, N=No) | AQ2: CN already achieved | AR2: CN 2024-2030 | AS2: CN 2031-2050 | AT2: all CN | AU2: Any CN | AV2: CN | AW2: NZ already achieved | AX2: NZ 2024-2030 | AY2: NZ 2031-2050 | AZ2: NZ | BA2: SBT already achieved | BB2: SBT 2024-2030 | BC2: SBT 2031-2050 | BD2: Any SBT | BE2: RE100 already achieved | BF2: RE100 2024-2030 | BG2: RE100 2031-2050 | BH2: Any RE100 | BI2: CN/NZ - does the company have a voluntary CN or NZ target? | BJ2: CN/NZ by 2030 | BK2: CN/NZ by 2050 | BL2: will use cabon credits | BM2: will NOT use carbon credits | BN2: any commitment | BO2: any commitment already achieved | BP2: any commitment by 2030 | BQ2: any commitment from 2030 | BR2: NZ covering VC already achieved | BS2: NZ covering VC 2024-2030 | BT2: NZ covering VC 2031-2050 | BU2: Any NZ covering VC | BV2: NZ year | BW2: sbti nt | BX2: actions already due | BY2: actions due by 2030 | BZ2: actions due from 2030 | CA2: all actions
A3: 489 | B3: 3M | C3: Chemicals | D3: United States of America (USA) | E3: North America | F3: Y | G3: 2019 | H3: 2050 | I3: N | J3: Committed | L3: 2030 | M3: No | O3: 45231 | P3: 2023 | Q3: C | R3: operations | S3: carbon neutral | T3: C | U3: 2050 | V3: 2021 | Z3: Y | AB3: Y | AC3: N | AF3: N | AS3: 1 | AT3: 1 | AU3: 1 | AV3: =IF(AND(Q3<>"N",Q3<>"G",AZ3<>1),1,"") -> 1 | BB3: 1 | BD3: 1 | BG3: 1 | BH3: 1 | BI3: 1 | BK3: 1 | BL3: 1 | BN3: =MAX(BH3,BD3,AZ3,AV3) -> 1 | BP3: 1 | BQ3: 1 | BW3: =IF(J3="Targets Set",1,"")
A4: 498 | B4: ABB | C4: Industrial goods | D4: Switzerland | E4: Europe | F4: Y | G4: 2021 | H4: 2030 | I4: Y | J4: Targets Set | K4: 1.5°C | L4: 2030 | M4: Yes | N4: 2050 | O4: 01/05/2021 | P4: 2021 | Q4: N | T4: N | AC4: V | AD4: SBTi approved so value chain | AE4: Net Zero | AF4: V | AG4: 2050 | AH4: 2021 | AL4: R | AM4: 2023 | AN4: Y | AV4: =IF(AND(Q4<>"N",Q4<>"G",AZ4<>1),1,"") | AY4: 1 | AZ4: 1 | BB4: 1 | BD4: 1 | BF4: 1 | BH4: 1 | BI4: 1 | BK4: 1 | BL4: 1 | BN4: =MAX(BH4,BD4,AZ4,AV4) -> 1 | BP4: 1 | BQ4: 1 | BT4: 1 | BU4: 1 | BV4: =MAX(N4,AG4) -> 2050 | BW4: =IF(J4="Targets Set",1,"") -> 1 | CE4: SBTi short term | CH4: RE100 | CK4: Carbon Neutral | CO4: Overlap (CN to be removed) | CQ4: Net Zero | CT4: sum
A5: 376 | B5: Abbott Laboratories | C5: Health care and pharmaceuticals | D5: United States of America (USA) | E5: North America | F5: N | I5: Y | J5: Targets Set | K5: Well-below 2Â°C | L5: 2030 | M5: No | O5: 44805 | P5: 2022 | Q5: N | T5: N | AC5: N | AF5: N | AO5: C | AV5: =IF(AND(Q5<>"N",Q5<>"G",AZ5<>1),1,"") | BB5: 1 | BD5: 1 | BN5: =MAX(BH5,BD5,AZ5,AV5) -> 1 | BP5: 1 | BQ5: 1 | BW5: =IF(J5="Targets Set",1,"") -> 1 | CD5: Sector | CE5: <=2024 | CF5: 2025-2030 | CG5: 2031-2060 | CH5: <=2024 | CI5: 2025-2030 | CJ5: 2031-2060 | CK5: <=2024 | CL5: 2025-2030 | CM5: 2031-2060 | CN5: <=2024 | CO5: 2025-2030 | CP5: 2031-2060 | CQ5: <=2024 | CR5: 2025-2030 | CS5: 2031-2060 | CT5: no overlap | CU5: Yes | CV5: No | CW5: Unspecified
A6: 259 | B6: AbbVie | C6: Health care and pharmaceuticals | D6: United States of America (USA) | E6: North America | F6: N | I6: Y | J6: Targets Set | K6: 1.5Â°C | L6: 2030 | M6: No | O6: 45017 | P6: 2023 | Q6: N | T6: N | AC6: C | AD6: Scope 1 and 2 | AE6: Net Zero | AF6: C | AG6: 2050 | AH6: 2021 | AL6: Y | AV6: =IF(AND(Q6<>"N",Q6<>"G",AZ6<>1),1,"") | AY6: 1 | AZ6: 1 | BB6: 1 | BD6: 1 | BI6: 1 | BK6: 1 | BL6: 1 | BN6: =MAX(BH6,BD6,AZ6,AV6) -> 1 | BP6: 1 | BQ6: 1 | BV6: =MAX(N6,AG6) -> 2050 | BW6: =IF(J6="Targets Set",1,"") -> 1 | CD6: Aerospace and defense | CE6: =COUNTIFS(C:C,CD6,L:L,"<=2024",J:J, "Targets Set") -> 0 | CF6: =COUNTIFS(C:C,CD6,L:L,">=2025",L:L,"<=2030", J:J, "Targets Set") -> 1 | CG6: =COUNTIFS(C:C,CD6,L:L,">2030",J:J, "Targets Set") -> 0 | CH6: =COUNTIFS($C$3:$C$502,CD6,$H$3:$H$502,"<=2024") -> 0 | CI6: =COUNTIFS($C$3:$C$502,CD6,$H$3:$H$502,">=2025",$H$3:$H$502,"<=2030") -> 0 | CJ6: =COUNTIFS($C$3:$C$502,CD6,$H$6:$H$505,">2030") -> 0 | CK6: =COUNTIFS(C:C, CD6, U:U,"<=2024", T:T, "<>G") -> 1 | CL6: =COUNTIFS(C:C,CD6,U:U,">=2024",U:U,"<=2030",T:T, "<>G") -> 0 | CM6: =COUNTIFS(C:C,CD6,U:U,">2030", T:T, "<>G") -> 1 | CN6: =COUNTIFS(C:C, CD6, AZ:AZ, "1", U:U, "<=2024", T:T, "<>N",T:T, "<>G") -> 0 | CO6: =COUNTIFS(C:C, CD6, AZ:AZ, "1", U:U, ">2024", U:U, "<=2030", T:T, "<>N",T:T, "<>G") -> 0 | CP6: =COUNTIFS(C:C, CD6, AZ:AZ, "1",U:U, ">2030", T:T, "<>N", T:T, "<>G") -> 0 | CQ6: =COUNTIFS($C$3:$C$502,CD6,$BV$3:$BV$502,"<=2024") -> 0 | CR6: =COUNTIFS($C$3:$C$502,CD6,$BV$3:$BV$502,">=2025",$BV$3:$BV$502,"<=2030") -> 0 | CS6: =COUNTIFS($C$3:$C$502,CD6,$BV$3:$BV$502,">2030") -> 4 | CT6: =SUM(CE6:CM6)-SUM(CN6:CP6)+SUM(CQ6:CS6) -> 7 | CU6: =COUNTIFS($C$3:$C$502, CD6, $BL$3:$BL$502, "1") -> 4 | CV6: =COUNTIFS($C$3:$C$502, CD6, $BM$3:$BM$502, "1") -> 0 | CW6: =COUNTIF($C$3:$C$502, CD6)-CV6-CU6 -> 6
A7: 211 | B7: Accenture | C7: Financial services | D7: Ireland | E7: Europe | F7: Y | G7: 2019 | H7: 2023 | I7: Y | J7: Targets Set | K7: 1.5Â°C | L7: 2030 | M7: Yes | N7: 2040 | O7: 45444 | P7: 2024 | Q7: N | T7: N | AC7: V | AD7: Scope 1, 2 and 3 | AE7: Net Zero | AF7: V | AG7: 2040 | AH7: 2020 | AL7: Y | AV7: =IF(AND(Q7<>"N",Q7<>"G",AZ7<>1),1,"") | AY7: 1 | AZ7: 1 | BB7: 1 | BD7: 1 | BE7: 1 | BH7: 1 | BI7: 1 | BJ7: 1 | BK7: 1 | BL7: 1 | BN7: =MAX(BH7,BD7,AZ7,AV7) -> 1 | BO7: 1 | BP7: 1 | BQ7: 1 | BT7: 1 | BU7: 1 | BV7: =MAX(N7,AG7) -> 2040 | BW7: =IF(J7="Targets Set",1,"") -> 1 | CD7: Automotive | CE7: =COUNTIFS(C:C,CD7,L:L,"<=2024",J:J, "Targets Set") -> 0 | CF7: =COUNTIFS(C:C,CD7,L:L,">=2025",L:L,"<=2030", J:J, "Targets Set") -> 12 | CG7: =COUNTIFS(C:C,CD7,L:L,">2030",J:J, "Targets Set") -> 3 | CH7: =COUNTIFS($C$3:$C$502,CD7,$H$3:$H$502,"<=2024") -> 0 | CI7: =COUNTIFS($C$3:$C$502,CD7,$H$3:$H$502,">=2025",$H$3:$H$502,"<=2030") -> 1 | CJ7: =COUNTIFS($C$3:$C$502,CD7,$H$6:$H$505,">2030") -> 2 | CK7: =COUNTIFS(C:C, CD7, U:U,"<=2024", T:T, "<>G") -> 2 | CL7: =COUNTIFS(C:C,CD7,U:U,">=2024",U:U,"<=2030",T:T, "<>G") -> 3 | CM7: =COUNTIFS(C:C,CD7,U:U,">2030", T:T, "<>G") -> 17 | CN7: =COUNTIFS(C:C, CD7, AZ:AZ, "1", U:U, "<=2024", T:T, "<>N",T:T, "<>G") -> 0 | CO7: =COUNTIFS(C:C, CD7, AZ:AZ, "1", U:U, ">2024", U:U, "<=2030", T:T, "<>N",T:T, "<>G") -> 0 | CP7: =COUNTIFS(C:C, CD7, AZ:AZ, "1",U:U, ">2030", T:T, "<>N", T:T, "<>G") -> 1 | CQ7: =COUNTIFS($C$3:$C$502,CD7,$BV$3:$BV$502,"<=2024") -> 0 | CR7: =COUNTIFS($C$3:$C$502,CD7,$BV$3:$BV$502,">=2025",$BV$3:$BV$502,"<=2030") -> 0 | CS7: =COUNTIFS($C$3:$C$502,CD7,$BV$3:$BV$502,">2030") -> 7 | CT7: =SUM(CE7:CM7)-SUM(CN7:CP7)+SUM(CQ7:CS7) -> 46 | CU7: =COUNTIFS($C$3:$C$502, CD7, $BL$3:$BL$502, "1") -> 17 | CV7: =COUNTIFS($C$3:$C$502, CD7, $BM$3:$BM$502, "1") -> 0 | CW7: =COUNTIF($C$3:$C$502, CD7)-CV7-CU7 -> 20
A8: 391 | B8: ACS | C8: Engineering and construction | D8: Spain | E8: Europe | F8: N | I8: N | Q8: C | R8: scope 1 and 2 emissions | S8: climate neutral | T8: C | U8: 2045 | V8: 2021 | Z8: U | AA8: 2024 | AB8: Y | AC8: N | AF8: N | AS8: 1 | AT8: 1 | AU8: 1 | AV8: =IF(AND(Q8<>"N",Q8<>"G",AZ8<>1),1,"") -> 1 | BI8: 1 | BK8: 1 | BN8: =MAX(BH8,BD8,AZ8,AV8) -> 1 | BQ8: 1 | BW8: =IF(J8="Targets Set",1,"") | CD8: Chemicals | CE8: =COUNTIFS(C:C,CD8,L:L,"<=2024",J:J, "Targets Set") -> 0 | CF8: =COUNTIFS(C:C,CD8,L:L,">=2025",L:L,"<=2030", J:J, "Targets Set") -> 0 | CG8: =COUNTIFS(C:C,CD8,L:L,">2030",J:J, "Targets Set") -> 1 | CH8: =COUNTIFS($C$3:$C$502,CD8,$H$3:$H$502,"<=2024") -> 0 | CI8: =COUNTIFS($C$3:$C$502,CD8,$H$3:$H$502,">=2025",$H$3:$H$502,"<=2030") -> 0 | CJ8: =COUNTIFS($C$3:$C$502,CD8,$H$6:$H$505,">2030") -> 0 | CK8: =COUNTIFS(C:C, CD8, U:U,"<=2024", T:T, "<>G") -> 0 | CL8: =COUNTIFS(C:C,CD8,U:U,">=2024",U:U,"<=2030",T:T, "<>G") -> 1 | CM8: =COUNTIFS(C:C,CD8,U:U,">2030", T:T, "<>G") -> 3 | CN8: =COUNTIFS(C:C, CD8, AZ:AZ, "1", U:U, "<=2024", T:T, "<>N",T:T, "<>G") -> 0 | CO8: =COUNTIFS(C:C, CD8, AZ:AZ, "1", U:U, ">2024", U:U, "<=2030", T:T, "<>N",T:T, "<>G") -> 1 | CP8: =COUNTIFS(C:C, CD8, AZ:AZ, "1",U:U, ">2030", T:T, "<>N", T:T, "<>G") -> 0 | CQ8: =COUNTIFS($C$3:$C$502,CD8,$BV$3:$BV$502,"<=2024") -> 0 | CR8: =COUNTIFS($C$3:$C$502,CD8,$BV$3:$BV$502,">=2025",$BV$3:$BV$502,"<=2030") -> 0 | CS8: =COUNTIFS($C$3:$C$502,CD8,$BV$3:$BV$502,">2030") -> 3 | CT8: =SUM(CE8:CM8)-SUM(CN8:CP8)+SUM(CQ8:CS8) -> 7 | CU8: =COUNTIFS($C$3:$C$502, CD8, $BL$3:$BL$502, "1") -> 5 | CV8: =COUNTIFS($C$3:$C$502, CD8, $BM$3:$BM$502, "1") -> 0 | CW8: =COUNTIF($C$3:$C$502, CD8)-CV8-CU8 -> 5
A9: 203 | B9: AEON | C9: Retail | D9: Japan | E9: Asia | F9: Y | G9: 2018 | H9: 2030 | I9: Y | J9: Targets Set | K9: 1.5Â°C | L9: 2030 | M9: Yes | O9: 44409 | P9: 2021 | Q9: N | T9: N | AC9: C | AD9: our stores | AE9: Net Zero | AF9: C | AG9: 2040 | AH9: 2021 | AL9: Y | AM9: 2023 | AN9: Y | AV9: =IF(AND(Q9<>"N",Q9<>"G",AZ9<>1),1,"") | AY9: 1 | AZ9: 1 | BB9: 1 | BD9: 1 | BF9: 1 | BH9: 1 | BI9: 1 | BK9: 1 | BL9: 1 | BN9: =MAX(BH9,BD9,AZ9,AV9) -> 1 | BP9: 1 | BQ9: 1 | BV9: =MAX(N9,AG9) -> 2040 | BW9: =IF(J9="Targets Set",1,"") -> 1 | CD9: Energy and utilities | CE9: =COUNTIFS(C:C,CD9,L:L,"<=2024",J:J, "Targets Set") -> 1 | CF9: =COUNTIFS(C:C,CD9,L:L,">=2025",L:L,"<=2030", J:J, "Targets Set") -> 5 | CG9: =COUNTIFS(C:C,CD9,L:L,">2030",J:J, "Targets Set") -> 2 | CH9: =COUNTIFS($C$3:$C$502,CD9,$H$3:$H$502,"<=2024") -> 0 | CI9: =COUNTIFS($C$3:$C$502,CD9,$H$3:$H$502,">=2025",$H$3:$H$502,"<=2030") -> 0 | CJ9: =COUNTIFS($C$3:$C$502,CD9,$H$6:$H$505,">2030") -> 0 | CK9: =COUNTIFS(C:C, CD9, U:U,"<=2024", T:T, "<>G") -> 1 | CL9: =COUNTIFS(C:C,CD9,U:U,">=2024",U:U,"<=2030",T:T, "<>G") -> 2 | CM9: =COUNTIFS(C:C,CD9,U:U,">2030", T:T, "<>G") -> 5 | CN9: =COUNTIFS(C:C, CD9, AZ:AZ, "1", U:U, "<=2024", T:T, "<>N",T:T, "<>G") -> 0 | CO9: =COUNTIFS(C:C, CD9, AZ:AZ, "1", U:U, ">2024", U:U, "<=2030", T:T, "<>N",T:T, "<>G") -> 2 | CP9: =COUNTIFS(C:C, CD9, AZ:AZ, "1",U:U, ">2030", T:T, "<>N", T:T, "<>G") -> 1 | CQ9: =COUNTIFS($C$3:$C$502,CD9,$BV$3:$BV$502,"<=2024") -> 0 | CR9: =COUNTIFS($C$3:$C$502,CD9,$BV$3:$BV$502,">=2025",$BV$3:$BV$502,"<=2030") -> 0 | CS9: =COUNTIFS($C$3:$C$502,CD9,$BV$3:$BV$502,">2030") -> 8 | CT9: =SUM(CE9:CM9)-SUM(CN9:CP9)+SUM(CQ9:CS9) -> 21 | CU9: =COUNTIFS($C$3:$C$502, CD9, $BL$3:$BL$502, "1") -> 9 | CV9: =COUNTIFS($C$3:$C$502, CD9, $BM$3:$BM$502, "1") -> 0 | CW9: =COUNTIF($C$3:$C$502, CD9)-CV9-CU9 -> 13
A10: 34 | B10: Agricultural Bank of China | C10: Financial services | D10: China | E10: Asia | F10: N | I10: N | Q10: G | R10: operations | S10: carbon neutrality | T10: G | U10: 2060 | V10: 2023 | AC10: N | AF10: N | AV10: =IF(AND(Q10<>"N",Q10<>"G",AZ10<>1),1,"") | BN10: =MAX(BH10,BD10,AZ10,AV10) -> 0 | BW10: =IF(J10="Targets Set",1,"") | CD10: Engineering and construction | CE10: =COUNTIFS(C:C,CD10,L:L,"<=2024",J:J, "Targets Set") -> 0 | CF10: =COUNTIFS(C:C,CD10,L:L,">=2025",L:L,"<=2030", J:J, "Targets Set") -> 3 | CG10: =COUNTIFS(C:C,CD10,L:L,">2030",J:J, "Targets Set") -> 0 | CH10: =COUNTIFS($C$3:$C$502,CD10,$H$3:$H$502,"<=2024") -> 1 | CI10: =COUNTIFS($C$3:$C$502,CD10,$H$3:$H$502,">=2025",$H$3:$H$502,"<=2030") -> 0 | CJ10: =COUNTIFS($C$3:$C$502,CD10,$H$6:$H$505,">2030") -> 1 | CK10: =COUNTIFS(C:C, CD10, U:U,"<=2024", T:T, "<>G") -> 0 | CL10: =COUNTIFS(C:C,CD10,U:U,">=2024",U:U,"<=2030",T:T, "<>G") -> 0 | CM10: =COUNTIFS(C:C,CD10,U:U,">2030", T:T, "<>G") -> 4 | CN10: =COUNTIFS(C:C, CD10, AZ:AZ, "1", U:U, "<=2024", T:T, "<>N",T:T, "<>G") -> 0 | CO10: =COUNTIFS(C:C, CD10, AZ:AZ, "1", U:U, ">2024", U:U, "<=2030", T:T, "<>N",T:T, "<>G") -> 0 | CP10: =COUNTIFS(C:C, CD10, AZ:AZ, "1",U:U, ">2030", T:T, "<>N", T:T, "<>G") -> 1 | CQ10: =COUNTIFS($C$3:$C$502,CD10,$BV$3:$BV$502,"<=2024") -> 0 | CR10: =COUNTIFS($C$3:$C$502,CD10,$BV$3:$BV$502,">=2025",$BV$3:$BV$502,"<=2030") -> 0 | CS10: =COUNTIFS($C$3:$C$502,CD10,$BV$3:$BV$502,">2030") -> 1 | CT10: =SUM(CE10:CM10)-SUM(CN10:CP10)+SUM(CQ10:CS10) -> 9 | CU10: =COUNTIFS($C$3:$C$502, CD10, $BL$3:$BL$502, "1") -> 1 | CV10: =COUNTIFS($C$3:$C$502, CD10, $BM$3:$BM$502, "1") -> 0 | CW10: =COUNTIF($C$3:$C$502, CD10)-CV10-CU10 -> 17
A11: 446 | B11: AIA Group | C11: Financial services | D11: Hong Kong | E11: Asia | F11: N | I11: Y | J11: Targets Set | K11: 1.5°C | L11: 2030 | M11: No | O11: 01/11/2023 | P11: 2023 | Q11: N | T11: N | AC11: C | AD11: company | AE11: Net Zero | AF11: C | AG11: 2050 | AH11: 2021 | AL11: U | AM11: 2023 | AN11: Y | AV11: =IF(AND(Q11<>"N",Q11<>"G",AZ11<>1),1,"") | AY11: 1 | AZ11: 1 | BB11: 1 | BD11: 1 | BI11: 1 | BK11: 1 | BN11: =MAX(BH11,BD11,AZ11,AV11) -> 1 | BP11: 1 | BQ11: 1 | BV11: =MAX(N11,AG11) -> 2050 | BW11: =IF(J11="Targets Set",1,"") -> 1 | CD11: Financial services | CE11: =COUNTIFS(C:C,CD11,L:L,"<=2024",J:J, "Targets Set") -> 0 | CF11: =COUNTIFS(C:C,CD11,L:L,">=2025",L:L,"<=2030", J:J, "Targets Set") -> 4 | CG11: =COUNTIFS(C:C,CD11,L:L,">2030",J:J, "Targets Set") -> 1 | CH11: =COUNTIFS($C$3:$C$502,CD11,$H$3:$H$502,"<=2024") -> 11 | CI11: =COUNTIFS($C$3:$C$502,CD11,$H$3:$H$502,">=2025",$H$3:$H$502,"<=2030") -> 9 | CJ11: =COUNTIFS($C$3:$C$502,CD11,$H$6:$H$505,">2030") -> 2 | CK11: =COUNTIFS(C:C, CD11, U:U,"<=2024", T:T, "<>G") -> 29 | CL11: =COUNTIFS(C:C,CD11,U:U,">=2024",U:U,"<=2030",T:T, "<>G") -> 13 | CM11: =COUNTIFS(C:C,CD11,U:U,">2030", T:T, "<>G") -> 12 | CN11: =COUNTIFS(C:C, CD11, AZ:AZ, "1", U:U, "<=2024", T:T, "<>N",T:T, "<>G") -> 26 | CO11: =COUNTIFS(C:C, CD11, AZ:AZ, "1", U:U, ">2024", U:U, "<=2030", T:T, "<>N",T:T, "<>G") -> 6 | CP11: =COUNTIFS(C:C, CD11, AZ:AZ, "1",U:U, ">2030", T:T, "<>N", T:T, "<>G") -> 2 | CQ11: =COUNTIFS($C$3:$C$502,CD11,$BV$3:$BV$502,"<=2024") -> 0 | CR11: =COUNTIFS($C$3:$C$502,CD11,$BV$3:$BV$502,">=2025",$BV$3:$BV$502,"<=2030") -> 15 | CS11: =COUNTIFS($C$3:$C$502,CD11,$BV$3:$BV$502,">2030") -> 52 | CT11: =SUM(CE11:CM11)-SUM(CN11:CP11)+SUM(CQ11:CS11) -> 114 | CU11: =COUNTIFS($C$3:$C$502, CD11, $BL$3:$BL$502, "1") -> 67 | CV11: =COUNTIFS($C$3:$C$502, CD11, $BM$3:$BM$502, "1") -> 2 | CW11: =COUNTIF($C$3:$C$502, CD11)-CV11-CU11 -> 58
A12: 324 | B12: AIG | C12: Financial services | D12: United States of America (USA) | E12: North America | F12: N | I12: N | Q12: N | T12: N | AC12: C+F | AD12: operations and underwriting and investments portfolios | AE12: Net Zero GHG emissions | AF12: C+F | AG12: 2050 | AH12: 2022 | AL12: U | AP12: N | AV12: =IF(AND(Q12<>"N",Q12<>"G",AZ12<>1),1,"") | AY12: 1 | AZ12: 1 | BI12: 1 | BK12: 1 | BN12: =MAX(BH12,BD12,AZ12,AV12) -> 1 | BQ12: 1 | BT12: 1 | BU12: 1 | BV12: =MAX(N12,AG12) -> 2050 | BW12: =IF(J12="Targets Set",1,"") | CD12: Food, beverages and agriculture | CE12: =COUNTIFS(C:C,CD12,L:L,"<=2024",J:J, "Targets Set") -> 0 | CF12: =COUNTIFS(C:C,CD12,L:L,">=2025",L:L,"<=2030", J:J, "Targets Set") -> 12 | CG12: =COUNTIFS(C:C,CD12,L:L,">2030",J:J, "Targets Set") -> 1 | CH12: =COUNTIFS($C$3:$C$502,CD12,$H$3:$H$502,"<=2024") -> 1 | CI12: =COUNTIFS($C$3:$C$502,CD12,$H$3:$H$502,">=2025",$H$3:$H$502,"<=2030") -> 3 | CJ12: =COUNTIFS($C$3:$C$502,CD12,$H$6:$H$505,">2030") -> 2 | CK12: =COUNTIFS(C:C, CD12, U:U,"<=2024", T:T, "<>G") -> 0 | CL12: =COUNTIFS(C:C,CD12,U:U,">=2024",U:U,"<=2030",T:T, "<>G") -> 3 | CM12: =COUNTIFS(C:C,CD12,U:U,">2030", T:T, "<>G") -> 0 | CN12: =COUNTIFS(C:C, CD12, AZ:AZ, "1", U:U, "<=2024", T:T, "<>N",T:T, "<>G") -> 0 | CO12: =COUNTIFS(C:C, CD12, AZ:AZ, "1", U:U, ">2024", U:U, "<=2030", T:T, "<>N",T:T, "<>G") -> 3 | CP12: =COUNTIFS(C:C, CD12, AZ:AZ, "1",U:U, ">2030", T:T, "<>N", T:T, "<>G") -> 0 | CQ12: =COUNTIFS($C$3:$C$502,CD12,$BV$3:$BV$502,"<=2024") -> 0 | CR12: =COUNTIFS($C$3:$C$502,CD12,$BV$3:$BV$502,">=2025",$BV$3:$BV$502,"<=2030") -> 0 | CS12: =COUNTIFS($C$3:$C$502,CD12,$BV$3:$BV$502,">2030") -> 13 | CT12: =SUM(CE12:CM12)-SUM(CN12:CP12)+SUM(CQ12:CS12) -> 32 | CU12: =COUNTIFS($C$3:$C$502, CD12, $BL$3:$BL$502, "1") -> 8 | CV12: =COUNTIFS($C$3:$C$502, CD12, $BM$3:$BM$502, "1") -> 0 | CW12: =COUNTIF($C$3:$C$502, CD12)-CV12-CU12 -> 13
A13: 496 | B13: Air France-KLM Group | C13: Transportation and logistics | D13: France | E13: Europe | F13: N | I13: Y | J13: Targets Set | K13: Well-below 2°C | L13: 2030 | M13: No | O13: 01/01/2023 | P13: 2023 | Q13: N | T13: N | AC13: C | AD13: activities | AE13: Net Zero | AF13: C | AG13: 2050 | AH13: 2021 | AL13: U | AM13: 2022 | AN13: Y | AV13: =IF(AND(Q13<>"N",Q13<>"G",AZ13<>1),1,"") | AY13: 1 | AZ13: 1 | BB13: 1 | BD13: 1 | BI13: 1 | BK13: 1 | BN13: =MAX(BH13,BD13,AZ13,AV13) -> 1 | BP13: 1 | BQ13: 1 | BV13: =MAX(N13,AG13) -> 2050 | BW13: =IF(J13="Targets Set",1,"") -> 1 | CD13: Health care and pharmaceuticals | CE13: =COUNTIFS(C:C,CD13,L:L,"<=2024",J:J, "Targets Set") -> 0 | CF13: =COUNTIFS(C:C,CD13,L:L,">=2025",L:L,"<=2030", J:J, "Targets Set") -> 13 | CG13: =COUNTIFS(C:C,CD13,L:L,">2030",J:J, "Targets Set") -> 1 | CH13: =COUNTIFS($C$3:$C$502,CD13,$H$3:$H$502,"<=2024") -> 1 | CI13: =COUNTIFS($C$3:$C$502,CD13,$H$3:$H$502,">=2025",$H$3:$H$502,"<=2030") -> 8 | CJ13: =COUNTIFS($C$3:$C$502,CD13,$H$6:$H$505,">2030") -> 2 | CK13: =COUNTIFS(C:C, CD13, U:U,"<=2024", T:T, "<>G") -> 1 | CL13: =COUNTIFS(C:C,CD13,U:U,">=2024",U:U,"<=2030",T:T, "<>G") -> 8 | CM13: =COUNTIFS(C:C,CD13,U:U,">2030", T:T, "<>G") -> 1 | CN13: =COUNTIFS(C:C, CD13, AZ:AZ, "1", U:U, "<=2024", T:T, "<>N",T:T, "<>G") -> 1 | CO13: =COUNTIFS(C:C, CD13, AZ:AZ, "1", U:U, ">2024", U:U, "<=2030", T:T, "<>N",T:T, "<>G") -> 6 | CP13: =COUNTIFS(C:C, CD13, AZ:AZ, "1",U:U, ">2030", T:T, "<>N", T:T, "<>G") -> 0 | CQ13: =COUNTIFS($C$3:$C$502,CD13,$BV$3:$BV$502,"<=2024") -> 0 | CR13: =COUNTIFS($C$3:$C$502,CD13,$BV$3:$BV$502,">=2025",$BV$3:$BV$502,"<=2030") -> 1 | CS13: =COUNTIFS($C$3:$C$502,CD13,$BV$3:$BV$502,">2030") -> 14 | CT13: =SUM(CE13:CM13)-SUM(CN13:CP13)+SUM(CQ13:CS13) -> 43 | CU13: =COUNTIFS($C$3:$C$502, CD13, $BL$3:$BL$502, "1") -> 12 | CV13: =COUNTIFS($C$3:$C$502, CD13, $BM$3:$BM$502, "1") -> 1 | CW13: =COUNTIF($C$3:$C$502, CD13)-CV13-CU13 -> 12
A14: 183 | B14: Airbus | C14: Aerospace and defense | D14: Netherlands | E14: Europe | F14: N | I14: Y | J14: Targets Set | K14: 1.5Â°C | L14: 2030 | M14: No | O14: 44958 | P14: 2023 | Q14: N | T14: N | AC14: C | AD14: undefined | AE14: Net Zero | AF14: C | AG14: 2050 | AH14: 2020 | AL14: Y | AV14: =IF(AND(Q14<>"N",Q14<>"G",AZ14<>1),1,"") | AY14: 1 | AZ14: 1 | BB14: 1 | BD14: 1 | BI14: 1 | BK14: 1 | BL14: 1 | BN14: =MAX(BH14,BD14,AZ14,AV14) -> 1 | BP14: 1 | BQ14: 1 | BV14: =MAX(N14,AG14) -> 2050 | BW14: =IF(J14="Targets Set",1,"") -> 1 | CD14: Household and personal products | CE14: =COUNTIFS(C:C,CD14,L:L,"<=2024",J:J, "Targets Set") -> 0 | CF14: =COUNTIFS(C:C,CD14,L:L,">=2025",L:L,"<=2030", J:J, "Targets Set") -> 4 | CG14: =COUNTIFS(C:C,CD14,L:L,">2030",J:J, "Targets Set") -> 0 | CH14: =COUNTIFS($C$3:$C$502,CD14,$H$3:$H$502,"<=2024") -> 0 | CI14: =COUNTIFS($C$3:$C$502,CD14,$H$3:$H$502,">=2025",$H$3:$H$502,"<=2030") -> 3 | CJ14: =COUNTIFS($C$3:$C$502,CD14,$H$6:$H$505,">2030") -> 0 | CK14: =COUNTIFS(C:C, CD14, U:U,"<=2024", T:T, "<>G") -> 1 | CL14: =COUNTIFS(C:C,CD14,U:U,">=2024",U:U,"<=2030",T:T, "<>G") -> 1 | CM14: =COUNTIFS(C:C,CD14,U:U,">2030", T:T, "<>G") -> 0 | CN14: =COUNTIFS(C:C, CD14, AZ:AZ, "1", U:U, "<=2024", T:T, "<>N",T:T, "<>G") -> 1 | CO14: =COUNTIFS(C:C, CD14, AZ:AZ, "1", U:U, ">2024", U:U, "<=2030", T:T, "<>N",T:T, "<>G") -> 1 | CP14: =COUNTIFS(C:C, CD14, AZ:AZ, "1",U:U, ">2030", T:T, "<>N", T:T, "<>G") -> 0 | CQ14: =COUNTIFS($C$3:$C$502,CD14,$BV$3:$BV$502,"<=2024") -> 0 | CR14: =COUNTIFS($C$3:$C$502,CD14,$BV$3:$BV$502,">=2025",$BV$3:$BV$502,"<=2030") -> 0 | CS14: =COUNTIFS($C$3:$C$502,CD14,$BV$3:$BV$502,">2030") -> 5 | CT14: =SUM(CE14:CM14)-SUM(CN14:CP14)+SUM(CQ14:CS14) -> 12 | CU14: =COUNTIFS($C$3:$C$502, CD14, $BL$3:$BL$502, "1") -> 2 | CV14: =COUNTIFS($C$3:$C$502, CD14, $BM$3:$BM$502, "1") -> 2 | CW14: =COUNTIF($C$3:$C$502, CD14)-CV14-CU14 -> 3
A15: 462 | B15: Aisin | C15: Automotive | D15: Japan | E15: Asia | F15: N | I15: Y | J15: Targets Set | K15: 1.5Â°C | L15: 2031 | M15: No | O15: 45261 | P15: 2023 | Q15: C | R15: products and production | S15: Carbon Neutrality | T15: C | U15: 2035 | V15: 2021 | Z15: Y | AA15: 2023 | AB15: Y | AC15: N | AF15: N | AS15: 1 | AT15: 1 | AU15: 1 | AV15: =IF(AND(Q15<>"N",Q15<>"G",AZ15<>1),1,"") -> 1 | BC15: 1 | BD15: 1 | BI15: 1 | BK15: 1 | BL15: 1 | BN15: =MAX(BH15,BD15,AZ15,AV15) -> 1 | BQ15: 1 | BW15: =IF(J15="Targets Set",1,"") -> 1 | CD15: Industrial goods | CE15: =COUNTIFS(C:C,CD15,L:L,"<=2024",J:J, "Targets Set") -> 0 | CF15: =COUNTIFS(C:C,CD15,L:L,">=2025",L:L,"<=2030", J:J, "Targets Set") -> 14 | CG15: =COUNTIFS(C:C,CD15,L:L,">2030",J:J, "Targets Set") -> 2 | CH15: =COUNTIFS($C$3:$C$502,CD15,$H$3:$H$502,"<=2024") -> 0 | CI15: =COUNTIFS($C$3:$C$502,CD15,$H$3:$H$502,">=2025",$H$3:$H$502,"<=2030") -> 5 | CJ15: =COUNTIFS($C$3:$C$502,CD15,$H$6:$H$505,">2030") -> 2 | CK15: =COUNTIFS(C:C, CD15, U:U,"<=2024", T:T, "<>G") -> 0 | CL15: =COUNTIFS(C:C,CD15,U:U,">=2024",U:U,"<=2030",T:T, "<>G") -> 5 | CM15: =COUNTIFS(C:C,CD15,U:U,">2030", T:T, "<>G") -> 5 | CN15: =COUNTIFS(C:C, CD15, AZ:AZ, "1", U:U, "<=2024", T:T, "<>N",T:T, "<>G") -> 0 | CO15: =COUNTIFS(C:C, CD15, AZ:AZ, "1", U:U, ">2024", U:U, "<=2030", T:T, "<>N",T:T, "<>G") -> 3 | CP15: =COUNTIFS(C:C, CD15, AZ:AZ, "1",U:U, ">2030", T:T, "<>N", T:T, "<>G") -> 1 | CQ15: =COUNTIFS($C$3:$C$502,CD15,$BV$3:$BV$502,"<=2024") -> 0 | CR15: =COUNTIFS($C$3:$C$502,CD15,$BV$3:$BV$502,">=2025",$BV$3:$BV$502,"<=2030") -> 2 | CS15: =COUNTIFS($C$3:$C$502,CD15,$BV$3:$BV$502,">2030") -> 18 | CT15: =SUM(CE15:CM15)-SUM(CN15:CP15)+SUM(CQ15:CS15) -> 49 | CU15: =COUNTIFS($C$3:$C$502, CD15, $BL$3:$BL$502, "1") -> 13 | CV15: =COUNTIFS($C$3:$C$502, CD15, $BM$3:$BM$502, "1") -> 0 | CW15: =COUNTIF($C$3:$C$502, CD15)-CV15-CU15 -> 21
A16: 152 | B16: Albertsons | C16: Retail | D16: United States of America (USA) | E16: North America | F16: N | I16: Y | J16: Targets Set | K16: 1.5Â°C | L16: 2030 | M16: No | O16: 44652 | P16: 2022 | Q16: N | T16: N | AC16: C | AD16: Scope 1 and 2 | AE16: Net Zero | AF16: C | AG16: 2040 | AH16: 2022 | AL16: Y | AV16: =IF(AND(Q16<>"N",Q16<>"G",AZ16<>1),1,"") | AY16: 1 | AZ16: 1 | BB16: 1 | BD16: 1 | BI16: 1 | BK16: 1 | BL16: 1 | BN16: =MAX(BH16,BD16,AZ16,AV16) -> 1 | BP16: 1 | BQ16: 1 | BV16: =MAX(N16,AG16) -> 2040 | BW16: =IF(J16="Targets Set",1,"") -> 1 | CD16: Metals and mining | CE16: =COUNTIFS(C:C,CD16,L:L,"<=2024",J:J, "Targets Set") -> 0 | CF16: =COUNTIFS(C:C,CD16,L:L,">=2025",L:L,"<=2030", J:J, "Targets Set") -> 1 | CG16: =COUNTIFS(C:C,CD16,L:L,">2030",J:J, "Targets Set") -> 0 | CH16: =COUNTIFS($C$3:$C$502,CD16,$H$3:$H$502,"<=2024") -> 0 | CI16: =COUNTIFS($C$3:$C$502,CD16,$H$3:$H$502,">=2025",$H$3:$H$502,"<=2030") -> 0 | CJ16: =COUNTIFS($C$3:$C$502,CD16,$H$6:$H$505,">2030") -> 1 | CK16: =COUNTIFS(C:C, CD16, U:U,"<=2024", T:T, "<>G") -> 0 | CL16: =COUNTIFS(C:C,CD16,U:U,">=2024",U:U,"<=2030",T:T, "<>G") -> 0 | CM16: =COUNTIFS(C:C,CD16,U:U,">2030", T:T, "<>G") -> 9 | CN16: =COUNTIFS(C:C, CD16, AZ:AZ, "1", U:U, "<=2024", T:T, "<>N",T:T, "<>G") -> 0 | CO16: =COUNTIFS(C:C, CD16, AZ:AZ, "1", U:U, ">2024", U:U, "<=2030", T:T, "<>N",T:T, "<>G") -> 0 | CP16: =COUNTIFS(C:C, CD16, AZ:AZ, "1",U:U, ">2030", T:T, "<>N", T:T, "<>G") -> 1 | CQ16: =COUNTIFS($C$3:$C$502,CD16,$BV$3:$BV$502,"<=2024") -> 0 | CR16: =COUNTIFS($C$3:$C$502,CD16,$BV$3:$BV$502,">=2025",$BV$3:$BV$502,"<=2030") -> 0 | CS16: =COUNTIFS($C$3:$C$502,CD16,$BV$3:$BV$502,">2030") -> 10 | CT16: =SUM(CE16:CM16)-SUM(CN16:CP16)+SUM(CQ16:CS16) -> 20 | CU16: =COUNTIFS($C$3:$C$502, CD16, $BL$3:$BL$502, "1") -> 9 | CV16: =COUNTIFS($C$3:$C$502, CD16, $BM$3:$BM$502, "1") -> 0 | CW16: =COUNTIF($C$3:$C$502, CD16)-CV16-CU16 -> 31
A17: 70 | B17: Alibaba Group Holding | C17: Retail | D17: China | E17: Asia | F17: N | I17: N | J17: Committed | L17: 2030 | M17: Yes | O17: 44531 | P17: 2021 | Q17: C | R17: operations | S17: carbon neutrality | T17: C | U17: 2030 | V17: 2021 | Z17: Y | AA17: 2023 | AB17: Y | AC17: N | AF17: N | AR17: 1 | AT17: 1 | AU17: 1 | AV17: =IF(AND(Q17<>"N",Q17<>"G",AZ17<>1),1,"") -> 1 | BB17: 1 | BD17: 1 | BI17: 1 | BJ17: 1 | BK17: 1 | BL17: 1 | BN17: =MAX(BH17,BD17,AZ17,AV17) -> 1 | BP17: 1 | BQ17: 1 | BW17: =IF(J17="Targets Set",1,"") | CD17: Oil and gas | CE17: =COUNTIFS(C:C,CD17,L:L,"<=2024",J:J, "Targets Set") -> 0 | CF17: =COUNTIFS(C:C,CD17,L:L,">=2025",L:L,"<=2030", J:J, "Targets Set") -> 0 | CG17: =COUNTIFS(C:C,CD17,L:L,">2030",J:J, "Targets Set") -> 0 | CH17: =COUNTIFS($C$3:$C$502,CD17,$H$3:$H$502,"<=2024") -> 0 | CI17: =COUNTIFS($C$3:$C$502,CD17,$H$3:$H$502,">=2025",$H$3:$H$502,"<=2030") -> 0 | CJ17: =COUNTIFS($C$3:$C$502,CD17,$H$6:$H$505,">2030") -> 3 | CK17: =COUNTIFS(C:C, CD17, U:U,"<=2024", T:T, "<>G") -> 0 | CL17: =COUNTIFS(C:C,CD17,U:U,">=2024",U:U,"<=2030",T:T, "<>G") -> 3 | CM17: =COUNTIFS(C:C,CD17,U:U,">2030", T:T, "<>G") -> 9 | CN17: =COUNTIFS(C:C, CD17, AZ:AZ, "1", U:U, "<=2024", T:T, "<>N",T:T, "<>G") -> 0 | CO17: =COUNTIFS(C:C, CD17, AZ:AZ, "1", U:U, ">2024", U:U, "<=2030", T:T, "<>N",T:T, "<>G") -> 1 | CP17: =COUNTIFS(C:C, CD17, AZ:AZ, "1",U:U, ">2030", T:T, "<>N", T:T, "<>G") -> 2 | CQ17: =COUNTIFS($C$3:$C$502,CD17,$BV$3:$BV$502,"<=2024") -> 0 | CR17: =COUNTIFS($C$3:$C$502,CD17,$BV$3:$BV$502,">=2025",$BV$3:$BV$502,"<=2030") -> 0 | CS17: =COUNTIFS($C$3:$C$502,CD17,$BV$3:$BV$502,">2030") -> 20 | CT17: =SUM(CE17:CM17)-SUM(CN17:CP17)+SUM(CQ17:CS17) -> 32 | CU17: =COUNTIFS($C$3:$C$502, CD17, $BL$3:$BL$502, "1") -> 22 | CV17: =COUNTIFS($C$3:$C$502, CD17, $BM$3:$BM$502, "1") -> 0 | CW17: =COUNTIF($C$3:$C$502, CD17)-CV17-CU17 -> 21
A18: 177 | B18: Alimentation Couche-Tard | C18: Retail | D18: Canada | E18: North America | F18: N | I18: N | Q18: C | R18: scope 1 and 2 | S18: carbon neutral | T18: C | U18: 2030 | V18: 2024 | Z18: Y | AA18: 2024 | AB18: Y | AC18: N | AF18: N | AO18: Y | AP18: N | AR18: 1 | AT18: 1 | AU18: 1 | AV18: =IF(AND(Q18<>"N",Q18<>"G",AZ18<>1),1,"") -> 1 | BI18: 1 | BJ18: 1 | BK18: 1 | BL18: 1 | BN18: =MAX(BH18,BD18,AZ18,AV18) -> 1 | BP18: 1 | BQ18: 1 | BW18: =IF(J18="Targets Set",1,"") | CD18: Real estate | CE18: =COUNTIFS(C:C,CD18,L:L,"<=2024",J:J, "Targets Set") -> 0 | CF18: =COUNTIFS(C:C,CD18,L:L,">=2025",L:L,"<=2030", J:J, "Targets Set") -> 0 | CG18: =COUNTIFS(C:C,CD18,L:L,">2030",J:J, "Targets Set") -> 0 | CH18: =COUNTIFS($C$3:$C$502,CD18,$H$3:$H$502,"<=2024") -> 0 | CI18: =COUNTIFS($C$3:$C$502,CD18,$H$3:$H$502,">=2025",$H$3:$H$502,"<=2030") -> 0 | CJ18: =COUNTIFS($C$3:$C$502,CD18,$H$6:$H$505,">2030") -> 0 | CK18: =COUNTIFS(C:C, CD18, U:U,"<=2024", T:T, "<>G") -> 0 | CL18: =COUNTIFS(C:C,CD18,U:U,">=2024",U:U,"<=2030",T:T, "<>G") -> 0 | CM18: =COUNTIFS(C:C,CD18,U:U,">2030", T:T, "<>G") -> 0 | CN18: =COUNTIFS(C:C, CD18, AZ:AZ, "1", U:U, "<=2024", T:T, "<>N",T:T, "<>G") -> 0 | CO18: =COUNTIFS(C:C, CD18, AZ:AZ, "1", U:U, ">2024", U:U, "<=2030", T:T, "<>N",T:T, "<>G") -> 0 | CP18: =COUNTIFS(C:C, CD18, AZ:AZ, "1",U:U, ">2030", T:T, "<>N", T:T, "<>G") -> 0 | CQ18: =COUNTIFS($C$3:$C$502,CD18,$BV$3:$BV$502,"<=2024") -> 0 | CR18: =COUNTIFS($C$3:$C$502,CD18,$BV$3:$BV$502,">=2025",$BV$3:$BV$502,"<=2030") -> 0 | CS18: =COUNTIFS($C$3:$C$502,CD18,$BV$3:$BV$502,">2030") -> 0 | CT18: =SUM(CE18:CM18)-SUM(CN18:CP18)+SUM(CQ18:CS18) -> 0 | CU18: =COUNTIFS($C$3:$C$502, CD18, $BL$3:$BL$502, "1") -> 0 | CV18: =COUNTIFS($C$3:$C$502, CD18, $BM$3:$BM$502, "1") -> 0 | CW18: =COUNTIF($C$3:$C$502, CD18)-CV18-CU18 -> 3
A19: 82 | B19: Allianz | C19: Financial services | D19: Germany | E19: Europe | F19: Y | G19: 2018 | H19: 2023 | I19: N | Q19: C | R19: operations | S19: carbon neutral | T19: C | U19: 2012 | V19: 2019 | Z19: Y | AA19: 2022 | AB19: Y | AC19: F | AD19: Investment Portfolio | AE19: Net Zero | AF19: F | AG19: 2050 | AH19: 2020 | AL19: R | AQ19: 1 | AT19: 1 | AU19: 1 | AV19: =IF(AND(Q19<>"N",Q19<>"G",AZ19<>1),1,"") | AY19: 1 | AZ19: 1 | BE19: 1 | BH19: 1 | BI19: 1 | BJ19: 1 | BK19: 1 | BL19: 1 | BN19: =MAX(BH19,BD19,AZ19,AV19) -> 1 | BO19: 1 | BP19: 1 | BQ19: 1 | BT19: 1 | BU19: 1 | BV19: =MAX(N19,AG19) -> 2050 | BW19: =IF(J19="Targets Set",1,"") | CD19: Retail | CE19: =COUNTIFS(C:C,CD19,L:L,"<=2024",J:J, "Targets Set") -> 1 | CF19: =COUNTIFS(C:C,CD19,L:L,">=2025",L:L,"<=2030", J:J, "Targets Set") -> 19 | CG19: =COUNTIFS(C:C,CD19,L:L,">2030",J:J, "Targets Set") -> 3 | CH19: =COUNTIFS($C$3:$C$502,CD19,$H$3:$H$502,"<=2024") -> 0 | CI19: =COUNTIFS($C$3:$C$502,CD19,$H$3:$H$502,">=2025",$H$3:$H$502,"<=2030") -> 6 | CJ19: =COUNTIFS($C$3:$C$502,CD19,$H$6:$H$505,">2030") -> 1 | CK19: =COUNTIFS(C:C, CD19, U:U,"<=2024", T:T, "<>G") -> 1 | CL19: =COUNTIFS(C:C,CD19,U:U,">=2024",U:U,"<=2030",T:T, "<>G") -> 3 | CM19: =COUNTIFS(C:C,CD19,U:U,">2030", T:T, "<>G") -> 4 | CN19: =COUNTIFS(C:C, CD19, AZ:AZ, "1", U:U, "<=2024", T:T, "<>N",T:T, "<>G") -> 1 | CO19: =COUNTIFS(C:C, CD19, AZ:AZ, "1", U:U, ">2024", U:U, "<=2030", T:T, "<>N",T:T, "<>G") -> 1 | CP19: =COUNTIFS(C:C, CD19, AZ:AZ, "1",U:U, ">2030", T:T, "<>N", T:T, "<>G") -> 2 | CQ19: =COUNTIFS($C$3:$C$502,CD19,$BV$3:$BV$502,"<=2024") -> 0 | CR19: =COUNTIFS($C$3:$C$502,CD19,$BV$3:$BV$502,">=2025",$BV$3:$BV$502,"<=2030") -> 0 | CS19: =COUNTIFS($C$3:$C$502,CD19,$BV$3:$BV$502,">2030") -> 25 | CT19: =SUM(CE19:CM19)-SUM(CN19:CP19)+SUM(CQ19:CS19) -> 59 | CU19: =COUNTIFS($C$3:$C$502, CD19, $BL$3:$BL$502, "1") -> 15 | CV19: =COUNTIFS($C$3:$C$502, CD19, $BM$3:$BM$502, "1") -> 2 | CW19: =COUNTIF($C$3:$C$502, CD19)-CV19-CU19 -> 29
A20: 244 | B20: Allstate | C20: Financial services | D20: United States of America (USA) | E20: North America | F20: N | I20: N | Q20: N | T20: N | AC20: C | AD20: Scope 1 and 2 emissions | AE20: Net Zero | AF20: C | AG20: 2030 | AH20: 2022 | AL20: U | AV20: =IF(AND(Q20<>"N",Q20<>"G",AZ20<>1),1,"") | AX20: 1 | AZ20: 1 | BI20: 1 | BJ20: 1 | BK20: 1 | BN20: =MAX(BH20,BD20,AZ20,AV20) -> 1 | BP20: 1 | BQ20: 1 | BV20: =MAX(N20,AG20) -> 2030 | BW20: =IF(J20="Targets Set",1,"") | CD20: Technology | CE20: =COUNTIFS(C:C,CD20,L:L,"<=2024",J:J, "Targets Set") -> 1 | CF20: =COUNTIFS(C:C,CD20,L:L,">=2025",L:L,"<=2030", J:J, "Targets Set") -> 7 | CG20: =COUNTIFS(C:C,CD20,L:L,">2030",J:J, "Targets Set") -> 3 | CH20: =COUNTIFS($C$3:$C$502,CD20,$H$3:$H$502,"<=2024") -> 4 | CI20: =COUNTIFS($C$3:$C$502,CD20,$H$3:$H$502,">=2025",$H$3:$H$502,"<=2030") -> 1 | CJ20: =COUNTIFS($C$3:$C$502,CD20,$H$6:$H$505,">2030") -> 0 | CK20: =COUNTIFS(C:C, CD20, U:U,"<=2024", T:T, "<>G") -> 3 | CL20: =COUNTIFS(C:C,CD20,U:U,">=2024",U:U,"<=2030",T:T, "<>G") -> 2 | CM20: =COUNTIFS(C:C,CD20,U:U,">2030", T:T, "<>G") -> 2 | CN20: =COUNTIFS(C:C, CD20, AZ:AZ, "1", U:U, "<=2024", T:T, "<>N",T:T, "<>G") -> 1 | CO20: =COUNTIFS(C:C, CD20, AZ:AZ, "1", U:U, ">2024", U:U, "<=2030", T:T, "<>N",T:T, "<>G") -> 1 | CP20: =COUNTIFS(C:C, CD20, AZ:AZ, "1",U:U, ">2030", T:T, "<>N", T:T, "<>G") -> 0 | CQ20: =COUNTIFS($C$3:$C$502,CD20,$BV$3:$BV$502,"<=2024") -> 2 | CR20: =COUNTIFS($C$3:$C$502,CD20,$BV$3:$BV$502,">=2025",$BV$3:$BV$502,"<=2030") -> 3 | CS20: =COUNTIFS($C$3:$C$502,CD20,$BV$3:$BV$502,">2030") -> 5 | CT20: =SUM(CE20:CM20)-SUM(CN20:CP20)+SUM(CQ20:CS20) -> 31 | CU20: =COUNTIFS($C$3:$C$502, CD20, $BL$3:$BL$502, "1") -> 11 | CV20: =COUNTIFS($C$3:$C$502, CD20, $BM$3:$BM$502, "1") -> 0 | CW20: =COUNTIF($C$3:$C$502, CD20)-CV20-CU20 -> 6
A21: 17 | B21: Alphabet | C21: Technology | D21: United States of America (USA) | E21: North America | F21: N | I21: N | J21: Committed | L21: 2030 | M21: No | O21: 44805 | P21: 2022 | Q21: N | T21: N | AC21: V | AD21: operations and value chain | AE21: Net Zero | AF21: V | AG21: 2030 | AH21: 2020 | AL21: Y | AM21: 2024 | AN21: Y | AV21: =IF(AND(Q21<>"N",Q21<>"G",AZ21<>1),1,"") | AX21: 1 | AZ21: 1 | BB21: 1 | BD21: 1 | BI21: 1 | BK21: 1 | BL21: 1 | BN21: =MAX(BH21,BD21,AZ21,AV21) -> 1 | BP21: 1 | BQ21: 1 | BS21: 1 | BU21: 1 | BV21: =MAX(N21,AG21) -> 2030 | BW21: =IF(J21="Targets Set",1,"") | CD21: Telecommunications and media | CE21: =COUNTIFS(C:C,CD21,L:L,"<=2024",J:J, "Targets Set") -> 1 | CF21: =COUNTIFS(C:C,CD21,L:L,">=2025",L:L,"<=2030", J:J, "Targets Set") -> 10 | CG21: =COUNTIFS(C:C,CD21,L:L,">2030",J:J, "Targets Set") -> 1 | CH21: =COUNTIFS($C$3:$C$502,CD21,$H$3:$H$502,"<=2024") -> 1 | CI21: =COUNTIFS($C$3:$C$502,CD21,$H$3:$H$502,">=2025",$H$3:$H$502,"<=2030") -> 4 | CJ21: =COUNTIFS($C$3:$C$502,CD21,$H$6:$H$505,">2030") -> 2 | CK21: =COUNTIFS(C:C, CD21, U:U,"<=2024", T:T, "<>G") -> 0 | CL21: =COUNTIFS(C:C,CD21,U:U,">=2024",U:U,"<=2030",T:T, "<>G") -> 3 | CM21: =COUNTIFS(C:C,CD21,U:U,">2030", T:T, "<>G") -> 5 | CN21: =COUNTIFS(C:C, CD21, AZ:AZ, "1", U:U, "<=2024", T:T, "<>N",T:T, "<>G") -> 0 | CO21: =COUNTIFS(C:C, CD21, AZ:AZ, "1", U:U, ">2024", U:U, "<=2030", T:T, "<>N",T:T, "<>G") -> 2 | CP21: =COUNTIFS(C:C, CD21, AZ:AZ, "1",U:U, ">2030", T:T, "<>N", T:T, "<>G") -> 1 | CQ21: =COUNTIFS($C$3:$C$502,CD21,$BV$3:$BV$502,"<=2024") -> 1 | CR21: =COUNTIFS($C$3:$C$502,CD21,$BV$3:$BV$502,">=2025",$BV$3:$BV$502,"<=2030") -> 1 | CS21: =COUNTIFS($C$3:$C$502,CD21,$BV$3:$BV$502,">2030") -> 7 | CT21: =SUM(CE21:CM21)-SUM(CN21:CP21)+SUM(CQ21:CS21) -> 33 | CU21: =COUNTIFS($C$3:$C$502, CD21, $BL$3:$BL$502, "1") -> 8 | CV21: =COUNTIFS($C$3:$C$502, CD21, $BM$3:$BM$502, "1") -> 0 | CW21: =COUNTIF($C$3:$C$502, CD21)-CV21-CU21 -> 12
A22: 214 | B22: Aluminum Corp. of China | C22: Metals and mining | D22: China | E22: Asia | F22: N | I22: N | Q22: G | R22: Scope 1 and 2 | S22: Carbon Neutrality | T22: G | U22: 2060 | V22: 2021 | AC22: N | AF22: N | AV22: =IF(AND(Q22<>"N",Q22<>"G",AZ22<>1),1,"") | BN22: =MAX(BH22,BD22,AZ22,AV22) -> 0 | BW22: =IF(J22="Targets Set",1,"") | CD22: Transportation and logistics | CE22: =COUNTIFS(C:C,CD22,L:L,"<=2024",J:J, "Targets Set") -> 0 | CF22: =COUNTIFS(C:C,CD22,L:L,">=2025",L:L,"<=2030", J:J, "Targets Set") -> 7 | CG22: =COUNTIFS(C:C,CD22,L:L,">2030",J:J, "Targets Set") -> 3 | CH22: =COUNTIFS($C$3:$C$502,CD22,$H$3:$H$502,"<=2024") -> 0 | CI22: =COUNTIFS($C$3:$C$502,CD22,$H$3:$H$502,">=2025",$H$3:$H$502,"<=2030") -> 0 | CJ22: =COUNTIFS($C$3:$C$502,CD22,$H$6:$H$505,">2030") -> 0 | CK22: =COUNTIFS(C:C, CD22, U:U,"<=2024", T:T, "<>G") -> 1 | CL22: =COUNTIFS(C:C,CD22,U:U,">=2024",U:U,"<=2030",T:T, "<>G") -> 0 | CM22: =COUNTIFS(C:C,CD22,U:U,">2030", T:T, "<>G") -> 6 | CN22: =COUNTIFS(C:C, CD22, AZ:AZ, "1", U:U, "<=2024", T:T, "<>N",T:T, "<>G") -> 1 | CO22: =COUNTIFS(C:C, CD22, AZ:AZ, "1", U:U, ">2024", U:U, "<=2030", T:T, "<>N",T:T, "<>G") -> 0 | CP22: =COUNTIFS(C:C, CD22, AZ:AZ, "1",U:U, ">2030", T:T, "<>N", T:T, "<>G") -> 2 | CQ22: =COUNTIFS($C$3:$C$502,CD22,$BV$3:$BV$502,"<=2024") -> 0 | CR22: =COUNTIFS($C$3:$C$502,CD22,$BV$3:$BV$502,">=2025",$BV$3:$BV$502,"<=2030") -> 0 | CS22: =COUNTIFS($C$3:$C$502,CD22,$BV$3:$BV$502,">2030") -> 9 | CT22: =SUM(CE22:CM22)-SUM(CN22:CP22)+SUM(CQ22:CS22) -> 23 | CU22: =COUNTIFS($C$3:$C$502, CD22, $BL$3:$BL$502, "1") -> 5 | CV22: =COUNTIFS($C$3:$C$502, CD22, $BM$3:$BM$502, "1") -> 1 | CW22: =COUNTIF($C$3:$C$502, CD22)-CV22-CU22 -> 14
A23: 2 | B23: Amazon | C23: Retail | D23: United States of America (USA) | E23: North America | F23: N | I23: N | J23: Removed | M23: No | O23: 43983 | P23: 2020 | Q23: N | T23: N | AC23: C | AD23: Scope 1 and 2 | AE23: Net Zero | AF23: C | AG23: 2040 | AH23: 2019 | AL23: Y | AM23: 2023 | AN23: Y | AV23: =IF(AND(Q23<>"N",Q23<>"G",AZ23<>1),1,"") | AY23: 1 | AZ23: 1 | BI23: 1 | BK23: 1 | BL23: 1 | BN23: =MAX(BH23,BD23,AZ23,AV23) -> 1 | BQ23: 1 | BV23: =MAX(N23,AG23) -> 2040 | BW23: =IF(J23="Targets Set",1,"") | CD23: sum | CE23: =SUM(CE6:CE22) -> 4 | CF23: =SUM(CF6:CF22) -> 112 | CG23: =SUM(CG6:CG22) -> 21 | CH23: =SUM(CH6:CH22) -> 19 | CI23: =SUM(CI6:CI22) -> 40 | CJ23: =SUM(CJ6:CJ22) -> 18 | CK23: =SUM(CK6:CK22) -> 40 | CL23: =SUM(CL6:CL22) -> 47 | ... CW23: =SUM(CW6:CW22) -> 284
A24: 328 | B24: America Movil | C24: Telecommunications and media | D24: United States of America (USA) | E24: North America | F24: N | I24: Y | J24: Targets Set | K24: 1.5Â°C | L24: 2030 | M24: No | O24: 44044 | P24: 2020 | Q24: N | T24: N | AC24: N | AF24: N | AV24: =IF(AND(Q24<>"N",Q24<>"G",AZ24<>1),1,"") | BB24: 1 | BD24: 1 | BN24: =MAX(BH24,BD24,AZ24,AV24) -> 1 | BP24: 1 | BQ24: 1 | BW24: =IF(J24="Targets Set",1,"") -> 1 | CE24: SBTi short term | CH24: RE100 | CK24: Carbon Neutral | CO24: Overlap (CN to be removed) | CQ24: Net Zero | CT24: sum
A25: 278 | B25: American Airlines Group | C25: Transportation and Logistics | D25: United States of America (USA) | E25: North America | F25: N | I25: Y | J25: Targets Set | K25: Well-below 2Â°C | L25: 2035 | M25: No | O25: 44652 | P25: 2022 | Q25: N | T25: N | AC25: C | AD25: undefined | AE25: Net Zero | AF25: C | AG25: 2050 | AH25: 2020 | AL25: Y | AV25: =IF(AND(Q25<>"N",Q25<>"G",AZ25<>1),1,"") | AY25: 1 | AZ25: 1 | BC25: 1 | BD25: 1 | BI25: 1 | BK25: 1 | BL25: 1 | BN25: =MAX(BH25,BD25,AZ25,AV25) -> 1 | BQ25: 1 | BV25: =MAX(N25,AG25) -> 2050 | BW25: =IF(J25="Targets Set",1,"") -> 1 | CD25: region | CE25: <=2024 | CF25: 2025-2030 | CG25: 2031-2060 | CH25: <=2024 | CI25: 2025-2030 | CJ25: 2031-2060 | CK25: <=2024 | CL25: 2025-2030 | CM25: 2031-2060 | CN25: <=2024 | CO25: 2025-2030 | CP25: 2031-2060 | CQ25: <=2024 | CR25: 2025-2030 | CS25: 2031-2060 | CT25: no overlap
A26: 195 | B26: American Express | C26: Financial services | D26: United States of America (USA) | E26: North America | F26: Y | G26: 2020 | H26: 2025 | I26: N | J26: Committed | L26: 2030 | M26: No | O26: 44440 | P26: 2021 | Q26: C | R26: operations - scope 1, 2 and partial 3 | S26: carbon neutral | T26: C | U26: 2018 | V26: 2018 | Z26: Y | AA26: 2023 | AB26: Y | AC26: V | AD26: undefined but SBTi approved | AE26: Net Zero | AF26: V | AG26: 2035 | AH26: 2021 | AL26: U | AQ26: 1 | AT26: 1 | AU26: 1 | AV26: =IF(AND(Q26<>"N",Q26<>"G",AZ26<>1),1,"") | AY26: 1 | AZ26: 1 | BB26: 1 | BD26: 1 | BF26: 1 | BH26: 1 | BI26: 1 | BJ26: 1 | BK26: 1 | BL26: 1 | BN26: =MAX(BH26,BD26,AZ26,AV26) -> 1 | BO26: 1 | BP26: 1 | BQ26: 1 | BT26: 1 | BU26: 1 | BV26: =MAX(N26,AG26) -> 2035 | BW26: =IF(J26="Targets Set",1,"") | CD26: Asia | CE26: =COUNTIFS(E:E,CD26,L:L,"<=2024", J:J, "Targets Set") -> 0 | CF26: =COUNTIFS(E:E,CD26,L:L,">=2025",L:L,"<=2030", J:J, "Targets Set") -> 19 | CG26: =COUNTIFS(E:E,CD26,L:L,">2030", J:J, "Targets Set") -> 4 | CH26: =COUNTIFS($E$3:$E$502,CD26,$H$3:$H$502,"<=2024") -> 1 | CI26: =COUNTIFS($E$3:$E$502,CD26,$H$3:$H$502,">=2025",$H$3:$H$502,"<=2030") -> 3 | CJ26: =COUNTIFS($E$3:$E$502,CD26,$H$6:$H$505,">2030") -> 8 | CK26: =COUNTIFS($E$3:$E$502,CD26,$U$3:$U$502,"<=2024") -> 3 | CL26: =COUNTIFS(E:E,CD26,U:U,">=2024",U:U,"<=2030",T:T, "<>G") -> 15 | CM26: =COUNTIFS(E:E,CD26,U:U,">2030", T:T, "<>G") -> 34 | CN26: =COUNTIFS(E:E,CD26,AZ:AZ,"1", AU:AU, "1",U:U, "<=2024") -> 2 | CO26: =COUNTIFS(E:E,CD26,AZ:AZ,"1", AU:AU, "1",U:U, ">2024", U:U,"<=2030" ) -> 4 | CP26: =COUNTIFS(E:E,CD26,AZ:AZ,"1", AU:AU, "1",U:U, ">2030") -> 4 | CQ26: =COUNTIFS($E$3:$E$502,CD26,$BV$3:$BV$502,"<=2024") -> 0 | CR26: =COUNTIFS($E$3:$E$502,CD26,$BV$3:$BV$502,">=2025",$BV$3:$BV$502,"<=2030") -> 3 | CS26: =COUNTIFS($E$3:$E$502,CD26,$BV$3:$BV$502,">2030") -> 46 | CT26: =SUM(CE26:CM26)-SUM(CN26:CP26)+SUM(CQ26:CS26) -> 126 | CU26: =COUNTIFS($E$3:$E$502, CD26, $BL$3:$BL$502, "1") -> 54 | CV26: =COUNTIFS($E$3:$E$502, CD26, $BM$3:$BM$502, "1") -> 1 | CW26: =COUNTIFS($E$3:$E$502, CD26)-CV26-CU26 -> 155
A27: 231 | B27: Anheuser-Busch InBev | C27: Food, beverages and agriculture | D27: Belgium | E27: Europe | F27: Y | G27: 2017 | H27: 2025 | I27: Y | J27: Targets Set | K27: 1.5°C | L27: 2025 | M27: Yes | P27: 2018 | Q27: N | T27: N | AC27: V | AD27: Scope 1, 2 and 3 | AE27: Net Zero | AF27: V | AG27: 2040 | AH27: 2021 | AL27: Y | AV27: =IF(AND(Q27<>"N",Q27<>"G",AZ27<>1),1,"") | AY27: 1 | AZ27: 1 | BB27: 1 | BD27: 1 | BF27: 1 | BH27: 1 | BI27: 1 | BK27: 1 | BL27: 1 | BN27: =MAX(BH27,BD27,AZ27,AV27) -> 1 | BP27: 1 | BQ27: 1 | BT27: 1 | BU27: 1 | BV27: =MAX(N27,AG27) -> 2040 | BW27: =IF(J27="Targets Set",1,"") -> 1 | CD27: Europe | CE27: =COUNTIFS(E:E,CD27,L:L,"<=2024", J:J, "Targets Set") -> 1 | CF27: =COUNTIFS(E:E,CD27,L:L,">=2025",L:L,"<=2030", J:J, "Targets Set") -> 53 | CG27: =COUNTIFS(E:E,CD27,L:L,">2030", J:J, "Targets Set") -> 5 | CH27: =COUNTIFS($E$3:$E$502,CD27,$H$3:$H$502,"<=2024") -> 9 | CI27: =COUNTIFS($E$3:$E$502,CD27,$H$3:$H$502,">=2025",$H$3:$H$502,"<=2030") -> 21 | CJ27: =COUNTIFS($E$3:$E$502,CD27,$H$6:$H$505,">2030") -> 5 | CK27: =COUNTIFS($E$3:$E$502,CD27,$U$3:$U$502,"<=2024") -> 13 | CL27: =COUNTIFS(E:E,CD27,U:U,">=2024",U:U,"<=2030",T:T, "<>G") -> 16 | CM27: =COUNTIFS(E:E,CD27,U:U,">2030", T:T, "<>G") -> 31 | CN27: =COUNTIFS(E:E,CD27,AZ:AZ,"1", AU:AU, "1",U:U, "<=2024") -> 11 | CO27: =COUNTIFS(E:E,CD27,AZ:AZ,"1", AU:AU, "1",U:U, ">2024", U:U,"<=2030" ) -> 15 | CP27: =COUNTIFS(E:E,CD27,AZ:AZ,"1", AU:AU, "1",U:U, ">2030") -> 8 | CQ27: =COUNTIFS($E$3:$E$502,CD27,$BV$3:$BV$502,"<=2024") -> 0 | CR27: =COUNTIFS($E$3:$E$502,CD27,$BV$3:$BV$502,">=2025",$BV$3:$BV$502,"<=2030") -> 11 | CS27: =COUNTIFS($E$3:$E$502,CD27,$BV$3:$BV$502,">2030") -> 73 | CT27: =SUM(CE27:CM27)-SUM(CN27:CP27)+SUM(CQ27:CS27) -> 204 | CU27: =COUNTIFS($E$3:$E$502, CD27, $BL$3:$BL$502, "1") -> 70 | CV27: =COUNTIFS($E$3:$E$502, CD27, $BM$3:$BM$502, "1") -> 4 | CW27: =COUNTIFS($E$3:$E$502, CD27)-CV27-CU27 -> 43
A28: 371 | B28: Ansteel Group | C28: Metals and mining | D28: China | E28: Asia | F28: N | I28: N | Q28: G | R28: organization | S28: carbon neutrality | T28: G | U28: 2060 | V28: 2021 | AC28: N | AF28: N | AV28: =IF(AND(Q28<>"N",Q28<>"G",AZ28<>1),1,"") | BN28: =MAX(BH28,BD28,AZ28,AV28) -> 0 | BW28: =IF(J28="Targets Set",1,"") | CD28: North America | CE28: =COUNTIFS(E:E,CD28,L:L,"<=2024", J:J, "Targets Set") -> 3 | CF28: =COUNTIFS(E:E,CD28,L:L,">=2025",L:L,"<=2030", J:J, "Targets Set") -> 39 | CG28: =COUNTIFS(E:E,CD28,L:L,">2030", J:J, "Targets Set") -> 12 | CH28: =COUNTIFS($E$3:$E$502,CD28,$H$3:$H$502,"<=2024") -> 9 | CI28: =COUNTIFS($E$3:$E$502,CD28,$H$3:$H$502,">=2025",$H$3:$H$502,"<=2030") -> 13 | CJ28: =COUNTIFS($E$3:$E$502,CD28,$H$6:$H$505,">2030") -> 5 | CK28: =COUNTIFS($E$3:$E$502,CD28,$U$3:$U$502,"<=2024") -> 21 | CL28: =COUNTIFS(E:E,CD28,U:U,">=2024",U:U,"<=2030",T:T, "<>G") -> 14 | CM28: =COUNTIFS(E:E,CD28,U:U,">2030", T:T, "<>G") -> 17 | CN28: =COUNTIFS(E:E,CD28,AZ:AZ,"1", AU:AU, "1",U:U, "<=2024") -> 15 | CO28: =COUNTIFS(E:E,CD28,AZ:AZ,"1", AU:AU, "1",U:U, ">2024", U:U,"<=2030" ) -> 8 | CP28: =COUNTIFS(E:E,CD28,AZ:AZ,"1", AU:AU, "1",U:U, ">2030") -> 2 | CQ28: =COUNTIFS($E$3:$E$502,CD28,$BV$3:$BV$502,"<=2024") -> 3 | CR28: =COUNTIFS($E$3:$E$502,CD28,$BV$3:$BV$502,">=2025",$BV$3:$BV$502,"<=2030") -> 8 | CS28: =COUNTIFS($E$3:$E$502,CD28,$BV$3:$BV$502,">2030") -> 71 | CT28: =SUM(CE28:CM28)-SUM(CN28:CP28)+SUM(CQ28:CS28) -> 190 | CU28: =COUNTIFS($E$3:$E$502, CD28, $BL$3:$BL$502, "1") -> 73 | CV28: =COUNTIFS($E$3:$E$502, CD28, $BM$3:$BM$502, "1") -> 3 | CW28: =COUNTIFS($E$3:$E$502, CD28)-CV28-CU28 -> 81
A29: 323 | B29: ANZ Group Holdings | C29: Financial services | D29: Australia | E29: Other | F29: Y | G29: 2019 | H29: 2025 | I29: N | Q29: N | T29: N | AC29: C | AD29: scope 1 and 290& reduction and financed emissions | AE29: Net Zero | AF29: C | AG29: 2050 | AH29: 2021 | AL29: U | AM29: 2023 | AN29: Y | AV29: =IF(AND(Q29<>"N",Q29<>"G",AZ29<>1),1,"") | AY29: 1 | AZ29: 1 | BF29: 1 | BH29: 1 | BI29: 1 | BK29: 1 | BN29: =MAX(BH29,BD29,AZ29,AV29) -> 1 | BP29: 1 | BQ29: 1 | BV29: =MAX(N29,AG29) -> 2050 | BW29: =IF(J29="Targets Set",1,"") | CD29: other | CE29: =COUNTIFS(E:E,CD29,L:L,"<=2024", J:J, "Targets Set") -> 0 | CF29: =COUNTIFS(E:E,CD29,L:L,">=2025",L:L,"<=2030", J:J, "Targets Set") -> 1 | CG29: =COUNTIFS(E:E,CD29,L:L,">2030", J:J, "Targets Set") -> 0 | CH29: =COUNTIFS($E$3:$E$502,CD29,$H$3:$H$502,"<=2024") -> 0 | CI29: =COUNTIFS($E$3:$E$502,CD29,$H$3:$H$502,">=2025",$H$3:$H$502,"<=2030") -> 3 | CJ29: =COUNTIFS($E$3:$E$502,CD29,$H$6:$H$505,">2030") -> 0 | CK29: =COUNTIFS($E$3:$E$502,CD29,$U$3:$U$502,"<=2024") -> 3 | CL29: =COUNTIFS(E:E,CD29,U:U,">=2024",U:U,"<=2030",T:T, "<>G") -> 2 | CM29: =COUNTIFS(E:E,CD29,U:U,">2030", T:T, "<>G") -> 1 | CN29: =COUNTIFS(E:E,CD29,AZ:AZ,"1", AU:AU, "1",U:U, "<=2024") -> 3 | CO29: =COUNTIFS(E:E,CD29,AZ:AZ,"1", AU:AU, "1",U:U, ">2024", U:U,"<=2030" ) -> 0 | CP29: =COUNTIFS(E:E,CD29,AZ:AZ,"1", AU:AU, "1",U:U, ">2030") -> 0 | CQ29: =COUNTIFS($E$3:$E$502,CD29,$BV$3:$BV$502,"<=2024") -> 0 | CR29: =COUNTIFS($E$3:$E$502,CD29,$BV$3:$BV$502,">=2025",$BV$3:$BV$502,"<=2030") -> 0 | CS29: =COUNTIFS($E$3:$E$502,CD29,$BV$3:$BV$502,">2030") -> 11 | CT29: =SUM(CE29:CM29)-SUM(CN29:CP29)+SUM(CQ29:CS29) -> 18 | CU29: =COUNTIFS($E$3:$E$502, CD29, $BL$3:$BL$502, "1") -> 11 | CV29: =COUNTIFS($E$3:$E$502, CD29, $BM$3:$BM$502, "1") -> 0 | CW29: =COUNTIFS($E$3:$E$502, CD29)-CV29-CU29 -> 5
A30: 491 | B30: Apollo Global Management | C30: Financial services | D30: United States of America (USA) | E30: North America | F30: N | I30: N | Q30: C | R30: Scope 1 and 2 GHG emissions | S30: carbon-neutral | T30: C | U30: 2023 | V30: 2023 | Z30: Y | AA30: 2023 | AB30: Y | AC30: N | AF30: N | AQ30: 1 | AT30: 1 | AU30: 1 | AV30: =IF(AND(Q30<>"N",Q30<>"G",AZ30<>1),1,"") -> 1 | BI30: 1 | BJ30: 1 | BK30: 1 | BL30: 1 | BN30: =MAX(BH30,BD30,AZ30,AV30) -> 1 | BO30: 1 | BP30: 1 | BQ30: 1 | BW30: =IF(J30="Targets Set",1,"") | CD30: sum | CE30: =SUM(CE26:CE29) -> 4 | CF30: =SUM(CF26:CF29) -> 112 | CG30: =SUM(CG26:CG29) -> 21 | CH30: =SUM(CH26:CH29) -> 19 | CI30: =SUM(CI26:CI29) -> 40 | CJ30: =SUM(CJ26:CJ29) -> 18 | CK30: =SUM(CK26:CK29) -> 40 | CL30: =SUM(CL26:CL29) -> 47 | ... CW30: =SUM(CW26:CW29) -> 284
A31: 7 | B31: Apple | C31: Technology | D31: United States of America (USA) | E31: North America | F31: Y | G31: 2016 | H31: 2021 | I31: Y | J31: Targets Set | K31: 1.5Â°C | L31: 2030 | M31: No | O31: 44317 | P31: 2021 | Q31: C, V | R31: corporate operations, entire value chain | S31: carbon neutrality | T31: C | U31: 2020 | V31: 2020 | W31: V | X31: 2030 | Y31: 2020 | Z31: R | AA31: 2024 | AB31: Y | AC31: N | AF31: N | AQ31: 1 | AT31: 1 | AU31: 1 | AV31: =IF(AND(Q31<>"N",Q31<>"G",AZ31<>1),1,"") -> 1 | BB31: 1 | BD31: 1 | BE31: 1 | BH31: 1 | BI31: 1 | BJ31: 1 | BK31: 1 | BL31: 1 | BN31: =MAX(BH31,BD31,AZ31,AV31) -> 1 | BO31: 1 | BP31: 1 | BQ31: 1 | BW31: =IF(J31="Targets Set",1,"") -> 1
A32: 190 | B32: ArcelorMittal | C32: Metals and mining | D32: Luxembourg | E32: Europe | F32: N | I32: N | J32: Removed | M32: No | O32: 44593 | P32: 2022 | Q32: C | R32: Scope 1 and 2 | S32: Carbon Neutral | T32: C | U32: 2050 | V32: 2020 | Z32: Y | AB32: Y | AC32: C | AD32: Scope 1 and 2 | AE32: Net Zero | AF32: C | AG32: 2050 | AH32: 2020 | AL32: Y | AS32: 1 | AT32: 1 | AU32: 1 | AV32: =IF(AND(Q32<>"N",Q32<>"G",AZ32<>1),1,"") | AY32: 1 | AZ32: 1 | BI32: 1 | BK32: 1 | BL32: 1 | BN32: =MAX(BH32,BD32,AZ32,AV32) -> 1 | BQ32: 1 | BV32: =MAX(N32,AG32) -> 2050 | BW32: =IF(J32="Targets Set",1,"")
A33: 117 | B33: Archer Daniels Midland | C33: Food, beverages and agriculture | D33: United States of America (USA) | E33: North America | F33: N | I33: N | J33: Committed | L33: 2030 | M33: No | O33: 44652 | P33: 2022 | Q33: N | T33: N | AC33: N | AF33: N | AV33: =IF(AND(Q33<>"N",Q33<>"G",AZ33<>1),1,"") | BB33: 1 | BD33: 1 | BN33: =MAX(BH33,BD33,AZ33,AV33) -> 1 | BP33: 1 | BQ33: 1 | BW33: =IF(J33="Targets Set",1,"")
A34: 481 | B34: Arrow Electronics | C34: Retail | D34: United States of America (USA) | E34: North America | F34: N | I34: N | J34: Committed | L34: 2030 | M34: No | O34: 45170 | P34: 2023 | Q34: N | T34: N | AC34: N | AF34: N | AV34: =IF(AND(Q34<>"N",Q34<>"G",AZ34<>1),1,"") | BB34: 1 | BD34: 1 | BN34: =MAX(BH34,BD34,AZ34,AV34) -> 1 | BP34: 1 | BQ34: 1 | BW34: =IF(J34="Targets Set",1,"")
A35: 245 | B35: Assicurazioni Generali | C35: Financial services | D35: Italy | E35: Europe | F35: N | I35: N | Q35: N | T35: N | AC35: C, F | AD35: operational activities, insurance portfolio | AE35: Net-Zero emissions | AF35: C | AG35: 2040 | AH35: 2021 | AI35: F | AJ35: 2050 | AK35: 2021 | AL35: R | AO35: Y | AP35: N | AV35: =IF(AND(Q35<>"N",Q35<>"G",AZ35<>1),1,"") | AY35: 1 | AZ35: 1 | BI35: 1 | BK35: 1 | BL35: 1 | BN35: =MAX(BH35,BD35,AZ35,AV35) -> 1 | BQ35: 1 | BT35: 1 | BU35: 1 | BV35: =MAX(N35,AG35) -> 2040 | BW35: =IF(J35="Targets Set",1,"")
A36: 329 | B36: AstraZeneca | C36: Health care and pharmaceuticals | D36: United Kingdom | E36: Europe | F36: Y | G36: 2016 | H36: 2025 | I36: Y | J36: Targets Set | K36: 1.5Â°C | L36: 2026 | M36: Yes | N36: 2045 | O36: 44470 | P36: 2021 | Q36: N | T36: N | AC36: V | AD36: value chain (Scopes 1, 2 and 3) | AE36: Net Zero | AF36: V | AG36: 2045 | AH36: 2020 | AL36: Y | AV36: =IF(AND(Q36<>"N",Q36<>"G",AZ36<>1),1,"") | AY36: 1 | AZ36: 1 | BB36: 1 | BD36: 1 | BF36: 1 | BH36: 1 | BI36: 1 | BK36: 1 | BL36: 1 | BN36: =MAX(BH36,BD36,AZ36,AV36) -> 1 | BP36: 1 | BQ36: 1 | BT36: 1 | BU36: 1 | BV36: =MAX(N36,AG36) -> 2045 | BW36: =IF(J36="Targets Set",1,"") -> 1
A37: 74 | B37: AT&T | C37: Telecommunications and media | D37: United States of America (USA) | E37: North America | F37: N | I37: Y | J37: Targets Set | K37: 1.5Â°C | L37: 2024 | M37: No | O37: 43891 | P37: 2020 | Q37: C | R37: entire global operations | S37: carbon neutral | T37: C | U37: 2035 | V37: 2018 | Z37: Y | AB37: Y | AC37: N | AF37: N | AS37: 1 | AT37: 1 | AU37: 1 | AV37: =IF(AND(Q37<>"N",Q37<>"G",AZ37<>1),1,"") -> 1 | BB37: 1 | BD37: 1 | BI37: 1 | BK37: 1 | BL37: 1 | BN37: =MAX(BH37,BD37,AZ37,AV37) -> 1 | BP37: 1 | BQ37: 1 | BW37: =IF(J37="Targets Set",1,"") -> 1 | CE37: =137/500 -> 0.274 | CJ37: =144+11 -> 155
A38: 147 | B38: Aviation Industry Corp. of China | C38: Aerospace and defense | D38: China | E38: Asia | F38: N | I38: N | Q38: I | T38: I | AC38: V | AD38: Scope 1, 2 and 3 | AE38: Net Zero | AF38: V | AG38: 2050 | AH38: 2021 | AL38: Y | AV38: =IF(AND(Q38<>"N",Q38<>"G",AZ38<>1),1,"") | AY38: 1 | AZ38: 1 | BI38: 1 | BK38: 1 | BL38: 1 | BN38: =MAX(BH38,BD38,AZ38,AV38) -> 1 | BQ38: 1 | BT38: 1 | BU38: 1 | BV38: =MAX(N38,AG38) -> 2050 | BW38: =IF(J38="Targets Set",1,"")
A39: 126 | B39: AXA | C39: Financial services | D39: France | E39: Europe | F39: Y | G39: 2017 | H39: 2025 | I39: N | J39: Committed | L39: 2030 | M39: No | O39: 42156 | P39: 2015 | Q39: C, V | R39: operations, Scope 3 business travel, IT equipment manufacturing and purchased services, and upstream energy emissions | S39: carbon neutral | T39: C | U39: 2020 | V39: 2020 | W39: V | X39: 2025 | Y39: 2020 | Z39: Y | AA39: 2024 | AB39: Y | AC39: F | AD39: insurance and reinsurance underwriting portfolios | AE39: Net-Zero greenhouse gas emissions | AF39: F | AG39: 2050 | AH39: 2023 | AL39: U | AQ39: 1 | AT39: 1 | AU39: 1 | AV39: =IF(AND(Q39<>"N",Q39<>"G",AZ39<>1),1,"") | AY39: 1 | AZ39: 1 | BB39: 1 | BD39: 1 | BF39: 1 | BH39: 1 | BI39: 1 | BJ39: 1 | BK39: 1 | BL39: 1 | BN39: =MAX(BH39,BD39,AZ39,AV39) -> 1 | BO39: 1 | BP39: 1 | BQ39: 1 | BT39: 1 | BU39: 1 | BV39: =MAX(N39,AG39) -> 2050 | BW39: =IF(J39="Targets Set",1,"")
A40: 200 | B40: Banco Bilbao Vizcaya Argentaria | C40: Financial services | D40: Spain | E40: Europe | F40: N | I40: N | J40: Committed | L40: 2030 | M40: No | O40: 43101 | P40: 2018 | Q40: C | R40: scope 1 and 2 | S40: carbon neutral | T40: C | U40: 2020 | V40: 2020 | Z40: Y | AA40: 2024 | AB40: Y | AC40: V | AD40: direct and indirect emissions | AE40: zero net emissions | AF40: V | AG40: 2050 | AH40: 2021 | AL40: Y | AQ40: 1 | AT40: 1 | AU40: 1 | AV40: =IF(AND(Q40<>"N",Q40<>"G",AZ40<>1),1,"") | AY40: 1 | AZ40: 1 | BB40: 1 | BD40: 1 | BI40: 1 | BJ40: 1 | BK40: 1 | BL40: 1 | BN40: =MAX(BH40,BD40,AZ40,AV40) -> 1 | BO40: 1 | BP40: 1 | BQ40: 1 | BT40: 1 | BU40: 1 | BV40: =MAX(N40,AG40) -> 2050 | BW40: =IF(J40="Targets Set",1,"")
A41: 252 | B41: Banco Bradesco | C41: Financial services | D41: Brazil | E41: Other | F41: N | I41: N | Q41: C | R41: operations, scope 3 operational emissions | S41: offset 100%/neutralized | T41: C | U41: 2006 | V41: 2006 | W41: C | X41: 2019 | Y41: 2019 | Z41: Y | AA41: 2024 | AB41: Y | AC41: C+F | AD41: operations and portfolios | AE41: Net Zero carbon emissions | AF41: C+F | AG41: 2050 | AH41: 2021 | AL41: Y | AQ41: 1 | AT41: 1 | AU41: 1 | AV41: =IF(AND(Q41<>"N",Q41<>"G",AZ41<>1),1,"") | AY41: 1 | AZ41: 1 | BI41: 1 | BJ41: 1 | BK41: 1 | BL41: 1 | BN41: =MAX(BH41,BD41,AZ41,AV41) -> 1 | BO41: 1 | BP41: 1 | BQ41: 1 | BT41: 1 | BU41: 1 | BV41: =MAX(N41,AG41) -> 2050 | BW41: =IF(J41="Targets Set",1,"")
A42: 217 | B42: Banco do Brasil | C42: Financial services | D42: Brazil | E42: Other | F42: N | I42: N | J42: Committed | L42: 2030 | M42: Yes | O42: 44197 | P42: 2021 | Q42: C, F | R42: scope 1 and 2, financed emissions (value chain) | S42: offsetting 100% of GHG emissions, emissions neutrality | T42: C | U42: 2030 | V42: 2023 | W42: F | X42: 2050 | Y42: 2023 | Z42: Y | AA42: 2022 | AB42: Y | AC42: N | AF42: N | AO42: Y | AP42: N | AR42: 1 | AT42: 1 | AU42: 1 | AV42: =IF(AND(Q42<>"N",Q42<>"G",AZ42<>1),1,"") -> 1 | BB42: 1 | BD42: 1 | BI42: 1 | BJ42: 1 | BK42: 1 | BL42: 1 | BN42: =MAX(BH42,BD42,AZ42,AV42) -> 1 | BP42: 1 | BQ42: 1 | BW42: =IF(J42="Targets Set",1,"")
A43: 62 | B43: Banco Santander | C43: Financial services | D43: Spain | E43: Europe | F43: N | I43: N | Q43: C | R43: own operations | S43: carbon neutral | T43: C | U43: 2020 | V43: 2019 | Z43: Y | AA43: 2022 | AB43: Y | AC43: C, F | AD43: our operations, portfolios | AE43: Net Zero | AF43: C | AG43: 2050 | AH43: 2021 | AI43: F | AJ43: 2050 | AK43: 2021 | AL43: Y | AM43: 2023 | AN43: Y | AQ43: 1 | AT43: 1 | AU43: 1 | AV43: =IF(AND(Q43<>"N",Q43<>"G",AZ43<>1),1,"") | AY43: 1 | AZ43: 1 | BI43: 1 | BJ43: 1 | BK43: 1 | BL43: 1 | BN43: =MAX(BH43,BD43,AZ43,AV43) -> 1 | BO43: 1 | BP43: 1 | BQ43: 1 | BT43: 1 | BU43: 1 | BV43: =MAX(N43,AG43) -> 2050 | BW43: =IF(J43="Targets Set",1,"")
A44: 38 | B44: Bank of America | C44: Financial services | D44: United States of America (USA) | E44: North America | F44: N | I44: N | Q44: C | R44: undefined | S44: carbon neutral | T44: C | U44: 2020 | V44: 2016 | Z44: Y | AA44: 2022 | AB44: Y | AC44: V, F | AD44: Scope 1, 2 and 3 | AE44: Net Zero | AF44: V | AG44: 2030 | AH44: 2021 | AI44: F | AJ44: 2050 | AK44: 2021 | AL44: U | AQ44: 1 | AT44: 1 | AU44: 1 | AV44: =IF(AND(Q44<>"N",Q44<>"G",AZ44<>1),1,"") | AX44: 1 | AZ44: 1 | BI44: 1 | BJ44: 1 | BK44: 1 | BL44: 1 | BN44: =MAX(BH44,BD44,AZ44,AV44) -> 1 | BO44: 1 | BP44: 1 | BQ44: 1 | BS44: 1 | BU44: 1 | BV44: =MAX(N44,AG44) -> 2030 | BW44: =IF(J44="Targets Set",1,"")
A45: 37 | B45: Bank of China | C45: Financial services | D45: China | E45: Asia | F45: N | I45: N | Q45: C | R45: undefined | S45: carbon neutrality | T45: C | U45: 2030 | V45: 2021 | Z45: U | AA45: 2023 | AB45: Y | AC45: N | AF45: N | AO45: N | AP45: N | AR45: 1 | AT45: 1 | AU45: 1 | AV45: =IF(AND(Q45<>"N",Q45<>"G",AZ45<>1),1,"") -> 1 | BI45: 1 | BJ45: 1 | BK45: 1 | BN45: =MAX(BH45,BD45,AZ45,AV45) -> 1 | BP45: 1 | BQ45: 1 | BW45: =IF(J45="Targets Set",1,"")
A46: 154 | B46: Bank of Communications | C46: Financial services | D46: China | E46: Asia | F46: N | I46: N | Q46: G | R46: Scope 1 and 2 | S46: carbon neutral | T46: G | U46: 2060 | V46: 2021 | AC46: N | AF46: N | AV46: =IF(AND(Q46<>"N",Q46<>"G",AZ46<>1),1,"") | BN46: =MAX(BH46,BD46,AZ46,AV46) -> 0 | BW46: =IF(J46="Targets Set",1,"")
A47: 294 | B47: Bank of Montreal | C47: Financial services | D47: Canada | E47: North America | F47: N | I47: N | Q47: C | R47: operations | S47: carbon neutrality | T47: C | U47: 2010 | V47: 2010 | Z47: Y | AA47: 2023 | AB47: Y | AC47: F | AD47: financed emissions | AE47: Net Zero | AF47: F | AG47: 2050 | AH47: 2021 | AL47: Y | AM47: 2023 | AN47: Y | AQ47: 1 | AT47: 1 | AU47: 1 | AV47: =IF(AND(Q47<>"N",Q47<>"G",AZ47<>1),1,"") | AY47: 1 | AZ47: 1 | BI47: 1 | BJ47: 1 | BK47: 1 | BL47: 1 | BN47: =MAX(BH47,BD47,AZ47,AV47) -> 1 | BO47: 1 | BP47: 1 | BQ47: 1 | BT47: 1 | BU47: 1 | BV47: =MAX(N47,AG47) -> 2050 | BW47: =IF(J47="Targets Set",1,"")
A48: 466 | B48: Bank of New York Mellon | C48: Financial services | D48: United States of America (USA) | E48: North America | F48: N | I48: N | Q48: C | R48: Scope 1, 2, and 3 business travel emissions | S48: carbon neutral | T48: C | U48: 2015 | V48: 2015 | Z48: Y | AA48: 2023 | AB48: Y | AC48: N | AF48: N | AQ48: 1 | AT48: 1 | AU48: 1 | AV48: =IF(AND(Q48<>"N",Q48<>"G",AZ48<>1),1,"") -> 1 | BI48: 1 | BJ48: 1 | BK48: 1 | BL48: 1 | BN48: =MAX(BH48,BD48,AZ48,AV48) -> 1 | BO48: 1 | BP48: 1 | BQ48: 1 | BW48: =IF(J48="Targets Set",1,"")
A49: 281 | B49: Bank of Nova Scotia | C49: Financial services | D49: Canada | E49: North America | F49: N | I49: N | Q49: C | R49: banking alliance operations | S49: carbon neutrality | T49: C | U49: 2030 | V49: 2022 | Z49: Y | AA49: 2023 | AB49: Y | AC49: F | AD49: financed emissions | AE49: Net Zero | AF49: F | AG49: 2050 | AH49: 2022 | AL49: R | AM49: 2023 | AN49: Y | AR49: 1 | AT49: 1 | AU49: 1 | AV49: =IF(AND(Q49<>"N",Q49<>"G",AZ49<>1),1,"") | AY49: 1 | AZ49: 1 | BI49: 1 | BJ49: 1 | BK49: 1 | BL49: 1 | BN49: =MAX(BH49,BD49,AZ49,AV49) -> 1 | BP49: 1 | BQ49: 1 | BT49: 1 | BU49: 1 | BV49: =MAX(N49,AG49) -> 2050 | BW49: =IF(J49="Targets Set",1,"")
A50: 212 | B50: Barclays | C50: Financial services | D50: United Kingdom | E50: Europe | F50: Y | G50: 2019 | H50: 2025 | I50: N | Q50: N | T50: N | AC50: V | AD50: scope 1, 2 and 3 | AE50: Net Zero | AF50: V | AG50: 2050 | AH50: 2020 | AL50: U | AV50: =IF(AND(Q50<>"N",Q50<>"G",AZ50<>1),1,"") | AY50: 1 | AZ50: 1 | BF50: 1 | BH50: 1 | BI50: 1 | BK50: 1 | BN50: =MAX(BH50,BD50,AZ50,AV50) -> 1 | BP50: 1 | BQ50: 1 | BT50: 1 | BU50: 1 | BV50: =MAX(N50,AG50) -> 2050 | BW50: =IF(J50="Targets Set",1,"")
A51: 172 | B51: BASF | C51: Chemicals | D51: Germany | E51: Europe | F51: N | I51: N | Q51: N | T51: N | AC51: C | AD51: scope 1, 2, and 3.1 (partial scope 3) | AE51: Net-Zero CO2Â emissions | AF51: C | AG51: 2050 | AH51: 2021 | AL51: Y | AM51: 2023 | AN51: Y | AV51: =IF(AND(Q51<>"N",Q51<>"G",AZ51<>1),1,"") | AY51: 1 | AZ51: 1 | BI51: 1 | BK51: 1 | BL51: 1 | BN51: =MAX(BH51,BD51,AZ51,AV51) -> 1 | BQ51: 1 | BV51: =MAX(N51,AG51) -> 2050 | BW51: =IF(J51="Targets Set",1,"")
A52: 286 | B52: Bayer | C52: Health care and pharmaceuticals | D52: Germany | E52: Europe | F52: N | I52: Y | J52: Targets Set | K52: 1.5Â°C | L52: 2029 | M52: Yes | O52: 44044 | P52: 2020 | Q52: C | R52: operations | S52: climate neutral | T52: C | U52: 2030 | V52: 2019 | Z52: Y | AA52: 2023 | AB52: Y | AC52: V | AD52: entire value chain | AE52: Net Zero | AF52: V | AG52: 2050 | AH52: 2023 | AL52: Y | AR52: 1 | AT52: 1 | AU52: 1 | AV52: =IF(AND(Q52<>"N",Q52<>"G",AZ52<>1),1,"") | AY52: 1 | AZ52: 1 | BB52: 1 | BD52: 1 | BI52: 1 | BJ52: 1 | BK52: 1 | BL52: 1 | BN52: =MAX(BH52,BD52,AZ52,AV52) -> 1 | BP52: 1 | BQ52: 1 | BT52: 1 | BU52: 1 | BV52: =MAX(N52,AG52) -> 2050 | BW52: =IF(J52="Targets Set",1,"") -> 1
A53: 192 | B53: Beijing Automotive Group | C53: Automotive | D53: China | E53: Asia | F53: N | I53: N | Q53: N | T53: N | AC53: N | AF53: N | AV53: =IF(AND(Q53<>"N",Q53<>"G",AZ53<>1),1,"") | BN53: =MAX(BH53,BD53,AZ53,AV53) -> 0 | BW53: =IF(J53="Targets Set",1,"")
A54: 458 | B54: Beijing Jianlong Heavy Industry Group | C54: Metals and mining | D54: China | E54: Asia | F54: N | I54: N | Q54: N | T54: N | AC54: N | AF54: N | AV54: =IF(AND(Q54<>"N",Q54<>"G",AZ54<>1),1,"") | BN54: =MAX(BH54,BD54,AZ54,AV54) -> 0 | BW54: =IF(J54="Targets Set",1,"")
A55: 9 | B55: Berkshire Hathaway | C55: Financial services | D55: United States of America (USA) | E55: North America | F55: N | I55: N | Q55: N | T55: N | AC55: N | AF55: N | AV55: =IF(AND(Q55<>"N",Q55<>"G",AZ55<>1),1,"") | BN55: =MAX(BH55,BD55,AZ55,AV55) -> 0 | BW55: =IF(J55="Targets Set",1,"")
A56: 352 | B56: Best Buy | C56: Retail | D56: United States of America (USA) | E56: North America | F56: N | I56: Y | J56: Targets Set | K56: 1.5Â°C | L56: 2030 | M56: No | O56: 43647 | P56: 2019 | Q56: C | R56: operational carbon usage | S56: carbon neutrality | T56: C | U56: 2040 | V56: 2019 | Z56: Y | AB56: Y | AC56: C | AD56: our business | AE56: Net-Zero annual carbon emissions by 2040 | AF56: C | AG56: 2040 | AH56: 2020 | AL56: Y | AS56: 1 | AT56: 1 | AU56: 1 | AV56: =IF(AND(Q56<>"N",Q56<>"G",AZ56<>1),1,"") | AY56: 1 | AZ56: 1 | BB56: 1 | BD56: 1 | BI56: 1 | BK56: 1 | BL56: 1 | BN56: =MAX(BH56,BD56,AZ56,AV56) -> 1 | BP56: 1 | BQ56: 1 | BV56: =MAX(N56,AG56) -> 2040 | BW56: =IF(J56="Targets Set",1,"") -> 1
A57: 258 | B57: Bharat Petroleum | C57: Oil and gas | D57: India | E57: Asia | F57: N | I57: N | Q57: N | T57: N | AC57: C | AD57: Scope 1 and 2 | AE57: Net Zero | AF57: C | AG57: 2040 | AH57: 2021 | AL57: Y | AV57: =IF(AND(Q57<>"N",Q57<>"G",AZ57<>1),1,"") | AY57: 1 | AZ57: 1 | BI57: 1 | BK57: 1 | BL57: 1 | BN57: =MAX(BH57,BD57,AZ57,AV57) -> 1 | BQ57: 1 | BV57: =MAX(N57,AG57) -> 2040 | BW57: =IF(J57="Targets Set",1,"")
A58: 268 | B58: BHP Group | C58: Metals and mining | D58: Australia | E58: Other | F58: N | I58: N | Q58: N | T58: N | AC58: C | AD58: operations | AE58: Net-Zero | AF58: C | AG58: 2050 | AH58: 2020 | AL58: Y | AO58: Y | AP58: N | AV58: =IF(AND(Q58<>"N",Q58<>"G",AZ58<>1),1,"") | AY58: 1 | AZ58: 1 | BI58: 1 | BK58: 1 | BL58: 1 | BN58: =MAX(BH58,BD58,AZ58,AV58) -> 1 | BQ58: 1 | BV58: =MAX(N58,AG58) -> 2050 | BW58: =IF(J58="Targets Set",1,"")
A59: 41 | B59: BMW Group | C59: Automotive | D59: Germany | E59: Europe | F59: Y | G59: 2015 | H59: 2050 | I59: Y | J59: Targets Set | K59: 1.5Â°C/Well-below 2Â°C | L59: 2030 | M59: Yes | O59: 44593 | P59: 2022 | Q59: F | R59: asset portfolio | S59: carbon neutrality | T59: F | U59: 2050 | V59: 2020 | Z59: Y | AB59: Y | AC59: V | AD59: entire value chain | AE59: Net Zero | AF59: V | AG59: 2050 | AH59: 2022 | AL59: U | AO59: C | AP59: N | AS59: 1 | AT59: 1 | AU59: 1 | AV59: =IF(AND(Q59<>"N",Q59<>"G",AZ59<>1),1,"") | AY59: 1 | AZ59: 1 | BB59: 1 | BD59: 1 | BG59: 1 | BH59: 1 | BI59: 1 | BK59: 1 | BL59: 1 | BN59: =MAX(BH59,BD59,AZ59,AV59) -> 1 | BP59: 1 | BQ59: 1 | BT59: 1 | BU59: 1 | BV59: =MAX(N59,AG59) -> 2050 | BW59: =IF(J59="Targets Set",1,"") -> 1
A60: 64 | B60: BNP Paribas | C60: Financial services | D60: France | E60: Europe | F60: N | I60: N | J60: Committed | L60: 2030 | M60: No | O60: 42461 | P60: 2016 | Q60: F | R60: account credit and investment activities | S60: carbon neutrality | T60: F | U60: 2050 | V60: 2015 | Z60: Y | AB60: Y | AC60: I | AF60: I | AS60: 1 | AT60: 1 | AU60: 1 | AV60: =IF(AND(Q60<>"N",Q60<>"G",AZ60<>1),1,"") -> 1 | BB60: 1 | BD60: 1 | BI60: 1 | BK60: 1 | BL60: 1 | BN60: =MAX(BH60,BD60,AZ60,AV60) -> 1 | BP60: 1 | BQ60: 1 | BW60: =IF(J60="Targets Set",1,"")
A61: 159 | B61: Boeing | C61: Aerospace and defense | D61: United States of America (USA) | E61: North America | F61: N | I61: N | Q61: C | R61: scope 1 and 2 GHG emissions | S61: mitigated | T61: C | U61: 2020 | V61: 2020 | Z61: Y | AA61: 2024 | AB61: Y | AC61: N | AF61: N | AO61: C | AQ61: 1 | AT61: 1 | AU61: 1 | AV61: =IF(AND(Q61<>"N",Q61<>"G",AZ61<>1),1,"") -> 1 | BI61: 1 | BJ61: 1 | BK61: 1 | BL61: 1 | BN61: =MAX(BH61,BD61,AZ61,AV61) -> 1 | BO61: 1 | BP61: 1 | BQ61: 1 | BW61: =IF(J61="Targets Set",1,"")
A62: 105 | B62: Bosch Group | C62: Automotive | D62: Germany | E62: Europe | F62: N | I62: N | Q62: C | R62: scope 1 & 2 | S62: carbon neutral | T62: C | U62: 2020 | V62: 2019 | Z62: Y | AA62: 2023 | AB62: Y | AC62: N | AF62: N | AQ62: 1 | AT62: 1 | AU62: 1 | AV62: =IF(AND(Q62<>"N",Q62<>"G",AZ62<>1),1,"") -> 1 | BI62: 1 | BJ62: 1 | BK62: 1 | BL62: 1 | BN62: =MAX(BH62,BD62,AZ62,AV62) -> 1 | BO62: 1 | BP62: 1 | BQ62: 1 | BW62: =IF(J62="Targets Set",1,"")
A63: 225 | B63: Bouygues | C63: Engineering and construction | D63: France | E63: Europe | F63: N | I63: Y | J63: Targets Set | K63: 1.5Â°C | L63: 2030 | M63: No | O63: 44593 | P63: 2022 | Q63: N | T63: N | AC63: N | AF63: N | AO63: V | AV63: =IF(AND(Q63<>"N",Q63<>"G",AZ63<>1),1,"") | BB63: 1 | BD63: 1 | BN63: =MAX(BH63,BD63,AZ63,AV63) -> 1 | BP63: 1 | BQ63: 1 | BW63: =IF(J63="Targets Set",1,"") -> 1
A64: 25 | B64: BP | C64: Oil and gas | D64: United Kingdom | E64: Europe | F64: N | I64: N | Q64: N | T64: N | AC64: V | AD64: operations, production, and sold energy products | AE64: Net Zero | AF64: V | AG64: 2050 | AH64: 2020 | AL64: Y | AM64: 2024 | AN64: Y | AV64: =IF(AND(Q64<>"N",Q64<>"G",AZ64<>1),1,"") | AY64: 1 | AZ64: 1 | BI64: 1 | BK64: 1 | BL64: 1 | BN64: =MAX(BH64,BD64,AZ64,AV64) -> 1 | BQ64: 1 | BT64: 1 | BU64: 1 | BV64: =MAX(N64,AG64) -> 2050 | BW64: =IF(J64="Targets Set",1,"")
A65: 342 | B65: Bristol-Myers Squibb | C65: Health care and pharmaceuticals | D65: United States of America (USA) | E65: North America | F65: N | I65: Y | J65: Targets Set | K65: 1.5°C | L65: 2028 | M65: Yes | N65: 2050 | O65: 01/07/2024 | P65: 2024 | Q65: N | T65: N | AC65: V | AD65: Scopes 1, 2 and 3 | AE65: Net-Zero emission | AF65: V | AG65: 2050 | AH65: 2024 | AL65: Y | AV65: =IF(AND(Q65<>"N",Q65<>"G",AZ65<>1),1,"") | AY65: 1 | AZ65: 1 | BB65: 1 | BD65: 1 | BI65: 1 | BK65: 1 | BL65: 1 | BN65: =MAX(BH65,BD65,AZ65,AV65) -> 1 | BP65: 1 | BQ65: 1 | BT65: 1 | BU65: 1 | BV65: =MAX(N65,AG65) -> 2050 | BW65: =IF(J65="Targets Set",1,"") -> 1
A66: 464 | B66: British American Tobacco | C66: Food, beverages and agriculture | D66: United Kingdom | E66: Europe | F66: N | I66: Y | J66: Targets Set | K66: 1.5Â°C | L66: 2030 | M66: No | O66: 44743 | P66: 2022 | Q66: N | T66: N | AC66: V | AD66: Value Chain | AE66: Net Zero GHG Emissions | AF66: V | AG66: 2050 | AH66: 2021 | AL66: Y | AV66: =IF(AND(Q66<>"N",Q66<>"G",AZ66<>1),1,"") | AY66: 1 | AZ66: 1 | BB66: 1 | BD66: 1 | BI66: 1 | BK66: 1 | BL66: 1 | BN66: =MAX(BH66,BD66,AZ66,AV66) -> 1 | BP66: 1 | BQ66: 1 | BT66: 1 | BU66: 1 | BV66: =MAX(N66,AG66) -> 2050 | BW66: =IF(J66="Targets Set",1,"") -> 1
A67: 427 | B67: Broadcom | C67: Technology | D67: United States of America (USA) | E67: North America | F67: N | I67: N | J67: Committed | L67: 2030 | M67: No | O67: 45323 | P67: 2024 | Q67: N | T67: N | AC67: N | AF67: N | AV67: =IF(AND(Q67<>"N",Q67<>"G",AZ67<>1),1,"") | BB67: 1 | BD67: 1 | BN67: =MAX(BH67,BD67,AZ67,AV67) -> 1 | BP67: 1 | BQ67: 1 | BW67: =IF(J67="Targets Set",1,"")
A68: 113 | B68: Brookfield | C68: Financial services | D68: Canada | E68: North America | F68: N | I68: N | Q68: N | T68: N | AC68: F | AD68: assets we manage | AE68: Net Zero emissions | AF68: F | AG68: 2050 | AH68: 2022 | AL68: U | AV68: =IF(AND(Q68<>"N",Q68<>"G",AZ68<>1),1,"") | AY68: 1 | AZ68: 1 | BI68: 1 | BK68: 1 | BN68: =MAX(BH68,BD68,AZ68,AV68) -> 1 | BQ68: 1 | BT68: 1 | BU68: 1 | BV68: =MAX(N68,AG68) -> 2050 | BW68: =IF(J68="Targets Set",1,"")
A69: 230 | B69: Bunge | C69: Food, beverages and agriculture | D69: United States of America (USA) | E69: North America | F69: N | I69: Y | J69: Targets Set | K69: Well-below 2Â°C | L69: 2030 | M69: No | O69: 44501 | P69: 2021 | Q69: N | T69: N | AC69: N | AF69: N | AV69: =IF(AND(Q69<>"N",Q69<>"G",AZ69<>1),1,"") | BB69: 1 | BD69: 1 | BN69: =MAX(BH69,BD69,AZ69,AV69) -> 1 | BP69: 1 | BQ69: 1 | BW69: =IF(J69="Targets Set",1,"") -> 1
A70: 143 | B70: BYD | C70: Automotive | D70: China | E70: Asia | F70: N | I70: N | J70: Committed | L70: 2030 | M70: Yes | O70: 45505 | P70: 2024 | Q70: G | R70: company | S70: carbon neutral | T70: G | U70: 2060 | V70: 2021 | AC70: N | AF70: N | AO70: Y | AP70: N | AV70: =IF(AND(Q70<>"N",Q70<>"G",AZ70<>1),1,"") | BB70: 1 | BD70: 1 | BN70: =MAX(BH70,BD70,AZ70,AV70) -> 1 | BP70: 1 | BQ70: 1 | BW70: =IF(J70="Targets Set",1,"")
A71: 334 | B71: Caixa Economica Federal | C71: Financial services | D71: Brazil | E71: Other | F71: N | I71: N | Q71: N | T71: N | AC71: N | AF71: N | AV71: =IF(AND(Q71<>"N",Q71<>"G",AZ71<>1),1,"") | BN71: =MAX(BH71,BD71,AZ71,AV71) -> 0 | BW71: =IF(J71="Targets Set",1,"")
A72: 367 | B72: Canadian Imperial Bank of Commerce | C72: Financial services | D72: Canada | E72: North America | F72: N | I72: N | Q72: C | R72: operations | S72: carbon neutrality | T72: C | U72: 2024 | V72: 2021 | Z72: Y | AA72: 2023 | AB72: Y | AC72: C+F | AD72: operational and financing activities | AE72: Net Zero | AF72: C+F | AG72: 2050 | AH72: 2021 | AL72: Y | AM72: 2023 | AN72: Y | AR72: 1 | AT72: 1 | AU72: 1 | AV72: =IF(AND(Q72<>"N",Q72<>"G",AZ72<>1),1,"") | AY72: 1 | AZ72: 1 | BI72: 1 | BJ72: 1 | BK72: 1 | BL72: 1 | BN72: =MAX(BH72,BD72,AZ72,AV72) -> 1 | BP72: 1 | BQ72: 1 | BT72: 1 | BU72: 1 | BV72: =MAX(N72,AG72) -> 2050 | BW72: =IF(J72="Targets Set",1,"")
A73: 304 | B73: Capital One Financial | C73: Financial services | D73: United States of America (USA) | E73: North America | F73: Y | G73: 2018 | H73: 2021 | I73: N | Q73: C | R73: Scope 1 and 2 emissions and business travel emissions in Scope 3 | S73: carbon neutral | T73: C | U73: 2030 | V73: 2017 | Z73: N | AA73: 2023 | AB73: N | AC73: N | AF73: N | AR73: 1 | AT73: 1 | AU73: 1 | AV73: =IF(AND(Q73<>"N",Q73<>"G",AZ73<>1),1,"") -> 1 | BE73: 1 | BH73: 1 | BI73: 1 | BJ73: 1 | BK73: 1 | BM73: 1 | BN73: =MAX(BH73,BD73,AZ73,AV73) -> 1 | BO73: 1 | BP73: 1 | BQ73: 1 | BW73: =IF(J73="Targets Set",1,"")
A74: 27 | B74: Cardinal Health | C74: Retail | D74: United States of America (USA) | E74: North America | F74: N | I74: Y | J74: Targets Set | K74: 1.5Â°C | L74: 2030 | M74: No | O74: 45352 | P74: 2024 | Q74: N | T74: N | AC74: N | AF74: N | AV74: =IF(AND(Q74<>"N",Q74<>"G",AZ74<>1),1,"") | BB74: 1 | BD74: 1 | BN74: =MAX(BH74,BD74,AZ74,AV74) -> 1 | BP74: 1 | BQ74: 1 | BW74: =IF(J74="Targets Set",1,"") -> 1
A75: 122 | B75: Carrefour | C75: Retail | D75: France | E75: Europe | F75: N | I75: Y | J75: Targets Set | K75: Well-below 2Â°C | L75: 2030 | M75: No | O75: 43983 | P75: 2020 | Q75: C | R75: direct emissions | S75: carbon neutrality | T75: C | U75: 2040 | V75: 2021 | Z75: U | AB75: Y | AC75: N | AF75: N | AS75: 1 | AT75: 1 | AU75: 1 | AV75: =IF(AND(Q75<>"N",Q75<>"G",AZ75<>1),1,"") -> 1 | BB75: 1 | BD75: 1 | BI75: 1 | BK75: 1 | BN75: =MAX(BH75,BD75,AZ75,AV75) -> 1 | BP75: 1 | BQ75: 1 | BW75: =IF(J75="Targets Set",1,"") -> 1
A76: 199 | B76: Caterpillar | C76: Industrial goods | D76: United States of America (USA) | E76: North America | F76: N | I76: N | Q76: N | T76: N | AC76: N | AF76: N | AO76: C | AV76: =IF(AND(Q76<>"N",Q76<>"G",AZ76<>1),1,"") | BN76: =MAX(BH76,BD76,AZ76,AV76) -> 0 | BW76: =IF(J76="Targets Set",1,"")
A77: 18 | B77: Cencora | C77: Retail | D77: United States of America (USA) | E77: North America | F77: N | I77: Y | J77: Targets Set | K77: 1.5Â°C | L77: 2026 | M77: No | O77: 45231 | P77: 2023 | Q77: N | T77: N | AC77: N | AF77: N | AV77: =IF(AND(Q77<>"N",Q77<>"G",AZ77<>1),1,"") | BB77: 1 | BD77: 1 | BN77: =MAX(BH77,BD77,AZ77,AV77) -> 1 | BP77: 1 | BQ77: 1 | BW77: =IF(J77="Targets Set",1,"") -> 1
A78: 390 | B78: Cenovus Energy | C78: Metals and mining | D78: Canada | E78: North America | F78: N | I78: N | Q78: N | T78: N | AC78: C | AD78: operations | AE78: Net Zero emissions | AF78: C | AG78: 2050 | AH78: 2020 | AL78: U | AO78: Y | AV78: =IF(AND(Q78<>"N",Q78<>"G",AZ78<>1),1,"") | AY78: 1 | AZ78: 1 | BI78: 1 | BK78: 1 | BN78: =MAX(BH78,BD78,AZ78,AV78) -> 1 | BQ78: 1 | BV78: =MAX(N78,AG78) -> 2050 | BW78: =IF(J78="Targets Set",1,"")
A79: 46 | B79: Centene | C79: Health care and pharmaceuticals | D79: United States of America (USA) | E79: North America | F79: N | I79: N | Q79: N | T79: N | AC79: N | AF79: N | AO79: N | AP79: N | AV79: =IF(AND(Q79<>"N",Q79<>"G",AZ79<>1),1,"") | BN79: =MAX(BH79,BD79,AZ79,AV79) -> 0 | BW79: =IF(J79="Targets Set",1,"")
A80: 485 | B80: Centrica | C80: Energy and utilities | D80: United Kingdom | E80: Europe | F80: N | I80: N | Q80: N | T80: N | AC80: C, V | AD80: business (scope 1 and 2), customers (scope 1, 2, and 3) | AE80: Net Zero | AF80: C | AG80: 2045 | AH80: 2021 | AI80: V | AJ80: 2050 | AK80: 2021 | AL80: U | AM80: 2023 | AN80: Y | AV80: =IF(AND(Q80<>"N",Q80<>"G",AZ80<>1),1,"") | AY80: 1 | AZ80: 1 | BI80: 1 | BK80: 1 | BN80: =MAX(BH80,BD80,AZ80,AV80) -> 1 | BQ80: 1 | BT80: 1 | BU80: 1 | BV80: =MAX(N80,AG80) -> 2045 | BW80: =IF(J80="Targets Set",1,"")
A81: 420 | B81: CFE | C81: Industrial goods | D81: Mexico | E81: North America | F81: N | I81: N | Q81: N | T81: N | AC81: N | AF81: N | AV81: =IF(AND(Q81<>"N",Q81<>"G",AZ81<>1),1,"") | BN81: =MAX(BH81,BD81,AZ81,AV81) -> 0 | BW81: =IF(J81="Targets Set",1,"")
A82: 255 | B82: Charter Communications | C82: Telecommunications and media | D82: United States of America (USA) | E82: North America | F82: N | I82: N | Q82: C | R82: operations | S82: carbon neutral | T82: C | U82: 2035 | V82: 2020 | Z82: U | AB82: Y | AC82: N | AF82: N | AS82: 1 | AT82: 1 | AU82: 1 | AV82: =IF(AND(Q82<>"N",Q82<>"G",AZ82<>1),1,"") -> 1 | BI82: 1 | BK82: 1 | BN82: =MAX(BH82,BD82,AZ82,AV82) -> 1 | BQ82: 1 | BW82: =IF(J82="Targets Set",1,"")
A83: 385 | B83: Chery Holding Group | C83: Automotive | D83: China | E83: Asia | F83: N | I83: N | Q83: N | T83: N | AC83: N | AF83: N | AV83: =IF(AND(Q83<>"N",Q83<>"G",AZ83<>1),1,"") | BN83: =MAX(BH83,BD83,AZ83,AV83) -> 0 | BW83: =IF(J83="Targets Set",1,"")
A84: 29 | B84: Chevron | C84: Oil and gas | D84: United States of America (USA) | E84: North America | F84: N | I84: N | Q84: N | T84: N | AC84: C | AD84: upstream scope 1 and 2 | AE84: Net Zero | AF84: C | AG84: 2050 | AH84: 2021 | AL84: Y | AM84: 2023 | AN84: Y | AV84: =IF(AND(Q84<>"N",Q84<>"G",AZ84<>1),1,"") | AY84: 1 | AZ84: 1 | BI84: 1 | BK84: 1 | BL84: 1 | BN84: =MAX(BH84,BD84,AZ84,AV84) -> 1 | BQ84: 1 | BV84: =MAX(N84,AG84) -> 2050 | BW84: =IF(J84="Targets Set",1,"")
A85: 44 | B85: China Baowu Steel Group | C85: Metals and mining | D85: China | E85: Asia | F85: N | I85: N | Q85: C | R85: undefined | S85: carbon neutrality | T85: C | U85: 2050 | V85: 2020 | Z85: U | AB85: Y | AC85: N | AF85: N | AS85: 1 | AT85: 1 | AU85: 1 | AV85: =IF(AND(Q85<>"N",Q85<>"G",AZ85<>1),1,"") -> 1 | BI85: 1 | BK85: 1 | BN85: =MAX(BH85,BD85,AZ85,AV85) -> 1 | BQ85: 1 | BW85: =IF(J85="Targets Set",1,"")
A86: 63 | B86: China Communications Construction | C86: Engineering and construction | D86: China | E86: Asia | F86: N | I86: N | Q86: G | R86: global products and operations | S86: carbon neutral | T86: G | U86: 2060 | V86: 2023 | AC86: N | AF86: N | AV86: =IF(AND(Q86<>"N",Q86<>"G",AZ86<>1),1,"") | BN86: =MAX(BH86,BD86,AZ86,AV86) -> 0 | BW86: =IF(J86="Targets Set",1,"")
A87: 30 | B87: China Construction Bank | C87: Financial services | D87: China | E87: Asia | F87: N | I87: N | Q87: G | R87: undefined | S87: carbon neutrality | T87: G | U87: 2060 | V87: 2021 | AC87: N | AF87: N | AV87: =IF(AND(Q87<>"N",Q87<>"G",AZ87<>1),1,"") | BN87: =MAX(BH87,BD87,AZ87,AV87) -> 0 | BW87: =IF(J87="Targets Set",1,"")
A88: 418 | B88: China Datang | C88: Energy and utilities | D88: China | E88: Asia | F88: N | I88: N | Q88: G | R88: undefined | S88: carbon neutral | T88: G | U88: 2060 | V88: 2021 | AC88: N | AF88: N | AV88: =IF(AND(Q88<>"N",Q88<>"G",AZ88<>1),1,"") | BN88: =MAX(BH88,BD88,AZ88,AV88) -> 0 | BW88: =IF(J88="Targets Set",1,"")
A89: 435 | B89: China Electronics | C89: Industrial goods | D89: China | E89: Asia | F89: N | I89: N | Q89: N | T89: N | AC89: N | AF89: N | AV89: =IF(AND(Q89<>"N",Q89<>"G",AZ89<>1),1,"") | BN89: =MAX(BH89,BD89,AZ89,AV89) -> 0 | BW89: =IF(J89="Targets Set",1,"")
A90: 253 | B90: China Electronics Technology Group | C90: Aerospace and defense | D90: China | E90: Asia | F90: N | I90: N | Q90: N | T90: N | AC90: N | AF90: N | AO90: N | AP90: N | AV90: =IF(AND(Q90<>"N",Q90<>"G",AZ90<>1),1,"") | BN90: =MAX(BH90,BD90,AZ90,AV90) -> 0 | BW90: =IF(J90="Targets Set",1,"")
A91: 239 | B91: China Energy Engineering Group | C91: Engineering and construction | D91: China | E91: Asia | F91: N | I91: N | Q91: G | R91: undefined | S91: carbon neutral | T91: G | U91: 2060 | V91: 2022 | AC91: N | AF91: N | AV91: =IF(AND(Q91<>"N",Q91<>"G",AZ91<>1),1,"") | BN91: =MAX(BH91,BD91,AZ91,AV91) -> 0 | BW91: =IF(J91="Targets Set",1,"")
A92: 84 | B92: China Energy Investment | C92: Metals and mining | D92: China | E92: Asia | F92: N | I92: N | Q92: G | R92: undefined | S92: carbon neutrality | T92: G | U92: 2060 | V92: 2022 | AC92: N | AF92: N | AV92: =IF(AND(Q92<>"N",Q92<>"G",AZ92<>1),1,"") | BN92: =MAX(BH92,BD92,AZ92,AV92) -> 0 | BW92: =IF(J92="Targets Set",1,"")
A93: 129 | B93: China FAW Group | C93: Automotive | D93: China | E93: Asia | F93: N | I93: N | Q93: G | R93: undefined | S93: carbon neutrality | T93: G | U93: 2060 | V93: 2022 | AC93: N | AF93: N | AV93: =IF(AND(Q93<>"N",Q93<>"G",AZ93<>1),1,"") | BN93: =MAX(BH93,BD93,AZ93,AV93) -> 0 | BW93: =IF(J93="Targets Set",1,"")
A94: 336 | B94: China Huadian | C94: Energy and utilities | D94: China | E94: Asia | F94: N | I94: N | Q94: G | R94: undefined | S94: carbon neutrality | T94: G | U94: 2060 | V94: 2021 | AC94: N | AF94: N | AV94: =IF(AND(Q94<>"N",Q94<>"G",AZ94<>1),1,"") | BN94: =MAX(BH94,BD94,AZ94,AV94) -> 0 | BW94: =IF(J94="Targets Set",1,"")
A95: 238 | B95: China Huaneng Group | C95: Energy and utilities | D95: China | E95: Asia | F95: N | I95: N | Q95: G | R95: undefined | S95: carbon neutrality | T95: G | U95: 2060 | V95: 2021 | AC95: N | AF95: N | AV95: =IF(AND(Q95<>"N",Q95<>"G",AZ95<>1),1,"") | BN95: =MAX(BH95,BD95,AZ95,AV95) -> 0 | BW95: =IF(J95="Targets Set",1,"")
A96: 59 | B96: China Life Insurance | C96: Financial services | D96: China | E96: Asia | F96: N | I96: N | Q96: N | T96: N | AC96: N | AF96: N | AO96: N | AP96: N | AV96: =IF(AND(Q96<>"N",Q96<>"G",AZ96<>1),1,"") | BN96: =MAX(BH96,BD96,AZ96,AV96) -> 0 | BW96: =IF(J96="Targets Set",1,"")
A97: 179 | B97: China Merchants Bank | C97: Financial services | D97: China | E97: Asia | F97: N | I97: N | Q97: G | R97: undefined | S97: carbon neutrality | T97: G | U97: 2060 | V97: 2021 | AC97: N | AF97: N | AO97: N | AP97: N | AV97: =IF(AND(Q97<>"N",Q97<>"G",AZ97<>1),1,"") | BN97: =MAX(BH97,BD97,AZ97,AV97) -> 0 | BW97: =IF(J97="Targets Set",1,"")
A98: 69 | B98: China Minmetals | C98: Metals and mining | D98: China | E98: Asia | F98: N | I98: N | Q98: G | R98: undefined | S98: carbon neutral | T98: G | U98: 2060 | V98: 2022 | AC98: N | AF98: N | AV98: =IF(AND(Q98<>"N",Q98<>"G",AZ98<>1),1,"") | BN98: =MAX(BH98,BD98,AZ98,AV98) -> 0 | BW98: =IF(J98="Targets Set",1,"")
A99: 351 | B99: China Minsheng Banking | C99: Financial services | D99: China | E99: Asia | F99: N | I99: N | Q99: G | R99: undefined | S99: carbon neutrality | T99: G | U99: 2060 | V99: 2021 | AC99: N | AF99: N | AV99: =IF(AND(Q99<>"N",Q99<>"G",AZ99<>1),1,"") | BN99: =MAX(BH99,BD99,AZ99,AV99) -> 0 | BW99: =IF(J99="Targets Set",1,"")
A100: 55 | B100: China Mobile Communications | C100: Telecommunications and media | D100: China | E100: Asia | F100: N | I100: N | Q100: G | R100: undefined | S100: carbon neutrality | T100: G | U100: 2060 | V100: 2021 | AC100: N | AF100: N | AP100: N | AV100: =IF(AND(Q100<>"N",Q100<>"G",AZ100<>1),1,"") | BN100: =MAX(BH100,BD100,AZ100,AV100) -> 0 | BW100: =IF(J100="Targets Set",1,"")
A101: 483 | B101: China National Aviation Fuel Group | C101: Oil and gas | D101: China | E101: Asia | F101: N | I101: N | Q101: N | T101: N | AC101: N | AF101: N | AV101: =IF(AND(Q101<>"N",Q101<>"G",AZ101<>1),1,"") | BN101: =MAX(BH101,BD101,AZ101,AV101) -> 0 | BW101: =IF(J101="Targets Set",1,"")
...

Sheet 2023
A1: Company information - source: Fortune, accessed 2 August 2023 https://fortune.com/global500/ | G1: RE100 - source: RE100 (The Climate Group), 2021 Progress and Insights Annual Report https://www.there100.org/stepping-re100-gathers-speed-challenging-markets and member page https://www.there100.org/re100-members accessed on 7 August 2023 | J1: Science Based Targets - source: Science Based Targets initiative, accessed 7 August 2023 https://sciencebasedtargets.org/download/excel | T1: Carbon neutral - source: desk-based research undertaken by Climate Impact Partners conducted between June and August 2023. See methodology section of full report for more details. Download full report via https://www.climateimpact.com/news-insights/fortune-global-500-climate-commitments/ | X1: {=IF(W1="", "", IFERROR(MAX(--_xlfn.TEXTSPLIT(W1,"+")), W1))} | Z1: Net zero - source: desk-based research undertaken by Climate Impact Partners conducted between June and August 2023. See methodology section of full report for more details. Download full report via https://www.climateimpact.com/news-insights/fortune-global-500-climate-commitments/ | AD1: {=IF(AC1="", "", IFERROR(MAX(--_xlfn.TEXTSPLIT(AC1,"+")), AC1))}
A2: Rank | B2: Company name | C2: Headquarters | D2: Sector | E2: Revenue ($M) | F2: Profits ($M) | G2: RE100 goal | H2: From | I2: Announced | J2: Target status | K2: Target classification (near term) - temp | L2: Target year (near term) (earlier of the two dates if there were two) (where target status was committed, 2030) | M2: Long term - Target Status | N2: Long term - Target Classification | O2: Long term - Target Year | P2: Net zero committed (SBTi) (Y = yes, N = no) | Q2: SBTi NZ approved | R2: Net zero year (SBTi) | S2: Commitment year | T2: Scope of target | U2: Scope of target in their own words | V2: From | W2: year broken down | X2: Announced2 | Y2: Source | Z2: Scope of target3 | AA2: Scope of target in their own words4 | AB2: From 5 | AC2: From 6 | AD2: CN | AE2: NZ | AF2: SBTi | AG2: CC | AH2: REGION | AI2: SECTOR7 | AJ2: NZ year | AK2: at least one of the actions | AQ2: SBTi short term | AT2: RE100 | AW2: Carbon Neutral | BA2: NC overlap | BC2: Net Zero | BF2: sum | BG2: CC overlap
A3: 1 | B3: Walmart | C3: United States of America (USA) | D3: Retailing | E3: $611,289 | F3: $11,680 | G3: Y | H3: 2035 | I3: 2015 | J3: T | K3: 1.5°C | L3: 2025 | P3: Y | Q3: c | S3: 2016 | W3: {=IF(V3="", "", IFERROR(MAX(--_xlfn.TEXTSPLIT(V3,"+")), V3))} | Z3: C | AA3: global operations | AB3: 2040 | AC3: {=IF(AB3="", "", IFERROR(MAX(--_xlfn.TEXTSPLIT(AB3,"+")), AB3))} -> 2040 | AD3: =IF(AND(Table1[[#This Row],[year broken down ]]<>"",Table1[[#This Row],[Scope of target]]<>"G",AE3=""),1,"") | AE3: =IF(OR(Table1[[#This Row],[Net zero year (SBTi)]]<>"",Table1[[#This Row],[From 6]]<>""),1,"") -> 1 | AF3: =IF(OR(Table1[[#This Row],[SBTi NZ approved]]="s",Table1[[#This Row],[Target status]]="T"),1,"") -> 1 | AH3: =_xlfn.XLOOKUP(C3,ref!A:A,ref!B:B, "Other") -> North America | AI3: =_xlfn.XLOOKUP(D3,ref!D:D,ref!E:E) -> Retail | AJ3: =IF(Table1[[#This Row],[NZ]]=1, MAX(Table1[[#This Row],[From 6]], Table1[[#This Row],[Net zero year (SBTi)]]), "") -> 2040 | AK3: =IF(OR($AD3<>"",$AE3<>"",$AF3<>"",$G3="Y"),1,0) -> 1 | AP3: Sector | AQ3: <=2023 | AR3: 2024-2030 | AS3: 2031-2060 | AT3: <=2023 | AU3: 2024-2030 | AV3: 2031-2060 | AW3: <=2023 | AX3: 2024-2030 | AY3: 2031-2060 | AZ3: <=2023 | BA3: 2024-2030 | BB3: 2031-2060 | BC3: <=2023 | BD3: 2024-2030 | BE3: 2031-2060 | BF3: no overlap | BG3: Yes | BH3: No | BI3: Unspecified
A4: 2 | B4: Saudi Aramco | C4: Saudi Arabia | D4: Energy | E4: $603,651 | F4: $159,069 | W4: {=IF(V4="", "", IFERROR(MAX(--_xlfn.TEXTSPLIT(V4,"+")), V4))} | Z4: C | AA4: across wholly-owned operated assets | AB4: 2050 | AC4: {=IF(AB4="", "", IFERROR(MAX(--_xlfn.TEXTSPLIT(AB4,"+")), AB4))} -> 2050 | AD4: =IF(AND(Table1[[#This Row],[year broken down ]]<>"",Table1[[#This Row],[Scope of target]]<>"G",AE4=""),1,"") | AE4: =IF(OR(Table1[[#This Row],[Net zero year (SBTi)]]<>"",Table1[[#This Row],[From 6]]<>""),1,"") -> 1 | AF4: =IF(OR(Table1[[#This Row],[SBTi NZ approved]]="s",Table1[[#This Row],[Target status]]="T"),1,"") | AH4: =_xlfn.XLOOKUP(C4,ref!A:A,ref!B:B, "Other") -> Other | AI4: =_xlfn.XLOOKUP(D4,ref!D:D,ref!E:E) -> Energy and utilities | AJ4: =IF(Table1[[#This Row],[NZ]]=1, MAX(Table1[[#This Row],[From 6]], Table1[[#This Row],[Net zero year (SBTi)]]), "") -> 2050 | AK4: =IF(OR($AD4<>"",$AE4<>"",$AF4<>"",$G4="Y"),1,0) -> 1 | AP4: Aerospace and defense | AQ4: =COUNTIFS(AI:AI,AP4,L:L,"<=2023", J:J, "T") -> 0 | AR4: =COUNTIFS(AI:AI,AP4,L:L,">=2024",L:L,"<=2030", J:J, "T") -> 1 | AS4: =COUNTIFS(AI:AI,AP4,L:L,">2030",J:J, "T") -> 0 | AT4: =COUNTIFS($AI$5:$AI$504,AP4,$H$5:$H$504,"<=2023") -> 1 | AU4: =COUNTIFS($AI$5:$AI$504,AP4,$H$5:$H$504,">=2024",$H$5:$H$504,"<=2030") -> 0 | AV4: =COUNTIFS($AI$5:$AI$504,AP4,$H$5:$H$504,">2030") -> 0 | AW4: =COUNTIFS(AI:AI,AP4,W:W,"<=2023",T:T, "<>G") -> 0 | AX4: =COUNTIFS(AI:AI,AP4,W:W,">=2024",W:W,"<=2030",T:T, "<>G") -> 0 | AY4: =COUNTIFS(AI:AI,AP4,W:W,">2030",T:T, "<>G") -> 0 | AZ4: =COUNTIFS(AI:AI,AP4,AE:AE, "1", W:W, "<=2023",W:W, "<>",T:T, "<>G") -> 0 | BA4: =COUNTIFS(AI:AI,AP4,T:T,"<G>",AE:AE,"1",W:W, ">2023",W:W, "<=2030") -> 0 | BB4: =COUNTIFS(AI:AI,AP4,AE:AE, "1", W:W, ">2030",T:T, "<>G") -> 0 | BC4: =COUNTIFS(AI:AI,AP4,AJ:AJ,"<=2023") -> 1 | BD4: =COUNTIFS(AI:AI,AP4,AJ:AJ,">=2024",AJ:AJ,"<=2030") -> 0 | BE4: =COUNTIFS(AI:AI,AP4,AJ:AJ,">2030") -> 3 | BF4: =SUM(AQ4:AY4)-SUM(AZ4:BB4)+SUM(BC4:BE4) -> 6 | BG4: =COUNTIFS($AI$5:$AI$508, AP4, $AG$5:$AG$508, "Y") -> 0 | BH4: =COUNTIFS($AI$5:$AI$508, AP4, $AG$5:$AG$508, "N") -> 0 | BI4: =COUNTIF($AI$5:$AI$508, AP4)-BH4-BG4 -> 11
A5: 3 | B5: State Grid | C5: China | D5: Energy | E5: $530,009 | F5: $8,192 | T5: G | U5: undefined | V5: 2060 | W5: {=IF(V5="", "", IFERROR(MAX(--_xlfn.TEXTSPLIT(V5,"+")), V5))} -> 2060 | X5: 2021 | Y5: http://www.sgcc.com.cn/html/files/2022-06/10/20220610161501291488481.pdf | AC5: {=IF(AB5="", "", IFERROR(MAX(--_xlfn.TEXTSPLIT(AB5,"+")), AB5))} | AD5: =IF(AND(Table1[[#This Row],[year broken down ]]<>"",Table1[[#This Row],[Scope of target]]<>"G",AE5=""),1,"") | AE5: =IF(OR(Table1[[#This Row],[Net zero year (SBTi)]]<>"",Table1[[#This Row],[From 6]]<>""),1,"") | AF5: =IF(OR(Table1[[#This Row],[SBTi NZ approved]]="s",Table1[[#This Row],[Target status]]="T"),1,"") | AG5: U | AH5: =_xlfn.XLOOKUP(C5,ref!A:A,ref!B:B, "Other") -> Asia | AI5: =_xlfn.XLOOKUP(D5,ref!D:D,ref!E:E) -> Energy and utilities | AJ5: =IF(Table1[[#This Row],[NZ]]=1, MAX(Table1[[#This Row],[From 6]], Table1[[#This Row],[Net zero year (SBTi)]]), "") | AK5: =IF(OR($AD5<>"",$AE5<>"",$AF5<>"",$G5="Y"),1,0) -> 0 | AP5: Automotive | AQ5: =COUNTIFS(AI:AI,AP5,L:L,"<=2023", J:J, "T") -> 0 | AR5: =COUNTIFS(AI:AI,AP5,L:L,">=2024",L:L,"<=2030", J:J, "T") -> 8 | AS5: =COUNTIFS(AI:AI,AP5,L:L,">2030",J:J, "T") -> 3 | AT5: =COUNTIFS($AI$5:$AI$504,AP5,$H$5:$H$504,"<=2023") -> 0 | AU5: =COUNTIFS($AI$5:$AI$504,AP5,$H$5:$H$504,">=2024",$H$5:$H$504,"<=2030") -> 1 | AV5: =COUNTIFS($AI$5:$AI$504,AP5,$H$5:$H$504,">2030") -> 6 | AW5: =COUNTIFS(AI:AI,AP5,W:W,"<=2023",T:T, "<>G") -> 1 | AX5: =COUNTIFS(AI:AI,AP5,W:W,">=2024",W:W,"<=2030",T:T, "<>G") -> 2 | AY5: =COUNTIFS(AI:AI,AP5,W:W,">2030",T:T, "<>G") -> 20 | AZ5: =COUNTIFS(AI:AI,AP5,AE:AE, "1", W:W, "<=2023",W:W, "<>",T:T, "<>G") -> 0 | BA5: =COUNTIFS(AI:AI,AP5,T:T,"<G>",AE:AE,"1",W:W, ">2023",W:W, "<=2030") -> 1 | BB5: =COUNTIFS(AI:AI,AP5,AE:AE, "1", W:W, ">2030",T:T, "<>G") -> 1 | BC5: =COUNTIFS(AI:AI,AP5,AJ:AJ,"<=2023") -> 0 | BD5: =COUNTIFS(AI:AI,AP5,AJ:AJ,">=2024",AJ:AJ,"<=2030") -> 0 | BE5: =COUNTIFS(AI:AI,AP5,AJ:AJ,">2030") -> 6 | BF5: =SUM(AQ5:AY5)-SUM(AZ5:BB5)+SUM(BC5:BE5) -> 45 | BG5: =COUNTIFS($AI$5:$AI$508, AP5, $AG$5:$AG$508, "Y") -> 10 | BH5: =COUNTIFS($AI$5:$AI$508, AP5, $AG$5:$AG$508, "N") -> 0 | BI5: =COUNTIF($AI$5:$AI$508, AP5)-BH5-BG5 -> 24
A6: 4 | B6: Amazon | C6: United States of America (USA) | D6: Retailing | E6: $513,983 | F6: $-2,722 | J6: R | W6: {=IF(V6="", "", IFERROR(MAX(--_xlfn.TEXTSPLIT(V6,"+")), V6))} | Z6: C | AA6: across our business (operations) | AB6: 2040 | AC6: {=IF(AB6="", "", IFERROR(MAX(--_xlfn.TEXTSPLIT(AB6,"+")), AB6))} -> 2040 | AD6: =IF(AND(Table1[[#This Row],[year broken down ]]<>"",Table1[[#This Row],[Scope of target]]<>"G",AE6=""),1,"") | AE6: =IF(OR(Table1[[#This Row],[Net zero year (SBTi)]]<>"",Table1[[#This Row],[From 6]]<>""),1,"") -> 1 | AF6: =IF(OR(Table1[[#This Row],[SBTi NZ approved]]="s",Table1[[#This Row],[Target status]]="T"),1,"") | AH6: =_xlfn.XLOOKUP(C6,ref!A:A,ref!B:B, "Other") -> North America | AI6: =_xlfn.XLOOKUP(D6,ref!D:D,ref!E:E) -> Retail | AJ6: =IF(Table1[[#This Row],[NZ]]=1, MAX(Table1[[#This Row],[From 6]], Table1[[#This Row],[Net zero year (SBTi)]]), "") -> 2040 | AK6: =IF(OR($AD6<>"",$AE6<>"",$AF6<>"",$G6="Y"),1,0) -> 1 | AP6: Chemicals | AQ6: =COUNTIFS(AI:AI,AP6,L:L,"<=2023", J:J, "T") -> 0 | AR6: =COUNTIFS(AI:AI,AP6,L:L,">=2024",L:L,"<=2030", J:J, "T") -> 0 | AS6: =COUNTIFS(AI:AI,AP6,L:L,">2030",J:J, "T") -> 2 | AT6: =COUNTIFS($AI$5:$AI$504,AP6,$H$5:$H$504,"<=2023") -> 0 | AU6: =COUNTIFS($AI$5:$AI$504,AP6,$H$5:$H$504,">=2024",$H$5:$H$504,"<=2030") -> 0 | AV6: =COUNTIFS($AI$5:$AI$504,AP6,$H$5:$H$504,">2030") -> 1 | AW6: =COUNTIFS(AI:AI,AP6,W:W,"<=2023",T:T, "<>G") -> 0 | AX6: =COUNTIFS(AI:AI,AP6,W:W,">=2024",W:W,"<=2030",T:T, "<>G") -> 1 | AY6: =COUNTIFS(AI:AI,AP6,W:W,">2030",T:T, "<>G") -> 5 | AZ6: =COUNTIFS(AI:AI,AP6,AE:AE, "1", W:W, "<=2023",W:W, "<>",T:T, "<>G") -> 0 | BA6: =COUNTIFS(AI:AI,AP6,T:T,"<G>",AE:AE,"1",W:W, ">2023",W:W, "<=2030") -> 1 | BB6: =COUNTIFS(AI:AI,AP6,AE:AE, "1", W:W, ">2030",T:T, "<>G") -> 0 | BC6: =COUNTIFS(AI:AI,AP6,AJ:AJ,"<=2023") -> 0 | BD6: =COUNTIFS(AI:AI,AP6,AJ:AJ,">=2024",AJ:AJ,"<=2030") -> 0 | BE6: =COUNTIFS(AI:AI,AP6,AJ:AJ,">2030") -> 3 | BF6: =SUM(AQ6:AY6)-SUM(AZ6:BB6)+SUM(BC6:BE6) -> 11 | BG6: =COUNTIFS($AI$5:$AI$508, AP6, $AG$5:$AG$508, "Y") -> 1 | BH6: =COUNTIFS($AI$5:$AI$508, AP6, $AG$5:$AG$508, "N") -> 0 | BI6: =COUNTIF($AI$5:$AI$508, AP6)-BH6-BG6 -> 12
A7: 5 | B7: China National Petroleum | C7: China | D7: Petroleum Refining | E7: $483,019 | F7: $21,080 | T7: G | U7: undefined | V7: 2060 | W7: {=IF(V7="", "", IFERROR(MAX(--_xlfn.TEXTSPLIT(V7,"+")), V7))} -> 2060 | X7: 2020 | Y7: http://www.petrochina.com.cn/ptr/xhtml/images/2021esgen.pdf http://iis.aastocks.com/20230330/10653446-0.PDF | AC7: {=IF(AB7="", "", IFERROR(MAX(--_xlfn.TEXTSPLIT(AB7,"+")), AB7))} | AD7: =IF(AND(Table1[[#This Row],[year broken down ]]<>"",Table1[[#This Row],[Scope of target]]<>"G",AE7=""),1,"") | AE7: =IF(OR(Table1[[#This Row],[Net zero year (SBTi)]]<>"",Table1[[#This Row],[From 6]]<>""),1,"") | AF7: =IF(OR(Table1[[#This Row],[SBTi NZ approved]]="s",Table1[[#This Row],[Target status]]="T"),1,"") | AG7: U | AH7: =_xlfn.XLOOKUP(C7,ref!A:A,ref!B:B, "Other") -> Asia | AI7: =_xlfn.XLOOKUP(D7,ref!D:D,ref!E:E) -> Oil and gas | AJ7: =IF(Table1[[#This Row],[NZ]]=1, MAX(Table1[[#This Row],[From 6]], Table1[[#This Row],[Net zero year (SBTi)]]), "") | AK7: =IF(OR($AD7<>"",$AE7<>"",$AF7<>"",$G7="Y"),1,0) -> 0 | AP7: Energy and utilities | AQ7: =COUNTIFS(AI:AI,AP7,L:L,"<=2023", J:J, "T") -> 0 | AR7: =COUNTIFS(AI:AI,AP7,L:L,">=2024",L:L,"<=2030", J:J, "T") -> 8 | AS7: =COUNTIFS(AI:AI,AP7,L:L,">2030",J:J, "T") -> 2 | AT7: =COUNTIFS($AI$5:$AI$504,AP7,$H$5:$H$504,"<=2023") -> 0 | AU7: =COUNTIFS($AI$5:$AI$504,AP7,$H$5:$H$504,">=2024",$H$5:$H$504,"<=2030") -> 0 | AV7: =COUNTIFS($AI$5:$AI$504,AP7,$H$5:$H$504,">2030") -> 0 | AW7: =COUNTIFS(AI:AI,AP7,W:W,"<=2023",T:T, "<>G") -> 2 | AX7: =COUNTIFS(AI:AI,AP7,W:W,">=2024",W:W,"<=2030",T:T, "<>G") -> 3 | AY7: =COUNTIFS(AI:AI,AP7,W:W,">2030",T:T, "<>G") -> 18 | AZ7: =COUNTIFS(AI:AI,AP7,AE:AE, "1", W:W, "<=2023",W:W, "<>",T:T, "<>G") -> 0 | BA7: =COUNTIFS(AI:AI,AP7,T:T,"<G>",AE:AE,"1",W:W, ">2023",W:W, "<=2030") -> 1 | BB7: =COUNTIFS(AI:AI,AP7,AE:AE, "1", W:W, ">2030",T:T, "<>G") -> 2 | BC7: =COUNTIFS(AI:AI,AP7,AJ:AJ,"<=2023") -> 1 | BD7: =COUNTIFS(AI:AI,AP7,AJ:AJ,">=2024",AJ:AJ,"<=2030") -> 0 | BE7: =COUNTIFS(AI:AI,AP7,AJ:AJ,">2030") -> 33 | BF7: =SUM(AQ7:AY7)-SUM(AZ7:BB7)+SUM(BC7:BE7) -> 64 | BG7: =COUNTIFS($AI$5:$AI$508, AP7, $AG$5:$AG$508, "Y") -> 13 | BH7: =COUNTIFS($AI$5:$AI$508, AP7, $AG$5:$AG$508, "N") -> 1 | BI7: =COUNTIF($AI$5:$AI$508, AP7)-BH7-BG7 -> 70
A8: 6 | B8: Sinopec Group | C8: China | D8: Energy | E8: $471,154 | F8: $9,657 | T8: G | U8: undefined | V8: 2060 | W8: {=IF(V8="", "", IFERROR(MAX(--_xlfn.TEXTSPLIT(V8,"+")), V8))} -> 2060 | X8: 2021 | Y8: http://www.sinopecgroup.com/group/en/Resource/Pdf/SustainReport2022en.pdf | AC8: {=IF(AB8="", "", IFERROR(MAX(--_xlfn.TEXTSPLIT(AB8,"+")), AB8))} | AD8: =IF(AND(Table1[[#This Row],[year broken down ]]<>"",Table1[[#This Row],[Scope of target]]<>"G",AE8=""),1,"") | AE8: =IF(OR(Table1[[#This Row],[Net zero year (SBTi)]]<>"",Table1[[#This Row],[From 6]]<>""),1,"") | AF8: =IF(OR(Table1[[#This Row],[SBTi NZ approved]]="s",Table1[[#This Row],[Target status]]="T"),1,"") | AG8: U | AH8: =_xlfn.XLOOKUP(C8,ref!A:A,ref!B:B, "Other") -> Asia | AI8: =_xlfn.XLOOKUP(D8,ref!D:D,ref!E:E) -> Energy and utilities | AJ8: =IF(Table1[[#This Row],[NZ]]=1, MAX(Table1[[#This Row],[From 6]], Table1[[#This Row],[Net zero year (SBTi)]]), "") | AK8: =IF(OR($AD8<>"",$AE8<>"",$AF8<>"",$G8="Y"),1,0) -> 0 | AP8: Engineering and construction | AQ8: =COUNTIFS(AI:AI,AP8,L:L,"<=2023", J:J, "T") -> 0 | AR8: =COUNTIFS(AI:AI,AP8,L:L,">=2024",L:L,"<=2030", J:J, "T") -> 1 | AS8: =COUNTIFS(AI:AI,AP8,L:L,">2030",J:J, "T") -> 1 | AT8: =COUNTIFS($AI$5:$AI$504,AP8,$H$5:$H$504,"<=2023") -> 0 | AU8: =COUNTIFS($AI$5:$AI$504,AP8,$H$5:$H$504,">=2024",$H$5:$H$504,"<=2030") -> 1 | AV8: =COUNTIFS($AI$5:$AI$504,AP8,$H$5:$H$504,">2030") -> 0 | AW8: =COUNTIFS(AI:AI,AP8,W:W,"<=2023",T:T, "<>G") -> 0 | AX8: =COUNTIFS(AI:AI,AP8,W:W,">=2024",W:W,"<=2030",T:T, "<>G") -> 0 | AY8: =COUNTIFS(AI:AI,AP8,W:W,">2030",T:T, "<>G") -> 3 | AZ8: =COUNTIFS(AI:AI,AP8,AE:AE, "1", W:W, "<=2023",W:W, "<>",T:T, "<>G") -> 0 | BA8: =COUNTIFS(AI:AI,AP8,T:T,"<G>",AE:AE,"1",W:W, ">2023",W:W, "<=2030") -> 0 | BB8: =COUNTIFS(AI:AI,AP8,AE:AE, "1", W:W, ">2030",T:T, "<>G") -> 1 | BC8: =COUNTIFS(AI:AI,AP8,AJ:AJ,"<=2023") -> 0 | BD8: =COUNTIFS(AI:AI,AP8,AJ:AJ,">=2024",AJ:AJ,"<=2030") -> 0 | BE8: =COUNTIFS(AI:AI,AP8,AJ:AJ,">2030") -> 1 | BF8: =SUM(AQ8:AY8)-SUM(AZ8:BB8)+SUM(BC8:BE8) -> 6 | BG8: =COUNTIFS($AI$5:$AI$508, AP8, $AG$5:$AG$508, "Y") -> 2 | BH8: =COUNTIFS($AI$5:$AI$508, AP8, $AG$5:$AG$508, "N") -> 0 | BI8: =COUNTIF($AI$5:$AI$508, AP8)-BH8-BG8 -> 17
A9: 7 | B9: Exxon Mobil | C9: United States of America (USA) | D9: Energy | E9: $413,680 | F9: $55,740 | W9: {=IF(V9="", "", IFERROR(MAX(--_xlfn.TEXTSPLIT(V9,"+")), V9))} | Z9: C | AA9: scope 1,2 | AB9: 2050 | AC9: {=IF(AB9="", "", IFERROR(MAX(--_xlfn.TEXTSPLIT(AB9,"+")), AB9))} -> 2050 | AD9: =IF(AND(Table1[[#This Row],[year broken down ]]<>"",Table1[[#This Row],[Scope of target]]<>"G",AE9=""),1,"") | AE9: =IF(OR(Table1[[#This Row],[Net zero year (SBTi)]]<>"",Table1[[#This Row],[From 6]]<>""),1,"") -> 1 | AF9: =IF(OR(Table1[[#This Row],[SBTi NZ approved]]="s",Table1[[#This Row],[Target status]]="T"),1,"") | AH9: =_xlfn.XLOOKUP(C9,ref!A:A,ref!B:B, "Other") -> North America | AI9: =_xlfn.XLOOKUP(D9,ref!D:D,ref!E:E) -> Energy and utilities | AJ9: =IF(Table1[[#This Row],[NZ]]=1, MAX(Table1[[#This Row],[From 6]], Table1[[#This Row],[Net zero year (SBTi)]]), "") -> 2050 | AK9: =IF(OR($AD9<>"",$AE9<>"",$AF9<>"",$G9="Y"),1,0) -> 1 | AP9: Financial services | AQ9: =COUNTIFS(AI:AI,AP9,L:L,"<=2023", J:J, "T") -> 0 | AR9: =COUNTIFS(AI:AI,AP9,L:L,">=2024",L:L,"<=2030", J:J, "T") -> 1 | AS9: =COUNTIFS(AI:AI,AP9,L:L,">2030",J:J, "T") -> 0 | AT9: =COUNTIFS($AI$5:$AI$504,AP9,$H$5:$H$504,"<=2023") -> 11 | AU9: =COUNTIFS($AI$5:$AI$504,AP9,$H$5:$H$504,">=2024",$H$5:$H$504,"<=2030") -> 7 | AV9: =COUNTIFS($AI$5:$AI$504,AP9,$H$5:$H$504,">2030") -> 2 | AW9: =COUNTIFS(AI:AI,AP9,W:W,"<=2023",T:T, "<>G") -> 24 | AX9: =COUNTIFS(AI:AI,AP9,W:W,">=2024",W:W,"<=2030",T:T, "<>G") -> 13 | AY9: =COUNTIFS(AI:AI,AP9,W:W,">2030",T:T, "<>G") -> 9 | AZ9: =COUNTIFS(AI:AI,AP9,AE:AE, "1", W:W, "<=2023",W:W, "<>",T:T, "<>G") -> 23 | BA9: =COUNTIFS(AI:AI,AP9,T:T,"<G>",AE:AE,"1",W:W, ">2023",W:W, "<=2030") -> 6 | BB9: =COUNTIFS(AI:AI,AP9,AE:AE, "1", W:W, ">2030",T:T, "<>G") -> 0 | BC9: =COUNTIFS(AI:AI,AP9,AJ:AJ,"<=2023") -> 1 | BD9: =COUNTIFS(AI:AI,AP9,AJ:AJ,">=2024",AJ:AJ,"<=2030") -> 6 | BE9: =COUNTIFS(AI:AI,AP9,AJ:AJ,">2030") -> 44 | BF9: =SUM(AQ9:AY9)-SUM(AZ9:BB9)+SUM(BC9:BE9) -> 89 | BG9: =COUNTIFS($AI$5:$AI$508, AP9, $AG$5:$AG$508, "Y") -> 40 | BH9: =COUNTIFS($AI$5:$AI$508, AP9, $AG$5:$AG$508, "N") -> 2 | BI9: =COUNTIF($AI$5:$AI$508, AP9)-BH9-BG9 -> 58
A10: 8 | B10: Apple | C10: United States of America (USA) | D10: Technology | E10: $394,328 | F10: $99,803 | G10: Y | H10: 2021 | I10: 2016 | J10: T | K10: 1.5°C | L10: 2030 | P10: N | S10: 2021 | T10: C + V | U10: operations + entire product footprint | V10: 2021 + 2030 | W10: {=IF(V10="", "", IFERROR(MAX(--_xlfn.TEXTSPLIT(V10,"+")), V10))} -> 2030 | X10: 2020 | Y10: https://www.apple.com/environment/pdf/Apple_Environmental_Progress_Report_2023.pdf https://www.apple.com/newsroom/2020/07/apple-commits-to-be-100-percent-carbon-neutral-for-its-supply-chain-and-products-by-2030/ https://www.apple.com/newsroom/2020/07/apple-commits-to-be-100-percent-carbon-neutral-for-its-supply-chain-and-products-by-2030/ | AC10: {=IF(AB10="", "", IFERROR(MAX(--_xlfn.TEXTSPLIT(AB10,"+")), AB10))} | AD10: =IF(AND(Table1[[#This Row],[year broken down ]]<>"",Table1[[#This Row],[Scope of target]]<>"G",AE10=""),1,"") -> 1 | AE10: =IF(OR(Table1[[#This Row],[Net zero year (SBTi)]]<>"",Table1[[#This Row],[From 6]]<>""),1,"") | AF10: =IF(OR(Table1[[#This Row],[SBTi NZ approved]]="s",Table1[[#This Row],[Target status]]="T"),1,"") -> 1 | AG10: Y | AH10: =_xlfn.XLOOKUP(C10,ref!A:A,ref!B:B, "Other") -> North America | AI10: =_xlfn.XLOOKUP(D10,ref!D:D,ref!E:E) -> Technology | AJ10: =IF(Table1[[#This Row],[NZ]]=1, MAX(Table1[[#This Row],[From 6]], Table1[[#This Row],[Net zero year (SBTi)]]), "") | AK10: =IF(OR($AD10<>"",$AE10<>"",$AF10<>"",$G10="Y"),1,0) -> 1 | AP10: Food, beverages and agriculture | AQ10: =COUNTIFS(AI:AI,AP10,L:L,"<=2023", J:J, "T") -> 0 | AR10: =COUNTIFS(AI:AI,AP10,L:L,">=2024",L:L,"<=2030", J:J, "T") -> 18 | AS10: =COUNTIFS(AI:AI,AP10,L:L,">2030",J:J, "T") -> 0 | AT10: =COUNTIFS($AI$5:$AI$504,AP10,$H$5:$H$504,"<=2023") -> 0 | AU10: =COUNTIFS($AI$5:$AI$504,AP10,$H$5:$H$504,">=2024",$H$5:$H$504,"<=2030") -> 6 | AV10: =COUNTIFS($AI$5:$AI$504,AP10,$H$5:$H$504,">2030") -> 1 | AW10: =COUNTIFS(AI:AI,AP10,W:W,"<=2023",T:T, "<>G") -> 1 | AX10: =COUNTIFS(AI:AI,AP10,W:W,">=2024",W:W,"<=2030",T:T, "<>G") -> 2 | AY10: =COUNTIFS(AI:AI,AP10,W:W,">2030",T:T, "<>G") -> 4 | AZ10: =COUNTIFS(AI:AI,AP10,AE:AE, "1", W:W, "<=2023",W:W, "<>",T:T, "<>G") -> 1 | BA10: =COUNTIFS(AI:AI,AP10,T:T,"<G>",AE:AE,"1",W:W, ">2023",W:W, "<=2030") -> 2 | BB10: =COUNTIFS(AI:AI,AP10,AE:AE, "1", W:W, ">2030",T:T, "<>G") -> 1 | BC10: =COUNTIFS(AI:AI,AP10,AJ:AJ,"<=2023") -> 0 | BD10: =COUNTIFS(AI:AI,AP10,AJ:AJ,">=2024",AJ:AJ,"<=2030") -> 0 | BE10: =COUNTIFS(AI:AI,AP10,AJ:AJ,">2030") -> 18 | BF10: =SUM(AQ10:AY10)-SUM(AZ10:BB10)+SUM(BC10:BE10) -> 46 | BG10: =COUNTIFS($AI$5:$AI$508, AP10, $AG$5:$AG$508, "Y") -> 4 | BH10: =COUNTIFS($AI$5:$AI$508, AP10, $AG$5:$AG$508, "N") -> 0 | BI10: =COUNTIF($AI$5:$AI$508, AP10)-BH10-BG10 -> 31
A11: 9 | B11: Shell | C11: Netherlands | D11: Energy | E11: $386,201 | F11: $42,309 | W11: {=IF(V11="", "", IFERROR(MAX(--_xlfn.TEXTSPLIT(V11,"+")), V11))} | Z11: C | AA11: business | AB11: 2050 | AC11: {=IF(AB11="", "", IFERROR(MAX(--_xlfn.TEXTSPLIT(AB11,"+")), AB11))} -> 2050 | AD11: =IF(AND(Table1[[#This Row],[year broken down ]]<>"",Table1[[#This Row],[Scope of target]]<>"G",AE11=""),1,"") | AE11: =IF(OR(Table1[[#This Row],[Net zero year (SBTi)]]<>"",Table1[[#This Row],[From 6]]<>""),1,"") -> 1 | AF11: =IF(OR(Table1[[#This Row],[SBTi NZ approved]]="s",Table1[[#This Row],[Target status]]="T"),1,"") | AH11: =_xlfn.XLOOKUP(C11,ref!A:A,ref!B:B, "Other") -> Europe | AI11: =_xlfn.XLOOKUP(D11,ref!D:D,ref!E:E) -> Energy and utilities | AJ11: =IF(Table1[[#This Row],[NZ]]=1, MAX(Table1[[#This Row],[From 6]], Table1[[#This Row],[Net zero year (SBTi)]]), "") -> 2050 | AK11: =IF(OR($AD11<>"",$AE11<>"",$AF11<>"",$G11="Y"),1,0) -> 1 | AP11: Health care and pharmaceuticals | AQ11: =COUNTIFS(AI:AI,AP11,L:L,"<=2023", J:J, "T") -> 0 | AR11: =COUNTIFS(AI:AI,AP11,L:L,">=2024",L:L,"<=2030", J:J, "T") -> 12 | AS11: =COUNTIFS(AI:AI,AP11,L:L,">2030",J:J, "T") -> 2 | AT11: =COUNTIFS($AI$5:$AI$504,AP11,$H$5:$H$504,"<=2023") -> 0 | AU11: =COUNTIFS($AI$5:$AI$504,AP11,$H$5:$H$504,">=2024",$H$5:$H$504,"<=2030") -> 8 | AV11: =COUNTIFS($AI$5:$AI$504,AP11,$H$5:$H$504,">2030") -> 0 | AW11: =COUNTIFS(AI:AI,AP11,W:W,"<=2023",T:T, "<>G") -> 1 | AX11: =COUNTIFS(AI:AI,AP11,W:W,">=2024",W:W,"<=2030",T:T, "<>G") -> 9 | AY11: =COUNTIFS(AI:AI,AP11,W:W,">2030",T:T, "<>G") -> 4 | AZ11: =COUNTIFS(AI:AI,AP11,AE:AE, "1", W:W, "<=2023",W:W, "<>",T:T, "<>G") -> 1 | BA11: =COUNTIFS(AI:AI,AP11,T:T,"<G>",AE:AE,"1",W:W, ">2023",W:W, "<=2030") -> 7 | BB11: =COUNTIFS(AI:AI,AP11,AE:AE, "1", W:W, ">2030",T:T, "<>G") -> 0 | BC11: =COUNTIFS(AI:AI,AP11,AJ:AJ,"<=2023") -> 0 | BD11: =COUNTIFS(AI:AI,AP11,AJ:AJ,">=2024",AJ:AJ,"<=2030") -> 0 | BE11: =COUNTIFS(AI:AI,AP11,AJ:AJ,">2030") -> 13 | BF11: =SUM(AQ11:AY11)-SUM(AZ11:BB11)+SUM(BC11:BE11) -> 41 | BG11: =COUNTIFS($AI$5:$AI$508, AP11, $AG$5:$AG$508, "Y") -> 9 | BH11: =COUNTIFS($AI$5:$AI$508, AP11, $AG$5:$AG$508, "N") -> 0 | BI11: =COUNTIF($AI$5:$AI$508, AP11)-BH11-BG11 -> 22
A12: 10 | B12: UnitedHealth Group | C12: United States of America (USA) | D12: Health Care | E12: $324,162 | F12: $20,120 | J12: C | L12: 2030 | P12: Y | Q12: c | S12: 2022 | W12: {=IF(V12="", "", IFERROR(MAX(--_xlfn.TEXTSPLIT(V12,"+")), V12))} | Z12: C | AA12: operational | AB12: 2035 | AC12: {=IF(AB12="", "", IFERROR(MAX(--_xlfn.TEXTSPLIT(AB12,"+")), AB12))} -> 2035 | AD12: =IF(AND(Table1[[#This Row],[year broken down ]]<>"",Table1[[#This Row],[Scope of target]]<>"G",AE12=""),1,"") | AE12: =IF(OR(Table1[[#This Row],[Net zero year (SBTi)]]<>"",Table1[[#This Row],[From 6]]<>""),1,"") -> 1 | AF12: =IF(OR(Table1[[#This Row],[SBTi NZ approved]]="s",Table1[[#This Row],[Target status]]="T"),1,"") | AH12: =_xlfn.XLOOKUP(C12,ref!A:A,ref!B:B, "Other") -> North America | AI12: =_xlfn.XLOOKUP(D12,ref!D:D,ref!E:E) -> Health care and pharmaceuticals | AJ12: =IF(Table1[[#This Row],[NZ]]=1, MAX(Table1[[#This Row],[From 6]], Table1[[#This Row],[Net zero year (SBTi)]]), "") -> 2035 | AK12: =IF(OR($AD12<>"",$AE12<>"",$AF12<>"",$G12="Y"),1,0) -> 1 | AP12: Household and personal products | AQ12: =COUNTIFS(AI:AI,AP12,L:L,"<=2023", J:J, "T") -> 0 | AR12: =COUNTIFS(AI:AI,AP12,L:L,">=2024",L:L,"<=2030", J:J, "T") -> 3 | AS12: =COUNTIFS(AI:AI,AP12,L:L,">2030",J:J, "T") -> 0 | AT12: =COUNTIFS($AI$5:$AI$504,AP12,$H$5:$H$504,"<=2023") -> 0 | AU12: =COUNTIFS($AI$5:$AI$504,AP12,$H$5:$H$504,">=2024",$H$5:$H$504,"<=2030") -> 2 | AV12: =COUNTIFS($AI$5:$AI$504,AP12,$H$5:$H$504,">2030") -> 0 | AW12: =COUNTIFS(AI:AI,AP12,W:W,"<=2023",T:T, "<>G") -> 1 | AX12: =COUNTIFS(AI:AI,AP12,W:W,">=2024",W:W,"<=2030",T:T, "<>G") -> 1 | AY12: =COUNTIFS(AI:AI,AP12,W:W,">2030",T:T, "<>G") -> 0 | AZ12: =COUNTIFS(AI:AI,AP12,AE:AE, "1", W:W, "<=2023",W:W, "<>",T:T, "<>G") -> 1 | BA12: =COUNTIFS(AI:AI,AP12,T:T,"<G>",AE:AE,"1",W:W, ">2023",W:W, "<=2030") -> 1 | BB12: =COUNTIFS(AI:AI,AP12,AE:AE, "1", W:W, ">2030",T:T, "<>G") -> 0 | BC12: =COUNTIFS(AI:AI,AP12,AJ:AJ,"<=2023") -> 0 | BD12: =COUNTIFS(AI:AI,AP12,AJ:AJ,">=2024",AJ:AJ,"<=2030") -> 0 | BE12: =COUNTIFS(AI:AI,AP12,AJ:AJ,">2030") -> 3 | BF12: =SUM(AQ12:AY12)-SUM(AZ12:BB12)+SUM(BC12:BE12) -> 8 | BG12: =COUNTIFS($AI$5:$AI$508, AP12, $AG$5:$AG$508, "Y") -> 2 | BH12: =COUNTIFS($AI$5:$AI$508, AP12, $AG$5:$AG$508, "N") -> 0 | BI12: =COUNTIF($AI$5:$AI$508, AP12)-BH12-BG12 -> 1
A13: 11 | B13: CVS Health | C13: United States of America (USA) | D13: Health Care | E13: $322,467 | F13: $4,149 | J13: T | K13: 1.5°C | L13: 2030 | M13: Targets Set | N13: 1.5°C | O13: 2050 | P13: Y | Q13: s | R13: 2050 | S13: 2021 | T13: C | U13: company | V13: 2030 | W13: {=IF(V13="", "", IFERROR(MAX(--_xlfn.TEXTSPLIT(V13,"+")), V13))} -> 2030 | X13: 2021 | Y13: https://www.cvshealth.com/content/dam/enterprise/cvs-enterprise/pdfs/2022/2022-ESGReport.pdf https://www.cvshealth.com/content/dam/enterprise/cvs-enterprise/pdfs/2022/2022-ESGReport-appendix.pdf | Z13: V | AA13: value chain | AB13: 2050 | AC13: {=IF(AB13="", "", IFERROR(MAX(--_xlfn.TEXTSPLIT(AB13,"+")), AB13))} -> 2050 | AD13: =IF(AND(Table1[[#This Row],[year broken down ]]<>"",Table1[[#This Row],[Scope of target]]<>"G",AE13=""),1,"") | AE13: =IF(OR(Table1[[#This Row],[Net zero year (SBTi)]]<>"",Table1[[#This Row],[From 6]]<>""),1,"") -> 1 | AF13: =IF(OR(Table1[[#This Row],[SBTi NZ approved]]="s",Table1[[#This Row],[Target status]]="T"),1,"") -> 1 | AG13: U | AH13: =_xlfn.XLOOKUP(C13,ref!A:A,ref!B:B, "Other") -> North America | AI13: =_xlfn.XLOOKUP(D13,ref!D:D,ref!E:E) -> Health care and pharmaceuticals | AJ13: =IF(Table1[[#This Row],[NZ]]=1, MAX(Table1[[#This Row],[From 6]], Table1[[#This Row],[Net zero year (SBTi)]]), "") -> 2050 | AK13: =IF(OR($AD13<>"",$AE13<>"",$AF13<>"",$G13="Y"),1,0) -> 1 | AP13: Industrial goods | AQ13: =COUNTIFS(AI:AI,AP13,L:L,"<=2023", J:J, "T") -> 0 | AR13: =COUNTIFS(AI:AI,AP13,L:L,">=2024",L:L,"<=2030", J:J, "T") -> 7 | AS13: =COUNTIFS(AI:AI,AP13,L:L,">2030",J:J, "T") -> 1 | AT13: =COUNTIFS($AI$5:$AI$504,AP13,$H$5:$H$504,"<=2023") -> 0 | AU13: =COUNTIFS($AI$5:$AI$504,AP13,$H$5:$H$504,">=2024",$H$5:$H$504,"<=2030") -> 2 | AV13: =COUNTIFS($AI$5:$AI$504,AP13,$H$5:$H$504,">2030") -> 0 | AW13: =COUNTIFS(AI:AI,AP13,W:W,"<=2023",T:T, "<>G") -> 0 | AX13: =COUNTIFS(AI:AI,AP13,W:W,">=2024",W:W,"<=2030",T:T, "<>G") -> 1 | AY13: =COUNTIFS(AI:AI,AP13,W:W,">2030",T:T, "<>G") -> 12 | AZ13: =COUNTIFS(AI:AI,AP13,AE:AE, "1", W:W, "<=2023",W:W, "<>",T:T, "<>G") -> 0 | BA13: =COUNTIFS(AI:AI,AP13,T:T,"<G>",AE:AE,"1",W:W, ">2023",W:W, "<=2030") -> 1 | BB13: =COUNTIFS(AI:AI,AP13,AE:AE, "1", W:W, ">2030",T:T, "<>G") -> 2 | BC13: =COUNTIFS(AI:AI,AP13,AJ:AJ,"<=2023") -> 0 | BD13: =COUNTIFS(AI:AI,AP13,AJ:AJ,">=2024",AJ:AJ,"<=2030") -> 0 | BE13: =COUNTIFS(AI:AI,AP13,AJ:AJ,">2030") -> 9 | BF13: =SUM(AQ13:AY13)-SUM(AZ13:BB13)+SUM(BC13:BE13) -> 29 | BG13: =COUNTIFS($AI$5:$AI$508, AP13, $AG$5:$AG$508, "Y") -> 6 | BH13: =COUNTIFS($AI$5:$AI$508, AP13, $AG$5:$AG$508, "N") -> 0 | BI13: =COUNTIF($AI$5:$AI$508, AP13)-BH13-BG13 -> 37
A14: 12 | B14: Trafigura Group | C14: Singapore | D14: Wholesalers | E14: $318,476 | F14: $6,994 | T14: C | U14: operational | V14: 2050 | W14: {=IF(V14="", "", IFERROR(MAX(--_xlfn.TEXTSPLIT(V14,"+")), V14))} -> 2050 | X14: 2022 | Y14: https://www.trafigura.com/media/3581/2022_trafigura_sustainability_report.pdf | AC14: {=IF(AB14="", "", IFERROR(MAX(--_xlfn.TEXTSPLIT(AB14,"+")), AB14))} | AD14: =IF(AND(Table1[[#This Row],[year broken down ]]<>"",Table1[[#This Row],[Scope of target]]<>"G",AE14=""),1,"") -> 1 | AE14: =IF(OR(Table1[[#This Row],[Net zero year (SBTi)]]<>"",Table1[[#This Row],[From 6]]<>""),1,"") | AF14: =IF(OR(Table1[[#This Row],[SBTi NZ approved]]="s",Table1[[#This Row],[Target status]]="T"),1,"") | AG14: Y | AH14: =_xlfn.XLOOKUP(C14,ref!A:A,ref!B:B, "Other") -> Asia | AI14: =_xlfn.XLOOKUP(D14,ref!D:D,ref!E:E) -> Retail | AJ14: =IF(Table1[[#This Row],[NZ]]=1, MAX(Table1[[#This Row],[From 6]], Table1[[#This Row],[Net zero year (SBTi)]]), "") | AK14: =IF(OR($AD14<>"",$AE14<>"",$AF14<>"",$G14="Y"),1,0) -> 1 | AP14: Metals and mining | AQ14: =COUNTIFS(AI:AI,AP14,L:L,"<=2023", J:J, "T") -> 0 | AR14: =COUNTIFS(AI:AI,AP14,L:L,">=2024",L:L,"<=2030", J:J, "T") -> 0 | AS14: =COUNTIFS(AI:AI,AP14,L:L,">2030",J:J, "T") -> 0 | AT14: =COUNTIFS($AI$5:$AI$504,AP14,$H$5:$H$504,"<=2023") -> 0 | AU14: =COUNTIFS($AI$5:$AI$504,AP14,$H$5:$H$504,">=2024",$H$5:$H$504,"<=2030") -> 0 | AV14: =COUNTIFS($AI$5:$AI$504,AP14,$H$5:$H$504,">2030") -> 0 | AW14: =COUNTIFS(AI:AI,AP14,W:W,"<=2023",T:T, "<>G") -> 0 | AX14: =COUNTIFS(AI:AI,AP14,W:W,">=2024",W:W,"<=2030",T:T, "<>G") -> 0 | AY14: =COUNTIFS(AI:AI,AP14,W:W,">2030",T:T, "<>G") -> 0 | AZ14: =COUNTIFS(AI:AI,AP14,AE:AE, "1", W:W, "<=2023",W:W, "<>",T:T, "<>G") -> 0 | BA14: =COUNTIFS(AI:AI,AP14,T:T,"<G>",AE:AE,"1",W:W, ">2023",W:W, "<=2030") -> 0 | BB14: =COUNTIFS(AI:AI,AP14,AE:AE, "1", W:W, ">2030",T:T, "<>G") -> 0 | BC14: =COUNTIFS(AI:AI,AP14,AJ:AJ,"<=2023") -> 0 | BD14: =COUNTIFS(AI:AI,AP14,AJ:AJ,">=2024",AJ:AJ,"<=2030") -> 0 | BE14: =COUNTIFS(AI:AI,AP14,AJ:AJ,">2030") -> 0 | BF14: =SUM(AQ14:AY14)-SUM(AZ14:BB14)+SUM(BC14:BE14) -> 0 | BG14: =COUNTIFS($AI$5:$AI$508, AP14, $AG$5:$AG$508, "Y") -> 0 | BH14: =COUNTIFS($AI$5:$AI$508, AP14, $AG$5:$AG$508, "N") -> 0 | BI14: =COUNTIF($AI$5:$AI$508, AP14)-BH14-BG14 -> 0
A15: 13 | B15: China State Construction Engineering | C15: China | D15: Engineering & Construction | E15: $305,885 | F15: $4,234 | T15: G | U15: undefined | V15: 2060 | W15: {=IF(V15="", "", IFERROR(MAX(--_xlfn.TEXTSPLIT(V15,"+")), V15))} -> 2060 | X15: 2021 | Y15: https://english.cscec.com/tzgx/reports/202206/P020220617672797745003.pdf https://manager.wisdomir.com/files/409/2023/0427/20230427170001_82663644_en.pdf | AC15: {=IF(AB15="", "", IFERROR(MAX(--_xlfn.TEXTSPLIT(AB15,"+")), AB15))} | AD15: =IF(AND(Table1[[#This Row],[year broken down ]]<>"",Table1[[#This Row],[Scope of target]]<>"G",AE15=""),1,"") | AE15: =IF(OR(Table1[[#This Row],[Net zero year (SBTi)]]<>"",Table1[[#This Row],[From 6]]<>""),1,"") | AF15: =IF(OR(Table1[[#This Row],[SBTi NZ approved]]="s",Table1[[#This Row],[Target status]]="T"),1,"") | AG15: U | AH15: =_xlfn.XLOOKUP(C15,ref!A:A,ref!B:B, "Other") -> Asia | AI15: =_xlfn.XLOOKUP(D15,ref!D:D,ref!E:E) -> Engineering and construction | AJ15: =IF(Table1[[#This Row],[NZ]]=1, MAX(Table1[[#This Row],[From 6]], Table1[[#This Row],[Net zero year (SBTi)]]), "") | AK15: =IF(OR($AD15<>"",$AE15<>"",$AF15<>"",$G15="Y"),1,0) -> 0 | AP15: Oil and gas | AQ15: =COUNTIFS(AI:AI,AP15,L:L,"<=2023", J:J, "T") -> 0 | AR15: =COUNTIFS(AI:AI,AP15,L:L,">=2024",L:L,"<=2030", J:J, "T") -> 0 | AS15: =COUNTIFS(AI:AI,AP15,L:L,">2030",J:J, "T") -> 0 | AT15: =COUNTIFS($AI$5:$AI$504,AP15,$H$5:$H$504,"<=2023") -> 0 | AU15: =COUNTIFS($AI$5:$AI$504,AP15,$H$5:$H$504,">=2024",$H$5:$H$504,"<=2030") -> 0 | AV15: =COUNTIFS($AI$5:$AI$504,AP15,$H$5:$H$504,">2030") -> 0 | AW15: =COUNTIFS(AI:AI,AP15,W:W,"<=2023",T:T, "<>G") -> 0 | AX15: =COUNTIFS(AI:AI,AP15,W:W,">=2024",W:W,"<=2030",T:T, "<>G") -> 0 | AY15: =COUNTIFS(AI:AI,AP15,W:W,">2030",T:T, "<>G") -> 1 | AZ15: =COUNTIFS(AI:AI,AP15,AE:AE, "1", W:W, "<=2023",W:W, "<>",T:T, "<>G") -> 0 | BA15: =COUNTIFS(AI:AI,AP15,T:T,"<G>",AE:AE,"1",W:W, ">2023",W:W, "<=2030") -> 0 | BB15: =COUNTIFS(AI:AI,AP15,AE:AE, "1", W:W, ">2030",T:T, "<>G") -> 0 | BC15: =COUNTIFS(AI:AI,AP15,AJ:AJ,"<=2023") -> 0 | BD15: =COUNTIFS(AI:AI,AP15,AJ:AJ,">=2024",AJ:AJ,"<=2030") -> 0 | BE15: =COUNTIFS(AI:AI,AP15,AJ:AJ,">2030") -> 0 | BF15: =SUM(AQ15:AY15)-SUM(AZ15:BB15)+SUM(BC15:BE15) -> 1 | BG15: =COUNTIFS($AI$5:$AI$508, AP15, $AG$5:$AG$508, "Y") -> 0 | BH15: =COUNTIFS($AI$5:$AI$508, AP15, $AG$5:$AG$508, "N") -> 0 | BI15: =COUNTIF($AI$5:$AI$508, AP15)-BH15-BG15 -> 3
