Workbook

Sheet 2024
A1: Rank | B1: Company Name | C1: 2023 rank | D1: Target summary | E1: Who dunnit? | F1: Date completed | G1: compared with 2023 data? | H1: Profits usable ($M) | I1: Sector (Fortune) | J1: Sector (final classification) | K1: Country | L1: Region | M1: RE100 (Y/N) | N1: Joining year | O1: Target year | P1: SBT (Y = yes, N=no) | Q1: Target status - NT | R1: Target classification NT - temp | S1: Target year NT (earlier of the two dates if there were two) - if committed, then year set to 2030 | T1: Net zero committed (SBTi) | U1: SBTi NZ approved year | V1: Commitment date (SBTi) | W1: Commitment year (SBTi) | X1: Carbon neutral commitment (C = company, V = value chain, G= Government, S = subsidiary, U = unspecified, x = less than 50% of rev, N=no) | Y1: Carbon neutral scope(s) (in their words) (+ indicates two targets/ a later target) | Z1: Carbon neutral claim (in their words) | AA1: Carbon neutral commitment - EARLY | AB1: Earlier carbon neutral target year | AC1: Earlier carbon neutral announcement year | AD1: Carbon neutral commitment - LATE | AE1: Later carbon neutral target year | AF1: Later carbon neutral announcement year | AG1: Carbon credits (Y = yes, N = no, R = removals only, U = unclear) | AH1: Souce Date | AI1: Source Target Mention (Y or N) | AJ1: Sustainability report | AK1: Press release | AL1: Source | AM1: Notes (including climate positive) | AN1: Net zero commitment (V = value chain, C = company, S = subsidiary, U = unclear, x = less than 50% rev) | AO1: Primary net zero scope (in their words) | AP1: Primary net zero claim (in their words) | AQ1: Net Zero Target - EARLY | AR1: Earlier net zero target year | AS1: Earlier net zero announcement year | AT1: Net Zero Target - LATE | AU1: Later net zero target year | AV1: Later net zero announcement year | AW1: Carbon credits (Y = yes, N = no, R = removals only, U = unclear).1 | AX1: Source.1 | AY1: Souce Date.1 | AZ1: Source Target Mention (Y or N).1 | BA1: Sustainability report.1 | BB1: Press release.1 | BC1: Notes | BD1: Reduction targets for Decarbonization (V = value chain, C = company) | BE1: Source.2 | BF1: Using Carbon Credits without target (Y=yes, N=No) | BG1: Source.3 | BH1: Questions | BI1: Interesting points | BJ1: CN already achieved | BK1: CN 2024-2030 | BL1: CN 2031-2050 | BM1: Any CN | BN1: NZ already achieved | BO1: NZ 2024-2030 | BP1: NZ 2031-2050 | BQ1: Any NZ | BR1: SBT already achieved | BS1: SBT 2024-2030 | BT1: SBT 2031-2050 | BU1: Any SBT | BV1: RE100 already achieved | BW1: RE100 2024-2030 | BX1: RE100 2031-2050 | BY1: Any RE100 | BZ1: CN/NZ - does the company have a voluntary CN or NZ target? | CA1: CN/NZ by 2030 | CB1: CN/NZ by 2050 | CC1: will use cabon credits | CD1: will NOT use carbon credits | CE1: any commitment | CF1: any commitment already achieved | CG1: any commitment by 2030 | CH1: any commitment by 2050 | CI1: NZ covering VC already achieved | CJ1: NZ covering VC 2024-2030 | CK1: NZ covering VC 2031-2050 | CL1: Any NZ covering VC | CM1: NZ year
A2: 489 | B2: 3M | C2: 443 | D2: =CONCATENATE((IF(BM2=1, "CN", "")),(IF(BQ2=1, " NZ", "")),(IF(BU2=1, " SBT", "")),(IF(BY2=1, " RE100", ""))) -> CN SBT RE100 | E2: DT * | F2: 45511 | G2: DT | H2: -6995 | J2: Chemicals | K2: United States of America (USA) | L2: North America | M2: Y | N2: 2019 | O2: 2050 | P2: N | Q2: Committed | S2: 2030 | T2: No | V2: 45231 | W2: 2023 | X2: C | Y2: operations | Z2: carbon neutral | AA2: C | AB2: 2050 | AC2: 2021 | AG2: Y | AI2: Y | AL2: https://multimedia.3m.com/mws/media/2395043O/3m-2024-global-impact-report.pdf | AN2: N | AQ2: N | BL2: 1 | BM2: 1 | BS2: 1 | BU2: 1 | BX2: 1 | BY2: 1 | BZ2: 1 | CB2: 1 | CC2: 1 | CE2: 1 | CG2: 1 | CH2: 1
A3: 498 | B3: ABB | D3: =CONCATENATE((IF(BM3=1, "CN", "")),(IF(BQ3=1, " NZ", "")),(IF(BU3=1, " SBT", "")),(IF(BY3=1, " RE100", ""))) -> NZ SBT RE100 | E3: AJ | F3: 45512 | H3: 3745 | I3: Industrial Machinery | J3: Industrial goods | K3: Switzerland | L3: Europe | M3: Y | N3: 2021 | O3: 2030 | P3: Y | Q3: Targets Set | R3: 1.5°C | S3: 2030 | T3: Yes | U3: 2050 | V3: 01/05/2021 | W3: 2021 | X3: N | AA3: N | AN3: V | AO3: SBTi approved so value chain | AP3: Net Zero | AQ3: V | AR3: 2050 | AS3: 2021 | AW3: R | AX3: https://global.abb/group/en/sustainability | AY3: 2023 | AZ3: Y | BA3: https://search.abb.com/library/Download.aspx?DocumentID=9AKK108469A1083&LanguageCode=en&DocumentPartId=&Action=Launch | BP3: 1 | BQ3: 1 | BS3: 1 | BU3: 1 | BW3: 1 | BY3: 1 | BZ3: 1 | CB3: 1 | CC3: 1 | CE3: 1 | CG3: 1 | CH3: 1 | CK3: 1 | CL3: 1 | CM3: =MAX(U3,AR3) -> 2050 | CR3: SBTi short term | CU3: RE100 | CX3: Carbon Neutral | DA3: Net Zero | DD3: sum
A4: 376 | B4: Abbott Laboratories | C4: 338 | D4: =CONCATENATE((IF(BM4=1, "CN", "")),(IF(BQ4=1, " NZ", "")),(IF(BU4=1, " SBT", "")),(IF(BY4=1, " RE100", ""))) -> SBT | E4: EC | F4: 45482 | G4: DT | H4: 5723 | J4: Health care and pharmaceuticals | K4: United States of America (USA) | L4: North America | M4: N | P4: Y | Q4: Targets Set | R4: Well-below 2Â°C | S4: 2030 | T4: No | V4: 44805 | W4: 2022 | X4: N | AA4: N | AN4: N | AQ4: N | BD4: C | BE4: https://www.abbott.com/content/dam/corp/abbott/en-us/hub-new/Abbott-2023-Global-Sustainability-Report-June-2024.pdf | BS4: 1 | BU4: 1 | CE4: 1 | CG4: 1 | CH4: 1 | CQ4: Sector | CR4: <=2024 | CS4: 2025-2030 | CT4: 2031-2060 | CU4: <=2024 | CV4: 2025-2030 | CW4: 2031-2060 | CX4: <=2024 | CY4: 2025-2030 | CZ4: 2031-2060 | DA4: <=2024 | DB4: 2025-2030 | DC4: 2031-2060 | DE4: Yes | DF4: No | DG4: Unspecified
A5: 259 | B5: AbbVie | C5: 240 | D5: =CONCATENATE((IF(BM5=1, "CN", "")),(IF(BQ5=1, " NZ", "")),(IF(BU5=1, " SBT", "")),(IF(BY5=1, " RE100", ""))) -> NZ SBT | E5: DT | F5: 45477 | G5: DT | H5: 4863 | J5: Health care and pharmaceuticals | K5: United States of America (USA) | L5: North America | M5: N | P5: Y | Q5: Targets Set | R5: 1.5Â°C | S5: 2030 | T5: No | V5: 45017 | W5: 2023 | X5: N | AA5: N | AN5: C | AO5: Scope 1 and 2 | AP5: Net Zero | AQ5: C | AR5: 2050 | AS5: 2021 | AW5: Y | AX5: https://www.abbvie.co.uk/content/dam/abbvie-dotcom/gb/documents/OCTOBER%20UK-ABBV-230401%20-%20Carbon%20Reduction%20Plan.pdf https://www.abbvie.com/sustainability/environmental-social-and-governance/environmental-sustainability.html#:~:text=In%20our%20determined%20effort%20to,and%20use%20cleaner%20energy%20sources | BP5: 1 | BQ5: 1 | BS5: 1 | BU5: 1 | BZ5: 1 | CB5: 1 | CC5: 1 | CE5: 1 | CG5: 1 | CH5: 1 | CM5: =MAX(U5,AR5) -> 2050 | CQ5: Aerospace and defense | CR5: =COUNTIFS($J$2:$J$501,CQ5,$S$2:$S$501,"<=2024") -> 0 | CS5: =COUNTIFS($J$2:$J$501,CQ5,$S$2:$S$501,">=2025",$S$2:$S$501,"<=2030") -> 1 | CT5: =COUNTIFS($J$2:$J$501,CQ5,$S$2:$S$501,">2030") -> 0 | CU5: =COUNTIFS($J$2:$J$501,CQ5,$O$2:$O$501,"<=2024") -> 0 | CV5: =COUNTIFS($J$2:$J$501,CQ5,$O$2:$O$501,">=2025",$O$2:$O$501,"<=2030") -> 0 | CW5: =COUNTIFS($J$2:$J$501,CQ5,$O$5:$O$504,">2030") -> 0 | CX5: =COUNTIFS($J$2:$J$501,CQ5,$AB$2:$AB$501,"<=2024") -> 1 | CY5: =COUNTIFS($J$2:$J$501,CQ5,$AB$2:$AB$501,">=2024",$AB$2:$AB$501,"<=2030") -> 0 | CZ5: =COUNTIFS($J$2:$J$501,CQ5,$AB$2:$AB$501,">2030") -> 1 | DA5: =COUNTIFS($J$2:$J$501,CQ5,$CM$2:$CM$501,"<=2024") -> 0 | DB5: =COUNTIFS($J$2:$J$501,CQ5,$CM$2:$CM$501,">=2025",$CM$2:$CM$501,"<=2030") -> 0 | DC5: =COUNTIFS($J$2:$J$501,CQ5,$CM$2:$CM$501,">2030") -> 4 | DD5: =SUM(CR5:DC5) -> 7 | DE5: =COUNTIFS($J$2:$J$501, CQ5, $CC$2:$CC$501, "1") -> 4 | DF5: =COUNTIFS($J$2:$J$501, CQ5, $CD$2:$CD$501, "1") -> 0 | DG5: =COUNTIF($J$2:$J$501, CQ5)-DF5-DE5 -> 6
A6: 211 | B6: Accenture | C6: 220 | D6: =CONCATENATE((IF(BM6=1, "CN", "")),(IF(BQ6=1, " NZ", "")),(IF(BU6=1, " SBT", "")),(IF(BY6=1, " RE100", ""))) -> NZ SBT RE100 | E6: DT | F6: 45477 | G6: DT | H6: 6871.6 | J6: Financial services | K6: Ireland | L6: Europe | M6: Y | N6: 2019 | O6: 2023 | P6: Y | Q6: Targets Set | R6: 1.5Â°C | S6: 2030 | T6: Yes | U6: 2040 | V6: 45444 | W6: 2024 | X6: N | AA6: N | AN6: V | AO6: Scope 1, 2 and 3 | AP6: Net Zero | AQ6: V | AR6: 2040 | AS6: 2020 | AW6: Y | AX6: https://www.accenture.com/content/dam/accenture/final/corporate/corporate-initiatives/sustainability/document/360-Value-Report-2023.pdf | BP6: 1 | BQ6: 1 | BS6: 1 | BU6: 1 | BV6: 1 | BY6: 1 | BZ6: 1 | CA6: 1 | CB6: 1 | CC6: 1 | CE6: 1 | CF6: 1 | CG6: 1 | CH6: 1 | CK6: 1 | CL6: 1 | CM6: =MAX(U6,AR6) -> 2040 | CQ6: Automotive | CR6: =COUNTIFS($J$2:$J$501,CQ6,$S$2:$S$501,"<=2024") -> 0 | CS6: =COUNTIFS($J$2:$J$501,CQ6,$S$2:$S$501,">=2025",$S$2:$S$501,"<=2030") -> 16 | CT6: =COUNTIFS($J$2:$J$501,CQ6,$S$2:$S$501,">2030") -> 3 | CU6: =COUNTIFS($J$2:$J$501,CQ6,$O$2:$O$501,"<=2024") -> 0 | CV6: =COUNTIFS($J$2:$J$501,CQ6,$O$2:$O$501,">=2025",$O$2:$O$501,"<=2030") -> 1 | CW6: =COUNTIFS($J$2:$J$501,CQ6,$O$5:$O$504,">2030") -> 2 | CX6: =COUNTIFS($J$2:$J$501,CQ6,$AB$2:$AB$501,"<=2024") -> 2 | CY6: =COUNTIFS($J$2:$J$501,CQ6,$AB$2:$AB$501,">=2024",$AB$2:$AB$501,"<=2030") -> 3 | CZ6: =COUNTIFS($J$2:$J$501,CQ6,$AB$2:$AB$501,">2030") -> 21 | DA6: =COUNTIFS($J$2:$J$501,CQ6,$CM$2:$CM$501,"<=2024") -> 0 | DB6: =COUNTIFS($J$2:$J$501,CQ6,$CM$2:$CM$501,">=2025",$CM$2:$CM$501,"<=2030") -> 0 | DC6: =COUNTIFS($J$2:$J$501,CQ6,$CM$2:$CM$501,">2030") -> 7 | DD6: =SUM(CR6:DC6) -> 55 | DE6: =COUNTIFS($J$2:$J$501, CQ6, $CC$2:$CC$501, "1") -> 17 | DF6: =COUNTIFS($J$2:$J$501, CQ6, $CD$2:$CD$501, "1") -> 0 | DG6: =COUNTIF($J$2:$J$501, CQ6)-DF6-DE6 -> 20
A7: 391 | B7: ACS | C7: 428 | D7: =CONCATENATE((IF(BM7=1, "CN", "")),(IF(BQ7=1, " NZ", "")),(IF(BU7=1, " SBT", "")),(IF(BY7=1, " RE100", ""))) -> CN | E7: AJ | F7: 45511 | G7: AJ | H7: 843.4 | J7: Engineering and construction | K7: Spain | L7: Europe | M7: N | P7: N | X7: C | Y7: scope 1 and 2 emissions | Z7: climate neutral | AA7: C | AB7: 2045 | AC7: 2021 | AG7: U | AH7: 2024 | AI7: Y | AJ7: https://www.grupoacs.com/ficheros_editor/File/03_accionistas_inversores/06_junta_general_accionistas/2024/5%20Informaci%C3%B3n%20no%20financiera.pdf | AL7: https://www.grupoacs.com/sostenibilidad/estrategia-de-sostenibilidad/plan-director-sostenibilidad-2025/ | AN7: N | AQ7: N | BL7: 1 | BM7: 1 | BZ7: 1 | CB7: 1 | CE7: 1 | CH7: 1 | CQ7: Chemicals | CR7: =COUNTIFS($J$2:$J$501,CQ7,$S$2:$S$501,"<=2024") -> 0 | CS7: =COUNTIFS($J$2:$J$501,CQ7,$S$2:$S$501,">=2025",$S$2:$S$501,"<=2030") -> 2 | CT7: =COUNTIFS($J$2:$J$501,CQ7,$S$2:$S$501,">2030") -> 1 | CU7: =COUNTIFS($J$2:$J$501,CQ7,$O$2:$O$501,"<=2024") -> 0 | CV7: =COUNTIFS($J$2:$J$501,CQ7,$O$2:$O$501,">=2025",$O$2:$O$501,"<=2030") -> 0 | CW7: =COUNTIFS($J$2:$J$501,CQ7,$O$5:$O$504,">2030") -> 0 | CX7: =COUNTIFS($J$2:$J$501,CQ7,$AB$2:$AB$501,"<=2024") -> 0 | CY7: =COUNTIFS($J$2:$J$501,CQ7,$AB$2:$AB$501,">=2024",$AB$2:$AB$501,"<=2030") -> 1 | CZ7: =COUNTIFS($J$2:$J$501,CQ7,$AB$2:$AB$501,">2030") -> 4 | DA7: =COUNTIFS($J$2:$J$501,CQ7,$CM$2:$CM$501,"<=2024") -> 0 | DB7: =COUNTIFS($J$2:$J$501,CQ7,$CM$2:$CM$501,">=2025",$CM$2:$CM$501,"<=2030") -> 0 | DC7: =COUNTIFS($J$2:$J$501,CQ7,$CM$2:$CM$501,">2030") -> 3 | DD7: =SUM(CR7:DC7) -> 11 | DE7: =COUNTIFS($J$2:$J$501, CQ7, $CC$2:$CC$501, "1") -> 5 | DF7: =COUNTIFS($J$2:$J$501, CQ7, $CD$2:$CD$501, "1") -> 0 | DG7: =COUNTIF($J$2:$J$501, CQ7)-DF7-DE7 -> 5
A8: 203 | B8: AEON | C8: 189 | D8: =CONCATENATE((IF(BM8=1, "CN", "")),(IF(BQ8=1, " NZ", "")),(IF(BU8=1, " SBT", "")),(IF(BY8=1, " RE100", ""))) -> NZ SBT RE100 | E8: EC | F8: 45477 | G8: DT | H8: 312.2 | J8: Retail | K8: Japan | L8: Asia | M8: Y | N8: 2018 | O8: 2030 | P8: Y | Q8: Targets Set | R8: 1.5Â°C | S8: 2030 | T8: Yes | V8: 44409 | W8: 2021 | X8: N | AA8: N | AN8: C | AO8: our stores | AP8: Net Zero | AQ8: C | AR8: 2040 | AS8: 2021 | AW8: Y | AX8: https://ssl4.eir-parts.net/doc/8267/ir_material_for_fiscal_ym23/116815/00.pdf | AY8: 2023 | AZ8: Y | BA8: https://www.aeon-jreit.co.jp/en/sustainability/pdf/report/Sustainability_Report_all_e_2023_.pdf | BP8: 1 | BQ8: 1 | BS8: 1 | BU8: 1 | BW8: 1 | BY8: 1 | BZ8: 1 | CB8: 1 | CC8: 1 | CE8: 1 | CG8: 1 | CH8: 1 | CM8: =MAX(U8,AR8) -> 2040 | CQ8: Energy and utilities | CR8: =COUNTIFS($J$2:$J$501,CQ8,$S$2:$S$501,"<=2024") -> 1 | CS8: =COUNTIFS($J$2:$J$501,CQ8,$S$2:$S$501,">=2025",$S$2:$S$501,"<=2030") -> 5 | CT8: =COUNTIFS($J$2:$J$501,CQ8,$S$2:$S$501,">2030") -> 2 | CU8: =COUNTIFS($J$2:$J$501,CQ8,$O$2:$O$501,"<=2024") -> 0 | CV8: =COUNTIFS($J$2:$J$501,CQ8,$O$2:$O$501,">=2025",$O$2:$O$501,"<=2030") -> 0 | CW8: =COUNTIFS($J$2:$J$501,CQ8,$O$5:$O$504,">2030") -> 0 | CX8: =COUNTIFS($J$2:$J$501,CQ8,$AB$2:$AB$501,"<=2024") -> 1 | CY8: =COUNTIFS($J$2:$J$501,CQ8,$AB$2:$AB$501,">=2024",$AB$2:$AB$501,"<=2030") -> 2 | CZ8: =COUNTIFS($J$2:$J$501,CQ8,$AB$2:$AB$501,">2030") -> 12 | DA8: =COUNTIFS($J$2:$J$501,CQ8,$CM$2:$CM$501,"<=2024") -> 0 | DB8: =COUNTIFS($J$2:$J$501,CQ8,$CM$2:$CM$501,">=2025",$CM$2:$CM$501,"<=2030") -> 0 | DC8: =COUNTIFS($J$2:$J$501,CQ8,$CM$2:$CM$501,">2030") -> 8 | DD8: =SUM(CR8:DC8) -> 31 | DE8: =COUNTIFS($J$2:$J$501, CQ8, $CC$2:$CC$501, "1") -> 9 | DF8: =COUNTIFS($J$2:$J$501, CQ8, $CD$2:$CD$501, "1") -> 0 | DG8: =COUNTIF($J$2:$J$501, CQ8)-DF8-DE8 -> 13
A9: 34 | B9: Agricultural Bank of China | C9: 32 | D9: =CONCATENATE((IF(BM9=1, "CN", "")),(IF(BQ9=1, " NZ", "")),(IF(BU9=1, " SBT", "")),(IF(BY9=1, " RE100", ""))) | E9: EC | F9: 45474 | G9: DT | H9: 38048.7 | J9: Financial services | K9: China | L9: Asia | M9: N | P9: N | X9: G | Y9: operations | Z9: carbon neutrality | AA9: G | AB9: 2060 | AC9: 2023 | AL9: https://www.abchina.com/en/aboutus/csr-report/202403/P020240328668627319429.pdf | AN9: N | AQ9: N | BH9: they offset but don't specify why. Also have the Governement target - could put down as 2060 as per the gov target? | CQ9: Engineering and construction | CR9: =COUNTIFS($J$2:$J$501,CQ9,$S$2:$S$501,"<=2024") -> 0 | CS9: =COUNTIFS($J$2:$J$501,CQ9,$S$2:$S$501,">=2025",$S$2:$S$501,"<=2030") -> 3 | CT9: =COUNTIFS($J$2:$J$501,CQ9,$S$2:$S$501,">2030") -> 0 | CU9: =COUNTIFS($J$2:$J$501,CQ9,$O$2:$O$501,"<=2024") -> 1 | CV9: =COUNTIFS($J$2:$J$501,CQ9,$O$2:$O$501,">=2025",$O$2:$O$501,"<=2030") -> 0 | CW9: =COUNTIFS($J$2:$J$501,CQ9,$O$5:$O$504,">2030") -> 1 | CX9: =COUNTIFS($J$2:$J$501,CQ9,$AB$2:$AB$501,"<=2024") -> 0 | CY9: =COUNTIFS($J$2:$J$501,CQ9,$AB$2:$AB$501,">=2024",$AB$2:$AB$501,"<=2030") -> 0 | CZ9: =COUNTIFS($J$2:$J$501,CQ9,$AB$2:$AB$501,">2030") -> 8 | DA9: =COUNTIFS($J$2:$J$501,CQ9,$CM$2:$CM$501,"<=2024") -> 0 | DB9: =COUNTIFS($J$2:$J$501,CQ9,$CM$2:$CM$501,">=2025",$CM$2:$CM$501,"<=2030") -> 0 | DC9: =COUNTIFS($J$2:$J$501,CQ9,$CM$2:$CM$501,">2030") -> 1 | DD9: =SUM(CR9:DC9) -> 14 | DE9: =COUNTIFS($J$2:$J$501, CQ9, $CC$2:$CC$501, "1") -> 1 | DF9: =COUNTIFS($J$2:$J$501, CQ9, $CD$2:$CD$501, "1") -> 0 | DG9: =COUNTIF($J$2:$J$501, CQ9)-DF9-DE9 -> 17
A10: 446 | B10: AIA Group | D10: =CONCATENATE((IF(BM10=1, "CN", "")),(IF(BQ10=1, " NZ", "")),(IF(BU10=1, " SBT", "")),(IF(BY10=1, " RE100", ""))) -> NZ SBT | E10: AJ | F10: 45512 | H10: 3764 | I10: Insurance: Life, Health (stock) | J10: Financial services | K10: Hong Kong | L10: Asia | M10: N | P10: Y | Q10: Targets Set | R10: 1.5°C | S10: 2030 | T10: No | V10: 01/11/2023 | W10: 2023 | X10: N | AA10: N | AN10: C | AO10: company | AP10: Net Zero | AQ10: C | AR10: 2050 | AS10: 2021 | AW10: U | AX10: https://www.aia.com/content/dam/group-wise/en/docs/ESG/AIA_Group_ESG_Report_2023_Summary.pdf | AY10: 2023 | AZ10: Y | BA10: https://www.aia.com/content/dam/group-wise/en/docs/ESG/AIA_Group_ESG_Report_2023_Summary.pdf | BP10: 1 | BQ10: 1 | BS10: 1 | BU10: 1 | BZ10: 1 | CB10: 1 | CE10: 1 | CG10: 1 | CH10: 1 | CM10: =MAX(U10,AR10) -> 2050 | CQ10: Financial services | CR10: =COUNTIFS($J$2:$J$501,CQ10,$S$2:$S$501,"<=2024") -> 0 | CS10: =COUNTIFS($J$2:$J$501,CQ10,$S$2:$S$501,">=2025",$S$2:$S$501,"<=2030") -> 17 | CT10: =COUNTIFS($J$2:$J$501,CQ10,$S$2:$S$501,">2030") -> 1 | CU10: =COUNTIFS($J$2:$J$501,CQ10,$O$2:$O$501,"<=2024") -> 11 | CV10: =COUNTIFS($J$2:$J$501,CQ10,$O$2:$O$501,">=2025",$O$2:$O$501,"<=2030") -> 9 | CW10: =COUNTIFS($J$2:$J$501,CQ10,$O$5:$O$504,">2030") -> 2 | CX10: =COUNTIFS($J$2:$J$501,CQ10,$AB$2:$AB$501,"<=2024") -> 29 | CY10: =COUNTIFS($J$2:$J$501,CQ10,$AB$2:$AB$501,">=2024",$AB$2:$AB$501,"<=2030") -> 13 | CZ10: =COUNTIFS($J$2:$J$501,CQ10,$AB$2:$AB$501,">2030") -> 25 | DA10: =COUNTIFS($J$2:$J$501,CQ10,$CM$2:$CM$501,"<=2024") -> 0 | DB10: =COUNTIFS($J$2:$J$501,CQ10,$CM$2:$CM$501,">=2025",$CM$2:$CM$501,"<=2030") -> 15 | DC10: =COUNTIFS($J$2:$J$501,CQ10,$CM$2:$CM$501,">2030") -> 52 | DD10: =SUM(CR10:DC10) -> 174 | DE10: =COUNTIFS($J$2:$J$501, CQ10, $CC$2:$CC$501, "1") -> 67 | DF10: =COUNTIFS($J$2:$J$501, CQ10, $CD$2:$CD$501, "1") -> 2 | DG10: =COUNTIF($J$2:$J$501, CQ10)-DF10-DE10 -> 58
A11: 324 | B11: AIG | C11: 248 | D11: =CONCATENATE((IF(BM11=1, "CN", "")),(IF(BQ11=1, " NZ", "")),(IF(BU11=1, " SBT", "")),(IF(BY11=1, " RE100", ""))) -> NZ | E11: AJ | F11: 45477 | G11: AJ | H11: 3643 | J11: Financial services | K11: United States of America (USA) | L11: North America | M11: N | P11: N | X11: N | AA11: N | AN11: C+F | AO11: operations and underwriting and investments portfolios | AP11: Net Zero GHG emissions | AQ11: C+F | AR11: 2050 | AS11: 2022 | AW11: U | AX11: https://aig.gcs-web.com/node/53226/pdf | BF11: N | BP11: 1 | BQ11: 1 | BZ11: 1 | CB11: 1 | CE11: 1 | CH11: 1 | CK11: 1 | CL11: 1 | CM11: =MAX(U11,AR11) -> 2050 | CQ11: Food, beverages and agriculture | CR11: =COUNTIFS($J$2:$J$501,CQ11,$S$2:$S$501,"<=2024") -> 0 | CS11: =COUNTIFS($J$2:$J$501,CQ11,$S$2:$S$501,">=2025",$S$2:$S$501,"<=2030") -> 15 | CT11: =COUNTIFS($J$2:$J$501,CQ11,$S$2:$S$501,">2030") -> 1 | CU11: =COUNTIFS($J$2:$J$501,CQ11,$O$2:$O$501,"<=2024") -> 1 | CV11: =COUNTIFS($J$2:$J$501,CQ11,$O$2:$O$501,">=2025",$O$2:$O$501,"<=2030") -> 3 | CW11: =COUNTIFS($J$2:$J$501,CQ11,$O$5:$O$504,">2030") -> 2 | CX11: =COUNTIFS($J$2:$J$501,CQ11,$AB$2:$AB$501,"<=2024") -> 0 | CY11: =COUNTIFS($J$2:$J$501,CQ11,$AB$2:$AB$501,">=2024",$AB$2:$AB$501,"<=2030") -> 3 | CZ11: =COUNTIFS($J$2:$J$501,CQ11,$AB$2:$AB$501,">2030") -> 0 | DA11: =COUNTIFS($J$2:$J$501,CQ11,$CM$2:$CM$501,"<=2024") -> 0 | DB11: =COUNTIFS($J$2:$J$501,CQ11,$CM$2:$CM$501,">=2025",$CM$2:$CM$501,"<=2030") -> 0 | DC11: =COUNTIFS($J$2:$J$501,CQ11,$CM$2:$CM$501,">2030") -> 13 | DD11: =SUM(CR11:DC11) -> 38 | DE11: =COUNTIFS($J$2:$J$501, CQ11, $CC$2:$CC$501, "1") -> 8 | DF11: =COUNTIFS($J$2:$J$501, CQ11, $CD$2:$CD$501, "1") -> 0 | DG11: =COUNTIF($J$2:$J$501, CQ11)-DF11-DE11 -> 13
A12: 496 | B12: Air France-KLM Group | D12: =CONCATENATE((IF(BM12=1, "CN", "")),(IF(BQ12=1, " NZ", "")),(IF(BU12=1, " SBT", "")),(IF(BY12=1, " RE100", ""))) -> NZ SBT | E12: AJ | F12: 45512 | H12: 1009.7 | I12: Airlines | J12: Transportation and logistics | K12: France | L12: Europe | M12: N | P12: Y | Q12: Targets Set | R12: Well-below 2°C | S12: 2030 | T12: No | V12: 01/01/2023 | W12: 2023 | X12: N | AA12: N | AN12: C | AO12: activities | AP12: Net Zero | AQ12: C | AR12: 2050 | AS12: 2021 | AW12: U | AX12: https://www.airfranceklm.com/en/our-commitments | AY12: 2022 | AZ12: Y | BA12: https://sustainabilityreport.airfranceklm.com/sustainability-report-2022-en/ | BP12: 1 | BQ12: 1 | BS12: 1 | BU12: 1 | BZ12: 1 | CB12: 1 | CE12: 1 | CG12: 1 | CH12: 1 | CM12: =MAX(U12,AR12) -> 2050 | CQ12: Health care and pharmaceuticals | CR12: =COUNTIFS($J$2:$J$501,CQ12,$S$2:$S$501,"<=2024") -> 0 | CS12: =COUNTIFS($J$2:$J$501,CQ12,$S$2:$S$501,">=2025",$S$2:$S$501,"<=2030") -> 15 | CT12: =COUNTIFS($J$2:$J$501,CQ12,$S$2:$S$501,">2030") -> 1 | CU12: =COUNTIFS($J$2:$J$501,CQ12,$O$2:$O$501,"<=2024") -> 1 | CV12: =COUNTIFS($J$2:$J$501,CQ12,$O$2:$O$501,">=2025",$O$2:$O$501,"<=2030") -> 8 | CW12: =COUNTIFS($J$2:$J$501,CQ12,$O$5:$O$504,">2030") -> 2 | CX12: =COUNTIFS($J$2:$J$501,CQ12,$AB$2:$AB$501,"<=2024") -> 1 | CY12: =COUNTIFS($J$2:$J$501,CQ12,$AB$2:$AB$501,">=2024",$AB$2:$AB$501,"<=2030") -> 8 | CZ12: =COUNTIFS($J$2:$J$501,CQ12,$AB$2:$AB$501,">2030") -> 3 | DA12: =COUNTIFS($J$2:$J$501,CQ12,$CM$2:$CM$501,"<=2024") -> 0 | DB12: =COUNTIFS($J$2:$J$501,CQ12,$CM$2:$CM$501,">=2025",$CM$2:$CM$501,"<=2030") -> 1 | DC12: =COUNTIFS($J$2:$J$501,CQ12,$CM$2:$CM$501,">2030") -> 14 | DD12: =SUM(CR12:DC12) -> 54 | DE12: =COUNTIFS($J$2:$J$501, CQ12, $CC$2:$CC$501, "1") -> 12 | DF12: =COUNTIFS($J$2:$J$501, CQ12, $CD$2:$CD$501, "1") -> 1 | DG12: =COUNTIF($J$2:$J$501, CQ12)-DF12-DE12 -> 12
A13: 183 | B13: Airbus | C13: 219 | D13: =CONCATENATE((IF(BM13=1, "CN", "")),(IF(BQ13=1, " NZ", "")),(IF(BU13=1, " SBT", "")),(IF(BY13=1, " RE100", ""))) -> NZ SBT | E13: DT - AJ | F13: 45477 | G13: DT | H13: 4096.1 | J13: Aerospace and defense | K13: Netherlands | L13: Europe | M13: N | P13: Y | Q13: Targets Set | R13: 1.5Â°C | S13: 2030 | T13: No | V13: 44958 | W13: 2023 | X13: N | AA13: N | AN13: C | AO13: undefined | AP13: Net Zero | AQ13: C | AR13: 2050 | AS13: 2020 | AW13: Y | AX13: https://www.airbus.com/en/sustainability/respecting-the-planet/decarbonisation | BP13: 1 | BQ13: 1 | BS13: 1 | BU13: 1 | BZ13: 1 | CB13: 1 | CC13: 1 | CE13: 1 | CG13: 1 | CH13: 1 | CM13: =MAX(U13,AR13) -> 2050 | CQ13: Household and personal products | CR13: =COUNTIFS($J$2:$J$501,CQ13,$S$2:$S$501,"<=2024") -> 0 | CS13: =COUNTIFS($J$2:$J$501,CQ13,$S$2:$S$501,">=2025",$S$2:$S$501,"<=2030") -> 4 | CT13: =COUNTIFS($J$2:$J$501,CQ13,$S$2:$S$501,">2030") -> 0 | CU13: =COUNTIFS($J$2:$J$501,CQ13,$O$2:$O$501,"<=2024") -> 0 | CV13: =COUNTIFS($J$2:$J$501,CQ13,$O$2:$O$501,">=2025",$O$2:$O$501,"<=2030") -> 3 | CW13: =COUNTIFS($J$2:$J$501,CQ13,$O$5:$O$504,">2030") -> 0 | CX13: =COUNTIFS($J$2:$J$501,CQ13,$AB$2:$AB$501,"<=2024") -> 1 | CY13: =COUNTIFS($J$2:$J$501,CQ13,$AB$2:$AB$501,">=2024",$AB$2:$AB$501,"<=2030") -> 1 | CZ13: =COUNTIFS($J$2:$J$501,CQ13,$AB$2:$AB$501,">2030") -> 0 | DA13: =COUNTIFS($J$2:$J$501,CQ13,$CM$2:$CM$501,"<=2024") -> 0 | DB13: =COUNTIFS($J$2:$J$501,CQ13,$CM$2:$CM$501,">=2025",$CM$2:$CM$501,"<=2030") -> 0 | DC13: =COUNTIFS($J$2:$J$501,CQ13,$CM$2:$CM$501,">2030") -> 5 | DD13: =SUM(CR13:DC13) -> 14 | DE13: =COUNTIFS($J$2:$J$501, CQ13, $CC$2:$CC$501, "1") -> 2 | DF13: =COUNTIFS($J$2:$J$501, CQ13, $CD$2:$CD$501, "1") -> 2 | DG13: =COUNTIF($J$2:$J$501, CQ13)-DF13-DE13 -> 3
A14: 462 | B14: Aisin | C14: 470 | D14: =CONCATENATE((IF(BM14=1, "CN", "")),(IF(BQ14=1, " NZ", "")),(IF(BU14=1, " SBT", "")),(IF(BY14=1, " RE100", ""))) -> CN SBT | E14: DT * | F14: 45511 | G14: DT | H14: 628.3 | J14: Automotive | K14: Japan | L14: Asia | M14: N | P14: Y | Q14: Targets Set | R14: 1.5Â°C | S14: 2031 | T14: No | V14: 45261 | W14: 2023 | X14: C | Y14: products and production | Z14: Carbon Neutrality | AA14: C | AB14: 2035 | AC14: 2021 | AG14: Y | AH14: 2023 | AI14: Y | AJ14: https://www.aisin.com/en/sustainability/report/pdf/aisin_ar2023_en_a3.pdf | AL14: https://www.aisin.com/en/sustainability/report/pdf/aisin_ar2022_en_a3.pdf | AN14: N | AQ14: N | BL14: 1 | BM14: 1 | BT14: 1 | BU14: 1 | BZ14: 1 | CB14: 1 | CC14: 1 | CE14: 1 | CH14: 1 | CQ14: Industrial goods | CR14: =COUNTIFS($J$2:$J$501,CQ14,$S$2:$S$501,"<=2024") -> 0 | CS14: =COUNTIFS($J$2:$J$501,CQ14,$S$2:$S$501,">=2025",$S$2:$S$501,"<=2030") -> 16 | CT14: =COUNTIFS($J$2:$J$501,CQ14,$S$2:$S$501,">2030") -> 2 | CU14: =COUNTIFS($J$2:$J$501,CQ14,$O$2:$O$501,"<=2024") -> 0 | CV14: =COUNTIFS($J$2:$J$501,CQ14,$O$2:$O$501,">=2025",$O$2:$O$501,"<=2030") -> 5 | CW14: =COUNTIFS($J$2:$J$501,CQ14,$O$5:$O$504,">2030") -> 2 | CX14: =COUNTIFS($J$2:$J$501,CQ14,$AB$2:$AB$501,"<=2024") -> 0 | CY14: =COUNTIFS($J$2:$J$501,CQ14,$AB$2:$AB$501,">=2024",$AB$2:$AB$501,"<=2030") -> 5 | CZ14: =COUNTIFS($J$2:$J$501,CQ14,$AB$2:$AB$501,">2030") -> 7 | DA14: =COUNTIFS($J$2:$J$501,CQ14,$CM$2:$CM$501,"<=2024") -> 0 | DB14: =COUNTIFS($J$2:$J$501,CQ14,$CM$2:$CM$501,">=2025",$CM$2:$CM$501,"<=2030") -> 2 | DC14: =COUNTIFS($J$2:$J$501,CQ14,$CM$2:$CM$501,">2030") -> 18 | DD14: =SUM(CR14:DC14) -> 57 | DE14: =COUNTIFS($J$2:$J$501, CQ14, $CC$2:$CC$501, "1") -> 13 | DF14: =COUNTIFS($J$2:$J$501, CQ14, $CD$2:$CD$501, "1") -> 0 | DG14: =COUNTIF($J$2:$J$501, CQ14)-DF14-DE14 -> 21
A15: 152 | B15: Albertsons | C15: 164 | D15: =CONCATENATE((IF(BM15=1, "CN", "")),(IF(BQ15=1, " NZ", "")),(IF(BU15=1, " SBT", "")),(IF(BY15=1, " RE100", ""))) -> NZ SBT | E15: DT | F15: 45476 | G15: AJ | H15: 1296 | J15: Retail | K15: United States of America (USA) | L15: North America | M15: N | P15: Y | Q15: Targets Set | R15: 1.5Â°C | S15: 2030 | T15: No | V15: 44652 | W15: 2022 | X15: N | AA15: N | AN15: C | AO15: Scope 1 and 2 | AP15: Net Zero | AQ15: C | AR15: 2040 | AS15: 2022 | AW15: Y | AX15: https://s29.q4cdn.com/239956855/files/our_impact/sustainability_doc/albcdacsiv199540_aci_23_esg-report-1-2.pdf| https://www.supermarketnews.com/sustainability/albertsons-unveils-recipe-change-esg-platform | BC15: We work with energy providers in our operating areas to purchase utility-scale renewable energy and renewable energy credits. | BP15: 1 | BQ15: 1 | BS15: 1 | BU15: 1 | BZ15: 1 | CB15: 1 | CC15: 1 | CE15: 1 | CG15: 1 | CH15: 1 | CM15: =MAX(U15,AR15) -> 2040 | CQ15: Metals and mining | CR15: =COUNTIFS($J$2:$J$501,CQ15,$S$2:$S$501,"<=2024") -> 0 | CS15: =COUNTIFS($J$2:$J$501,CQ15,$S$2:$S$501,">=2025",$S$2:$S$501,"<=2030") -> 1 | CT15: =COUNTIFS($J$2:$J$501,CQ15,$S$2:$S$501,">2030") -> 0 | CU15: =COUNTIFS($J$2:$J$501,CQ15,$O$2:$O$501,"<=2024") -> 0 | CV15: =COUNTIFS($J$2:$J$501,CQ15,$O$2:$O$501,">=2025",$O$2:$O$501,"<=2030") -> 0 | CW15: =COUNTIFS($J$2:$J$501,CQ15,$O$5:$O$504,">2030") -> 1 | CX15: =COUNTIFS($J$2:$J$501,CQ15,$AB$2:$AB$501,"<=2024") -> 0 | CY15: =COUNTIFS($J$2:$J$501,CQ15,$AB$2:$AB$501,">=2024",$AB$2:$AB$501,"<=2030") -> 0 | CZ15: =COUNTIFS($J$2:$J$501,CQ15,$AB$2:$AB$501,">2030") -> 19 | DA15: =COUNTIFS($J$2:$J$501,CQ15,$CM$2:$CM$501,"<=2024") -> 0 | DB15: =COUNTIFS($J$2:$J$501,CQ15,$CM$2:$CM$501,">=2025",$CM$2:$CM$501,"<=2030") -> 0 | DC15: =COUNTIFS($J$2:$J$501,CQ15,$CM$2:$CM$501,">2030") -> 10 | DD15: =SUM(CR15:DC15) -> 31 | DE15: =COUNTIFS($J$2:$J$501, CQ15, $CC$2:$CC$501, "1") -> 9 | DF15: =COUNTIFS($J$2:$J$501, CQ15, $CD$2:$CD$501, "1") -> 0 | DG15: =COUNTIF($J$2:$J$501, CQ15)-DF15-DE15 -> 31
A16: 70 | B16: Alibaba Group Holding | C16: 68 | D16: =CONCATENATE((IF(BM16=1, "CN", "")),(IF(BQ16=1, " NZ", "")),(IF(BU16=1, " SBT", "")),(IF(BY16=1, " RE100", ""))) -> CN SBT | E16: DT - AJ | F16: 45475 | G16: DT | H16: 11165.1 | J16: Retail | K16: China | L16: Asia | M16: N | P16: N | Q16: Committed | S16: 2030 | T16: Yes | V16: 44531 | W16: 2021 | X16: C | Y16: operations | Z16: carbon neutrality | AA16: C | AB16: 2030 | AC16: 2021 | AG16: Y | AH16: 2023 | AI16: Y | AJ16: https://data.alibabagroup.com/ecms-files/1509739361/fcaefa3d-0989-48fb-b003-fa96aa04880e/2023%20Alibaba%20ESG%20Report-Final.pdf | AL16: https://data.alibabagroup.com/ecms-files/1509739361/fcaefa3d-0989-48fb-b003-fa96aa04880e/2023%20Alibaba%20ESG%20Report-Final.pdf | AM16: In 2021, Alibaba set ambitious targets of achieving carbon neutrality in our own operations and halving the energy intensity across our value chain by 2030 and driving emission reduction of 1.5 gigatons over 15 years in our platform ecosystem s. Combining these efforts with our projects on carbon removal and carbon offsets, we have achieved a year-over-year decrease of 5.7%1 of our carbon intensity throughout the value chain | AN16: N | AQ16: N | BK16: 1 | BM16: 1 | BS16: 1 | BU16: 1 | BZ16: 1 | CA16: 1 | CB16: 1 | CC16: 1 | CE16: 1 | CG16: 1 | CH16: 1 | CQ16: Oil and gas | CR16: =COUNTIFS($J$2:$J$501,CQ16,$S$2:$S$501,"<=2024") -> 0 | CS16: =COUNTIFS($J$2:$J$501,CQ16,$S$2:$S$501,">=2025",$S$2:$S$501,"<=2030") -> 0 | CT16: =COUNTIFS($J$2:$J$501,CQ16,$S$2:$S$501,">2030") -> 0 | CU16: =COUNTIFS($J$2:$J$501,CQ16,$O$2:$O$501,"<=2024") -> 0 | CV16: =COUNTIFS($J$2:$J$501,CQ16,$O$2:$O$501,">=2025",$O$2:$O$501,"<=2030") -> 0 | CW16: =COUNTIFS($J$2:$J$501,CQ16,$O$5:$O$504,">2030") -> 3 | CX16: =COUNTIFS($J$2:$J$501,CQ16,$AB$2:$AB$501,"<=2024") -> 0 | CY16: =COUNTIFS($J$2:$J$501,CQ16,$AB$2:$AB$501,">=2024",$AB$2:$AB$501,"<=2030") -> 3 | CZ16: =COUNTIFS($J$2:$J$501,CQ16,$AB$2:$AB$501,">2030") -> 12 | DA16: =COUNTIFS($J$2:$J$501,CQ16,$CM$2:$CM$501,"<=2024") -> 0 | DB16: =COUNTIFS($J$2:$J$501,CQ16,$CM$2:$CM$501,">=2025",$CM$2:$CM$501,"<=2030") -> 0 | DC16: =COUNTIFS($J$2:$J$501,CQ16,$CM$2:$CM$501,">2030") -> 20 | DD16: =SUM(CR16:DC16) -> 38 | DE16: =COUNTIFS($J$2:$J$501, CQ16, $CC$2:$CC$501, "1") -> 22 | DF16: =COUNTIFS($J$2:$J$501, CQ16, $CD$2:$CD$501, "1") -> 0 | DG16: =COUNTIF($J$2:$J$501, CQ16)-DF16-DE16 -> 21
A17: 177 | B17: Alimentation Couche-Tard | C17: 214 | D17: =CONCATENATE((IF(BM17=1, "CN", "")),(IF(BQ17=1, " NZ", "")),(IF(BU17=1, " SBT", "")),(IF(BY17=1, " RE100", ""))) -> CN | E17: AJ | F17: 45476 | G17: DT | H17: 3090.9 | J17: Retail | K17: Canada | L17: North America | M17: N | P17: N | X17: C | Y17: scope 1 and 2 | Z17: carbon neutral | AA17: C | AB17: 2030 | AC17: 2024 | AG17: Y | AH17: 2024 | AI17: Y | AJ17: https://corpo.couche-tard.com/wp-content/uploads/2024/06/ACT_Sustainability_Report_2024.pdf | AL17: https://corpo.couche-tard.com/wp-content/uploads/2024/06/ACT_Sustainability_Report_2024.pdf | AN17: N | AQ17: N | BD17: Y | BE17: https://corpo.couche-tard.com/wp-content/uploads/2024/06/ACT_Sustainability_Report_2024.pdf | BF17: N | BI17: BAD: we aim to reduce our Scope 1 and 2Â emissions by 50%, using a range of solution including carbon credits if needed. | BK17: 1 | BM17: 1 | BZ17: 1 | CA17: 1 | CB17: 1 | CC17: 1 | CE17: 1 | CG17: 1 | CH17: 1 | CQ17: Real estate | CR17: =COUNTIFS($J$2:$J$501,CQ17,$S$2:$S$501,"<=2024") -> 0 | CS17: =COUNTIFS($J$2:$J$501,CQ17,$S$2:$S$501,">=2025",$S$2:$S$501,"<=2030") -> 0 | CT17: =COUNTIFS($J$2:$J$501,CQ17,$S$2:$S$501,">2030") -> 0 | CU17: =COUNTIFS($J$2:$J$501,CQ17,$O$2:$O$501,"<=2024") -> 0 | CV17: =COUNTIFS($J$2:$J$501,CQ17,$O$2:$O$501,">=2025",$O$2:$O$501,"<=2030") -> 0 | CW17: =COUNTIFS($J$2:$J$501,CQ17,$O$5:$O$504,">2030") -> 0 | CX17: =COUNTIFS($J$2:$J$501,CQ17,$AB$2:$AB$501,"<=2024") -> 0 | CY17: =COUNTIFS($J$2:$J$501,CQ17,$AB$2:$AB$501,">=2024",$AB$2:$AB$501,"<=2030") -> 0 | CZ17: =COUNTIFS($J$2:$J$501,CQ17,$AB$2:$AB$501,">2030") -> 2 | DA17: =COUNTIFS($J$2:$J$501,CQ17,$CM$2:$CM$501,"<=2024") -> 0 | DB17: =COUNTIFS($J$2:$J$501,CQ17,$CM$2:$CM$501,">=2025",$CM$2:$CM$501,"<=2030") -> 0 | DC17: =COUNTIFS($J$2:$J$501,CQ17,$CM$2:$CM$501,">2030") -> 0 | DD17: =SUM(CR17:DC17) -> 2 | DE17: =COUNTIFS($J$2:$J$501, CQ17, $CC$2:$CC$501, "1") -> 0 | DF17: =COUNTIFS($J$2:$J$501, CQ17, $CD$2:$CD$501, "1") -> 0 | DG17: =COUNTIF($J$2:$J$501, CQ17)-DF17-DE17 -> 3
A18: 82 | B18: Allianz | C18: 67 | D18: =CONCATENATE((IF(BM18=1, "CN", "")),(IF(BQ18=1, " NZ", "")),(IF(BU18=1, " SBT", "")),(IF(BY18=1, " RE100", ""))) -> CN NZ RE100 | E18: DT | F18: 45475 | G18: DT | H18: 9233.3 | J18: Financial services | K18: Germany | L18: Europe | M18: Y | N18: 2018 | O18: 2023 | P18: N | X18: C | Y18: operations | Z18: carbon neutral | AA18: C | AB18: 2012 | AC18: 2019 | AG18: Y | AH18: 2022 | AI18: Y | AJ18: https://www.allianz.com/content/dam/onemarketing/azcom/Allianz_com/sustainability/documents/Allianz_Group_Sustainability_Report_2022-web.pdf | AL18: https://www.allianz.com/content/dam/onemarketing/azcom/Allianz_com/sustainability/documents/Allianz_Group_Sustainability_Report_2022-web.pdf | AN18: F | AO18: Investment Portfolio | AP18: Net Zero | AQ18: F | AR18: 2050 | AS18: 2020 | AW18: R | AX18: https://www.allianz.com/content/dam/onemarketing/azcom/Allianz_com/sustainability/documents/Allianz_Group_Sustainability_Report_2023-web.pdf | BC18: ith the publication of our first comprehensive net-zero transition plan in 2023, we further detailed our commitment to achieve net-zero emissions by 2050, covering proprietary investments and, for the first time, our P&C insurance business The (1) Net Zero 2050 scenario is determined by an orderly transition to net-zero emissions by 2050 following the target to limit global warming to 1.5Â°C through stringent climate policies at the cost of moderate economic strain in the initial years. | BJ18: 1 | BM18: 1 | BP18: 1 | BQ18: 1 | BV18: 1 | BY18: 1 | BZ18: 1 | CA18: 1 | CB18: 1 | CC18: 1 | CE18: 1 | CF18: 1 | CG18: 1 | CH18: 1 | CK18: 1 | CL18: 1 | CM18: =MAX(U18,AR18) -> 2050 | CQ18: Retail | CR18: =COUNTIFS($J$2:$J$501,CQ18,$S$2:$S$501,"<=2024") -> 1 | CS18: =COUNTIFS($J$2:$J$501,CQ18,$S$2:$S$501,">=2025",$S$2:$S$501,"<=2030") -> 24 | CT18: =COUNTIFS($J$2:$J$501,CQ18,$S$2:$S$501,">2030") -> 3 | CU18: =COUNTIFS($J$2:$J$501,CQ18,$O$2:$O$501,"<=2024") -> 0 | CV18: =COUNTIFS($J$2:$J$501,CQ18,$O$2:$O$501,">=2025",$O$2:$O$501,"<=2030") -> 6 | CW18: =COUNTIFS($J$2:$J$501,CQ18,$O$5:$O$504,">2030") -> 1 | CX18: =COUNTIFS($J$2:$J$501,CQ18,$AB$2:$AB$501,"<=2024") -> 1 | CY18: =COUNTIFS($J$2:$J$501,CQ18,$AB$2:$AB$501,">=2024",$AB$2:$AB$501,"<=2030") -> 3 | CZ18: =COUNTIFS($J$2:$J$501,CQ18,$AB$2:$AB$501,">2030") -> 6 | DA18: =COUNTIFS($J$2:$J$501,CQ18,$CM$2:$CM$501,"<=2024") -> 0 | DB18: =COUNTIFS($J$2:$J$501,CQ18,$CM$2:$CM$501,">=2025",$CM$2:$CM$501,"<=2030") -> 0 | DC18: =COUNTIFS($J$2:$J$501,CQ18,$CM$2:$CM$501,">2030") -> 25 | DD18: =SUM(CR18:DC18) -> 70 | DE18: =COUNTIFS($J$2:$J$501, CQ18, $CC$2:$CC$501, "1") -> 15 | DF18: =COUNTIFS($J$2:$J$501, CQ18, $CD$2:$CD$501, "1") -> 2 | DG18: =COUNTIF($J$2:$J$501, CQ18)-DF18-DE18 -> 29
A19: 244 | B19: Allstate | C19: 276 | D19: =CONCATENATE((IF(BM19=1, "CN", "")),(IF(BQ19=1, " NZ", "")),(IF(BU19=1, " SBT", "")),(IF(BY19=1, " RE100", ""))) -> NZ | E19: EC | F19: 45477 | G19: AJ | H19: -188 | J19: Financial services | K19: United States of America (USA) | L19: North America | M19: N | P19: N | X19: N | AA19: N | AN19: C | AO19: Scope 1 and 2 emissions | AP19: Net Zero | AQ19: C | AR19: 2030 | AS19: 2022 | AW19: U | AX19: https://delivery.contenthub.allstate.com/api/public/content/2023-sustainability-report?v=67b36ebf | BC19: https://delivery.contenthub.allstate.com/api/public/content/4860fd4e881a42899a718e0db304a33e?v=878016db#:~:text=In%20December%202022%2C%20Allstate%20announced,a%20goal%20for%20financed%20emissions. | BO19: 1 | BQ19: 1 | BZ19: 1 | CA19: 1 | CB19: 1 | CE19: 1 | CG19: 1 | CH19: 1 | CM19: =MAX(U19,AR19) -> 2030 | CQ19: Technology | CR19: =COUNTIFS($J$2:$J$501,CQ19,$S$2:$S$501,"<=2024") -> 1 | CS19: =COUNTIFS($J$2:$J$501,CQ19,$S$2:$S$501,">=2025",$S$2:$S$501,"<=2030") -> 10 | CT19: =COUNTIFS($J$2:$J$501,CQ19,$S$2:$S$501,">2030") -> 3 | CU19: =COUNTIFS($J$2:$J$501,CQ19,$O$2:$O$501,"<=2024") -> 4 | CV19: =COUNTIFS($J$2:$J$501,CQ19,$O$2:$O$501,">=2025",$O$2:$O$501,"<=2030") -> 1 | CW19: =COUNTIFS($J$2:$J$501,CQ19,$O$5:$O$504,">2030") -> 0 | CX19: =COUNTIFS($J$2:$J$501,CQ19,$AB$2:$AB$501,"<=2024") -> 3 | CY19: =COUNTIFS($J$2:$J$501,CQ19,$AB$2:$AB$501,">=2024",$AB$2:$AB$501,"<=2030") -> 2 | CZ19: =COUNTIFS($J$2:$J$501,CQ19,$AB$2:$AB$501,">2030") -> 2 | DA19: =COUNTIFS($J$2:$J$501,CQ19,$CM$2:$CM$501,"<=2024") -> 2 | DB19: =COUNTIFS($J$2:$J$501,CQ19,$CM$2:$CM$501,">=2025",$CM$2:$CM$501,"<=2030") -> 3 | DC19: =COUNTIFS($J$2:$J$501,CQ19,$CM$2:$CM$501,">2030") -> 5 | DD19: =SUM(CR19:DC19) -> 36 | DE19: =COUNTIFS($J$2:$J$501, CQ19, $CC$2:$CC$501, "1") -> 11 | DF19: =COUNTIFS($J$2:$J$501, CQ19, $CD$2:$CD$501, "1") -> 0 | DG19: =COUNTIF($J$2:$J$501, CQ19)-DF19-DE19 -> 6
A20: 17 | B20: Alphabet | C20: 17 | D20: =CONCATENATE((IF(BM20=1, "CN", "")),(IF(BQ20=1, " NZ", "")),(IF(BU20=1, " SBT", "")),(IF(BY20=1, " RE100", ""))) -> NZ SBT | E20: DT | F20: 45475 | G20: AJ | H20: 73795 | J20: Technology | K20: United States of America (USA) | L20: North America | M20: N | P20: N | Q20: Committed | S20: 2030 | T20: No | V20: 44805 | W20: 2022 | X20: N | AA20: N | AN20: V | AO20: operations and value chain | AP20: Net Zero | AQ20: V | AR20: 2030 | AS20: 2020 | AW20: Y | AX20: https://www.gstatic.com/gumdrop/sustainability/google-2023-environmental-report.pdf | AY20: 2024 | AZ20: Y | BA20: https://www.gstatic.com/gumdrop/sustainability/google-2024-environmental-report.pdf | BC20: Our operational emissions are then further compensated for by high-quality carbon credits enabled through contracted carbon offset projects, which capture and destroy highly potent GHGs. Our operational emissions are then further compensated for by high-quality carbon credits enabled through contracted carbon offset projects, which capture and destroy highly potent GHGs. | BO20: 1 | BQ20: 1 | BS20: 1 | BU20: 1 | BZ20: 1 | CB20: 1 | CC20: 1 | CE20: 1 | CG20: 1 | CH20: 1 | CJ20: 1 | CL20: 1 | CM20: =MAX(U20,AR20) -> 2030 | CQ20: Telecommunications and media | CR20: =COUNTIFS($J$2:$J$501,CQ20,$S$2:$S$501,"<=2024") -> 1 | CS20: =COUNTIFS($J$2:$J$501,CQ20,$S$2:$S$501,">=2025",$S$2:$S$501,"<=2030") -> 11 | CT20: =COUNTIFS($J$2:$J$501,CQ20,$S$2:$S$501,">2030") -> 1 | CU20: =COUNTIFS($J$2:$J$501,CQ20,$O$2:$O$501,"<=2024") -> 1 | CV20: =COUNTIFS($J$2:$J$501,CQ20,$O$2:$O$501,">=2025",$O$2:$O$501,"<=2030") -> 4 | CW20: =COUNTIFS($J$2:$J$501,CQ20,$O$5:$O$504,">2030") -> 2 | CX20: =COUNTIFS($J$2:$J$501,CQ20,$AB$2:$AB$501,"<=2024") -> 0 | CY20: =COUNTIFS($J$2:$J$501,CQ20,$AB$2:$AB$501,">=2024",$AB$2:$AB$501,"<=2030") -> 3 | CZ20: =COUNTIFS($J$2:$J$501,CQ20,$AB$2:$AB$501,">2030") -> 8 | DA20: =COUNTIFS($J$2:$J$501,CQ20,$CM$2:$CM$501,"<=2024") -> 1 | DB20: =COUNTIFS($J$2:$J$501,CQ20,$CM$2:$CM$501,">=2025",$CM$2:$CM$501,"<=2030") -> 1 | DC20: =COUNTIFS($J$2:$J$501,CQ20,$CM$2:$CM$501,">2030") -> 7 | DD20: =SUM(CR20:DC20) -> 40 | DE20: =COUNTIFS($J$2:$J$501, CQ20, $CC$2:$CC$501, "1") -> 8 | DF20: =COUNTIFS($J$2:$J$501, CQ20, $CD$2:$CD$501, "1") -> 0 | DG20: =COUNTIF($J$2:$J$501, CQ20)-DF20-DE20 -> 12
A21: 214 | B21: Aluminum Corp. of China | C21: 166 | D21: =CONCATENATE((IF(BM21=1, "CN", "")),(IF(BQ21=1, " NZ", "")),(IF(BU21=1, " SBT", "")),(IF(BY21=1, " RE100", ""))) | E21: DT | F21: 45476 | G21: AJ | H21: 876.5 | J21: Metals and mining | K21: China | L21: Asia | M21: N | P21: N | X21: G | Y21: Scope 1 and 2 | Z21: Carbon Neutrality | AA21: G | AB21: 2060 | AC21: 2021 | AL21: https://www.chalco.com.cn/en/tzzgxen/tzggen/202203/P020220323614314766465.pdf | AM21: refers to the statement made by General Secretary Xi Jinping at the General Debate of the 75th session of the UN General Assembly that â€œChina will scale up its Intended Nationally Determined Contributions (INDCs) by adopting more vigorous policies and measures and aim to have CO2 emissions peak before 2030 and achieve carbon neutrality before 2060â€ | AN21: N | AQ21: N | CQ21: Transportation and logistics | CR21: =COUNTIFS($J$2:$J$501,CQ21,$S$2:$S$501,"<=2024") -> 0 | CS21: =COUNTIFS($J$2:$J$501,CQ21,$S$2:$S$501,">=2025",$S$2:$S$501,"<=2030") -> 8 | CT21: =COUNTIFS($J$2:$J$501,CQ21,$S$2:$S$501,">2030") -> 3 | CU21: =COUNTIFS($J$2:$J$501,CQ21,$O$2:$O$501,"<=2024") -> 0 | CV21: =COUNTIFS($J$2:$J$501,CQ21,$O$2:$O$501,">=2025",$O$2:$O$501,"<=2030") -> 0 | CW21: =COUNTIFS($J$2:$J$501,CQ21,$O$5:$O$504,">2030") -> 0 | CX21: =COUNTIFS($J$2:$J$501,CQ21,$AB$2:$AB$501,"<=2024") -> 1 | CY21: =COUNTIFS($J$2:$J$501,CQ21,$AB$2:$AB$501,">=2024",$AB$2:$AB$501,"<=2030") -> 0 | CZ21: =COUNTIFS($J$2:$J$501,CQ21,$AB$2:$AB$501,">2030") -> 8 | DA21: =COUNTIFS($J$2:$J$501,CQ21,$CM$2:$CM$501,"<=2024") -> 0 | DB21: =COUNTIFS($J$2:$J$501,CQ21,$CM$2:$CM$501,">=2025",$CM$2:$CM$501,"<=2030") -> 0 | DC21: =COUNTIFS($J$2:$J$501,CQ21,$CM$2:$CM$501,">2030") -> 9 | DD21: =SUM(CR21:DC21) -> 29 | DE21: =COUNTIFS($J$2:$J$501, CQ21, $CC$2:$CC$501, "1") -> 5 | DF21: =COUNTIFS($J$2:$J$501, CQ21, $CD$2:$CD$501, "1") -> 1 | DG21: =COUNTIF($J$2:$J$501, CQ21)-DF21-DE21 -> 14
A22: 2 | B22: Amazon | C22: 4 | D22: =CONCATENATE((IF(BM22=1, "CN", "")),(IF(BQ22=1, " NZ", "")),(IF(BU22=1, " SBT", "")),(IF(BY22=1, " RE100", ""))) -> NZ | E22: DT | F22: 45474 | G22: AJ | H22: 30425 | J22: Retail | K22: United States of America (USA) | L22: North America | M22: N | P22: N | Q22: Removed | T22: No | V22: 43983 | W22: 2020 | X22: N | AA22: N | AN22: C | AO22: Scope 1 and 2 | AP22: Net Zero | AQ22: C | AR22: 2040 | AS22: 2019 | AW22: Y | AX22: https://sustainability.aboutamazon.com/2022-sustainability-report.pdf https://s3.amazonaws.com/sustainabledevelopment.report/2023/sustainable-development-report-2023.pdf | AY22: 2023 | AZ22: Y | BA22: https://sustainability.aboutamazon.com/2023-sustainability-report.pdf | BP22: 1 | BQ22: 1 | BZ22: 1 | CB22: 1 | CC22: 1 | CE22: 1 | CH22: 1 | CM22: =MAX(U22,AR22) -> 2040 | CQ22: sum | CR22: =SUM(CR5:CR21) -> 4 | CS22: =SUM(CS5:CS21) -> 148 | CT22: =SUM(CT5:CT21) -> 21 | CU22: =SUM(CU5:CU21) -> 19 | CV22: =SUM(CV5:CV21) -> 40 | CW22: =SUM(CW5:CW21) -> 18 | CX22: =SUM(CX5:CX21) -> 40 | CY22: =SUM(CY5:CY21) -> 47 | ... DG22: =SUM(DG5:DG21) -> 284
A23: 328 | B23: America Movil | C23: 349 | D23: =CONCATENATE((IF(BM23=1, "CN", "")),(IF(BQ23=1, " NZ", "")),(IF(BU23=1, " SBT", "")),(IF(BY23=1, " RE100", ""))) -> SBT | E23: EC | F23: 45482 | G23: DT | H23: 4291.5 | J23: Telecommunications and media | K23: United States of America (USA) | L23: North America | M23: N | P23: Y | Q23: Targets Set | R23: 1.5Â°C | S23: 2030 | T23: No | V23: 44044 | W23: 2020 | X23: N | AA23: N | AN23: N | AQ23: N | BS23: 1 | BU23: 1 | CE23: 1 | CG23: 1 | CH23: 1 | CR23: SBTi short term | CU23: RE100 | CX23: Carbon Neutral | DA23: Net Zero | DD23: sum
A24: 278 | B24: American Airlines Group | C24: 291 | D24: =CONCATENATE((IF(BM24=1, "CN", "")),(IF(BQ24=1, " NZ", "")),(IF(BU24=1, " SBT", "")),(IF(BY24=1, " RE100", ""))) -> NZ SBT | E24: DT | F24: 45478 | G24: AJ | H24: 822 | J24: Transportation and Logistics | K24: United States of America (USA) | L24: North America | M24: N | P24: Y | Q24: Targets Set | R24: Well-below 2Â°C | S24: 2035 | T24: No | V24: 44652 | W24: 2022 | X24: N | AA24: N | AN24: C | AO24: undefined | AP24: Net Zero | AQ24: C | AR24: 2050 | AS24: 2020 | AW24: Y | AX24: https://s202.q4cdn.com/986123435/files/images/esg/American-Airlines-Sustainability-Report-2023.pdf https://www.unpri.org/pri-blog/seven-major-companies-that-committed-to-net-zero-emissions-in-2020/6909.article | BP24: 1 | BQ24: 1 | BT24: 1 | BU24: 1 | BZ24: 1 | CB24: 1 | CC24: 1 | CE24: 1 | CH24: 1 | CM24: =MAX(U24,AR24) -> 2050 | CQ24: region | CR24: <=2024 | CS24: 2025-2030 | CT24: 2031-2060 | CU24: <=2024 | CV24: 2025-2030 | CW24: 2031-2060 | CX24: <=2024 | CY24: 2025-2030 | CZ24: 2031-2060 | DA24: <=2024 | DB24: 2025-2030 | DC24: 2031-2060
A25: 195 | B25: American Express | C25: 253 | D25: =CONCATENATE((IF(BM25=1, "CN", "")),(IF(BQ25=1, " NZ", "")),(IF(BU25=1, " SBT", "")),(IF(BY25=1, " RE100", ""))) -> CN NZ SBT RE100 | E25: AJ | F25: 45477 | G25: AJ | H25: 8374 | J25: Financial services | K25: United States of America (USA) | L25: North America | M25: Y | N25: 2020 | O25: 2025 | P25: N | Q25: Committed | S25: 2030 | T25: No | V25: 44440 | W25: 2021 | X25: C | Y25: operations - scope 1, 2 and partial 3 | Z25: carbon neutral | AA25: C | AB25: 2018 | AC25: 2018 | AG25: Y | AH25: 2023 | AI25: Y | AJ25: https://www.americanexpress.com/content/dam/amex/en-us/newsroom/pdfs/AXP_2022-2023_ESG_Report.pdf | AL25: https://www.americanexpress.com/content/dam/amex/en-us/newsroom/pdfs/AXP-2021-2022-ESG-Report.pdf | AN25: V | AO25: undefined but SBTi approved | AP25: Net Zero | AQ25: V | AR25: 2035 | AS25: 2021 | AW25: U | AX25: https://www.americanexpress.com/content/dam/amex/en-us/newsroom/pdfs/AXP-2021-2022-ESG-Report.pdf | BJ25: 1 | BM25: 1 | BP25: 1 | BQ25: 1 | BS25: 1 | BU25: 1 | BW25: 1 | BY25: 1 | BZ25: 1 | CA25: 1 | CB25: 1 | CC25: 1 | CE25: 1 | CF25: 1 | CG25: 1 | CH25: 1 | CK25: 1 | CL25: 1 | CM25: =MAX(U25,AR25) -> 2035 | CQ25: Asia | CR25: =COUNTIFS($L$2:$L$501,CQ25,$S$2:$S$501,"<=2024") -> 0 | CS25: =COUNTIFS($L$2:$L$501,CQ25,$S$2:$S$501,">=2025",$S$2:$S$501,"<=2030") -> 30 | CT25: =COUNTIFS($L$2:$L$501,CQ25,$S$2:$S$501,">2030") -> 4 | CU25: =COUNTIFS($L$2:$L$501,CQ25,$O$2:$O$501,"<=2024") -> 1 | CV25: =COUNTIFS($L$2:$L$501,CQ25,$O$2:$O$501,">=2025",$O$2:$O$501,"<=2030") -> 3 | CW25: =COUNTIFS($L$2:$L$501,CQ25,$O$5:$O$504,">2030") -> 8 | CX25: =COUNTIFS($L$2:$L$501,CQ25,$AB$2:$AB$501,"<=2024") -> 3 | CY25: =COUNTIFS($L$2:$L$501,CQ25,$AB$2:$AB$501,">=2024",$AB$2:$AB$501,"<=2030") -> 15 | CZ25: =COUNTIFS($L$2:$L$501,CQ25,$AB$2:$AB$501,">2030") -> 89 | DA25: =COUNTIFS($L$2:$L$501,CQ25,$CM$2:$CM$501,"<=2024") -> 0 | DB25: =COUNTIFS($L$2:$L$501,CQ25,$CM$2:$CM$501,">=2025",$CM$2:$CM$501,"<=2030") -> 3 | DC25: =COUNTIFS($L$2:$L$501,CQ25,$CM$2:$CM$501,">2030") -> 46 | DD25: =SUM(CR25:DC25) -> 202 | DE25: =COUNTIFS($L$2:$L$501, CQ25, $BF$2:$BF$501, "Y") -> 6 | DF25: =COUNTIFS($L$2:$L$501, CQ25, $BF$2:$BF$501, "N") -> 16 | DG25: =COUNTIFS($L$2:$L$501, CQ25)-DF25-DE25 -> 188
A26: 231 | B26: Anheuser-Busch InBev | C26: 241 | D26: =CONCATENATE((IF(BM26=1, "CN", "")),(IF(BQ26=1, " NZ", "")),(IF(BU26=1, " SBT", "")),(IF(BY26=1, " RE100", ""))) -> NZ SBT RE100 | E26: DT | F26: 45477 | G26: DT | H26: 5341 | J26: Food, beverages and agriculture | K26: Belgium | L26: Europe | M26: Y | N26: 2017 | O26: 2025 | P26: Y | Q26: Targets Set | R26: 1.5°C | S26: 2025 | T26: Yes | W26: 2018 | X26: N | AA26: N | AN26: V | AO26: Scope 1, 2 and 3 | AP26: Net Zero | AQ26: V | AR26: 2040 | AS26: 2021 | AW26: Y | AX26: https://www.ab-inbev.com/assets/pressreleases/2023/AB%20InBev_2022%20ESG%20Report_FINAL.pdf | BP26: 1 | BQ26: 1 | BS26: 1 | BU26: 1 | BW26: 1 | BY26: 1 | BZ26: 1 | CB26: 1 | CC26: 1 | CE26: 1 | CG26: 1 | CH26: 1 | CK26: 1 | CL26: 1 | CM26: =MAX(U26,AR26) -> 2040 | CQ26: Europe | CR26: =COUNTIFS($L$2:$L$501,CQ26,$S$2:$S$501,"<=2024") -> 1 | CS26: =COUNTIFS($L$2:$L$501,CQ26,$S$2:$S$501,">=2025",$S$2:$S$501,"<=2030") -> 64 | CT26: =COUNTIFS($L$2:$L$501,CQ26,$S$2:$S$501,">2030") -> 5 | CU26: =COUNTIFS($L$2:$L$501,CQ26,$O$2:$O$501,"<=2024") -> 9 | CV26: =COUNTIFS($L$2:$L$501,CQ26,$O$2:$O$501,">=2025",$O$2:$O$501,"<=2030") -> 21 | CW26: =COUNTIFS($L$2:$L$501,CQ26,$O$5:$O$504,">2030") -> 5 | CX26: =COUNTIFS($L$2:$L$501,CQ26,$AB$2:$AB$501,"<=2024") -> 13 | CY26: =COUNTIFS($L$2:$L$501,CQ26,$AB$2:$AB$501,">=2024",$AB$2:$AB$501,"<=2030") -> 16 | CZ26: =COUNTIFS($L$2:$L$501,CQ26,$AB$2:$AB$501,">2030") -> 31 | DA26: =COUNTIFS($L$2:$L$501,CQ26,$CM$2:$CM$501,"<=2024") -> 0 | DB26: =COUNTIFS($L$2:$L$501,CQ26,$CM$2:$CM$501,">=2025",$CM$2:$CM$501,"<=2030") -> 11 | DC26: =COUNTIFS($L$2:$L$501,CQ26,$CM$2:$CM$501,">2030") -> 73 | DD26: =SUM(CR26:DC26) -> 249 | DE26: =COUNTIFS($L$2:$L$501, CQ26, $BF$2:$BF$501, "Y") -> 6 | DF26: =COUNTIFS($L$2:$L$501, CQ26, $BF$2:$BF$501, "N") -> 10 | DG26: =COUNTIFS($L$2:$L$501, CQ26)-DF26-DE26 -> 101
A27: 371 | B27: Ansteel Group | C27: 283 | D27: =CONCATENATE((IF(BM27=1, "CN", "")),(IF(BQ27=1, " NZ", "")),(IF(BU27=1, " SBT", "")),(IF(BY27=1, " RE100", ""))) | E27: AJ | F27: 45478 | G27: AJ | H27: -83.1 | J27: Metals and mining | K27: China | L27: Asia | M27: N | P27: N | X27: G | Y27: organization | Z27: carbon neutrality | AA27: G | AB27: 2060 | AC27: 2021 | AL27: http://en.ansteel.cn/upload/pdf/2021.pdf | AN27: N | AQ27: N | CQ27: North America | CR27: =COUNTIFS($L$2:$L$501,CQ27,$S$2:$S$501,"<=2024") -> 3 | CS27: =COUNTIFS($L$2:$L$501,CQ27,$S$2:$S$501,">=2025",$S$2:$S$501,"<=2030") -> 52 | CT27: =COUNTIFS($L$2:$L$501,CQ27,$S$2:$S$501,">2030") -> 12 | CU27: =COUNTIFS($L$2:$L$501,CQ27,$O$2:$O$501,"<=2024") -> 9 | CV27: =COUNTIFS($L$2:$L$501,CQ27,$O$2:$O$501,">=2025",$O$2:$O$501,"<=2030") -> 13 | CW27: =COUNTIFS($L$2:$L$501,CQ27,$O$5:$O$504,">2030") -> 5 | CX27: =COUNTIFS($L$2:$L$501,CQ27,$AB$2:$AB$501,"<=2024") -> 21 | CY27: =COUNTIFS($L$2:$L$501,CQ27,$AB$2:$AB$501,">=2024",$AB$2:$AB$501,"<=2030") -> 14 | CZ27: =COUNTIFS($L$2:$L$501,CQ27,$AB$2:$AB$501,">2030") -> 17 | DA27: =COUNTIFS($L$2:$L$501,CQ27,$CM$2:$CM$501,"<=2024") -> 3 | DB27: =COUNTIFS($L$2:$L$501,CQ27,$CM$2:$CM$501,">=2025",$CM$2:$CM$501,"<=2030") -> 8 | DC27: =COUNTIFS($L$2:$L$501,CQ27,$CM$2:$CM$501,">2030") -> 71 | DD27: =SUM(CR27:DC27) -> 228 | DE27: =COUNTIFS($L$2:$L$501, CQ27, $BF$2:$BF$501, "Y") -> 8 | DF27: =COUNTIFS($L$2:$L$501, CQ27, $BF$2:$BF$501, "N") -> 14 | DG27: =COUNTIFS($L$2:$L$501, CQ27)-DF27-DE27 -> 135
A28: 323 | B28: ANZ Group Holdings | D28: =CONCATENATE((IF(BM28=1, "CN", "")),(IF(BQ28=1, " NZ", "")),(IF(BU28=1, " SBT", "")),(IF(BY28=1, " RE100", ""))) -> NZ RE100 | E28: AJ | F28: 45511 | H28: 4724 | I28: Banks: Commercial and Savings | J28: Financial services | K28: Australia | L28: Other | M28: Y | N28: 2019 | O28: 2025 | P28: N | X28: N | AA28: N | AN28: C | AO28: scope 1 and 290& reduction and financed emissions | AP28: Net Zero | AQ28: C | AR28: 2050 | AS28: 2021 | AW28: U | AX28: https://www.anz.com.au/about-us/esg/environmental-sustainability/climate-change/ | AY28: 2023 | AZ28: Y | BA28: https://www.anz.com.au/content/dam/anzcomau/about-us/anz-2023-esg-supplement.pdf | BP28: 1 | BQ28: 1 | BW28: 1 | BY28: 1 | BZ28: 1 | CB28: 1 | CE28: 1 | CG28: 1 | CH28: 1 | CM28: =MAX(U28,AR28) -> 2050 | CQ28: other | CR28: =COUNTIFS($L$2:$L$501,CQ28,$S$2:$S$501,"<=2024") -> 0 | CS28: =COUNTIFS($L$2:$L$501,CQ28,$S$2:$S$501,">=2025",$S$2:$S$501,"<=2030") -> 2 | CT28: =COUNTIFS($L$2:$L$501,CQ28,$S$2:$S$501,">2030") -> 0 | CU28: =COUNTIFS($L$2:$L$501,CQ28,$O$2:$O$501,"<=2024") -> 0 | CV28: =COUNTIFS($L$2:$L$501,CQ28,$O$2:$O$501,">=2025",$O$2:$O$501,"<=2030") -> 3 | CW28: =COUNTIFS($L$2:$L$501,CQ28,$O$5:$O$504,">2030") -> 0 | CX28: =COUNTIFS($L$2:$L$501,CQ28,$AB$2:$AB$501,"<=2024") -> 3 | CY28: =COUNTIFS($L$2:$L$501,CQ28,$AB$2:$AB$501,">=2024",$AB$2:$AB$501,"<=2030") -> 2 | CZ28: =COUNTIFS($L$2:$L$501,CQ28,$AB$2:$AB$501,">2030") -> 1 | DA28: =COUNTIFS($L$2:$L$501,CQ28,$CM$2:$CM$501,"<=2024") -> 0 | DB28: =COUNTIFS($L$2:$L$501,CQ28,$CM$2:$CM$501,">=2025",$CM$2:$CM$501,"<=2030") -> 0 | DC28: =COUNTIFS($L$2:$L$501,CQ28,$CM$2:$CM$501,">2030") -> 11 | DD28: =SUM(CR28:DC28) -> 22 | DE28: =COUNTIFS($L$2:$L$501, CQ28, $BF$2:$BF$501, "Y") -> 1 | DF28: =COUNTIFS($L$2:$L$501, CQ28, $BF$2:$BF$501, "N") -> 2 | DG28: =COUNTIFS($L$2:$L$501, CQ28)-DF28-DE28 -> 13
A29: 491 | B29: Apollo Global Management | D29: =CONCATENATE((IF(BM29=1, "CN", "")),(IF(BQ29=1, " NZ", "")),(IF(BU29=1, " SBT", "")),(IF(BY29=1, " RE100", ""))) -> CN | E29: AJ | F29: 45512 | H29: 5047 | I29: Diversified Financials | J29: Financial services | K29: United States of America (USA) | L29: North America | M29: N | P29: N | X29: C | Y29: Scope 1 and 2 GHG emissions | Z29: carbon-neutral | AA29: C | AB29: 2023 | AC29: 2023 | AG29: Y | AH29: 2023 | AI29: Y | AJ29: https://www.apollo.com/content/dam/apolloaem/documents/insights/apollo-2023-sustainability-report-june-2024.pdf | AL29: https://www.apollo.com/content/dam/apolloaem/documents/insights/apollo-2023-sustainability-report-june-2024.pdf | AN29: N | AQ29: N | BJ29: 1 | BM29: 1 | BZ29: 1 | CA29: 1 | CB29: 1 | CC29: 1 | CE29: 1 | CF29: 1 | CG29: 1 | CH29: 1 | CQ29: sum | CR29: =SUM(CR25:CR28) -> 4 | CS29: =SUM(CS25:CS28) -> 148 | CT29: =SUM(CT25:CT28) -> 21 | CU29: =SUM(CU25:CU28) -> 19 | CV29: =SUM(CV25:CV28) -> 40 | CW29: =SUM(CW25:CW28) -> 18 | CX29: =SUM(CX25:CX28) -> 40 | CY29: =SUM(CY25:CY28) -> 47 | ... DG29: =SUM(DG25:DG28) -> 437
A30: 7 | B30: Apple | C30: 8 | D30: =CONCATENATE((IF(BM30=1, "CN", "")),(IF(BQ30=1, " NZ", "")),(IF(BU30=1, " SBT", "")),(IF(BY30=1, " RE100", ""))) -> CN SBT RE100 | E30: DT | F30: 45474 | G30: AJ | H30: 96995 | J30: Technology | K30: United States of America (USA) | L30: North America | M30: Y | N30: 2016 | O30: 2021 | P30: Y | Q30: Targets Set | R30: 1.5Â°C | S30: 2030 | T30: No | V30: 44317 | W30: 2021 | X30: C, V | Y30: corporate operations, entire value chain | Z30: carbon neutrality | AA30: C | AB30: 2020 | AC30: 2020 | AD30: V | AE30: 2030 | AF30: 2020 | AG30: R | AH30: 2024 | AI30: Y | AJ30: https://www.apple.com/environment/pdf/Apple_Environmental_Progress_Report_2024.pdf | AL30: https://www.apple.com/environment/pdf/Apple_Environmental_Progress_Report_2024.pdf | AM30: Achieve carbon neutrality for our entire carbon footprint by 2030 â€” reducing related emissions by 75 percent compared with 2015. Since 2015, weâ€™ve reduced emissions by over 55 percent across our value chain.We achieved carbon neutrality in 2020 by expanding energy efficiency initiatives, sourcing 100 percent renewable electricity for Apple facilities, and investing in high-quality carbon credits to offset the remaining hard-to-decarbonize corporate emissions. | AN30: N | AQ30: N | BJ30: 1 | BM30: 1 | BS30: 1 | BU30: 1 | BV30: 1 | BY30: 1 | BZ30: 1 | CA30: 1 | CB30: 1 | CC30: 1 | CE30: 1 | CF30: 1 | CG30: 1 | CH30: 1
A31: 190 | B31: ArcelorMittal | C31: 155 | D31: =CONCATENATE((IF(BM31=1, "CN", "")),(IF(BQ31=1, " NZ", "")),(IF(BU31=1, " SBT", "")),(IF(BY31=1, " RE100", ""))) -> CN NZ | E31: DT | F31: 45476 | G31: AJ | H31: 919 | J31: Metals and mining | K31: Luxembourg | L31: Europe | M31: N | P31: N | Q31: Removed | T31: No | V31: 44593 | W31: 2022 | X31: C | Y31: Scope 1 and 2 | Z31: Carbon Neutral | AA31: C | AB31: 2050 | AC31: 2020 | AG31: Y | AI31: Y | AL31: https://corporate.arcelormittal.com/media/vrqovnik/arcelor-mittal-integrated-annual-review-2023.pdf | AN31: C | AO31: Scope 1 and 2 | AP31: Net Zero | AQ31: C | AR31: 2050 | AS31: 2020 | AW31: Y | AX31: https://corporate.arcelormittal.com/climate-action/leading-our-industry-s-efforts-to-decarbonise | BL31: 1 | BM31: 1 | BP31: 1 | BQ31: 1 | BZ31: 1 | CB31: 1 | CC31: 1 | CE31: 1 | CH31: 1 | CM31: =MAX(U31,AR31) -> 2050
A32: 117 | B32: Archer Daniels Midland | C32: 98 | D32: =CONCATENATE((IF(BM32=1, "CN", "")),(IF(BQ32=1, " NZ", "")),(IF(BU32=1, " SBT", "")),(IF(BY32=1, " RE100", ""))) -> SBT | E32: EC | F32: 45475 | G32: DT | H32: 3483 | J32: Food, beverages and agriculture | K32: United States of America (USA) | L32: North America | M32: N | P32: N | Q32: Committed | S32: 2030 | T32: No | V32: 44652 | W32: 2022 | X32: N | AA32: N | AL32: https://www.adm.com/globalassets/sustainability/sustainability-reports/final_archer-daniels-midland-adm_2023-corporate-sustainability-report_51424.pdf | AN32: N | AQ32: N | AX32: https://www.adm.com/globalassets/sustainability/sustainability-reports/final_archer-daniels-midland-adm_2023-corporate-sustainability-report_51424.pdf | BS32: 1 | BU32: 1 | CE32: 1 | CG32: 1 | CH32: 1
A33: 481 | B33: Arrow Electronics | C33: 404 | D33: =CONCATENATE((IF(BM33=1, "CN", "")),(IF(BQ33=1, " NZ", "")),(IF(BU33=1, " SBT", "")),(IF(BY33=1, " RE100", ""))) -> SBT | E33: DT * | F33: 45511 | G33: DT | H33: 903.5 | J33: Retail | K33: United States of America (USA) | L33: North America | M33: N | P33: N | Q33: Committed | S33: 2030 | T33: No | V33: 45170 | W33: 2023 | X33: N | AA33: N | AN33: N | AQ33: N | BS33: 1 | BU33: 1 | CE33: 1 | CG33: 1 | CH33: 1
A34: 245 | B34: Assicurazioni Generali | C34: 137 | D34: =CONCATENATE((IF(BM34=1, "CN", "")),(IF(BQ34=1, " NZ", "")),(IF(BU34=1, " SBT", "")),(IF(BY34=1, " RE100", ""))) -> NZ | E34: AJ | F34: 45476 | G34: AJ | H34: 4050.7 | J34: Financial services | K34: Italy | L34: Europe | M34: N | P34: N | X34: N | AA34: N | AN34: C, F | AO34: operational activities, insurance portfolio | AP34: Net-Zero emissions | AQ34: C | AR34: 2040 | AS34: 2021 | AT34: F | AU34: 2050 | AV34: 2021 | AW34: R | AX34: https://www.generali.com/media/press-releases/all/2021/Generali-updates-its-strategy-for-climate-protection | BC34: https://www.generali.com/doc/jcr:10e8853d-1fa8-44b2-958e-3ca826a3bd30/Annual%20Integrated%20Report%20and%20Consolidated%20Financial%20Statements%202023_Generali%20Group_final_interactive.pdf/lang:en/Annual_Integrated_Report_and_Consolidated_Financial_Statements_2023_Generali_Group_final_interactive.pdf | BD34: Y | BE34: https://www.generali.com/sustainability/our-commitment-to-the-environment-and-climate | BF34: N | BP34: 1 | BQ34: 1 | BZ34: 1 | CB34: 1 | CC34: 1 | CE34: 1 | CH34: 1 | CK34: 1 | CL34: 1 | CM34: =MAX(U34,AR34) -> 2040
A35: 329 | B35: AstraZeneca | C35: 331 | D35: =CONCATENATE((IF(BM35=1, "CN", "")),(IF(BQ35=1, " NZ", "")),(IF(BU35=1, " SBT", "")),(IF(BY35=1, " RE100", ""))) -> NZ SBT RE100 | E35: EC | F35: 45482 | G35: DT | H35: 5955 | J35: Health care and pharmaceuticals | K35: United Kingdom | L35: Europe | M35: Y | N35: 2016 | O35: 2025 | P35: Y | Q35: Targets Set | R35: 1.5Â°C | S35: 2026 | T35: Yes | U35: 2045 | V35: 44470 | W35: 2021 | X35: N | AA35: N | AN35: V | AO35: value chain (Scopes 1, 2 and 3) | AP35: Net Zero | AQ35: V | AR35: 2045 | AS35: 2020 | AW35: Y | AX35: https://www.astrazeneca.com/content/dam/az/Sustainability/2024/pdf/Ambition-Zero-Carbon-Infographic-2023.pdf | BC35: https://www.astrazeneca.com/media-centre/press-releases/2020/astrazenecas-ambition-zero-carbon-strategy-to-eliminate-emissions-by-2025-and-be-carbon-negative-across-the-entire-value-chain-by-2030-22012020.html#modal-historic-confirmation | BP35: 1 | BQ35: 1 | BS35: 1 | BU35: 1 | BW35: 1 | BY35: 1 | BZ35: 1 | CB35: 1 | CC35: 1 | CE35: 1 | CG35: 1 | CH35: 1 | CK35: 1 | CL35: 1 | CM35: =MAX(U35,AR35) -> 2045
A36: 74 | B36: AT&T | C36: 78 | D36: =CONCATENATE((IF(BM36=1, "CN", "")),(IF(BQ36=1, " NZ", "")),(IF(BU36=1, " SBT", "")),(IF(BY36=1, " RE100", ""))) -> CN SBT | E36: DT - AJ | F36: 45475 | G36: DT | H36: 14400 | J36: Telecommunications and media | K36: United States of America (USA) | L36: North America | M36: N | P36: Y | Q36: Targets Set | R36: 1.5Â°C | S36: 2024 | T36: No | V36: 43891 | W36: 2020 | X36: C | Y36: entire global operations | Z36: carbon neutral | AA36: C | AB36: 2035 | AC36: 2018 | AG36: Y | AI36: Y | AL36: https://about.att.com/ecms/dam/csr/2019/environment/ClimateStrategyTransitionPlan.pdf https://sustainability.att.com/progress/esg-data | AM36: Though AT&T aims to reduce our footprint to as close to zero emissions as possible, there may be some sources of emissions that cannot be eliminated. In these cases, we will invest in high-quality carbon ofsets to cover the associated emissions. | AN36: N | AQ36: N | BL36: 1 | BM36: 1 | BS36: 1 | BU36: 1 | BZ36: 1 | CB36: 1 | CC36: 1 | CE36: 1 | CG36: 1 | CH36: 1
A37: 147 | B37: Aviation Industry Corp. of China | C37: 150 | D37: =CONCATENATE((IF(BM37=1, "CN", "")),(IF(BQ37=1, " NZ", "")),(IF(BU37=1, " SBT", "")),(IF(BY37=1, " RE100", ""))) -> NZ | E37: DT | F37: 45476 | G37: AJ | H37: 1644.1 | J37: Aerospace and defense | K37: China | L37: Asia | M37: N | P37: N | X37: I | AA37: I | AN37: V | AO37: Scope 1, 2 and 3 | AP37: Net Zero | AQ37: V | AR37: 2050 | AS37: 2021 | AW37: Y | AX37: https://calec.china-airlines.com/csr/en/download/2022/2022-en-CSR.pdf | BC37: CAL complies with the IATA and national carbon reduction targets by leading the industry in announcing the â€œtarget for achieving net zero carbon emissions by 2050â€ in October 2021 | BP37: 1 | BQ37: 1 | BZ37: 1 | CB37: 1 | CC37: 1 | CE37: 1 | CH37: 1 | CK37: 1 | CL37: 1 | CM37: =MAX(U37,AR37) -> 2050
A38: 126 | B38: AXA | C38: 91 | D38: =CONCATENATE((IF(BM38=1, "CN", "")),(IF(BQ38=1, " NZ", "")),(IF(BU38=1, " SBT", "")),(IF(BY38=1, " RE100", ""))) -> CN NZ SBT RE100 | E38: DT - AJ | F38: 45475 | G38: DT | H38: 7771.7 | J38: Financial services | K38: France | L38: Europe | M38: Y | N38: 2017 | O38: 2025 | P38: N | Q38: Committed | S38: 2030 | T38: No | V38: 42156 | W38: 2015 | X38: C, V | Y38: operations, Scope 3 business travel, IT equipment manufacturing and purchased services, and upstream energy emissions | Z38: carbon neutral | AA38: C | AB38: 2020 | AC38: 2020 | AD38: V | AE38: 2025 | AF38: 2020 | AG38: Y | AH38: 2024 | AI38: Y | AJ38: https://www-axa-com.cdn.axa-contento-118412.eu/www-axa-com/8b8dfa69-13e3-4c34-bae3-8fb939102a2d_axa_climate_and_biodiversity_report_2024_va.pdf | AL38: https://www.axa.com/en/commitments/environmental-footprint-management | AN38: F | AO38: insurance and reinsurance underwriting portfolios | AP38: Net-Zero greenhouse gas emissions | AQ38: F | AR38: 2050 | AS38: 2023 | AW38: U | AX38: https://www.axa.com/en/commitments/axa-net-zero-strategy-for-investment-and-underwriting | BJ38: 1 | BM38: 1 | BP38: 1 | BQ38: 1 | BS38: 1 | BU38: 1 | BW38: 1 | BY38: 1 | BZ38: 1 | CA38: 1 | CB38: 1 | CC38: 1 | CE38: 1 | CF38: 1 | CG38: 1 | CH38: 1 | CK38: 1 | CL38: 1 | CM38: =MAX(U38,AR38) -> 2050
A39: 200 | B39: Banco Bilbao Vizcaya Argentaria | C39: 318 | D39: =CONCATENATE((IF(BM39=1, "CN", "")),(IF(BQ39=1, " NZ", "")),(IF(BU39=1, " SBT", "")),(IF(BY39=1, " RE100", ""))) -> CN NZ SBT | E39: EC | F39: 45481 | G39: AJ | H39: 8669 | J39: Financial services | K39: Spain | L39: Europe | M39: N | P39: N | Q39: Committed | S39: 2030 | T39: No | V39: 43101 | W39: 2018 | X39: C | Y39: scope 1 and 2 | Z39: carbon neutral | AA39: C | AB39: 2020 | AC39: 2020 | AG39: Y | AH39: 2024 | AI39: Y | AK39: https://shareholdersandinvestors.bbva.com/wp-content/uploads/2024/03/BBVAInformeTCFD_ENG_Dic23_v05-03-24.pdf | AL39: https://www.garantibbvainvestorrelations.com/en/sustainability/detail/Sustainable-Finance-Strategy/2213/9625/0#:~:text=These%20interim%20targets%20make%20up,scope%201%20and%202%20emissions. | AN39: V | AO39: direct and indirect emissions | AP39: zero net emissions | AQ39: V | AR39: 2050 | AS39: 2021 | AW39: Y | AX39: https://shareholdersandinvestors.bbva.com/wp-content/uploads/2024/03/BBVAInformeTCFD_ENG_Dic23_v05-03-24.pdf | BC39: https://www.bbva.com/en/bbva-commits-to-net-zero-emissions-by-2050/ | BJ39: 1 | BM39: 1 | BP39: 1 | BQ39: 1 | BS39: 1 | BU39: 1 | BZ39: 1 | CA39: 1 | CB39: 1 | CC39: 1 | CE39: 1 | CF39: 1 | CG39: 1 | CH39: 1 | CK39: 1 | CL39: 1 | CM39: =MAX(U39,AR39) -> 2050
A40: 252 | B40: Banco Bradesco | C40: 273 | D40: =CONCATENATE((IF(BM40=1, "CN", "")),(IF(BQ40=1, " NZ", "")),(IF(BU40=1, " SBT", "")),(IF(BY40=1, " RE100", ""))) -> CN NZ | E40: EC | F40: 45477 | G40: AJ | H40: 2854.2 | J40: Financial services | K40: Brazil | L40: Other | M40: N | P40: N | X40: C | Y40: operations, scope 3 operational emissions | Z40: offset 100%/neutralized | AA40: C | AB40: 2006 | AC40: 2006 | AD40: C | AE40: 2019 | AF40: 2019 | AG40: Y | AH40: 2024 | AI40: Y | AJ40: https://banco.bradesco/assets/classic/pdf/sustentabilidade/en/bradesco-2023-ESG-report.pdf | AL40: https://banco.bradesco/assets/classic/pdf/sustentabilidade/en/bradesco-2023-ESG-report.pdf | AN40: C+F | AO40: operations and portfolios | AP40: Net Zero carbon emissions | AQ40: C+F | AR40: 2050 | AS40: 2021 | AW40: Y | AX40: https://banco.bradesco/assets/classic/pdf/sustentabilidade/en/bradesco-2023-ESG-report.pdf https://api.mziq.com/mzfilemanager/v2/d/80f2e993-0a30-421a-9470-a4d5c8ad5e9f/5a878306-1f11-92ad-e1c2-c1706aee734b?origin=2 | BJ40: 1 | BM40: 1 | BP40: 1 | BQ40: 1 | BZ40: 1 | CA40: 1 | CB40: 1 | CC40: 1 | CE40: 1 | CF40: 1 | CG40: 1 | CH40: 1 | CK40: 1 | CL40: 1 | CM40: =MAX(U40,AR40) -> 2050
A41: 217 | B41: Banco do Brasil | C41: 251 | D41: =CONCATENATE((IF(BM41=1, "CN", "")),(IF(BQ41=1, " NZ", "")),(IF(BU41=1, " SBT", "")),(IF(BY41=1, " RE100", ""))) -> CN SBT | E41: AJ | F41: 45477 | G41: AJ | H41: 5980.4 | J41: Financial services | K41: Brazil | L41: Other | M41: N | P41: N | Q41: Committed | S41: 2030 | T41: Yes | V41: 44197 | W41: 2021 | X41: C, F | Y41: scope 1 and 2, financed emissions (value chain) | Z41: offsetting 100% of GHG emissions, emissions neutrality | AA41: C | AB41: 2030 | AC41: 2023 | AD41: F | AE41: 2050 | AF41: 2023 | AG41: Y | AH41: 2022 | AI41: Y | AJ41: https://api.mziq.com/mzfilemanager/v2/d/5760dff3-15e1-4962-9e81-322a0b3d0bbd/90234c9e-5912-5db4-caf7-1ea4d7efa0a4?origin=2 | AL41: https://api.mziq.com/mzfilemanager/v2/d/5760dff3-15e1-4962-9e81-322a0b3d0bbd/90234c9e-5912-5db4-caf7-1ea4d7efa0a4?origin=2 | AN41: N | AQ41: N | BD41: Y | BE41: https://api.mziq.com/mzfilemanager/v2/d/5760dff3-15e1-4962-9e81-322a0b3d0bbd/90234c9e-5912-5db4-caf7-1ea4d7efa0a4?origin=2 | BF41: N | BI41: https://iupana.com/2023/08/14/the-carbon-opportunity-banco-do-brasil-wants-to-capture/?lang=en | BK41: 1 | BM41: 1 | BS41: 1 | BU41: 1 | BZ41: 1 | CA41: 1 | CB41: 1 | CC41: 1 | CE41: 1 | CG41: 1 | CH41: 1
A42: 62 | B42: Banco Santander | C42: 104 | D42: =CONCATENATE((IF(BM42=1, "CN", "")),(IF(BQ42=1, " NZ", "")),(IF(BU42=1, " SBT", "")),(IF(BY42=1, " RE100", ""))) -> CN NZ | E42: EC | F42: 45475 | G42: DT | H42: 11973.8 | J42: Financial services | K42: Spain | L42: Europe | M42: N | P42: N | X42: C | Y42: own operations | Z42: carbon neutral | AA42: C | AB42: 2020 | AC42: 2019 | AG42: Y | AH42: 2022 | AI42: Y | AJ42: https://www.santander.com/content/dam/santander-com/en/contenido-paginas/nuestro-compromiso/reports/2023/doc-informes-usa-informe-anual-integrado-2023-disponible-en-ingles.pdf | AL42: https://www.santander.com/content/dam/santander-com/en/documentos/informe-financiero-anual/2022/ifa-2022-consolidated-annual-financial-report-en.pdf | AN42: C, F | AO42: our operations, portfolios | AP42: Net Zero | AQ42: C | AR42: 2050 | AS42: 2021 | AT42: F | AU42: 2050 | AV42: 2021 | AW42: Y | AX42: https://www.santander.com/content/dam/santander-com/es/documentos/informe-anual-de-sostenibilidad/2023/ias-2023-climate-finance-2023-es.pdf | AY42: 2023 | AZ42: Y | BA42: https://www.santander.co.uk/content/dam/sites/santander-uk-sustainability/resources/documents/santander-2023-ESG-supplement.pdf | BJ42: 1 | BM42: 1 | BP42: 1 | BQ42: 1 | BZ42: 1 | CA42: 1 | CB42: 1 | CC42: 1 | CE42: 1 | CF42: 1 | CG42: 1 | CH42: 1 | CK42: 1 | CL42: 1 | CM42: =MAX(U42,AR42) -> 2050
A43: 38 | B43: Bank of America | C43: 82 | D43: =CONCATENATE((IF(BM43=1, "CN", "")),(IF(BQ43=1, " NZ", "")),(IF(BU43=1, " SBT", "")),(IF(BY43=1, " RE100", ""))) -> CN NZ | E43: DT | F43: 45475 | G43: DT | H43: 26515 | J43: Financial services | K43: United States of America (USA) | L43: North America | M43: N | P43: N | X43: C | Y43: undefined | Z43: carbon neutral | AA43: C | AB43: 2020 | AC43: 2016 | AG43: Y | AH43: 2022 | AI43: Y | AK43: https://about.bankofamerica.com/content/dam/about/pdfs/approach-to-zero-2022.pdf | AL43: https://about.bankofamerica.com/content/dam/about/pdfs/approach-to-zero-2022.pdf | AN43: V, F | AO43: Scope 1, 2 and 3 | AP43: Net Zero | AQ43: V | AR43: 2030 | AS43: 2021 | AT43: F | AU43: 2050 | AV43: 2021 | AW43: U | AX43: https://d1io3yog0oux5.cloudfront.net/_a89f6b82dc7daa3d2fb98042426565da/bankofamerica/db/867/10038/annual_report/BAC+2023+Annual+Report.pdf | BC43: Building on our history of climate leadership, we are working towards 2030 targets for our operations and supply chain. Our Net Zero goal includes operations, supply chain and financing activities (i.e., Scope 1, Scope 2 and material Scope 3) In 2021, the Corporation committed to achieving net zero greenhouse gas emissions before 2050 in our financing activities, operations and supply chain (Net Zero goal), and in 2022, we released our Approach to ZeroTM, a framework for how we plan to achieve our Net Zero goal. In line with this approach, we have set interim 2030 targets across our financing activities (2030 Financing Activity Emissions Targets), operations and supply chain, all of which are further supported and complemented by our $1.5 trillion sustainable finance goal (which is aligned with the 17 UN Sustainable Development Goals) of which $1 trillion is dedicated to supporting the transition toward a low-carbon economy, including capital mobilized across clean energy sectors and tailored financial solutions for emerging areas of the low-carbon economy. I | BJ43: 1 | BM43: 1 | BO43: 1 | BQ43: 1 | BZ43: 1 | CA43: 1 | CB43: 1 | CC43: 1 | CE43: 1 | CF43: 1 | CG43: 1 | CH43: 1 | CJ43: 1 | CL43: 1 | CM43: =MAX(U43,AR43) -> 2030
A44: 37 | B44: Bank of China | C44: 49 | D44: =CONCATENATE((IF(BM44=1, "CN", "")),(IF(BQ44=1, " NZ", "")),(IF(BU44=1, " SBT", "")),(IF(BY44=1, " RE100", ""))) -> CN | E44: AJ - EC | F44: 45475 | G44: DT | H44: 32758.3 | J44: Financial services | K44: China | L44: Asia | M44: N | P44: N | X44: C | Y44: undefined | Z44: carbon neutrality | AA44: C | AB44: 2030 | AC44: 2021 | AG44: U | AH44: 2023 | AI44: Y | AJ44: https://pic.bankofchina.com/bocappd/report/202403/P020240328720914424945.pdf | AL44: https://pic.bankofchina.com/bocappd/report/202403/P020240328720914424945.pdf | AM44: mention dual carbon goals | AN44: N | AQ44: N | BD44: N | BF44: N | BK44: 1 | BM44: 1 | BZ44: 1 | CA44: 1 | CB44: 1 | CE44: 1 | CG44: 1 | CH44: 1
A45: 154 | B45: Bank of Communications | C45: 161 | D45: =CONCATENATE((IF(BM45=1, "CN", "")),(IF(BQ45=1, " NZ", "")),(IF(BU45=1, " SBT", "")),(IF(BY45=1, " RE100", ""))) | E45: DT | F45: 45476 | G45: AJ | H45: 13098.6 | J45: Financial services | K45: China | L45: Asia | M45: N | P45: N | X45: G | Y45: Scope 1 and 2 | Z45: carbon neutral | AA45: G | AB45: 2060 | AC45: 2021 | AL45: https://www.bankcomm.com/BankCommSite/shtml/jyjr/en/2600223/2600642/5040673.shtml?channelId=2600642 | AN45: N | AQ45: N
A46: 294 | B46: Bank of Montreal | C46: 433 | D46: =CONCATENATE((IF(BM46=1, "CN", "")),(IF(BQ46=1, " NZ", "")),(IF(BU46=1, " SBT", "")),(IF(BY46=1, " RE100", ""))) -> CN NZ | E46: AJ | F46: 45511 | G46: AJ | H46: 3237 | J46: Financial services | K46: Canada | L46: North America | M46: N | P46: N | X46: C | Y46: operations | Z46: carbon neutrality | AA46: C | AB46: 2010 | AC46: 2010 | AG46: Y | AH46: 2023 | AI46: Y | AJ46: https://our-impact.bmo.com/wp-content/uploads/2024/03/BMO_2023_SR_EN.pdf | AL46: https://our-impact.bmo.com/wp-content/uploads/2024/03/BMO_2023_SR_EN.pdf | AN46: F | AO46: financed emissions | AP46: Net Zero | AQ46: F | AR46: 2050 | AS46: 2021 | AW46: Y | AX46: https://our-impact.bmo.com/wp-content/uploads/2024/03/BMO_2023_SR_EN.pdf | AY46: 2023 | AZ46: Y | BA46: https://our-impact.bmo.com/wp-content/uploads/2024/03/BMO_2023_SR_EN.pdf | BJ46: 1 | BM46: 1 | BP46: 1 | BQ46: 1 | BZ46: 1 | CA46: 1 | CB46: 1 | CC46: 1 | CE46: 1 | CF46: 1 | CG46: 1 | CH46: 1 | CK46: 1 | CL46: 1 | CM46: =MAX(U46,AR46) -> 2050
A47: 466 | B47: Bank of New York Mellon | D47: =CONCATENATE((IF(BM47=1, "CN", "")),(IF(BQ47=1, " NZ", "")),(IF(BU47=1, " SBT", "")),(IF(BY47=1, " RE100", ""))) -> CN | E47: AJ | F47: 45512 | H47: 3286 | I47: Banks: Commercial and Savings | J47: Financial services | K47: United States of America (USA) | L47: North America | M47: N | P47: N | X47: C | Y47: Scope 1, 2, and 3 business travel emissions | Z47: carbon neutral | AA47: C | AB47: 2015 | AC47: 2015 | AG47: Y | AH47: 2023 | AI47: Y | AJ47: https://www.bnymellonim.com/content/dam/imemea/pdfs/tcfd-reports/T12584_IM_EMEA_Entity_TCFD_Report.pdf | AL47: https://www.bnymellonim.com/content/dam/imemea/pdfs/tcfd-reports/T12584_IM_EMEA_Entity_TCFD_Report.pdf | AN47: N | AQ47: N | BC47: For financed emissions, BNYM IM EMEA does not adopt any binding net zero commitments as part of its strategy because management of portfolios is directed by its clients and delegated to affiliated Investment Management Firms. | BJ47: 1 | BM47: 1 | BZ47: 1 | CA47: 1 | CB47: 1 | CC47: 1 | CE47: 1 | CF47: 1 | CG47: 1 | CH47: 1
A48: 281 | B48: Bank of Nova Scotia | C48: 415 | D48: =CONCATENATE((IF(BM48=1, "CN", "")),(IF(BQ48=1, " NZ", "")),(IF(BU48=1, " SBT", "")),(IF(BY48=1, " RE100", ""))) -> CN NZ | E48: AJ | F48: 45511 | G48: AJ | H48: 5495 | J48: Financial services | K48: Canada | L48: North America | M48: N | P48: N | X48: C | Y48: banking alliance operations | Z48: carbon neutrality | AA48: C | AB48: 2030 | AC48: 2022 | AG48: Y | AH48: 2023 | AI48: Y | AJ48: https://www.scotiabank.com/content/dam/scotiabank/corporate/Documents/Scotiabank_2023_ESG_Report_Final.pdf | AL48: https://esgnews.com/scotiabank-announces-net-zero-strategy-and-a-commitment-to-mobilize-350-billion-in-climate-related-financing/ | AN48: F | AO48: financed emissions | AP48: Net Zero | AQ48: F | AR48: 2050 | AS48: 2022 | AW48: R | AX48: https://esgnews.com/scotiabank-announces-net-zero-strategy-and-a-commitment-to-mobilize-350-billion-in-climate-related-financing/ | AY48: 2023 | AZ48: Y | BA48: https://www.scotiabank.com/content/dam/scotiabank/corporate/Documents/Scotiabank_2023_ESG_Report_Final.pdf | BK48: 1 | BM48: 1 | BP48: 1 | BQ48: 1 | BZ48: 1 | CA48: 1 | CB48: 1 | CC48: 1 | CE48: 1 | CG48: 1 | CH48: 1 | CK48: 1 | CL48: 1 | CM48: =MAX(U48,AR48) -> 2050
A49: 212 | B49: Barclays | C49: 325 | D49: =CONCATENATE((IF(BM49=1, "CN", "")),(IF(BQ49=1, " NZ", "")),(IF(BU49=1, " SBT", "")),(IF(BY49=1, " RE100", ""))) -> NZ RE100 | E49: EC | F49: 45481 | G49: DT | H49: 6535.9 | J49: Financial services | K49: United Kingdom | L49: Europe | M49: Y | N49: 2019 | O49: 2025 | P49: N | X49: N | AA49: N | AN49: V | AO49: scope 1, 2 and 3 | AP49: Net Zero | AQ49: V | AR49: 2050 | AS49: 2020 | AW49: U | AX49: https://reclaimfinance.org/site/en/2024/02/14/barclays-climate-strategy-greenwashing-and-business-as-usual/#:~:text=In%20March%202020%2C%20Barclays%20announced,timelines%20of%20the%20Paris%20Agreement. | BP49: 1 | BQ49: 1 | BW49: 1 | BY49: 1 | BZ49: 1 | CB49: 1 | CE49: 1 | CG49: 1 | CH49: 1 | CK49: 1 | CL49: 1 | CM49: =MAX(U49,AR49) -> 2050
A50: 172 | B50: BASF | C50: 119 | D50: =CONCATENATE((IF(BM50=1, "CN", "")),(IF(BQ50=1, " NZ", "")),(IF(BU50=1, " SBT", "")),(IF(BY50=1, " RE100", ""))) -> NZ | E50: EC - AJ | F50: 45475 | G50: AJ | H50: 243.2 | J50: Chemicals | K50: Germany | L50: Europe | M50: N | P50: N | X50: N | AA50: N | AN50: C | AO50: scope 1, 2, and 3.1 (partial scope 3) | AP50: Net-Zero CO2Â emissions | AQ50: C | AR50: 2050 | AS50: 2021 | AW50: Y | AX50: https://report.basf.com/2023/en/combined-managements-report/environmental-social-governance/environmental/energy-and-climate-protection.html | AY50: 2023 | AZ50: Y | BA50: https://report.basf.com/2023/en/combined-managements-report/environmental-social-governance/environmental/energy-and-climate-protection.html | BC50: https://www.basf.com/global/en/media/news-releases/2021/03/p-21-166.html | BP50: 1 | BQ50: 1 | BZ50: 1 | CB50: 1 | CC50: 1 | CE50: 1 | CH50: 1 | CM50: =MAX(U50,AR50) -> 2050
A51: 286 | B51: Bayer | C51: 265 | D51: =CONCATENATE((IF(BM51=1, "CN", "")),(IF(BQ51=1, " NZ", "")),(IF(BU51=1, " SBT", "")),(IF(BY51=1, " RE100", ""))) -> CN NZ SBT | E51: AJ | F51: 45477 | G51: AJ | H51: -3179.4 | J51: Health care and pharmaceuticals | K51: Germany | L51: Europe | M51: N | P51: Y | Q51: Targets Set | R51: 1.5Â°C | S51: 2029 | T51: Yes | V51: 44044 | W51: 2020 | X51: C | Y51: operations | Z51: climate neutral | AA51: C | AB51: 2030 | AC51: 2019 | AG51: Y | AH51: 2023 | AI51: Y | AJ51: https://www.bayer.com/sites/default/files/2024-03/bayer-sustainability-highlight-report-2023.pdf | AL51: https://www.bayer.com/sites/default/files/2024-02-28-com-offsetting-publication-0.pdf https://www.bayer.com/en/news-stories/we-are-raising-the-bar https://www.bayer.com/media/en-us/bayer-to-significantly-step-up-its-sustainability-efforts/ | AN51: V | AO51: entire value chain | AP51: Net Zero | AQ51: V | AR51: 2050 | AS51: 2023 | AW51: Y | AX51: https://www.bayer.com/en/sustainability/climate-commitment-net-zero-2050#:~:text=Bayer%20is%20on%20a%20path,projects%20with%20recognized%20quality%20standards. https://www.bayer.com/en/news-stories/we-are-raising-the-bar | BK51: 1 | BM51: 1 | BP51: 1 | BQ51: 1 | BS51: 1 | BU51: 1 | BZ51: 1 | CA51: 1 | CB51: 1 | CC51: 1 | CE51: 1 | CG51: 1 | CH51: 1 | CK51: 1 | CL51: 1 | CM51: =MAX(U51,AR51) -> 2050
A52: 192 | B52: Beijing Automotive Group | C52: 193 | D52: =CONCATENATE((IF(BM52=1, "CN", "")),(IF(BQ52=1, " NZ", "")),(IF(BU52=1, " SBT", "")),(IF(BY52=1, " RE100", ""))) | E52: EC | F52: 45477 | G52: DT | H52: 328.1 | J52: Automotive | K52: China | L52: Asia | M52: N | P52: N | X52: N | AA52: N | AL52: https://www.baicgroup.com.cn/uploadfile/shezebaogao/szbg2022.pdf | AN52: N | AQ52: N | AX52: https://www.baicgroup.com.cn/uploadfile/shezebaogao/szbg2022.pdf
A53: 458 | B53: Beijing Jianlong Heavy Industry Group | C53: 465 | D53: =CONCATENATE((IF(BM53=1, "CN", "")),(IF(BQ53=1, " NZ", "")),(IF(BU53=1, " SBT", "")),(IF(BY53=1, " RE100", ""))) | E53: AJ | F53: 45512 | G53: AJ | H53: 138.9 | J53: Metals and mining | K53: China | L53: Asia | M53: N | P53: N | X53: N | AA53: N | AN53: N | AQ53: N
A54: 9 | B54: Berkshire Hathaway | C54: 14 | D54: =CONCATENATE((IF(BM54=1, "CN", "")),(IF(BQ54=1, " NZ", "")),(IF(BU54=1, " SBT", "")),(IF(BY54=1, " RE100", ""))) | E54: DT - AJ | F54: 45475 | G54: AJ | H54: 96223 | J54: Financial services | K54: United States of America (USA) | L54: North America | M54: N | P54: N | X54: N | AA54: N | AN54: N | AQ54: N
A55: 352 | B55: Best Buy | C55: 311 | D55: =CONCATENATE((IF(BM55=1, "CN", "")),(IF(BQ55=1, " NZ", "")),(IF(BU55=1, " SBT", "")),(IF(BY55=1, " RE100", ""))) -> CN NZ SBT | E55: EC | F55: 45481 | G55: AJ | H55: 1241 | J55: Retail | K55: United States of America (USA) | L55: North America | M55: N | P55: Y | Q55: Targets Set | R55: 1.5Â°C | S55: 2030 | T55: No | V55: 43647 | W55: 2019 | X55: C | Y55: operational carbon usage | Z55: carbon neutrality | AA55: C | AB55: 2040 | AC55: 2019 | AG55: Y | AI55: Y | AL55: https://corporate.bestbuy.com/wp-content/uploads/2023/07/FY23_CRS_Report.pdf | AN55: C | AO55: our business | AP55: Net-Zero annual carbon emissions by 2040 | AQ55: C | AR55: 2040 | AS55: 2020 | AW55: Y | AX55: https://corporate.bestbuy.com/wp-content/uploads/2023/07/FY23_CRS_Report.pdf | BL55: 1 | BM55: 1 | BP55: 1 | BQ55: 1 | BS55: 1 | BU55: 1 | BZ55: 1 | CB55: 1 | CC55: 1 | CE55: 1 | CG55: 1 | CH55: 1 | CM55: =MAX(U55,AR55) -> 2040
A56: 258 | B56: Bharat Petroleum | C56: 233 | D56: =CONCATENATE((IF(BM56=1, "CN", "")),(IF(BQ56=1, " NZ", "")),(IF(BU56=1, " SBT", "")),(IF(BY56=1, " RE100", ""))) -> NZ | E56: DT | F56: 45477 | G56: DT | H56: 3245.4 | J56: Oil and gas | K56: India | L56: Asia | M56: N | P56: N | X56: N | AA56: N | AN56: C | AO56: Scope 1 and 2 | AP56: Net Zero | AQ56: C | AR56: 2040 | AS56: 2021 | AW56: Y | AX56: https://www.bharatpetroleum.in/images/files/SUSTAINABLE%20DEVELOPMENT%20REPORT_22-23-05-02-24.pdf https://economictimes.indiatimes.com/industry/renewables/bpcl-strives-for-net-zero-carbon-emissions-by-2040/articleshow/93860104.cms?from=mdr | BP56: 1 | BQ56: 1 | BZ56: 1 | CB56: 1 | CC56: 1 | CE56: 1 | CH56: 1 | CM56: =MAX(U56,AR56) -> 2040
A57: 268 | B57: BHP Group | C57: 180 | D57: =CONCATENATE((IF(BM57=1, "CN", "")),(IF(BQ57=1, " NZ", "")),(IF(BU57=1, " SBT", "")),(IF(BY57=1, " RE100", ""))) -> NZ | E57: AJ | F57: 45476 | G57: DT | H57: 12921 | J57: Metals and mining | K57: Australia | L57: Other | M57: N | P57: N | X57: N | AA57: N | AN57: C | AO57: operations | AP57: Net-Zero | AQ57: C | AR57: 2050 | AS57: 2020 | AW57: Y | AX57: https://www.theguardian.com/business/2021/may/16/people-are-sceptical-why-mining-giant-bhp-wants-to-get-to-net-zero-and-how-it-plans-to-do-it | BC57: https://www.bhp.com/sustainability/climate-change/operational-ghg-emission-reductions | BD57: Y | BE57: https://www.bhp.com/sustainability/climate-change/operational-ghg-emission-reductions | BF57: N | BI57: https://www.bloomberg.com/news/articles/2024-06-26/bhp-uncertain-net-zero-emissions-target-will-be-reached-by-2050 | BP57: 1 | BQ57: 1 | BZ57: 1 | CB57: 1 | CC57: 1 | CE57: 1 | CH57: 1 | CM57: =MAX(U57,AR57) -> 2050
A58: 41 | B58: BMW Group | C58: 57 | D58: =CONCATENATE((IF(BM58=1, "CN", "")),(IF(BQ58=1, " NZ", "")),(IF(BU58=1, " SBT", "")),(IF(BY58=1, " RE100", ""))) -> CN NZ SBT RE100 | E58: AJ | F58: 45475 | G58: DT | H58: 12205.2 | J58: Automotive | K58: Germany | L58: Europe | M58: Y | N58: 2015 | O58: 2050 | P58: Y | Q58: Targets Set | R58: 1.5Â°C/Well-below 2Â°C | S58: 2030 | T58: Yes | V58: 44593 | W58: 2022 | X58: F | Y58: asset portfolio | Z58: carbon neutrality | AA58: F | AB58: 2050 | AC58: 2020 | AG58: Y | AI58: Y | AL58: https://www.bmwgroup.com/en/report/2022/bmw-group-report/next-level-sustainability/index.html | AN58: V | AO58: entire value chain | AP58: Net Zero | AQ58: V | AR58: 2050 | AS58: 2022 | AW58: U | AX58: https://esgnews.com/amp/bmw-announces-commitment-to-sustainability-goals-climate-neutrality-by-2050/ | BC58: refers to this target as climate-neutral as well | BD58: C | BE58: https://www.bmwgroup.com/en/report/2023/downloads/BMW-Group-Report-2023-en.pdf | BF58: N | BL58: 1 | BM58: 1 | BP58: 1 | BQ58: 1 | BS58: 1 | BU58: 1 | BX58: 1 | BY58: 1 | BZ58: 1 | CB58: 1 | CC58: 1 | CE58: 1 | CG58: 1 | CH58: 1 | CK58: 1 | CL58: 1 | CM58: =MAX(U58,AR58) -> 2050
A59: 64 | B59: BNP Paribas | C59: 127 | D59: =CONCATENATE((IF(BM59=1, "CN", "")),(IF(BQ59=1, " NZ", "")),(IF(BU59=1, " SBT", "")),(IF(BY59=1, " RE100", ""))) -> CN SBT | E59: EC - AJ | F59: 45476 | G59: AJ | H59: 11864.6 | J59: Financial services | K59: France | L59: Europe | M59: N | P59: N | Q59: Committed | S59: 2030 | T59: No | V59: 42461 | W59: 2016 | X59: F | Y59: account credit and investment activities | Z59: carbon neutrality | AA59: F | AB59: 2050 | AC59: 2015 | AG59: Y | AI59: Y | AL59: https://docfinder.bnpparibas-am.com/api/files/F5EE3377-26CE-4DFD-B770-DBD29323D78B | AN59: I | AQ59: I | BL59: 1 | BM59: 1 | BS59: 1 | BU59: 1 | BZ59: 1 | CB59: 1 | CC59: 1 | CE59: 1 | CG59: 1 | CH59: 1
A60: 159 | B60: Boeing | C60: 197 | D60: =CONCATENATE((IF(BM60=1, "CN", "")),(IF(BQ60=1, " NZ", "")),(IF(BU60=1, " SBT", "")),(IF(BY60=1, " RE100", ""))) -> CN | E60: EC | F60: 45477 | G60: DT | H60: -2222 | J60: Aerospace and defense | K60: United States of America (USA) | L60: North America | M60: N | P60: N | X60: C | Y60: scope 1 and 2 GHG emissions | Z60: mitigated | AA60: C | AB60: 2020 | AC60: 2020 | AG60: Y | AH60: 2024 | AI60: Y | AJ60: https://www.boeing.com/content/dam/boeing/boeingdotcom/sustainability/pdf/2024-boeing-sustainability-socialImpact-report.pdf?v=0710 | AL60: https://www.boeing.com/content/dam/boeing/boeingdotcom/sustainability/pdf/2024-boeing-sustainability-socialImpact-report.pdf?v=0710 | AN60: N | AQ60: N | BD60: C | BE60: https://www.boeing.com/content/dam/boeing/boeingdotcom/sustainability/pdf/2024-boeing-sustainability-socialImpact-report.pdf | BJ60: 1 | BM60: 1 | BZ60: 1 | CA60: 1 | CB60: 1 | CC60: 1 | CE60: 1 | CF60: 1 | CG60: 1 | CH60: 1
A61: 105 | B61: Bosch Group | C61: 118 | D61: =CONCATENATE((IF(BM61=1, "CN", "")),(IF(BQ61=1, " NZ", "")),(IF(BU61=1, " SBT", "")),(IF(BY61=1, " RE100", ""))) -> CN | E61: EC | F61: 45475 | G61: AJ | H61: 2271.3 | J61: Automotive | K61: Germany | L61: Europe | M61: N | P61: N | X61: C | Y61: scope 1 & 2 | Z61: carbon neutral | AA61: C | AB61: 2020 | AC61: 2019 | AG61: Y | AH61: 2023 | AI61: Y | AJ61: https://assets.bosch.com/media/global/sustainability/reporting_and_data/2023/bosch-sustainability-report-2023.pdf | AL61: https://assets.bosch.com/media/global/sustainability/reporting_and_data/2023/bosch-sustainability-report-2023.pdf | AM61: https://www.bosch-presse.de/pressportal/de/en/climate-action-bosch-to-be-carbon-neutral-worldwide-by-2020-188800.html | AN61: N | AQ61: N | BJ61: 1 | BM61: 1 | BZ61: 1 | CA61: 1 | CB61: 1 | CC61: 1 | CE61: 1 | CF61: 1 | CG61: 1 | CH61: 1
A62: 225 | B62: Bouygues | C62: 309 | D62: =CONCATENATE((IF(BM62=1, "CN", "")),(IF(BQ62=1, " NZ", "")),(IF(BU62=1, " SBT", "")),(IF(BY62=1, " RE100", ""))) -> SBT | E62: EC | F62: 45481 | G62: AJ | H62: 1124.3 | J62: Engineering and construction | K62: France | L62: Europe | M62: N | P62: Y | Q62: Targets Set | R62: 1.5Â°C | S62: 2030 | T62: No | V62: 44593 | W62: 2022 | X62: N | AA62: N | AN62: N | AQ62: N | BD62: V | BE62: https://www.bouygues.com/wp-content/uploads/2024/02/bouygues_2023_integrated_report_va.pdf | BS62: 1 | BU62: 1 | CE62: 1 | CG62: 1 | CH62: 1
A63: 25 | B63: BP | C63: 22 | D63: =CONCATENATE((IF(BM63=1, "CN", "")),(IF(BQ63=1, " NZ", "")),(IF(BU63=1, " SBT", "")),(IF(BY63=1, " RE100", ""))) -> NZ | E63: AJ - DT | F63: 45474 | G63: AJ | H63: 15239 | J63: Oil and gas | K63: United Kingdom | L63: Europe | M63: N | P63: N | X63: N | AA63: N | AN63: V | AO63: operations, production, and sold energy products | AP63: Net Zero | AQ63: V | AR63: 2050 | AS63: 2020 | AW63: Y | AX63: https://www.bp.com/content/dam/bp/country-sites/en_gb/united-kingdom/home/reports/bp-net-zero-progress-update-2024.pdf | AY63: 2024 | AZ63: Y | BA63: https://www.bp.com/content/dam/bp/business-sites/en/global/corporate/pdfs/sustainability/group-reports/bp-sustainability-report-2023.pdf | BC63: https://www.bp.com/content/dam/bp/business-sites/en/global/corporate/pdfs/sustainability/group-reports/bp-sustainability-report-2023.pdf | BP63: 1 | BQ63: 1 | BZ63: 1 | CB63: 1 | CC63: 1 | CE63: 1 | CH63: 1 | CK63: 1 | CL63: 1 | CM63: =MAX(U63,AR63) -> 2050
A64: 342 | B64: Bristol-Myers Squibb | C64: 312 | D64: =CONCATENATE((IF(BM64=1, "CN", "")),(IF(BQ64=1, " NZ", "")),(IF(BU64=1, " SBT", "")),(IF(BY64=1, " RE100", ""))) -> NZ SBT | E64: EC | F64: 45481 | G64: AJ | H64: 8025 | J64: Health care and pharmaceuticals | K64: United States of America (USA) | L64: North America | M64: N | P64: Y | Q64: Targets Set | R64: 1.5°C | S64: 2028 | T64: Yes | U64: 2050 | V64: 01/07/2024 | W64: 2024 | X64: N | AA64: N | AN64: V | AO64: Scopes 1, 2 and 3 | AP64: Net-Zero emission | AQ64: V | AR64: 2050 | AS64: 2024 | AW64: Y | AX64: https://www.esg.bms.com/assets/bms-esg/us/documents/BMS-ESG-Report-2023.pdf | BC64: https://www.bms.com/assets/bms/gb/en_gb/images/UK-Final-Carbon-Reduction-Plan-270324.pdf | BP64: 1 | BQ64: 1 | BS64: 1 | BU64: 1 | BZ64: 1 | CB64: 1 | CC64: 1 | CE64: 1 | CG64: 1 | CH64: 1 | CK64: 1 | CL64: 1 | CM64: =MAX(U64,AR64) -> 2050
A65: 464 | B65: British American Tobacco | C65: 445 | D65: =CONCATENATE((IF(BM65=1, "CN", "")),(IF(BQ65=1, " NZ", "")),(IF(BU65=1, " SBT", "")),(IF(BY65=1, " RE100", ""))) -> NZ SBT | E65: DT * | F65: 45511 | G65: DT | H65: -17855.4 | J65: Food, beverages and agriculture | K65: United Kingdom | L65: Europe | M65: N | P65: Y | Q65: Targets Set | R65: 1.5Â°C | S65: 2030 | T65: No | V65: 44743 | W65: 2022 | X65: N | AA65: N | AN65: V | AO65: Value Chain | AP65: Net Zero GHG Emissions | AQ65: V | AR65: 2050 | AS65: 2021 | AW65: Y | AX65: https://www.bat.com/sustainability-and-esg/environment-and-climate/climate-change#:~:text=In%202021%2C%20BAT%20signed%2Dup,by%202050%20at%20the%20latest. https://www.bat.com/content/dam/batcom/global/main-nav/investors-and-reporting/reporting/combined-annual-and-esg-report/BAT_Combined_Performance_and_Sustainability_Summary_2023.pdf | BP65: 1 | BQ65: 1 | BS65: 1 | BU65: 1 | BZ65: 1 | CB65: 1 | CC65: 1 | CE65: 1 | CG65: 1 | CH65: 1 | CK65: 1 | CL65: 1 | CM65: =MAX(U65,AR65) -> 2050
A66: 427 | B66: Broadcom | C66: 462 | D66: =CONCATENATE((IF(BM66=1, "CN", "")),(IF(BQ66=1, " NZ", "")),(IF(BU66=1, " SBT", "")),(IF(BY66=1, " RE100", ""))) -> SBT | E66: DT** | F66: 45512 | G66: DT | H66: 14082 | J66: Technology | K66: United States of America (USA) | L66: North America | M66: N | P66: N | Q66: Committed | S66: 2030 | T66: No | V66: 45323 | W66: 2024 | X66: N | AA66: N | AN66: N | AQ66: N | BS66: 1 | BU66: 1 | CE66: 1 | CG66: 1 | CH66: 1
A67: 113 | B67: Brookfield | C67: 117 | D67: =CONCATENATE((IF(BM67=1, "CN", "")),(IF(BQ67=1, " NZ", "")),(IF(BU67=1, " SBT", "")),(IF(BY67=1, " RE100", ""))) -> NZ | E67: EC | F67: 45475 | G67: AJ | H67: 1130 | J67: Financial services | K67: Canada | L67: North America | M67: N | P67: N | X67: N | AA67: N | AN67: F | AO67: assets we manage | AP67: Net Zero emissions | AQ67: F | AR67: 2050 | AS67: 2022 | AW67: U | AX67: https://www.brookfield.com/responsibility/2022-sustainability-report | BP67: 1 | BQ67: 1 | BZ67: 1 | CB67: 1 | CE67: 1 | CH67: 1 | CK67: 1 | CL67: 1 | CM67: =MAX(U67,AR67) -> 2050
A68: 230 | B68: Bunge | C68: 194 | D68: =CONCATENATE((IF(BM68=1, "CN", "")),(IF(BQ68=1, " NZ", "")),(IF(BU68=1, " SBT", "")),(IF(BY68=1, " RE100", ""))) -> SBT | E68: EC | F68: 45477 | G68: DT | H68: 2243 | J68: Food, beverages and agriculture | K68: United States of America (USA) | L68: North America | M68: N | P68: Y | Q68: Targets Set | R68: Well-below 2Â°C | S68: 2030 | T68: No | V68: 44501 | W68: 2021 | X68: N | AA68: N | AN68: N | AQ68: N | BS68: 1 | BU68: 1 | CE68: 1 | CG68: 1 | CH68: 1
A69: 143 | B69: BYD | C69: 212 | D69: =CONCATENATE((IF(BM69=1, "CN", "")),(IF(BQ69=1, " NZ", "")),(IF(BU69=1, " SBT", "")),(IF(BY69=1, " RE100", ""))) -> SBT | E69: AJ | F69: 45476 | G69: DT | H69: 4243.5 | J69: Automotive | K69: China | L69: Asia | M69: N | P69: N | Q69: Committed | S69: 2030 | T69: Yes | V69: 45505 | W69: 2024 | X69: G | Y69: company | Z69: carbon neutral | AA69: G | AB69: 2060 | AC69: 2021 | AL69: https://www.bydglobal.com/sitesresources/common/tools/generic/web/viewer.html?file=%2Fsites%2FSatellite%2FBYD%20PDF%20Viewer%3Fblobcol%3Durldata%26blobheader%3Dapplication%252Fpdf%26blobkey%3Did%26blobtable%3DMungoBlobs%26blobwhere%3D1638928374508%26ssbinary%3Dtrue | AN69: N | AQ69: N | BD69: Y | BE69: https://en.byd.com/news/byd-reflects-on-its-cop26-journey-and-the-importance-of-electrification-in-driving-a-greener-world/#:~:text=Through%20sustainable%20development%20and%20pioneering,electrification%20on%20a%20global%20scale. | BF69: N | BS69: 1 | BU69: 1 | CE69: 1 | CG69: 1 | CH69: 1
A70: 334 | B70: Caixa Economica Federal | C70: 406 | D70: =CONCATENATE((IF(BM70=1, "CN", "")),(IF(BQ70=1, " NZ", "")),(IF(BU70=1, " SBT", "")),(IF(BY70=1, " RE100", ""))) | E70: AJ | F70: 45511 | G70: AJ | H70: 2349.7 | J70: Financial services | K70: Brazil | L70: Other | M70: N | P70: N | X70: N | AA70: N | AN70: N | AQ70: N
A71: 367 | B71: Canadian Imperial Bank of Commerce | D71: =CONCATENATE((IF(BM71=1, "CN", "")),(IF(BQ71=1, " NZ", "")),(IF(BU71=1, " SBT", "")),(IF(BY71=1, " RE100", ""))) -> CN NZ | E71: AJ | F71: 45511 | H71: 3704.2 | I71: Banks: Commercial and Savings | J71: Financial services | K71: Canada | L71: North America | M71: N | P71: N | X71: C | Y71: operations | Z71: carbon neutrality | AA71: C | AB71: 2024 | AC71: 2021 | AG71: Y | AH71: 2023 | AI71: Y | AJ71: https://www.cibc.com/content/dam/about_cibc/corporate_responsibility/pdfs/cibc-sustainability-report-2023-en.pdf | AL71: https://www.newswire.ca/news-releases/cibc-declares-net-zero-ambition-by-2050-increases-sustainable-finance-target-874670170.html | AN71: C+F | AO71: operational and financing activities | AP71: Net Zero | AQ71: C+F | AR71: 2050 | AS71: 2021 | AW71: Y | AX71: https://www.newswire.ca/news-releases/cibc-declares-net-zero-ambition-by-2050-increases-sustainable-finance-target-874670170.html | AY71: 2023 | AZ71: Y | BA71: https://www.cibc.com/content/dam/about_cibc/corporate_responsibility/pdfs/cibc-sustainability-report-2023-en.pdf | BK71: 1 | BM71: 1 | BP71: 1 | BQ71: 1 | BZ71: 1 | CA71: 1 | CB71: 1 | CC71: 1 | CE71: 1 | CG71: 1 | CH71: 1 | CK71: 1 | CL71: 1 | CM71: =MAX(U71,AR71) -> 2050
A72: 304 | B72: Capital One Financial | C72: 386 | D72: =CONCATENATE((IF(BM72=1, "CN", "")),(IF(BQ72=1, " NZ", "")),(IF(BU72=1, " SBT", "")),(IF(BY72=1, " RE100", ""))) -> CN RE100 | E72: DT | F72: 45482 | G72: DT | H72: 4887 | J72: Financial services | K72: United States of America (USA) | L72: North America | M72: Y | N72: 2018 | O72: 2021 | P72: N | X72: C | Y72: Scope 1 and 2 emissions and business travel emissions in Scope 3 | Z72: carbon neutral | AA72: C | AB72: 2030 | AC72: 2017 | AG72: N | AH72: 2023 | AI72: N | AJ72: https://ecm.capitalone.com/WCM/stories/pdfs/2023-capital-one-environmental-social-and-governance-report.pdf?external_id=Our-Commitments | AL72: https://ecm.capitalone.com/WCM/stories/pdfs/2023-capital-one-environmental-social-and-governance-report.pdf?external_id=Environment | AM72: Discontinued use of carbon offsets to achieve our GHG reduction targets. Introduced goal to reduce Scope 1 emissions by 50% and Scope 3 (Categories 1-14) emissions by 50% by 2030 (from a baseline year of 2019) | AN72: N | AQ72: N | BK72: 1 | BM72: 1 | BV72: 1 | BY72: 1 | BZ72: 1 | CA72: 1 | CB72: 1 | CD72: 1 | CE72: 1 | CF72: 1 | CG72: 1 | CH72: 1
A73: 27 | B73: Cardinal Health | C73: 34 | D73: =CONCATENATE((IF(BM73=1, "CN", "")),(IF(BQ73=1, " NZ", "")),(IF(BU73=1, " SBT", "")),(IF(BY73=1, " RE100", ""))) -> SBT | E73: EC | F73: 45474 | G73: DT | H73: 261 | J73: Retail | K73: United States of America (USA) | L73: North America | M73: N | P73: Y | Q73: Targets Set | R73: 1.5Â°C | S73: 2030 | T73: No | V73: 45352 | W73: 2024 | X73: N | AA73: N | AN73: N | AQ73: N | BH73: The UK arm has a net zero plan but not the US - what % revenue comes from UK? | BI73: https://www.cardinalhealth.co.uk/content/dam/corp/web/documents/Report/cardinal-health-uk-nhs-carbon-reduction-plan.pdf | BS73: 1 | BU73: 1 | CE73: 1 | CG73: 1 | CH73: 1
A74: 122 | B74: Carrefour | C74: 125 | D74: =CONCATENATE((IF(BM74=1, "CN", "")),(IF(BQ74=1, " NZ", "")),(IF(BU74=1, " SBT", "")),(IF(BY74=1, " RE100", ""))) -> CN SBT | E74: EC | F74: 45476 | G74: AJ | H74: 1793.5 | J74: Retail | K74: France | L74: Europe | M74: N | P74: Y | Q74: Targets Set | R74: Well-below 2Â°C | S74: 2030 | T74: No | V74: 43983 | W74: 2020 | X74: C | Y74: direct emissions | Z74: carbon neutrality | AA74: C | AB74: 2040 | AC74: 2021 | AG74: U | AI74: Y | AL74: https://www.carrefour.com/sites/default/files/2023-04/Carrefour%20DPEF_English%20Version.pdf | AN74: N | AQ74: N | BL74: 1 | BM74: 1 | BS74: 1 | BU74: 1 | BZ74: 1 | CB74: 1 | CE74: 1 | CG74: 1 | CH74: 1
A75: 199 | B75: Caterpillar | C75: 230 | D75: =CONCATENATE((IF(BM75=1, "CN", "")),(IF(BQ75=1, " NZ", "")),(IF(BU75=1, " SBT", "")),(IF(BY75=1, " RE100", ""))) | E75: DT | F75: 45477 | G75: DT | H75: 10335 | J75: Industrial goods | K75: United States of America (USA) | L75: North America | M75: N | P75: N | X75: N | AA75: N | AN75: N | AQ75: N | BD75: C | BE75: https://www.climateaction100.org/company/caterpillar-inc/#skeletabsPanel1 https://www.caterpillar.com/en/company/sustainability/2030-sustainability-goals.html https://www.caterpillar.com/en/company/sustainability/energy-climate.html
A76: 18 | B76: Cencora | C76: 24 | D76: =CONCATENATE((IF(BM76=1, "CN", "")),(IF(BQ76=1, " NZ", "")),(IF(BU76=1, " SBT", "")),(IF(BY76=1, " RE100", ""))) -> SBT | E76: AJ - DT | F76: 45474 | G76: AJ | H76: 1745.3 | J76: Retail | K76: United States of America (USA) | L76: North America | M76: N | P76: Y | Q76: Targets Set | R76: 1.5Â°C | S76: 2026 | T76: No | V76: 45231 | W76: 2023 | X76: N | AA76: N | AN76: N | AQ76: N | BC76: https://www.amerisourcebergen.com/-/media/assets/amerisourcebergen/pdf/ab-fy22-esg-summary-report.pdf | BS76: 1 | BU76: 1 | CE76: 1 | CG76: 1 | CH76: 1
A77: 390 | B77: Cenovus Energy | C77: 277 | D77: =CONCATENATE((IF(BM77=1, "CN", "")),(IF(BQ77=1, " NZ", "")),(IF(BU77=1, " SBT", "")),(IF(BY77=1, " RE100", ""))) -> NZ | E77: AJ | F77: 45478 | G77: AJ | H77: 3045.3 | J77: Metals and mining | K77: Canada | L77: North America | M77: N | P77: N | X77: N | AA77: N | AN77: C | AO77: operations | AP77: Net Zero emissions | AQ77: C | AR77: 2050 | AS77: 2020 | AW77: U | AX77: https://www.cbc.ca/news/canada/calgary/cenovus-oilsands-sustainability-strategy-1.5420652 | BD77: Y | BE77: https://www.cenovus.com/News-and-Stories/News-releases/2023/2696943 | BP77: 1 | BQ77: 1 | BZ77: 1 | CB77: 1 | CE77: 1 | CH77: 1 | CM77: =MAX(U77,AR77) -> 2050
A78: 46 | B78: Centene | C78: 60 | D78: =CONCATENATE((IF(BM78=1, "CN", "")),(IF(BQ78=1, " NZ", "")),(IF(BU78=1, " SBT", "")),(IF(BY78=1, " RE100", ""))) | E78: AJ - EC | F78: 45475 | G78: DT | H78: 2702 | J78: Health care and pharmaceuticals | K78: United States of America (USA) | L78: North America | M78: N | P78: N | X78: N | AA78: N | AN78: N | AQ78: N | BD78: N | BF78: N
A79: 485 | B79: Centrica | D79: =CONCATENATE((IF(BM79=1, "CN", "")),(IF(BQ79=1, " NZ", "")),(IF(BU79=1, " SBT", "")),(IF(BY79=1, " RE100", ""))) -> NZ | E79: AJ | F79: 45512 | H79: 4883 | I79: Utilities | J79: Energy and utilities | K79: United Kingdom | L79: Europe | M79: N | P79: N | X79: N | AA79: N | AN79: C, V | AO79: business (scope 1 and 2), customers (scope 1, 2, and 3) | AP79: Net Zero | AQ79: C | AR79: 2045 | AS79: 2021 | AT79: V | AU79: 2050 | AV79: 2021 | AW79: U | AX79: https://www.centrica.com/stories/2021/centricas-climate-transition-plan/ | AY79: 2023 | AZ79: Y | BA79: https://www.centrica.com/media/inqbe0ip/people-planet-plan-report-2023.pdf | BP79: 1 | BQ79: 1 | BZ79: 1 | CB79: 1 | CE79: 1 | CH79: 1 | CK79: 1 | CL79: 1 | CM79: =MAX(U79,AR79) -> 2045
A80: 420 | B80: CFE | D80: =CONCATENATE((IF(BM80=1, "CN", "")),(IF(BQ80=1, " NZ", "")),(IF(BU80=1, " SBT", "")),(IF(BY80=1, " RE100", ""))) | E80: DT** | F80: 45512 | H80: 5481.6 | J80: Industrial goods | K80: Mexico | L80: North America | M80: N | P80: N | X80: N | AA80: N | AN80: N | AQ80: N
A81: 255 | B81: Charter Communications | C81: 261 | D81: =CONCATENATE((IF(BM81=1, "CN", "")),(IF(BQ81=1, " NZ", "")),(IF(BU81=1, " SBT", "")),(IF(BY81=1, " RE100", ""))) -> CN | E81: AJ | F81: 45477 | G81: AJ | H81: 4557 | J81: Telecommunications and media | K81: United States of America (USA) | L81: North America | M81: N | P81: N | X81: C | Y81: operations | Z81: carbon neutral | AA81: C | AB81: 2035 | AC81: 2020 | AG81: U | AI81: Y | AL81: https://www.nyc.gov/assets/dep/downloads/pdf/air/air-pollution-control-code-variance-4-charter-spectrum-addendum-2.pdf | AN81: N | AQ81: N | BL81: 1 | BM81: 1 | BZ81: 1 | CB81: 1 | CE81: 1 | CH81: 1
A82: 385 | B82: Chery Holding Group | D82: =CONCATENATE((IF(BM82=1, "CN", "")),(IF(BQ82=1, " NZ", "")),(IF(BU82=1, " SBT", "")),(IF(BY82=1, " RE100", ""))) | E82: AJ | F82: 45511 | H82: 585.7 | I82: Motor Vehicles & Parts | J82: Automotive | K82: China | L82: Asia | M82: N | P82: N | X82: N | AA82: N | AN82: N | AQ82: N
A83: 29 | B83: Chevron | C83: 23 | D83: =CONCATENATE((IF(BM83=1, "CN", "")),(IF(BQ83=1, " NZ", "")),(IF(BU83=1, " SBT", "")),(IF(BY83=1, " RE100", ""))) -> NZ | E83: AJ | F83: 45474 | G83: AJ | H83: 21369 | J83: Oil and gas | K83: United States of America (USA) | L83: North America | M83: N | P83: N | X83: N | AA83: N | AN83: C | AO83: upstream scope 1 and 2 | AP83: Net Zero | AQ83: C | AR83: 2050 | AS83: 2021 | AW83: Y | AX83: https://www.chevron.com/newsroom/2021/Q4/chevron-sets-net-zero-aspiration-and-new-GHG-intensity-target | AY83: 2023 | AZ83: Y | BA83: https://www.chevron.com/newsroom/media/publications/corporate-sustainability-report | BC83: https://www.chevron.com/newsroom/media/publications/corporate-sustainability-report | BP83: 1 | BQ83: 1 | BZ83: 1 | CB83: 1 | CC83: 1 | CE83: 1 | CH83: 1 | CM83: =MAX(U83,AR83) -> 2050
A84: 44 | B84: China Baowu Steel Group | C84: 44 | D84: =CONCATENATE((IF(BM84=1, "CN", "")),(IF(BQ84=1, " NZ", "")),(IF(BU84=1, " SBT", "")),(IF(BY84=1, " RE100", ""))) -> CN | E84: EC | F84: 45474 | G84: DT | H84: 2493.8 | J84: Metals and mining | K84: China | L84: Asia | M84: N | P84: N | X84: C | Y84: undefined | Z84: carbon neutrality | AA84: C | AB84: 2050 | AC84: 2020 | AG84: U | AI84: Y | AL84: https://res.baowugroup.com/attach/2021/10/29/1a2ad022172a46f6b2f31b5377a07ea5.pdf | AN84: N | AQ84: N | BL84: 1 | BM84: 1 | BZ84: 1 | CB84: 1 | CE84: 1 | CH84: 1
A85: 63 | B85: China Communications Construction | C85: 63 | D85: =CONCATENATE((IF(BM85=1, "CN", "")),(IF(BQ85=1, " NZ", "")),(IF(BU85=1, " SBT", "")),(IF(BY85=1, " RE100", ""))) | E85: DT | F85: 45475 | G85: DT | H85: 1672.3 | J85: Engineering and construction | K85: China | L85: Asia | M85: N | P85: N | X85: G | Y85: global products and operations | Z85: carbon neutral | AA85: G | AB85: 2060 | AC85: 2023 | AL85: https://www.chinaccs.com.hk/en/about/esg/esg01.pdf https://en.ccccltd.cn/tzzgx/dxbg/202403/P020240430625761317276.pdf | AM85: The Company formulated the â€œImplementation Rules of China Comservice for the Management of â€˜Carbon Peak, Carbon Neutralityâ€™ in 2023â€, which clarifies the â€œDual Carbonâ€ management indicators and specific implementation rules of the Groupâ€™s subsidiaries, objectively evaluates the implementation and effectiveness of the various tasks, and promotes the effective completion of the â€œDual Carbonâ€ work. I | AN85: N | AQ85: N
A86: 30 | B86: China Construction Bank | C86: 29 | D86: =CONCATENATE((IF(BM86=1, "CN", "")),(IF(BQ86=1, " NZ", "")),(IF(BU86=1, " SBT", "")),(IF(BY86=1, " RE100", ""))) | E86: EC | F86: 45474 | G86: AJ | H86: 46990 | J86: Financial services | K86: China | L86: Asia | M86: N | P86: N | X86: G | Y86: undefined | Z86: carbon neutrality | AA86: G | AB86: 2060 | AC86: 2021 | AL86: https://www.ccccltd.cn/shzr/zrbg/202209/P020220920571098883908.pdf | AN86: N | AQ86: N
A87: 418 | B87: China Datang | C87: 396 | D87: =CONCATENATE((IF(BM87=1, "CN", "")),(IF(BQ87=1, " NZ", "")),(IF(BU87=1, " SBT", "")),(IF(BY87=1, " RE100", ""))) | E87: DT | F87: 45482 | G87: DT | H87: 332.9 | J87: Energy and utilities | K87: China | L87: Asia | M87: N | P87: N | X87: G | Y87: undefined | Z87: carbon neutral | AA87: G | AB87: 2060 | AC87: 2021 | AL87: https://www.china-cdt.com/dtwz/UPLOAD/BB9DA6A4-05CB-3A0A-6054-568DB5A3383E16600250995441.pdf | AN87: N | AQ87: N
A88: 435 | B88: China Electronics | C88: 368 | D88: =CONCATENATE((IF(BM88=1, "CN", "")),(IF(BQ88=1, " NZ", "")),(IF(BU88=1, " SBT", "")),(IF(BY88=1, " RE100", ""))) | E88: DT | F88: 45481 | G88: DT | H88: 26.8 | J88: Industrial goods | K88: China | L88: Asia | M88: N | P88: N | X88: N | AA88: N | AN88: N | AQ88: N
A89: 253 | B89: China Electronics Technology Group | C89: 252 | D89: =CONCATENATE((IF(BM89=1, "CN", "")),(IF(BQ89=1, " NZ", "")),(IF(BU89=1, " SBT", "")),(IF(BY89=1, " RE100", ""))) | E89: AJ | F89: 45477 | G89: AJ | H89: 2563 | J89: Aerospace and defense | K89: China | L89: Asia | M89: N | P89: N | X89: N | AA89: N | AN89: N | AQ89: N | BC89: could not find anything | BD89: N | BF89: N
A90: 239 | B90: China Energy Engineering Group | C90: 256 | D90: =CONCATENATE((IF(BM90=1, "CN", "")),(IF(BQ90=1, " NZ", "")),(IF(BU90=1, " SBT", "")),(IF(BY90=1, " RE100", ""))) | E90: AJ | F90: 45477 | G90: AJ | H90: 600 | J90: Engineering and construction | K90: China | L90: Asia | M90: N | P90: N | X90: G | Y90: undefined | Z90: carbon neutral | AA90: G | AB90: 2060 | AC90: 2022 | AL90: https://www1.hkexnews.hk/listedco/listconews/sehk/2023/0330/2023033004476.pdf | AN90: N | AQ90: N
A91: 84 | B91: China Energy Investment | C91: 76 | D91: =CONCATENATE((IF(BM91=1, "CN", "")),(IF(BQ91=1, " NZ", "")),(IF(BU91=1, " SBT", "")),(IF(BY91=1, " RE100", ""))) | E91: DT | F91: 45475 | G91: DT | H91: 6339.1 | J91: Metals and mining | K91: China | L91: Asia | M91: N | P91: N | X91: G | Y91: undefined | Z91: carbon neutrality | AA91: G | AB91: 2060 | AC91: 2022 | AL91: http://www.ceic.com/gjnyjtww/jtgsbg/202305/3753834acccd47758d40a99d0ed14ad3/files/b736223431eb4434908f62d7bf8156b4.pdf | AN91: N | AQ91: N
A92: 129 | B92: China FAW Group | C92: 131 | D92: =CONCATENATE((IF(BM92=1, "CN", "")),(IF(BQ92=1, " NZ", "")),(IF(BU92=1, " SBT", "")),(IF(BY92=1, " RE100", ""))) | E92: EC - AJ | F92: 45476 | G92: AJ | H92: 2864.2 | J92: Automotive | K92: China | L92: Asia | M92: N | P92: N | X92: G | Y92: undefined | Z92: carbon neutrality | AA92: G | AB92: 2060 | AC92: 2022 | AL92: https://downloads.ctfassets.net/mt8w0y3iajsh/6AYQ2nyQcvlBr58DedN1G9/97efd8b46284451229c5d31841aa1ae6/FAW_Sustainable_Development_Report_2022.pdf | AN92: N | AQ92: N
A93: 336 | B93: China Huadian | C93: 323 | D93: =CONCATENATE((IF(BM93=1, "CN", "")),(IF(BQ93=1, " NZ", "")),(IF(BU93=1, " SBT", "")),(IF(BY93=1, " RE100", ""))) | E93: EC | F93: 45481 | G93: DT | H93: 1909.5 | J93: Energy and utilities | K93: China | L93: Asia | M93: N | P93: N | X93: G | Y93: undefined | Z93: carbon neutrality | AA93: G | AB93: 2060 | AC93: 2021 | AL93: https://www1.hkexnews.hk/listedco/listconews/sehk/2023/0419/2023041900261.pdf | AM93: https://www.worldbenchmarkingalliance.org/publication/electric-utilities/companies/china-huadian-corporation-2/#:~:text=China%20Huadian%20just%20released%20its,50%25%20of%20its%20installed%20capacity. | AN93: N | AQ93: N
A94: 238 | B94: China Huaneng Group | C94: 209 | D94: =CONCATENATE((IF(BM94=1, "CN", "")),(IF(BQ94=1, " NZ", "")),(IF(BU94=1, " SBT", "")),(IF(BY94=1, " RE100", ""))) | E94: EC | F94: 45477 | G94: DT | H94: 1632.1 | J94: Energy and utilities | K94: China | L94: Asia | M94: N | P94: N | X94: G | Y94: undefined | Z94: carbon neutrality | AA94: G | AB94: 2060 | AC94: 2021 | AL94: https://www.chng.com.cn/en/documents/816545/837789/3cdbdd89-c975-457e-9f6f-76d370e1e855.pdf | AN94: N | AQ94: N
A95: 59 | B95: China Life Insurance | C95: 54 | D95: =CONCATENATE((IF(BM95=1, "CN", "")),(IF(BQ95=1, " NZ", "")),(IF(BU95=1, " SBT", "")),(IF(BY95=1, " RE100", ""))) | E95: AJ | F95: 45475 | G95: DT | H95: -841.2 | J95: Financial services | K95: China | L95: Asia | M95: N | P95: N | X95: N | AA95: N | AN95: N | AQ95: N | BC95: confusion as similar company (china life) mentions a parent company goal of net zero operations by 2045 but not clear this applies to THIS company | BD95: N | BF95: N
A96: 179 | B96: China Merchants Bank | C96: 179 | D96: =CONCATENATE((IF(BM96=1, "CN", "")),(IF(BQ96=1, " NZ", "")),(IF(BU96=1, " SBT", "")),(IF(BY96=1, " RE100", ""))) | E96: AJ | F96: 45476 | G96: DT | H96: 20708.7 | J96: Financial services | K96: China | L96: Asia | M96: N | P96: N | X96: G | Y96: undefined | Z96: carbon neutrality | AA96: G | AB96: 2060 | AC96: 2021 | AL96: https://s3gw.cmbimg.com/lb50.01-cmbweb-prd/CIOAMananger/20240325/46e9e604-5282-45de-9ccd-a7378a14bec3.pdf | AN96: N | AQ96: N | BD96: N | BF96: N
A97: 69 | B97: China Minmetals | C97: 65 | D97: =CONCATENATE((IF(BM97=1, "CN", "")),(IF(BQ97=1, " NZ", "")),(IF(BU97=1, " SBT", "")),(IF(BY97=1, " RE100", ""))) | E97: DT - AJ | F97: 45475 | G97: DT | H97: 766 | J97: Metals and mining | K97: China | L97: Asia | M97: N | P97: N | X97: G | Y97: undefined | Z97: carbon neutral | AA97: G | AB97: 2060 | AC97: 2022 | AL97: http://www.minmetals.com/english/sustainabledevelopment/sustainabilityreport/202307/P020230824370906926933.pdf | AN97: N | AQ97: N
A98: 351 | B98: China Minsheng Banking | C98: 329 | D98: =CONCATENATE((IF(BM98=1, "CN", "")),(IF(BQ98=1, " NZ", "")),(IF(BU98=1, " SBT", "")),(IF(BY98=1, " RE100", ""))) | E98: EC | F98: 45481 | G98: DT | H98: 5060.3 | J98: Financial services | K98: China | L98: Asia | M98: N | P98: N | X98: G | Y98: undefined | Z98: carbon neutrality | AA98: G | AB98: 2060 | AC98: 2021 | AL98: https://en.cmbc.com.cn/upload/images/2023/9/2023%20Environmental,%20Social%20and%20Governance%20Report%20CMBC.pdf | AN98: N | AQ98: N
A99: 55 | B99: China Mobile Communications | C99: 62 | D99: =CONCATENATE((IF(BM99=1, "CN", "")),(IF(BQ99=1, " NZ", "")),(IF(BU99=1, " SBT", "")),(IF(BY99=1, " RE100", ""))) | E99: DT - AJ | F99: 45475 | G99: DT | H99: 15253.4 | J99: Telecommunications and media | K99: China | L99: Asia | M99: N | P99: N | X99: G | Y99: undefined | Z99: carbon neutrality | AA99: G | AB99: 2060 | AC99: 2021 | AL99: https://www.chinamobileltd.com/en/ir/reports/ar2023/sd2023.pdf | AN99: N | AQ99: N | AX99: https://www.chinamobileltd.com/en/ir/reports/ar2023/sd2023.pdf | BC99: C2 Three Energy - China Mobile Carbon Peaking and Carbon Neutrality Action Plan | BF99: N
A100: 483 | B100: China National Aviation Fuel Group | C100: 483 | D100: =CONCATENATE((IF(BM100=1, "CN", "")),(IF(BQ100=1, " NZ", "")),(IF(BU100=1, " SBT", "")),(IF(BY100=1, " RE100", ""))) | E100: DT * | F100: 45511 | G100: DT | H100: 98.8 | J100: Oil and gas | K100: China | L100: Asia | M100: N | P100: N | X100: N | AA100: N | AN100: N | AQ100: N
...

Sheet 2023
A1: Column1 | B1: Column2 | C1: Column3 | D1: Column4 | E1: Column5 | F1: Column6 | G1: Column7 | H1: Column8 | I1: Column9 | J1: Column10 | K1: Column11 | L1: Column12 | M1: Column13 | N1: Column14 | O1: Column15 | P1: Column152 | Q1: Column16 | R1: Column17 | S1: Column18 | T1: Column19 | U1: Column20 | V1: Column202 | W1: Column21 | X1: Column22 | Y1: Column23 | Z1: Column24 | AA1: Column25 | AB1: Column26 | AC1: Column27 | AD1: Column28 | AE1: Column29 | AF1: Column30 | AG1: Column31 | AH1: Column32 | AI1: Column33 | AJ1: Column34 | AK1: Column35 | AL1: Column36 | AM1: Column37 | AN1: Column38 | AO1: Column39 | AP1: Column40 | AQ1: Column41 | AR1: Column42 | AS1: Column43
A2: Company information - source: Fortune, accessed 2 August 2023 https://fortune.com/global500/ | G2: RE100 - source: RE100 (The Climate Group), 2021 Progress and Insights Annual Report https://www.there100.org/stepping-re100-gathers-speed-challenging-markets and member page https://www.there100.org/re100-members accessed on 7 August 2023 | J2: Science Based Targets - source: Science Based Targets initiative, accessed 7 August 2023 https://sciencebasedtargets.org/download/excel | M2: Carbon neutral - source: desk-based research undertaken by Climate Impact Partners conducted between June and August 2023. See methodology section of full report for more details. Download full report via https://www.climateimpact.com/news-insights/fortune-global-500-climate-commitments/ | P2: {=IF(O2="", "", IFERROR(MAX(--_xlfn.TEXTSPLIT(O2,"+")), O2))} | S2: Net zero - source: desk-based research undertaken by Climate Impact Partners conducted between June and August 2023. See methodology section of full report for more details. Download full report via https://www.climateimpact.com/news-insights/fortune-global-500-climate-commitments/ | V2: {=IF(U2="", "", IFERROR(MAX(--_xlfn.TEXTSPLIT(U2,"+")), U2))} | Y2: CSO - source: desk-based research undertaken by Climate Impact Partners conducted between June and August 2023. See methodology section of full report for more details. Download full report via https://www.climateimpact.com/news-insights/fortune-global-500-climate-commitments/ | AB2: Emissions - source: desk-based research undertaken by Climate Impact Partners conducted between June and August 2023. See methodology section of full report for more details. Download full report via https://www.climateimpact.com/news-insights/fortune-global-500-climate-commitments/
A3: Rank | B3: Company name | C3: Headquarters | D3: Sector | E3: Revenue ($M) | F3: Profits ($M) | G3: RE100 goal | H3: From | I3: Announced | J3: Target (T) or committed (C) | K3: From (earlier of the two dates if there were two near-term targets, where target status was committed we put 2030) | L3: Announced | M3: Scope of target | N3: Scope of target in their own words | O3: From | P3: year broken down | Q3: Announced | R3: Source | S3: Scope of target | T3: Scope of target in their own words | U3: From | V3: {=IF(U3="", "", IFERROR(MAX(--_xlfn.TEXTSPLIT(U3,"+")), U3))} -> From | W3: Announced | X3: Source | Y3: CSO or equivalent | Z3: Title | AA3: Source | AV3: SBTi short term | AY3: RE100 | BB3: Carbon Neutral | BE3: Net Zero | BH3: sum
M4: C = company, V = value chain, G= government, F = financed emissions, + = the scope of the later target | N4: + = the scope of the later target | O4: + = the date of the later target | P4: {=IF(O4="", "", IFERROR(MAX(--_xlfn.TEXTSPLIT(O4,"+")), O4))} -> + = the date of the later target | Q4: + = the date of the later target | S4: V = value chain, C = company, S = subsidiary, U = unclear, x = less than 25% rev, + = the scope of the later target, SBTi = target approved under SBTi's Net Zero standard, SBTi? = have a net zero target listed by SBTi but unclear whether this is under the new standard | T4: + = the scope of the later target | U4: + = the date of the later target | V4: {=IF(U4="", "", IFERROR(MAX(--_xlfn.TEXTSPLIT(U4,"+")), U4))} -> + = the date of the later target | W4: + = the date of the later target | AB4: Most recent reporting year | AC4: Scope 1 emissions (reporting year) | AD4: Scope 2 emissions (reporting year) (location-based) | AE4: Scope 2 emissions (reporting year) (market-based) | AF4: Scope 3 emissions (reporting year) | AG4: Scope 3 complete? (Y/N) | AH4: Scope 1 + 2 emissions (reporting year) (market-based) | AI4: Total emissions (reporting year) | AJ4: Previous year | AK4: Scope 1 emissions (previous year) | AL4: Scope 2 emissions (previous year) (location-based) | AM4: Scope 2 emissions (previous year) (market-based) | AN4: Scope 3 emissions (previous year) | AO4: Scope 1 + 2 emissions (previous year) (market-based) | AP4: Total emissions (previous year) | AQ4: Emissions data source | AU4: Sector | AV4: <=2023 | AW4: 2024-2030 | AX4: 2031-2060 | AY4: <=2023 | AZ4: 2024-2030 | BA4: 2031-2060 | BB4: <=2023 | BC4: 2024-2030 | BD4: 2031-2060 | BE4: <=2023 | BF4: 2024-2030 | BG4: 2031-2060
A5: 1 | B5: Walmart | C5: United States of America (USA) | D5: Retailing | E5: $611,289 | F5: $11,680 | G5: Y | H5: 2035 | I5: 2015 | J5: T | K5: 2025 | L5: 2016 | P5: {=IF(O5="", "", IFERROR(MAX(--_xlfn.TEXTSPLIT(O5,"+")), O5))} | S5: C | T5: global operations | U5: 2040 | V5: {=IF(U5="", "", IFERROR(MAX(--_xlfn.TEXTSPLIT(U5,"+")), U5))} -> 2040 | W5: 2015 | X5: https://corporate.walmart.com/esgreport/media-library/document/walmart-fy2023-esg-highlights/_proxyDocument?id=00000188-7cfc-df51-a9b9-7ffca4320000 https://corporate.walmart.com/esgreport/environmental/climate-change https://corporate.walmart.com/newsroom/2020/09/21/walmart-sets-goal-to-become-a-regenerative-company | Y5: Y | Z5: CSO | AA5: https://corporate.walmart.com/esgreport/esg-oversight-and-management | AB5: 2021 | AC5: =7.37*1000000 -> 7370000 | AE5: =6.62*1000000 -> 6620000 | AG5: N | AH5: =AC5+AE5 -> 13990000 | AI5: =AH5 -> 13990000 | AJ5: 2020 | AK5: 15930000 | AM5: =8.68*1000000 -> 8680000 | AO5: =AK5+AM5 -> 24610000 | AP5: =AO5 -> 24610000 | AQ5: https://corporate.walmart.com/esgreport/esg-issues/climate-change | AR5: =_xlfn.XLOOKUP(C5,Sheet1!A:A,Sheet1!B:B, "Other") -> North America | AS5: =_xlfn.XLOOKUP(D5,Sheet1!D:D,Sheet1!E:E) -> Retail | AU5: Aerospace and defense | AV5: =COUNTIFS($AS$5:$AS$504,AU5,$K$5:$K$504,"<=2023") -> 0 | AW5: =COUNTIFS($AS$5:$AS$504,AU5,$K$5:$K$504,">=2024",$K$5:$K$504,"<=2030") -> 1 | AX5: =COUNTIFS($AS$5:$AS$504,AU5,$K$5:$K$504,">2030") -> 0 | AY5: =COUNTIFS($AS$5:$AS$504,AU5,$H$5:$H$504,"<=2023") -> 1 | AZ5: =COUNTIFS($AS$5:$AS$504,AU5,$H$5:$H$504,">=2024",$H$5:$H$504,"<=2030") -> 0 | BA5: =COUNTIFS($AS$5:$AS$504,AU5,$H$5:$H$504,">2030") -> 0 | BB5: =COUNTIFS($AS$5:$AS$504,AU5,$P$5:$P$504,"<=2023") -> 0 | BC5: =COUNTIFS($AS$5:$AS$504,AU5,$P$5:$P$504,">=2024",$P$5:$P$504,"<=2030") -> 0 | BD5: =COUNTIFS($AS$5:$AS$504,AU5,$P$5:$P$504,">2030") -> 1 | BE5: =COUNTIFS($AS$5:$AS$504,AU5,$V$5:$V$504,"<=2023") -> 1 | BF5: =COUNTIFS($AS$5:$AS$504,AU5,$V$5:$V$504,">=2024",$V$5:$V$504,"<=2030") -> 0 | BG5: =COUNTIFS($AS$5:$AS$504,AU5,$V$5:$V$504,">2030") -> 3 | BH5: =SUM(AV5:BG5) -> 7
A6: 2 | B6: Saudi Aramco | C6: Saudi Arabia | D6: Energy | E6: $603,651 | F6: $159,069 | P6: {=IF(O6="", "", IFERROR(MAX(--_xlfn.TEXTSPLIT(O6,"+")), O6))} | S6: C | T6: across wholly-owned operated assets | U6: 2050 | V6: {=IF(U6="", "", IFERROR(MAX(--_xlfn.TEXTSPLIT(U6,"+")), U6))} -> 2050 | W6: 2021 | X6: https://www.aramco.com/-/media/downloads/sustainability-report/report-2022/2022-sustainability-report-en.pdf | Y6: Y | Z6: CSO | AA6: https://gccbdi.org/events/eventdetails.aspx?id=1572767#:~:text=Matthew%20Bateson%2C%20Chief%20Sustainability%20Officer%2C%20Saudi%20Aramco | AB6: 2022 | AC6: 55700000 | AE6: 16100000 | AG6: N | AH6: =AC6+AE6 -> 71800000 | AI6: =AH6 -> 71800000 | AJ6: 2021 | AK6: 52300000 | AM6: 15500000 | AO6: =AK6+AM6 -> 67800000 | AP6: =AO6 -> 67800000 | AQ6: https://www.aramco.com/-/media/downloads/sustainability-report/report-2022/2022-sustainability-report-en.pdf | AR6: =_xlfn.XLOOKUP(C6,Sheet1!A:A,Sheet1!B:B, "Other") -> Other | AS6: =_xlfn.XLOOKUP(D6,Sheet1!D:D,Sheet1!E:E) -> Energy and utilities | AU6: Automotive | AV6: =COUNTIFS($AS$5:$AS$504,AU6,$K$5:$K$504,"<=2023") -> 0 | AW6: =COUNTIFS($AS$5:$AS$504,AU6,$K$5:$K$504,">=2024",$K$5:$K$504,"<=2030") -> 8 | AX6: =COUNTIFS($AS$5:$AS$504,AU6,$K$5:$K$504,">2030") -> 3 | AY6: =COUNTIFS($AS$5:$AS$504,AU6,$H$5:$H$504,"<=2023") -> 0 | AZ6: =COUNTIFS($AS$5:$AS$504,AU6,$H$5:$H$504,">=2024",$H$5:$H$504,"<=2030") -> 1 | BA6: =COUNTIFS($AS$5:$AS$504,AU6,$H$5:$H$504,">2030") -> 6 | BB6: =COUNTIFS($AS$5:$AS$504,AU6,$P$5:$P$504,"<=2023") -> 1 | BC6: =COUNTIFS($AS$5:$AS$504,AU6,$P$5:$P$504,">=2024",$P$5:$P$504,"<=2030") -> 2 | BD6: =COUNTIFS($AS$5:$AS$504,AU6,$P$5:$P$504,">2030") -> 24 | BE6: =COUNTIFS($AS$5:$AS$504,AU6,$V$5:$V$504,"<=2023") -> 0 | BF6: =COUNTIFS($AS$5:$AS$504,AU6,$V$5:$V$504,">=2024",$V$5:$V$504,"<=2030") -> 0 | BG6: =COUNTIFS($AS$5:$AS$504,AU6,$V$5:$V$504,">2030") -> 6 | BH6: =SUM(AV6:BG6) -> 51
A7: 3 | B7: State Grid | C7: China | D7: Energy | E7: $530,009 | F7: $8,192 | M7: G | N7: undefined | O7: 2060 | P7: {=IF(O7="", "", IFERROR(MAX(--_xlfn.TEXTSPLIT(O7,"+")), O7))} -> 2060 | Q7: 2021 | R7: http://www.sgcc.com.cn/html/files/2022-06/10/20220610161501291488481.pdf | V7: {=IF(U7="", "", IFERROR(MAX(--_xlfn.TEXTSPLIT(U7,"+")), U7))} | AB7: 2020 | AG7: N | AH7: 5272000 | AI7: =AH7 -> 5272000 | AJ7: 2019 | AO7: 3877000 | AP7: =AO7 -> 3877000 | AQ7: http://www.sgcc.com.cn/html/files/2022-06/10/20220610161501291488481.pdf | AR7: =_xlfn.XLOOKUP(C7,Sheet1!A:A,Sheet1!B:B, "Other") -> Asia | AS7: =_xlfn.XLOOKUP(D7,Sheet1!D:D,Sheet1!E:E) -> Energy and utilities | AU7: Chemicals | AV7: =COUNTIFS($AS$5:$AS$504,AU7,$K$5:$K$504,"<=2023") -> 0 | AW7: =COUNTIFS($AS$5:$AS$504,AU7,$K$5:$K$504,">=2024",$K$5:$K$504,"<=2030") -> 0 | AX7: =COUNTIFS($AS$5:$AS$504,AU7,$K$5:$K$504,">2030") -> 2 | AY7: =COUNTIFS($AS$5:$AS$504,AU7,$H$5:$H$504,"<=2023") -> 0 | AZ7: =COUNTIFS($AS$5:$AS$504,AU7,$H$5:$H$504,">=2024",$H$5:$H$504,"<=2030") -> 0 | BA7: =COUNTIFS($AS$5:$AS$504,AU7,$H$5:$H$504,">2030") -> 1 | BB7: =COUNTIFS($AS$5:$AS$504,AU7,$P$5:$P$504,"<=2023") -> 0 | BC7: =COUNTIFS($AS$5:$AS$504,AU7,$P$5:$P$504,">=2024",$P$5:$P$504,"<=2030") -> 1 | BD7: =COUNTIFS($AS$5:$AS$504,AU7,$P$5:$P$504,">2030") -> 7 | BE7: =COUNTIFS($AS$5:$AS$504,AU7,$V$5:$V$504,"<=2023") -> 0 | BF7: =COUNTIFS($AS$5:$AS$504,AU7,$V$5:$V$504,">=2024",$V$5:$V$504,"<=2030") -> 0 | BG7: =COUNTIFS($AS$5:$AS$504,AU7,$V$5:$V$504,">2030") -> 3 | BH7: =SUM(AV7:BG7) -> 14
A8: 4 | B8: Amazon | C8: United States of America (USA) | D8: Retailing | E8: $513,983 | F8: $-2,722 | P8: {=IF(O8="", "", IFERROR(MAX(--_xlfn.TEXTSPLIT(O8,"+")), O8))} | S8: C | T8: across our business (operations) | U8: 2040 | V8: {=IF(U8="", "", IFERROR(MAX(--_xlfn.TEXTSPLIT(U8,"+")), U8))} -> 2040 | W8: 2019 | X8: https://sustainability.aboutamazon.com/2021-sustainability-report.pdf https://sustainability.aboutamazon.com/amazon-2021-carbon-neutralization.pdf | Y8: Y | Z8: Vice President of Worldwide Sustainability | AA8: https://s2.q4cdn.com/299287126/files/doc_financials/2023/ar/Amazon-2022-Annual-Report.pdf | AB8: 2022 | AC8: 13400000 | AE8: 2890000 | AF8: 54980000 | AG8: Y | AH8: =AC8+AE8 -> 16290000 | AI8: =AF8+AH8 -> 71270000 | AJ8: 2021 | AK8: 12110000 | AM8: 4070000 | AN8: 55360000 | AO8: =AM8+AK8 -> 16180000 | AP8: =AO8+AN8 -> 71540000 | AQ8: https://sustainability.aboutamazon.co.uk/2022-sustainability-report.pdf | AR8: =_xlfn.XLOOKUP(C8,Sheet1!A:A,Sheet1!B:B, "Other") -> North America | AS8: =_xlfn.XLOOKUP(D8,Sheet1!D:D,Sheet1!E:E) -> Retail | AU8: Energy and utilities | AV8: =COUNTIFS($AS$5:$AS$504,AU8,$K$5:$K$504,"<=2023") -> 0 | AW8: =COUNTIFS($AS$5:$AS$504,AU8,$K$5:$K$504,">=2024",$K$5:$K$504,"<=2030") -> 8 | AX8: =COUNTIFS($AS$5:$AS$504,AU8,$K$5:$K$504,">2030") -> 2 | AY8: =COUNTIFS($AS$5:$AS$504,AU8,$H$5:$H$504,"<=2023") -> 0 | AZ8: =COUNTIFS($AS$5:$AS$504,AU8,$H$5:$H$504,">=2024",$H$5:$H$504,"<=2030") -> 0 | BA8: =COUNTIFS($AS$5:$AS$504,AU8,$H$5:$H$504,">2030") -> 0 | BB8: =COUNTIFS($AS$5:$AS$504,AU8,$P$5:$P$504,"<=2023") -> 2 | BC8: =COUNTIFS($AS$5:$AS$504,AU8,$P$5:$P$504,">=2024",$P$5:$P$504,"<=2030") -> 3 | BD8: =COUNTIFS($AS$5:$AS$504,AU8,$P$5:$P$504,">2030") -> 31 | BE8: =COUNTIFS($AS$5:$AS$504,AU8,$V$5:$V$504,"<=2023") -> 0 | BF8: =COUNTIFS($AS$5:$AS$504,AU8,$V$5:$V$504,">=2024",$V$5:$V$504,"<=2030") -> 0 | BG8: =COUNTIFS($AS$5:$AS$504,AU8,$V$5:$V$504,">2030") -> 33 | BH8: =SUM(AV8:BG8) -> 79
A9: 5 | B9: China National Petroleum | C9: China | D9: Petroleum Refining | E9: $483,019 | F9: $21,080 | M9: G | N9: undefined | O9: 2060 | P9: {=IF(O9="", "", IFERROR(MAX(--_xlfn.TEXTSPLIT(O9,"+")), O9))} -> 2060 | Q9: 2020 | R9: http://www.petrochina.com.cn/ptr/xhtml/images/2021esgen.pdf http://iis.aastocks.com/20230330/10653446-0.PDF | V9: {=IF(U9="", "", IFERROR(MAX(--_xlfn.TEXTSPLIT(U9,"+")), U9))} | AB9: 2022 | AC9: 119680000 | AE9: 40880000 | AG9: N | AH9: =AC9+AE9 -> 160560000 | AI9: 160560000 | AJ9: 2021 | AK9: 121390000 | AM9: 38150000 | AO9: =AM9+AK9 -> 159540000 | AP9: =AO9 -> 159540000 | AQ9: http://iis.aastocks.com/20230330/10653446-0.PDF http://www.petrochina.com.cn/petrochina/xhtml/images/shyhj/2021esgen.pdf | AR9: =_xlfn.XLOOKUP(C9,Sheet1!A:A,Sheet1!B:B, "Other") -> Asia | AS9: =_xlfn.XLOOKUP(D9,Sheet1!D:D,Sheet1!E:E) -> Oil and gas | AU9: Engineering and construction | AV9: =COUNTIFS($AS$5:$AS$504,AU9,$K$5:$K$504,"<=2023") -> 0 | AW9: =COUNTIFS($AS$5:$AS$504,AU9,$K$5:$K$504,">=2024",$K$5:$K$504,"<=2030") -> 1 | AX9: =COUNTIFS($AS$5:$AS$504,AU9,$K$5:$K$504,">2030") -> 1 | AY9: =COUNTIFS($AS$5:$AS$504,AU9,$H$5:$H$504,"<=2023") -> 0 | AZ9: =COUNTIFS($AS$5:$AS$504,AU9,$H$5:$H$504,">=2024",$H$5:$H$504,"<=2030") -> 1 | BA9: =COUNTIFS($AS$5:$AS$504,AU9,$H$5:$H$504,">2030") -> 0 | BB9: =COUNTIFS($AS$5:$AS$504,AU9,$P$5:$P$504,"<=2023") -> 0 | BC9: =COUNTIFS($AS$5:$AS$504,AU9,$P$5:$P$504,">=2024",$P$5:$P$504,"<=2030") -> 0 | BD9: =COUNTIFS($AS$5:$AS$504,AU9,$P$5:$P$504,">2030") -> 8 | BE9: =COUNTIFS($AS$5:$AS$504,AU9,$V$5:$V$504,"<=2023") -> 0 | BF9: =COUNTIFS($AS$5:$AS$504,AU9,$V$5:$V$504,">=2024",$V$5:$V$504,"<=2030") -> 0 | BG9: =COUNTIFS($AS$5:$AS$504,AU9,$V$5:$V$504,">2030") -> 1 | BH9: =SUM(AV9:BG9) -> 12
A10: 6 | B10: Sinopec Group | C10: China | D10: Energy | E10: $471,154 | F10: $9,657 | M10: G | N10: undefined | O10: 2060 | P10: {=IF(O10="", "", IFERROR(MAX(--_xlfn.TEXTSPLIT(O10,"+")), O10))} -> 2060 | Q10: 2021 | R10: http://www.sinopecgroup.com/group/en/Resource/Pdf/SustainReport2022en.pdf | V10: {=IF(U10="", "", IFERROR(MAX(--_xlfn.TEXTSPLIT(U10,"+")), U10))} | AB10: 2022 | AC10: 137720000 | AE10: 24070000 | AG10: N | AH10: =AC10+AE10 -> 161790000 | AI10: =AH10+AF10 -> 161790000 | AJ10: 2021 | AK10: =148.38*1000000 -> 148380000 | AM10: =24.18*1000000 -> 24180000 | AO10: =AK10+AM10 -> 172560000 | AP10: =AO10 -> 172560000 | AQ10: http://www.sinopecgroup.com/group/en/Resource/Pdf/SustainReport2022en.pdf http://www.sinopec.com/listco/en/Resource/Pdf/2023032506.pdf | AR10: =_xlfn.XLOOKUP(C10,Sheet1!A:A,Sheet1!B:B, "Other") -> Asia | AS10: =_xlfn.XLOOKUP(D10,Sheet1!D:D,Sheet1!E:E) -> Energy and utilities | AU10: Financial services | AV10: =COUNTIFS($AS$5:$AS$504,AU10,$K$5:$K$504,"<=2023") -> 0 | AW10: =COUNTIFS($AS$5:$AS$504,AU10,$K$5:$K$504,">=2024",$K$5:$K$504,"<=2030") -> 1 | AX10: =COUNTIFS($AS$5:$AS$504,AU10,$K$5:$K$504,">2030") -> 0 | AY10: =COUNTIFS($AS$5:$AS$504,AU10,$H$5:$H$504,"<=2023") -> 11 | AZ10: =COUNTIFS($AS$5:$AS$504,AU10,$H$5:$H$504,">=2024",$H$5:$H$504,"<=2030") -> 7 | BA10: =COUNTIFS($AS$5:$AS$504,AU10,$H$5:$H$504,">2030") -> 2 | BB10: =COUNTIFS($AS$5:$AS$504,AU10,$P$5:$P$504,"<=2023") -> 24 | BC10: =COUNTIFS($AS$5:$AS$504,AU10,$P$5:$P$504,">=2024",$P$5:$P$504,"<=2030") -> 13 | BD10: =COUNTIFS($AS$5:$AS$504,AU10,$P$5:$P$504,">2030") -> 22 | BE10: =COUNTIFS($AS$5:$AS$504,AU10,$V$5:$V$504,"<=2023") -> 1 | BF10: =COUNTIFS($AS$5:$AS$504,AU10,$V$5:$V$504,">=2024",$V$5:$V$504,"<=2030") -> 6 | BG10: =COUNTIFS($AS$5:$AS$504,AU10,$V$5:$V$504,">2030") -> 44 | BH10: =SUM(AV10:BG10) -> 131
A11: 7 | B11: Exxon Mobil | C11: United States of America (USA) | D11: Energy | E11: $413,680 | F11: $55,740 | P11: {=IF(O11="", "", IFERROR(MAX(--_xlfn.TEXTSPLIT(O11,"+")), O11))} | S11: C | T11: scope 1,2 | U11: 2050 | V11: {=IF(U11="", "", IFERROR(MAX(--_xlfn.TEXTSPLIT(U11,"+")), U11))} -> 2050 | W11: 2022 | X11: https://corporate.exxonmobil.com/-/media/global/files/advancing-climate-solutions-progress-report/2023/2023-advancing-climate-solutions-progress-report.pdf https://corporate.exxonmobil.com/news/news-releases/2022/0118_exxonmobil-announces-ambition-for-net-zero-greenhouse-gas-emissions-by-2050 | Y11: Y | Z11: Vice President-Global Operations & Sustainability | AA11: https://corporate.exxonmobil.com/news/reporting-and-publications/sustainability-report/governance/climate-governance | AB11: 2022 | AC11: 96000000 | AD11: 7000000 | AE11: 4000000 | AF11: 540000000 | AG11: N | AH11: =AC11+AE11 -> 100000000 | AI11: =AH11+AF11 -> 640000000 | AJ11: 2021 | AK11: 96000000 | AL11: 7000000 | AM11: 7000000 | AO11: =AK11+AM11 -> 103000000 | AP11: =AO11 -> 103000000 | AQ11: https://corporate.exxonmobil.com/-/media/global/files/advancing-climate-solutions-progress-report/2023/2023-acs-ghg-data-supplement.pdf | AR11: =_xlfn.XLOOKUP(C11,Sheet1!A:A,Sheet1!B:B, "Other") -> North America | AS11: =_xlfn.XLOOKUP(D11,Sheet1!D:D,Sheet1!E:E) -> Energy and utilities | AU11: Food, beverages and agriculture | AV11: =COUNTIFS($AS$5:$AS$504,AU11,$K$5:$K$504,"<=2023") -> 0 | AW11: =COUNTIFS($AS$5:$AS$504,AU11,$K$5:$K$504,">=2024",$K$5:$K$504,"<=2030") -> 18 | AX11: =COUNTIFS($AS$5:$AS$504,AU11,$K$5:$K$504,">2030") -> 0 | AY11: =COUNTIFS($AS$5:$AS$504,AU11,$H$5:$H$504,"<=2023") -> 0 | AZ11: =COUNTIFS($AS$5:$AS$504,AU11,$H$5:$H$504,">=2024",$H$5:$H$504,"<=2030") -> 6 | BA11: =COUNTIFS($AS$5:$AS$504,AU11,$H$5:$H$504,">2030") -> 1 | BB11: =COUNTIFS($AS$5:$AS$504,AU11,$P$5:$P$504,"<=2023") -> 1 | BC11: =COUNTIFS($AS$5:$AS$504,AU11,$P$5:$P$504,">=2024",$P$5:$P$504,"<=2030") -> 2 | BD11: =COUNTIFS($AS$5:$AS$504,AU11,$P$5:$P$504,">2030") -> 4 | BE11: =COUNTIFS($AS$5:$AS$504,AU11,$V$5:$V$504,"<=2023") -> 0 | BF11: =COUNTIFS($AS$5:$AS$504,AU11,$V$5:$V$504,">=2024",$V$5:$V$504,"<=2030") -> 0 | BG11: =COUNTIFS($AS$5:$AS$504,AU11,$V$5:$V$504,">2030") -> 18 | BH11: =SUM(AV11:BG11) -> 50
A12: 8 | B12: Apple | C12: United States of America (USA) | D12: Technology | E12: $394,328 | F12: $99,803 | G12: Y | H12: 2021 | I12: 2016 | J12: T | K12: 2030 | L12: 2021 | M12: C + V | N12: operations + entire product footprint | O12: 2021 + 2030 | P12: {=IF(O12="", "", IFERROR(MAX(--_xlfn.TEXTSPLIT(O12,"+")), O12))} -> 2030 | Q12: 2020 | R12: https://www.apple.com/environment/pdf/Apple_Environmental_Progress_Report_2023.pdf https://www.apple.com/newsroom/2020/07/apple-commits-to-be-100-percent-carbon-neutral-for-its-supply-chain-and-products-by-2030/ https://www.apple.com/newsroom/2020/07/apple-commits-to-be-100-percent-carbon-neutral-for-its-supply-chain-and-products-by-2030/ | V12: {=IF(U12="", "", IFERROR(MAX(--_xlfn.TEXTSPLIT(U12,"+")), U12))} | Y12: Y | Z12: Vice President Environment, Policy and Social Initiatives - In this capacity, her responsibilities include those of a Chief Sustainability Officer for Apple, reporting directly to Apple‘s CEO, Tim Cook | AA12: https://www.apple.com/environment/pdf/Apple_Environmental_Progress_Report_2023.pdf | AB12: 2022 | AC12: 55200 | AE12: 3000 | AF12: =265800+20280000 -> 20545800 | AG12: Y | AH12: =AC12+AE12 -> 58200 | AI12: =AH12+AF12 -> 20604000 | AJ12: 2021 | AK12: 55200 | AM12: 2780 | AN12: 23128400 | AO12: =AK12+AM12 -> 57980 | AP12: =AO12+AN12 -> 23186380 | AQ12: https://www.apple.com/environment/pdf/Apple_Environmental_Progress_Report_2023.pdf | AR12: =_xlfn.XLOOKUP(C12,Sheet1!A:A,Sheet1!B:B, "Other") -> North America | AS12: =_xlfn.XLOOKUP(D12,Sheet1!D:D,Sheet1!E:E) -> Technology | AU12: Health care and pharmaceuticals | AV12: =COUNTIFS($AS$5:$AS$504,AU12,$K$5:$K$504,"<=2023") -> 0 | AW12: =COUNTIFS($AS$5:$AS$504,AU12,$K$5:$K$504,">=2024",$K$5:$K$504,"<=2030") -> 12 | AX12: =COUNTIFS($AS$5:$AS$504,AU12,$K$5:$K$504,">2030") -> 2 | AY12: =COUNTIFS($AS$5:$AS$504,AU12,$H$5:$H$504,"<=2023") -> 0 | AZ12: =COUNTIFS($AS$5:$AS$504,AU12,$H$5:$H$504,">=2024",$H$5:$H$504,"<=2030") -> 8 | BA12: =COUNTIFS($AS$5:$AS$504,AU12,$H$5:$H$504,">2030") -> 0 | BB12: =COUNTIFS($AS$5:$AS$504,AU12,$P$5:$P$504,"<=2023") -> 1 | BC12: =COUNTIFS($AS$5:$AS$504,AU12,$P$5:$P$504,">=2024",$P$5:$P$504,"<=2030") -> 9 | BD12: =COUNTIFS($AS$5:$AS$504,AU12,$P$5:$P$504,">2030") -> 6 | BE12: =COUNTIFS($AS$5:$AS$504,AU12,$V$5:$V$504,"<=2023") -> 0 | BF12: =COUNTIFS($AS$5:$AS$504,AU12,$V$5:$V$504,">=2024",$V$5:$V$504,"<=2030") -> 0 | BG12: =COUNTIFS($AS$5:$AS$504,AU12,$V$5:$V$504,">2030") -> 13 | BH12: =SUM(AV12:BG12) -> 51
A13: 9 | B13: Shell | C13: Netherlands | D13: Energy | E13: $386,201 | F13: $42,309 | P13: {=IF(O13="", "", IFERROR(MAX(--_xlfn.TEXTSPLIT(O13,"+")), O13))} | S13: C | T13: business | U13: 2050 | V13: {=IF(U13="", "", IFERROR(MAX(--_xlfn.TEXTSPLIT(U13,"+")), U13))} -> 2050 | W13: 2021 | X13: https://www.shell.com/powering-progress/achieving-net-zero-emissions.html | AB13: 2022 | AC13: 51000000 | AD13: 8000000 | AE13: 7000000 | AF13: 2084000000 | AG13: N | AH13: =AE13+AC13 -> 58000000 | AI13: =AH13+AF13 -> 2142000000 | AJ13: 2021 | AK13: 60000000 | AL13: 9000000 | AM13: 8000000 | AN13: 2309000000 | AO13: =AM13+AK13 -> 68000000 | AP13: =AO13+AN13 -> 2377000000 | AQ13: https://reports.shell.com/sustainability-report/2022/_assets/downloads/shell-sustainability-report-2022.pdf | AR13: =_xlfn.XLOOKUP(C13,Sheet1!A:A,Sheet1!B:B, "Other") -> Europe | AS13: =_xlfn.XLOOKUP(D13,Sheet1!D:D,Sheet1!E:E) -> Energy and utilities | AU13: Household and personal products | AV13: =COUNTIFS($AS$5:$AS$504,AU13,$K$5:$K$504,"<=2023") -> 0 | AW13: =COUNTIFS($AS$5:$AS$504,AU13,$K$5:$K$504,">=2024",$K$5:$K$504,"<=2030") -> 3 | AX13: =COUNTIFS($AS$5:$AS$504,AU13,$K$5:$K$504,">2030") -> 0 | AY13: =COUNTIFS($AS$5:$AS$504,AU13,$H$5:$H$504,"<=2023") -> 0 | AZ13: =COUNTIFS($AS$5:$AS$504,AU13,$H$5:$H$504,">=2024",$H$5:$H$504,"<=2030") -> 2 | BA13: =COUNTIFS($AS$5:$AS$504,AU13,$H$5:$H$504,">2030") -> 0 | BB13: =COUNTIFS($AS$5:$AS$504,AU13,$P$5:$P$504,"<=2023") -> 1 | BC13: =COUNTIFS($AS$5:$AS$504,AU13,$P$5:$P$504,">=2024",$P$5:$P$504,"<=2030") -> 1 | BD13: =COUNTIFS($AS$5:$AS$504,AU13,$P$5:$P$504,">2030") -> 0 | BE13: =COUNTIFS($AS$5:$AS$504,AU13,$V$5:$V$504,"<=2023") -> 0 | BF13: =COUNTIFS($AS$5:$AS$504,AU13,$V$5:$V$504,">=2024",$V$5:$V$504,"<=2030") -> 0 | BG13: =COUNTIFS($AS$5:$AS$504,AU13,$V$5:$V$504,">2030") -> 3 | BH13: =SUM(AV13:BG13) -> 10
A14: 10 | B14: UnitedHealth Group | C14: United States of America (USA) | D14: Health Care | E14: $324,162 | F14: $20,120 | J14: C | L14: 2022 | P14: {=IF(O14="", "", IFERROR(MAX(--_xlfn.TEXTSPLIT(O14,"+")), O14))} | S14: C | T14: operational | U14: 2035 | V14: {=IF(U14="", "", IFERROR(MAX(--_xlfn.TEXTSPLIT(U14,"+")), U14))} -> 2035 | W14: 2021 | X14: https://www.beckerspayer.com/payer/unitedhealth-group-commits-to-net-zero-carbon-emissions-going-paperless.html https://sustainability.uhg.com/content/dam/sustainability-report/2022/pdf/2022-sustainability-report-Commitments.pdf | Y14: Y | Z14: CSO | AA14: https://sustainability.uhg.com/content/dam/sustainability-report/2022/pdf/2022-sustainability-report.pdf | AB14: 2022 | AC14: 122356 | AD14: 383896 | AE14: 383896 | AF14: 13788578 | AG14: Y | AH14: 506252 | AI14: 14294830 | AJ14: 2021 | AK14: 121572 | AL14: 362038 | AM14: 334277 | AN14: 12491631 | AO14: =AM14+AK14 -> 455849 | AP14: =AO14+AN14 -> 12947480 | AQ14: https://sustainability.uhg.com/content/dam/sustainability-report/2022/pdf/2022-sustainability-report.pdf | AR14: =_xlfn.XLOOKUP(C14,Sheet1!A:A,Sheet1!B:B, "Other") -> North America | AS14: =_xlfn.XLOOKUP(D14,Sheet1!D:D,Sheet1!E:E) -> Health care and pharmaceuticals | AU14: Industrial goods | AV14: =COUNTIFS($AS$5:$AS$504,AU14,$K$5:$K$504,"<=2023") -> 0 | AW14: =COUNTIFS($AS$5:$AS$504,AU14,$K$5:$K$504,">=2024",$K$5:$K$504,"<=2030") -> 7 | AX14: =COUNTIFS($AS$5:$AS$504,AU14,$K$5:$K$504,">2030") -> 1 | AY14: =COUNTIFS($AS$5:$AS$504,AU14,$H$5:$H$504,"<=2023") -> 0 | AZ14: =COUNTIFS($AS$5:$AS$504,AU14,$H$5:$H$504,">=2024",$H$5:$H$504,"<=2030") -> 2 | BA14: =COUNTIFS($AS$5:$AS$504,AU14,$H$5:$H$504,">2030") -> 0 | BB14: =COUNTIFS($AS$5:$AS$504,AU14,$P$5:$P$504,"<=2023") -> 0 | BC14: =COUNTIFS($AS$5:$AS$504,AU14,$P$5:$P$504,">=2024",$P$5:$P$504,"<=2030") -> 1 | BD14: =COUNTIFS($AS$5:$AS$504,AU14,$P$5:$P$504,">2030") -> 27 | BE14: =COUNTIFS($AS$5:$AS$504,AU14,$V$5:$V$504,"<=2023") -> 0 | BF14: =COUNTIFS($AS$5:$AS$504,AU14,$V$5:$V$504,">=2024",$V$5:$V$504,"<=2030") -> 0 | BG14: =COUNTIFS($AS$5:$AS$504,AU14,$V$5:$V$504,">2030") -> 9 | BH14: =SUM(AV14:BG14) -> 47
A15: 11 | B15: CVS Health | C15: United States of America (USA) | D15: Health Care | E15: $322,467 | F15: $4,149 | J15: T | K15: 2030 | L15: 2021 | M15: C | N15: company | O15: 2030 | P15: {=IF(O15="", "", IFERROR(MAX(--_xlfn.TEXTSPLIT(O15,"+")), O15))} -> 2030 | Q15: 2021 | R15: https://www.cvshealth.com/content/dam/enterprise/cvs-enterprise/pdfs/2022/2022-ESGReport.pdf https://www.cvshealth.com/content/dam/enterprise/cvs-enterprise/pdfs/2022/2022-ESGReport-appendix.pdf | S15: V | T15: value chain | U15: 2050 | V15: {=IF(U15="", "", IFERROR(MAX(--_xlfn.TEXTSPLIT(U15,"+")), U15))} -> 2050 | W15: 2021 | X15: https://www.cvshealth.com/content/dam/enterprise/cvs-enterprise/pdfs/2022/2022-ESGReport.pdf | Y15: Y | Z15: CSO | AA15: https://investors.cvshealth.com/investors/corporate-governance/board-of-directors/person-details/default.aspx?ItemId=74af3569-8539-4123-90b3-b36530a28eb9 | AB15: 2022 | AC15: 250062 | AE15: 786266 | AF15: 14457271 | AG15: Y | AH15: =AC15+AE15 -> 1036328 | AI15: =AF15+AH15 -> 15493599 | AJ15: 2021 | AK15: 188377 | AL15: 842057 | AM15: 881824 | AN15: =5470842+28827+152475 -> 5652144 | AO15: =AK15+AM15 -> 1070201 | AP15: =AN15+AO15 -> 6722345 | AQ15: https://www.cvshealth.com/content/dam/enterprise/cvs-enterprise/pdfs/2021/cvs-health-ghg-verification-statement-2021.pdf https://www.cvshealth.com/content/dam/enterprise/cvs-enterprise/pdfs/2019/cvs-health-ghg-verification-statement-2019.pdf | AR15: =_xlfn.XLOOKUP(C15,Sheet1!A:A,Sheet1!B:B, "Other") -> North America | AS15: =_xlfn.XLOOKUP(D15,Sheet1!D:D,Sheet1!E:E) -> Health care and pharmaceuticals | AU15: Metals and mining | AV15: =COUNTIFS($AS$5:$AS$504,AU15,$K$5:$K$504,"<=2023") -> 0 | AW15: =COUNTIFS($AS$5:$AS$504,AU15,$K$5:$K$504,">=2024",$K$5:$K$504,"<=2030") -> 0 | AX15: =COUNTIFS($AS$5:$AS$504,AU15,$K$5:$K$504,">2030") -> 0 | AY15: =COUNTIFS($AS$5:$AS$504,AU15,$H$5:$H$504,"<=2023") -> 0 | AZ15: =COUNTIFS($AS$5:$AS$504,AU15,$H$5:$H$504,">=2024",$H$5:$H$504,"<=2030") -> 0 | BA15: =COUNTIFS($AS$5:$AS$504,AU15,$H$5:$H$504,">2030") -> 0 | BB15: =COUNTIFS($AS$5:$AS$504,AU15,$P$5:$P$504,"<=2023") -> 0 | BC15: =COUNTIFS($AS$5:$AS$504,AU15,$P$5:$P$504,">=2024",$P$5:$P$504,"<=2030") -> 0 | BD15: =COUNTIFS($AS$5:$AS$504,AU15,$P$5:$P$504,">2030") -> 0 | BE15: =COUNTIFS($AS$5:$AS$504,AU15,$V$5:$V$504,"<=2023") -> 0 | BF15: =COUNTIFS($AS$5:$AS$504,AU15,$V$5:$V$504,">=2024",$V$5:$V$504,"<=2030") -> 0 | BG15: =COUNTIFS($AS$5:$AS$504,AU15,$V$5:$V$504,">2030") -> 0 | BH15: =SUM(AV15:BG15) -> 0
A16: 12 | B16: Trafigura Group | C16: Singapore | D16: Wholesalers | E16: $318,476 | F16: $6,994 | M16: C | N16: operational | O16: 2050 | P16: {=IF(O16="", "", IFERROR(MAX(--_xlfn.TEXTSPLIT(O16,"+")), O16))} -> 2050 | Q16: 2022 | R16: https://www.trafigura.com/media/3581/2022_trafigura_sustainability_report.pdf | V16: {=IF(U16="", "", IFERROR(MAX(--_xlfn.TEXTSPLIT(U16,"+")), U16))} | AB16: 2022 | AF16: 15600000 | AG16: N | AH16: 2395000 | AI16: =AH16+AF16 -> 17995000 | AJ16: 2021 | AN16: 14500000 | AO16: 2724000 | AP16: =AO16+AN16 -> 17224000 | AQ16: https://www.trafigura.com/media/3581/2022_trafigura_sustainability_report.pdf | AR16: =_xlfn.XLOOKUP(C16,Sheet1!A:A,Sheet1!B:B, "Other") -> Asia | AS16: =_xlfn.XLOOKUP(D16,Sheet1!D:D,Sheet1!E:E) -> Retail | AU16: Oil and gas | AV16: =COUNTIFS($AS$5:$AS$504,AU16,$K$5:$K$504,"<=2023") -> 0 | AW16: =COUNTIFS($AS$5:$AS$504,AU16,$K$5:$K$504,">=2024",$K$5:$K$504,"<=2030") -> 0 | AX16: =COUNTIFS($AS$5:$AS$504,AU16,$K$5:$K$504,">2030") -> 0 | AY16: =COUNTIFS($AS$5:$AS$504,AU16,$H$5:$H$504,"<=2023") -> 0 | AZ16: =COUNTIFS($AS$5:$AS$504,AU16,$H$5:$H$504,">=2024",$H$5:$H$504,"<=2030") -> 0 | BA16: =COUNTIFS($AS$5:$AS$504,AU16,$H$5:$H$504,">2030") -> 0 | BB16: =COUNTIFS($AS$5:$AS$504,AU16,$P$5:$P$504,"<=2023") -> 0 | BC16: =COUNTIFS($AS$5:$AS$504,AU16,$P$5:$P$504,">=2024",$P$5:$P$504,"<=2030") -> 0 | BD16: =COUNTIFS($AS$5:$AS$504,AU16,$P$5:$P$504,">2030") -> 2 | BE16: =COUNTIFS($AS$5:$AS$504,AU16,$V$5:$V$504,"<=2023") -> 0 | BF16: =COUNTIFS($AS$5:$AS$504,AU16,$V$5:$V$504,">=2024",$V$5:$V$504,"<=2030") -> 0 | BG16: =COUNTIFS($AS$5:$AS$504,AU16,$V$5:$V$504,">2030") -> 0 | BH16: =SUM(AV16:BG16) -> 2
A17: 13 | B17: China State Construction Engineering | C17: China | D17: Engineering & Construction | E17: $305,885 | F17: $4,234 | M17: G | N17: undefined | O17: 2060 | P17: {=IF(O17="", "", IFERROR(MAX(--_xlfn.TEXTSPLIT(O17,"+")), O17))} -> 2060 | Q17: 2021 | R17: https://english.cscec.com/tzgx/reports/202206/P020220617672797745003.pdf https://manager.wisdomir.com/files/409/2023/0427/20230427170001_82663644_en.pdf | V17: {=IF(U17="", "", IFERROR(MAX(--_xlfn.TEXTSPLIT(U17,"+")), U17))} | AB17: N | AG17: N | AQ17: https://manager.wisdomir.com/files/409/2023/0427/20230427170001_82663644_en.pdf | AR17: =_xlfn.XLOOKUP(C17,Sheet1!A:A,Sheet1!B:B, "Other") -> Asia | AS17: =_xlfn.XLOOKUP(D17,Sheet1!D:D,Sheet1!E:E) -> Engineering and construction | AU17: Real estate | AV17: =COUNTIFS($AS$5:$AS$504,AU17,$K$5:$K$504,"<=2023") -> 0 | AW17: =COUNTIFS($AS$5:$AS$504,AU17,$K$5:$K$504,">=2024",$K$5:$K$504,"<=2030") -> 0 | AX17: =COUNTIFS($AS$5:$AS$504,AU17,$K$5:$K$504,">2030") -> 0 | AY17: =COUNTIFS($AS$5:$AS$504,AU17,$H$5:$H$504,"<=2023") -> 0 | AZ17: =COUNTIFS($AS$5:$AS$504,AU17,$H$5:$H$504,">=2024",$H$5:$H$504,"<=2030") -> 0 | BA17: =COUNTIFS($AS$5:$AS$504,AU17,$H$5:$H$504,">2030") -> 0 | BB17: =COUNTIFS($AS$5:$AS$504,AU17,$P$5:$P$504,"<=2023") -> 0 | BC17: =COUNTIFS($AS$5:$AS$504,AU17,$P$5:$P$504,">=2024",$P$5:$P$504,"<=2030") -> 0 | BD17: =COUNTIFS($AS$5:$AS$504,AU17,$P$5:$P$504,">2030") -> 0 | BE17: =COUNTIFS($AS$5:$AS$504,AU17,$V$5:$V$504,"<=2023") -> 0 | BF17: =COUNTIFS($AS$5:$AS$504,AU17,$V$5:$V$504,">=2024",$V$5:$V$504,"<=2030") -> 0 | BG17: =COUNTIFS($AS$5:$AS$504,AU17,$V$5:$V$504,">2030") -> 0 | BH17: =SUM(AV17:BG17) -> 0
A18: 14 | B18: Berkshire Hathaway | C18: United States of America (USA) | D18: Financials | E18: $302,089 | F18: $-22,819 | P18: {=IF(O18="", "", IFERROR(MAX(--_xlfn.TEXTSPLIT(O18,"+")), O18))} | V18: {=IF(U18="", "", IFERROR(MAX(--_xlfn.TEXTSPLIT(U18,"+")), U18))} | Y18: Y | Z18: CSO | AA18: https://www.brkenergy.com/about-us/leadership/cathy-s-woollums#:~:text=Woollums%20is%20responsible%20for%20developing,sustainability%20strategy%20throughout%20the%20company. | AB18: N | AG18: N | AJ18: 2021 | AP18: 79300000 | AQ18: https://www.berkshirehathaway.com/2022ar/2022ar.pdf https://www.berkshirehathaway.com/2021ar/2021ar.pdf | AR18: =_xlfn.XLOOKUP(C18,Sheet1!A:A,Sheet1!B:B, "Other") -> North America | AS18: =_xlfn.XLOOKUP(D18,Sheet1!D:D,Sheet1!E:E) -> Financial services | AU18: Retail | AV18: =COUNTIFS($AS$5:$AS$504,AU18,$K$5:$K$504,"<=2023") -> 0 | AW18: =COUNTIFS($AS$5:$AS$504,AU18,$K$5:$K$504,">=2024",$K$5:$K$504,"<=2030") -> 12 | AX18: =COUNTIFS($AS$5:$AS$504,AU18,$K$5:$K$504,">2030") -> 1 | AY18: =COUNTIFS($AS$5:$AS$504,AU18,$H$5:$H$504,"<=2023") -> 1 | AZ18: =COUNTIFS($AS$5:$AS$504,AU18,$H$5:$H$504,">=2024",$H$5:$H$504,"<=2030") -> 4 | BA18: =COUNTIFS($AS$5:$AS$504,AU18,$H$5:$H$504,">2030") -> 2 | BB18: =COUNTIFS($AS$5:$AS$504,AU18,$P$5:$P$504,"<=2023") -> 0 | BC18: =COUNTIFS($AS$5:$AS$504,AU18,$P$5:$P$504,">=2024",$P$5:$P$504,"<=2030") -> 3 | BD18: =COUNTIFS($AS$5:$AS$504,AU18,$P$5:$P$504,">2030") -> 13 | BE18: =COUNTIFS($AS$5:$AS$504,AU18,$V$5:$V$504,"<=2023") -> 0 | BF18: =COUNTIFS($AS$5:$AS$504,AU18,$V$5:$V$504,">=2024",$V$5:$V$504,"<=2030") -> 0 | BG18: =COUNTIFS($AS$5:$AS$504,AU18,$V$5:$V$504,">2030") -> 17 | BH18: =SUM(AV18:BG18) -> 53
A19: 15 | B19: Volkswagen | C19: Germany | D19: Motor Vehicles & Parts | E19: $293,685 | F19: $15,223 | J19: T | K19: 2030 | L19: 2022 | M19: V | N19: includes our supply chains, plants and business divisions and our customers’ use of the vehicles | O19: 2050 | P19: {=IF(O19="", "", IFERROR(MAX(--_xlfn.TEXTSPLIT(O19,"+")), O19))} -> 2050 | R19: https://www.volkswagen-group.com/en/reporting-15808 | V19: {=IF(U19="", "", IFERROR(MAX(--_xlfn.TEXTSPLIT(U19,"+")), U19))} | Y19: Y | Z19: CSO | AA19: https://www.cdp.net/en/formatted_responses/responses?campaign_id=79520704&discloser_id=978558&locale=en&organization_name=Volkswagen+AG&organization_number=20309&program=Investor&project_year=2022&redirect=https%3A%2F%2Fcdp.credit360.com%2Fsurveys%2F2022%2F6wz4wms4%2F193352&survey_id=78646008 | AB19: 2022 | AC19: 4460000 | AE19: 2110000 | AF19: 395620000 | AG19: Y | AH19: =AC19+AE19 -> 6570000 | AI19: =AC19+AE19+AF19 -> 402190000 | AJ19: 2021 | AK19: 4670000 | AM19: 2410000 | AN19: 364140000 | AO19: =AK19+AM19 -> 7080000 | AP19: =AN19+AM19+AK19 -> 371220000 | AQ19: https://www.volkswagen-group.com/en/reporting-15808 | AR19: =_xlfn.XLOOKUP(C19,Sheet1!A:A,Sheet1!B:B, "Other") -> Europe | AS19: =_xlfn.XLOOKUP(D19,Sheet1!D:D,Sheet1!E:E) -> Automotive | AU19: Technology | AV19: =COUNTIFS($AS$5:$AS$504,AU19,$K$5:$K$504,"<=2023") -> 0 | AW19: =COUNTIFS($AS$5:$AS$504,AU19,$K$5:$K$504,">=2024",$K$5:$K$504,"<=2030") -> 13 | AX19: =COUNTIFS($AS$5:$AS$504,AU19,$K$5:$K$504,">2030") -> 3 | AY19: =COUNTIFS($AS$5:$AS$504,AU19,$H$5:$H$504,"<=2023") -> 5 | AZ19: =COUNTIFS($AS$5:$AS$504,AU19,$H$5:$H$504,">=2024",$H$5:$H$504,"<=2030") -> 3 | BA19: =COUNTIFS($AS$5:$AS$504,AU19,$H$5:$H$504,">2030") -> 6 | BB19: =COUNTIFS($AS$5:$AS$504,AU19,$P$5:$P$504,"<=2023") -> 3 | BC19: =COUNTIFS($AS$5:$AS$504,AU19,$P$5:$P$504,">=2024",$P$5:$P$504,"<=2030") -> 5 | BD19: =COUNTIFS($AS$5:$AS$504,AU19,$P$5:$P$504,">2030") -> 7 | BE19: =COUNTIFS($AS$5:$AS$504,AU19,$V$5:$V$504,"<=2023") -> 1 | BF19: =COUNTIFS($AS$5:$AS$504,AU19,$V$5:$V$504,">=2024",$V$5:$V$504,"<=2030") -> 6 | BG19: =COUNTIFS($AS$5:$AS$504,AU19,$V$5:$V$504,">2030") -> 15 | BH19: =SUM(AV19:BG19) -> 67
A20: 16 | B20: Uniper | C20: Germany | D20: Energy | E20: $288,309 | F20: $-19,961 | M20: V | N20: 1,2 + 1,2,3 | O20: 2035 + 2040 | P20: {=IF(O20="", "", IFERROR(MAX(--_xlfn.TEXTSPLIT(O20,"+")), O20))} -> 2040 | Q20: 2023 | R20: https://www.uniper.energy/news/uniper-accelerates-the-green-transformation-and-posts-exceptionally-strong-first-half-earnings#:~:text=It%20will%20end%20coal%2Dfired,and%202%20emissions%20by%202035. | V20: {=IF(U20="", "", IFERROR(MAX(--_xlfn.TEXTSPLIT(U20,"+")), U20))} | Y20: Y | Z20: Chief Operating Officer and Chief Sustainability Officer | AA20: https://www.uniper.energy/sites/default/files/2023-04/2023_04_FY_2022_Uniper_Sustainability_Report.pdf | AB20: 2022 | AC20: 55600000 | AD20: 655941 | AE20: 887721 | AF20: 90000000 | AG20: N | AH20: =AC20+AE20 -> 56487721 | AI20: =AF20+AH20 -> 146487721 | AJ20: 2021 | AK20: 50900000 | AL20: 596924 | AM20: 799391 | AN20: 106400000 | AO20: =AK20+AM20 -> 51699391 | AP20: =AN20+AO20 -> 158099391 | AQ20: https://www.uniper.energy/sites/default/files/2023-04/2023_04_FY_2022_Uniper_Sustainability_Report.pdf | AR20: =_xlfn.XLOOKUP(C20,Sheet1!A:A,Sheet1!B:B, "Other") -> Europe | AS20: =_xlfn.XLOOKUP(D20,Sheet1!D:D,Sheet1!E:E) -> Energy and utilities | AU20: Telecommunications and media | AV20: =COUNTIFS($AS$5:$AS$504,AU20,$K$5:$K$504,"<=2023") -> 0 | AW20: =COUNTIFS($AS$5:$AS$504,AU20,$K$5:$K$504,">=2024",$K$5:$K$504,"<=2030") -> 9 | AX20: =COUNTIFS($AS$5:$AS$504,AU20,$K$5:$K$504,">2030") -> 2 | AY20: =COUNTIFS($AS$5:$AS$504,AU20,$H$5:$H$504,"<=2023") -> 1 | AZ20: =COUNTIFS($AS$5:$AS$504,AU20,$H$5:$H$504,">=2024",$H$5:$H$504,"<=2030") -> 2 | BA20: =COUNTIFS($AS$5:$AS$504,AU20,$H$5:$H$504,">2030") -> 1 | BB20: =COUNTIFS($AS$5:$AS$504,AU20,$P$5:$P$504,"<=2023") -> 1 | BC20: =COUNTIFS($AS$5:$AS$504,AU20,$P$5:$P$504,">=2024",$P$5:$P$504,"<=2030") -> 3 | BD20: =COUNTIFS($AS$5:$AS$504,AU20,$P$5:$P$504,">2030") -> 7 | BE20: =COUNTIFS($AS$5:$AS$504,AU20,$V$5:$V$504,"<=2023") -> 0 | BF20: =COUNTIFS($AS$5:$AS$504,AU20,$V$5:$V$504,">=2024",$V$5:$V$504,"<=2030") -> 1 | BG20: =COUNTIFS($AS$5:$AS$504,AU20,$V$5:$V$504,">2030") -> 8 | BH20: =SUM(AV20:BG20) -> 35
A21: 17 | B21: Alphabet | C21: United States of America (USA) | D21: Technology | E21: $282,836 | F21: $59,972 | J21: C | L21: 2022 | M21: C | N21: operations | O21: 2007 | P21: {=IF(O21="", "", IFERROR(MAX(--_xlfn.TEXTSPLIT(O21,"+")), O21))} -> 2007 | Q21: 2007 | R21: https://www.gstatic.com/gumdrop/sustainability/google-2022-environmental-report.pdf | S21: V | T21: all of our operations and value chain | U21: 2030 | V21: {=IF(U21="", "", IFERROR(MAX(--_xlfn.TEXTSPLIT(U21,"+")), U21))} -> 2030 | W21: 2020 | X21: https://www.gstatic.com/gumdrop/sustainability/google-2022-environmental-report.pdf | Y21: Y | Z21: CSO | AA21: https://www.linkedin.com/in/katebrandt/ | AB21: 2021 | AC21: 45073 | AD21: 6576239 | AE21: 1823132 | AF21: 9503000 | AG21: Y | AH21: =AC21+AE21 -> 1868205 | AI21: =AH21+AF21 -> 11371205 | AJ21: 2020 | AK21: 38694 | AL21: 5865095 | AM21: 911415 | AN21: 9376000 | AO21: =AK21+AM21 -> 950109 | AP21: =AO21+AN21 -> 10326109 | AQ21: https://www.gstatic.com/gumdrop/sustainability/google-2022-environmental-report.pdf | AR21: =_xlfn.XLOOKUP(C21,Sheet1!A:A,Sheet1!B:B, "Other") -> North America | AS21: =_xlfn.XLOOKUP(D21,Sheet1!D:D,Sheet1!E:E) -> Technology | AU21: Transportation and logistics | AV21: =COUNTIFS($AS$5:$AS$504,AU21,$K$5:$K$504,"<=2023") -> 0 | AW21: =COUNTIFS($AS$5:$AS$504,AU21,$K$5:$K$504,">=2024",$K$5:$K$504,"<=2030") -> 8 | AX21: =COUNTIFS($AS$5:$AS$504,AU21,$K$5:$K$504,">2030") -> 3 | AY21: =COUNTIFS($AS$5:$AS$504,AU21,$H$5:$H$504,"<=2023") -> 0 | AZ21: =COUNTIFS($AS$5:$AS$504,AU21,$H$5:$H$504,">=2024",$H$5:$H$504,"<=2030") -> 0 | BA21: =COUNTIFS($AS$5:$AS$504,AU21,$H$5:$H$504,">2030") -> 0 | BB21: =COUNTIFS($AS$5:$AS$504,AU21,$P$5:$P$504,"<=2023") -> 1 | BC21: =COUNTIFS($AS$5:$AS$504,AU21,$P$5:$P$504,">=2024",$P$5:$P$504,"<=2030") -> 0 | BD21: =COUNTIFS($AS$5:$AS$504,AU21,$P$5:$P$504,">2030") -> 10 | BE21: =COUNTIFS($AS$5:$AS$504,AU21,$V$5:$V$504,"<=2023") -> 0 | BF21: =COUNTIFS($AS$5:$AS$504,AU21,$V$5:$V$504,">=2024",$V$5:$V$504,"<=2030") -> 0 | BG21: =COUNTIFS($AS$5:$AS$504,AU21,$V$5:$V$504,">2030") -> 8 | BH21: =SUM(AV21:BG21) -> 30
A22: 18 | B22: McKesson | C22: United States of America (USA) | D22: Health Care | E22: $276,711 | F22: $3,560 | J22: T | K22: 2032 | L22: 2023 | P22: {=IF(O22="", "", IFERROR(MAX(--_xlfn.TEXTSPLIT(O22,"+")), O22))} | V22: {=IF(U22="", "", IFERROR(MAX(--_xlfn.TEXTSPLIT(U22,"+")), U22))} | Y22: Y | Z22: Executive Vice President & Chief Impact Officer | AA22: https://www.mckesson.com/About-McKesson/Executive-Team/ | AB22: 2022 | AC22: 132494 | AD22: 144162 | AE22: 141301 | AF22: 31994399 | AG22: Y | AH22: =AC22+AE22 -> 273795 | AI22: =AH22+AF22 -> 32268194 | AJ22: 2021 | AK22: 74025 | AL22: 169478 | AM22: 183349 | AN22: 26875944 | AO22: 257374 | AP22: =AN22+AO22 -> 27133318 | AQ22: https://www.mckesson.com/uploadedFiles/McKessoncom/Content/_Documents/About_McKesson/McKesson%20FY22%20FY23%20Impact%20Report.pdf | AR22: =_xlfn.XLOOKUP(C22,Sheet1!A:A,Sheet1!B:B, "Other") -> North America | AS22: =_xlfn.XLOOKUP(D22,Sheet1!D:D,Sheet1!E:E) -> Health care and pharmaceuticals | AU22: sum | AV22: =SUM(AV5:AV21) -> 0 | AW22: =SUM(AW5:AW21) -> 101 | AX22: =SUM(AX5:AX21) -> 20 | AY22: =SUM(AY5:AY21) -> 19 | AZ22: =SUM(AZ5:AZ21) -> 36 | BA22: =SUM(BA5:BA21) -> 19 | BB22: =SUM(BB5:BB21) -> 35 | BC22: =SUM(BC5:BC21) -> 43 | ... BH22: =SUM(BH5:BH21) -> 639
A23: 19 | B23: Toyota Motor | C23: Japan | D23: Motor Vehicles & Parts | E23: $274,491 | F23: $18,110 | J23: T | K23: 2035 | L23: 2022 | M23: V | N23: factories+ company and value chain (1,2,3) | O23: 2035 + 2050 | P23: {=IF(O23="", "", IFERROR(MAX(--_xlfn.TEXTSPLIT(O23,"+")), O23))} -> 2050 | Q23: 2021 | R23: https://www.reuters.com/business/sustainable-business/toyota-will-aim-make-its-factories-carbon-neutral-by-2035-says-exec-2021-06-11/ | V23: {=IF(U23="", "", IFERROR(MAX(--_xlfn.TEXTSPLIT(U23,"+")), U23))} | Y23: Y | Z23: CSO | AA23: https://global.toyota/pages/global_toyota/ir/library/annual/2022_001_integrated_en.pdf | AB23: 2021 | AC23: 2560000 | AE23: 3690000 | AF23: 373360000 | AG23: N | AH23: =AC23+AE23 -> 6250000 | AI23: =AH23+AF23 -> 379610000 | AJ23: 2020 | AK23: 2450000 | AM23: 3420000 | AN23: 324970000 | AO23: =AM23+AK23 -> 5870000 | AP23: =AO23+AN23 -> 330840000 | AQ23: https://global.toyota/pages/global_toyota/ir/library/annual/2022_001_integrated_en.pdf | AR23: =_xlfn.XLOOKUP(C23,Sheet1!A:A,Sheet1!B:B, "Other") -> Asia | AS23: =_xlfn.XLOOKUP(D23,Sheet1!D:D,Sheet1!E:E) -> Automotive | AV23: SBTi short term | AY23: RE100 | BB23: Carbon Neutral | BE23: Net Zero | BH23: sum
A24: 20 | B24: TotalEnergies | C24: France | D24: Energy | E24: $263,310 | F24: $20,526 | P24: {=IF(O24="", "", IFERROR(MAX(--_xlfn.TEXTSPLIT(O24,"+")), O24))} | S24: C | T24: scope 1 and 2 | U24: 2050 | V24: {=IF(U24="", "", IFERROR(MAX(--_xlfn.TEXTSPLIT(U24,"+")), U24))} -> 2050 | W24: 2020 | X24: https://gasmobility.totalenergies.com/total-adopts-new-climate-ambition-get-net-zero-2050 | Y24: Y | Z24: President, Strategy & Sustainability | AA24: https://totalenergies.com/group/identity/governance/biographies/executive-committee-members | AB24: 2022 | AC24: 37000000 | AE24: 2000000 | AF24: 381000000 | AG24: Y | AH24: =AC24+AE24 -> 39000000 | AI24: =AH24+AF24 -> 420000000 | AJ24: 2021 | AK24: 33000000 | AM24: 2000000 | AN24: 370000000 | AO24: =AK24+AM24 -> 35000000 | AP24: =AO24+AN24 -> 405000000 | AQ24: https://totalenergies.com/system/files/documents/2023-03/Sustainability_Climate_2023_Progress_Report_EN.pdf | AR24: =_xlfn.XLOOKUP(C24,Sheet1!A:A,Sheet1!B:B, "Other") -> Europe | AS24: =_xlfn.XLOOKUP(D24,Sheet1!D:D,Sheet1!E:E) -> Energy and utilities | AU24: region | AV24: <=2023 | AW24: 2024-2030 | AX24: 2031-2060 | AY24: <=2023 | AZ24: 2024-2030 | BA24: 2031-2060 | BB24: <=2023 | BC24: 2024-2030 | BD24: 2031-2060 | BE24: <=2023 | BF24: 2024-2030 | BG24: 2031-2060
A25: 21 | B25: Glencore | C25: Switzerland | D25: Energy | E25: $255,984 | F25: $17,320 | P25: {=IF(O25="", "", IFERROR(MAX(--_xlfn.TEXTSPLIT(O25,"+")), O25))} | S25: V | T25: total emissions footprint | U25: 2050 | V25: {=IF(U25="", "", IFERROR(MAX(--_xlfn.TEXTSPLIT(U25,"+")), U25))} -> 2050 | W25: 2020 | X25: https://www.glencore.com/media-and-insights/news/Climate-Report-2020--Pathway-to-Net-Zero | Y25: Y | Z25: Head, Sustainable Development | AA25: https://www.weforum.org/people/anna-krutikov | AB25: 2022 | AC25: 16607777 | AD25: 10434000 | AE25: 11433000 | AF25: 342101000 | AG25: Y | AH25: =AE25+AC25 -> 28040777 | AI25: =AH25+AF25 -> 370141777 | AJ25: 2021 | AK25: 15946000 | AL25: 10355000 | AM25: 11428000 | AN25: 364652000 | AO25: =AM25+AK25 -> 27374000 | AP25: =AO25+AN25 -> 392026000 | AQ25: https://www.glencore.com/.rest/api/v1/documents/static/63d21a4e-30f6-40ca-b0f6-00ec64a718cf/GLEN_2022_sustainability_report.pdf | AR25: =_xlfn.XLOOKUP(C25,Sheet1!A:A,Sheet1!B:B, "Other") -> Europe | AS25: =_xlfn.XLOOKUP(D25,Sheet1!D:D,Sheet1!E:E) -> Energy and utilities | AU25: Asia | AV25: =COUNTIFS($AR$5:$AR$504,AU25,$K$5:$K$504,"<=2023") -> 0 | AW25: =COUNTIFS($AR$5:$AR$504,AU25,$K$5:$K$504,">=2024",$K$5:$K$504,"<=2030") -> 15 | AX25: =COUNTIFS($AR$5:$AR$504,AU25,$K$5:$K$504,">2030") -> 5 | AY25: =COUNTIFS($AR$5:$AR$504,AU25,$H$5:$H$504,"<=2023") -> 0 | AZ25: =COUNTIFS($AR$5:$AR$504,AU25,$H$5:$H$504,">=2024",$H$5:$H$504,"<=2030") -> 4 | BA25: =COUNTIFS($AR$5:$AR$504,AU25,$H$5:$H$504,">2030") -> 12 | BB25: =COUNTIFS($AR$5:$AR$504,AU25,$P$5:$P$504,"<=2023") -> 1 | BC25: =COUNTIFS($AR$5:$AR$504,AU25,$P$5:$P$504,">=2024",$P$5:$P$504,"<=2030") -> 13 | BD25: =COUNTIFS($AR$5:$AR$504,AU25,$P$5:$P$504,">2030") -> 110 | BE25: =COUNTIFS($AR$5:$AR$504,AU25,$V$5:$V$504,"<=2023") -> 0 | BF25: =COUNTIFS($AR$5:$AR$504,AU25,$V$5:$V$504,">=2024",$V$5:$V$504,"<=2030") -> 0 | BG25: =COUNTIFS($AR$5:$AR$504,AU25,$V$5:$V$504,">2030") -> 44 | BH25: =SUM(AV25:BG25) -> 204
A26: 22 | B26: BP | C26: United Kingdom | D26: Energy | E26: $248,891 | F26: $-2,487 | P26: {=IF(O26="", "", IFERROR(MAX(--_xlfn.TEXTSPLIT(O26,"+")), O26))} | S26: V | T26: entire operations on an absolute basis | U26: 2050 | V26: {=IF(U26="", "", IFERROR(MAX(--_xlfn.TEXTSPLIT(U26,"+")), U26))} -> 2050 | W26: 2020 | X26: https://www.bp.com/en/global/corporate/sustainability/getting-to-net-zero.html | Y26: Y | Z26: EVP, strategy, sustainability & ventures | AA26: https://www.bp.com/en/global/corporate/who-we-are/board-and-executive-management/leadership-team/giulia-chierchia.html | AB26: 2022 | AC26: 1500000 | AE26: 30400000 | AF26: 307000000 | AG26: N | AH26: =AE26+AC26 -> 31900000 | AI26: =AH26+AF26 -> 338900000 | AJ26: 2021 | AK26: 2400000 | AM26: 33200000 | AN26: 304000000 | AO26: =AK26+AM26 -> 35600000 | AP26: =AN26+AO26 -> 339600000 | AQ26: https://www.bp.com/content/dam/bp/business-sites/en/global/corporate/pdfs/sustainability/group-reports/bp-sustainability-report-2022.pdf | AR26: =_xlfn.XLOOKUP(C26,Sheet1!A:A,Sheet1!B:B, "Other") -> Europe | AS26: =_xlfn.XLOOKUP(D26,Sheet1!D:D,Sheet1!E:E) -> Energy and utilities | AU26: Europe | AV26: =COUNTIFS($AR$5:$AR$504,AU26,$K$5:$K$504,"<=2023") -> 0 | AW26: =COUNTIFS($AR$5:$AR$504,AU26,$K$5:$K$504,">=2024",$K$5:$K$504,"<=2030") -> 52 | AX26: =COUNTIFS($AR$5:$AR$504,AU26,$K$5:$K$504,">2030") -> 4 | AY26: =COUNTIFS($AR$5:$AR$504,AU26,$H$5:$H$504,"<=2023") -> 8 | AZ26: =COUNTIFS($AR$5:$AR$504,AU26,$H$5:$H$504,">=2024",$H$5:$H$504,"<=2030") -> 18 | BA26: =COUNTIFS($AR$5:$AR$504,AU26,$H$5:$H$504,">2030") -> 2 | BB26: =COUNTIFS($AR$5:$AR$504,AU26,$P$5:$P$504,"<=2023") -> 15 | BC26: =COUNTIFS($AR$5:$AR$504,AU26,$P$5:$P$504,">=2024",$P$5:$P$504,"<=2030") -> 17 | BD26: =COUNTIFS($AR$5:$AR$504,AU26,$P$5:$P$504,">2030") -> 35 | BE26: =COUNTIFS($AR$5:$AR$504,AU26,$V$5:$V$504,"<=2023") -> 0 | BF26: =COUNTIFS($AR$5:$AR$504,AU26,$V$5:$V$504,">=2024",$V$5:$V$504,"<=2030") -> 6 | BG26: =COUNTIFS($AR$5:$AR$504,AU26,$V$5:$V$504,">2030") -> 60 | BH26: =SUM(AV26:BG26) -> 217
A27: 23 | B27: Chevron | C27: United States of America (USA) | D27: Energy | E27: $246,252 | F27: $35,465 | P27: {=IF(O27="", "", IFERROR(MAX(--_xlfn.TEXTSPLIT(O27,"+")), O27))} | S27: C | T27: operational emissions | U27: 2050 | V27: {=IF(U27="", "", IFERROR(MAX(--_xlfn.TEXTSPLIT(U27,"+")), U27))} -> 2050 | W27: 2021 | X27: https://www.reuters.com/business/sustainable-business/chevron-commits-net-zero-emissions-by-2050-2021-10-11/ | AB27: 2022 | AC27: 53000000 | AE27: 3000000 | AF27: 592000000 | AG27: N | AH27: =AE27+AC27 -> 56000000 | AI27: =AH27+AF27 -> 648000000 | AJ27: 2021 | AK27: 57000000 | AM27: 4000000 | AN27: 621000000 | AO27: =AM27+AK27 -> 61000000 | AP27: =AO27+AN27 -> 682000000 | AQ27: https://www.chevron.com/-/media/shared-media/documents/chevron-sustainability-report-2022.pdf | AR27: =_xlfn.XLOOKUP(C27,Sheet1!A:A,Sheet1!B:B, "Other") -> North America | AS27: =_xlfn.XLOOKUP(D27,Sheet1!D:D,Sheet1!E:E) -> Energy and utilities | AU27: North America | AV27: =COUNTIFS($AR$5:$AR$504,AU27,$K$5:$K$504,"<=2023") -> 0 | AW27: =COUNTIFS($AR$5:$AR$504,AU27,$K$5:$K$504,">=2024",$K$5:$K$504,"<=2030") -> 32 | AX27: =COUNTIFS($AR$5:$AR$504,AU27,$K$5:$K$504,">2030") -> 11 | AY27: =COUNTIFS($AR$5:$AR$504,AU27,$H$5:$H$504,"<=2023") -> 11 | AZ27: =COUNTIFS($AR$5:$AR$504,AU27,$H$5:$H$504,">=2024",$H$5:$H$504,"<=2030") -> 12 | BA27: =COUNTIFS($AR$5:$AR$504,AU27,$H$5:$H$504,">2030") -> 5 | BB27: =COUNTIFS($AR$5:$AR$504,AU27,$P$5:$P$504,"<=2023") -> 17 | BC27: =COUNTIFS($AR$5:$AR$504,AU27,$P$5:$P$504,">=2024",$P$5:$P$504,"<=2030") -> 13 | BD27: =COUNTIFS($AR$5:$AR$504,AU27,$P$5:$P$504,">2030") -> 17 | BE27: =COUNTIFS($AR$5:$AR$504,AU27,$V$5:$V$504,"<=2023") -> 3 | BF27: =COUNTIFS($AR$5:$AR$504,AU27,$V$5:$V$504,">=2024",$V$5:$V$504,"<=2030") -> 7 | BG27: =COUNTIFS($AR$5:$AR$504,AU27,$V$5:$V$504,">2030") -> 67 | BH27: =SUM(AV27:BG27) -> 195
A28: 24 | B28: AmerisourceBergen | C28: United States of America (USA) | D28: Health Care | E28: $238,587 | F28: $1,699 | J28: T | K28: 2032 | L28: 2023 | P28: {=IF(O28="", "", IFERROR(MAX(--_xlfn.TEXTSPLIT(O28,"+")), O28))} | V28: {=IF(U28="", "", IFERROR(MAX(--_xlfn.TEXTSPLIT(U28,"+")), U28))} | Y28: Y | Z28: Senior Vice President, Global Sustainability & ESG Integration Program Officer, | AA28: https://www.amerisourcebergen.com/-/media/assets/amerisourcebergen/pdf/ab-fy22-esg-summary-report.pdf | AB28: 2021 | AC28: 124035 | AD28: 97397 | AF28: 23627236 | AG28: Y | AH28: =AD28+AC28 -> 221432 | AI28: =AH28+AF28 -> 23848668 | AJ28: 2020 | AK28: 33361.3 | AL28: 74293.6 | AN28: 25777.7 | AO28: =AK28+AL28 -> 107654.9 | AP28: =AO28+AN28 -> 133432.6 | AQ28: https://www.amerisourcebergen.com/-/media/assets/amerisourcebergen/pdf/ab-fy22-esg-summary-report.pdf https://www.amerisourcebergen.com/-/media/assets/amerisourcebergen/pdf/AmerisourceBergen_2021_GS_summaryreport.pdf | AR28: =_xlfn.XLOOKUP(C28,Sheet1!A:A,Sheet1!B:B, "Other") -> North America | AS28: =_xlfn.XLOOKUP(D28,Sheet1!D:D,Sheet1!E:E) -> Health care and pharmaceuticals | AU28: other | AV28: =COUNTIFS($AR$5:$AR$504,AU28,$K$5:$K$504,"<=2023") -> 0 | AW28: =COUNTIFS($AR$5:$AR$504,AU28,$K$5:$K$504,">=2024",$K$5:$K$504,"<=2030") -> 2 | AX28: =COUNTIFS($AR$5:$AR$504,AU28,$K$5:$K$504,">2030") -> 0 | AY28: =COUNTIFS($AR$5:$AR$504,AU28,$H$5:$H$504,"<=2023") -> 0 | AZ28: =COUNTIFS($AR$5:$AR$504,AU28,$H$5:$H$504,">=2024",$H$5:$H$504,"<=2030") -> 2 | BA28: =COUNTIFS($AR$5:$AR$504,AU28,$H$5:$H$504,">2030") -> 0 | BB28: =COUNTIFS($AR$5:$AR$504,AU28,$P$5:$P$504,"<=2023") -> 2 | BC28: =COUNTIFS($AR$5:$AR$504,AU28,$P$5:$P$504,">=2024",$P$5:$P$504,"<=2030") -> 0 | BD28: =COUNTIFS($AR$5:$AR$504,AU28,$P$5:$P$504,">2030") -> 7 | BE28: =COUNTIFS($AR$5:$AR$504,AU28,$V$5:$V$504,"<=2023") -> 0 | BF28: =COUNTIFS($AR$5:$AR$504,AU28,$V$5:$V$504,">=2024",$V$5:$V$504,"<=2030") -> 0 | BG28: =COUNTIFS($AR$5:$AR$504,AU28,$V$5:$V$504,">2030") -> 10 | BH28: =SUM(AV28:BG28) -> 23
A29: 25 | B29: Samsung Electronics | C29: South Korea | D29: Technology | E29: $234,129 | F29: $42,398 | G29: Y | H29: 2050 | I29: 2022 | P29: {=IF(O29="", "", IFERROR(MAX(--_xlfn.TEXTSPLIT(O29,"+")), O29))} | S29: C | T29: scope 1,2 | U29: 2050 | V29: {=IF(U29="", "", IFERROR(MAX(--_xlfn.TEXTSPLIT(U29,"+")), U29))} -> 2050 | W29: 2022 | X29: https://news.samsung.com/global/samsung-electronics-announces-new-environmental-strategy https://www.samsung.com/levant/sustainability/environment/climate-action/ | Y29: Y | Z29: Corporate Sustainability Vice President | AA29: https://www.cdp.net/en/formatted_responses/responses?campaign_id=79520704&discloser_id=966788&locale=en&organization_name=Samsung+Electronics&organization_number=16191&program=Investor&project_year=2022&redirect=https%3A%2F%2Fcdp.credit360.com%2Fsurveys%2F2022%2F6wz4wms4%2F186996&survey_id=78646008 | AB29: 2021 | AC29: 7604000 | AD29: 12566000 | AE29: 9796000 | AG29: N | AH29: =AC29+AE29 -> 17400000 | AI29: =AH29 -> 17400000 | AJ29: 2020 | AK29: 5726000 | AM29: 9079000 | AO29: 14805000 | AP29: 14805000 | AQ29: https://images.samsung.com/is/content/samsung/assets/uk/sustainability/overview/Samsung_Electronics_Sustainability_Report_2022.pdf | AR29: =_xlfn.XLOOKUP(C29,Sheet1!A:A,Sheet1!B:B, "Other") -> Asia | AS29: =_xlfn.XLOOKUP(D29,Sheet1!D:D,Sheet1!E:E) -> Technology | AU29: sum | AV29: =SUM(AV25:AV28) -> 0 | AW29: =SUM(AW25:AW28) -> 101 | AX29: =SUM(AX25:AX28) -> 20 | AY29: =SUM(AY25:AY28) -> 19 | AZ29: =SUM(AZ25:AZ28) -> 36 | BA29: =SUM(BA25:BA28) -> 19 | BB29: =SUM(BB25:BB28) -> 35 | BC29: =SUM(BC25:BC28) -> 43 | ... BH29: =SUM(BH25:BH28) -> 639
A30: 26 | B30: Costco Wholesale | C30: United States of America (USA) | D30: Retailing | E30: $226,954 | F30: $5,844 | P30: {=IF(O30="", "", IFERROR(MAX(--_xlfn.TEXTSPLIT(O30,"+")), O30))} | V30: {=IF(U30="", "", IFERROR(MAX(--_xlfn.TEXTSPLIT(U30,"+")), U30))} | AB30: 2021 | AG30: N | AH30: =2647132 -> 2647132 | AI30: =AH30 -> 2647132 | AJ30: 2020 | AK30: 1200000 | AM30: =AO30-AK30 -> 1433033 | AN30: 141800000 | AO30: 2633033 | AP30: =AN30+AO30 -> 144433033 | AQ30: https://mobilecontent.costco.com/live/resource/img/static-us-landing-pages/5aClimate-Action-Plan.pdf | AR30: =_xlfn.XLOOKUP(C30,Sheet1!A:A,Sheet1!B:B, "Other") -> North America | AS30: =_xlfn.XLOOKUP(D30,Sheet1!D:D,Sheet1!E:E) -> Retail
A31: 27 | B31: Hon Hai Precision Industry | C31: Taiwan, Province of China | D31: Technology | E31: $222,535 | F31: $4,751 | J31: T | K31: 2030 | L31: 2023 | P31: {=IF(O31="", "", IFERROR(MAX(--_xlfn.TEXTSPLIT(O31,"+")), O31))} | S31: V | T31: suppy chain | U31: 2050 | V31: {=IF(U31="", "", IFERROR(MAX(--_xlfn.TEXTSPLIT(U31,"+")), U31))} -> 2050 | W31: 2020 | X31: https://www.honhai.com/s3/reports/CSR/EN/2021/HonHai_2021_Sustainability%20Report_EN.pdf | AB31: 2021 | AC31: 237946 | AE31: 5982836 | AG31: N | AH31: =AC31+AE31 -> 6220782 | AI31: =AH31+AF31 -> 6220782 | AJ31: 2020 | AK31: 152602 | AM31: 5265000 | AO31: =AK31+AM31 -> 5417602 | AP31: =AO31 -> 5417602 | AQ31: https://www.honhai.com/s3/reports/CSR/EN/2020/2020%E9%B4%BB%E6%B5%B7%20CSR%20report-%E8%8B%B1%E6%96%87%E7%89%88.pdf https://www.honhai.com/s3/reports/CSR/EN/2021/HonHai_2021_Sustainability%20Report_EN.pdf | AR31: =_xlfn.XLOOKUP(C31,Sheet1!A:A,Sheet1!B:B, "Other") -> Asia | AS31: =_xlfn.XLOOKUP(D31,Sheet1!D:D,Sheet1!E:E) -> Technology
A32: 28 | B32: Industrial & Commercial Bank of China | C32: China | D32: Financials | E32: $214,766 | F32: $53,589 | M32: C | N32: operations | O32: 2060 | P32: {=IF(O32="", "", IFERROR(MAX(--_xlfn.TEXTSPLIT(O32,"+")), O32))} -> 2060 | Q32: 2021 | R32: https://v.icbc.com.cn/userfiles/Resources/ICBCLTD/download/2023/2022ESGen202303.pdf | V32: {=IF(U32="", "", IFERROR(MAX(--_xlfn.TEXTSPLIT(U32,"+")), U32))} | AB32: 2022 | AC32: 97400 | AE32: 1923900 | AG32: N | AH32: =AE32+AC32 -> 2021300 | AI32: =AH32 -> 2021300 | AJ32: 2021 | AK32: 129600 | AM32: 2033000 | AO32: =AM32+AK32 -> 2162600 | AP32: =AO32 -> 2162600 | AQ32: https://v.icbc.com.cn/userfiles/Resources/ICBCLTD/download/2023/2022ESGen202303.pdf | AR32: =_xlfn.XLOOKUP(C32,Sheet1!A:A,Sheet1!B:B, "Other") -> Asia | AS32: =_xlfn.XLOOKUP(D32,Sheet1!D:D,Sheet1!E:E) -> Financial services
A33: 29 | B33: China Construction Bank | C33: China | D33: Financials | E33: $202,753 | F33: $48,145 | M33: G | N33: undefined | O33: 2060 | P33: {=IF(O33="", "", IFERROR(MAX(--_xlfn.TEXTSPLIT(O33,"+")), O33))} -> 2060 | Q33: 2022 | R33: http://en.ccb.com/eng/attachDir/2023/07/2023071716521332187.pdf | V33: {=IF(U33="", "", IFERROR(MAX(--_xlfn.TEXTSPLIT(U33,"+")), U33))} | AB33: 2022 | AG33: N | AH33: 1682812.2 | AI33: =AH33 -> 1682812.2 | AJ33: 2021 | AO33: 1692538.7 | AP33: =AO33 -> 1692538.7 | AQ33: http://en.ccb.com/eng/attachDir/2023/07/2023071716521332187.pdf | AR33: =_xlfn.XLOOKUP(C33,Sheet1!A:A,Sheet1!B:B, "Other") -> Asia | AS33: =_xlfn.XLOOKUP(D33,Sheet1!D:D,Sheet1!E:E) -> Financial services
A34: 30 | B34: Microsoft | C34: United States of America (USA) | D34: Technology | E34: $198,270 | F34: $72,738 | G34: Y | H34: 2014 | I34: 2015 | J34: T | K34: 2030 | L34: 2019 | M34: C | O34: 2012 | P34: {=IF(O34="", "", IFERROR(MAX(--_xlfn.TEXTSPLIT(O34,"+")), O34))} -> 2012 | Q34: 2012 | R34: https://www.microsoft.com/en-gb/store/b/sustainability | S34: V | T34: company, supply and value chan | U34: 2030 | V34: {=IF(U34="", "", IFERROR(MAX(--_xlfn.TEXTSPLIT(U34,"+")), U34))} -> 2030 | W34: 2020 | X34: https://blogs.microsoft.com/blog/2020/01/16/microsoft-will-be-carbon-negative-by-2030/ | Y34: Y | Z34: CSO | AA34: https://query.prod.cms.rt.microsoft.com/cms/api/am/binary/RW15mgm | AB34: 2022 | AC34: 139413 | AE34: 288029 | AF34: 12571000 | AG34: Y | AH34: =AE34+AC34 -> 427442 | AI34: =AH34+AF34 -> 12998442 | AJ34: 2021 | AK34: 123704 | AM34: 429405 | AN34: 12511000 | AO34: =AM34+AK34 -> 553109 | AP34: =AO34+AN34 -> 13064109 | AQ34: https://query.prod.cms.rt.microsoft.com/cms/api/am/binary/RW15mgm | AR34: =_xlfn.XLOOKUP(C34,Sheet1!A:A,Sheet1!B:B, "Other") -> North America | AS34: =_xlfn.XLOOKUP(D34,Sheet1!D:D,Sheet1!E:E) -> Technology
A35: 31 | B35: Stellantis | C35: Netherlands | D35: Motor Vehicles & Parts | E35: $188,888 | F35: $17,669 | P35: {=IF(O35="", "", IFERROR(MAX(--_xlfn.TEXTSPLIT(O35,"+")), O35))} | S35: V | T35: whole value chain | U35: 2038 | V35: {=IF(U35="", "", IFERROR(MAX(--_xlfn.TEXTSPLIT(U35,"+")), U35))} -> 2038 | W35: 2022 | X35: https://www.stellantis.com/content/dam/stellantis-corporate/sustainability/csr-disclosure/stellantis/2022/Stellantis-2022-CSR-Report.pdf | Y35: Y | Z35: Chief Communication & CSR Officer | AA35: https://www.stellantis.com/en/company/governance/top-executive-team | AB35: 2022 | AC35: 1526757 | AE35: 1916359 | AF35: 444200000 | AG35: N | AH35: =AE35+AC35 -> 3443116 | AI35: =AF35+AH35 -> 447643116 | AJ35: 2021 | AK35: 1641028 | AM35: 2233459 | AN35: 523300000 | AO35: =AK35+AM35 -> 3874487 | AP35: =AO35+AN35 -> 527174487 | AQ35: https://www.stellantis.com/content/dam/stellantis-corporate/sustainability/csr-disclosure/stellantis/2022/Stellantis-2022-CSR-Report.pdf | AR35: =_xlfn.XLOOKUP(C35,Sheet1!A:A,Sheet1!B:B, "Other") -> Europe | AS35: =_xlfn.XLOOKUP(D35,Sheet1!D:D,Sheet1!E:E) -> Automotive
A36: 32 | B36: Agricultural Bank of China | C36: China | D36: Financials | E36: $187,061 | F36: $38,524 | P36: {=IF(O36="", "", IFERROR(MAX(--_xlfn.TEXTSPLIT(O36,"+")), O36))} | V36: {=IF(U36="", "", IFERROR(MAX(--_xlfn.TEXTSPLIT(U36,"+")), U36))} | AB36: 2022 | AC36: 222353.26 | AE36: 1931555.8 | AG36: N | AH36: 2153909 | AI36: 2153909 | AJ36: 2021 | AK36: 20663.74 | AM36: 237531.54 | AO36: 258195.28 | AP36: 258195.28 | AQ36: https://www.abchina.com/en/aboutus/csr-report/202303/P020230331664255776160.pdf https://www.abchina.com/en/aboutus/csr-report/202203/P020220507559489867566.pdf | AR36: =_xlfn.XLOOKUP(C36,Sheet1!A:A,Sheet1!B:B, "Other") -> Asia | AS36: =_xlfn.XLOOKUP(D36,Sheet1!D:D,Sheet1!E:E) -> Financial services
A37: 33 | B37: Ping An Insurance | C37: China | D37: Financials | E37: $181,566 | F37: $12,454 | M37: C | N37: operations | O37: 2030 | P37: {=IF(O37="", "", IFERROR(MAX(--_xlfn.TEXTSPLIT(O37,"+")), O37))} -> 2030 | Q37: 2021 | R37: https://group.pingan.com/media/news/News-2021/Ping-An-to-achieve-operational-carbon-neutrality-in-2030.html | V37: {=IF(U37="", "", IFERROR(MAX(--_xlfn.TEXTSPLIT(U37,"+")), U37))} | AB37: 2022 | AC37: 2818.15 | AE37: 285890.98 | AF37: 37960.75 | AG37: N | AH37: =AE37+AC37 -> 288709.13 | AI37: =AH37+AF37 -> 326669.88 | AJ37: 2021 | AK37: 6121.76 | AM37: 376336.09 | AN37: 46537 | AO37: =AM37+AK37 -> 382457.85 | AP37: =AO37+AN37 -> 428994.85 | AQ37: https://group.pingan.com/resource/pingan/ESG/Report/pingan-sustainability-report-22.pdf | AR37: =_xlfn.XLOOKUP(C37,Sheet1!A:A,Sheet1!B:B, "Other") -> Asia | AS37: =_xlfn.XLOOKUP(D37,Sheet1!D:D,Sheet1!E:E) -> Financial services
A38: 34 | B38: Cardinal Health | C38: United States of America (USA) | D38: Health Care | E38: $181,364 | F38: $-933 | J38: C | L38: 2021 | P38: {=IF(O38="", "", IFERROR(MAX(--_xlfn.TEXTSPLIT(O38,"+")), O38))} | V38: {=IF(U38="", "", IFERROR(MAX(--_xlfn.TEXTSPLIT(U38,"+")), U38))} | Y38: Y | Z38: Vice President, Environmental, Social and Governance (ESG) | AA38: https://newsroom.cardinalhealth.com/2022-04-18-Cardinal-Health-names-Megan-Maltenfort-to-lead-Environmental,-Social-and-Governance | AB38: 2022 | AC38: 151120 | AD38: 214389 | AF38: 8992 | AG38: N | AH38: =AC38+AD38 -> 365509 | AI38: =AF38+AH38 -> 374501 | AJ38: 2021 | AK38: 156100 | AL38: 234339 | AO38: =AK38+AL38 -> 390439 | AP38: =AO38 -> 390439 | AQ38: https://www.cardinalhealth.com/content/dam/corp/web/documents/Report/cardinal-health-fy22-ESG-report.pdf | AR38: =_xlfn.XLOOKUP(C38,Sheet1!A:A,Sheet1!B:B, "Other") -> North America | AS38: =_xlfn.XLOOKUP(D38,Sheet1!D:D,Sheet1!E:E) -> Health care and pharmaceuticals
A39: 35 | B39: Cigna | C39: United States of America (USA) | D39: Health Care | E39: $180,516 | F39: $6,668 | G39: Y | H39: 2030 | I39: 2022 | M39: C | N39: scope 1,2 | O39: 2040 | P39: {=IF(O39="", "", IFERROR(MAX(--_xlfn.TEXTSPLIT(O39,"+")), O39))} -> 2040 | R39: https://www.cigna.com/static/www-cigna-com/docs/cigna-connects-2021-corporate-responsibility-report.pdf | V39: {=IF(U39="", "", IFERROR(MAX(--_xlfn.TEXTSPLIT(U39,"+")), U39))} | AB39: 2021 | AC39: 14049 | AD39: 98570 | AE39: 94596 | AF39: 2822 | AG39: N | AH39: =AC39+AE39 -> 108645 | AI39: =AC39+AE39+AF39 -> 111467 | AJ39: 2020 | AK39: 12687 | AL39: 116261 | AN39: 8394 | AO39: =AK39+AL39 -> 128948 | AP39: =AO39+AN39 -> 137342 | AQ39: https://www.cigna.com/static/www-cigna-com/docs/cigna-connects-2021-corporate-responsibility-report.pdf | AR39: =_xlfn.XLOOKUP(C39,Sheet1!A:A,Sheet1!B:B, "Other") -> North America | AS39: =_xlfn.XLOOKUP(D39,Sheet1!D:D,Sheet1!E:E) -> Health care and pharmaceuticals
A40: 36 | B40: Marathon Petroleum | C40: United States of America (USA) | D40: Energy | E40: $180,012 | F40: $14,516 | P40: {=IF(O40="", "", IFERROR(MAX(--_xlfn.TEXTSPLIT(O40,"+")), O40))} | V40: {=IF(U40="", "", IFERROR(MAX(--_xlfn.TEXTSPLIT(U40,"+")), U40))} | Y40: Y | Z40: senior vice president, Health, Environment, Safety and Security of Marathon Petroleum Corporation | AA40: https://www.marathonpetroleum.com/About/Leadership/#james-r-wilkins | AB40: 2021 | AC40: 33000000 | AE40: 6900000 | AF40: 379000000 | AG40: N | AH40: =AC40+AE40 -> 39900000 | AI40: =AH40+AF40 -> 418900000 | AJ40: 2020 | AK40: 32200000 | AM40: 8000000 | AN40: 352000000 | AO40: =AK40+AM40 -> 40200000 | AP40: =AO40+AN40 -> 392200000 | AQ40: https://www.marathonpetroleum.com/content/documents/Responsibility/DOWNLOAD%20MPC_MPLX%202021%20Sustainability%20Report.pdf | AR40: =_xlfn.XLOOKUP(C40,Sheet1!A:A,Sheet1!B:B, "Other") -> North America | AS40: =_xlfn.XLOOKUP(D40,Sheet1!D:D,Sheet1!E:E) -> Energy and utilities
A41: 37 | B41: Phillips 66 | C41: United States of America (USA) | D41: Energy | E41: $175,702 | F41: $11,024 | P41: {=IF(O41="", "", IFERROR(MAX(--_xlfn.TEXTSPLIT(O41,"+")), O41))} | V41: {=IF(U41="", "", IFERROR(MAX(--_xlfn.TEXTSPLIT(U41,"+")), U41))} | Y41: Y | Z41: Executive Vice President, Emerging Energy and Sustainability | AA41: https://investor.phillips66.com/corporate-governance/person-details/default.aspx?ItemId=5ba02a9c-ee9a-4fb0-93b1-34ea30c859c6 | AB41: 2021 | AC41: =30.3*1000000 -> 30300000 | AE41: =4.5*1000000 -> 4500000 | AF41: 350000000 | AG41: N | AH41: =AC41+AE41 -> 34800000 | AI41: =AH41+AF41 -> 384800000 | AJ41: 2020 | AK41: =25.5*1000000 -> 25500000 | AM41: =4.6*1000000 -> 4600000 | AN41: =313000000 -> 313000000 | AO41: =AK41+AM41 -> 30100000 | AP41: =AN41+AO41 -> 343100000 | AQ41: https://issuu.com/phillips66co/docs/2022sustainabilityreport?fr=sYTYwYzUxMzk1MDc | AR41: =_xlfn.XLOOKUP(C41,Sheet1!A:A,Sheet1!B:B, "Other") -> North America | AS41: =_xlfn.XLOOKUP(D41,Sheet1!D:D,Sheet1!E:E) -> Energy and utilities
A42: 38 | B42: Sinochem Holdings | C42: China | D42: Chemicals | E42: $173,834 | F42: $-1 | M42: G | O42: 2060 | P42: {=IF(O42="", "", IFERROR(MAX(--_xlfn.TEXTSPLIT(O42,"+")), O42))} -> 2060 | Q42: 2021 | R42: https://www.sinochem.com/Portals/137/Uploads/Files/2022/9-16/637989499685024191.pdf | V42: {=IF(U42="", "", IFERROR(MAX(--_xlfn.TEXTSPLIT(U42,"+")), U42))} | AB42: N | AG42: N | AR42: =_xlfn.XLOOKUP(C42,Sheet1!A:A,Sheet1!B:B, "Other") -> Asia | AS42: =_xlfn.XLOOKUP(D42,Sheet1!D:D,Sheet1!E:E) -> Chemicals
A43: 39 | B43: China Railway Engineering Group | C43: China | D43: Engineering & Construction | E43: $171,669 | F43: $2,035 | M43: G | N43: undefined | O43: 2060 | P43: {=IF(O43="", "", IFERROR(MAX(--_xlfn.TEXTSPLIT(O43,"+")), O43))} -> 2060 | R43: http://www.crecg.com/eportal/fileDir/zgztywz/resource/cms/article/10212924/10248937/2022%20Annual%20Report.pdf http://www.crecg.com/zgztywz/resource/cms/article/10203385/10247107/23-07%20Environment,%20Social%20and%20Governance%20Report%20and%20Social%20Responsibility%20Report%20of%20CREC.pdf | V43: {=IF(U43="", "", IFERROR(MAX(--_xlfn.TEXTSPLIT(U43,"+")), U43))} | AB43: 2022 | AG43: N | AI43: 1632.9429 | AJ43: N | AQ43: http://www.crecg.com/zgztywz/resource/cms/article/10203385/10247107/23-07%20Environment,%20Social%20and%20Governance%20Report%20and%20Social%20Responsibility%20Report%20of%20CREC.pdf | AR43: =_xlfn.XLOOKUP(C43,Sheet1!A:A,Sheet1!B:B, "Other") -> Asia | AS43: =_xlfn.XLOOKUP(D43,Sheet1!D:D,Sheet1!E:E) -> Engineering and construction
A44: 40 | B44: Valero Energy | C44: United States of America (USA) | D44: Energy | E44: $171,189 | F44: $11,528 | M44: C | N44: 1,2 | O44: 2035 | P44: {=IF(O44="", "", IFERROR(MAX(--_xlfn.TEXTSPLIT(O44,"+")), O44))} -> 2035 | Q44: 2020 | R44: https://www.valero.com/sites/default/files/valero-documents/ESG_Report%20_August_2022_FINAL_SinglePages.pdf | V44: {=IF(U44="", "", IFERROR(MAX(--_xlfn.TEXTSPLIT(U44,"+")), U44))} | AB44: 2021 | AC44: =23.7*1000000 -> 23700000 | AE44: =4.9*1000000 -> 4900000 | AG44: N | AH44: =AC44+AE44 -> 28600000 | AI44: =AH44 -> 28600000 | AJ44: 2020 | AK44: =23*1000000 -> 23000000 | AM44: =4.5*1000000 -> 4500000 | AO44: =AK44+AM44 -> 27500000 | AP44: =AO44 -> 27500000 | AQ44: https://www.valero.com/sites/default/files/valero-documents/ESG_Report%20_August_2022_FINAL_SinglePages.pdf | AR44: =_xlfn.XLOOKUP(C44,Sheet1!A:A,Sheet1!B:B, "Other") -> North America | AS44: =_xlfn.XLOOKUP(D44,Sheet1!D:D,Sheet1!E:E) -> Energy and utilities
A45: 41 | B45: Gazprom | C45: Russia | D45: Energy | E45: $167,832 | F45: $17,641 | P45: {=IF(O45="", "", IFERROR(MAX(--_xlfn.TEXTSPLIT(O45,"+")), O45))} | V45: {=IF(U45="", "", IFERROR(MAX(--_xlfn.TEXTSPLIT(U45,"+")), U45))} | AB45: 2021 | AC45: 243280000 | AE45: 12400000 | AF45: 1150750000 | AG45: U | AH45: =AC45+AE45 -> 255680000 | AI45: =AF45+AH45 -> 1406430000 | AJ45: 2020 | AK45: 210320000 | AM45: 11790000 | AN45: 1078500000 | AO45: =AK45+AM45 -> 222110000 | AP45: =AO45+AN45 -> 1300610000 | AQ45: https://sustainability.gazpromreport.ru/fileadmin/f/2021/sustainability-report-en-2021.pdf | AR45: =_xlfn.XLOOKUP(C45,Sheet1!A:A,Sheet1!B:B, "Other") -> Europe | AS45: =_xlfn.XLOOKUP(D45,Sheet1!D:D,Sheet1!E:E) -> Energy and utilities
A46: 42 | B46: China National Offshore Oil | C46: China | D46: Mining, Crude-Oil Production | E46: $164,762 | F46: $16,988 | M46: C | N46: undefined | O46: 2050 | P46: {=IF(O46="", "", IFERROR(MAX(--_xlfn.TEXTSPLIT(O46,"+")), O46))} -> 2050 | Q46: 2022 | R46: https://mp.weixin.qq.com/s?__biz=MzU1MTkwNDAwOA==&mid=2247531492&idx=1&sn=fc594f697ff3aa99856976f605eaff87&chksm=fb880d83ccff8495fb120d2d9ed6f5a04b5cca7c611d5b8d1f0d472ad94c0f3f76fc7037c705&mpshare=1&scene=1&srcid=0629jqunGl2NGML27nEo8XmI&sharer_sharetime=1656481757160&sharer_shareid=cb4aaad979aabdeb9f4ca214e36659b8&exportkey=AWne%2FH1yY11C0e6pgMLIpJI%3D&acctmode=0&pass_ticket=hQkF6tsH5kja6osjdyRoAMZXZs3PuEEHlTh2mZ0ErwnKU5uo56r830IVyKii4bwe&wx_header=0#rd | V46: {=IF(U46="", "", IFERROR(MAX(--_xlfn.TEXTSPLIT(U46,"+")), U46))} | AB46: N | AG46: N | AR46: =_xlfn.XLOOKUP(C46,Sheet1!A:A,Sheet1!B:B, "Other") -> Asia | AS46: =_xlfn.XLOOKUP(D46,Sheet1!D:D,Sheet1!E:E) -> Oil and gas
A47: 43 | B47: China Railway Construction | C47: China | D47: Engineering & Construction | E47: $163,037 | F47: $1,800 | M47: G | N47: undefined | O47: 2060 | P47: {=IF(O47="", "", IFERROR(MAX(--_xlfn.TEXTSPLIT(O47,"+")), O47))} -> 2060 | Q47: 2021 | R47: https://ungc-production.s3.us-west-2.amazonaws.com/attachments/cop_2022/516283/original/2021.pdf?1659602124 | V47: {=IF(U47="", "", IFERROR(MAX(--_xlfn.TEXTSPLIT(U47,"+")), U47))} | AB47: N | AG47: N | AJ47: N | AR47: =_xlfn.XLOOKUP(C47,Sheet1!A:A,Sheet1!B:B, "Other") -> Asia | AS47: =_xlfn.XLOOKUP(D47,Sheet1!D:D,Sheet1!E:E) -> Engineering and construction
A48: 44 | B48: China Baowu Steel Group | C48: China | D48: Materials | E48: $161,698 | F48: $2,493 | M48: C | N48: undefined | O48: 2050 | P48: {=IF(O48="", "", IFERROR(MAX(--_xlfn.TEXTSPLIT(O48,"+")), O48))} -> 2050 | Q48: 2021 | R48: https://res.baowugroup.com/attach/2022/08/08/b54e4736c3a3439a956a03aae9095980.pdf | V48: {=IF(U48="", "", IFERROR(MAX(--_xlfn.TEXTSPLIT(U48,"+")), U48))} | AB48: N | AG48: N | AR48: =_xlfn.XLOOKUP(C48,Sheet1!A:A,Sheet1!B:B, "Other") -> Asia | AS48: =_xlfn.XLOOKUP(D48,Sheet1!D:D,Sheet1!E:E) -> Industrial goods
A49: 45 | B49: Mitsubishi | C49: Japan | D49: Wholesalers | E49: $159,371 | F49: $8,723 | P49: {=IF(O49="", "", IFERROR(MAX(--_xlfn.TEXTSPLIT(O49,"+")), O49))} | S49: C | T49: 1,2 | U49: 2050 | V49: {=IF(U49="", "", IFERROR(MAX(--_xlfn.TEXTSPLIT(U49,"+")), U49))} -> 2050 | W49: 2021 | X49: https://www.mitsubishicorp.com/jp/en/carbon-neutral/pdf/20211018.pdf | Y49: Y | Z49: Group Chief Sustainability Officer | AA49: https://mitsubishicorp.disclosure.site/pdf/202303en.pdf | AB49: 2021 | AC49: 21046000 | AE49: 1806000 | AG49: N | AH49: =AC49+AE49 -> 22852000 | AI49: =AF49+AH49 -> 22852000 | AJ49: 2020 | AK49: 6774000 | AM49: 2411000 | AO49: =AK49+AM49 -> 9185000 | AP49: =AN49+AO49 -> 9185000 | AQ49: https://mitsubishicorp.disclosure.site/pdf/202303en.pdf | AR49: =_xlfn.XLOOKUP(C49,Sheet1!A:A,Sheet1!B:B, "Other") -> Asia | AS49: =_xlfn.XLOOKUP(D49,Sheet1!D:D,Sheet1!E:E) -> Retail
A50: 46 | B50: Ford Motor | C50: United States of America (USA) | D50: Motor Vehicles & Parts | E50: $158,057 | F50: $-1,981 | J50: T | K50: 2035 | L50: 2021 | M50: V | N50: our vehicles, our operations and our supply chain. | O50: 2050 | P50: {=IF(O50="", "", IFERROR(MAX(--_xlfn.TEXTSPLIT(O50,"+")), O50))} -> 2050 | Q50: 2020 | R50: https://abcnews.go.com/Business/ford-announces-carbon-neutral-targets/story?id=76796290 | V50: {=IF(U50="", "", IFERROR(MAX(--_xlfn.TEXTSPLIT(U50,"+")), U50))} | Y50: Y | Z50: Vice President, Chief Sustainability, Environment and Safety Officer | AA50: https://corporate.ford.com/content/dam/corporate/us/en-us/documents/reports/ford-cdp-climate-report.pdf https://www.linkedin.com/in/bob-holycross-9316669/ | AB50: 2022 | AC50: 1250000 | AE50: 1750000 | AF50: 334800000 | AG50: Y | AH50: =AE50+AC50 -> 3000000 | AI50: =AH50+AF50 -> 337800000 | AJ50: 2021 | AK50: 1070000 | AM50: 2000000 | AN50: 299900000 | AO50: =AK50+AM50 -> 3070000 | AP50: =AO50+AN50 -> 302970000 | AQ50: https://corporate.ford.com/content/dam/corporate/us/en-us/documents/reports/2023-integrated-sustainability-and-financial-report.pdf | AR50: =_xlfn.XLOOKUP(C50,Sheet1!A:A,Sheet1!B:B, "Other") -> North America | AS50: =_xlfn.XLOOKUP(D50,Sheet1!D:D,Sheet1!E:E) -> Automotive
A51: 47 | B51: Mercedes-Benz Group | C51: Germany | D51: Motor Vehicles & Parts | E51: $157,782 | F51: $15,252 | M51: C + V | N51: production + along the entire value chain and over the vehicles' entire life cycle | O51: 2022 + 2039 | P51: {=IF(O51="", "", IFERROR(MAX(--_xlfn.TEXTSPLIT(O51,"+")), O51))} -> 2039 | Q51: 2019 | R51: https://group.mercedes-benz.com/sustainability/climate/ambition-2039-our-path-to-co2-neutrality.html https://www.businesswire.com/news/home/20220411005483/en/Mercedes-Benz-Cars-Aims-to-Slash-CO2-Emissions-by-More-Than-50-Percent-by-End-of-This-Decade | V51: {=IF(U51="", "", IFERROR(MAX(--_xlfn.TEXTSPLIT(U51,"+")), U51))} | AB51: 2022 | AF51: =AI51-AH51 -> 123300000 | AG51: N | AH51: 500000 | AI51: 123800000 | AJ51: 2021 | AN51: =AP51-AO51 -> 123300000 | AO51: 900000 | AP51: 124200000 | AQ51: https://sustainabilityreport.mercedes-benz.com/2022/_assets/downloads/entire-mercedes-benz-sr22.pdf | AR51: =_xlfn.XLOOKUP(C51,Sheet1!A:A,Sheet1!B:B, "Other") -> Europe | AS51: =_xlfn.XLOOKUP(D51,Sheet1!D:D,Sheet1!E:E) -> Automotive
A52: 48 | B52: Home Depot | C52: United States of America (USA) | D52: Retailing | E52: $157,403 | F52: $17,105 | G52: Y | H52: 2030 | I52: 2021 | J52: C | L52: 2021 | P52: {=IF(O52="", "", IFERROR(MAX(--_xlfn.TEXTSPLIT(O52,"+")), O52))} | V52: {=IF(U52="", "", IFERROR(MAX(--_xlfn.TEXTSPLIT(U52,"+")), U52))} | Y52: Y | Z52: CSO | AA52: https://corporate.homedepot.com/sites/default/files/2022-10/2022_ESG_Report_final_4.pdf | AB52: 2021 | AC52: 642000 | AE52: 1007000 | AG52: N | AH52: =AE52+AC52 -> 1649000 | AI52: =AH52 -> 1649000 | AJ52: 2020 | AK52: 607000 | AM52: 1214000 | AO52: =AM52+AK52 -> 1821000 | AP52: =AO52 -> 1821000 | AQ52: https://corporate.homedepot.com/sites/default/files/2022-10/2022_ESG_Report_final_4.pdf | AR52: =_xlfn.XLOOKUP(C52,Sheet1!A:A,Sheet1!B:B, "Other") -> North America | AS52: =_xlfn.XLOOKUP(D52,Sheet1!D:D,Sheet1!E:E) -> Retail
A53: 49 | B53: Bank of China | C53: China | D53: Financials | E53: $156,924 | F53: $33,811 | M53: C | N53: own operations | O53: 2030 | P53: {=IF(O53="", "", IFERROR(MAX(--_xlfn.TEXTSPLIT(O53,"+")), O53))} -> 2030 | Q53: 2021 | R53: https://www.bochk.com/dam/bochk/desktop/top/aboutus/esg/report/SustainabilityReport2022_en.pdf | V53: {=IF(U53="", "", IFERROR(MAX(--_xlfn.TEXTSPLIT(U53,"+")), U53))} | AB53: 2022 | AC53: 575 | AE53: =48522+86 -> 48608 | AF53: =49182-49097 -> 85 | AG53: N | AH53: 49097 | AI53: 49182 | AJ53: 2021 | AK53: 577 | AM53: 50074 | AO53: 50650 | AP53: 50715 | AQ53: https://www.bochk.com/dam/bochk/desktop/top/aboutus/esg/report/SustainabilityReport2022_en.pdf https://www.bochk.com/dam/bochk/desktop/top/aboutus/esg/report/SustainabilityReport2019_en.pdf | AR53: =_xlfn.XLOOKUP(C53,Sheet1!A:A,Sheet1!B:B, "Other") -> Asia | AS53: =_xlfn.XLOOKUP(D53,Sheet1!D:D,Sheet1!E:E) -> Financial services
A54: 50 | B54: General Motors | C54: United States of America (USA) | D54: Motor Vehicles & Parts | E54: $156,735 | F54: $9,934 | G54: Y | H54: 2035 | I54: 2016 | J54: T | K54: 2035 | L54: 2021 | M54: C | N54: global products and operations | O54: 2040 | P54: {=IF(O54="", "", IFERROR(MAX(--_xlfn.TEXTSPLIT(O54,"+")), O54))} -> 2040 | Q54: 2021 | R54: https://www.gmsustainability.com/_pdf/resources-and-downloads/GM_2022_SR.pdf https://news.gm.com/newsroom.detail.html/Pages/news/us/en/2021/jan/0128-carbon.html | V54: {=IF(U54="", "", IFERROR(MAX(--_xlfn.TEXTSPLIT(U54,"+")), U54))} | Y54: Y | Z54: CSO | AA54: https://www.gmsustainability.com/_pdf/cdp/Climate_Change_2022_Information_Request-General_Motors_Company.pdf | AB54: 2022 | AC54: 1466452 | AD54: 2996074 | AE54: 2078738 | AF54: 272722604 | AG54: Y | AH54: =AC54+AE54 -> 3545190 | AI54: =AF54+AH54 -> 276267794 | AJ54: 2021 | AK54: 1252906 | AL54: 2881767 | AM54: 2150694 | AN54: 286427945 | AO54: =AK54+AM54 -> 3403600 | AP54: =AN54+AO54 -> 289831545 | AQ54: https://www.gmsustainability.com/_pdf/resources-and-downloads/GM_ESG_Data_2022.pdf | AR54: =_xlfn.XLOOKUP(C54,Sheet1!A:A,Sheet1!B:B, "Other") -> North America | AS54: =_xlfn.XLOOKUP(D54,Sheet1!D:D,Sheet1!E:E) -> Automotive
A55: 51 | B55: Elevance Health | C55: United States of America (USA) | D55: Health Care | E55: $156,595 | F55: $6,025 | G55: Y | H55: 2025 | I55: 2019 | M55: C | N55: operations | O55: 2022 | P55: {=IF(O55="", "", IFERROR(MAX(--_xlfn.TEXTSPLIT(O55,"+")), O55))} -> 2022 | Q55: U | R55: https://www.elevancehealth.com/annual-report/2022/Elevance_Health_Impact_Report_2022.pdf | S55: C | T55: undefined | U55: 2050 | V55: {=IF(U55="", "", IFERROR(MAX(--_xlfn.TEXTSPLIT(U55,"+")), U55))} -> 2050 | W55: 2022 | X55: https://www.elevancehealth.com/annual-report/2022/Elevance_Health_Impact_Report_2022.pdf https://www.elevancehealth.com/who-we-are/corporate-responsibility/environmental-sustainability https://www.elevancehealth.com/our-approach-to-health/whole-health/addressing-the-whole-health-effects-of-climate-change | Y55: Y | Z55: CSO | AA55: https://www.elevancehealth.com/who-we-are/senior-leadership/hakon-mattson#:~:text=Hakon%20Mattson%20serves%20as%20chief,whole%20health%20and%20health%20equity. | AB55: 2022 | AC55: 15725 | AD55: 81290 | AF55: 4823738 | AG55: U | AH55: =AD55+AC55 -> 97015 | AI55: =AF55+AH55 -> 4920753 | AJ55: 2021 | AK55: 11800 | AL55: 73700 | AN55: 947300 | AO55: =AK55+AL55 -> 85500 | AP55: =AN55+AO55 -> 1032800 | AQ55: https://www.elevancehealth.com/annual-report/2022/Elevance_Health_Impact_Report_2022.pdf | AR55: =_xlfn.XLOOKUP(C55,Sheet1!A:A,Sheet1!B:B, "Other") -> North America | AS55: =_xlfn.XLOOKUP(D55,Sheet1!D:D,Sheet1!E:E) -> Health care and pharmaceuticals
A56: 52 | B56: JD.com | C56: China | D56: Retailing | E56: $155,533 | F56: $1,543 | M56: G | N56: undefined | O56: 2060 | P56: {=IF(O56="", "", IFERROR(MAX(--_xlfn.TEXTSPLIT(O56,"+")), O56))} -> 2060 | Q56: 2020 | R56: https://ir.jd.com/system/files-encrypted/nasdaq_kms/assets/2023/06/20/18-39-49/JD.com%2C%20Inc.%202022%20Environmental%2C%20Social%20and%20Governance%20Report.pdf | V56: {=IF(U56="", "", IFERROR(MAX(--_xlfn.TEXTSPLIT(U56,"+")), U56))} | AB56: 2022 | AC56: 2399143.9 | AE56: 1197932.2 | AF56: 3069.18 | AG56: U | AH56: =AE56+AC56 -> 3597076.1 | AI56: 3600145.2 | AJ56: 2021 | AK56: 238774.9 | AM56: 271067.08 | AN56: 1906566.7 | AO56: =AK56+AM56 -> 509841.98 | AP56: =AO56+AN56 -> 2416408.6 | AQ56: https://ir.jd.com/system/files-encrypted/nasdaq_kms/assets/2023/06/20/18-39-49/JD.com%2C%20Inc.%202022%20Environmental%2C%20Social%20and%20Governance%20Report.pdf https://ir.jd.com/system/files-encrypted/nasdaq_kms/assets/2022/05/24/11-43-02/2021%20JD.com%20Environmental%20Social%20and%20Governance%20Report.pdf | AR56: =_xlfn.XLOOKUP(C56,Sheet1!A:A,Sheet1!B:B, "Other") -> Asia | AS56: =_xlfn.XLOOKUP(D56,Sheet1!D:D,Sheet1!E:E) -> Retail
A57: 53 | B57: JPMorgan Chase | C57: United States of America (USA) | D57: Financials | E57: $154,792 | F57: $37,676 | G57: Y | H57: 2020 | I57: 2017 | M57: C | N57: operational | O57: 2020 | P57: {=IF(O57="", "", IFERROR(MAX(--_xlfn.TEXTSPLIT(O57,"+")), O57))} -> 2020 | Q57: 2020 | R57: https://www.jpmorganchase.com/content/dam/jpmc/jpmorgan-chase-and-co/documents/Climate-Report-2022.pdf | S57: F | T57: lending and investment portfolios | U57: 2050 | V57: {=IF(U57="", "", IFERROR(MAX(--_xlfn.TEXTSPLIT(U57,"+")), U57))} -> 2050 | W57: 2021 | X57: https://www.jpmorganchase.com/content/dam/jpmc/jpmorgan-chase-and-co/documents/Climate-Report-2022.pdf | Y57: Y | Z57: Global Head of Sustainability | AA57: https://www.jpmorganchase.com/content/dam/jpmc/jpmorgan-chase-and-co/documents/Climate-Report-2022.pdf | AB57: 2021 | AC57: 84911 | AD57: 755514 | AE57: 6280 | AF57: 38336 | AG57: N | AH57: =AE57+AC57 -> 91191 | AI57: =AH57+AF57 -> 129527 | AJ57: 2020 | AK57: 81944 | AL57: 816054 | AM57: 4929 | AN57: 36169 | AO57: =AM57+AK57 -> 86873 | AP57: =AO57+AN57 -> 123042 | AQ57: https://www.jpmorganchase.com/content/dam/jpmc/jpmorgan-chase-and-co/documents/esg-environmental-data-table-ada-1.pdf | AR57: =_xlfn.XLOOKUP(C57,Sheet1!A:A,Sheet1!B:B, "Other") -> North America | AS57: =_xlfn.XLOOKUP(D57,Sheet1!D:D,Sheet1!E:E) -> Financial services
A58: 54 | B58: China Life Insurance | C58: China | D58: Financials | E58: $151,487 | F58: $6,859 | P58: {=IF(O58="", "", IFERROR(MAX(--_xlfn.TEXTSPLIT(O58,"+")), O58))} | V58: {=IF(U58="", "", IFERROR(MAX(--_xlfn.TEXTSPLIT(U58,"+")), U58))} | AB58: 2022 | AC58: 48385.05 | AE58: 650858.65 | AG58: N | AH58: =AC58+AE58 -> 699243.7 | AI58: =AH58 -> 699243.7 | AJ58: 2021 | AK58: 56112.23 | AM58: 1006550.1 | AO58: =AK58+AM58 -> 1062662.3 | AP58: =AO58 -> 1062662.3 | AQ58: https://www.e-chinalife.com/c/2023-03-29/9360c73a-1490-4c4d-b3b4-b2a6c9cd5cf2.shtml | AR58: =_xlfn.XLOOKUP(C58,Sheet1!A:A,Sheet1!B:B, "Other") -> Asia | AS58: =_xlfn.XLOOKUP(D58,Sheet1!D:D,Sheet1!E:E) -> Financial services
A59: 55 | B59: Electricité de France | C59: France | D59: Energy | E59: $150,902 | F59: $-18,869 | J59: T | K59: 2030 | L59: 2020 | M59: C | O59: 2050 | P59: {=IF(O59="", "", IFERROR(MAX(--_xlfn.TEXTSPLIT(O59,"+")), O59))} -> 2050 | Q59: 2020 | R59: https://www.edf.fr/en/the-edf-group/taking-action-as-a-responsible-company/corporate-social-responsibility/doing-even-more-to-reduce-co2-emissions | V59: {=IF(U59="", "", IFERROR(MAX(--_xlfn.TEXTSPLIT(U59,"+")), U59))} | Y59: Y | Z59: CSO | AA59: https://www.edf.fr/sites/groupe/files/contrib/groupe-edf/engagements/2021/impact/edfgroup_impact2021-rapport_va.pdf | AB59: 2022 | AC59: 24000000 | AE59: 390000 | AF59: 95900000 | AG59: Y | AH59: =AC59+AE59 -> 24390000 | AI59: =AH59+AF59 -> 120290000 | AJ59: 2021 | AK59: 27380000 | AM59: 290000 | AN59: 101800000 | AO59: =AM59+AK59 -> 27670000 | AP59: =AO59+AN59 -> 129470000 | AQ59: https://www.edf.fr/en/the-edf-group/taking-action-as-a-responsible-company/corporate-social-responsibility/reports-and-indicators/greenhouse-effect-gas-emissions | AR59: =_xlfn.XLOOKUP(C59,Sheet1!A:A,Sheet1!B:B, "Other") -> Europe | AS59: =_xlfn.XLOOKUP(D59,Sheet1!D:D,Sheet1!E:E) -> Energy and utilities
A60: 56 | B60: Equinor | C60: Norway | D60: Energy | E60: $150,806 | F60: $28,746 | P60: {=IF(O60="", "", IFERROR(MAX(--_xlfn.TEXTSPLIT(O60,"+")), O60))} | S60: V | T60: SCOPE 1, 2 AND 3 | U60: 2050 | V60: {=IF(U60="", "", IFERROR(MAX(--_xlfn.TEXTSPLIT(U60,"+")), U60))} -> 2050 | W60: 2022 | X60: https://cdn.equinor.com/files/h61q9gi9/global/6a64fb766c58f70ef37807deca2ee036a3f4096b.pdf?energy-transition-plan-2022-equinor.pdf https://www.equinor.com/news/archive/20201102-emissions | Y60: Y | Z60: Executive Vice President Safety, Security & Sustainability | AA60: https://www.equinor.com/about-us/corporate-executive-committee | AB60: 2022 | AC60: 11400000 | AD60: 100000 | AE60: 2500000 | AF60: =243000000+50000 -> 243050000 | AG60: N | AH60: =AC60+AE60 -> 13900000 | AI60: =AF60+AH60 -> 256950000 | AJ60: 2021 | AK60: 12000000 | AL60: 100000 | AM60: 2700000 | AN60: =249000000+10000 -> 249010000 | AO60: =AK60+AM60 -> 14700000 | AP60: =AN60+AO60 -> 263710000 | AQ60: https://cdn.equinor.com/files/h61q9gi9/global/03d92ebc1ab4f124aabe4fa5be40da3dec6e24b4.pdf?2022-annual-report-equinor.pdf | AR60: =_xlfn.XLOOKUP(C60,Sheet1!A:A,Sheet1!B:B, "Other") -> Europe | AS60: =_xlfn.XLOOKUP(D60,Sheet1!D:D,Sheet1!E:E) -> Energy and utilities
A61: 57 | B61: BMW Group | C61: Germany | D61: Motor Vehicles & Parts | E61: $149,991 | F61: $18,870 | G61: Y | H61: 2050 | I61: 2015 | J61: T | K61: 2030 | L61: 2022 | M61: F | N61: asset portfolio | O61: 2050 | P61: {=IF(O61="", "", IFERROR(MAX(--_xlfn.TEXTSPLIT(O61,"+")), O61))} -> 2050 | Q61: 2020 | R61: https://www.bmwgroup.com/en/report/2022/bmw-group-report/next-level-sustainability/index.html | V61: {=IF(U61="", "", IFERROR(MAX(--_xlfn.TEXTSPLIT(U61,"+")), U61))} | Y61: Y | Z61: Head of Sustainability, Mobility | AA61: https://www.bmwgroup.com/content/dam/grpw/websites/bmwgroup_com/ir/downloads/en/2023/bericht/BMW-Group-CDP-2022.pdf | AB61: 2022 | AC61: 694057 | AE61: 91300 | AF61: 116586786 | AG61: N | AH61: =AC61+AE61 -> 785357 | AI61: =AH61+AF61 -> 117372143 | AJ61: 2021 | AK61: 699713 | AM61: 134849 | AN61: 121705368 | AO61: =AK61+AM61 -> 834562 | AP61: =AO61+AN61 -> 122539930 | AQ61: https://www.bmwgroup.com/content/dam/grpw/websites/bmwgroup_com/ir/downloads/en/2023/bericht/BMW-Group-Report-2022-en.pdf | AR61: =_xlfn.XLOOKUP(C61,Sheet1!A:A,Sheet1!B:B, "Other") -> Europe | AS61: =_xlfn.XLOOKUP(D61,Sheet1!D:D,Sheet1!E:E) -> Automotive
A62: 58 | B62: Kroger | C62: United States of America (USA) | D62: Food & Drug Stores | E62: $148,258 | F62: $2,244 | J62: C | L62: 2022 | P62: {=IF(O62="", "", IFERROR(MAX(--_xlfn.TEXTSPLIT(O62,"+")), O62))} | V62: {=IF(U62="", "", IFERROR(MAX(--_xlfn.TEXTSPLIT(U62,"+")), U62))} | Y62: Y | Z62: group vice president of Corporate Affairs, who serves as chief sustainability officer | AA62: https://www.linkedin.com/in/keithdailey/ | AB62: 2021 | AC62: 2303388 | AD62: 2747205 | AE62: 2948060 | AF62: 2398328 | AG62: N | AH62: =AE62+AC62 -> 5251448 | AI62: =AH62+AF62 -> 7649776 | AJ62: 2020 | AK62: =AC62/1.112 -> 2071392.1 | AL62: =AD62/0.91 -> 3018906.6 | AM62: =AE62/0.92 -> 3204413 | AN62: =AF62/1.145 -> 2094609.6 | AO62: =AK62+AM62 -> 5275805.1 | AP62: =AO62+AN62 -> 7370414.7 | AQ62: https://www.thekrogerco.com/wp-content/uploads/2022/08/Kroger-Co-2022-ESG-Report.pdf | AR62: =_xlfn.XLOOKUP(C62,Sheet1!A:A,Sheet1!B:B, "Other") -> North America | AS62: =_xlfn.XLOOKUP(D62,Sheet1!D:D,Sheet1!E:E) -> Food, beverages and agriculture
A63: 59 | B63: Enel | C63: Italy | D63: Energy | E63: $147,790 | F63: $1,769 | J63: T | K63: 2030 | L63: 2023 | P63: {=IF(O63="", "", IFERROR(MAX(--_xlfn.TEXTSPLIT(O63,"+")), O63))} | S63: V | T63: across the value chain | U63: 2040 | V63: {=IF(U63="", "", IFERROR(MAX(--_xlfn.TEXTSPLIT(U63,"+")), U63))} -> 2040 | W63: 2021 | X63: https://www.enel.com/content/dam/enel-com/documenti/investitori/sostenibilita/2021/net-zero_en.pdf https://www.enel.com/content/dam/enel-com/documenti/investitori/sostenibilita/2022/sustainability-report_2022.pdf https://www.enel.com/content/dam/enel-com/documenti/investitori/sostenibilita/zero-emissions-ambition-report.pdf | Y63: Y | Z63: Chief Innovability® Officer (Innovation and Sustainability) | AA63: https://www.enel.com/company/about-us/chairman-management-team | AB63: 2022 | AC63: 53070000 | AD63: 4020000 | AE63: 6060000 | AF63: 75800000 | AG63: N | AH63: =AC63+AE63 -> 59130000 | AI63: =AF63+AH63 -> 134930000 | AJ63: 2021 | AK63: 51570000 | AL63: 3770000 | AM63: 6110000 | AN63: 70460000 | AO63: =AK63+AM63 -> 57680000 | AP63: =AN63+AO63 -> 128140000 | AQ63: https://www.enel.com/content/dam/enel-com/documenti/investitori/sostenibilita/2022/sustainability-report_2022.pdf | AR63: =_xlfn.XLOOKUP(C63,Sheet1!A:A,Sheet1!B:B, "Other") -> Europe | AS63: =_xlfn.XLOOKUP(D63,Sheet1!D:D,Sheet1!E:E) -> Energy and utilities
A64: 60 | B64: Centene | C64: United States of America (USA) | D64: Health Care | E64: $144,547 | F64: $1,202 | P64: {=IF(O64="", "", IFERROR(MAX(--_xlfn.TEXTSPLIT(O64,"+")), O64))} | V64: {=IF(U64="", "", IFERROR(MAX(--_xlfn.TEXTSPLIT(U64,"+")), U64))} | AB64: 2022 | AC64: 26862 | AD64: 90101 | AF64: 2016819 | AG64: Y | AH64: =AC64+AD64 -> 116963 | AI64: =AF64+AH64 -> 2133782 | AJ64: 2021 | AK64: 36667 | AL64: 113122 | AN64: 1868213 | AO64: =AK64+AL64 -> 149789 | AP64: =AN64+AO64 -> 2018002 | AQ64: https://www.centene.com/content/dam/centenedotcom/investor_docs/Centene_2022_ESHG_Report.pdf | AR64: =_xlfn.XLOOKUP(C64,Sheet1!A:A,Sheet1!B:B, "Other") -> North America | AS64: =_xlfn.XLOOKUP(D64,Sheet1!D:D,Sheet1!E:E) -> Health care and pharmaceuticals
A65: 61 | B65: ENI | C65: Italy | D65: Energy | E65: $140,607 | F65: $14,606 | M65: V | N65: 1,2 + processes and products | O65: 2030 + 2050 | P65: {=IF(O65="", "", IFERROR(MAX(--_xlfn.TEXTSPLIT(O65,"+")), O65))} -> 2050 | Q65: 2020 | R65: https://www.eni.com/static/en-IT/infographics/eni-for-2022/home https://www.eni.com/assets/documents/eng/just-transition/2022/eni-for-2022-just-transition-eng.pdf | V65: {=IF(U65="", "", IFERROR(MAX(--_xlfn.TEXTSPLIT(U65,"+")), U65))} | AB65: 2022 | AC65: 39390000 | AE65: 790000 | AF65: =1000000*(164+9.9+1.7+1.5+1.3+0.5) -> 178900000 | AG65: Y | AH65: =AE65+AC65 -> 40180000 | AI65: =AH65+AF65 -> 219080000 | AJ65: 2021 | AK65: 40080000 | AM65: 810000 | AN65: =1000000*(176+11.1+6.1+2.8+0.5) -> 196500000 | AO65: =AK65+AM65 -> 40890000 | AP65: =AO65+AN65 -> 237390000 | AQ65: https://www.eni.com/assets/documents/eng/just-transition/2022/eni-for-2022-sustainability-performance-eng.pdf | AR65: =_xlfn.XLOOKUP(C65,Sheet1!A:A,Sheet1!B:B, "Other") -> Europe | AS65: =_xlfn.XLOOKUP(D65,Sheet1!D:D,Sheet1!E:E) -> Energy and utilities
A66: 62 | B66: China Mobile Communications | C66: China | D66: Telecommunications | E66: $139,597 | F66: $14,718 | M66: G | O66: 2060 | P66: {=IF(O66="", "", IFERROR(MAX(--_xlfn.TEXTSPLIT(O66,"+")), O66))} -> 2060 | Q66: 2021 | R66: https://www.chinamobileltd.com/en/ir/reports/ar2022/sd2022.pdf | V66: {=IF(U66="", "", IFERROR(MAX(--_xlfn.TEXTSPLIT(U66,"+")), U66))} | AB66: 2022 | AC66: 220000 | AE66: 34240000 | AF66: =1000*(37.13+3.47) -> 40600 | AG66: N | AH66: =AC66+AE66 -> 34460000 | AI66: =AH66+AF66 -> 34500600 | AJ66: 2021 | AK66: 240000 | AM66: 33580000 | AN66: =1000*(10.24+4.72) -> 14960 | AO66: =AM66+AK66 -> 33820000 | AP66: =AO66+AN66 -> 33834960 | AQ66: https://www.chinamobileltd.com/en/ir/reports/ar2022/sd2022.pdf | AR66: =_xlfn.XLOOKUP(C66,Sheet1!A:A,Sheet1!B:B, "Other") -> Asia | AS66: =_xlfn.XLOOKUP(D66,Sheet1!D:D,Sheet1!E:E) -> Telecommunications and media
A67: 63 | B67: China Communications Construction | C67: China | D67: Engineering & Construction | E67: $138,270 | F67: $1,255 | P67: {=IF(O67="", "", IFERROR(MAX(--_xlfn.TEXTSPLIT(O67,"+")), O67))} | V67: {=IF(U67="", "", IFERROR(MAX(--_xlfn.TEXTSPLIT(U67,"+")), U67))} | AB67: N | AG67: N | AJ67: N | AR67: =_xlfn.XLOOKUP(C67,Sheet1!A:A,Sheet1!B:B, "Other") -> Asia | AS67: =_xlfn.XLOOKUP(D67,Sheet1!D:D,Sheet1!E:E) -> Engineering and construction
A68: 64 | B68: Verizon Communications | C68: United States of America (USA) | D68: Telecommunications | E68: $136,835 | F68: $21,256 | J68: T | K68: 2030 | L68: 2021 | P68: {=IF(O68="", "", IFERROR(MAX(--_xlfn.TEXTSPLIT(O68,"+")), O68))} | S68: C | T68: scope 1,2 | U68: 2035 | V68: {=IF(U68="", "", IFERROR(MAX(--_xlfn.TEXTSPLIT(U68,"+")), U68))} -> 2035 | W68: 2019 | X68: Latest report: https://www.verizon.com/about/sites/default/files/Verizon-2022-ESG-Report.pdf news item 2019: https://www.verizon.com/about/news/verizon-goes-carbon-neutral-2035 Website: https://www.verizon.com/about/responsibility/sustainability | Y68: Y | Z68: CSO | AA68: https://www.cdp.net/en/formatted_responses/responses?campaign_id=74241094&discloser_id=895415&locale=en&organization_name=Verizon+Communications+Inc.&organization_number=20175&program=Investor&project_year=2021&redirect=https%3A%2F%2Fcdp.credit360.com%2Fsurveys%2F2021%2Fdbbr64mv%2F142611&survey_id=73557641 | AB68: 2022 | AC68: 273904 | AD68: 3498643 | AE68: 3075077 | AF68: 14401431 | AG68: Y | AH68: =AC68+AE68 -> 3348981 | AI68: =AH68+AF68 -> 17750412 | AJ68: 2021 | AK68: 310145 | AL68: 3554155 | AM68: 3222342 | AN68: 15267192 | AO68: =AK68+AM68 -> 3532487 | AP68: =AO68+AN68 -> 18799679 | AQ68: https://www.verizon.com/about/investors/verizon-emissions-and-energy-data | AR68: =_xlfn.XLOOKUP(C68,Sheet1!A:A,Sheet1!B:B, "Other") -> North America | AS68: =_xlfn.XLOOKUP(D68,Sheet1!D:D,Sheet1!E:E) -> Telecommunications and media
A69: 65 | B69: China Minmetals | C69: China | D69: Materials | E69: $133,541 | F69: $877 | M69: G | N69: undefined | O69: 2060 | P69: {=IF(O69="", "", IFERROR(MAX(--_xlfn.TEXTSPLIT(O69,"+")), O69))} -> 2060 | Q69: 2021 | R69: http://www.minmetals.com/english/sustainabledevelopment/sustainabilityreport/202206/P020221203630542453904.pdf | S69: C | T69: undefined | U69: 2050 | V69: {=IF(U69="", "", IFERROR(MAX(--_xlfn.TEXTSPLIT(U69,"+")), U69))} -> 2050 | W69: 2021 | X69: http://www.minmetals.com/english/sustainabledevelopment/sustainabilityreport/202206/P020221203630542453904.pdf | AB69: N | AG69: N | AJ69: N | AQ69: http://www.minmetals.com/english/sustainabledevelopment/sustainabilityreport/202206/P020221203630542453904.pdf | AR69: =_xlfn.XLOOKUP(C69,Sheet1!A:A,Sheet1!B:B, "Other") -> Asia | AS69: =_xlfn.XLOOKUP(D69,Sheet1!D:D,Sheet1!E:E) -> Industrial goods
A70: 66 | B70: Walgreens Boots Alliance | C70: United States of America (USA) | D70: Food & Drug Stores | E70: $132,703 | F70: $4,337 | P70: {=IF(O70="", "", IFERROR(MAX(--_xlfn.TEXTSPLIT(O70,"+")), O70))} | V70: {=IF(U70="", "", IFERROR(MAX(--_xlfn.TEXTSPLIT(U70,"+")), U70))} | AB70: 2022 | AC70: 323000 | AD70: 1218000 | AE70: 1177000 | AF70: 61000 | AG70: N | AH70: =AE70+AC70 -> 1500000 | AI70: =AH70+AF70 -> 1561000 | AJ70: 2021 | AK70: 339000 | AL70: 1324000 | AM70: 1277000 | AN70: 56000 | AO70: =AM70+AK70 -> 1616000 | AP70: =AO70+AN70 -> 1672000 | AQ70: https://www.walgreensbootsalliance.com/sites/www/files/asset/2022-esg-report_0.pdf | AR70: =_xlfn.XLOOKUP(C70,Sheet1!A:A,Sheet1!B:B, "Other") -> North America | AS70: =_xlfn.XLOOKUP(D70,Sheet1!D:D,Sheet1!E:E) -> Food, beverages and agriculture
A71: 67 | B71: Allianz | C71: Germany | D71: Financials | E71: $129,059 | F71: $7,087 | G71: Y | H71: 2023 | I71: 2018 | J71: C | L71: 2018 | M71: C | N71: operations | O71: 2012 | P71: {=IF(O71="", "", IFERROR(MAX(--_xlfn.TEXTSPLIT(O71,"+")), O71))} -> 2012 | Q71: 2019 | R71: https://www.allianz.com/content/dam/onemarketing/azcom/Allianz_com/sustainability/documents/Allianz_Group_Sustainability_Report_2022-web.pdf | S71: C + F | T71: our own operations + investments | U71: 2030 | V71: {=IF(U71="", "", IFERROR(MAX(--_xlfn.TEXTSPLIT(U71,"+")), U71))} -> 2030 | W71: 2019 | X71: https://www.allianz.com/content/dam/onemarketing/azcom/Allianz_com/sustainability/documents/Allianz_Group_Sustainability_Report_2022-web.pdf | Y71: Y | Z71: Group CSO | AA71: https://www.allianz.com/en/about-us/corporate-management/board-of-management/sustainability-board.html | AB71: 2022 | AC71: 30953 | AD71: 138339 | AE71: 30490 | AF71: 92467 | AG71: N | AH71: =AE71+AC71 -> 61443 | AI71: =AH71+AF71 -> 153910 | AJ71: 2021 | AK71: 28699 | AL71: 149599 | AM71: 54689 | AN71: 55359 | AO71: =AM71+AK71 -> 83388 | AP71: =AO71+AN71 -> 138747 | AQ71: https://www.allianz.com/content/dam/onemarketing/azcom/Allianz_com/sustainability/documents/Allianz_Group_Sustainability_Report_2022-web.pdf | AR71: =_xlfn.XLOOKUP(C71,Sheet1!A:A,Sheet1!B:B, "Other") -> Europe | AS71: =_xlfn.XLOOKUP(D71,Sheet1!D:D,Sheet1!E:E) -> Financial services
